Workbook

Sheet Resumo
B1: ="SIMULAÇÃO RATEIO FIXO — "&Premissas!$B$13&" × COPASUL | Resumo Executivo" -> SIMULAÇÃO RATEIO FIXO — Cassilândia 03 × COPASUL | Resumo Executivo
B2: ="18 Unidades Consumidoras · Jun/2026–Mai/2031 · Energisa MS · Usina: "&Premissas!$B$13 -> 18 Unidades Consumidoras · Jun/2026–Mai/2031 · Energisa MS · Usina: Cassilândia 03
B4: ⚡ GERAÇÃO INJETADA | D4: 📄 PPA PAGO À HELEXIA | F4: ✅ ECONOMIA LÍQUIDA | H4: 🏦 BANCO RESIDUAL | J4: 🌟 VALOR TOTAL
B5: =Simulacao!B6/1000000 -> 8.3804424 | D5: =Simulacao!B7 -> 3708345.8 | F5: =Simulacao!B252 -> 1930957.3 | H5: =Simulacao!B273*Premissas!$B$17 -> 396994.51 | J5: =Simulacao!B278 -> 2296874.3
B6: 3,375 MWh injetados em 60 meses | D6: Custo total do contrato PPA | F6: Rede evitada menos PPA pago | H6: Banco total Copasul @ PPA | J6: Economia + banco ATRIBUÍVEL a Helexia
B8: A. CUSTO COPASUL — ANÁLISE 24 MESES | I8: B. INDICADORES-CHAVE
B9: COMPONENTE | E9: R$ | F9: % | G9: R$/mês | I9: Usina contratada | K9: =Premissas!$B$13 -> Cassilândia 03
B10: Custo SEM Helexia — baseline 60m | E10: =Simulacao!B249 -> 6111913.8 | F10: =Simulacao!B249/Simulacao!B249 -> 1 | G10: =(Simulacao!B249)/60 -> 101865.23 | I10: Período do contrato | K10: Jun/2026 – Mai/2031 (60 meses)
B11: Custo rede remanescente (COM Helexia) | E11: =Simulacao!B250 -> 472610.77 | F11: =Simulacao!B250/Simulacao!B249 -> 0.077326151 | G11: =(Simulacao!B250)/60 -> 7876.8461 | I11: Potência contratada | K11: =VLOOKUP(Premissas!$B$13,PVSYST_Helexia!$B$5:$F$7,5,0)&" kWac" -> 625 kWac
B12: PPA pago à Helexia | E12: =Simulacao!B7 -> 3708345.8 | F12: =Simulacao!B7/Simulacao!B249 -> 0.60674052 | G12: =(Simulacao!B7)/60 -> 61805.763 | I12: Geração P50 total | K12: =Simulacao!B6/1000 -> 8380.4424
B13: Custo total COM Helexia (rede + PPA) | E13: =Simulacao!B251 -> 4180956.5 | F13: =Simulacao!B251/Simulacao!B249 -> 0.68406667 | G13: =(Simulacao!B251)/60 -> 69682.609 | I13: PPA (R$/kWh) | K13: =Premissas!$B$17 -> 0.4425
B14: ★ ECONOMIA LÍQUIDA (rede − PPA) | E14: =Simulacao!B252 -> 1930957.3 | F14: =Simulacao!B252/Simulacao!B249 -> 0.31593333 | G14: =(Simulacao!B252)/60 -> 32182.621 | I14: Tarifa Grupo A FP | K14: =Premissas!$B$5 -> 0.52647111
B15: + Banco atribuível Helexia @ PPA (net NHS/AMD + Grupo B) | E15: =Simulacao!B285 -> 365917.04 | F15: =IFERROR(Simulacao!B285/Simulacao!B249,0) -> 0.059869471 | G15: =Simulacao!B285/60 -> 6098.6174 | I15: Tarifa Grupo B3 | K15: =Premissas!$B$7 -> 1.1568636
B16: ★ VALOR TOTAL HELEXIA (economia + banco atribuível) | E16: =Simulacao!B278 -> 2296874.3 | F16: =Simulacao!B278/Simulacao!B249 -> 0.3758028 | G16: =(Simulacao!B278)/60 -> 38281.238 | I16: Economia média/mês | K16: =Simulacao!B252/60 -> 32182.621
I17: % redução custo Copasul | K17: =IFERROR(Simulacao!B252/Simulacao!B249,0) -> 0.31593333
I18: Banco residual (kWh) | K18: =Simulacao!B273 -> 897162.74
B20: C. ANÁLISE VISUAL — ECONOMIA E BANCO DE CRÉDITOS
P22: Mês | Q22: SEM Helexia | R22: PPA | S22: Rede COM | T22: Eco mensal | U22: Eco acumulada
P23: Jun/26 | Q23: =Simulacao!D249 -> 29915.013 | R23: =Simulacao!D7 -> 54865.575 | S23: =Simulacao!D250 -> 2940.4293 | T23: =Simulacao!D252 -> -27890.991 | U23: =T23 -> -27890.991
P24: Jul/26 | Q24: =Simulacao!E249 -> 231390.51 | R24: =Simulacao!E7 -> 57750.675 | S24: =Simulacao!E250 -> 82568.136 | T24: =Simulacao!E252 -> 91071.696 | U24: =U23+T24 -> 63180.705
P25: Ago/26 | Q25: =Simulacao!F249 -> 156547.56 | R25: =Simulacao!F7 -> 69326.475 | S25: =Simulacao!F250 -> 1104.9864 | T25: =Simulacao!F252 -> 86116.099 | U25: =U24+T25 -> 149296.8
P26: Set/26 | Q26: =Simulacao!G249 -> 42616.08 | R26: =Simulacao!G7 -> 65051.925 | S26: =Simulacao!G250 -> 2690.9343 | T26: =Simulacao!G252 -> -25126.779 | U26: =U25+T26 -> 124170.02
P27: Out/26 | Q27: =Simulacao!H249 -> 43352.771 | R27: =Simulacao!H7 -> 66852.9 | S27: =Simulacao!H250 -> 0 | T27: =Simulacao!H252 -> -23500.129 | U27: =U26+T27 -> 100669.9
P28: Nov/26 | Q28: =Simulacao!I249 -> 43210.246 | R28: =Simulacao!I7 -> 64640.4 | S28: =Simulacao!I250 -> 0 | T28: =Simulacao!I252 -> -21430.154 | U28: =U27+T28 -> 79239.741
P29: Dez/26 | Q29: =Simulacao!J249 -> 44658.731 | R29: =Simulacao!J7 -> 61379.175 | S29: =Simulacao!J250 -> 0 | T29: =Simulacao!J252 -> -16720.444 | U29: =U28+T29 -> 62519.298
P30: Jan/27 | Q30: =Simulacao!K249 -> 42484.598 | R30: =Simulacao!K7 -> 63022.753 | S30: =Simulacao!K250 -> 0 | T30: =Simulacao!K252 -> -20538.155 | U30: =U29+T30 -> 41981.143
P31: Fev/27 | Q31: =Simulacao!L249 -> 45032.044 | R31: =Simulacao!L7 -> 56158.671 | S31: =Simulacao!L250 -> 0 | T31: =Simulacao!L252 -> -11126.626 | U31: =U30+T31 -> 30854.517
P32: Mar/27 | Q32: =Simulacao!M249 -> 208536.62 | R32: =Simulacao!M7 -> 64414.061 | S32: =Simulacao!M250 -> 0 | T32: =Simulacao!M252 -> 144122.56 | U32: =U31+T32 -> 174977.08
P33: Abr/27 | Q33: =Simulacao!N249 -> 35167.544 | R33: =Simulacao!N7 -> 64273.169 | S33: =Simulacao!N250 -> 0 | T33: =Simulacao!N252 -> -29105.625 | U33: =U32+T33 -> 145871.45
P34: Mai/27 | Q34: =Simulacao!O249 -> 32721.222 | R34: =Simulacao!O7 -> 60152.078 | S34: =Simulacao!O250 -> 0 | T34: =Simulacao!O252 -> -27430.856 | U34: =U33+T34 -> 118440.59
P35: Jun/27 | Q35: =Simulacao!P249 -> 70853.527 | R35: =Simulacao!P7 -> 54591.247 | S35: =Simulacao!P250 -> 0 | T35: =Simulacao!P252 -> 16262.28 | U35: =U34+T35 -> 134702.87
P36: Jul/27 | Q36: =Simulacao!Q249 -> 281671.07 | R36: =Simulacao!Q7 -> 57461.922 | S36: =Simulacao!Q250 -> 0 | T36: =Simulacao!Q252 -> 224209.15 | U36: =U35+T36 -> 358912.03
P37: Ago/27 | Q37: =Simulacao!R249 -> 161721.87 | R37: =Simulacao!R7 -> 68979.843 | S37: =Simulacao!R250 -> 0 | T37: =Simulacao!R252 -> 92742.025 | U37: =U36+T37 -> 451654.05
P38: Set/27 | Q38: =Simulacao!S249 -> 43681.482 | R38: =Simulacao!S7 -> 64726.665 | S38: =Simulacao!S250 -> 0 | T38: =Simulacao!S252 -> -21045.183 | U38: =U37+T38 -> 430608.87
P39: Out/27 | Q39: =Simulacao!T249 -> 44436.59 | R39: =Simulacao!T7 -> 66518.636 | S39: =Simulacao!T250 -> 0 | T39: =Simulacao!T252 -> -22082.045 | U39: =U38+T39 -> 408526.82
P40: Nov/27 | Q40: =Simulacao!U249 -> 44290.502 | R40: =Simulacao!U7 -> 64317.198 | S40: =Simulacao!U250 -> 0 | T40: =Simulacao!U252 -> -20026.696 | U40: =U39+T40 -> 388500.13
P41: Dez/27 | Q41: =Simulacao!V249 -> 45775.2 | R41: =Simulacao!V7 -> 61072.279 | S41: =Simulacao!V250 -> 0 | T41: =Simulacao!V252 -> -15297.079 | U41: =U40+T41 -> 373203.05
P42: Jan/28 | Q42: =Simulacao!W249 -> 42484.598 | R42: =Simulacao!W7 -> 63022.753 | S42: =Simulacao!W250 -> 0 | T42: =Simulacao!W252 -> -20538.155 | U42: =U41+T42 -> 352664.89
P43: Fev/28 | Q43: =Simulacao!X249 -> 45032.044 | R43: =Simulacao!X7 -> 56158.671 | S43: =Simulacao!X250 -> 0 | T43: =Simulacao!X252 -> -11126.626 | U43: =U42+T43 -> 341538.27
P44: Mar/28 | Q44: =Simulacao!Y249 -> 212454.37 | R44: =Simulacao!Y7 -> 64414.061 | S44: =Simulacao!Y250 -> 0 | T44: =Simulacao!Y252 -> 148040.31 | U44: =U43+T44 -> 489578.58
B45: D. BANCO DE CRÉDITOS — SALDO FINAL MAI/2028 POR UC | Banco total Copasul (incl. geração própria) | P45: Abr/28 | Q45: =Simulacao!Z249 -> 35167.544 | R45: =Simulacao!Z7 -> 64273.169 | S45: =Simulacao!Z250 -> 0 | T45: =Simulacao!Z252 -> -29105.625 | U45: =U44+T45 -> 460472.96
B46: Unidade Consumidora | C46: Grupo | D46: Saldo (kWh) | E46: Valor @ PPA (R$) | F46: % do banco total | P46: Mai/28 | Q46: =Simulacao!AA249 -> 32721.222 | R46: =Simulacao!AA7 -> 60152.078 | S46: =Simulacao!AA250 -> 0 | T46: =Simulacao!AA252 -> -27430.856 | U46: =U45+T46 -> 433042.1
B47: NHS — Novo Horizonte do Sul | C47: A4V | D47: =Simulacao!B255 -> 254510.59 | E47: =Simulacao!B255*Premissas!$B$17 -> 112620.93 | F47: =IFERROR(Simulacao!B255/Simulacao!B273,0) -> 0.28368386 | P47: Jun/28 | Q47: =Simulacao!AB249 -> 76710.703 | R47: =Simulacao!AB7 -> 54318.291 | S47: =Simulacao!AB250 -> 0 | T47: =Simulacao!AB252 -> 22392.412 | U47: =U46+T47 -> 455434.51
B48: AMD — Amandina | C48: A3A | D48: =Simulacao!B256 -> 609455.6 | E48: =Simulacao!B256*Premissas!$B$17 -> 269684.1 | F48: =IFERROR(Simulacao!B256/Simulacao!B273,0) -> 0.67931443 | P48: Jul/28 | Q48: =Simulacao!AC249 -> 374061.52 | R48: =Simulacao!AC7 -> 57174.612 | S48: =Simulacao!AC250 -> 0 | T48: =Simulacao!AC252 -> 316886.91 | U48: =U47+T48 -> 772321.42
B49: AREC | C49: B3 | D49: =Simulacao!B257 -> 627.07106 | E49: =Simulacao!B257*Premissas!$B$17 -> 277.47895 | F49: =IFERROR(Simulacao!B257/Simulacao!B273,0) -> 0.00069894907 | P49: Ago/28 | Q49: =Simulacao!AD249 -> 246358.78 | R49: =Simulacao!AD7 -> 68634.943 | S49: =Simulacao!AD250 -> 72492.947 | T49: =Simulacao!AD252 -> 105230.89 | U49: =U48+T49 -> 877552.31
B50: Banheiro Motoristas | C50: B3 | D50: =Simulacao!B258 -> 65.992243 | E50: =Simulacao!B258*Premissas!$B$17 -> 29.201568 | F50: =IFERROR(Simulacao!B258/Simulacao!B273,0) -> 7.3556602e-05 | P50: Set/28 | Q50: =Simulacao!AE249 -> 33539.253 | R50: =Simulacao!AE7 -> 64403.032 | S50: =Simulacao!AE250 -> 0 | T50: =Simulacao!AE252 -> -30863.78 | U50: =U49+T50 -> 846688.53
B51: CTC Copasul | C51: B3 | D51: =Simulacao!B259 -> 0 | E51: =Simulacao!B259*Premissas!$B$17 -> 0 | F51: =IFERROR(Simulacao!B259/Simulacao!B273,0) -> 0 | P51: Out/28 | Q51: =Simulacao!AF249 -> 33539.253 | R51: =Simulacao!AF7 -> 66186.042 | S51: =Simulacao!AF250 -> 0 | T51: =Simulacao!AF252 -> -32646.79 | U51: =U50+T51 -> 814041.75
B52: Depósito Irrigação | C52: B3 | D52: =Simulacao!B260 -> 174.63084 | E52: =Simulacao!B260*Premissas!$B$17 -> 77.274148 | F52: =IFERROR(Simulacao!B260/Simulacao!B273,0) -> 0.0001946479 | P52: Nov/28 | Q52: =Simulacao!AG249 -> 33539.253 | R52: =Simulacao!AG7 -> 63995.612 | S52: =Simulacao!AG250 -> 0 | T52: =Simulacao!AG252 -> -30456.359 | U52: =U51+T52 -> 783585.39
B53: Entreposto | C53: B3 | D53: =Simulacao!B261 -> 207.78163 | E53: =Simulacao!B261*Premissas!$B$17 -> 91.943372 | F53: =IFERROR(Simulacao!B261/Simulacao!B273,0) -> 0.0002315986 | P53: Dez/28 | Q53: =Simulacao!AH249 -> 33539.253 | R53: =Simulacao!AH7 -> 60766.918 | S53: =Simulacao!AH250 -> 0 | T53: =Simulacao!AH252 -> -27227.665 | U53: =U52+T53 -> 756357.72
B54: Esc. Deodápolis | C54: B3 | D54: =Simulacao!B262 -> 273.73782 | E54: =Simulacao!B262*Premissas!$B$17 -> 121.12899 | F54: =IFERROR(Simulacao!B262/Simulacao!B273,0) -> 0.00030511502 | P54: Jan/29 | Q54: =Simulacao!AI249 -> 33539.253 | R54: =Simulacao!AI7 -> 62707.639 | S54: =Simulacao!AI250 -> 0 | T54: =Simulacao!AI252 -> -29168.386 | U54: =U53+T54 -> 727189.33
B55: Esc. Nova Andradina | C55: B3 | D55: =Simulacao!B263 -> 228.39983 | E55: =Simulacao!B263*Premissas!$B$17 -> 101.06693 | F55: =IFERROR(Simulacao!B263/Simulacao!B273,0) -> 0.00025458016 | P55: Fev/29 | Q55: =Simulacao!AJ249 -> 33539.253 | R55: =Simulacao!AJ7 -> 55877.877 | S55: =Simulacao!AJ250 -> 0 | T55: =Simulacao!AJ252 -> -22338.625 | U55: =U54+T55 -> 704850.71
B56: Esc. Regional Deodápolis | C56: B3 | D56: =Simulacao!B264 -> 0 | E56: =Simulacao!B264*Premissas!$B$17 -> 0 | F56: =IFERROR(Simulacao!B264/Simulacao!B273,0) -> 0 | P56: Mar/29 | Q56: =Simulacao!AK249 -> 221747.08 | R56: =Simulacao!AK7 -> 64091.991 | S56: =Simulacao!AK250 -> 0 | T56: =Simulacao!AK252 -> 157655.09 | U56: =U55+T56 -> 862505.8
B57: Galpão AE | C57: B3 | D57: =Simulacao!B265 -> 7584.3975 | E57: =Simulacao!B265*Premissas!$B$17 -> 3356.0959 | F57: =IFERROR(Simulacao!B265/Simulacao!B273,0) -> 0.0084537589 | P57: Abr/29 | Q57: =Simulacao!AL249 -> 33539.253 | R57: =Simulacao!AL7 -> 63951.803 | S57: =Simulacao!AL250 -> 0 | T57: =Simulacao!AL252 -> -30412.551 | U57: =U56+T57 -> 832093.25
B58: Irrigação CG | C58: B3 | D58: =Simulacao!B266 -> 0 | E58: =Simulacao!B266*Premissas!$B$17 -> 0 | F58: =IFERROR(Simulacao!B266/Simulacao!B273,0) -> 0 | P58: Mai/29 | Q58: =Simulacao!AM249 -> 33539.253 | R58: =Simulacao!AM7 -> 59851.318 | S58: =Simulacao!AM250 -> 0 | T58: =Simulacao!AM252 -> -26312.065 | U58: =U57+T58 -> 805781.18
B59: Laboratório de Solos | C59: B3 | D59: =Simulacao!B267 -> 14559.877 | E59: =Simulacao!B267*Premissas!$B$17 -> 6442.7457 | F59: =IFERROR(Simulacao!B267/Simulacao!B273,0) -> 0.016228803 | P59: Jun/29 | Q59: =Simulacao!AN249 -> 167595.69 | R59: =Simulacao!AN7 -> 54046.699 | S59: =Simulacao!AN250 -> 0 | T59: =Simulacao!AN252 -> 113549 | U59: =U58+T59 -> 919330.18
B60: Posto Carreteiro | C60: B3 | D60: =Simulacao!B268 -> 0 | E60: =Simulacao!B268*Premissas!$B$17 -> 0 | F60: =IFERROR(Simulacao!B268/Simulacao!B273,0) -> 0 | P60: Jul/29 | Q60: =Simulacao!AO249 -> 478137.1 | R60: =Simulacao!AO7 -> 56888.739 | S60: =Simulacao!AO250 -> 0 | T60: =Simulacao!AO252 -> 421248.37 | U60: =U59+T60 -> 1340578.5
B61: Refeitório Deodápolis | C61: B1 | D61: =Simulacao!B269 -> 8759.8746 | E61: =Simulacao!B269*Premissas!$B$17 -> 3876.2445 | F61: =IFERROR(Simulacao!B269/Simulacao!B273,0) -> 0.0097639751 | P61: Ago/29 | Q61: =Simulacao!AP249 -> 254930.19 | R61: =Simulacao!AP7 -> 68291.769 | S61: =Simulacao!AP250 -> 96084.011 | T61: =Simulacao!AP252 -> 90554.411 | U61: =U60+T61 -> 1431133
B62: Subest. Fiação | C62: B3 | D62: =Simulacao!B270 -> 714.79122 | E62: =Simulacao!B270*Premissas!$B$17 -> 316.29512 | F62: =IFERROR(Simulacao!B270/Simulacao!B273,0) -> 0.00079672415 | P62: Set/29 | Q62: =Simulacao!AQ249 -> 34377.734 | R62: =Simulacao!AQ7 -> 64081.017 | S62: =Simulacao!AQ250 -> 0 | T62: =Simulacao!AQ252 -> -29703.283 | U62: =U61+T62 -> 1401429.7
B63: TRR Maracaju | C63: B3 | D63: =Simulacao!B271 -> 0 | E63: =Simulacao!B271*Premissas!$B$17 -> 0 | F63: =IFERROR(Simulacao!B271/Simulacao!B273,0) -> 0 | P63: Out/29 | Q63: =Simulacao!AR249 -> 34377.734 | R63: =Simulacao!AR7 -> 65855.112 | S63: =Simulacao!AR250 -> 0 | T63: =Simulacao!AR252 -> -31477.378 | U63: =U62+T63 -> 1369952.3
B64: TOTAL — 17 UCs | D64: =Simulacao!B273 -> 897162.74 | E64: =Simulacao!B273*Premissas!$B$17 -> 396994.51 | F64: =1 -> 1 | P64: Nov/29 | Q64: =Simulacao!AS249 -> 34377.734 | R64: =Simulacao!AS7 -> 63675.634 | S64: =Simulacao!AS250 -> 0 | T64: =Simulacao!AS252 -> -29297.9 | U64: =U63+T64 -> 1340654.4
B65: E. BANCO ATRIBUÍVEL HELEXIA — O QUE A HELEXIA REALMENTE ENTREGA | P65: Dez/29 | Q65: =Simulacao!AT249 -> 34377.734 | R65: =Simulacao!AT7 -> 60463.083 | S65: =Simulacao!AT250 -> 0 | T65: =Simulacao!AT252 -> -26085.349 | U65: =U64+T65 -> 1314569
B66: Unidade / Grupo | C66: Banco SEM | D66: Banco COM | E66: Atribuível (kWh) | F66: Atribuível (R$) | P66: Jan/30 | Q66: =Simulacao!AU249 -> 34377.734 | R66: =Simulacao!AU7 -> 62394.101 | S66: =Simulacao!AU250 -> 0 | T66: =Simulacao!AU252 -> -28016.367 | U66: =U65+T66 -> 1286552.7
B67: NHS — Silos N. Horizonte | C67: =Simulacao!BK34 -> 32298.103 | D67: =Simulacao!BK31 -> 254510.59 | E67: =Simulacao!B281 -> 222212.48 | F67: =Simulacao!B281*Premissas!$B$17 -> 98329.024 | P67: Fev/30 | Q67: =Simulacao!AV249 -> 34377.734 | R67: =Simulacao!AV7 -> 55598.488 | S67: =Simulacao!AV250 -> 0 | T67: =Simulacao!AV252 -> -21220.754 | U67: =U66+T67 -> 1265331.9
B68: AMD — Silos Amandina | C68: =Simulacao!BK52 -> 37933.466 | D68: =Simulacao!BK49 -> 609455.6 | E68: =Simulacao!B282 -> 571522.14 | F68: =Simulacao!B282*Premissas!$B$17 -> 252898.55 | P68: Mar/30 | Q68: =Simulacao!AW249 -> 240506.44 | R68: =Simulacao!AW7 -> 63771.531 | S68: =Simulacao!AW250 -> 0 | T68: =Simulacao!AW252 -> 176734.91 | U68: =U67+T68 -> 1442066.8
B69: Grupo B (15 UCs) | C69: 0 | D69: =Simulacao!BK62+Simulacao!BK75+Simulacao!BK88+Simulacao!BK101+Simulacao!BK114+Simulacao!BK127+Simulacao!BK140+Simulacao!BK153+Simulacao!BK166+Simulacao!BK179+Simulacao!BK192+Simulacao!BK205+Simulacao!BK218+Simulacao!BK230+Simulacao!BK242 -> 33196.554 | E69: =Simulacao!B283 -> 33196.554 | F69: =Simulacao!B283*Premissas!$B$17 -> 14689.475 | P69: Abr/30 | Q69: =Simulacao!AX249 -> 34377.734 | R69: =Simulacao!AX7 -> 63632.044 | S69: =Simulacao!AX250 -> 0 | T69: =Simulacao!AX252 -> -29254.311 | U69: =U68+T69 -> 1412812.5
B70: TOTAL atribuível Helexia | C70: =C67+C68+C69 -> 70231.569 | D70: =D67+D68+D69 -> 897162.74 | E70: =Simulacao!B284 -> 826931.17 | F70: =Simulacao!B285 -> 365917.04 | P70: Mai/30 | Q70: =Simulacao!AY249 -> 34377.734 | R70: =Simulacao!AY7 -> 59552.061 | S70: =Simulacao!AY250 -> 0 | T70: =Simulacao!AY252 -> -25174.327 | U70: =U69+T70 -> 1387638.2
B71: NHS — Novo Horizonte do Sul (A4V) | C71: =Simulacao!BQ34 -> 0 | D71: =Simulacao!BQ31 -> 0 | E71: =Simulacao!B281 -> 222212.48 | F71: =Simulacao!B281*Premissas!$B$17 -> 98329.024 | P71: Jun/30 | Q71: =Simulacao!AZ249 -> 193852.78 | R71: =Simulacao!AZ7 -> 53776.466 | S71: =Simulacao!AZ250 -> 0 | T71: =Simulacao!AZ252 -> 140076.31 | U71: =U70+T71 -> 1527714.5
B72: AMD — Amandina (A3A) | C72: =Simulacao!BQ52 -> 0 | D72: =Simulacao!BQ49 -> 0 | E72: =Simulacao!B282 -> 571522.14 | F72: =Simulacao!B282*Premissas!$B$17 -> 252898.55 | P72: Jul/30 | Q72: =Simulacao!BA249 -> 492381.05 | R72: =Simulacao!BA7 -> 56604.295 | S72: =Simulacao!BA250 -> 119914.48 | T72: =Simulacao!BA252 -> 315862.27 | U72: =U71+T72 -> 1843576.8
B73: Grupo B — 15 UCs (SEM banco próprio = zero) | C73: 0 | D73: =Simulacao!B283 -> 33196.554 | E73: =Simulacao!B283 -> 33196.554 | F73: =Simulacao!B283*Premissas!$B$17 -> 14689.475 | P73: Ago/30 | Q73: =Simulacao!BB249 -> 263703.82 | R73: =Simulacao!BB7 -> 67950.31 | S73: =Simulacao!BB250 -> 92316.036 | T73: =Simulacao!BB252 -> 103437.48 | U73: =U72+T73 -> 1947014.3
B74: ★ BANCO ATRIBUÍVEL TOTAL HELEXIA | C74: — | D74: — | E74: =Simulacao!B284 -> 826931.17 | F74: =Simulacao!B285 -> 365917.04 | P74: Set/30 | Q74: =Simulacao!BC249 -> 35237.177 | R74: =Simulacao!BC7 -> 63760.612 | S74: =Simulacao!BC250 -> 0 | T74: =Simulacao!BC252 -> -28523.435 | U74: =U73+T74 -> 1918490.8
B75: * Banco COM = saldo que Copasul terá em Mai/2031. Banco SEM = projeção sem CS3. Atribuível = diferença gerada pela Helexia (Grupo B: 100%; NHS/AMD: COM−SEM). | P75: Out/30 | Q75: =Simulacao!BD249 -> 35237.177 | R75: =Simulacao!BD7 -> 65525.837 | S75: =Simulacao!BD250 -> 0 | T75: =Simulacao!BD252 -> -30288.659 | U75: =U74+T75 -> 1888202.2
P76: Nov/30 | Q76: =Simulacao!BE249 -> 35237.177 | R76: =Simulacao!BE7 -> 63357.256 | S76: =Simulacao!BE250 -> 74.112343 | T76: =Simulacao!BE252 -> -28194.191 | U76: =U75+T76 -> 1860008
P77: Dez/30 | Q77: =Simulacao!BF249 -> 35237.177 | R77: =Simulacao!BF7 -> 60160.768 | S77: =Simulacao!BF250 -> 200.42437 | T77: =Simulacao!BF252 -> -25124.015 | U77: =U76+T77 -> 1834884
P78: Jan/31 | Q78: =Simulacao!BG249 -> 35237.177 | R78: =Simulacao!BG7 -> 62082.13 | S78: =Simulacao!BG250 -> 179.18912 | T78: =Simulacao!BG252 -> -27024.142 | U78: =U77+T78 -> 1807859.8
P79: Fev/31 | Q79: =Simulacao!BH249 -> 35237.177 | R79: =Simulacao!BH7 -> 55320.495 | S79: =Simulacao!BH250 -> 1073.8596 | T79: =Simulacao!BH252 -> -21157.178 | U79: =U78+T79 -> 1786702.6
P80: Mar/31 | Q80: =Simulacao!BI249 -> 260772.35 | R80: =Simulacao!BI7 -> 63452.673 | S80: =Simulacao!BI250 -> 232.18062 | T80: =Simulacao!BI252 -> 197087.49 | U80: =U79+T80 -> 1983790.1
P81: Abr/31 | Q81: =Simulacao!BJ249 -> 35237.177 | R81: =Simulacao!BJ7 -> 63313.884 | S81: =Simulacao!BJ250 -> 235.48254 | T81: =Simulacao!BJ252 -> -28312.19 | U81: =U80+T81 -> 1955477.9
P82: Mai/31 | Q82: =Simulacao!BK249 -> 35237.177 | R82: =Simulacao!BK7 -> 59254.301 | S82: =Simulacao!BK250 -> 503.5544 | T82: =Simulacao!BK252 -> -24520.678 | U82: =U81+T82 -> 1930957.3
B108: ="Modelo V4_d · Usina: "&Premissas!$B$13&" · PPA: R$"&TEXT(Premissas!$B$17,"0.0000")&"/kWh"&" · Jun/2026–Mai/2031" -> Modelo V4_d · Usina: Cassilândia 03 · PPA: R$00.000/kWh · Jun/2026–Mai/2031

Sheet Premissas
A1: ="PREMISSAS — "&Premissas!$B$13&" × Copasul | Energisa MS" -> PREMISSAS — Cassilândia 03 × Copasul | Energisa MS | M1: 🎯 OTIMIZAÇÃO RATEIO — SOLVER CONFIG
A2: Azul = inputs editáveis | Preto = fórmulas | Verde = links entre abas | M2: Siga o passo a passo abaixo para maximizar Economia Líquida via Excel Solver
A4: A. TARIFAS ENERGISA MS (com tributos ICMS 17% + PIS/COFINS) | M4: ① CÉLULA OBJETIVO (aponte o Solver aqui): | P4: ENDEREÇO | Q4: VALOR ATUAL | R4: OBJETIVO
A5: Tarifa Grupo A FP com tributos (R$/kWh) | B5: 0.52647111 | C5: ← T_AFP: edit here | M5: Economia Líquida Copasul 24m (R$) | P5: Premissas!K5 | Q5: =Simulacao!B252 -> 1930957.3 | R5: ↑ MAXIMIZAR
A6: Tarifa Grupo A Ponta com tributos (R$/kWh) | B6: 2.9723794 | C6: ← T_APT: edit here
A7: Tarifa Grupo B3 com tributos (R$/kWh) | B7: 1.1568636 | C7: ← T_B3: edit here | M7: ② ATIVAR SOLVER (se ainda não estiver ativo) | O7: Arquivo → Opções → Suplementos → Gerenciar: Suplementos do Excel → Ir... → ✓ Solver Add-in → OK
A8: FA = TE_FP / TE_Ponta | B8: 0.60426705 | C8: ← FA: edit here | M8: ③ ABRIR SOLVER | O8: Guia Dados → botão "Solver" (canto direito da faixa de opções)
A9: ICMS (%) | B9: 0.17 | C9: ← ICMS: edit here | M9: ④ CONFIGURAR OBJETIVO | O9: Definir Objetivo: selecione a célula Premissas!K5 → marque ● Máx
A10: PIS + COFINS (%) | B10: 0.0855 | C10: ← PIS_COFINS: edit here | M10: ⑤ DEFINIR CÉLULAS VARIÁVEIS | O10: Alterando Células de Variáveis: Premissas!$B$33:$K$50 (170 variáveis = 17 UCs × 10 períodos)
A11: ICMS isenção autoconsumo remoto ativa? (Art. 23-A RICMS/MS) → 'Sim' = isento | 'Não' = ICMS cobrado sobre kWh compensados pelo CS3 | B11: Sim | C11: =IF($B$11="Sim",0,$B$5*$B$9/(1+$B$9)) -> 0 | D11: =IF($B$11="Sim",0,$B$6*$B$9/(1+$B$9)) -> 0 | E11: =IF($B$11="Sim",0,$B$7*$B$9/(1+$B$9)) -> 0 | F11: ← B=toggle (Sim/Não) | C=ICMS A_FP D=ICMS A_Ponta E=ICMS Grupo B (R$/kWh) — tudo 0 se Sim
A12: B. CONDIÇÕES DO CONTRATO | M12: ⑥ ADICIONAR AS RESTRIÇÕES (Adicionar → preencher cada linha → OK)
A13: Usina | B13: Cassilândia 03 | M13: Célula / Intervalo | O13: Relação | P13: Valor / Restrição | R13: Descrição
A14: Distribuidora | B14: Energisa MS | M14: Premissas!$B$33:$K$50 | O14: >= | P14: 0 | R14: Todos os rateios ≥ 0% (sem valores negativos, P1–P10)
A15: Início do contrato | B15: Jun/2026 | M15: Premissas!$B$51 | O15: = | P15: 1 | R15: Soma P1 = 100% (Jun–Set/26)
A16: Prazo (meses) | B16: 60 | M16: Premissas!$C$51 | O16: = | P16: 1 | R16: Soma P2 = 100% (Out/26–Mar/27)
A17: PPA Helexia CS3 (R$/kWh) | B17: 0.4425 | M17: Premissas!$D$51 | O17: = | P17: 1 | R17: Soma P3 = 100% (Abr–Set/27)
A18: H. CENÁRIO CONCORRENTE — ENERGIA ASSINATURA GRUPO B (ex: Plin Energia) | M18: Premissas!$E$51 | O18: = | P18: 1 | R18: Soma P4 = 100% (Out/27–Mai/28)
A19: Grupo B tem contrato Assinatura GD concorrente? | B19: Sim | C19: Desconto (%): | D19: 0.2 | E19: Tarifa B3 SEM efetiva: | F19: =IF(B19="Sim",B7*(1-D19),B7) -> 0.92549092 | M19: Premissas!$F$51 | O19: = | P19: 1 | R19: Soma P5 = 100% (Jun–Nov/28)
A20: C. PREMISSAS DE CRESCIMENTO E DEGRADAÇÃO | M20: Premissas!$G$51 | O20: = | P20: 1 | R20: Soma P6 = 100% (Dez/28–Mai/29)
A21: Crescimento consumo Y2 vs Y1 (%) | B21: 0.025 | C21: ← 2.5% editável | aplica a TODOS os UCs | M21: Premissas!$H$51 | O21: = | P21: 1 | R21: Soma P7 = 100% (Jun–Nov/29)
A22: Crescimento consumo Y3 parcial (Dez/27-Mai/28) (%) | B22: =B21 -> 0.025 | C22: ← mesmo % que Y2 por padrão | M22: Premissas!$I$51 | O22: = | P22: 1 | R22: Soma P8 = 100% (Dez/29–Mai/30)
A23: Degradação geração Y2 (%) | B23: 0.005 | C23: ← 0.5%/ano editável | M23: Premissas!$J$51 | O23: = | P23: 1 | R23: Soma P9 = 100% (Jun–Nov/30)
A24: Usar proxy Batayporã p/ Amandina gen? | B24: Sim | M24: Premissas!$K$51 | O24: = | P24: 1 | R24: Soma P10 = 100% (Dez/30–Mai/31)
A25: D. BANCOS DE CRÉDITOS — SALDO INICIAL (Mai/2026, FPt GD I) | M25: Premissas!$B$34:$K$34 | O25: = | P25: 0 | R25: BAT (linha 34) = 0% em todos os períodos (P1–P10)
A26: NHS — Silos Novo Horizonte do Sul (kWh) | B26: 148516 | M26: Premissas!$B$33:$E$50 | O26: <= | P26: 1 | R26: Todos os rateios ≤ 100% (limite superior)
A27: BAT — Silos Batayporã (kWh) [stranded — não transferível CS3] | B27: 906739
A28: AMD — Silos Amandina (kWh) | B28: 991029
A29: TOTAL NHS+AMD (kWh) | B29: =B26+B28 -> 1139545 | C29: ← BAT stranded bank não incluído no total | M29: ⑦ MÉTODO DE RESOLUÇÃO E OPÇÕES
M30: Método de Resolução: | O30: GRG Não-Linear | P30: O modelo tem funções IF (não-lineares). GRG é o método correto.
A31: ="E. RATEIO FIXO "&INDEX(PVSYST_Helexia!$A$5:$A$7,MATCH(Premissas!$B$13,PVSYST_Helexia!$B$5:$B$7,0))&" — 4 PERÍODOS (edit percentuais — devem somar 100% por período)" -> E. RATEIO FIXO HCS03 — 4 PERÍODOS (edit percentuais — devem somar 100% por período) | F31: Anos 3–5 (estado estacionário) | M31: Opções → Precisão: | O31: 0,000001 | P31: Maior precisão = resultado mais fino.
A32: UC / Planta | B32: P1: Jun–Set/26 | C32: P2: Out/26–Mar/27 | D32: P3: Abr/27–Set/27 | E32: P4: Out/27–Mai/28 | F32: P5: Jun–Nov/28 | G32: P6: Dez/28–Mai/29 | H32: P7: Jun–Nov/29 | I32: P8: Dez/29–Mai/30 | J32: P9: Jun–Nov/30 | K32: P10: Dez/30–Mai/31 | M32: Opções → Iterações: | O32: 1000 | P32: Permite mais buscas antes de parar.
A33: NHS — Silos N. Horizonte (A4V) | B33: 0.738 | C33: 0.5178 | D33: 0.6714 | E33: 0.2592 | F33: 0.4741 | G33: 0.4673 | H33: 0.4724 | I33: 0.4656 | J33: 0.5826 | K33: 0.4621 | M33: Opções → Convergência: | O33: 0,0001 | P33: Critério de parada quando melhoria < este valor.
A34: BAT — Silos Batayporã (A4V) | B34: 0 | C34: 0 | D34: 0 | E34: 0 | F34: 0 | G34: 0 | H34: 0 | I34: 0 | J34: 0 | K34: 0 | M34: ⚠ Otimização local: | O34: Execute 2–3 vezes | P34: GRG pode parar em mínimo local. Rode com rateios iniciais diferentes e fique com o melhor resultado.
A35: AMD — Silos Amandina (A3A) | B35: 0 | C35: 0 | D35: 0.0041 | E35: 0.1561 | F35: 0.3735 | G35: 0.3698 | H35: 0.3726 | I35: 0.3688 | J35: 0.2324 | K35: 0.2925
A36: AREC (B3) | B36: 0.027 | C36: 0.0532 | D36: 0.0311 | E36: 0.0674 | F36: 0.0156 | G36: 0.0171 | H36: 0.016 | I36: 0.0174 | J36: 0.0304 | K36: 0.0322 | M36: ⑧ EXECUTAR → clicar "Resolver" → aceitar "Manter Solução do Solver"
A37: Banheiro Motoristas (B3) | B37: 0.0033 | C37: 0.005 | D37: 0.004 | E37: 0.0045 | F37: 0.0026 | G37: 0.0027 | H37: 0.0026 | I37: 0.0027 | J37: 0.0027 | K37: 0.0034 | M37: Economia Liquida ANTES da otimização (R$): | P37: 670877.66 | Q37: ← valor antes de rodar o Solver (referência)
A38: CTC Copasul (B3) | B38: 0.0031 | C38: 0.0077 | D38: 0.0039 | E38: 0.0072 | F38: 0.0032 | G38: 0.0034 | H38: 0.0032 | I38: 0.0034 | J38: 0.0037 | K38: 0.0043 | M38: Vsalor Banco Residual ANTES da otimização (R$): | P38: =Resumo!H5 -> 396994.51 | Q38: ← valor antes de rodar o Solver (referência)
A39: Depósito Irrigação (B3) | B39: 0.0064 | C39: 0.0114 | D39: 0.0081 | E39: 0.0095 | F39: 0.007 | G39: 0.0075 | H39: 0.0071 | I39: 0.0076 | J39: 0.0098 | K39: 0.0044 | M39: Economia APÓS otimização (R$) — resultado: | P39: =Simulacao!B252 -> 1930957.3 | Q39: ← atualiza automaticamente após o Solver alterar B33:E50
A40: Entreposto (B3) | B40: 0.059 | C40: 0.1067 | D40: 0.0727 | E40: 0.2104 | F40: 0.006 | G40: 0.0064 | H40: 0.0061 | I40: 0.0065 | J40: 0.0075 | K40: 0.0313
A41: Esc. Deodápolis (B3) | B41: 0.0213 | C41: 0.0358 | D41: 0.026 | E41: 0.0439 | F41: 0.0111 | G41: 0.0121 | H41: 0.0113 | I41: 0.0123 | J41: 0.0181 | K41: 0.0212
A42: Esc. Nova Andradina (B3) | B42: 0.0121 | C42: 0.0296 | D42: 0.0159 | E42: 0.0286 | F42: 0.0122 | G42: 0.0133 | H42: 0.0125 | I42: 0.0136 | J42: 0.0137 | K42: 0.0177
A43: Esc. Regional Deodápolis (B3) | B43: 0.0046 | C43: 0.0157 | D43: 0.006 | E43: 0.0147 | F43: 0.0031 | G43: 0.0033 | H43: 0.0031 | I43: 0.0033 | J43: 0.0036 | K43: 0.0048
A44: Galpão AE (B3) | B44: 0.0059 | C44: 0.0043 | D44: 0.0059 | E44: 0.0043 | F44: 0.0025 | G44: 0.0026 | H44: 0.0025 | I44: 0.0027 | J44: 0.0027 | K44: 0.0033
A45: Irrigação CG (B3) | B45: 0.0042 | C45: 0.0114 | D45: 0.0055 | E45: 0.0102 | F45: 0.004 | G45: 0.0042 | H45: 0.004 | I45: 0.0043 | J45: 0.0049 | K45: 0.0043
A46: Lab. Solos (B3) | B46: 0.0234 | C46: 0.0483 | D46: 0.0147 | E46: 0.0267 | F46: 0.0025 | G46: 0.0026 | H46: 0.0025 | I46: 0.0027 | J46: 0.0027 | K46: 0.0033
A47: Posto Carreteiro (B3) | B47: 0.056 | C47: 0.0993 | D47: 0.0824 | E47: 0.1023 | F47: 0.0516 | G47: 0.0531 | H47: 0.052 | I47: 0.0535 | J47: 0.0452 | K47: 0.0699
A48: Refeitório Deodápolis (B1) | B48: 0.0011 | C48: 0.0018 | D48: 0.0014 | E48: 0.0016 | F48: 0.0025 | G48: 0.0026 | H48: 0.0025 | I48: 0.0027 | J48: 0.0027 | K48: 0.0033
A49: Subest. Fiação (B3) | B49: 0.0085 | C49: 0.0153 | D49: 0.0104 | E49: 0.0133 | F49: 0.0073 | G49: 0.008 | H49: 0.0075 | I49: 0.0081 | J49: 0.0101 | K49: 0.0114
A50: TRR Maracaju (B3) | B50: 0.026 | C50: 0.0365 | D50: 0.0367 | E50: 0.0399 | F50: 0.0214 | G50: 0.024 | H50: 0.022 | I50: 0.0246 | J50: 0.0272 | K50: 0.0306
A51: TOTAL (deve = 100%) | B51: =SUM(B33:B50) -> 0.9999 | C51: =SUM(C33:C50) -> 0.9998 | D51: =SUM(D33:D50) -> 1.0002 | E51: =SUM(E33:E50) -> 0.9998 | F51: =SUM(F33:F50) -> 1.0002 | G51: =SUM(G33:G50) -> 1 | H51: =SUM(H33:H50) -> 0.9999 | I51: =SUM(I33:I50) -> 0.9998 | ... K51: =SUM(K33:K50) -> 1
A52: ⚠ Ajuste os percentuais acima para que cada coluna some exatamente 100%. BAT está fixo em 0% — seus créditos futuros entram via mecanismo de rateio próprio (seção F abaixo). A otimização automática maximiza o aproveitamento dos créditos CS3.
A53: ⚠ P5–P10 (Jun/2028–Mai/2031): alocação optimizada (SLSQP, 102 variáveis). NHS ~47–58%, AMD ~29–37%, Posto ~5–7%, TRR ~2–3%, outros GrupoB ~0.3–1.7%. Para re-optimizar P1–P4, use o Solver apenas em B33:E50.
A54: F. RATEIO DO SURPLUS BAT — 2 PERÍODOS (NH 39% / AMD 61% por padrão)
A55: BAT→NHS (%) | B55: 0.5 | C55: ← editável
A56: BAT→AMD (%) | B56: =1-B55 -> 0.5 | C56: ← = 1 − NHS%
A59: ="G. GERAÇÃO "&INDEX(PVSYST_Helexia!$A$5:$A$7,MATCH(Premissas!$B$13,PVSYST_Helexia!$B$5:$B$7,0))&" P50 — PVSYST "&Premissas!$B$13&" (kWh/mês)" -> G. GERAÇÃO HCS03 P50 — PVSYST Cassilândia 03 (kWh/mês)
A60: Degradação Y2 aplicada | B60: =Premissas!$B$23 -> 0.005 | C60: ← Y1: valor direto PVSYST | Y2/Y3: × (1−DEG)
A61: Jun/26 | B61: =INDEX(PVSYST_Helexia!$J$5:$U$7,MATCH(Premissas!$B$13,PVSYST_Helexia!$B$5:$B$7,0),6)*1000 -> 123990 | C61: kWh — CS3 P50 mês 06 (base=136,620 kWh)
A62: Jul/26 | B62: =INDEX(PVSYST_Helexia!$J$5:$U$7,MATCH(Premissas!$B$13,PVSYST_Helexia!$B$5:$B$7,0),7)*1000 -> 130510 | C62: kWh — CS3 P50 mês 07 (base=123,990 kWh)
A63: Ago/26 | B63: =INDEX(PVSYST_Helexia!$J$5:$U$7,MATCH(Premissas!$B$13,PVSYST_Helexia!$B$5:$B$7,0),8)*1000 -> 156670 | C63: kWh — CS3 P50 mês 08 (base=130,510 kWh)
A64: Set/26 | B64: =INDEX(PVSYST_Helexia!$J$5:$U$7,MATCH(Premissas!$B$13,PVSYST_Helexia!$B$5:$B$7,0),9)*1000 -> 147010 | C64: kWh — CS3 P50 mês 09 (base=156,670 kWh)
A65: Out/26 | B65: =INDEX(PVSYST_Helexia!$J$5:$U$7,MATCH(Premissas!$B$13,PVSYST_Helexia!$B$5:$B$7,0),10)*1000 -> 151080 | C65: kWh — CS3 P50 mês 10 (base=147,010 kWh)
A66: Nov/26 | B66: =INDEX(PVSYST_Helexia!$J$5:$U$7,MATCH(Premissas!$B$13,PVSYST_Helexia!$B$5:$B$7,0),11)*1000 -> 146080 | C66: kWh — CS3 P50 mês 11 (base=151,080 kWh)
A67: Dez/26 | B67: =INDEX(PVSYST_Helexia!$J$5:$U$7,MATCH(Premissas!$B$13,PVSYST_Helexia!$B$5:$B$7,0),12)*1000 -> 138710 | C67: kWh — CS3 P50 mês 12 (base=146,080 kWh)
A68: Jan/27 | B68: =INDEX(PVSYST_Helexia!$J$5:$U$7,MATCH(Premissas!$B$13,PVSYST_Helexia!$B$5:$B$7,0),1)*1000*(1-Premissas!$B$23) -> 142424.3 | C68: kWh — CS3 P50 mês 01 (base=2,000 kWh)
A69: Fev/27 | B69: =INDEX(PVSYST_Helexia!$J$5:$U$7,MATCH(Premissas!$B$13,PVSYST_Helexia!$B$5:$B$7,0),2)*1000*(1-Premissas!$B$23) -> 126912.25 | C69: kWh — CS3 P50 mês 02 (base=143,140 kWh)
A70: Mar/27 | B70: =INDEX(PVSYST_Helexia!$J$5:$U$7,MATCH(Premissas!$B$13,PVSYST_Helexia!$B$5:$B$7,0),3)*1000*(1-Premissas!$B$23) -> 145568.5 | C70: kWh — CS3 P50 mês 03 (base=127,550 kWh)
A71: Abr/27 | B71: =INDEX(PVSYST_Helexia!$J$5:$U$7,MATCH(Premissas!$B$13,PVSYST_Helexia!$B$5:$B$7,0),4)*1000*(1-Premissas!$B$23) -> 145250.1 | C71: kWh — CS3 P50 mês 04 (base=146,300 kWh)
A72: Mai/27 | B72: =INDEX(PVSYST_Helexia!$J$5:$U$7,MATCH(Premissas!$B$13,PVSYST_Helexia!$B$5:$B$7,0),5)*1000*(1-Premissas!$B$23) -> 135936.9 | C72: kWh — CS3 P50 mês 05 (base=145,980 kWh)
A73: Jun/27 | B73: =INDEX(PVSYST_Helexia!$J$5:$U$7,MATCH(Premissas!$B$13,PVSYST_Helexia!$B$5:$B$7,0),6)*1000*(1-Premissas!$B$23) -> 123370.05 | C73: kWh — CS3 P50 mês 06 (base=136,620 kWh)
A74: Jul/27 | B74: =INDEX(PVSYST_Helexia!$J$5:$U$7,MATCH(Premissas!$B$13,PVSYST_Helexia!$B$5:$B$7,0),7)*1000*(1-Premissas!$B$23) -> 129857.45 | C74: kWh — CS3 P50 mês 07 (base=123,990 kWh)
A75: Ago/27 | B75: =INDEX(PVSYST_Helexia!$J$5:$U$7,MATCH(Premissas!$B$13,PVSYST_Helexia!$B$5:$B$7,0),8)*1000*(1-Premissas!$B$23) -> 155886.65 | C75: kWh — CS3 P50 mês 08 (base=130,510 kWh)
A76: Set/27 | B76: =INDEX(PVSYST_Helexia!$J$5:$U$7,MATCH(Premissas!$B$13,PVSYST_Helexia!$B$5:$B$7,0),9)*1000*(1-Premissas!$B$23) -> 146274.95 | C76: kWh — CS3 P50 mês 09 (base=156,670 kWh)
A77: Out/27 | B77: =INDEX(PVSYST_Helexia!$J$5:$U$7,MATCH(Premissas!$B$13,PVSYST_Helexia!$B$5:$B$7,0),10)*1000*(1-Premissas!$B$23) -> 150324.6 | C77: kWh — CS3 P50 mês 10 (base=147,010 kWh)
A78: Nov/27 | B78: =INDEX(PVSYST_Helexia!$J$5:$U$7,MATCH(Premissas!$B$13,PVSYST_Helexia!$B$5:$B$7,0),11)*1000*(1-Premissas!$B$23) -> 145349.6 | C78: kWh — CS3 P50 mês 11 (base=151,080 kWh)
A79: Dez/27 | B79: =INDEX(PVSYST_Helexia!$J$5:$U$7,MATCH(Premissas!$B$13,PVSYST_Helexia!$B$5:$B$7,0),12)*1000*(1-Premissas!$B$23) -> 138016.45 | C79: kWh — CS3 P50 mês 12 (base=146,080 kWh)
A80: Jan/28 | B80: =INDEX(PVSYST_Helexia!$J$5:$U$7,MATCH(Premissas!$B$13,PVSYST_Helexia!$B$5:$B$7,0),1)*1000*(1-Premissas!$B$23) -> 142424.3 | C80: kWh — CS3 P50 mês 01 (base=2,000 kWh)
A81: Fev/28 | B81: =INDEX(PVSYST_Helexia!$J$5:$U$7,MATCH(Premissas!$B$13,PVSYST_Helexia!$B$5:$B$7,0),2)*1000*(1-Premissas!$B$23) -> 126912.25 | C81: kWh — CS3 P50 mês 02 (base=143,140 kWh)
A82: Mar/28 | B82: =INDEX(PVSYST_Helexia!$J$5:$U$7,MATCH(Premissas!$B$13,PVSYST_Helexia!$B$5:$B$7,0),3)*1000*(1-Premissas!$B$23) -> 145568.5 | C82: kWh — CS3 P50 mês 03 (base=127,550 kWh)
A83: Abr/28 | B83: =INDEX(PVSYST_Helexia!$J$5:$U$7,MATCH(Premissas!$B$13,PVSYST_Helexia!$B$5:$B$7,0),4)*1000*(1-Premissas!$B$23) -> 145250.1 | C83: kWh — CS3 P50 mês 04 (base=146,300 kWh)
A84: Mai/28 | B84: =INDEX(PVSYST_Helexia!$J$5:$U$7,MATCH(Premissas!$B$13,PVSYST_Helexia!$B$5:$B$7,0),5)*1000*(1-Premissas!$B$23) -> 135936.9 | C84: kWh — CS3 P50 mês 05 (base=145,980 kWh)
A85: Jun/28 | B85: =INDEX(PVSYST_Helexia!$J$5:$U$7,MATCH(Premissas!$B$13,PVSYST_Helexia!$B$5:$B$7,0),6)*1000*(1-Premissas!$B$23)^2 -> 122753.2 | C85: kWh — CS3 P50 mês 06
A86: Jul/28 | B86: =INDEX(PVSYST_Helexia!$J$5:$U$7,MATCH(Premissas!$B$13,PVSYST_Helexia!$B$5:$B$7,0),7)*1000*(1-Premissas!$B$23)^2 -> 129208.16 | C86: kWh — CS3 P50 mês 07
A87: Ago/28 | B87: =INDEX(PVSYST_Helexia!$J$5:$U$7,MATCH(Premissas!$B$13,PVSYST_Helexia!$B$5:$B$7,0),8)*1000*(1-Premissas!$B$23)^2 -> 155107.22 | C87: kWh — CS3 P50 mês 08
A88: Set/28 | B88: =INDEX(PVSYST_Helexia!$J$5:$U$7,MATCH(Premissas!$B$13,PVSYST_Helexia!$B$5:$B$7,0),9)*1000*(1-Premissas!$B$23)^2 -> 145543.58 | C88: kWh — CS3 P50 mês 09
A89: Out/28 | B89: =INDEX(PVSYST_Helexia!$J$5:$U$7,MATCH(Premissas!$B$13,PVSYST_Helexia!$B$5:$B$7,0),10)*1000*(1-Premissas!$B$23)^2 -> 149572.98 | C89: kWh — CS3 P50 mês 10
A90: Nov/28 | B90: =INDEX(PVSYST_Helexia!$J$5:$U$7,MATCH(Premissas!$B$13,PVSYST_Helexia!$B$5:$B$7,0),11)*1000*(1-Premissas!$B$23)^2 -> 144622.85 | C90: kWh — CS3 P50 mês 11
A91: Dez/28 | B91: =INDEX(PVSYST_Helexia!$J$5:$U$7,MATCH(Premissas!$B$13,PVSYST_Helexia!$B$5:$B$7,0),12)*1000*(1-Premissas!$B$23)^2 -> 137326.37 | C91: kWh — CS3 P50 mês 12
A92: Jan/29 | B92: =INDEX(PVSYST_Helexia!$J$5:$U$7,MATCH(Premissas!$B$13,PVSYST_Helexia!$B$5:$B$7,0),1)*1000*(1-Premissas!$B$23)^2 -> 141712.18 | C92: kWh — CS3 P50 mês 01
A93: Fev/29 | B93: =INDEX(PVSYST_Helexia!$J$5:$U$7,MATCH(Premissas!$B$13,PVSYST_Helexia!$B$5:$B$7,0),2)*1000*(1-Premissas!$B$23)^2 -> 126277.69 | C93: kWh — CS3 P50 mês 02
A94: Mar/29 | B94: =INDEX(PVSYST_Helexia!$J$5:$U$7,MATCH(Premissas!$B$13,PVSYST_Helexia!$B$5:$B$7,0),3)*1000*(1-Premissas!$B$23)^2 -> 144840.66 | C94: kWh — CS3 P50 mês 03
A95: Abr/29 | B95: =INDEX(PVSYST_Helexia!$J$5:$U$7,MATCH(Premissas!$B$13,PVSYST_Helexia!$B$5:$B$7,0),4)*1000*(1-Premissas!$B$23)^2 -> 144523.85 | C95: kWh — CS3 P50 mês 04
A96: Mai/29 | B96: =INDEX(PVSYST_Helexia!$J$5:$U$7,MATCH(Premissas!$B$13,PVSYST_Helexia!$B$5:$B$7,0),5)*1000*(1-Premissas!$B$23)^2 -> 135257.22 | C96: kWh — CS3 P50 mês 05
A97: Jun/29 | B97: =INDEX(PVSYST_Helexia!$J$5:$U$7,MATCH(Premissas!$B$13,PVSYST_Helexia!$B$5:$B$7,0),6)*1000*(1-Premissas!$B$23)^3 -> 122139.43 | C97: kWh — CS3 P50 mês 06
A98: Jul/29 | B98: =INDEX(PVSYST_Helexia!$J$5:$U$7,MATCH(Premissas!$B$13,PVSYST_Helexia!$B$5:$B$7,0),7)*1000*(1-Premissas!$B$23)^3 -> 128562.12 | C98: kWh — CS3 P50 mês 07
A99: Ago/29 | B99: =INDEX(PVSYST_Helexia!$J$5:$U$7,MATCH(Premissas!$B$13,PVSYST_Helexia!$B$5:$B$7,0),8)*1000*(1-Premissas!$B$23)^3 -> 154331.68 | C99: kWh — CS3 P50 mês 08
A100: Set/29 | B100: =INDEX(PVSYST_Helexia!$J$5:$U$7,MATCH(Premissas!$B$13,PVSYST_Helexia!$B$5:$B$7,0),9)*1000*(1-Premissas!$B$23)^3 -> 144815.86 | C100: kWh — CS3 P50 mês 09
A101: Out/29 | B101: =INDEX(PVSYST_Helexia!$J$5:$U$7,MATCH(Premissas!$B$13,PVSYST_Helexia!$B$5:$B$7,0),10)*1000*(1-Premissas!$B$23)^3 -> 148825.11 | C101: kWh — CS3 P50 mês 10
A102: Nov/29 | B102: =INDEX(PVSYST_Helexia!$J$5:$U$7,MATCH(Premissas!$B$13,PVSYST_Helexia!$B$5:$B$7,0),11)*1000*(1-Premissas!$B$23)^3 -> 143899.74 | C102: kWh — CS3 P50 mês 11
A103: Dez/29 | B103: =INDEX(PVSYST_Helexia!$J$5:$U$7,MATCH(Premissas!$B$13,PVSYST_Helexia!$B$5:$B$7,0),12)*1000*(1-Premissas!$B$23)^3 -> 136639.74 | C103: kWh — CS3 P50 mês 12
...

Sheet Simulacao
A1: SIMULAÇÃO RATEIO FIXO — Cassilândia 03 × COPASUL | 18 UCs | Jun/2026–Mai/2031
A2: Energisa MS · Todas as células são fórmulas · Azul=input Premissas · Verde=link entre abas
A4: INDICADOR / UC | B4: TOTAL 60m ou SALDO FINAL | C4: MÉD/mês ou unidade | D4: Jun/26 | E4: Jul/26 | F4: Ago/26 | G4: Set/26 | H4: Out/26 | I4: Nov/26 | J4: Dez/26 | K4: Jan/27 | L4: Fev/27 | M4: Mar/27 | N4: Abr/27 | O4: Mai/27 | P4: Jun/27 | Q4: Jul/27 | R4: Ago/27 | S4: Set/27 | T4: Out/27 | U4: Nov/27 | V4: Dez/27 | W4: Jan/28 | X4: Fev/28 | Y4: Mar/28 | Z4: Abr/28 | AA4: Mai/28 | AB4: Jun/28 | AC4: Jul/28 | AD4: Ago/28 | AE4: Set/28 | AF4: Out/28 | AG4: Nov/28 | AH4: Dez/28 | AI4: Jan/29 | AJ4: Fev/29 | AK4: Mar/29 | AL4: Abr/29 | AM4: Mai/29 | AN4: Jun/29 | AO4: Jul/29 | AP4: Ago/29 | AQ4: Set/29 | AR4: Out/29 | AS4: Nov/29 | AT4: Dez/29 | AU4: Jan/30 | AV4: Fev/30 | AW4: Mar/30 | AX4: Abr/30 | AY4: Mai/30 | AZ4: Jun/30 | BA4: Jul/30 | BB4: Ago/30 | BC4: Set/30 | BD4: Out/30 | BE4: Nov/30 | BF4: Dez/30 | BG4: Jan/31 | BH4: Fev/31 | BI4: Mar/31 | BJ4: Abr/31 | BK4: Mai/31
A5: 0. Cassilândia 03 — GERAÇÃO E CUSTO PPA
A6: HCS03 Geração P50 (kWh) | B6: 8380442.4 | C6: 139674.04 | D6: 123990 | E6: 130510 | F6: 156670 | G6: 147010 | H6: 151080 | I6: 146080 | J6: 138710 | K6: 142424.3 | L6: 126912.25 | M6: 145568.5 | N6: 145250.1 | O6: 135936.9 | P6: 123370.05 | Q6: 129857.45 | R6: 155886.65 | S6: 146274.95 | T6: 150324.6 | U6: 145349.6 | V6: 138016.45 | W6: 142424.3 | X6: 126912.25 | Y6: 145568.5 | Z6: 145250.1 | AA6: 135936.9 | AB6: 122753.2 | AC6: 129208.16 | AD6: 155107.22 | AE6: 145543.58 | AF6: 149572.98 | AG6: 144622.85 | AH6: 137326.37 | AI6: 141712.18 | AJ6: 126277.69 | AK6: 144840.66 | AL6: 144523.85 | AM6: 135257.22 | AN6: 122139.43 | AO6: 128562.12 | AP6: 154331.68 | AQ6: 144815.86 | AR6: 148825.11 | AS6: 143899.74 | AT6: 136639.74 | AU6: 141003.62 | AV6: 125646.3 | AW6: 144116.45 | AX6: 143801.23 | AY6: 134580.93 | AZ6: 121528.74 | BA6: 127919.31 | BB6: 153560.02 | BC6: 144091.78 | BD6: 148080.99 | BE6: 143180.24 | BF6: 135956.54 | BG6: 140298.6 | BH6: 125018.07 | BI6: 143395.87 | BJ6: 143082.22 | BK6: 133908.02
A7: PPA Helexia — custo total (R$) | B7: 3708345.8 | C7: 61805.763 | D7: 54865.575 | E7: 57750.675 | F7: 69326.475 | G7: 65051.925 | H7: 66852.9 | I7: 64640.4 | J7: 61379.175 | K7: 63022.753 | L7: 56158.671 | M7: 64414.061 | N7: 64273.169 | O7: 60152.078 | P7: 54591.247 | Q7: 57461.922 | R7: 68979.843 | S7: 64726.665 | T7: 66518.636 | U7: 64317.198 | V7: 61072.279 | W7: 63022.753 | X7: 56158.671 | Y7: 64414.061 | Z7: 64273.169 | AA7: 60152.078 | AB7: 54318.291 | AC7: 57174.612 | AD7: 68634.943 | AE7: 64403.032 | AF7: 66186.042 | AG7: 63995.612 | AH7: 60766.918 | AI7: 62707.639 | AJ7: 55877.877 | AK7: 64091.991 | AL7: 63951.803 | AM7: 59851.318 | AN7: 54046.699 | AO7: 56888.739 | AP7: 68291.769 | AQ7: 64081.017 | AR7: 65855.112 | AS7: 63675.634 | AT7: 60463.083 | AU7: 62394.101 | AV7: 55598.488 | AW7: 63771.531 | AX7: 63632.044 | AY7: 59552.061 | AZ7: 53776.466 | BA7: 56604.295 | BB7: 67950.31 | BC7: 63760.612 | BD7: 65525.837 | BE7: 63357.256 | BF7: 60160.768 | BG7: 62082.13 | BH7: 55320.495 | BI7: 63452.673 | BJ7: 63313.884 | BK7: 59254.301
A8: 1. BAT — BATAYPORÃ — GERAÇÃO, CONSUMO E SURPLUS
A9: BAT Geração própria (kWh) | B9: 5593986.3 | C9: 93233.104 | D9: 72286.9 | E9: 88336.8 | F9: 93082.7 | G9: 94433.4 | H9: 95906.8 | I9: 107980.6 | J9: 106603.9 | K9: 113687.7 | L9: 90676.241 | M9: 102546.59 | N9: 73341.151 | O9: 91158.517 | P9: 71925.465 | Q9: 87895.116 | R9: 92617.287 | S9: 93961.233 | T9: 95427.266 | U9: 107440.7 | V9: 106070.88 | W9: 113119.27 | X9: 90222.859 | Y9: 102033.86 | Z9: 72974.446 | AA9: 90702.724 | AB9: 71565.838 | AC9: 87455.64 | AD9: 92154.2 | AE9: 93491.427 | AF9: 94950.13 | AG9: 106903.49 | AH9: 105540.53 | AI9: 112553.67 | AJ9: 89771.745 | AK9: 101523.69 | AL9: 72609.574 | AM9: 90249.211 | AN9: 71208.009 | AO9: 87018.362 | AP9: 91693.429 | AQ9: 93023.97 | AR9: 94475.379 | AS9: 106368.98 | AT9: 105012.82 | AU9: 111990.9 | AV9: 89322.886 | AW9: 101016.07 | AX9: 72246.526 | AY9: 89797.965 | AZ9: 70851.969 | BA9: 86583.27 | BB9: 91234.962 | BC9: 92558.85 | BD9: 94003.002 | BE9: 105837.13 | BF9: 104487.76 | BG9: 111430.95 | BH9: 88876.272 | BI9: 100510.99 | BJ9: 71885.293 | BK9: 89348.975
A10: BAT Consumo FP (kWh) | B10: 3509998.1 | C10: 58499.968 | D10: 78336 | E10: 115718.4 | F10: 23364 | G10: 10800 | H10: 10800 | I10: 10800 | J10: 3402 | K10: 116816.17 | L10: 129020.85 | M10: 58936.68 | N10: 36531 | O10: 81593.28 | P10: 80294.4 | Q10: 118611.36 | R10: 23948.1 | S10: 11070 | T10: 11070 | U10: 11070 | V10: 3487.05 | W10: 116816.17 | X10: 129020.85 | Y10: 58936.68 | Z10: 36531 | AA10: 81593.28 | AB10: 82301.76 | AC10: 121576.64 | AD10: 24546.802 | AE10: 11346.75 | AF10: 11346.75 | AG10: 11346.75 | AH10: 3574.2262 | AI10: 119736.58 | AJ10: 132246.37 | AK10: 60410.097 | AL10: 37444.275 | AM10: 83633.112 | AN10: 84359.304 | AO10: 124616.06 | AP10: 25160.473 | AQ10: 11630.419 | AR10: 11630.419 | AS10: 11630.419 | AT10: 3663.5819 | AU10: 122729.99 | AV10: 135552.53 | AW10: 61920.349 | AX10: 38380.382 | AY10: 85723.94 | AZ10: 86468.287 | BA10: 127731.46 | BB10: 25789.484 | BC10: 11921.179 | BD10: 11921.179 | BE10: 11921.179 | BF10: 3755.1715 | BG10: 125798.24 | BH10: 138941.34 | BI10: 63468.358 | BJ10: 39339.891 | BK10: 87867.038
A11: BAT Consumo Ponta (kWh) | B11: 389999.79 | C11: 6499.9965 | D11: 8704 | E11: 12857.6 | F11: 2596 | G11: 1200 | H11: 1200 | I11: 1200 | J11: 378 | K11: 12979.575 | L11: 14335.65 | M11: 6548.52 | N11: 4059 | O11: 9065.92 | P11: 8921.6 | Q11: 13179.04 | R11: 2660.9 | S11: 1230 | T11: 1230 | U11: 1230 | V11: 387.45 | W11: 12979.575 | X11: 14335.65 | Y11: 6548.52 | Z11: 4059 | AA11: 9065.92 | AB11: 9144.64 | AC11: 13508.516 | AD11: 2727.4225 | AE11: 1260.75 | AF11: 1260.75 | AG11: 1260.75 | AH11: 397.13625 | AI11: 13304.064 | AJ11: 14694.041 | AK11: 6712.233 | AL11: 4160.475 | AM11: 9292.568 | AN11: 9373.256 | AO11: 13846.229 | AP11: 2795.6081 | AQ11: 1292.2687 | AR11: 1292.2687 | AS11: 1292.2687 | AT11: 407.06466 | AU11: 13636.666 | AV11: 15061.392 | AW11: 6880.0388 | AX11: 4264.4869 | AY11: 9524.8822 | AZ11: 9607.5874 | BA11: 14192.385 | BB11: 2865.4983 | BC11: 1324.5755 | BD11: 1324.5755 | BE11: 1324.5755 | BF11: 417.24127 | BG11: 13977.583 | BH11: 15437.927 | BI11: 7052.0398 | BJ11: 4371.099 | BK11: 9763.0043
A12: BAT auto-comp. FP (kWh) | B12: 3030085.2 | C12: 50501.419 | D12: 72286.9 | E12: 88336.8 | F12: 23364 | G12: 10800 | H12: 10800 | I12: 10800 | J12: 3402 | K12: 113687.7 | L12: 90676.241 | M12: 58936.68 | N12: 36531 | O12: 81593.28 | P12: 71925.465 | Q12: 87895.116 | R12: 23948.1 | S12: 11070 | T12: 11070 | U12: 11070 | V12: 3487.05 | W12: 113119.27 | X12: 90222.859 | Y12: 58936.68 | Z12: 36531 | AA12: 81593.28 | AB12: 71565.838 | AC12: 87455.64 | AD12: 24546.802 | AE12: 11346.75 | AF12: 11346.75 | AG12: 11346.75 | AH12: 3574.2262 | AI12: 112553.67 | AJ12: 89771.745 | AK12: 60410.097 | AL12: 37444.275 | AM12: 83633.112 | AN12: 71208.009 | AO12: 87018.362 | AP12: 25160.473 | AQ12: 11630.419 | AR12: 11630.419 | AS12: 11630.419 | AT12: 3663.5819 | AU12: 111990.9 | AV12: 89322.886 | AW12: 61920.349 | AX12: 38380.382 | AY12: 85723.94 | AZ12: 70851.969 | BA12: 86583.27 | BB12: 25789.484 | BC12: 11921.179 | BD12: 11921.179 | BE12: 11921.179 | BF12: 3755.1715 | BG12: 111430.95 | BH12: 88876.272 | BI12: 63468.358 | BJ12: 39339.891 | BK12: 87867.038
A13: BAT auto-comp. Ponta via FA (kWh) | B13: 107850.19 | C13: 1797.5031 | D13: 0 | E13: 0 | F13: 2596 | G13: 1200 | H13: 1200 | I13: 1200 | J13: 378 | K13: 0 | L13: 0 | M13: 6548.52 | N13: 4059 | O13: 5779.9575 | P13: 0 | Q13: 0 | R13: 2660.9 | S13: 1230 | T13: 1230 | U13: 1230 | V13: 387.45 | W13: 0 | X13: 0 | Y13: 6548.52 | Z13: 4059 | AA13: 5504.5371 | AB13: 0 | AC13: 0 | AD13: 2727.4225 | AE13: 1260.75 | AF13: 1260.75 | AG13: 1260.75 | AH13: 397.13625 | AI13: 0 | AJ13: 0 | AK13: 6712.233 | AL13: 4160.475 | AM13: 3997.8905 | AN13: 0 | AO13: 0 | AP13: 2795.6081 | AQ13: 1292.2687 | AR13: 1292.2687 | AS13: 1292.2687 | AT13: 407.06466 | AU13: 0 | AV13: 0 | AW13: 6880.0388 | AX13: 4264.4869 | AY13: 2461.799 | AZ13: 0 | BA13: 0 | BB13: 2865.4983 | BC13: 1324.5755 | BD13: 1324.5755 | BE13: 1324.5755 | BF13: 417.24127 | BG13: 0 | BH13: 0 | BI13: 7052.0398 | BJ13: 4371.099 | BK13: 895.48547
A14: ★ BAT surplus líquido → rateio (kWh) | B14: 2385420.1 | C14: 39757.002 | D14: 0 | E14: 0 | F14: 65422.586 | G14: 81647.523 | H14: 83120.923 | I14: 95194.723 | J14: 102576.35 | K14: 0 | L14: 0 | M14: 32772.781 | N14: 30092.923 | O14: 0 | P14: 0 | Q14: 0 | R14: 64265.67 | S14: 80855.709 | T14: 82321.742 | U14: 94335.173 | V14: 101942.64 | W14: 0 | X14: 0 | Y14: 32260.048 | Z14: 29726.217 | AA14: 0 | AB14: 0 | AC14: 0 | AD14: 63093.793 | AE14: 80058.265 | AF14: 81516.968 | AG14: 93470.332 | AH14: 101309.08 | AI14: 0 | AJ14: 0 | AK14: 30005.534 | AL14: 28280.139 | AM14: 0 | AN14: 0 | AO14: 0 | AP14: 61906.512 | AQ14: 79254.979 | AR14: 80706.388 | AS14: 92599.985 | AT14: 100675.59 | AU14: 0 | AV14: 0 | AW14: 27709.962 | AX14: 26808.855 | AY14: 0 | AZ14: 0 | BA14: 0 | BB14: 60703.372 | BC14: 78445.634 | BD14: 79889.786 | BE14: 91723.915 | BF14: 100042.1 | BG14: 0 | BH14: 0 | BI14: 25372.229 | BJ14: 25311.681 | BK14: 0
A15: BAT banco stranded — depleção por consumo próprio apenas
A16: BAT banco início mês (kWh) | B16: 582152.89 | C16: — | D16: 906739 | E16: 886285.67 | F16: 837626.06 | G16: 837626.06 | H16: 837626.06 | I16: 837626.06 | J16: 837626.06 | K16: 837626.06 | L16: 813017.73 | M16: 750949.09 | N16: 750949.09 | O16: 750949.09 | P16: 745511.16 | Q16: 722377.89 | R16: 669851.69 | S16: 669851.69 | T16: 669851.69 | U16: 669851.69 | V16: 669851.69 | W16: 669851.69 | X16: 644674.91 | Y16: 582152.89 | Z16: 582152.89 | AA16: 582152.89 | AB16: 576259.17 | AC16: 550389.8 | AD16: 493913.59 | AE16: 493913.59 | AF16: 493913.59 | AG16: 493913.59 | AH16: 493913.59 | AI16: 493913.59 | AJ16: 464713.82 | AK16: 397922.06 | AL16: 397922.06 | AM16: 397922.06 | AN16: 389159.91 | AO16: 360496.84 | AP16: 299985.05 | AQ16: 299985.05 | AR16: 299985.05 | AS16: 299985.05 | AT16: 299985.05 | AU16: 299985.05 | AV16: 266678.68 | AW16: 195523.97 | AX16: 195523.97 | AY16: 195523.97 | AZ16: 183835.3 | BA16: 152319.41 | BB16: 87684.274 | BC16: 87684.274 | BD16: 87684.274 | BE16: 87684.274 | BF16: 87684.274 | BG16: 87684.274 | BH16: 50185.511 | BI16: 0 | BJ16: 0 | BK16: 0
A17: BAT banco draw (kWh) | B17: 906739 | C17: 15112.317 | D17: 20453.327 | E17: 48659.609 | F17: 0 | G17: 0 | H17: 0 | I17: 0 | J17: 0 | K17: 24608.336 | L17: 62068.64 | M17: 0 | N17: 0 | O17: 5437.9309 | P17: 23133.268 | Q17: 52526.204 | R17: 0 | S17: 0 | T17: 0 | U17: 0 | V17: 0 | W17: 25176.774 | X17: 62522.021 | Y17: 0 | Z17: 0 | AA17: 5893.7235 | AB17: 25869.363 | AC17: 56476.212 | AD17: 0 | AE17: 0 | AF17: 0 | AG17: 0 | AH17: 0 | AI17: 29199.771 | AJ17: 66791.758 | AK17: 0 | AL17: 0 | AM17: 8762.1483 | AN17: 28663.072 | AO17: 60511.787 | AP17: 0 | AQ17: 0 | AR17: 0 | AS17: 0 | AT17: 0 | AU17: 33306.376 | AV17: 71154.704 | AW17: 0 | AX17: 0 | AY17: 11688.678 | AZ17: 31515.89 | BA17: 64635.132 | BB17: 0 | BC17: 0 | BD17: 0 | BE17: 0 | BF17: 0 | BG17: 37498.762 | BH17: 50185.511 | BI17: 0 | BJ17: 0 | BK17: 0
A18: BAT banco fim mês (kWh) | B18: 576259.17 | C18: — | D18: 886285.67 | E18: 837626.06 | F18: 837626.06 | G18: 837626.06 | H18: 837626.06 | I18: 837626.06 | J18: 837626.06 | K18: 813017.73 | L18: 750949.09 | M18: 750949.09 | N18: 750949.09 | O18: 745511.16 | P18: 722377.89 | Q18: 669851.69 | R18: 669851.69 | S18: 669851.69 | T18: 669851.69 | U18: 669851.69 | V18: 669851.69 | W18: 644674.91 | X18: 582152.89 | Y18: 582152.89 | Z18: 582152.89 | AA18: 576259.17 | AB18: 550389.8 | AC18: 493913.59 | AD18: 493913.59 | AE18: 493913.59 | AF18: 493913.59 | AG18: 493913.59 | AH18: 493913.59 | AI18: 464713.82 | AJ18: 397922.06 | AK18: 397922.06 | AL18: 397922.06 | AM18: 389159.91 | AN18: 360496.84 | AO18: 299985.05 | AP18: 299985.05 | AQ18: 299985.05 | AR18: 299985.05 | AS18: 299985.05 | AT18: 299985.05 | AU18: 266678.68 | AV18: 195523.97 | AW18: 195523.97 | AX18: 195523.97 | AY18: 183835.3 | AZ18: 152319.41 | BA18: 87684.274 | BB18: 87684.274 | BC18: 87684.274 | BD18: 87684.274 | BE18: 87684.274 | BF18: 87684.274 | BG18: 50185.511 | BH18: 0 | BI18: 0 | BJ18: 0 | BK18: 0
A19: BAT créditos → NHS (kWh, T+1) | B19: 1192710.1 | C19: 19878.501 | D19: 0 | E19: 0 | F19: 0 | G19: 32711.293 | H19: 40823.762 | I19: 41560.462 | J19: 47597.362 | K19: 51288.174 | L19: 0 | M19: 0 | N19: 16386.391 | O19: 15046.461 | P19: 0 | Q19: 0 | R19: 0 | S19: 32132.835 | T19: 40427.855 | U19: 41160.871 | V19: 47167.587 | W19: 50971.32 | X19: 0 | Y19: 0 | Z19: 16130.024 | AA19: 14863.108 | AB19: 0 | AC19: 0 | AD19: 0 | AE19: 31546.897 | AF19: 40029.132 | AG19: 40758.484 | AH19: 46735.166 | AI19: 50654.54 | AJ19: 0 | AK19: 0 | AL19: 15002.767 | AM19: 14140.07 | AN19: 0 | AO19: 0 | AP19: 0 | AQ19: 30953.256 | AR19: 39627.489 | AS19: 40353.194 | AT19: 46299.993 | AU19: 50337.796 | AV19: 0 | AW19: 0 | AX19: 13854.981 | AY19: 13404.428 | AZ19: 0 | BA19: 0 | BB19: 0 | BC19: 30351.686 | BD19: 39222.817 | BE19: 39944.893 | BF19: 45861.958 | BG19: 50021.048 | BH19: 0 | BI19: 0 | BJ19: 12686.114 | BK19: 12655.84
A20: BAT créditos → AMD (kWh, T+1) | B20: 1192710.1 | C20: 19878.501 | D20: 0 | E20: 0 | F20: 0 | G20: 32711.293 | H20: 40823.762 | I20: 41560.462 | J20: 47597.362 | K20: 51288.174 | L20: 0 | M20: 0 | N20: 16386.391 | O20: 15046.461 | P20: 0 | Q20: 0 | R20: 0 | S20: 32132.835 | T20: 40427.855 | U20: 41160.871 | V20: 47167.587 | W20: 50971.32 | X20: 0 | Y20: 0 | Z20: 16130.024 | AA20: 14863.108 | AB20: 0 | AC20: 0 | AD20: 0 | AE20: 31546.897 | AF20: 40029.132 | AG20: 40758.484 | AH20: 46735.166 | AI20: 50654.54 | AJ20: 0 | AK20: 0 | AL20: 15002.767 | AM20: 14140.07 | AN20: 0 | AO20: 0 | AP20: 0 | AQ20: 30953.256 | AR20: 39627.489 | AS20: 40353.194 | AT20: 46299.993 | AU20: 50337.796 | AV20: 0 | AW20: 0 | AX20: 13854.981 | AY20: 13404.428 | AZ20: 0 | BA20: 0 | BB20: 0 | BC20: 30351.686 | BD20: 39222.817 | BE20: 39944.893 | BF20: 45861.958 | BG20: 50021.048 | BH20: 0 | BI20: 0 | BJ20: 12686.114 | BK20: 12655.84
A21: NHS — N. Horizonte do Sul (A4V)
A22: Consumo FP (kWh) | B22: 8849247.7 | C22: 147487.46 | D22: 108694.9 | E22: 328938.1 | F22: 190977.6 | G22: 126478.8 | H22: 28215 | I22: 42209.6 | J22: 42209.6 | K22: 72539.147 | L22: 249812.69 | M22: 340170.95 | N22: 105347.76 | O22: 64384.555 | P22: 111412.27 | Q22: 337161.55 | R22: 195752.04 | S22: 129640.77 | T22: 28920.375 | U22: 43264.84 | V22: 43264.84 | W22: 72539.147 | X22: 249812.69 | Y22: 340170.95 | Z22: 105347.76 | AA22: 64384.555 | AB22: 114197.58 | AC22: 345590.59 | AD22: 200645.84 | AE22: 132881.79 | AF22: 29643.384 | AG22: 44346.461 | AH22: 44346.461 | AI22: 74352.626 | AJ22: 256058.01 | AK22: 348675.23 | AL22: 107981.45 | AM22: 65994.169 | AN22: 117052.52 | AO22: 354230.36 | AP22: 205661.99 | AQ22: 136203.83 | AR22: 30384.469 | AS22: 45455.123 | AT22: 45455.123 | AU22: 76211.442 | AV22: 262459.46 | AW22: 357392.11 | AX22: 110680.99 | AY22: 67644.023 | AZ22: 119978.83 | BA22: 363086.11 | BB22: 210803.54 | BC22: 139608.93 | BD22: 31144.081 | BE22: 46591.501 | BF22: 46591.501 | BG22: 78116.728 | BH22: 269020.95 | BI22: 366326.91 | BJ22: 113448.01 | BK22: 69335.124
A23: Consumo Ponta (kWh) [via FA] | B23: 983250.33 | C23: 16387.506 | D23: 12077.2 | E23: 36548.7 | F23: 21219.7 | G23: 14053.2 | H23: 3135 | I23: 4690 | J23: 4690 | K23: 8059.8825 | L23: 27757 | M23: 37796.772 | N23: 11705.295 | O23: 7153.885 | P23: 12379.13 | Q23: 37462.417 | R23: 21750.192 | S23: 14404.53 | T23: 3213.375 | U23: 4807.25 | V23: 4807.25 | W23: 8059.8825 | X23: 27757 | Y23: 37796.772 | Z23: 11705.295 | AA23: 7153.885 | AB23: 12688.608 | AC23: 38398.978 | AD23: 22293.947 | AE23: 14764.643 | AF23: 3293.7094 | AG23: 4927.4312 | AH23: 4927.4312 | AI23: 8261.3796 | AJ23: 28450.925 | AK23: 38741.692 | AL23: 11997.927 | AM23: 7332.7321 | AN23: 13005.823 | AO23: 39358.952 | AP23: 22851.296 | AQ23: 15133.759 | AR23: 3376.0521 | AS23: 5050.617 | AT23: 5050.617 | AU23: 8467.9141 | AV23: 29162.198 | AW23: 39710.234 | AX23: 12297.876 | AY23: 7516.0504 | AZ23: 13330.969 | BA23: 40342.926 | BB23: 23422.578 | BC23: 15512.103 | BD23: 3460.4534 | BE23: 5176.8825 | BF23: 5176.8825 | BG23: 8679.6119 | BH23: 29891.253 | BI23: 40702.99 | BJ23: 12605.322 | BK23: 7703.9517
A24: Geração própria (kWh) | B24: 4634513.1 | C24: 77241.885 | D24: 60380.6 | E24: 76551.2 | F24: 79815.6 | G24: 78203 | H24: 73160.1 | I24: 91030.5 | J24: 88631.7 | K24: 83044.59 | L24: 75743.778 | M24: 89408.909 | N24: 62411.773 | O24: 77836.363 | P24: 60078.697 | Q24: 76168.444 | R24: 79416.522 | S24: 77811.985 | T24: 72794.299 | U24: 90575.348 | V24: 88188.541 | W24: 82629.368 | X24: 75365.059 | Y24: 88961.864 | Z24: 62099.714 | AA24: 77447.181 | AB24: 59778.304 | AC24: 75787.602 | AD24: 79019.439 | AE24: 77422.925 | AF24: 72430.328 | AG24: 90122.471 | AH24: 87747.599 | AI24: 82216.221 | AJ24: 74988.234 | AK24: 88517.055 | AL24: 61789.216 | AM24: 77059.945 | AN24: 59479.412 | AO24: 75408.664 | AP24: 78624.342 | AQ24: 77035.81 | AR24: 72068.176 | AS24: 89671.858 | AT24: 87308.861 | AU24: 81805.14 | AV24: 74613.293 | AW24: 88074.47 | AX24: 61480.269 | AY24: 76674.645 | AZ24: 59182.015 | BA24: 75031.62 | BB24: 78231.22 | BC24: 76650.631 | BD24: 71707.835 | BE24: 89223.499 | BF24: 86872.316 | BG24: 81396.114 | BH24: 74240.226 | BI24: 87634.098 | BJ24: 61172.868 | BK24: 76291.272
A25: Auto-comp. FP (kWh) | B25: 3884122.7 | C25: 64735.379 | D25: 60380.6 | E25: 76551.2 | F25: 79815.6 | G25: 78203 | H25: 28215 | I25: 42209.6 | J25: 42209.6 | K25: 72539.147 | L25: 75743.778 | M25: 89408.909 | N25: 62411.773 | O25: 64384.555 | P25: 60078.697 | Q25: 76168.444 | R25: 79416.522 | S25: 77811.985 | T25: 28920.375 | U25: 43264.84 | V25: 43264.84 | W25: 72539.147 | X25: 75365.059 | Y25: 88961.864 | Z25: 62099.714 | AA25: 64384.555 | AB25: 59778.304 | AC25: 75787.602 | AD25: 79019.439 | AE25: 77422.925 | AF25: 29643.384 | AG25: 44346.461 | AH25: 44346.461 | AI25: 74352.626 | AJ25: 74988.234 | AK25: 88517.055 | AL25: 61789.216 | AM25: 65994.169 | AN25: 59479.412 | AO25: 75408.664 | AP25: 78624.342 | AQ25: 77035.81 | AR25: 30384.469 | AS25: 45455.123 | AT25: 45455.123 | AU25: 76211.442 | AV25: 74613.293 | AW25: 88074.47 | AX25: 61480.269 | AY25: 67644.023 | AZ25: 59182.015 | BA25: 75031.62 | BB25: 78231.22 | BC25: 76650.631 | BD25: 31144.081 | BE25: 46591.501 | BF25: 46591.501 | BG25: 78116.728 | BH25: 74240.226 | BI25: 87634.098 | BJ25: 61172.868 | BK25: 69335.124
A26: Auto-comp. Ponta via FA (kWh) | B26: 118996.39 | C26: 1983.2731 | D26: 0 | E26: 0 | F26: 0 | G26: 0 | H26: 3135 | I26: 4690 | J26: 4690 | K26: 6348.093 | L26: 0 | M26: 0 | N26: 0 | O26: 7153.885 | P26: 0 | Q26: 0 | R26: 0 | S26: 0 | T26: 3213.375 | U26: 4807.25 | V26: 4807.25 | W26: 6097.1875 | X26: 0 | Y26: 0 | Z26: 0 | AA26: 7153.885 | AB26: 0 | AC26: 0 | AD26: 0 | AE26: 0 | AF26: 3293.7094 | AG26: 4927.4312 | AH26: 4927.4312 | AI26: 4751.7111 | AJ26: 0 | AK26: 0 | AL26: 0 | AM26: 6686.6838 | AN26: 0 | AO26: 0 | AP26: 0 | AQ26: 0 | AR26: 3376.0521 | AS26: 5050.617 | AT26: 5050.617 | AU26: 3380.0872 | AV26: 0 | AW26: 0 | AX26: 0 | AY26: 5456.9073 | AZ26: 0 | BA26: 0 | BB26: 0 | BC26: 0 | BD26: 3460.4534 | BE26: 5176.8825 | BF26: 5176.8825 | BG26: 1981.6249 | BH26: 0 | BI26: 0 | BJ26: 0 | BK26: 4203.3711
A27: HCS03 créditos recebidos (kWh) | B27: 4146923.6 | C27: 69115.393 | D27: 91504.62 | E27: 96316.38 | F27: 115622.46 | G27: 108493.38 | H27: 78229.224 | I27: 75640.224 | J27: 71824.038 | K27: 73747.303 | L27: 65715.163 | M27: 75375.369 | N27: 97520.917 | O27: 91268.035 | P27: 82830.652 | Q27: 87186.292 | R27: 104662.3 | S27: 98209.001 | T27: 38964.136 | U27: 37674.616 | V27: 35773.864 | W27: 36916.379 | X27: 32895.655 | Y27: 37731.355 | Z27: 37648.826 | AA27: 35234.844 | AB27: 58197.292 | AC27: 61257.59 | AD27: 73536.331 | AE27: 69002.209 | AF27: 70912.548 | AG27: 68565.694 | AH27: 64172.612 | AI27: 66222.101 | AJ27: 59009.564 | AK27: 67684.039 | AL27: 67535.995 | AM27: 63205.697 | AN27: 57698.669 | AO27: 60732.746 | AP27: 72906.286 | AQ27: 68411.011 | AR27: 70304.983 | AS27: 67978.236 | AT27: 63619.461 | AU27: 65651.284 | AV27: 58500.917 | AW27: 67100.621 | AX27: 66953.853 | AY27: 62660.881 | AZ27: 70802.642 | BA27: 74525.791 | BB27: 89464.069 | BC27: 83947.87 | BD27: 86271.983 | BE27: 83416.807 | BF27: 62825.516 | BG27: 64831.983 | BH27: 57770.85 | BI27: 66263.232 | BJ27: 66118.296 | BK27: 61878.898
A28: BAT créditos → NHS (kWh) | B28: 1192710.1 | C28: 19878.501 | D28: 0 | E28: 0 | F28: 0 | G28: 32711.293 | H28: 40823.762 | I28: 41560.462 | J28: 47597.362 | K28: 51288.174 | L28: 0 | M28: 0 | N28: 16386.391 | O28: 15046.461 | P28: 0 | Q28: 0 | R28: 0 | S28: 32132.835 | T28: 40427.855 | U28: 41160.871 | V28: 47167.587 | W28: 50971.32 | X28: 0 | Y28: 0 | Z28: 16130.024 | AA28: 14863.108 | AB28: 0 | AC28: 0 | AD28: 0 | AE28: 31546.897 | AF28: 40029.132 | AG28: 40758.484 | AH28: 46735.166 | AI28: 50654.54 | AJ28: 0 | AK28: 0 | AL28: 15002.767 | AM28: 14140.07 | AN28: 0 | AO28: 0 | AP28: 0 | AQ28: 30953.256 | AR28: 39627.489 | AS28: 40353.194 | AT28: 46299.993 | AU28: 50337.796 | AV28: 0 | AW28: 0 | AX28: 13854.981 | AY28: 13404.428 | AZ28: 0 | BA28: 0 | BB28: 0 | BC28: 30351.686 | BD28: 39222.817 | BE28: 39944.893 | BF28: 45861.958 | BG28: 50021.048 | BH28: 0 | BI28: 0 | BJ28: 12686.114 | BK28: 12655.84
A29: Banco início mês COM Helexia (kWh) | B29: 262414.01 | C29: — | D29: 148516 | E29: 171719.79 | F29: 0 | G29: 4460.46 | H29: 92928.873 | I29: 256926.96 | J29: 422948.54 | K29: 588792.04 | L29: 721500.13 | M29: 567211.39 | N29: 329274.93 | O29: 380875.19 | P29: 500641.49 | Q29: 511652.38 | R29: 275849.1 | S29: 228181.55 | T29: 282856.58 | U29: 406122.49 | V29: 532268.49 | W29: 660133.64 | X29: 750898.78 | Y29: 563411.81 | Z29: 287384.29 | AA29: 262414.01 | AB29: 325574.59 | AC29: 308354.26 | AD29: 36262.494 | AE29: 0 | AF29: 45090.241 | AG29: 198818.87 | AH29: 353919.05 | AI29: 508227.97 | AJ29: 627160.06 | AK29: 458016.49 | AL29: 201428.83 | AM29: 217920.02 | AN29: 305262.41 | AO29: 283864.67 | AP29: 640.6952 | AQ29: 0 | AR29: 40196.243 | AS29: 191812.42 | AT29: 344360.59 | AU29: 496133.78 | AV29: 609296.73 | AW29: 431691.03 | AX29: 163757.65 | AY29: 175014.04 | AZ29: 256702.3 | BA29: 244646.74 | BB29: 0 | BC29: 0 | BD29: 51341.257 | BE29: 217399.81 | BF29: 383393.51 | BG29: 532361.8 | BH29: 639409.74 | BI29: 452932.91 | BJ29: 173144.05 | BK29: 178812.8
A30: Bank draw COM Helexia (kWh) | B30: 3785853.1 | C30: 63097.552 | D30: 19986.528 | E30: 171719.79 | F30: 0 | G30: 4460.46 | H30: 0 | I30: 0 | J30: 0 | K30: 2832.836 | L30: 154288.74 | M30: 237936.46 | N30: 19371.063 | O30: 0 | P30: 20486.191 | Q30: 235803.28 | R30: 47667.559 | S30: 23838.02 | T30: 0 | U30: 0 | V30: 0 | W30: 7212.7806 | X30: 187486.97 | Y30: 276027.52 | Z30: 41100.305 | AA30: 0 | AB30: 20998.345 | AC30: 272091.77 | AD30: 36262.494 | AE30: 0 | AF30: 0 | AG30: 0 | AH30: 0 | AI30: 5808.1415 | AJ30: 169143.58 | AK30: 256587.66 | AL30: 19855.339 | AM30: 1069.1438 | AN30: 21523.304 | AO30: 283223.98 | AP30: 640.6952 | AQ30: 0 | AR30: 0 | AS30: 0 | AT30: 0 | AU30: 8419.8316 | AV30: 177605.7 | AW30: 267933.38 | AX30: 20351.723 | AY30: 3407.6707 | AZ30: 22061.387 | BA30: 244646.74 | BB30: 0 | BC30: 0 | BD30: 0 | BE30: 0 | BF30: 0 | BG30: 11084.482 | BH30: 186476.83 | BI30: 279788.85 | BJ30: 20860.516 | BK30: 5793.1019
A31: ★ Banco fim mês COM Helexia (kWh) | B31: 325574.59 | C31: — | D31: 171719.79 | E31: 0 | F31: 4460.46 | G31: 92928.873 | H31: 256926.96 | I31: 422948.54 | J31: 588792.04 | K31: 721500.13 | L31: 567211.39 | M31: 329274.93 | N31: 380875.19 | O31: 500641.49 | P31: 511652.38 | Q31: 275849.1 | R31: 228181.55 | S31: 282856.58 | T31: 406122.49 | U31: 532268.49 | V31: 660133.64 | W31: 750898.78 | X31: 563411.81 | Y31: 287384.29 | Z31: 262414.01 | AA31: 325574.59 | AB31: 308354.26 | AC31: 36262.494 | AD31: 0 | AE31: 45090.241 | AF31: 198818.87 | AG31: 353919.05 | AH31: 508227.97 | AI31: 627160.06 | AJ31: 458016.49 | AK31: 201428.83 | AL31: 217920.02 | AM31: 305262.41 | AN31: 283864.67 | AO31: 640.6952 | AP31: 0 | AQ31: 40196.243 | AR31: 191812.42 | AS31: 344360.59 | AT31: 496133.78 | AU31: 609296.73 | AV31: 431691.03 | AW31: 163757.65 | AX31: 175014.04 | AY31: 256702.3 | AZ31: 244646.74 | BA31: 0 | BB31: 0 | BC31: 51341.257 | BD31: 217399.81 | BE31: 383393.51 | BF31: 532361.8 | BG31: 639409.74 | BH31: 452932.91 | BI31: 173144.05 | BJ31: 178812.8 | BK31: 254510.59
A32: Banco início mês SEM Helexia (kWh) | B32: 16130.024 | C32: — | D32: 148516 | E32: 80215.172 | F32: 0 | G32: 0 | H32: 32711.293 | I32: 118480.15 | J32: 208861.52 | K32: 302880.98 | L32: 364674.6 | M32: 144670.69 | N32: 0 | O32: 16386.391 | P32: 44884.66 | Q32: 0 | R32: 0 | S32: 0 | T32: 32132.835 | U32: 116434.61 | V32: 204905.99 | W32: 296997.28 | X32: 358058.82 | Y32: 137676.2 | Z32: 0 | AA32: 16130.024 | AB32: 44055.758 | AC32: 0 | AD32: 0 | AE32: 0 | AF32: 31546.897 | AG32: 114362.97 | AH32: 200897.47 | AI32: 291033.77 | AJ32: 349551.9 | AK32: 121398.77 | AL32: 0 | AM32: 15002.767 | AN32: 40208.612 | AO32: 0 | AP32: 0 | AQ32: 0 | AR32: 30953.256 | AS32: 112264.45 | AT32: 196834.38 | AU32: 284988.11 | AV32: 338093.47 | AW32: 101986.86 | AX32: 0 | AY32: 13854.981 | AZ32: 36290.03 | BA32: 0 | BB32: 0 | BC32: 0 | BD32: 30351.686 | BE32: 110138.26 | BF32: 192715.15 | BG32: 278857.92 | BH32: 324353.26 | BI32: 80105.583 | BJ32: 0 | BK32: 12686.114
A33: Bank draw SEM Helexia (kWh) — gen+BAT, no CS3 | B33: 2059318.3 | C33: 34321.972 | D33: 68300.828 | E33: 80215.172 | F33: 0 | G33: 0 | H33: 0 | I33: 0 | J33: 0 | K33: 0 | L33: 220003.9 | M33: 144670.69 | N33: 0 | O33: 0 | P33: 44884.66 | Q33: 0 | R33: 0 | S33: 0 | T33: 0 | U33: 0 | V33: 0 | W33: 0 | X33: 220382.62 | Y33: 137676.2 | Z33: 0 | AA33: 0 | AB33: 44055.758 | AC33: 0 | AD33: 0 | AE33: 0 | AF33: 0 | AG33: 0 | AH33: 0 | AI33: 0 | AJ33: 228153.14 | AK33: 121398.77 | AL33: 0 | AM33: 0 | AN33: 40208.612 | AO33: 0 | AP33: 0 | AQ33: 0 | AR33: 0 | AS33: 0 | AT33: 0 | AU33: 2826.1339 | AV33: 236106.61 | AW33: 101986.86 | AX33: 0 | AY33: 0 | AZ33: 36290.03 | BA33: 0 | BB33: 0 | BC33: 0 | BD33: 0 | BE33: 0 | BF33: 0 | BG33: 7805.0956 | BH33: 244247.68 | BI33: 80105.583 | BJ33: 0 | BK33: 0
A34: Banco fim mês SEM Helexia (kWh) — gen+BAT, no CS3 | B34: 44055.758 | C34: — | D34: 80215.172 | E34: 0 | F34: 0 | G34: 32711.293 | H34: 118480.15 | I34: 208861.52 | J34: 302880.98 | K34: 364674.6 | L34: 144670.69 | M34: 0 | N34: 16386.391 | O34: 44884.66 | P34: 0 | Q34: 0 | R34: 0 | S34: 32132.835 | T34: 116434.61 | U34: 204905.99 | V34: 296997.28 | W34: 358058.82 | X34: 137676.2 | Y34: 0 | Z34: 16130.024 | AA34: 44055.758 | AB34: 0 | AC34: 0 | AD34: 0 | AE34: 31546.897 | AF34: 114362.97 | AG34: 200897.47 | AH34: 291033.77 | AI34: 349551.9 | AJ34: 121398.77 | AK34: 0 | AL34: 15002.767 | AM34: 40208.612 | AN34: 0 | AO34: 0 | AP34: 0 | AQ34: 30953.256 | AR34: 112264.45 | AS34: 196834.38 | AT34: 284988.11 | AU34: 338093.47 | AV34: 101986.86 | AW34: 0 | AX34: 13854.981 | AY34: 36290.03 | AZ34: 0 | BA34: 0 | BB34: 0 | BC34: 30351.686 | BD34: 110138.26 | BE34: 192715.15 | BF34: 278857.92 | BG34: 324353.26 | BH34: 80105.583 | BI34: 0 | BJ34: 12686.114 | BK34: 32298.103
A35: Custo SEM Helexia (R$) — só gen própria, sem HCS03/BAT/banco | B35: 3035458.3 | C35: 50590.972 | D35: 0 | E35: 199280.04 | F35: 121596.58 | G35: 0 | H35: 0 | I35: 0 | J35: 0 | K35: 0 | L35: 0 | M35: 168200.38 | N35: 0 | O35: 0 | P35: 40190.639 | Q35: 248757.85 | R35: 125897.11 | S35: 0 | T35: 0 | U35: 0 | V35: 0 | W35: 0 | X35: 0 | Y35: 172118.13 | Z35: 0 | AA35: 0 | AB35: 43171.45 | AC35: 256179.81 | AD35: 130298.86 | AE35: 0 | AF35: 0 | AG35: 0 | AH35: 0 | AI35: 0 | AJ35: 0 | AK35: 188207.83 | AL35: 0 | AM35: 0 | AN35: 47800.146 | AO35: 263781.31 | AP35: 134804.37 | AQ35: 0 | AR35: 0 | AS35: 0 | AT35: 0 | AU35: 0 | AV35: 0 | AW35: 206128.7 | AX35: 0 | AY35: 0 | AZ35: 52526.813 | BA35: 271566.85 | BB35: 139416.28 | BC35: 0 | BD35: 0 | BE35: 0 | BF35: 0 | BG35: 0 | BH35: 0 | BI35: 225535.17 | BJ35: 0 | BK35: 0
A36: Custo COM Helexia — rede remanescente (R$) | B36: 461336.25 | C36: 7688.9375 | D36: 0 | E36: 80528.774 | F36: 0 | G36: 0 | H36: 0 | I36: 0 | J36: 0 | K36: 0 | L36: 0 | M36: 0 | N36: 0 | O36: 0 | P36: 0 | Q36: 0 | R36: 0 | S36: 0 | T36: 0 | U36: 0 | V36: 0 | W36: 0 | X36: 0 | Y36: 0 | Z36: 0 | AA36: 0 | AB36: 0 | AC36: 0 | AD36: 72492.947 | AE36: 0 | AF36: 0 | AG36: 0 | AH36: 0 | AI36: 0 | AJ36: 0 | AK36: 0 | AL36: 0 | AM36: 0 | AN36: 0 | AO36: 0 | AP36: 96084.011 | AQ36: 0 | AR36: 0 | AS36: 0 | AT36: 0 | AU36: 0 | AV36: 0 | AW36: 0 | AX36: 0 | AY36: 0 | AZ36: 0 | BA36: 119914.48 | BB36: 92316.036 | BC36: 0 | BD36: 0 | BE36: 0 | BF36: 0 | BG36: 0 | BH36: 0 | BI36: 0 | BJ36: 0 | BK36: 0
A37: ★ Economia mensal (R$) | B37: 2574122.1 | C37: 42902.035 | D37: 0 | E37: 118751.27 | F37: 121596.58 | G37: 0 | H37: 0 | I37: 0 | J37: 0 | K37: 0 | L37: 0 | M37: 168200.38 | N37: 0 | O37: 0 | P37: 40190.639 | Q37: 248757.85 | R37: 125897.11 | S37: 0 | T37: 0 | U37: 0 | V37: 0 | W37: 0 | X37: 0 | Y37: 172118.13 | Z37: 0 | AA37: 0 | AB37: 43171.45 | AC37: 256179.81 | AD37: 57805.909 | AE37: 0 | AF37: 0 | AG37: 0 | AH37: 0 | AI37: 0 | AJ37: 0 | AK37: 188207.83 | AL37: 0 | AM37: 0 | AN37: 47800.146 | AO37: 263781.31 | AP37: 38720.361 | AQ37: 0 | AR37: 0 | AS37: 0 | AT37: 0 | AU37: 0 | AV37: 0 | AW37: 206128.7 | AX37: 0 | AY37: 0 | AZ37: 52526.813 | BA37: 151652.37 | BB37: 47100.248 | BC37: 0 | BD37: 0 | BE37: 0 | BF37: 0 | BG37: 0 | BH37: 0 | BI37: 225535.17 | BJ37: 0 | BK37: 0
A39: AMD — Amandina (A3A)
A40: Consumo FP (kWh) | B40: 6692611.4 | C40: 111543.52 | D40: 182444.7 | E40: 234799.2 | F40: 134799.3 | G40: 18637.2 | H40: 24382.8 | I40: 20225.7 | J40: 17142.3 | K40: 75822.735 | L40: 214709.01 | M40: 177591.7 | N40: 80409.61 | O40: 105195.24 | P40: 187005.82 | Q40: 240669.18 | R40: 138169.28 | S40: 19103.13 | T40: 24992.37 | U40: 20731.342 | V40: 17570.857 | W40: 75822.735 | X40: 214709.01 | Y40: 177591.7 | Z40: 80409.61 | AA40: 105195.24 | AB40: 191680.96 | AC40: 246685.91 | AD40: 141623.51 | AE40: 19580.708 | AF40: 25617.179 | AG40: 21249.626 | AH40: 18010.129 | AI40: 77718.303 | AJ40: 220076.73 | AK40: 182031.5 | AL40: 82419.85 | AM40: 107825.12 | AN40: 196472.99 | AO40: 252853.06 | AP40: 145164.1 | AQ40: 20070.226 | AR40: 26257.609 | AS40: 21780.867 | AT40: 18460.382 | AU40: 79661.261 | AV40: 225578.65 | AW40: 186582.29 | AX40: 84480.347 | AY40: 110520.75 | AZ40: 201384.81 | BA40: 259174.38 | BB40: 148793.2 | BC40: 20571.982 | BD40: 26914.049 | BE40: 22325.388 | BF40: 18921.892 | BG40: 81652.792 | BH40: 231218.11 | BI40: 191246.84 | BJ40: 86592.355 | BK40: 113283.77
A41: Consumo Ponta (kWh) [via FA] | B41: 743623.55 | C41: 12393.726 | D41: 20271.6 | E41: 26088.8 | F41: 14977.7 | G41: 2070.8 | H41: 2709.2 | I41: 2247.3 | J41: 1904.7 | K41: 8424.7825 | L41: 23856.567 | M41: 19732.377 | N41: 8934.4125 | O41: 11688.382 | P41: 20778.39 | Q41: 26741.02 | R41: 15352.142 | S41: 2122.57 | T41: 2776.93 | U41: 2303.4825 | V41: 1952.3175 | W41: 8424.7825 | X41: 23856.567 | Y41: 19732.377 | Z41: 8934.4125 | AA41: 11688.382 | AB41: 21297.85 | AC41: 27409.545 | AD41: 15735.946 | AE41: 2175.6343 | AF41: 2846.3532 | AG41: 2361.0696 | AH41: 2001.1254 | AI41: 8635.4021 | AJ41: 24452.982 | AK41: 20225.687 | AL41: 9157.7728 | AM41: 11980.592 | AN41: 21830.296 | AO41: 28094.784 | AP41: 16129.345 | AQ41: 2230.0251 | AR41: 2917.5121 | AS41: 2420.0963 | AT41: 2051.1536 | AU41: 8851.2871 | AV41: 25064.306 | AW41: 20731.329 | AX41: 9386.7171 | AY41: 12280.107 | AZ41: 22376.053 | BA41: 28797.154 | BB41: 16532.578 | BC41: 2285.7757 | BD41: 2990.4499 | BE41: 2480.5987 | BF41: 2102.4324 | BG41: 9072.5693 | BH41: 25690.914 | BI41: 21249.612 | BJ41: 9621.3851 | BK41: 12587.11
A42: Geração própria (kWh) | B42: 4482675.2 | C42: 74711.253 | D42: 57829.52 | E42: 70669.44 | F42: 74466.16 | G42: 75546.72 | H42: 76725.44 | I42: 86384.48 | J42: 85283.12 | K42: 90950.164 | L42: 72540.992 | M42: 82037.272 | N42: 58672.921 | O42: 72926.814 | P42: 57540.372 | Q42: 70316.093 | R42: 74093.829 | S42: 75168.986 | T42: 76341.813 | U42: 85952.558 | V42: 84856.704 | W42: 90950.164 | X42: 72540.992 | Y42: 82037.272 | Z42: 58672.921 | AA42: 72926.814 | AB42: 57252.671 | AC42: 69964.512 | AD42: 73723.36 | AE42: 74793.141 | AF42: 75960.104 | AG42: 85522.795 | AH42: 84432.421 | AI42: 90495.413 | AJ42: 72178.287 | AK42: 81627.086 | AL42: 58379.557 | AM42: 72562.18 | AN42: 56966.407 | AO42: 69614.69 | AP42: 73354.743 | AQ42: 74419.176 | AR42: 75580.303 | AS42: 85095.181 | AT42: 84010.259 | AU42: 90042.936 | AV42: 71817.396 | AW42: 81218.951 | AX42: 58087.659 | AY42: 72199.369 | AZ42: 56681.575 | BA42: 69266.616 | BB42: 72987.97 | BC42: 74047.08 | BD42: 75202.402 | BE42: 84669.705 | BF42: 83590.207 | BG42: 89592.721 | BH42: 71458.309 | BI42: 80812.856 | BJ42: 57797.221 | BK42: 71838.372
A43: Auto-comp. FP (kWh) | B43: 3240284.8 | C43: 54004.746 | D43: 57829.52 | E43: 70669.44 | F43: 74466.16 | G43: 18637.2 | H43: 24382.8 | I43: 20225.7 | J43: 17142.3 | K43: 75822.735 | L43: 72540.992 | M43: 82037.272 | N43: 58672.921 | O43: 72926.814 | P43: 57540.372 | Q43: 70316.093 | R43: 74093.829 | S43: 19103.13 | T43: 24992.37 | U43: 20731.342 | V43: 17570.857 | W43: 75822.735 | X43: 72540.992 | Y43: 82037.272 | Z43: 58672.921 | AA43: 72926.814 | AB43: 57252.671 | AC43: 69964.512 | AD43: 73723.36 | AE43: 19580.708 | AF43: 25617.179 | AG43: 21249.626 | AH43: 18010.129 | AI43: 77718.303 | AJ43: 72178.287 | AK43: 81627.086 | AL43: 58379.557 | AM43: 72562.18 | AN43: 56966.407 | AO43: 69614.69 | AP43: 73354.743 | AQ43: 20070.226 | AR43: 26257.609 | AS43: 21780.867 | AT43: 18460.382 | AU43: 79661.261 | AV43: 71817.396 | AW43: 81218.951 | AX43: 58087.659 | AY43: 72199.369 | AZ43: 56681.575 | BA43: 69266.616 | BB43: 72987.97 | BC43: 20571.982 | BD43: 26914.049 | BE43: 22325.388 | BF43: 18921.892 | BG43: 81652.792 | BH43: 71458.309 | BI43: 80812.856 | BJ43: 57797.221 | BK43: 71838.372
A44: Auto-comp. Ponta via FA (kWh) | B44: 82591.019 | C44: 1376.517 | D44: 0 | E44: 0 | F44: 0 | G44: 2070.8 | H44: 2709.2 | I44: 2247.3 | J44: 1904.7 | K44: 8424.7825 | L44: 0 | M44: 0 | N44: 0 | O44: 0 | P44: 0 | Q44: 0 | R44: 0 | S44: 2122.57 | T44: 2776.93 | U44: 2303.4825 | V44: 1952.3175 | W44: 8424.7825 | X44: 0 | Y44: 0 | Z44: 0 | AA44: 0 | AB44: 0 | AC44: 0 | AD44: 0 | AE44: 2175.6343 | AF44: 2846.3532 | AG44: 2361.0696 | AH44: 2001.1254 | AI44: 7720.7864 | AJ44: 0 | AK44: 0 | AL44: 0 | AM44: 0 | AN44: 0 | AO44: 0 | AP44: 0 | AQ44: 2230.0251 | AR44: 2917.5121 | AS44: 2420.0963 | AT44: 2051.1536 | AU44: 6273.3042 | AV44: 0 | AW44: 0 | AX44: 0 | AY44: 0 | AZ44: 0 | BA44: 0 | BB44: 0 | BC44: 2285.7757 | BD44: 2990.4499 | BE44: 2480.5987 | BF44: 2102.4324 | BG44: 4797.8374 | BH44: 0 | BI44: 0 | BJ44: 0 | BK44: 0
A45: HCS03 créditos recebidos (kWh) | B45: 1856647.1 | C45: 30944.119 | D45: 0 | E45: 0 | F45: 0 | G45: 0 | H45: 0 | I45: 0 | J45: 0 | K45: 0 | L45: 0 | M45: 0 | N45: 595.52541 | O45: 557.34129 | P45: 505.81721 | Q45: 532.41554 | R45: 639.13527 | S45: 599.7273 | T45: 23465.67 | U45: 22689.073 | V45: 21544.368 | W45: 22232.433 | X45: 19811.002 | Y45: 22723.243 | Z45: 22673.541 | AA45: 21219.75 | AB45: 45848.32 | AC45: 48259.249 | AD45: 57932.545 | AE45: 54360.525 | AF45: 55865.507 | AG45: 54016.635 | AH45: 50783.291 | AI45: 52405.164 | AJ45: 46697.489 | AK45: 53562.075 | AL45: 53444.92 | AM45: 50018.118 | AN45: 45509.153 | AO45: 47902.247 | AP45: 57503.984 | AQ45: 53958.388 | AR45: 55452.237 | AS45: 53617.042 | AT45: 50392.735 | AU45: 52002.134 | AV45: 46338.356 | AW45: 53150.148 | AX45: 53033.894 | AY45: 49633.447 | AZ45: 28243.278 | BA45: 29728.448 | BB45: 35687.349 | BC45: 33486.929 | BD45: 34414.021 | BE45: 33275.088 | BF45: 39767.287 | BG45: 41037.34 | BH45: 36567.785 | BI45: 41943.293 | BJ45: 41851.551 | BK45: 39168.097
A46: BAT créditos → AMD (kWh) | B46: 1192710.1 | C46: 19878.501 | D46: 0 | E46: 0 | F46: 0 | G46: 32711.293 | H46: 40823.762 | I46: 41560.462 | J46: 47597.362 | K46: 51288.174 | L46: 0 | M46: 0 | N46: 16386.391 | O46: 15046.461 | P46: 0 | Q46: 0 | R46: 0 | S46: 32132.835 | T46: 40427.855 | U46: 41160.871 | V46: 47167.587 | W46: 50971.32 | X46: 0 | Y46: 0 | Z46: 16130.024 | AA46: 14863.108 | AB46: 0 | AC46: 0 | AD46: 0 | AE46: 31546.897 | AF46: 40029.132 | AG46: 40758.484 | AH46: 46735.166 | AI46: 50654.54 | AJ46: 0 | AK46: 0 | AL46: 15002.767 | AM46: 14140.07 | AN46: 0 | AO46: 0 | AP46: 0 | AQ46: 30953.256 | AR46: 39627.489 | AS46: 40353.194 | AT46: 46299.993 | AU46: 50337.796 | AV46: 0 | AW46: 0 | AX46: 13854.981 | AY46: 13404.428 | AZ46: 0 | BA46: 0 | BB46: 0 | BC46: 30351.686 | BD46: 39222.817 | BE46: 39944.893 | BF46: 45861.958 | BG46: 50021.048 | BH46: 0 | BI46: 0 | BJ46: 12686.114 | BK46: 12655.84
A47: Banco início mês COM Helexia (kWh) | B47: 377435.83 | C47: — | D47: 991029 | E47: 832866.4 | F47: 625562.35 | G47: 540442.65 | H47: 630063.47 | I47: 723229.87 | J47: 830949.11 | K47: 946687.29 | L47: 976942.15 | M47: 795293.96 | N47: 667084.47 | O47: 631157.77 | P47: 580103.61 | Q47: 416757.88 | R47: 202683.56 | S47: 113841.02 | T47: 202639.44 | U47: 317882.41 | V47: 446953.57 | W47: 582951.37 | X47: 657671.1 | Y47: 495833.91 | Z47: 390347.66 | AA47: 377435.83 | AB47: 347044.08 | AC47: 223218.35 | AD47: 49396.215 | AE47: 13387.229 | AF47: 154507.08 | AG47: 300744.65 | AH47: 459792.94 | AI47: 623733.68 | AJ47: 738056.9 | AK47: 596388.77 | AL47: 516075 | AM47: 545327.22 | AN47: 554395.81 | AO47: 424271.49 | AP47: 242441.38 | AQ47: 201443.59 | AR47: 340704.19 | AS47: 485106.61 | AT47: 642391.16 | AU47: 804633.76 | AV47: 913089.07 | AW47: 764187.31 | AX47: 677665.9 | AY47: 702628.04 | AZ47: 704929.86 | BA47: 551439.83 | BB47: 343604.17 | BC47: 276126.56 | BD47: 393440.28 | BE47: 515365.47 | BF47: 650929.76 | BG47: 801227.32 | BH47: 892107.62 | BI47: 726399.77 | BJ47: 622743.15 | BK47: 632563.27
A48: Bank draw COM Helexia (kWh) | B48: 3718145.8 | C48: 61969.097 | D48: 158162.6 | E48: 207304.05 | F48: 85119.698 | G48: 0 | H48: 0 | I48: 0 | J48: 0 | K48: 36160.745 | L48: 181648.19 | M48: 128209.49 | N48: 52313.091 | O48: 66100.618 | P48: 163345.73 | Q48: 214074.32 | R48: 88842.54 | S48: 0 | T48: 0 | U48: 0 | V48: 0 | W48: 13611.458 | X48: 161837.18 | Y48: 105486.25 | Z48: 29978.709 | AA48: 45254.857 | AB48: 123825.73 | AC48: 173822.14 | AD48: 36008.986 | AE48: 0 | AF48: 0 | AG48: 0 | AH48: 0 | AI48: 1513.5951 | AJ48: 141668.13 | AK48: 80313.774 | AL48: 15155.175 | AM48: 19826.651 | AN48: 130124.33 | AO48: 181830.11 | AP48: 40997.786 | AQ48: 0 | AR48: 0 | AS48: 0 | AT48: 0 | AU48: 4266.2973 | AV48: 148901.75 | AW48: 86521.41 | AX48: 15534.054 | AY48: 22414.676 | AZ48: 153490.03 | BA48: 207835.66 | BB48: 67477.608 | BC48: 0 | BD48: 0 | BE48: 0 | BF48: 0 | BG48: 8118.0217 | BH48: 165707.85 | BI48: 103656.62 | BJ48: 15922.406 | BK48: 35763.512
A49: ★ Banco fim mês COM Helexia (kWh) | B49: 347044.08 | C49: — | D49: 832866.4 | E49: 625562.35 | F49: 540442.65 | G49: 630063.47 | H49: 723229.87 | I49: 830949.11 | J49: 946687.29 | K49: 976942.15 | L49: 795293.96 | M49: 667084.47 | N49: 631157.77 | O49: 580103.61 | P49: 416757.88 | Q49: 202683.56 | R49: 113841.02 | S49: 202639.44 | T49: 317882.41 | U49: 446953.57 | V49: 582951.37 | W49: 657671.1 | X49: 495833.91 | Y49: 390347.66 | Z49: 377435.83 | AA49: 347044.08 | AB49: 223218.35 | AC49: 49396.215 | AD49: 13387.229 | AE49: 154507.08 | AF49: 300744.65 | AG49: 459792.94 | AH49: 623733.68 | AI49: 738056.9 | AJ49: 596388.77 | AK49: 516075 | AL49: 545327.22 | AM49: 554395.81 | AN49: 424271.49 | AO49: 242441.38 | AP49: 201443.59 | AQ49: 340704.19 | AR49: 485106.61 | AS49: 642391.16 | AT49: 804633.76 | AU49: 913089.07 | AV49: 764187.31 | AW49: 677665.9 | AX49: 702628.04 | AY49: 704929.86 | AZ49: 551439.83 | BA49: 343604.17 | BB49: 276126.56 | BC49: 393440.28 | BD49: 515365.47 | BE49: 650929.76 | BF49: 801227.32 | BG49: 892107.62 | BH49: 726399.77 | BI49: 622743.15 | BJ49: 632563.27 | BK49: 609455.6
A50: Banco início mês SEM Helexia (kWh) | B50: 362827.64 | C50: — | D50: 991029 | E50: 832866.4 | F50: 625562.35 | G50: 540442.65 | H50: 630063.47 | I50: 723229.87 | J50: 830949.11 | K50: 946687.29 | L50: 1013102.9 | M50: 831454.71 | N50: 703245.22 | O50: 699495.77 | P50: 677977.2 | Q50: 514125.65 | R50: 299518.91 | S50: 210037.24 | T50: 298235.93 | U50: 390013.23 | V50: 496395.31 | W50: 610848.75 | X50: 676947.5 | Y50: 495299.31 | Z50: 367089.82 | AA50: 362827.64 | AB50: 340942.36 | AC50: 171268.31 | AD50: 0 | AE50: 0 | AF50: 86759.33 | AG50: 177131.39 | AH50: 282163.04 | AI50: 395320.5 | AJ50: 458752.15 | AK50: 270386.53 | AL50: 136510.68 | AM50: 127320.74 | AN50: 100511.29 | AO50: 0 | AP50: 0 | AQ50: 0 | AR50: 85302.206 | AS50: 174252.39 | AT50: 277919.9 | AU50: 389769.77 | AV50: 450489.24 | AW50: 255249.13 | AX50: 115577.57 | AY50: 101360.79 | AZ50: 69525.95 | BA50: 0 | BB50: 0 | BC50: 0 | BD50: 83826.784 | BE50: 171337.95 | BF50: 273627.16 | BG50: 384157.44 | BH50: 442118.41 | BI50: 239842.78 | BJ50: 94242.865 | BK50: 74897.553
A51: Bank draw SEM Helexia (kWh) — gen+BAT, no CS3 | B51: 3388196 | C51: 56469.934 | D51: 158162.6 | E51: 207304.05 | F51: 85119.698 | G51: 0 | H51: 0 | I51: 0 | J51: 0 | K51: 0 | L51: 181648.19 | M51: 128209.49 | N51: 20135.835 | O51: 36565.037 | P51: 163851.55 | Q51: 214606.73 | R51: 89481.675 | S51: 0 | T51: 0 | U51: 0 | V51: 0 | W51: 0 | X51: 181648.19 | Y51: 128209.49 | Z51: 20392.201 | AA51: 36748.39 | AB51: 169674.05 | AC51: 171268.31 | AD51: 0 | AE51: 0 | AF51: 0 | AG51: 0 | AH51: 0 | AI51: 0 | AJ51: 188365.62 | AK51: 133875.85 | AL51: 24192.702 | AM51: 40949.521 | AN51: 100511.29 | AO51: 0 | AP51: 0 | AQ51: 0 | AR51: 0 | AS51: 0 | AT51: 0 | AU51: 0 | AV51: 195240.11 | AW51: 139671.56 | AX51: 28071.761 | AY51: 45239.268 | AZ51: 69525.95 | BA51: 0 | BB51: 0 | BC51: 0 | BD51: 0 | BE51: 0 | BF51: 0 | BG51: 0 | BH51: 202275.63 | BI51: 145599.92 | BJ51: 32031.426 | BK51: 49619.928
A52: Banco fim mês SEM Helexia (kWh) — gen+BAT, no CS3 | B52: 340942.36 | C52: — | D52: 832866.4 | E52: 625562.35 | F52: 540442.65 | G52: 630063.47 | H52: 723229.87 | I52: 830949.11 | J52: 946687.29 | K52: 1013102.9 | L52: 831454.71 | M52: 703245.22 | N52: 699495.77 | O52: 677977.2 | P52: 514125.65 | Q52: 299518.91 | R52: 210037.24 | S52: 298235.93 | T52: 390013.23 | U52: 496395.31 | V52: 610848.75 | W52: 676947.5 | X52: 495299.31 | Y52: 367089.82 | Z52: 362827.64 | AA52: 340942.36 | AB52: 171268.31 | AC52: 0 | AD52: 0 | AE52: 86759.33 | AF52: 177131.39 | AG52: 282163.04 | AH52: 395320.5 | AI52: 458752.15 | AJ52: 270386.53 | AK52: 136510.68 | AL52: 127320.74 | AM52: 100511.29 | AN52: 0 | AO52: 0 | AP52: 0 | AQ52: 85302.206 | AR52: 174252.39 | AS52: 277919.9 | AT52: 389769.77 | AU52: 450489.24 | AV52: 255249.13 | AW52: 115577.57 | AX52: 101360.79 | AY52: 69525.95 | AZ52: 0 | BA52: 0 | BB52: 0 | BC52: 83826.784 | BD52: 171337.95 | BE52: 273627.16 | BF52: 384157.44 | BG52: 442118.41 | BH52: 239842.78 | BI52: 94242.865 | BJ52: 74897.553 | BK52: 37933.466
A53: Custo SEM Helexia (R$) — só gen própria, sem HCS03/BAT/banco | B53: 898723.27 | C53: 14978.721 | D53: 0 | E53: 0 | F53: 0 | G53: 0 | H53: 0 | I53: 0 | J53: 0 | K53: 0 | L53: 0 | M53: 0 | N53: 0 | O53: 0 | P53: 0 | Q53: 0 | R53: 0 | S53: 0 | T53: 0 | U53: 0 | V53: 0 | W53: 0 | X53: 0 | Y53: 0 | Z53: 0 | AA53: 0 | AB53: 0 | AC53: 84342.461 | AD53: 82520.672 | AE53: 0 | AF53: 0 | AG53: 0 | AH53: 0 | AI53: 0 | AJ53: 0 | AK53: 0 | AL53: 0 | AM53: 0 | AN53: 85417.815 | AO53: 179978.06 | AP53: 85748.085 | AQ53: 0 | AR53: 0 | AS53: 0 | AT53: 0 | AU53: 0 | AV53: 0 | AW53: 0 | AX53: 0 | AY53: 0 | AZ53: 106088.79 | BA53: 185577.02 | BB53: 89050.362 | BC53: 0 | BD53: 0 | BE53: 0 | BF53: 0 | BG53: 0 | BH53: 0 | BI53: 0 | BJ53: 0 | BK53: 0
A54: Custo COM Helexia — rede remanescente (R$) | B54: 0 | C54: 0 | D54: 0 | E54: 0 | F54: 0 | G54: 0 | H54: 0 | I54: 0 | J54: 0 | K54: 0 | L54: 0 | M54: 0 | N54: 0 | O54: 0 | P54: 0 | Q54: 0 | R54: 0 | S54: 0 | T54: 0 | U54: 0 | V54: 0 | W54: 0 | X54: 0 | Y54: 0 | Z54: 0 | AA54: 0 | AB54: 0 | AC54: 0 | AD54: 0 | AE54: 0 | AF54: 0 | AG54: 0 | AH54: 0 | AI54: 0 | AJ54: 0 | AK54: 0 | AL54: 0 | AM54: 0 | AN54: 0 | AO54: 0 | AP54: 0 | AQ54: 0 | AR54: 0 | AS54: 0 | AT54: 0 | AU54: 0 | AV54: 0 | AW54: 0 | AX54: 0 | AY54: 0 | AZ54: 0 | BA54: 0 | BB54: 0 | BC54: 0 | BD54: 0 | BE54: 0 | BF54: 0 | BG54: 0 | BH54: 0 | BI54: 0 | BJ54: 0 | BK54: 0
A55: ★ Economia mensal (R$) | B55: 898723.27 | C55: 14978.721 | D55: 0 | E55: 0 | F55: 0 | G55: 0 | H55: 0 | I55: 0 | J55: 0 | K55: 0 | L55: 0 | M55: 0 | N55: 0 | O55: 0 | P55: 0 | Q55: 0 | R55: 0 | S55: 0 | T55: 0 | U55: 0 | V55: 0 | W55: 0 | X55: 0 | Y55: 0 | Z55: 0 | AA55: 0 | AB55: 0 | AC55: 84342.461 | AD55: 82520.672 | AE55: 0 | AF55: 0 | AG55: 0 | AH55: 0 | AI55: 0 | AJ55: 0 | AK55: 0 | AL55: 0 | AM55: 0 | AN55: 85417.815 | AO55: 179978.06 | AP55: 85748.085 | AQ55: 0 | AR55: 0 | AS55: 0 | AT55: 0 | AU55: 0 | AV55: 0 | AW55: 0 | AX55: 0 | AY55: 0 | AZ55: 106088.79 | BA55: 185577.02 | BB55: 89050.362 | BC55: 0 | BD55: 0 | BE55: 0 | BF55: 0 | BG55: 0 | BH55: 0 | BI55: 0 | BJ55: 0 | BK55: 0
A57: AREC (B3)
A58: Consumo FP (kWh) | B58: 269375.21 | C58: 4489.5869 | D58: 3657.4 | E58: 3450.6 | F58: 3408.8 | G58: 4205 | H58: 5428 | I58: 6374 | J58: 6073.1 | K58: 4224.3325 | L58: 4441.0175 | M58: 5202.49 | N58: 4526.4 | O58: 4182.205 | P58: 3748.835 | Q58: 3536.865 | R58: 3494.02 | S58: 4310.125 | T58: 5563.7 | U58: 6533.35 | V58: 6224.9275 | W58: 4224.3325 | X58: 4441.0175 | Y58: 5202.49 | Z58: 4526.4 | AA58: 4182.205 | AB58: 4286.7601 | AC58: 4286.7601 | AD58: 4286.7601 | AE58: 4286.7601 | AF58: 4286.7601 | AG58: 4286.7601 | AH58: 4286.7601 | AI58: 4286.7601 | AJ58: 4286.7601 | AK58: 4286.7601 | AL58: 4286.7601 | AM58: 4286.7601 | AN58: 4393.9291 | AO58: 4393.9291 | AP58: 4393.9291 | AQ58: 4393.9291 | AR58: 4393.9291 | AS58: 4393.9291 | AT58: 4393.9291 | AU58: 4393.9291 | AV58: 4393.9291 | AW58: 4393.9291 | AX58: 4393.9291 | AY58: 4393.9291 | AZ58: 4503.7774 | BA58: 4503.7774 | BB58: 4503.7774 | BC58: 4503.7774 | BD58: 4503.7774 | BE58: 4503.7774 | BF58: 4503.7774 | BG58: 4503.7774 | BH58: 4503.7774 | BI58: 4503.7774 | BJ58: 4503.7774 | BK58: 4503.7774
A59: HCS03 créditos recebidos (kWh) | B59: 269692.61 | C59: 4494.8769 | D59: 3347.73 | E59: 3523.77 | F59: 4230.09 | G59: 3969.27 | H59: 8037.456 | I59: 7771.456 | J59: 7379.372 | K59: 7576.9728 | L59: 6751.7317 | M59: 7744.2442 | N59: 4517.2781 | O59: 4227.6376 | P59: 3836.8086 | Q59: 4038.5667 | R59: 4848.0748 | S59: 4549.1509 | T59: 10131.878 | U59: 9796.563 | V59: 9302.3087 | W59: 9599.3978 | X59: 8553.8857 | Y59: 9811.3169 | Z59: 9789.8567 | AA59: 9162.1471 | AB59: 1914.9499 | AC59: 2015.6473 | AD59: 2419.6726 | AE59: 2270.4798 | AF59: 2333.3384 | AG59: 2256.1165 | AH59: 2348.2809 | AI59: 2423.2783 | AJ59: 2159.3485 | AK59: 2476.7752 | AL59: 2471.3578 | AM59: 2312.8984 | AN59: 1954.2309 | AO59: 2056.994 | AP59: 2469.3069 | AQ59: 2317.0537 | AR59: 2381.2018 | AS59: 2302.3958 | AT59: 2377.5314 | AU59: 2453.4629 | AV59: 2186.2456 | AW59: 2507.6263 | AX59: 2502.1414 | AY59: 2341.7082 | AZ59: 3694.4736 | BA59: 3888.7471 | BB59: 4668.2247 | BC59: 4380.3901 | BD59: 4501.662 | BE59: 4352.6793 | BF59: 4377.8005 | BG59: 4517.6149 | BH59: 4025.5818 | BI59: 4617.3471 | BJ59: 4607.2476 | BK59: 4311.8384
A60: Banco início mês COM Helexia (kWh) | B60: 46665.079 | C60: — | D60: 0 | E60: 0 | F60: 73.17 | G60: 894.46 | H60: 658.73 | I60: 3268.186 | J60: 4665.642 | K60: 5971.914 | L60: 9324.5543 | M60: 11635.268 | N60: 14177.023 | O60: 14167.901 | P60: 14213.333 | Q60: 14301.307 | R60: 14803.009 | S60: 16157.063 | T60: 16396.089 | U60: 20964.267 | V60: 24227.48 | W60: 27304.862 | X60: 32679.927 | Y60: 36792.795 | Z60: 41401.622 | AA60: 46665.079 | AB60: 51645.021 | AC60: 49273.211 | AD60: 47002.098 | AE60: 45135.01 | AF60: 43118.73 | AG60: 41165.308 | AH60: 39134.665 | AI60: 37196.185 | AJ60: 35332.704 | AK60: 33205.292 | AL60: 31395.307 | AM60: 29579.905 | AN60: 27606.043 | AO60: 25166.345 | AP60: 22829.41 | AQ60: 20904.787 | AR60: 18827.912 | AS60: 16815.185 | AT60: 14723.651 | AU60: 12707.254 | AV60: 10766.787 | AW60: 8559.1039 | AX60: 6672.8011 | AY60: 4781.0133 | AZ60: 2728.7924 | BA60: 1919.4886 | BB60: 1304.4583 | BC60: 1468.9056 | BD60: 1345.5183 | BE60: 1343.403 | BF60: 1192.3049 | BG60: 1066.328 | BH60: 1080.1656 | BI60: 601.97004 | BJ60: 715.53976 | BK60: 819.01002
A61: Bank draw COM Helexia (kWh) | B61: 51658.127 | C61: 860.96878 | D61: 0 | E61: 0 | F61: 0 | G61: 235.73 | H61: 0 | I61: 0 | J61: 0 | K61: 0 | L61: 0 | M61: 0 | N61: 9.12189 | O61: 0 | P61: 0 | Q61: 0 | R61: 0 | S61: 0 | T61: 0 | U61: 0 | V61: 0 | W61: 0 | X61: 0 | Y61: 0 | Z61: 0 | AA61: 0 | AB61: 2371.8102 | AC61: 2271.1128 | AD61: 1867.0875 | AE61: 2016.2804 | AF61: 1953.4217 | AG61: 2030.6436 | AH61: 1938.4792 | AI61: 1863.4819 | AJ61: 2127.4116 | AK61: 1809.9849 | AL61: 1815.4023 | AM61: 1973.8617 | AN61: 2439.6982 | AO61: 2336.9352 | AP61: 1924.6222 | AQ61: 2076.8754 | AR61: 2012.7273 | AS61: 2091.5333 | AT61: 2016.3977 | AU61: 1940.4662 | AV61: 2207.6835 | AW61: 1886.3028 | AX61: 1891.7877 | AY61: 2052.221 | AZ61: 809.30376 | BA61: 615.03029 | BB61: 0 | BC61: 123.3873 | BD61: 2.1153651 | BE61: 151.09809 | BF61: 125.97686 | BG61: 0 | BH61: 478.19554 | BI61: 0 | BJ61: 0 | BK61: 191.93896
A62: ★ Banco fim mês COM Helexia (kWh) | B62: 51645.021 | C62: — | D62: 0 | E62: 73.17 | F62: 894.46 | G62: 658.73 | H62: 3268.186 | I62: 4665.642 | J62: 5971.914 | K62: 9324.5543 | L62: 11635.268 | M62: 14177.023 | N62: 14167.901 | O62: 14213.333 | P62: 14301.307 | Q62: 14803.009 | R62: 16157.063 | S62: 16396.089 | T62: 20964.267 | U62: 24227.48 | V62: 27304.862 | W62: 32679.927 | X62: 36792.795 | Y62: 41401.622 | Z62: 46665.079 | AA62: 51645.021 | AB62: 49273.211 | AC62: 47002.098 | AD62: 45135.01 | AE62: 43118.73 | AF62: 41165.308 | AG62: 39134.665 | AH62: 37196.185 | AI62: 35332.704 | AJ62: 33205.292 | AK62: 31395.307 | AL62: 29579.905 | AM62: 27606.043 | AN62: 25166.345 | AO62: 22829.41 | AP62: 20904.787 | AQ62: 18827.912 | AR62: 16815.185 | AS62: 14723.651 | AT62: 12707.254 | AU62: 10766.787 | AV62: 8559.1039 | AW62: 6672.8011 | AX62: 4781.0133 | AY62: 2728.7924 | AZ62: 1919.4886 | BA62: 1304.4583 | BB62: 1468.9056 | BC62: 1345.5183 | BD62: 1343.403 | BE62: 1192.3049 | BF62: 1066.328 | BG62: 1080.1656 | BH62: 601.97004 | BI62: 715.53976 | BJ62: 819.01002 | BK62: 627.07106
A63: Banco início mês SEM Helexia (kWh) | B63: 0 | C63: — | D63: 0 | E63: 0 | F63: 0 | G63: 0 | H63: 0 | I63: 0 | J63: 0 | K63: 0 | L63: 0 | M63: 0 | N63: 0 | O63: 0 | P63: 0 | Q63: 0 | R63: 0 | S63: 0 | T63: 0 | U63: 0 | V63: 0 | W63: 0 | X63: 0 | Y63: 0 | Z63: 0 | AA63: 0 | AB63: 0 | AC63: 0 | AD63: 0 | AE63: 0 | AF63: 0 | AG63: 0 | AH63: 0 | AI63: 0 | AJ63: 0 | AK63: 0 | AL63: 0 | AM63: 0 | AN63: 0 | AO63: 0 | AP63: 0 | AQ63: 0 | AR63: 0 | AS63: 0 | AT63: 0 | AU63: 0 | AV63: 0 | AW63: 0 | AX63: 0 | AY63: 0 | AZ63: 0 | BA63: 0 | BB63: 0 | BC63: 0 | BD63: 0 | BE63: 0 | BF63: 0 | BG63: 0 | BH63: 0 | BI63: 0 | BJ63: 0 | BK63: 0
A64: Bank draw SEM Helexia (kWh) | B64: 0 | C64: 0 | D64: 0 | E64: 0 | F64: 0 | G64: 0 | H64: 0 | I64: 0 | J64: 0 | K64: 0 | L64: 0 | M64: 0 | N64: 0 | O64: 0 | P64: 0 | Q64: 0 | R64: 0 | S64: 0 | T64: 0 | U64: 0 | V64: 0 | W64: 0 | X64: 0 | Y64: 0 | Z64: 0 | AA64: 0 | AB64: 0 | AC64: 0 | AD64: 0 | AE64: 0 | AF64: 0 | AG64: 0 | AH64: 0 | AI64: 0 | AJ64: 0 | AK64: 0 | AL64: 0 | AM64: 0 | AN64: 0 | AO64: 0 | AP64: 0 | AQ64: 0 | AR64: 0 | AS64: 0 | AT64: 0 | AU64: 0 | AV64: 0 | AW64: 0 | AX64: 0 | AY64: 0 | AZ64: 0 | BA64: 0 | BB64: 0 | BC64: 0 | BD64: 0 | BE64: 0 | BF64: 0 | BG64: 0 | BH64: 0 | BI64: 0 | BJ64: 0 | BK64: 0
A65: Banco fim mês SEM Helexia (kWh) | B65: 0 | C65: — | D65: 0 | E65: 0 | F65: 0 | G65: 0 | H65: 0 | I65: 0 | J65: 0 | K65: 0 | L65: 0 | M65: 0 | N65: 0 | O65: 0 | P65: 0 | Q65: 0 | R65: 0 | S65: 0 | T65: 0 | U65: 0 | V65: 0 | W65: 0 | X65: 0 | Y65: 0 | Z65: 0 | AA65: 0 | AB65: 0 | AC65: 0 | AD65: 0 | AE65: 0 | AF65: 0 | AG65: 0 | AH65: 0 | AI65: 0 | AJ65: 0 | AK65: 0 | AL65: 0 | AM65: 0 | AN65: 0 | AO65: 0 | AP65: 0 | AQ65: 0 | AR65: 0 | AS65: 0 | AT65: 0 | AU65: 0 | AV65: 0 | AW65: 0 | AX65: 0 | AY65: 0 | AZ65: 0 | BA65: 0 | BB65: 0 | BC65: 0 | BD65: 0 | BE65: 0 | BF65: 0 | BG65: 0 | BH65: 0 | BI65: 0 | BJ65: 0 | BK65: 0
A66: Custo SEM Helexia (R$) — só gen própria, sem HCS03/BAT/banco | B66: 249304.31 | C66: 4155.0719 | D66: 3384.8905 | E66: 3193.499 | F66: 3154.8134 | G66: 3891.6893 | H66: 5023.5647 | I66: 5899.0791 | J66: 5620.5989 | K66: 3909.5814 | L66: 4110.1214 | M66: 4814.8573 | N66: 4189.1421 | O66: 3870.5928 | P66: 3469.5128 | Q66: 3273.3364 | R66: 3233.6838 | S66: 3988.9815 | T66: 5149.1538 | U66: 6046.5561 | V66: 5761.1139 | W66: 3909.5814 | X66: 4110.1214 | Y66: 4814.8573 | Z66: 4189.1421 | AA66: 3870.5928 | AB66: 3967.3576 | AC66: 3967.3576 | AD66: 3967.3576 | AE66: 3967.3576 | AF66: 3967.3576 | AG66: 3967.3576 | AH66: 3967.3576 | AI66: 3967.3576 | AJ66: 3967.3576 | AK66: 3967.3576 | AL66: 3967.3576 | AM66: 3967.3576 | AN66: 4066.5415 | AO66: 4066.5415 | AP66: 4066.5415 | AQ66: 4066.5415 | AR66: 4066.5415 | AS66: 4066.5415 | AT66: 4066.5415 | AU66: 4066.5415 | AV66: 4066.5415 | AW66: 4066.5415 | AX66: 4066.5415 | AY66: 4066.5415 | AZ66: 4168.205 | BA66: 4168.205 | BB66: 4168.205 | BC66: 4168.205 | BD66: 4168.205 | BE66: 4168.205 | BF66: 4168.205 | BG66: 4168.205 | BH66: 4168.205 | BI66: 4168.205 | BJ66: 4168.205 | BK66: 4168.205
A67: Custo COM Helexia — rede remanescente (R$) | B67: 358.24597 | C67: 5.9707661 | D67: 358.24597 | E67: 0 | F67: 0 | G67: 0 | H67: 0 | I67: 0 | J67: 0 | K67: 0 | L67: 0 | M67: 0 | N67: 0 | O67: 0 | P67: 0 | Q67: 0 | R67: 0 | S67: 0 | T67: 0 | U67: 0 | V67: 0 | W67: 0 | X67: 0 | Y67: 0 | Z67: 0 | AA67: 0 | AB67: 0 | AC67: 0 | AD67: 0 | AE67: 0 | AF67: 0 | AG67: 0 | AH67: 0 | AI67: 0 | AJ67: 0 | AK67: 0 | AL67: 0 | AM67: 0 | AN67: 0 | AO67: 0 | AP67: 0 | AQ67: 0 | AR67: 0 | AS67: 0 | AT67: 0 | AU67: 0 | AV67: 0 | AW67: 0 | AX67: 0 | AY67: 0 | AZ67: 0 | BA67: 0 | BB67: 0 | BC67: 0 | BD67: 0 | BE67: 0 | BF67: 0 | BG67: 0 | BH67: 0 | BI67: 0 | BJ67: 0 | BK67: 0
A68: ★ Economia mensal (R$) | B68: 248946.07 | C68: 4149.1011 | D68: 3026.6445 | E68: 3193.499 | F68: 3154.8134 | G68: 3891.6893 | H68: 5023.5647 | I68: 5899.0791 | J68: 5620.5989 | K68: 3909.5814 | L68: 4110.1214 | M68: 4814.8573 | N68: 4189.1421 | O68: 3870.5928 | P68: 3469.5128 | Q68: 3273.3364 | R68: 3233.6838 | S68: 3988.9815 | T68: 5149.1538 | U68: 6046.5561 | V68: 5761.1139 | W68: 3909.5814 | X68: 4110.1214 | Y68: 4814.8573 | Z68: 4189.1421 | AA68: 3870.5928 | AB68: 3967.3576 | AC68: 3967.3576 | AD68: 3967.3576 | AE68: 3967.3576 | AF68: 3967.3576 | AG68: 3967.3576 | AH68: 3967.3576 | AI68: 3967.3576 | AJ68: 3967.3576 | AK68: 3967.3576 | AL68: 3967.3576 | AM68: 3967.3576 | AN68: 4066.5415 | AO68: 4066.5415 | AP68: 4066.5415 | AQ68: 4066.5415 | AR68: 4066.5415 | AS68: 4066.5415 | AT68: 4066.5415 | AU68: 4066.5415 | AV68: 4066.5415 | AW68: 4066.5415 | AX68: 4066.5415 | AY68: 4066.5415 | AZ68: 4168.205 | BA68: 4168.205 | BB68: 4168.205 | BC68: 4168.205 | BD68: 4168.205 | BE68: 4168.205 | BF68: 4168.205 | BG68: 4168.205 | BH68: 4168.205 | BI68: 4168.205 | BJ68: 4168.205 | BK68: 4168.205
A70: Banheiro Motoristas (B3)
A71: Consumo FP (kWh) | B71: 28440.424 | C71: 474.00707 | D71: 450 | E71: 450 | F71: 450 | G71: 450 | H71: 450 | I71: 450 | J71: 450 | K71: 461.25 | L71: 461.25 | M71: 461.25 | N71: 461.25 | O71: 461.25 | P71: 461.25 | Q71: 461.25 | R71: 461.25 | S71: 461.25 | T71: 461.25 | U71: 461.25 | V71: 461.25 | W71: 461.25 | X71: 461.25 | Y71: 461.25 | Z71: 461.25 | AA71: 461.25 | AB71: 472.78125 | AC71: 472.78125 | AD71: 472.78125 | AE71: 472.78125 | AF71: 472.78125 | AG71: 472.78125 | AH71: 472.78125 | AI71: 472.78125 | AJ71: 472.78125 | AK71: 472.78125 | AL71: 472.78125 | AM71: 472.78125 | AN71: 484.60078 | AO71: 484.60078 | AP71: 484.60078 | AQ71: 484.60078 | AR71: 484.60078 | AS71: 484.60078 | AT71: 484.60078 | AU71: 484.60078 | AV71: 484.60078 | AW71: 484.60078 | AX71: 484.60078 | AY71: 484.60078 | AZ71: 496.7158 | BA71: 496.7158 | BB71: 496.7158 | BC71: 496.7158 | BD71: 496.7158 | BE71: 496.7158 | BF71: 496.7158 | BG71: 496.7158 | BH71: 496.7158 | BI71: 496.7158 | BJ71: 496.7158 | BK71: 496.7158
A72: HCS03 créditos recebidos (kWh) | B72: 28446.266 | C72: 474.10444 | D72: 409.167 | E72: 430.683 | F72: 517.011 | G72: 485.133 | H72: 755.4 | I72: 730.4 | J72: 693.55 | K72: 712.1215 | L72: 634.56125 | M72: 727.8425 | N72: 581.0004 | O72: 543.7476 | P72: 493.4802 | Q72: 519.4298 | R72: 623.5466 | S72: 585.0998 | T72: 676.4607 | U72: 654.0732 | V72: 621.07403 | W72: 640.90935 | X72: 571.10512 | Y72: 655.05825 | Z72: 653.62545 | AA72: 611.71605 | AB72: 319.15832 | AC72: 335.94122 | AD72: 403.27876 | AE72: 378.4133 | AF72: 388.88974 | AG72: 376.01942 | AH72: 370.78119 | AI72: 382.62288 | AJ72: 340.94976 | AK72: 391.06978 | AL72: 390.21439 | AM72: 365.19448 | AN72: 317.56253 | AO72: 334.26152 | AP72: 401.26237 | AQ72: 376.52123 | AR72: 386.94529 | AS72: 374.13932 | AT72: 368.92729 | AU72: 380.70977 | AV72: 339.24501 | AW72: 389.11443 | AX72: 388.26332 | AY72: 363.36851 | AZ72: 328.12759 | BA72: 345.38214 | BB72: 414.61206 | BC72: 389.0478 | BD72: 399.81866 | BE72: 386.58665 | BF72: 462.25223 | BG72: 477.01524 | BH72: 425.06143 | BI72: 487.54596 | BJ72: 486.47956 | BK72: 455.28728
A73: Banco início mês COM Helexia (kWh) | B73: 3444.6298 | C73: — | D73: 0 | E73: 0 | F73: 0 | G73: 67.011 | H73: 102.144 | I73: 407.544 | J73: 687.944 | K73: 931.494 | L73: 1182.3655 | M73: 1355.6768 | N73: 1622.2693 | O73: 1742.0197 | P73: 1824.5173 | Q73: 1856.7475 | R73: 1914.9273 | S73: 2077.2239 | T73: 2201.0737 | U73: 2416.2844 | V73: 2609.1076 | W73: 2768.9316 | X73: 2948.5909 | Y73: 3058.4461 | Z73: 3252.2543 | AA73: 3444.6298 | AB73: 3595.0958 | AC73: 3441.4729 | AD73: 3304.6328 | AE73: 3235.1304 | AF73: 3140.7624 | AG73: 3056.8709 | AH73: 2960.1091 | AI73: 2858.109 | AJ73: 2767.9506 | AK73: 2636.1191 | AL73: 2554.4077 | AM73: 2471.8408 | AN73: 2364.254 | AO73: 2197.2158 | AP73: 2046.8765 | AQ73: 1963.5381 | AR73: 1855.4586 | AS73: 1757.8031 | AT73: 1647.3416 | AU73: 1531.6681 | AV73: 1427.7771 | AW73: 1282.4213 | AX73: 1186.935 | AY73: 1090.5975 | AZ73: 969.36524 | BA73: 800.77703 | BB73: 649.44337 | BC73: 567.33963 | BD73: 459.67163 | BE73: 362.77449 | BF73: 252.64534 | BG73: 218.18176 | BH73: 198.4812 | BI73: 126.82683 | BJ73: 117.657 | BK73: 107.42076
A74: Bank draw COM Helexia (kWh) | B74: 3529.1036 | C74: 58.818393 | D74: 0 | E74: 0 | F74: 0 | G74: 0 | H74: 0 | I74: 0 | J74: 0 | K74: 0 | L74: 0 | M74: 0 | N74: 0 | O74: 0 | P74: 0 | Q74: 0 | R74: 0 | S74: 0 | T74: 0 | U74: 0 | V74: 0 | W74: 0 | X74: 0 | Y74: 0 | Z74: 0 | AA74: 0 | AB74: 153.62293 | AC74: 136.84003 | AD74: 69.502486 | AE74: 94.367954 | AF74: 83.89151 | AG74: 96.761835 | AH74: 102.00006 | AI74: 90.158368 | AJ74: 131.83149 | AK74: 81.711475 | AL74: 82.566856 | AM74: 107.58677 | AN74: 167.03825 | AO74: 150.33926 | AP74: 83.338412 | AQ74: 108.07955 | AR74: 97.65549 | AS74: 110.46146 | AT74: 115.67349 | AU74: 103.89101 | AV74: 145.35577 | AW74: 95.486355 | AX74: 96.33746 | AY74: 121.23227 | AZ74: 168.58821 | BA74: 151.33366 | BB74: 82.103741 | BC74: 107.668 | BD74: 96.897137 | BE74: 110.12916 | BF74: 34.463574 | BG74: 19.700562 | BH74: 71.654367 | BI74: 9.1698362 | BJ74: 10.236239 | BK74: 41.428517
A75: ★ Banco fim mês COM Helexia (kWh) | B75: 3595.0958 | C75: — | D75: 0 | E75: 0 | F75: 67.011 | G75: 102.144 | H75: 407.544 | I75: 687.944 | J75: 931.494 | K75: 1182.3655 | L75: 1355.6768 | M75: 1622.2693 | N75: 1742.0197 | O75: 1824.5173 | P75: 1856.7475 | Q75: 1914.9273 | R75: 2077.2239 | S75: 2201.0737 | T75: 2416.2844 | U75: 2609.1076 | V75: 2768.9316 | W75: 2948.5909 | X75: 3058.4461 | Y75: 3252.2543 | Z75: 3444.6298 | AA75: 3595.0958 | AB75: 3441.4729 | AC75: 3304.6328 | AD75: 3235.1304 | AE75: 3140.7624 | AF75: 3056.8709 | AG75: 2960.1091 | AH75: 2858.109 | AI75: 2767.9506 | AJ75: 2636.1191 | AK75: 2554.4077 | AL75: 2471.8408 | AM75: 2364.254 | AN75: 2197.2158 | AO75: 2046.8765 | AP75: 1963.5381 | AQ75: 1855.4586 | AR75: 1757.8031 | AS75: 1647.3416 | AT75: 1531.6681 | AU75: 1427.7771 | AV75: 1282.4213 | AW75: 1186.935 | AX75: 1090.5975 | AY75: 969.36524 | AZ75: 800.77703 | BA75: 649.44337 | BB75: 567.33963 | BC75: 459.67163 | BD75: 362.77449 | BE75: 252.64534 | BF75: 218.18176 | BG75: 198.4812 | BH75: 126.82683 | BI75: 117.657 | BJ75: 107.42076 | BK75: 65.992243
A76: Banco início mês SEM Helexia (kWh) | B76: 0 | C76: — | D76: 0 | E76: 0 | F76: 0 | G76: 0 | H76: 0 | I76: 0 | J76: 0 | K76: 0 | L76: 0 | M76: 0 | N76: 0 | O76: 0 | P76: 0 | Q76: 0 | R76: 0 | S76: 0 | T76: 0 | U76: 0 | V76: 0 | W76: 0 | X76: 0 | Y76: 0 | Z76: 0 | AA76: 0 | AB76: 0 | AC76: 0 | AD76: 0 | AE76: 0 | AF76: 0 | AG76: 0 | AH76: 0 | AI76: 0 | AJ76: 0 | AK76: 0 | AL76: 0 | AM76: 0 | AN76: 0 | AO76: 0 | AP76: 0 | AQ76: 0 | AR76: 0 | AS76: 0 | AT76: 0 | AU76: 0 | AV76: 0 | AW76: 0 | AX76: 0 | AY76: 0 | AZ76: 0 | BA76: 0 | BB76: 0 | BC76: 0 | BD76: 0 | BE76: 0 | BF76: 0 | BG76: 0 | BH76: 0 | BI76: 0 | BJ76: 0 | BK76: 0
A77: Bank draw SEM Helexia (kWh) | B77: 0 | C77: 0 | D77: 0 | E77: 0 | F77: 0 | G77: 0 | H77: 0 | I77: 0 | J77: 0 | K77: 0 | L77: 0 | M77: 0 | N77: 0 | O77: 0 | P77: 0 | Q77: 0 | R77: 0 | S77: 0 | T77: 0 | U77: 0 | V77: 0 | W77: 0 | X77: 0 | Y77: 0 | Z77: 0 | AA77: 0 | AB77: 0 | AC77: 0 | AD77: 0 | AE77: 0 | AF77: 0 | AG77: 0 | AH77: 0 | AI77: 0 | AJ77: 0 | AK77: 0 | AL77: 0 | AM77: 0 | AN77: 0 | AO77: 0 | AP77: 0 | AQ77: 0 | AR77: 0 | AS77: 0 | AT77: 0 | AU77: 0 | AV77: 0 | AW77: 0 | AX77: 0 | AY77: 0 | AZ77: 0 | BA77: 0 | BB77: 0 | BC77: 0 | BD77: 0 | BE77: 0 | BF77: 0 | BG77: 0 | BH77: 0 | BI77: 0 | BJ77: 0 | BK77: 0
A78: Banco fim mês SEM Helexia (kWh) | B78: 0 | C78: — | D78: 0 | E78: 0 | F78: 0 | G78: 0 | H78: 0 | I78: 0 | J78: 0 | K78: 0 | L78: 0 | M78: 0 | N78: 0 | O78: 0 | P78: 0 | Q78: 0 | R78: 0 | S78: 0 | T78: 0 | U78: 0 | V78: 0 | W78: 0 | X78: 0 | Y78: 0 | Z78: 0 | AA78: 0 | AB78: 0 | AC78: 0 | AD78: 0 | AE78: 0 | AF78: 0 | AG78: 0 | AH78: 0 | AI78: 0 | AJ78: 0 | AK78: 0 | AL78: 0 | AM78: 0 | AN78: 0 | AO78: 0 | AP78: 0 | AQ78: 0 | AR78: 0 | AS78: 0 | AT78: 0 | AU78: 0 | AV78: 0 | AW78: 0 | AX78: 0 | AY78: 0 | AZ78: 0 | BA78: 0 | BB78: 0 | BC78: 0 | BD78: 0 | BE78: 0 | BF78: 0 | BG78: 0 | BH78: 0 | BI78: 0 | BJ78: 0 | BK78: 0
A79: Custo SEM Helexia (R$) — só gen própria, sem HCS03/BAT/banco | B79: 26321.354 | C79: 438.68924 | D79: 416.47091 | E79: 416.47091 | F79: 416.47091 | G79: 416.47091 | H79: 416.47091 | I79: 416.47091 | J79: 416.47091 | K79: 426.88269 | L79: 426.88269 | M79: 426.88269 | N79: 426.88269 | O79: 426.88269 | P79: 426.88269 | Q79: 426.88269 | R79: 426.88269 | S79: 426.88269 | T79: 426.88269 | U79: 426.88269 | V79: 426.88269 | W79: 426.88269 | X79: 426.88269 | Y79: 426.88269 | Z79: 426.88269 | AA79: 426.88269 | AB79: 437.55475 | AC79: 437.55475 | AD79: 437.55475 | AE79: 437.55475 | AF79: 437.55475 | AG79: 437.55475 | AH79: 437.55475 | AI79: 437.55475 | AJ79: 437.55475 | AK79: 437.55475 | AL79: 437.55475 | AM79: 437.55475 | AN79: 448.49362 | AO79: 448.49362 | AP79: 448.49362 | AQ79: 448.49362 | AR79: 448.49362 | AS79: 448.49362 | AT79: 448.49362 | AU79: 448.49362 | AV79: 448.49362 | AW79: 448.49362 | AX79: 448.49362 | AY79: 448.49362 | AZ79: 459.70596 | BA79: 459.70596 | BB79: 459.70596 | BC79: 459.70596 | BD79: 459.70596 | BE79: 459.70596 | BF79: 459.70596 | BG79: 459.70596 | BH79: 459.70596 | BI79: 459.70596 | BJ79: 459.70596 | BK79: 459.70596
A80: Custo COM Helexia — rede remanescente (R$) | B80: 69.585349 | C80: 1.1597558 | D80: 47.238213 | E80: 22.347135 | F80: 0 | G80: 0 | H80: 0 | I80: 0 | J80: 0 | K80: 0 | L80: 0 | M80: 0 | N80: 0 | O80: 0 | P80: 0 | Q80: 0 | R80: 0 | S80: 0 | T80: 0 | U80: 0 | V80: 0 | W80: 0 | X80: 0 | Y80: 0 | Z80: 0 | AA80: 0 | AB80: 0 | AC80: 0 | AD80: 0 | AE80: 0 | AF80: 0 | AG80: 0 | AH80: 0 | AI80: 0 | AJ80: 0 | AK80: 0 | AL80: 0 | AM80: 0 | AN80: 0 | AO80: 0 | AP80: 0 | AQ80: 0 | AR80: 0 | AS80: 0 | AT80: 0 | AU80: 0 | AV80: 0 | AW80: 0 | AX80: 0 | AY80: 0 | AZ80: 0 | BA80: 0 | BB80: 0 | BC80: 0 | BD80: 0 | BE80: 0 | BF80: 0 | BG80: 0 | BH80: 0 | BI80: 0 | BJ80: 0 | BK80: 0
A81: ★ Economia mensal (R$) | B81: 26251.769 | C81: 437.52948 | D81: 369.2327 | E81: 394.12378 | F81: 416.47091 | G81: 416.47091 | H81: 416.47091 | I81: 416.47091 | J81: 416.47091 | K81: 426.88269 | L81: 426.88269 | M81: 426.88269 | N81: 426.88269 | O81: 426.88269 | P81: 426.88269 | Q81: 426.88269 | R81: 426.88269 | S81: 426.88269 | T81: 426.88269 | U81: 426.88269 | V81: 426.88269 | W81: 426.88269 | X81: 426.88269 | Y81: 426.88269 | Z81: 426.88269 | AA81: 426.88269 | AB81: 437.55475 | AC81: 437.55475 | AD81: 437.55475 | AE81: 437.55475 | AF81: 437.55475 | AG81: 437.55475 | AH81: 437.55475 | AI81: 437.55475 | AJ81: 437.55475 | AK81: 437.55475 | AL81: 437.55475 | AM81: 437.55475 | AN81: 448.49362 | AO81: 448.49362 | AP81: 448.49362 | AQ81: 448.49362 | AR81: 448.49362 | AS81: 448.49362 | AT81: 448.49362 | AU81: 448.49362 | AV81: 448.49362 | AW81: 448.49362 | AX81: 448.49362 | AY81: 448.49362 | AZ81: 459.70596 | BA81: 459.70596 | BB81: 459.70596 | BC81: 459.70596 | BD81: 459.70596 | BE81: 459.70596 | BF81: 459.70596 | BG81: 459.70596 | BH81: 459.70596 | BI81: 459.70596 | BJ81: 459.70596 | BK81: 459.70596
A83: CTC Copasul (B3)
A84: Consumo FP (kWh) | B84: 37820.511 | C84: 630.34184 | D84: 364 | E84: 293 | F84: 369 | G84: 674 | H84: 752 | I84: 769 | J84: 670 | K84: 398.725 | L84: 917.375 | M84: 967.6 | N84: 541.2 | O84: 609.875 | P84: 373.1 | Q84: 300.325 | R84: 378.225 | S84: 690.85 | T84: 770.8 | U84: 788.225 | V84: 686.75 | W84: 398.725 | X84: 917.375 | Y84: 967.6 | Z84: 541.2 | AA84: 609.875 | AB84: 625.12187 | AC84: 625.12187 | AD84: 625.12187 | AE84: 625.12187 | AF84: 625.12187 | AG84: 625.12187 | AH84: 625.12187 | AI84: 625.12187 | AJ84: 625.12187 | AK84: 625.12187 | AL84: 625.12187 | AM84: 625.12187 | AN84: 640.74992 | AO84: 640.74992 | AP84: 640.74992 | AQ84: 640.74992 | AR84: 640.74992 | AS84: 640.74992 | AT84: 640.74992 | AU84: 640.74992 | AV84: 640.74992 | AW84: 640.74992 | AX84: 640.74992 | AY84: 640.74992 | AZ84: 656.76867 | BA84: 656.76867 | BB84: 656.76867 | BC84: 656.76867 | BD84: 656.76867 | BE84: 656.76867 | BF84: 656.76867 | BG84: 656.76867 | BH84: 656.76867 | BI84: 656.76867 | BJ84: 656.76867 | BK84: 656.76867
A85: HCS03 créditos recebidos (kWh) | B85: 37348.971 | C85: 622.48284 | D85: 384.369 | E85: 404.581 | F85: 485.677 | G85: 455.731 | H85: 1163.316 | I85: 1124.816 | J85: 1068.067 | K85: 1096.6671 | L85: 977.22433 | M85: 1120.8774 | N85: 566.47539 | O85: 530.15391 | P85: 481.14319 | Q85: 506.44405 | R85: 607.95793 | S85: 570.47231 | T85: 1082.3371 | U85: 1046.5171 | V85: 993.71844 | W85: 1025.455 | X85: 913.7682 | Y85: 1048.0932 | Z85: 1045.8007 | AA85: 978.74568 | AB85: 392.81024 | AC85: 413.46612 | AD85: 496.34309 | AE85: 465.73944 | AF85: 478.63353 | AG85: 462.79313 | AH85: 466.90965 | AI85: 481.82141 | AJ85: 429.34414 | AK85: 492.45824 | AL85: 491.38109 | AM85: 459.87453 | AN85: 390.84619 | AO85: 411.39879 | AP85: 493.86138 | AQ85: 463.41074 | AR85: 476.24036 | AS85: 460.47916 | AT85: 464.5751 | AU85: 479.4123 | AV85: 427.19742 | AW85: 489.99594 | AX85: 488.92418 | AY85: 457.57516 | AZ85: 449.65633 | BA85: 473.30145 | BB85: 568.17208 | BC85: 533.13958 | BD85: 547.89965 | BE85: 529.76688 | BF85: 584.61311 | BG85: 603.28398 | BH85: 537.5777 | BI85: 616.60225 | BJ85: 615.25356 | BK85: 575.80451
A86: Banco início mês COM Helexia (kWh) | B86: 4560.7124 | C86: — | D86: 0 | E86: 20.369 | F86: 131.95 | G86: 248.627 | H86: 30.358 | I86: 441.674 | J86: 797.49 | K86: 1195.557 | L86: 1893.4991 | M86: 1953.3484 | N86: 2106.6259 | O86: 2131.9013 | P86: 2052.1802 | Q86: 2160.2234 | R86: 2366.3424 | S86: 2596.0754 | T86: 2475.6977 | U86: 2787.2348 | V86: 3045.5269 | W86: 3352.4954 | X86: 3979.2253 | Y86: 3975.6185 | Z86: 4056.1117 | AA86: 4560.7124 | AB86: 4929.5831 | AC86: 4697.2715 | AD86: 4485.6157 | AE86: 4356.8369 | AF86: 4197.4545 | AG86: 4050.9662 | AH86: 3888.6374 | AI86: 3730.4252 | AJ86: 3587.1247 | AK86: 3391.347 | AL86: 3258.6833 | AM86: 3124.9426 | AN86: 2959.6952 | AO86: 2709.7915 | AP86: 2480.4404 | AQ86: 2333.5518 | AR86: 2156.2126 | AS86: 1991.7031 | AT86: 1811.4323 | AU86: 1635.2575 | AV86: 1473.9199 | AW86: 1260.3674 | AX86: 1109.6134 | AY86: 957.78765 | AZ86: 774.61288 | BA86: 567.50054 | BB86: 384.03332 | BC86: 295.43673 | BD86: 171.80764 | BE86: 62.938624 | BF86: 0 | BG86: 0 | BH86: 0 | BI86: 0 | BJ86: 0 | BK86: 0
A87: Bank draw COM Helexia (kWh) | B87: 5351.5577 | C87: 89.192628 | D87: 0 | E87: 0 | F87: 0 | G87: 218.269 | H87: 0 | I87: 0 | J87: 0 | K87: 0 | L87: 0 | M87: 0 | N87: 0 | O87: 79.72109 | P87: 0 | Q87: 0 | R87: 0 | S87: 120.37769 | T87: 0 | U87: 0 | V87: 0 | W87: 0 | X87: 3.6068 | Y87: 0 | Z87: 0 | AA87: 0 | AB87: 232.31164 | AC87: 211.65575 | AD87: 128.77878 | AE87: 159.38243 | AF87: 146.48835 | AG87: 162.32875 | AH87: 158.21222 | AI87: 143.30047 | AJ87: 195.77773 | AK87: 132.66364 | AL87: 133.74079 | AM87: 165.24734 | AN87: 249.90373 | AO87: 229.35113 | AP87: 146.88854 | AQ87: 177.33918 | AR87: 164.50956 | AS87: 180.27076 | AT87: 176.17482 | AU87: 161.33762 | AV87: 213.5525 | AW87: 150.75398 | AX87: 151.82574 | AY87: 183.17476 | AZ87: 207.11234 | BA87: 183.46722 | BB87: 88.596588 | BC87: 123.62909 | BD87: 108.86902 | BE87: 62.938624 | BF87: 0 | BG87: 0 | BH87: 0 | BI87: 0 | BJ87: 0 | BK87: 0
A88: ★ Banco fim mês COM Helexia (kWh) | B88: 4929.5831 | C88: — | D88: 20.369 | E88: 131.95 | F88: 248.627 | G88: 30.358 | H88: 441.674 | I88: 797.49 | J88: 1195.557 | K88: 1893.4991 | L88: 1953.3484 | M88: 2106.6259 | N88: 2131.9013 | O88: 2052.1802 | P88: 2160.2234 | Q88: 2366.3424 | R88: 2596.0754 | S88: 2475.6977 | T88: 2787.2348 | U88: 3045.5269 | V88: 3352.4954 | W88: 3979.2253 | X88: 3975.6185 | Y88: 4056.1117 | Z88: 4560.7124 | AA88: 4929.5831 | AB88: 4697.2715 | AC88: 4485.6157 | AD88: 4356.8369 | AE88: 4197.4545 | AF88: 4050.9662 | AG88: 3888.6374 | AH88: 3730.4252 | AI88: 3587.1247 | AJ88: 3391.347 | AK88: 3258.6833 | AL88: 3124.9426 | AM88: 2959.6952 | AN88: 2709.7915 | AO88: 2480.4404 | AP88: 2333.5518 | AQ88: 2156.2126 | AR88: 1991.7031 | AS88: 1811.4323 | AT88: 1635.2575 | AU88: 1473.9199 | AV88: 1260.3674 | AW88: 1109.6134 | AX88: 957.78765 | AY88: 774.61288 | AZ88: 567.50054 | BA88: 384.03332 | BB88: 295.43673 | BC88: 171.80764 | BD88: 62.938624 | BE88: 0 | BF88: 0 | BG88: 0 | BH88: 0 | BI88: 0 | BJ88: 0 | BK88: 0
A89: Banco início mês SEM Helexia (kWh) | B89: 0 | C89: — | D89: 0 | E89: 0 | F89: 0 | G89: 0 | H89: 0 | I89: 0 | J89: 0 | K89: 0 | L89: 0 | M89: 0 | N89: 0 | O89: 0 | P89: 0 | Q89: 0 | R89: 0 | S89: 0 | T89: 0 | U89: 0 | V89: 0 | W89: 0 | X89: 0 | Y89: 0 | Z89: 0 | AA89: 0 | AB89: 0 | AC89: 0 | AD89: 0 | AE89: 0 | AF89: 0 | AG89: 0 | AH89: 0 | AI89: 0 | AJ89: 0 | AK89: 0 | AL89: 0 | AM89: 0 | AN89: 0 | AO89: 0 | AP89: 0 | AQ89: 0 | AR89: 0 | AS89: 0 | AT89: 0 | AU89: 0 | AV89: 0 | AW89: 0 | AX89: 0 | AY89: 0 | AZ89: 0 | BA89: 0 | BB89: 0 | BC89: 0 | BD89: 0 | BE89: 0 | BF89: 0 | BG89: 0 | BH89: 0 | BI89: 0 | BJ89: 0 | BK89: 0
A90: Bank draw SEM Helexia (kWh) | B90: 0 | C90: 0 | D90: 0 | E90: 0 | F90: 0 | G90: 0 | H90: 0 | I90: 0 | J90: 0 | K90: 0 | L90: 0 | M90: 0 | N90: 0 | O90: 0 | P90: 0 | Q90: 0 | R90: 0 | S90: 0 | T90: 0 | U90: 0 | V90: 0 | W90: 0 | X90: 0 | Y90: 0 | Z90: 0 | AA90: 0 | AB90: 0 | AC90: 0 | AD90: 0 | AE90: 0 | AF90: 0 | AG90: 0 | AH90: 0 | AI90: 0 | AJ90: 0 | AK90: 0 | AL90: 0 | AM90: 0 | AN90: 0 | AO90: 0 | AP90: 0 | AQ90: 0 | AR90: 0 | AS90: 0 | AT90: 0 | AU90: 0 | AV90: 0 | AW90: 0 | AX90: 0 | AY90: 0 | AZ90: 0 | BA90: 0 | BB90: 0 | BC90: 0 | BD90: 0 | BE90: 0 | BF90: 0 | BG90: 0 | BH90: 0 | BI90: 0 | BJ90: 0 | BK90: 0
A91: Banco fim mês SEM Helexia (kWh) | B91: 0 | C91: — | D91: 0 | E91: 0 | F91: 0 | G91: 0 | H91: 0 | I91: 0 | J91: 0 | K91: 0 | L91: 0 | M91: 0 | N91: 0 | O91: 0 | P91: 0 | Q91: 0 | R91: 0 | S91: 0 | T91: 0 | U91: 0 | V91: 0 | W91: 0 | X91: 0 | Y91: 0 | Z91: 0 | AA91: 0 | AB91: 0 | AC91: 0 | AD91: 0 | AE91: 0 | AF91: 0 | AG91: 0 | AH91: 0 | AI91: 0 | AJ91: 0 | AK91: 0 | AL91: 0 | AM91: 0 | AN91: 0 | AO91: 0 | AP91: 0 | AQ91: 0 | AR91: 0 | AS91: 0 | AT91: 0 | AU91: 0 | AV91: 0 | AW91: 0 | AX91: 0 | AY91: 0 | AZ91: 0 | BA91: 0 | BB91: 0 | BC91: 0 | BD91: 0 | BE91: 0 | BF91: 0 | BG91: 0 | BH91: 0 | BI91: 0 | BJ91: 0 | BK91: 0
A92: Custo SEM Helexia (R$) — só gen própria, sem HCS03/BAT/banco | B92: 35002.539 | C92: 583.37565 | D92: 336.87869 | E92: 271.16884 | F92: 341.50615 | G92: 623.78088 | H92: 695.96917 | I92: 711.70252 | J92: 620.07892 | K92: 369.01637 | L92: 849.02223 | M92: 895.50501 | N92: 500.87569 | O92: 564.43377 | P92: 345.30066 | Q92: 277.94806 | R92: 350.0438 | S92: 639.3754 | T92: 713.3684 | U92: 729.49508 | V92: 635.58089 | W92: 369.01637 | X92: 849.02223 | Y92: 895.50501 | Z92: 500.87569 | AA92: 564.43377 | AB92: 578.54462 | AC92: 578.54462 | AD92: 578.54462 | AE92: 578.54462 | AF92: 578.54462 | AG92: 578.54462 | AH92: 578.54462 | AI92: 578.54462 | AJ92: 578.54462 | AK92: 578.54462 | AL92: 578.54462 | AM92: 578.54462 | AN92: 593.00823 | AO92: 593.00823 | AP92: 593.00823 | AQ92: 593.00823 | AR92: 593.00823 | AS92: 593.00823 | AT92: 593.00823 | AU92: 593.00823 | AV92: 593.00823 | AW92: 593.00823 | AX92: 593.00823 | AY92: 593.00823 | AZ92: 607.83344 | BA92: 607.83344 | BB92: 607.83344 | BC92: 607.83344 | BD92: 607.83344 | BE92: 607.83344 | BF92: 607.83344 | BG92: 607.83344 | BH92: 607.83344 | BI92: 607.83344 | BJ92: 607.83344 | BK92: 607.83344
A93: Custo COM Helexia — rede remanescente (R$) | B93: 545.50757 | C93: 9.0917929 | D93: 0 | E93: 0 | F93: 0 | G93: 0 | H93: 0 | I93: 0 | J93: 0 | K93: 0 | L93: 0 | M93: 0 | N93: 0 | O93: 0 | P93: 0 | Q93: 0 | R93: 0 | S93: 0 | T93: 0 | U93: 0 | V93: 0 | W93: 0 | X93: 0 | Y93: 0 | Z93: 0 | AA93: 0 | AB93: 0 | AC93: 0 | AD93: 0 | AE93: 0 | AF93: 0 | AG93: 0 | AH93: 0 | AI93: 0 | AJ93: 0 | AK93: 0 | AL93: 0 | AM93: 0 | AN93: 0 | AO93: 0 | AP93: 0 | AQ93: 0 | AR93: 0 | AS93: 0 | AT93: 0 | AU93: 0 | AV93: 0 | AW93: 0 | AX93: 0 | AY93: 0 | AZ93: 0 | BA93: 0 | BB93: 0 | BC93: 0 | BD93: 0 | BE93: 74.112343 | BF93: 83.474144 | BG93: 61.874496 | BH93: 137.88771 | BI93: 46.467072 | BJ93: 48.027317 | BK93: 93.664498
A94: ★ Economia mensal (R$) | B94: 34457.032 | C94: 574.28386 | D94: 336.87869 | E94: 271.16884 | F94: 341.50615 | G94: 623.78088 | H94: 695.96917 | I94: 711.70252 | J94: 620.07892 | K94: 369.01637 | L94: 849.02223 | M94: 895.50501 | N94: 500.87569 | O94: 564.43377 | P94: 345.30066 | Q94: 277.94806 | R94: 350.0438 | S94: 639.3754 | T94: 713.3684 | U94: 729.49508 | V94: 635.58089 | W94: 369.01637 | X94: 849.02223 | Y94: 895.50501 | Z94: 500.87569 | AA94: 564.43377 | AB94: 578.54462 | AC94: 578.54462 | AD94: 578.54462 | AE94: 578.54462 | AF94: 578.54462 | AG94: 578.54462 | AH94: 578.54462 | AI94: 578.54462 | AJ94: 578.54462 | AK94: 578.54462 | AL94: 578.54462 | AM94: 578.54462 | AN94: 593.00823 | AO94: 593.00823 | AP94: 593.00823 | AQ94: 593.00823 | AR94: 593.00823 | AS94: 593.00823 | AT94: 593.00823 | AU94: 593.00823 | AV94: 593.00823 | AW94: 593.00823 | AX94: 593.00823 | AY94: 593.00823 | AZ94: 607.83344 | BA94: 607.83344 | BB94: 607.83344 | BC94: 607.83344 | BD94: 607.83344 | BE94: 533.7211 | BF94: 524.3593 | BG94: 545.95894 | BH94: 469.94573 | BI94: 561.36637 | BJ94: 559.80612 | BK94: 514.16894
A96: Depósito Irrigação (B3)
A97: Consumo FP (kWh) | B97: 67184.655 | C97: 1119.7442 | D97: 1067 | E97: 899 | F97: 816 | G97: 719 | H97: 943 | I97: 925 | J97: 838 | K97: 897.9 | L97: 909.175 | M97: 1055.75 | N97: 1051.65 | O97: 1174.65 | P97: 1093.675 | Q97: 921.475 | R97: 836.4 | S97: 736.975 | T97: 966.575 | U97: 948.125 | V97: 858.95 | W97: 897.9 | X97: 909.175 | Y97: 1055.75 | Z97: 1051.65 | AA97: 1174.65 | AB97: 1204.0162 | AC97: 1204.0162 | AD97: 1204.0162 | AE97: 1204.0162 | AF97: 1204.0162 | AG97: 1204.0162 | AH97: 1204.0162 | AI97: 1204.0162 | AJ97: 1204.0162 | AK97: 1204.0162 | AL97: 1204.0162 | AM97: 1204.0162 | AN97: 1234.1167 | AO97: 1234.1167 | AP97: 1234.1167 | AQ97: 1234.1167 | AR97: 1234.1167 | AS97: 1234.1167 | AT97: 1234.1167 | AU97: 1234.1167 | AV97: 1234.1167 | AW97: 1234.1167 | AX97: 1234.1167 | AY97: 1234.1167 | AZ97: 1264.9696 | BA97: 1264.9696 | BB97: 1264.9696 | BC97: 1264.9696 | BD97: 1264.9696 | BE97: 1264.9696 | BF97: 1264.9696 | BG97: 1264.9696 | BH97: 1264.9696 | BI97: 1264.9696 | BJ97: 1264.9696 | BK97: 1264.9696
A98: HCS03 créditos recebidos (kWh) | B98: 67022.086 | C98: 1117.0348 | D98: 793.536 | E98: 835.264 | F98: 1002.688 | G98: 940.864 | H98: 1722.312 | I98: 1665.312 | J98: 1581.294 | K98: 1623.637 | L98: 1446.7997 | M98: 1659.4809 | N98: 1176.5258 | O98: 1101.0889 | P98: 999.29741 | Q98: 1051.8453 | R98: 1262.6819 | S98: 1184.8271 | T98: 1428.0837 | U98: 1380.8212 | V98: 1311.1563 | W98: 1353.0308 | X98: 1205.6664 | Y98: 1382.9008 | Z98: 1379.876 | AA98: 1291.4005 | AB98: 859.2724 | AC98: 904.45714 | AD98: 1085.7505 | AE98: 1018.805 | AF98: 1047.0108 | AG98: 1012.36 | AH98: 1029.9478 | AI98: 1062.8413 | AJ98: 947.08267 | AK98: 1086.3049 | AL98: 1083.9289 | AM98: 1014.4291 | AN98: 867.18998 | AO98: 912.79107 | AP98: 1095.7549 | AQ98: 1028.1926 | AR98: 1056.6583 | AS98: 1021.6881 | AT98: 1038.462 | AU98: 1071.6275 | AV98: 954.91188 | AW98: 1095.2851 | AX98: 1092.8893 | AY98: 1022.8151 | AZ98: 1190.9816 | BA98: 1253.6093 | BB98: 1504.8882 | BC98: 1412.0994 | BD98: 1451.1937 | BE98: 1403.1663 | BF98: 598.20876 | BG98: 617.31384 | BH98: 550.0795 | BI98: 630.94184 | BJ98: 629.56179 | BK98: 589.19531
A99: Banco início mês COM Helexia (kWh) | B99: 8253.4141 | C99: — | D99: 0 | E99: 0 | F99: 0 | G99: 186.688 | H99: 408.552 | I99: 1187.864 | J99: 1928.176 | K99: 2671.47 | L99: 3397.207 | M99: 3934.8317 | N99: 4538.5626 | O99: 4663.4384 | P99: 4589.8773 | Q99: 4495.4997 | R99: 4625.87 | S99: 5052.1519 | T99: 5500.004 | U99: 5961.5127 | V99: 6394.2089 | W99: 6846.4152 | X99: 7301.546 | Y99: 7598.0374 | Z99: 7925.1881 | AA99: 8253.4141 | AB99: 8370.1646 | AC99: 8025.4208 | AD99: 7725.8617 | AE99: 7607.5959 | AF99: 7422.3847 | AG99: 7265.3793 | AH99: 7073.723 | AI99: 6899.6545 | AJ99: 6758.4796 | AK99: 6501.546 | AL99: 6383.8347 | AM99: 6263.7473 | AN99: 6074.1602 | AO99: 5707.2335 | AP99: 5385.9079 | AQ99: 5247.5462 | AR99: 5041.6221 | AS99: 4864.1638 | AT99: 4651.7353 | AU99: 4456.0806 | AV99: 4293.5914 | AW99: 4014.3867 | AX99: 3875.5551 | AY99: 3734.3277 | AZ99: 3523.0262 | BA99: 3449.0382 | BB99: 3437.6779 | BC99: 3677.5965 | BD99: 3824.7264 | BE99: 4010.9505 | BF99: 4149.1472 | BG99: 3482.3864 | BH99: 2834.7307 | BI99: 2119.8406 | BJ99: 1485.8129 | BK99: 850.40511
A100: Bank draw COM Helexia (kWh) | B100: 9074.9419 | C100: 151.24903 | D100: 0 | E100: 0 | F100: 0 | G100: 0 | H100: 0 | I100: 0 | J100: 0 | K100: 0 | L100: 0 | M100: 0 | N100: 0 | O100: 73.56111 | P100: 94.377595 | Q100: 0 | R100: 0 | S100: 0 | T100: 0 | U100: 0 | V100: 0 | W100: 0 | X100: 0 | Y100: 0 | Z100: 0 | AA100: 0 | AB100: 344.74385 | AC100: 299.55911 | AD100: 118.26573 | AE100: 185.21122 | AF100: 157.00541 | AG100: 191.65629 | AH100: 174.06849 | AI100: 141.17491 | AJ100: 256.93358 | AK100: 117.71132 | AL100: 120.08738 | AM100: 189.58713 | AN100: 366.92668 | AO100: 321.32559 | AP100: 138.36172 | AQ100: 205.92407 | AR100: 177.45836 | AS100: 212.42852 | AT100: 195.65466 | AU100: 162.48916 | AV100: 279.20477 | AW100: 138.8316 | AX100: 141.22731 | AY100: 211.30159 | AZ100: 73.987954 | BA100: 11.360322 | BB100: 0 | BC100: 0 | BD100: 0 | BE100: 0 | BF100: 666.76081 | BG100: 647.65573 | BH100: 714.89007 | BI100: 634.02774 | BJ100: 635.40779 | BK100: 675.77426
A101: ★ Banco fim mês COM Helexia (kWh) | B101: 8370.1646 | C101: — | D101: 0 | E101: 0 | F101: 186.688 | G101: 408.552 | H101: 1187.864 | I101: 1928.176 | J101: 2671.47 | K101: 3397.207 | L101: 3934.8317 | M101: 4538.5626 | N101: 4663.4384 | O101: 4589.8773 | P101: 4495.4997 | Q101: 4625.87 | R101: 5052.1519 | S101: 5500.004 | T101: 5961.5127 | U101: 6394.2089 | V101: 6846.4152 | W101: 7301.546 | X101: 7598.0374 | Y101: 7925.1881 | Z101: 8253.4141 | AA101: 8370.1646 | AB101: 8025.4208 | AC101: 7725.8617 | AD101: 7607.5959 | AE101: 7422.3847 | AF101: 7265.3793 | AG101: 7073.723 | AH101: 6899.6545 | AI101: 6758.4796 | AJ101: 6501.546 | AK101: 6383.8347 | AL101: 6263.7473 | AM101: 6074.1602 | AN101: 5707.2335 | AO101: 5385.9079 | AP101: 5247.5462 | AQ101: 5041.6221 | AR101: 4864.1638 | AS101: 4651.7353 | AT101: 4456.0806 | AU101: 4293.5914 | AV101: 4014.3867 | AW101: 3875.5551 | AX101: 3734.3277 | AY101: 3523.0262 | AZ101: 3449.0382 | BA101: 3437.6779 | BB101: 3677.5965 | BC101: 3824.7264 | BD101: 4010.9505 | BE101: 4149.1472 | BF101: 3482.3864 | BG101: 2834.7307 | BH101: 2119.8406 | BI101: 1485.8129 | BJ101: 850.40511 | BK101: 174.63084
A102: Banco início mês SEM Helexia (kWh) | B102: 0 | C102: — | D102: 0 | E102: 0 | F102: 0 | G102: 0 | H102: 0 | I102: 0 | J102: 0 | K102: 0 | L102: 0 | M102: 0 | N102: 0 | O102: 0 | P102: 0 | Q102: 0 | R102: 0 | S102: 0 | T102: 0 | U102: 0 | V102: 0 | W102: 0 | X102: 0 | Y102: 0 | Z102: 0 | AA102: 0 | AB102: 0 | AC102: 0 | AD102: 0 | AE102: 0 | AF102: 0 | AG102: 0 | AH102: 0 | AI102: 0 | AJ102: 0 | AK102: 0 | AL102: 0 | AM102: 0 | AN102: 0 | AO102: 0 | AP102: 0 | AQ102: 0 | AR102: 0 | AS102: 0 | AT102: 0 | AU102: 0 | AV102: 0 | AW102: 0 | AX102: 0 | AY102: 0 | AZ102: 0 | BA102: 0 | BB102: 0 | BC102: 0 | BD102: 0 | BE102: 0 | BF102: 0 | BG102: 0 | BH102: 0 | BI102: 0 | BJ102: 0 | BK102: 0
A103: Bank draw SEM Helexia (kWh) | B103: 0 | C103: 0 | D103: 0 | E103: 0 | F103: 0 | G103: 0 | H103: 0 | I103: 0 | J103: 0 | K103: 0 | L103: 0 | M103: 0 | N103: 0 | O103: 0 | P103: 0 | Q103: 0 | R103: 0 | S103: 0 | T103: 0 | U103: 0 | V103: 0 | W103: 0 | X103: 0 | Y103: 0 | Z103: 0 | AA103: 0 | AB103: 0 | AC103: 0 | AD103: 0 | AE103: 0 | AF103: 0 | AG103: 0 | AH103: 0 | AI103: 0 | AJ103: 0 | AK103: 0 | AL103: 0 | AM103: 0 | AN103: 0 | AO103: 0 | AP103: 0 | AQ103: 0 | AR103: 0 | AS103: 0 | AT103: 0 | AU103: 0 | AV103: 0 | AW103: 0 | AX103: 0 | AY103: 0 | AZ103: 0 | BA103: 0 | BB103: 0 | BC103: 0 | BD103: 0 | BE103: 0 | BF103: 0 | BG103: 0 | BH103: 0 | BI103: 0 | BJ103: 0 | BK103: 0
A104: Banco fim mês SEM Helexia (kWh) | B104: 0 | C104: — | D104: 0 | E104: 0 | F104: 0 | G104: 0 | H104: 0 | I104: 0 | J104: 0 | K104: 0 | L104: 0 | M104: 0 | N104: 0 | O104: 0 | P104: 0 | Q104: 0 | R104: 0 | S104: 0 | T104: 0 | U104: 0 | V104: 0 | W104: 0 | X104: 0 | Y104: 0 | Z104: 0 | AA104: 0 | AB104: 0 | AC104: 0 | AD104: 0 | AE104: 0 | AF104: 0 | AG104: 0 | AH104: 0 | AI104: 0 | AJ104: 0 | AK104: 0 | AL104: 0 | AM104: 0 | AN104: 0 | AO104: 0 | AP104: 0 | AQ104: 0 | AR104: 0 | AS104: 0 | AT104: 0 | AU104: 0 | AV104: 0 | AW104: 0 | AX104: 0 | AY104: 0 | AZ104: 0 | BA104: 0 | BB104: 0 | BC104: 0 | BD104: 0 | BE104: 0 | BF104: 0 | BG104: 0 | BH104: 0 | BI104: 0 | BJ104: 0 | BK104: 0
A105: Custo SEM Helexia (R$) — só gen própria, sem HCS03/BAT/banco | B105: 62178.788 | C105: 1036.3131 | D105: 987.49881 | E105: 832.01634 | F105: 755.20059 | G105: 665.42797 | H105: 872.73794 | I105: 856.0791 | J105: 775.56139 | K105: 830.9983 | L105: 841.43321 | M105: 977.08704 | N105: 973.29253 | O105: 1087.1279 | P105: 1012.1863 | Q105: 852.81674 | R105: 774.0806 | S105: 682.06367 | T105: 894.55639 | U105: 877.48108 | V105: 794.95043 | W105: 830.9983 | X105: 841.43321 | Y105: 977.08704 | Z105: 973.29253 | AA105: 1087.1279 | AB105: 1114.3061 | AC105: 1114.3061 | AD105: 1114.3061 | AE105: 1114.3061 | AF105: 1114.3061 | AG105: 1114.3061 | AH105: 1114.3061 | AI105: 1114.3061 | AJ105: 1114.3061 | AK105: 1114.3061 | AL105: 1114.3061 | AM105: 1114.3061 | AN105: 1142.1638 | AO105: 1142.1638 | AP105: 1142.1638 | AQ105: 1142.1638 | AR105: 1142.1638 | AS105: 1142.1638 | AT105: 1142.1638 | AU105: 1142.1638 | AV105: 1142.1638 | AW105: 1142.1638 | AX105: 1142.1638 | AY105: 1142.1638 | AZ105: 1170.7179 | BA105: 1170.7179 | BB105: 1170.7179 | BC105: 1170.7179 | BD105: 1170.7179 | BE105: 1170.7179 | BF105: 1170.7179 | BG105: 1170.7179 | BH105: 1170.7179 | BI105: 1170.7179 | BJ105: 1170.7179 | BK105: 1170.7179
A106: Custo COM Helexia — rede remanescente (R$) | B106: 390.09442 | C106: 6.5015737 | D106: 316.36056 | E106: 73.733862 | F106: 0 | G106: 0 | H106: 0 | I106: 0 | J106: 0 | K106: 0 | L106: 0 | M106: 0 | N106: 0 | O106: 0 | P106: 0 | Q106: 0 | R106: 0 | S106: 0 | T106: 0 | U106: 0 | V106: 0 | W106: 0 | X106: 0 | Y106: 0 | Z106: 0 | AA106: 0 | AB106: 0 | AC106: 0 | AD106: 0 | AE106: 0 | AF106: 0 | AG106: 0 | AH106: 0 | AI106: 0 | AJ106: 0 | AK106: 0 | AL106: 0 | AM106: 0 | AN106: 0 | AO106: 0 | AP106: 0 | AQ106: 0 | AR106: 0 | AS106: 0 | AT106: 0 | AU106: 0 | AV106: 0 | AW106: 0 | AX106: 0 | AY106: 0 | AZ106: 0 | BA106: 0 | BB106: 0 | BC106: 0 | BD106: 0 | BE106: 0 | BF106: 0 | BG106: 0 | BH106: 0 | BI106: 0 | BJ106: 0 | BK106: 0
...

Sheet Input_Consumo_GrupoA
A1: INPUT — CONSUMO ORÇADO GRUPO A | Fonte: Consumo_Orçado_2026_GD
A2: Azul = valores editáveis (fonte: arquivo fornecido) | Preto = fórmulas de projeção Y2/Y3
A3: Mês | B3: NHS FP (kWh) | C3: NHS Ponta (kWh) | D3: BAT FP (kWh) | E3: BAT Ponta (kWh) | F3: AMD FP (kWh) | G3: AMD Ponta (kWh)
A4: Jan | B4: 70769.9 | C4: 7863.3 | D4: 113967 | E4: 12663 | F4: 73973.4 | G4: 8219.3
A5: Fev | B5: 243719.7 | C5: 27080 | D5: 125874 | E5: 13986 | F5: 209472.2 | G5: 23274.7
A6: Mar | B6: 331874.1 | C6: 36874.9 | D6: 57499.2 | E6: 6388.8 | F6: 173260.2 | G6: 19251.1
A7: Abr | B7: 102778.3 | C7: 11419.8 | D7: 35640 | E7: 3960 | F7: 78448.4 | G7: 8716.5
A8: Mai | B8: 62814.2 | C8: 6979.4 | D8: 79603.2 | E8: 8844.8 | F8: 102629.5 | G8: 11403.3
A9: Jun | B9: 108694.9 | C9: 12077.2 | D9: 78336 | E9: 8704 | F9: 182444.7 | G9: 20271.6
A10: Jul | B10: 328938.1 | C10: 36548.7 | D10: 115718.4 | E10: 12857.6 | F10: 234799.2 | G10: 26088.8
A11: Ago | B11: 190977.6 | C11: 21219.7 | D11: 23364 | E11: 2596 | F11: 134799.3 | G11: 14977.7
A12: Set | B12: 126478.8 | C12: 14053.2 | D12: 10800 | E12: 1200 | F12: 18637.2 | G12: 2070.8
A13: Out | B13: 28215 | C13: 3135 | D13: 10800 | E13: 1200 | F13: 24382.8 | G13: 2709.2
A14: Nov | B14: 42209.6 | C14: 4690 | D14: 10800 | E14: 1200 | F14: 20225.7 | G14: 2247.3
A15: Dez | B15: 42209.6 | C15: 4690 | D15: 3402 | E15: 378 | F15: 17142.3 | G15: 1904.7
A17: Crescimento Y2 aplicado automaticamente via Premissas!$B$21 (atualmente 2,5%). Altere lá para que todos os 18 UCs sejam atualizados.

Sheet Dados_Produção_Copasul

Sheet Amandina
A1: Unidade | B1: Data | C1: Geração (kWh) | D1: Yf Diário (kWh/kWp)
A2: Amandina | B2: 45716 | C2: 190.1 | D2: =IFERROR(C2/VLOOKUP(A2,Usinas!$A:$B,2,FALSE()),"") -> 0.27274032 | F2: Geração Mensal | H2: Mês | I2: Kwh | J2: MWh | L2: Proxi Bataypora | P2: proxy Rate | Q2: 0.8
A3: Amandina | B3: 45717 | C3: 249.5 | D3: =IFERROR(C3/VLOOKUP(A3,Usinas!$A:$B,2,FALSE()),"") -> 0.3579627 | F3: 45658 | G3: =+F3+30 -> 45688 | H3: =+F3 -> 45658 | I3: 0 | J3: 0 | L3: =+Batayporã!J3*Amandina!$Q$2 -> 91.4072
A4: Amandina | B4: 45718 | C4: 295.9 | D4: =IFERROR(C4/VLOOKUP(A4,Usinas!$A:$B,2,FALSE()),"") -> 0.42453372 | F4: =+B2 -> 45716 | G4: =+F4 -> 45716 | H4: =+F4 -> 45716 | I4: =SUMIFS($C$1:$C$366, $B$1:$B$366, ">="&F4, $B$1:$B$366, "<="&G4) -> 190.1 | J4: =+I4/1000 -> 0.1901 | L4: =+Batayporã!J4*Amandina!$Q$2 -> 72.90552
A5: Amandina | B5: 45719 | C5: 250.2 | D5: =IFERROR(C5/VLOOKUP(A5,Usinas!$A:$B,2,FALSE()),"") -> 0.358967 | F5: =+G4+1 -> 45717 | G5: =+F5+30 -> 45747 | H5: =+F5 -> 45717 | I5: =SUMIFS($C$1:$C$366, $B$1:$B$366, ">="&F5, $B$1:$B$366, "<="&G5) -> 7913.8 | J5: =+I5/1000 -> 7.9138 | L5: =+Batayporã!J5*Amandina!$Q$2 -> 82.44952
A6: Amandina | B6: 45720 | C6: 256.6 | D6: =IFERROR(C6/VLOOKUP(A6,Usinas!$A:$B,2,FALSE()),"") -> 0.36814921 | F6: =+G5+1 -> 45748 | G6: =+F6+29 -> 45777 | H6: =+F6 -> 45748 | I6: =SUMIFS($C$1:$C$366, $B$1:$B$366, ">="&F6, $B$1:$B$366, "<="&G6) -> 23902.8 | J6: =+I6/1000 -> 23.9028 | L6: =+Batayporã!J6*Amandina!$Q$2 -> 58.96776
A7: Amandina | B7: 45721 | C7: 241 | D7: =IFERROR(C7/VLOOKUP(A7,Usinas!$A:$B,2,FALSE()),"") -> 0.34576758 | F7: =+G6+1 -> 45778 | G7: =+F7+30 -> 45808 | H7: =+F7 -> 45778 | I7: =SUMIFS($C$1:$C$366, $B$1:$B$366, ">="&F7, $B$1:$B$366, "<="&G7) -> 28781.7 | J7: =+I7/1000 -> 28.7817 | L7: =+Batayporã!J7*Amandina!$Q$2 -> 73.29328
A8: Amandina | B8: 45722 | C8: 194.3 | D8: =IFERROR(C8/VLOOKUP(A8,Usinas!$A:$B,2,FALSE()),"") -> 0.27876614 | F8: =+G7+1 -> 45809 | G8: =+F8+29 -> 45838 | H8: =+F8 -> 45809 | I8: =SUMIFS($C$1:$C$366, $B$1:$B$366, ">="&F8, $B$1:$B$366, "<="&G8) -> 20798.2 | J8: =+I8/1000 -> 20.7982 | L8: =+Batayporã!J8*Amandina!$Q$2 -> 57.82952
A9: Amandina | B9: 45723 | C9: 89.9 | D9: =IFERROR(C9/VLOOKUP(A9,Usinas!$A:$B,2,FALSE()),"") -> 0.12898135 | F9: =+G8+1 -> 45839 | G9: =+F9+30 -> 45869 | H9: =+F9 -> 45839 | I9: =SUMIFS($C$1:$C$366, $B$1:$B$366, ">="&F9, $B$1:$B$366, "<="&G9) -> 37317.8 | J9: =+I9/1000 -> 37.3178 | L9: =+Batayporã!J9*Amandina!$Q$2 -> 70.66944
A10: Amandina | B10: 45724 | C10: 357.6 | D10: =IFERROR(C10/VLOOKUP(A10,Usinas!$A:$B,2,FALSE()),"") -> 0.51305595 | F10: =+G9+1 -> 45870 | G10: =+F10+30 -> 45900 | H10: =+F10 -> 45870 | I10: =SUMIFS($C$1:$C$366, $B$1:$B$366, ">="&F10, $B$1:$B$366, "<="&G10) -> 16177.9 | J10: =+I10/1000 -> 16.1779 | L10: =+Batayporã!J10*Amandina!$Q$2 -> 74.46616
A11: Amandina | B11: 45725 | C11: 287 | D11: =IFERROR(C11/VLOOKUP(A11,Usinas!$A:$B,2,FALSE()),"") -> 0.41176471 | F11: =+G10+1 -> 45901 | G11: =+F11+29 -> 45930 | H11: =+F11 -> 45901 | I11: =SUMIFS($C$1:$C$366, $B$1:$B$366, ">="&F11, $B$1:$B$366, "<="&G11) -> 37738.8 | J11: =+I11/1000 -> 37.7388 | L11: =+Batayporã!J11*Amandina!$Q$2 -> 75.54672
A12: Amandina | B12: 45726 | C12: 248.1 | D12: =IFERROR(C12/VLOOKUP(A12,Usinas!$A:$B,2,FALSE()),"") -> 0.35595409 | F12: =+G11+1 -> 45931 | G12: =+F12+30 -> 45961 | H12: =+F12 -> 45931 | I12: =SUMIFS($C$1:$C$366, $B$1:$B$366, ">="&F12, $B$1:$B$366, "<="&G12) -> 40322 | J12: =+I12/1000 -> 40.322 | L12: =+Batayporã!J12*Amandina!$Q$2 -> 76.72544
A13: Amandina | B13: 45727 | C13: 142.1 | D13: =IFERROR(C13/VLOOKUP(A13,Usinas!$A:$B,2,FALSE()),"") -> 0.20387374 | F13: =+G12+1 -> 45962 | G13: =+F13+29 -> 45991 | H13: =+F13 -> 45962 | I13: =SUMIFS($C$1:$C$366, $B$1:$B$366, ">="&F13, $B$1:$B$366, "<="&G13) -> 36462.9 | J13: =+I13/1000 -> 36.4629 | L13: =+Batayporã!J13*Amandina!$Q$2 -> 86.38448
A14: Amandina | B14: 45728 | C14: 224.8 | D14: =IFERROR(C14/VLOOKUP(A14,Usinas!$A:$B,2,FALSE()),"") -> 0.32252511 | F14: =+G13+1 -> 45992 | G14: =+F14+30 -> 46022 | H14: =+F14 -> 45992 | I14: =SUMIFS($C$1:$C$366, $B$1:$B$366, ">="&F14, $B$1:$B$366, "<="&G14) -> 19968.1 | J14: =+I14/1000 -> 19.9681 | L14: =+Batayporã!J14*Amandina!$Q$2 -> 85.28312
A15: Amandina | B15: 45729 | C15: 242.3 | D15: =IFERROR(C15/VLOOKUP(A15,Usinas!$A:$B,2,FALSE()),"") -> 0.34763271
A16: Amandina | B16: 45730 | C16: 288.4 | D16: =IFERROR(C16/VLOOKUP(A16,Usinas!$A:$B,2,FALSE()),"") -> 0.41377331
A17: Amandina | B17: 45731 | C17: 347.5 | D17: =IFERROR(C17/VLOOKUP(A17,Usinas!$A:$B,2,FALSE()),"") -> 0.49856528 | L17: =+SUM(L2:L14) -> 905.92816
A18: Amandina | B18: 45732 | C18: 310.4 | D18: =IFERROR(C18/VLOOKUP(A18,Usinas!$A:$B,2,FALSE()),"") -> 0.44533716
A19: Amandina | B19: 45733 | C19: 278 | D19: =IFERROR(C19/VLOOKUP(A19,Usinas!$A:$B,2,FALSE()),"") -> 0.39885222
A20: Amandina | B20: 45734 | C20: 222.1 | D20: =IFERROR(C20/VLOOKUP(A20,Usinas!$A:$B,2,FALSE()),"") -> 0.31865136
A21: Amandina | B21: 45735 | C21: 332.3 | D21: =IFERROR(C21/VLOOKUP(A21,Usinas!$A:$B,2,FALSE()),"") -> 0.47675753
A22: Amandina | B22: 45736 | C22: 318.3 | D22: =IFERROR(C22/VLOOKUP(A22,Usinas!$A:$B,2,FALSE()),"") -> 0.45667145
A23: Amandina | B23: 45737 | C23: 321.4 | D23: =IFERROR(C23/VLOOKUP(A23,Usinas!$A:$B,2,FALSE()),"") -> 0.46111908
A24: Amandina | B24: 45738 | C24: 272.8 | D24: =IFERROR(C24/VLOOKUP(A24,Usinas!$A:$B,2,FALSE()),"") -> 0.39139168
A25: Amandina | B25: 45739 | C25: 250.5 | D25: =IFERROR(C25/VLOOKUP(A25,Usinas!$A:$B,2,FALSE()),"") -> 0.35939742
A26: Amandina | B26: 45740 | C26: 281.2 | D26: =IFERROR(C26/VLOOKUP(A26,Usinas!$A:$B,2,FALSE()),"") -> 0.40344333
A27: Amandina | B27: 45741 | C27: 264.2 | D27: =IFERROR(C27/VLOOKUP(A27,Usinas!$A:$B,2,FALSE()),"") -> 0.37905308
A28: Amandina | B28: 45742 | C28: 275 | D28: =IFERROR(C28/VLOOKUP(A28,Usinas!$A:$B,2,FALSE()),"") -> 0.39454806
A29: Amandina | B29: 45743 | C29: 297 | D29: =IFERROR(C29/VLOOKUP(A29,Usinas!$A:$B,2,FALSE()),"") -> 0.42611191
... A356: Amandina | B356: 46022 | C356: 990.9 | D356: =IFERROR(C356/VLOOKUP(A356,Usinas!$A:$B,2,FALSE()),"") -> 1.4216643

Sheet Batayporã
A1: Unidade | B1: Data | C1: Geração (kWh) | D1: Yf Diário (kWh/kWp)
A2: Batayporã | B2: 45658 | C2: 3715.4 | D2: =IFERROR(C2/VLOOKUP(A2,Usinas!$A:$B,2,FALSE()),"") -> 5.2925926 | F2: Geração Mensal | H2: Mês | I2: Kwh | J2: MWh
A3: Batayporã | B3: 45659 | C3: 2498.6 | D3: =IFERROR(C3/VLOOKUP(A3,Usinas!$A:$B,2,FALSE()),"") -> 3.5592593 | F3: =+B2 -> 45658 | G3: =+B32 -> 45688 | H3: =+F3 -> 45658 | I3: =SUMIFS($C$1:$C$366, $B$1:$B$366, ">="&F3, $B$1:$B$366, "<="&G3) -> 114259 | J3: =+I3/1000 -> 114.259
A4: Batayporã | B4: 45660 | C4: 4061.9 | D4: =IFERROR(C4/VLOOKUP(A4,Usinas!$A:$B,2,FALSE()),"") -> 5.7861823 | F4: =+B33 -> 45689 | G4: =+F4+27 -> 45716 | H4: =+F4 -> 45689 | I4: =SUMIFS($C$1:$C$366, $B$1:$B$366, ">="&F4, $B$1:$B$366, "<="&G4) -> 91131.9 | J4: =+I4/1000 -> 91.1319
A5: Batayporã | B5: 45661 | C5: 3262.5 | D5: =IFERROR(C5/VLOOKUP(A5,Usinas!$A:$B,2,FALSE()),"") -> 4.6474359 | F5: =+G4+1 -> 45717 | G5: =+F5+30 -> 45747 | H5: =+F5 -> 45717 | I5: =SUMIFS($C$1:$C$366, $B$1:$B$366, ">="&F5, $B$1:$B$366, "<="&G5) -> 103061.9 | J5: =+I5/1000 -> 103.0619
A6: Batayporã | B6: 45662 | C6: 4061 | D6: =IFERROR(C6/VLOOKUP(A6,Usinas!$A:$B,2,FALSE()),"") -> 5.7849003 | F6: =+G5+1 -> 45748 | G6: =+F6+29 -> 45777 | H6: =+F6 -> 45748 | I6: =SUMIFS($C$1:$C$366, $B$1:$B$366, ">="&F6, $B$1:$B$366, "<="&G6) -> 73709.7 | J6: =+I6/1000 -> 73.7097
A7: Batayporã | B7: 45663 | C7: 4431.9 | D7: =IFERROR(C7/VLOOKUP(A7,Usinas!$A:$B,2,FALSE()),"") -> 6.3132479 | F7: =+G6+1 -> 45778 | G7: =+F7+30 -> 45808 | H7: =+F7 -> 45778 | I7: =SUMIFS($C$1:$C$366, $B$1:$B$366, ">="&F7, $B$1:$B$366, "<="&G7) -> 91616.6 | J7: =+I7/1000 -> 91.6166
A8: Batayporã | B8: 45664 | C8: 4460 | D8: =IFERROR(C8/VLOOKUP(A8,Usinas!$A:$B,2,FALSE()),"") -> 6.3532764 | F8: =+G7+1 -> 45809 | G8: =+F8+29 -> 45838 | H8: =+F8 -> 45809 | I8: =SUMIFS($C$1:$C$366, $B$1:$B$366, ">="&F8, $B$1:$B$366, "<="&G8) -> 72286.9 | J8: =+I8/1000 -> 72.2869
A9: Batayporã | B9: 45665 | C9: 3524.3 | D9: =IFERROR(C9/VLOOKUP(A9,Usinas!$A:$B,2,FALSE()),"") -> 5.0203704 | F9: =+G8+1 -> 45839 | G9: =+F9+30 -> 45869 | H9: =+F9 -> 45839 | I9: =SUMIFS($C$1:$C$366, $B$1:$B$366, ">="&F9, $B$1:$B$366, "<="&G9) -> 88336.8 | J9: =+I9/1000 -> 88.3368
A10: Batayporã | B10: 45666 | C10: 4744.5 | D10: =IFERROR(C10/VLOOKUP(A10,Usinas!$A:$B,2,FALSE()),"") -> 6.758547 | F10: =+G9+1 -> 45870 | G10: =+F10+30 -> 45900 | H10: =+F10 -> 45870 | I10: =SUMIFS($C$1:$C$366, $B$1:$B$366, ">="&F10, $B$1:$B$366, "<="&G10) -> 93082.7 | J10: =+I10/1000 -> 93.0827
A11: Batayporã | B11: 45667 | C11: 3305 | D11: =IFERROR(C11/VLOOKUP(A11,Usinas!$A:$B,2,FALSE()),"") -> 4.7079772 | F11: =+G10+1 -> 45901 | G11: =+F11+29 -> 45930 | H11: =+F11 -> 45901 | I11: =SUMIFS($C$1:$C$366, $B$1:$B$366, ">="&F11, $B$1:$B$366, "<="&G11) -> 94433.4 | J11: =+I11/1000 -> 94.4334
A12: Batayporã | B12: 45668 | C12: 4671.1 | D12: =IFERROR(C12/VLOOKUP(A12,Usinas!$A:$B,2,FALSE()),"") -> 6.6539886 | F12: =+G11+1 -> 45931 | G12: =+F12+30 -> 45961 | H12: =+F12 -> 45931 | I12: =SUMIFS($C$1:$C$366, $B$1:$B$366, ">="&F12, $B$1:$B$366, "<="&G12) -> 95906.8 | J12: =+I12/1000 -> 95.9068
A13: Batayporã | B13: 45669 | C13: 4211.9 | D13: =IFERROR(C13/VLOOKUP(A13,Usinas!$A:$B,2,FALSE()),"") -> 5.9998575 | F13: =+G12+1 -> 45962 | G13: =+F13+29 -> 45991 | H13: =+F13 -> 45962 | I13: =SUMIFS($C$1:$C$366, $B$1:$B$366, ">="&F13, $B$1:$B$366, "<="&G13) -> 107980.6 | J13: =+I13/1000 -> 107.9806
A14: Batayporã | B14: 45670 | C14: 4327.1 | D14: =IFERROR(C14/VLOOKUP(A14,Usinas!$A:$B,2,FALSE()),"") -> 6.1639601 | F14: =+G13+1 -> 45992 | G14: =+F14+30 -> 46022 | H14: =+F14 -> 45992 | I14: =SUMIFS($C$1:$C$366, $B$1:$B$366, ">="&F14, $B$1:$B$366, "<="&G14) -> 106603.9 | J14: =+I14/1000 -> 106.6039
A15: Batayporã | B15: 45671 | C15: 4370 | D15: =IFERROR(C15/VLOOKUP(A15,Usinas!$A:$B,2,FALSE()),"") -> 6.2250712
A16: Batayporã | B16: 45672 | C16: 4324 | D16: =IFERROR(C16/VLOOKUP(A16,Usinas!$A:$B,2,FALSE()),"") -> 6.1595442
A17: Batayporã | B17: 45673 | C17: 4173.6 | D17: =IFERROR(C17/VLOOKUP(A17,Usinas!$A:$B,2,FALSE()),"") -> 5.9452991
A18: Batayporã | B18: 45674 | C18: 2490.4 | D18: =IFERROR(C18/VLOOKUP(A18,Usinas!$A:$B,2,FALSE()),"") -> 3.5475783
A19: Batayporã | B19: 45675 | C19: 2419.1 | D19: =IFERROR(C19/VLOOKUP(A19,Usinas!$A:$B,2,FALSE()),"") -> 3.4460114
A20: Batayporã | B20: 45676 | C20: 3206.2 | D20: =IFERROR(C20/VLOOKUP(A20,Usinas!$A:$B,2,FALSE()),"") -> 4.5672365
A21: Batayporã | B21: 45677 | C21: 2768 | D21: =IFERROR(C21/VLOOKUP(A21,Usinas!$A:$B,2,FALSE()),"") -> 3.9430199
A22: Batayporã | B22: 45678 | C22: 3998.4 | D22: =IFERROR(C22/VLOOKUP(A22,Usinas!$A:$B,2,FALSE()),"") -> 5.6957265
A23: Batayporã | B23: 45679 | C23: 2927.9 | D23: =IFERROR(C23/VLOOKUP(A23,Usinas!$A:$B,2,FALSE()),"") -> 4.1707977
A24: Batayporã | B24: 45680 | C24: 3035.9 | D24: =IFERROR(C24/VLOOKUP(A24,Usinas!$A:$B,2,FALSE()),"") -> 4.3246439
A25: Batayporã | B25: 45681 | C25: 4013.7 | D25: =IFERROR(C25/VLOOKUP(A25,Usinas!$A:$B,2,FALSE()),"") -> 5.7175214
A26: Batayporã | B26: 45682 | C26: 3852.9 | D26: =IFERROR(C26/VLOOKUP(A26,Usinas!$A:$B,2,FALSE()),"") -> 5.4884615
... A366: Batayporã | B366: 46022 | C366: 3694.2 | D366: =IFERROR(C366/VLOOKUP(A366,Usinas!$A:$B,2,FALSE()),"") -> 5.2623932

Sheet Novo Horizonte do Sul
A1: Unidade | B1: Data | C1: Geração (kWh) | D1: Yf Diário (kWh/kWp)
A2: Novo Horizonte do Sul | B2: 45659 | C2: 1838.7 | D2: =IFERROR(C2/VLOOKUP(A2,Usinas!$A:$B,2,FALSE()),"") -> 2.9608696 | F2: Geração Mensal | H2: Mês | I2: Kwh | J2: MWh
A3: Novo Horizonte do Sul | B3: 45660 | C3: 2731.7 | D3: =IFERROR(C3/VLOOKUP(A3,Usinas!$A:$B,2,FALSE()),"") -> 4.3988728 | F3: =+B2 -> 45659 | G3: =+F3+29 -> 45688 | H3: =+F3 -> 45659 | I3: =SUMIFS($C$1:$C$366, $B$1:$B$366, ">="&F3, $B$1:$B$366, "<="&G3) -> 83461.9 | J3: =+I3/1000 -> 83.4619
A4: Novo Horizonte do Sul | B4: 45661 | C4: 3144 | D4: =IFERROR(C4/VLOOKUP(A4,Usinas!$A:$B,2,FALSE()),"") -> 5.0628019 | F4: =+G3+1 -> 45689 | G4: =+F4+27 -> 45716 | H4: =+F4 -> 45689 | I4: =SUMIFS($C$1:$C$366, $B$1:$B$366, ">="&F4, $B$1:$B$366, "<="&G4) -> 76124.4 | J4: =+I4/1000 -> 76.1244
A5: Novo Horizonte do Sul | B5: 45662 | C5: 3472.1 | D5: =IFERROR(C5/VLOOKUP(A5,Usinas!$A:$B,2,FALSE()),"") -> 5.5911433 | F5: =+G4+1 -> 45717 | G5: =+F5+30 -> 45747 | H5: =+F5 -> 45717 | I5: =SUMIFS($C$1:$C$366, $B$1:$B$366, ">="&F5, $B$1:$B$366, "<="&G5) -> 89858.2 | J5: =+I5/1000 -> 89.8582
A6: Novo Horizonte do Sul | B6: 45663 | C6: 3397.4 | D6: =IFERROR(C6/VLOOKUP(A6,Usinas!$A:$B,2,FALSE()),"") -> 5.4708535 | F6: =+G5+1 -> 45748 | G6: =+F6+29 -> 45777 | H6: =+F6 -> 45748 | I6: =SUMIFS($C$1:$C$366, $B$1:$B$366, ">="&F6, $B$1:$B$366, "<="&G6) -> 62725.4 | J6: =+I6/1000 -> 62.7254
A7: Novo Horizonte do Sul | B7: 45664 | C7: 3375.8 | D7: =IFERROR(C7/VLOOKUP(A7,Usinas!$A:$B,2,FALSE()),"") -> 5.4360709 | F7: =+G6+1 -> 45778 | G7: =+F7+30 -> 45808 | H7: =+F7 -> 45778 | I7: =SUMIFS($C$1:$C$366, $B$1:$B$366, ">="&F7, $B$1:$B$366, "<="&G7) -> 78227.5 | J7: =+I7/1000 -> 78.2275
A8: Novo Horizonte do Sul | B8: 45665 | C8: 3146.5 | D8: =IFERROR(C8/VLOOKUP(A8,Usinas!$A:$B,2,FALSE()),"") -> 5.0668277 | F8: =+G7+1 -> 45809 | G8: =+F8+29 -> 45838 | H8: =+F8 -> 45809 | I8: =SUMIFS($C$1:$C$366, $B$1:$B$366, ">="&F8, $B$1:$B$366, "<="&G8) -> 60380.6 | J8: =+I8/1000 -> 60.3806
A9: Novo Horizonte do Sul | B9: 45666 | C9: 3235.6 | D9: =IFERROR(C9/VLOOKUP(A9,Usinas!$A:$B,2,FALSE()),"") -> 5.210306 | F9: =+G8+1 -> 45839 | G9: =+F9+30 -> 45869 | H9: =+F9 -> 45839 | I9: =SUMIFS($C$1:$C$366, $B$1:$B$366, ">="&F9, $B$1:$B$366, "<="&G9) -> 76551.2 | J9: =+I9/1000 -> 76.5512
A10: Novo Horizonte do Sul | B10: 45667 | C10: 2990.9 | D10: =IFERROR(C10/VLOOKUP(A10,Usinas!$A:$B,2,FALSE()),"") -> 4.8162641 | F10: =+G9+1 -> 45870 | G10: =+F10+30 -> 45900 | H10: =+F10 -> 45870 | I10: =SUMIFS($C$1:$C$366, $B$1:$B$366, ">="&F10, $B$1:$B$366, "<="&G10) -> 79815.6 | J10: =+I10/1000 -> 79.8156
A11: Novo Horizonte do Sul | B11: 45668 | C11: 3034 | D11: =IFERROR(C11/VLOOKUP(A11,Usinas!$A:$B,2,FALSE()),"") -> 4.8856683 | F11: =+G10+1 -> 45901 | G11: =+F11+29 -> 45930 | H11: =+F11 -> 45901 | I11: =SUMIFS($C$1:$C$366, $B$1:$B$366, ">="&F11, $B$1:$B$366, "<="&G11) -> 78203 | J11: =+I11/1000 -> 78.203
A12: Novo Horizonte do Sul | B12: 45669 | C12: 3316.5 | D12: =IFERROR(C12/VLOOKUP(A12,Usinas!$A:$B,2,FALSE()),"") -> 5.3405797 | F12: =+G11+1 -> 45931 | G12: =+F12+30 -> 45961 | H12: =+F12 -> 45931 | I12: =SUMIFS($C$1:$C$366, $B$1:$B$366, ">="&F12, $B$1:$B$366, "<="&G12) -> 73160.1 | J12: =+I12/1000 -> 73.1601
A13: Novo Horizonte do Sul | B13: 45670 | C13: 3271.8 | D13: =IFERROR(C13/VLOOKUP(A13,Usinas!$A:$B,2,FALSE()),"") -> 5.268599 | F13: =+G12+1 -> 45962 | G13: =+F13+29 -> 45991 | H13: =+F13 -> 45962 | I13: =SUMIFS($C$1:$C$366, $B$1:$B$366, ">="&F13, $B$1:$B$366, "<="&G13) -> 91030.5 | J13: =+I13/1000 -> 91.0305
A14: Novo Horizonte do Sul | B14: 45671 | C14: 2991 | D14: =IFERROR(C14/VLOOKUP(A14,Usinas!$A:$B,2,FALSE()),"") -> 4.8164251 | F14: =+G13+1 -> 45992 | G14: =+F14+30 -> 46022 | H14: =+F14 -> 45992 | I14: =SUMIFS($C$1:$C$366, $B$1:$B$366, ">="&F14, $B$1:$B$366, "<="&G14) -> 88631.7 | J14: =+I14/1000 -> 88.6317
A15: Novo Horizonte do Sul | B15: 45672 | C15: 3157.2 | D15: =IFERROR(C15/VLOOKUP(A15,Usinas!$A:$B,2,FALSE()),"") -> 5.084058
A16: Novo Horizonte do Sul | B16: 45673 | C16: 3240.1 | D16: =IFERROR(C16/VLOOKUP(A16,Usinas!$A:$B,2,FALSE()),"") -> 5.2175523
A17: Novo Horizonte do Sul | B17: 45674 | C17: 2894.7 | D17: =IFERROR(C17/VLOOKUP(A17,Usinas!$A:$B,2,FALSE()),"") -> 4.6613527 | J17: =+SUM(J3:J14) -> 938.1701
A18: Novo Horizonte do Sul | B18: 45675 | C18: 1963.6 | D18: =IFERROR(C18/VLOOKUP(A18,Usinas!$A:$B,2,FALSE()),"") -> 3.1619968
A19: Novo Horizonte do Sul | B19: 45676 | C19: 2656 | D19: =IFERROR(C19/VLOOKUP(A19,Usinas!$A:$B,2,FALSE()),"") -> 4.2769726
A20: Novo Horizonte do Sul | B20: 45677 | C20: 1379.4 | D20: =IFERROR(C20/VLOOKUP(A20,Usinas!$A:$B,2,FALSE()),"") -> 2.221256
A21: Novo Horizonte do Sul | B21: 45678 | C21: 2442.7 | D21: =IFERROR(C21/VLOOKUP(A21,Usinas!$A:$B,2,FALSE()),"") -> 3.9334944
A22: Novo Horizonte do Sul | B22: 45679 | C22: 2855.3 | D22: =IFERROR(C22/VLOOKUP(A22,Usinas!$A:$B,2,FALSE()),"") -> 4.5979066
A23: Novo Horizonte do Sul | B23: 45680 | C23: 1825.6 | D23: =IFERROR(C23/VLOOKUP(A23,Usinas!$A:$B,2,FALSE()),"") -> 2.9397746
A24: Novo Horizonte do Sul | B24: 45681 | C24: 3219.2 | D24: =IFERROR(C24/VLOOKUP(A24,Usinas!$A:$B,2,FALSE()),"") -> 5.1838969
A25: Novo Horizonte do Sul | B25: 45682 | C25: 2932.2 | D25: =IFERROR(C25/VLOOKUP(A25,Usinas!$A:$B,2,FALSE()),"") -> 4.7217391
A26: Novo Horizonte do Sul | B26: 45683 | C26: 2721.4 | D26: =IFERROR(C26/VLOOKUP(A26,Usinas!$A:$B,2,FALSE()),"") -> 4.3822866
A27: Novo Horizonte do Sul | B27: 45684 | C27: 2272 | D27: =IFERROR(C27/VLOOKUP(A27,Usinas!$A:$B,2,FALSE()),"") -> 3.6586151
A28: Novo Horizonte do Sul | B28: 45685 | C28: 2223.6 | D28: =IFERROR(C28/VLOOKUP(A28,Usinas!$A:$B,2,FALSE()),"") -> 3.5806763
A29: Novo Horizonte do Sul | B29: 45686 | C29: 2824.9 | D29: =IFERROR(C29/VLOOKUP(A29,Usinas!$A:$B,2,FALSE()),"") -> 4.5489533
... A364: Novo Horizonte do Sul | B364: 46022 | C364: 2728.3 | D364: =IFERROR(C364/VLOOKUP(A364,Usinas!$A:$B,2,FALSE()),"") -> 4.3933977

Sheet Dados_Consumo_Copasul

Sheet Formula Dados Copasul
D4: 45658 | E4: 45689 | F4: 45717 | G4: 45748 | H4: 45778 | I4: 45809 | J4: 45839 | K4: 45870 | L4: 45901 | M4: 45931 | N4: 45962 | O4: 45992 | Q4: Total | S4: Meia Mensal
A5: Grupo B | B5: Consomo Fora Ponta Grupo B (kWh) | D5: =+SUMIFS('Memória de Massa - 2025'!$H$1:$H$217,'Memória de Massa - 2025'!$A$1:$A$217,'Formula Dados Copasul'!$A5,'Memória de Massa - 2025'!$F$1:$F$217,'Formula Dados Copasul'!D$4) -> 44785.32 | E5: =+SUMIFS('Memória de Massa - 2025'!$H$1:$H$217,'Memória de Massa - 2025'!$A$1:$A$217,'Formula Dados Copasul'!$A5,'Memória de Massa - 2025'!$F$1:$F$217,'Formula Dados Copasul'!E$4) -> 47470.69 | F5: =+SUMIFS('Memória de Massa - 2025'!$H$1:$H$217,'Memória de Massa - 2025'!$A$1:$A$217,'Formula Dados Copasul'!$A5,'Memória de Massa - 2025'!$F$1:$F$217,'Formula Dados Copasul'!F$4) -> 42520.65 | G5: =+SUMIFS('Memória de Massa - 2025'!$H$1:$H$217,'Memória de Massa - 2025'!$A$1:$A$217,'Formula Dados Copasul'!$A5,'Memória de Massa - 2025'!$F$1:$F$217,'Formula Dados Copasul'!G$4) -> 37072.04 | H5: =+SUMIFS('Memória de Massa - 2025'!$H$1:$H$217,'Memória de Massa - 2025'!$A$1:$A$217,'Formula Dados Copasul'!$A5,'Memória de Massa - 2025'!$F$1:$F$217,'Formula Dados Copasul'!H$4) -> 34493.16 | I5: =+SUMIFS('Memória de Massa - 2025'!$H$1:$H$217,'Memória de Massa - 2025'!$A$1:$A$217,'Formula Dados Copasul'!$A5,'Memória de Massa - 2025'!$F$1:$F$217,'Formula Dados Copasul'!I$4) -> 32323.4 | J5: =+SUMIFS('Memória de Massa - 2025'!$H$1:$H$217,'Memória de Massa - 2025'!$A$1:$A$217,'Formula Dados Copasul'!$A5,'Memória de Massa - 2025'!$F$1:$F$217,'Formula Dados Copasul'!J$4) -> 34695.56 | K5: =+SUMIFS('Memória de Massa - 2025'!$H$1:$H$217,'Memória de Massa - 2025'!$A$1:$A$217,'Formula Dados Copasul'!$A5,'Memória de Massa - 2025'!$F$1:$F$217,'Formula Dados Copasul'!K$4) -> 37764.79 | ... O5: =+SUMIFS('Memória de Massa - 2025'!$H$1:$H$217,'Memória de Massa - 2025'!$A$1:$A$217,'Formula Dados Copasul'!$A5,'Memória de Massa - 2025'!$F$1:$F$217,'Formula Dados Copasul'!O$4) -> 48254.06 | Q5: =+SUM(D5:O5) -> 498958.69 | S5: =+Q5/12 -> 41579.891
A6: A4 Verde | B6: Consumo Fora Ponta Grupo A (kWh) | D6: =+SUMIFS('Memória de Massa - 2025'!$H$1:$H$217,'Memória de Massa - 2025'!$A$1:$A$217,'Formula Dados Copasul'!$A6,'Memória de Massa - 2025'!$F$1:$F$217,'Formula Dados Copasul'!D$4) -> 50942.72 | E6: =+SUMIFS('Memória de Massa - 2025'!$H$1:$H$217,'Memória de Massa - 2025'!$A$1:$A$217,'Formula Dados Copasul'!$A6,'Memória de Massa - 2025'!$F$1:$F$217,'Formula Dados Copasul'!E$4) -> 200728.75 | F6: =+SUMIFS('Memória de Massa - 2025'!$H$1:$H$217,'Memória de Massa - 2025'!$A$1:$A$217,'Formula Dados Copasul'!$A6,'Memória de Massa - 2025'!$F$1:$F$217,'Formula Dados Copasul'!F$4) -> 207178.06 | G6: =+SUMIFS('Memória de Massa - 2025'!$H$1:$H$217,'Memória de Massa - 2025'!$A$1:$A$217,'Formula Dados Copasul'!$A6,'Memória de Massa - 2025'!$F$1:$F$217,'Formula Dados Copasul'!G$4) -> 75954.61 | H6: =+SUMIFS('Memória de Massa - 2025'!$H$1:$H$217,'Memória de Massa - 2025'!$A$1:$A$217,'Formula Dados Copasul'!$A6,'Memória de Massa - 2025'!$F$1:$F$217,'Formula Dados Copasul'!H$4) -> 87080.03 | I6: =+SUMIFS('Memória de Massa - 2025'!$H$1:$H$217,'Memória de Massa - 2025'!$A$1:$A$217,'Formula Dados Copasul'!$A6,'Memória de Massa - 2025'!$F$1:$F$217,'Formula Dados Copasul'!I$4) -> 147398.37 | J6: =+SUMIFS('Memória de Massa - 2025'!$H$1:$H$217,'Memória de Massa - 2025'!$A$1:$A$217,'Formula Dados Copasul'!$A6,'Memória de Massa - 2025'!$F$1:$F$217,'Formula Dados Copasul'!J$4) -> 307662.77 | K6: =+SUMIFS('Memória de Massa - 2025'!$H$1:$H$217,'Memória de Massa - 2025'!$A$1:$A$217,'Formula Dados Copasul'!$A6,'Memória de Massa - 2025'!$F$1:$F$217,'Formula Dados Copasul'!K$4) -> 309712.87 | ... O6: =+SUMIFS('Memória de Massa - 2025'!$H$1:$H$217,'Memória de Massa - 2025'!$A$1:$A$217,'Formula Dados Copasul'!$A6,'Memória de Massa - 2025'!$F$1:$F$217,'Formula Dados Copasul'!O$4) -> 11745.55 | Q6: =+SUM(D6:O6) -> 1504995.5 | S6: =+Q6/12 -> 125416.29
A7: A3A rural | B7: Consumo Fora Ponta Grupo A3A Rural (kWh) | D7: =+SUMIFS('Memória de Massa - 2025'!$H$1:$H$217,'Memória de Massa - 2025'!$A$1:$A$217,'Formula Dados Copasul'!$A7,'Memória de Massa - 2025'!$F$1:$F$217,'Formula Dados Copasul'!D$4) -> 72928.49 | E7: =+SUMIFS('Memória de Massa - 2025'!$H$1:$H$217,'Memória de Massa - 2025'!$A$1:$A$217,'Formula Dados Copasul'!$A7,'Memória de Massa - 2025'!$F$1:$F$217,'Formula Dados Copasul'!E$4) -> 212798.25 | F7: =+SUMIFS('Memória de Massa - 2025'!$H$1:$H$217,'Memória de Massa - 2025'!$A$1:$A$217,'Formula Dados Copasul'!$A7,'Memória de Massa - 2025'!$F$1:$F$217,'Formula Dados Copasul'!F$4) -> 177578.42 | G7: =+SUMIFS('Memória de Massa - 2025'!$H$1:$H$217,'Memória de Massa - 2025'!$A$1:$A$217,'Formula Dados Copasul'!$A7,'Memória de Massa - 2025'!$F$1:$F$217,'Formula Dados Copasul'!G$4) -> 84395.43 | H7: =+SUMIFS('Memória de Massa - 2025'!$H$1:$H$217,'Memória de Massa - 2025'!$A$1:$A$217,'Formula Dados Copasul'!$A7,'Memória de Massa - 2025'!$F$1:$F$217,'Formula Dados Copasul'!H$4) -> 106720.74 | I7: =+SUMIFS('Memória de Massa - 2025'!$H$1:$H$217,'Memória de Massa - 2025'!$A$1:$A$217,'Formula Dados Copasul'!$A7,'Memória de Massa - 2025'!$F$1:$F$217,'Formula Dados Copasul'!I$4) -> 183159.59 | J7: =+SUMIFS('Memória de Massa - 2025'!$H$1:$H$217,'Memória de Massa - 2025'!$A$1:$A$217,'Formula Dados Copasul'!$A7,'Memória de Massa - 2025'!$F$1:$F$217,'Formula Dados Copasul'!J$4) -> 223302.56 | K7: =+SUMIFS('Memória de Massa - 2025'!$H$1:$H$217,'Memória de Massa - 2025'!$A$1:$A$217,'Formula Dados Copasul'!$A7,'Memória de Massa - 2025'!$F$1:$F$217,'Formula Dados Copasul'!K$4) -> 130522.46 | ... O7: =+SUMIFS('Memória de Massa - 2025'!$H$1:$H$217,'Memória de Massa - 2025'!$A$1:$A$217,'Formula Dados Copasul'!$A7,'Memória de Massa - 2025'!$F$1:$F$217,'Formula Dados Copasul'!O$4) -> 15428.7 | Q7: =+SUM(D7:O7) -> 1245343.7 | S7: =+Q7/12 -> 103778.64
B9: Total Fora Ponta (kWh) | D9: =+SUM(D5:D7) -> 168656.53 | E9: =+SUM(E5:E7) -> 460997.69 | F9: =+SUM(F5:F7) -> 427277.13 | G9: =+SUM(G5:G7) -> 197422.08 | H9: =+SUM(H5:H7) -> 228293.93 | I9: =+SUM(I5:I7) -> 362881.36 | J9: =+SUM(J5:J7) -> 565660.89 | K9: =+SUM(K5:K7) -> 478000.12 | ... O9: =+SUM(O5:O7) -> 75428.31 | Q9: =+SUM(D9:O9) -> 3249297.9 | S9: =+Q9/12 -> 270774.83
A11: A4 Verde | B11: Consumo Ponta Grupo A (kWh) | D11: =+SUMIFS('Memória de Massa - 2025'!$G$1:$G$217,'Memória de Massa - 2025'!$A$1:$A$217,'Formula Dados Copasul'!$A11,'Memória de Massa - 2025'!$F$1:$F$217,'Formula Dados Copasul'!D$4) -> 10827.94 | E11: =+SUMIFS('Memória de Massa - 2025'!$G$1:$G$217,'Memória de Massa - 2025'!$A$1:$A$217,'Formula Dados Copasul'!$A11,'Memória de Massa - 2025'!$F$1:$F$217,'Formula Dados Copasul'!E$4) -> 37839.9 | F11: =+SUMIFS('Memória de Massa - 2025'!$G$1:$G$217,'Memória de Massa - 2025'!$A$1:$A$217,'Formula Dados Copasul'!$A11,'Memória de Massa - 2025'!$F$1:$F$217,'Formula Dados Copasul'!F$4) -> 27093.4 | G11: =+SUMIFS('Memória de Massa - 2025'!$G$1:$G$217,'Memória de Massa - 2025'!$A$1:$A$217,'Formula Dados Copasul'!$A11,'Memória de Massa - 2025'!$F$1:$F$217,'Formula Dados Copasul'!G$4) -> 4120.62 | H11: =+SUMIFS('Memória de Massa - 2025'!$G$1:$G$217,'Memória de Massa - 2025'!$A$1:$A$217,'Formula Dados Copasul'!$A11,'Memória de Massa - 2025'!$F$1:$F$217,'Formula Dados Copasul'!H$4) -> 7310.48 | I11: =+SUMIFS('Memória de Massa - 2025'!$G$1:$G$217,'Memória de Massa - 2025'!$A$1:$A$217,'Formula Dados Copasul'!$A11,'Memória de Massa - 2025'!$F$1:$F$217,'Formula Dados Copasul'!I$4) -> 22180.07 | J11: =+SUMIFS('Memória de Massa - 2025'!$G$1:$G$217,'Memória de Massa - 2025'!$A$1:$A$217,'Formula Dados Copasul'!$A11,'Memória de Massa - 2025'!$F$1:$F$217,'Formula Dados Copasul'!J$4) -> 53060.15 | K11: =+SUMIFS('Memória de Massa - 2025'!$G$1:$G$217,'Memória de Massa - 2025'!$A$1:$A$217,'Formula Dados Copasul'!$A11,'Memória de Massa - 2025'!$F$1:$F$217,'Formula Dados Copasul'!K$4) -> 44066.23 | ... O11: =+SUMIFS('Memória de Massa - 2025'!$G$1:$G$217,'Memória de Massa - 2025'!$A$1:$A$217,'Formula Dados Copasul'!$A11,'Memória de Massa - 2025'!$F$1:$F$217,'Formula Dados Copasul'!O$4) -> 2595.31 | Q11: =+SUM(D11:O11) -> 224581.82 | S11: =+Q11/12 -> 18715.152
A12: A3A rural | B12: Consumo Ponta Grupo A3A (kWh) | D12: =+SUMIFS('Memória de Massa - 2025'!$G$1:$G$217,'Memória de Massa - 2025'!$A$1:$A$217,'Formula Dados Copasul'!$A12,'Memória de Massa - 2025'!$F$1:$F$217,'Formula Dados Copasul'!D$4) -> 9264.15 | E12: =+SUMIFS('Memória de Massa - 2025'!$G$1:$G$217,'Memória de Massa - 2025'!$A$1:$A$217,'Formula Dados Copasul'!$A12,'Memória de Massa - 2025'!$F$1:$F$217,'Formula Dados Copasul'!E$4) -> 19948.64 | F12: =+SUMIFS('Memória de Massa - 2025'!$G$1:$G$217,'Memória de Massa - 2025'!$A$1:$A$217,'Formula Dados Copasul'!$A12,'Memória de Massa - 2025'!$F$1:$F$217,'Formula Dados Copasul'!F$4) -> 14932.89 | G12: =+SUMIFS('Memória de Massa - 2025'!$G$1:$G$217,'Memória de Massa - 2025'!$A$1:$A$217,'Formula Dados Copasul'!$A12,'Memória de Massa - 2025'!$F$1:$F$217,'Formula Dados Copasul'!G$4) -> 2769.48 | H12: =+SUMIFS('Memória de Massa - 2025'!$G$1:$G$217,'Memória de Massa - 2025'!$A$1:$A$217,'Formula Dados Copasul'!$A12,'Memória de Massa - 2025'!$F$1:$F$217,'Formula Dados Copasul'!H$4) -> 7312.1 | I12: =+SUMIFS('Memória de Massa - 2025'!$G$1:$G$217,'Memória de Massa - 2025'!$A$1:$A$217,'Formula Dados Copasul'!$A12,'Memória de Massa - 2025'!$F$1:$F$217,'Formula Dados Copasul'!I$4) -> 19556.78 | J12: =+SUMIFS('Memória de Massa - 2025'!$G$1:$G$217,'Memória de Massa - 2025'!$A$1:$A$217,'Formula Dados Copasul'!$A12,'Memória de Massa - 2025'!$F$1:$F$217,'Formula Dados Copasul'!J$4) -> 37585.8 | K12: =+SUMIFS('Memória de Massa - 2025'!$G$1:$G$217,'Memória de Massa - 2025'!$A$1:$A$217,'Formula Dados Copasul'!$A12,'Memória de Massa - 2025'!$F$1:$F$217,'Formula Dados Copasul'!K$4) -> 19255.01 | ... O12: =+SUMIFS('Memória de Massa - 2025'!$G$1:$G$217,'Memória de Massa - 2025'!$A$1:$A$217,'Formula Dados Copasul'!$A12,'Memória de Massa - 2025'!$F$1:$F$217,'Formula Dados Copasul'!O$4) -> 1514.84 | Q12: =+SUM(D12:O12) -> 138419.85 | S12: =+Q12/12 -> 11534.988
B14: Total Ponta (kWh) | D14: =+SUM(D11:D12) -> 20092.09 | E14: =+SUM(E11:E12) -> 57788.54 | F14: =+SUM(F11:F12) -> 42026.29 | G14: =+SUM(G11:G12) -> 6890.1 | H14: =+SUM(H11:H12) -> 14622.58 | I14: =+SUM(I11:I12) -> 41736.85 | J14: =+SUM(J11:J12) -> 90645.95 | K14: =+SUM(K11:K12) -> 63321.24 | ... O14: =+SUM(O11:O12) -> 4110.15 | Q14: =+SUM(D14:O14) -> 363001.67 | S14: =+Q14/12 -> 30250.139
B17: Total Consumo (kWh) | D17: =+SUM(D14,D9) -> 188748.62 | E17: =+SUM(E14,E9) -> 518786.23 | F17: =+SUM(F14,F9) -> 469303.42 | G17: =+SUM(G14,G9) -> 204312.18 | H17: =+SUM(H14,H9) -> 242916.51 | I17: =+SUM(I14,I9) -> 404618.21 | J17: =+SUM(J14,J9) -> 656306.84 | K17: =+SUM(K14,K9) -> 541321.36 | ... O17: =+SUM(O14,O9) -> 79538.46 | Q17: =+SUM(Q14,Q9) -> 3612299.6 | S17: =+Q17/12 -> 301024.96
A20: SiIos Novo Horizonte do Sul | B20: Produçao Usina 1 | D20: =+SUMIFS('Memória de Massa - 2025'!$K$1:$K$217,'Memória de Massa - 2025'!$B$1:$B$217,$A20,'Memória de Massa - 2025'!$F$1:$F$217,'Formula Dados Copasul'!D$4) -> 83461.9 | E20: =+SUMIFS('Memória de Massa - 2025'!$K$1:$K$217,'Memória de Massa - 2025'!$B$1:$B$217,$A20,'Memória de Massa - 2025'!$F$1:$F$217,'Formula Dados Copasul'!E$4) -> 76124.4 | F20: =+SUMIFS('Memória de Massa - 2025'!$K$1:$K$217,'Memória de Massa - 2025'!$B$1:$B$217,$A20,'Memória de Massa - 2025'!$F$1:$F$217,'Formula Dados Copasul'!F$4) -> 89858.2 | G20: =+SUMIFS('Memória de Massa - 2025'!$K$1:$K$217,'Memória de Massa - 2025'!$B$1:$B$217,$A20,'Memória de Massa - 2025'!$F$1:$F$217,'Formula Dados Copasul'!G$4) -> 62725.4 | H20: =+SUMIFS('Memória de Massa - 2025'!$K$1:$K$217,'Memória de Massa - 2025'!$B$1:$B$217,$A20,'Memória de Massa - 2025'!$F$1:$F$217,'Formula Dados Copasul'!H$4) -> 78227.5 | I20: =+SUMIFS('Memória de Massa - 2025'!$K$1:$K$217,'Memória de Massa - 2025'!$B$1:$B$217,$A20,'Memória de Massa - 2025'!$F$1:$F$217,'Formula Dados Copasul'!I$4) -> 60380.6 | J20: =+SUMIFS('Memória de Massa - 2025'!$K$1:$K$217,'Memória de Massa - 2025'!$B$1:$B$217,$A20,'Memória de Massa - 2025'!$F$1:$F$217,'Formula Dados Copasul'!J$4) -> 76551.2 | K20: =+SUMIFS('Memória de Massa - 2025'!$K$1:$K$217,'Memória de Massa - 2025'!$B$1:$B$217,$A20,'Memória de Massa - 2025'!$F$1:$F$217,'Formula Dados Copasul'!K$4) -> 79815.6 | ... O20: =+SUMIFS('Memória de Massa - 2025'!$K$1:$K$217,'Memória de Massa - 2025'!$B$1:$B$217,$A20,'Memória de Massa - 2025'!$F$1:$F$217,'Formula Dados Copasul'!O$4) -> 88631.7 | Q20: =+SUM(D20:O20) -> 938170.1 | S20: =+Q20/12 -> 78180.842
A21: Silos Batayporã | B21: Produção Usina 2 | D21: =+SUMIFS('Memória de Massa - 2025'!$K$1:$K$217,'Memória de Massa - 2025'!$B$1:$B$217,$A21,'Memória de Massa - 2025'!$F$1:$F$217,'Formula Dados Copasul'!D$4) -> 114259 | E21: =+SUMIFS('Memória de Massa - 2025'!$K$1:$K$217,'Memória de Massa - 2025'!$B$1:$B$217,$A21,'Memória de Massa - 2025'!$F$1:$F$217,'Formula Dados Copasul'!E$4) -> 91131.9 | F21: =+SUMIFS('Memória de Massa - 2025'!$K$1:$K$217,'Memória de Massa - 2025'!$B$1:$B$217,$A21,'Memória de Massa - 2025'!$F$1:$F$217,'Formula Dados Copasul'!F$4) -> 103061.9 | G21: =+SUMIFS('Memória de Massa - 2025'!$K$1:$K$217,'Memória de Massa - 2025'!$B$1:$B$217,$A21,'Memória de Massa - 2025'!$F$1:$F$217,'Formula Dados Copasul'!G$4) -> 73709.7 | H21: =+SUMIFS('Memória de Massa - 2025'!$K$1:$K$217,'Memória de Massa - 2025'!$B$1:$B$217,$A21,'Memória de Massa - 2025'!$F$1:$F$217,'Formula Dados Copasul'!H$4) -> 91616.6 | I21: =+SUMIFS('Memória de Massa - 2025'!$K$1:$K$217,'Memória de Massa - 2025'!$B$1:$B$217,$A21,'Memória de Massa - 2025'!$F$1:$F$217,'Formula Dados Copasul'!I$4) -> 72286.9 | J21: =+SUMIFS('Memória de Massa - 2025'!$K$1:$K$217,'Memória de Massa - 2025'!$B$1:$B$217,$A21,'Memória de Massa - 2025'!$F$1:$F$217,'Formula Dados Copasul'!J$4) -> 88336.8 | K21: =+SUMIFS('Memória de Massa - 2025'!$K$1:$K$217,'Memória de Massa - 2025'!$B$1:$B$217,$A21,'Memória de Massa - 2025'!$F$1:$F$217,'Formula Dados Copasul'!K$4) -> 93082.7 | ... O21: =+SUMIFS('Memória de Massa - 2025'!$K$1:$K$217,'Memória de Massa - 2025'!$B$1:$B$217,$A21,'Memória de Massa - 2025'!$F$1:$F$217,'Formula Dados Copasul'!O$4) -> 106603.9 | Q21: =+SUM(D21:O21) -> 1132410.2 | S21: =+Q21/12 -> 94367.517
A22: Silos Amandina | B22: Produção Usina 3 | D22: =+SUMIFS('Memória de Massa - 2025'!$K$1:$K$217,'Memória de Massa - 2025'!$B$1:$B$217,$A22,'Memória de Massa - 2025'!$F$1:$F$217,'Formula Dados Copasul'!D$4) -> 0 | E22: =+SUMIFS('Memória de Massa - 2025'!$K$1:$K$217,'Memória de Massa - 2025'!$B$1:$B$217,$A22,'Memória de Massa - 2025'!$F$1:$F$217,'Formula Dados Copasul'!E$4) -> 190.1 | F22: =+SUMIFS('Memória de Massa - 2025'!$K$1:$K$217,'Memória de Massa - 2025'!$B$1:$B$217,$A22,'Memória de Massa - 2025'!$F$1:$F$217,'Formula Dados Copasul'!F$4) -> 7913.8 | G22: =+SUMIFS('Memória de Massa - 2025'!$K$1:$K$217,'Memória de Massa - 2025'!$B$1:$B$217,$A22,'Memória de Massa - 2025'!$F$1:$F$217,'Formula Dados Copasul'!G$4) -> 23902.8 | H22: =+SUMIFS('Memória de Massa - 2025'!$K$1:$K$217,'Memória de Massa - 2025'!$B$1:$B$217,$A22,'Memória de Massa - 2025'!$F$1:$F$217,'Formula Dados Copasul'!H$4) -> 28781.7 | I22: =+SUMIFS('Memória de Massa - 2025'!$K$1:$K$217,'Memória de Massa - 2025'!$B$1:$B$217,$A22,'Memória de Massa - 2025'!$F$1:$F$217,'Formula Dados Copasul'!I$4) -> 20798.2 | J22: =+SUMIFS('Memória de Massa - 2025'!$K$1:$K$217,'Memória de Massa - 2025'!$B$1:$B$217,$A22,'Memória de Massa - 2025'!$F$1:$F$217,'Formula Dados Copasul'!J$4) -> 37317.8 | K22: =+SUMIFS('Memória de Massa - 2025'!$K$1:$K$217,'Memória de Massa - 2025'!$B$1:$B$217,$A22,'Memória de Massa - 2025'!$F$1:$F$217,'Formula Dados Copasul'!K$4) -> 16177.9 | ... O22: =+SUMIFS('Memória de Massa - 2025'!$K$1:$K$217,'Memória de Massa - 2025'!$B$1:$B$217,$A22,'Memória de Massa - 2025'!$F$1:$F$217,'Formula Dados Copasul'!O$4) -> 19968.1 | Q22: =+SUM(D22:O22) -> 269574.1 | S22: =+Q22/12 -> 22464.508
B24: Total Produção (kWH) | D24: =+SUM(D20:D22) -> 197720.9 | E24: =+SUM(E20:E22) -> 167446.4 | F24: =+SUM(F20:F22) -> 200833.9 | G24: =+SUM(G20:G22) -> 160337.9 | H24: =+SUM(H20:H22) -> 198625.8 | I24: =+SUM(I20:I22) -> 153465.7 | J24: =+SUM(J20:J22) -> 202205.8 | K24: =+SUM(K20:K22) -> 189076.2 | ... O24: =+SUM(O20:O22) -> 215203.7 | Q24: =+SUM(Q20:Q22) -> 2340154.4 | S24: =+SUM(S20:S22) -> 195012.87
A26: SiIos Novo Horizonte do Sul | B26: Compensão usina 1 | D26: =+SUMIFS('Memória de Massa - 2025'!$L$1:$L$217,'Memória de Massa - 2025'!$B$1:$B$217,$A26,'Memória de Massa - 2025'!$F$1:$F$217,'Formula Dados Copasul'!D$4) -> 54986 | E26: =+SUMIFS('Memória de Massa - 2025'!$L$1:$L$217,'Memória de Massa - 2025'!$B$1:$B$217,$A26,'Memória de Massa - 2025'!$F$1:$F$217,'Formula Dados Copasul'!E$4) -> 188910 | F26: =+SUMIFS('Memória de Massa - 2025'!$L$1:$L$217,'Memória de Massa - 2025'!$B$1:$B$217,$A26,'Memória de Massa - 2025'!$F$1:$F$217,'Formula Dados Copasul'!F$4) -> 32411 | G26: =+SUMIFS('Memória de Massa - 2025'!$L$1:$L$217,'Memória de Massa - 2025'!$B$1:$B$217,$A26,'Memória de Massa - 2025'!$F$1:$F$217,'Formula Dados Copasul'!G$4) -> 41488 | H26: =+SUMIFS('Memória de Massa - 2025'!$L$1:$L$217,'Memória de Massa - 2025'!$B$1:$B$217,$A26,'Memória de Massa - 2025'!$F$1:$F$217,'Formula Dados Copasul'!H$4) -> 55127 | I26: =+SUMIFS('Memória de Massa - 2025'!$L$1:$L$217,'Memória de Massa - 2025'!$B$1:$B$217,$A26,'Memória de Massa - 2025'!$F$1:$F$217,'Formula Dados Copasul'!I$4) -> 24600 | J26: =+SUMIFS('Memória de Massa - 2025'!$L$1:$L$217,'Memória de Massa - 2025'!$B$1:$B$217,$A26,'Memória de Massa - 2025'!$F$1:$F$217,'Formula Dados Copasul'!J$4) -> 10848 | K26: =+SUMIFS('Memória de Massa - 2025'!$L$1:$L$217,'Memória de Massa - 2025'!$B$1:$B$217,$A26,'Memória de Massa - 2025'!$F$1:$F$217,'Formula Dados Copasul'!K$4) -> 37261 | ... O26: =+SUMIFS('Memória de Massa - 2025'!$L$1:$L$217,'Memória de Massa - 2025'!$B$1:$B$217,$A26,'Memória de Massa - 2025'!$F$1:$F$217,'Formula Dados Copasul'!O$4) -> 8737 | Q26: =+SUM(D26:O26) -> 547684 | S26: =+Q26/12 -> 45640.333
A27: Silos Batayporã | B27: Compensão usina 2 | D27: =+SUMIFS('Memória de Massa - 2025'!$L$1:$L$217,'Memória de Massa - 2025'!$B$1:$B$217,$A27,'Memória de Massa - 2025'!$F$1:$F$217,'Formula Dados Copasul'!D$4) -> 6785 | E27: =+SUMIFS('Memória de Massa - 2025'!$L$1:$L$217,'Memória de Massa - 2025'!$B$1:$B$217,$A27,'Memória de Massa - 2025'!$F$1:$F$217,'Formula Dados Copasul'!E$4) -> 36315 | F27: =+SUMIFS('Memória de Massa - 2025'!$L$1:$L$217,'Memória de Massa - 2025'!$B$1:$B$217,$A27,'Memória de Massa - 2025'!$F$1:$F$217,'Formula Dados Copasul'!F$4) -> 63697 | G27: =+SUMIFS('Memória de Massa - 2025'!$L$1:$L$217,'Memória de Massa - 2025'!$B$1:$B$217,$A27,'Memória de Massa - 2025'!$F$1:$F$217,'Formula Dados Copasul'!G$4) -> 38586 | H27: =+SUMIFS('Memória de Massa - 2025'!$L$1:$L$217,'Memória de Massa - 2025'!$B$1:$B$217,$A27,'Memória de Massa - 2025'!$F$1:$F$217,'Formula Dados Copasul'!H$4) -> 37159 | I27: =+SUMIFS('Memória de Massa - 2025'!$L$1:$L$217,'Memória de Massa - 2025'!$B$1:$B$217,$A27,'Memória de Massa - 2025'!$F$1:$F$217,'Formula Dados Copasul'!I$4) -> 36580 | J27: =+SUMIFS('Memória de Massa - 2025'!$L$1:$L$217,'Memória de Massa - 2025'!$B$1:$B$217,$A27,'Memória de Massa - 2025'!$F$1:$F$217,'Formula Dados Copasul'!J$4) -> 64186 | K27: =+SUMIFS('Memória de Massa - 2025'!$L$1:$L$217,'Memória de Massa - 2025'!$B$1:$B$217,$A27,'Memória de Massa - 2025'!$F$1:$F$217,'Formula Dados Copasul'!K$4) -> 59224 | ... O27: =+SUMIFS('Memória de Massa - 2025'!$L$1:$L$217,'Memória de Massa - 2025'!$B$1:$B$217,$A27,'Memória de Massa - 2025'!$F$1:$F$217,'Formula Dados Copasul'!O$4) -> 5604 | Q27: =+SUM(D27:O27) -> 389018 | S27: =+Q27/12 -> 32418.167
A28: Silos Amandina | B28: Compensão usina 3 | D28: =+SUMIFS('Memória de Massa - 2025'!$L$1:$L$217,'Memória de Massa - 2025'!$B$1:$B$217,$A28,'Memória de Massa - 2025'!$F$1:$F$217,'Formula Dados Copasul'!D$4) -> 0 | E28: =+SUMIFS('Memória de Massa - 2025'!$L$1:$L$217,'Memória de Massa - 2025'!$B$1:$B$217,$A28,'Memória de Massa - 2025'!$F$1:$F$217,'Formula Dados Copasul'!E$4) -> 0 | F28: =+SUMIFS('Memória de Massa - 2025'!$L$1:$L$217,'Memória de Massa - 2025'!$B$1:$B$217,$A28,'Memória de Massa - 2025'!$F$1:$F$217,'Formula Dados Copasul'!F$4) -> 419 | G28: =+SUMIFS('Memória de Massa - 2025'!$L$1:$L$217,'Memória de Massa - 2025'!$B$1:$B$217,$A28,'Memória de Massa - 2025'!$F$1:$F$217,'Formula Dados Copasul'!G$4) -> 1423 | H28: =+SUMIFS('Memória de Massa - 2025'!$L$1:$L$217,'Memória de Massa - 2025'!$B$1:$B$217,$A28,'Memória de Massa - 2025'!$F$1:$F$217,'Formula Dados Copasul'!H$4) -> 9127 | I28: =+SUMIFS('Memória de Massa - 2025'!$L$1:$L$217,'Memória de Massa - 2025'!$B$1:$B$217,$A28,'Memória de Massa - 2025'!$F$1:$F$217,'Formula Dados Copasul'!I$4) -> 7190 | J28: =+SUMIFS('Memória de Massa - 2025'!$L$1:$L$217,'Memória de Massa - 2025'!$B$1:$B$217,$A28,'Memória de Massa - 2025'!$F$1:$F$217,'Formula Dados Copasul'!J$4) -> 9165 | K28: =+SUMIFS('Memória de Massa - 2025'!$L$1:$L$217,'Memória de Massa - 2025'!$B$1:$B$217,$A28,'Memória de Massa - 2025'!$F$1:$F$217,'Formula Dados Copasul'!K$4) -> 5142 | ... O28: =+SUMIFS('Memória de Massa - 2025'!$L$1:$L$217,'Memória de Massa - 2025'!$B$1:$B$217,$A28,'Memória de Massa - 2025'!$F$1:$F$217,'Formula Dados Copasul'!O$4) -> 16944 | Q28: =+SUM(D28:O28) -> 94200 | S28: =+Q28/12 -> 7850
B30: Total Compensação (kWH) | D30: =+SUM(D26:D28) -> 61771 | E30: =+SUM(E26:E28) -> 225225 | F30: =+SUM(F26:F28) -> 96527 | G30: =+SUM(G26:G28) -> 81497 | H30: =+SUM(H26:H28) -> 101413 | I30: =+SUM(I26:I28) -> 68370 | J30: =+SUM(J26:J28) -> 84199 | K30: =+SUM(K26:K28) -> 101627 | ... O30: =+SUM(O26:O28) -> 31285 | Q30: =+SUM(Q26:Q28) -> 1030902 | S30: =+SUM(S26:S28) -> 85908.5

Sheet Memória de Massa - 2025
B1: Nome | C1: CNPJ | D1: UC | E1: Grupo | F1: Mês | G1: Consumo Ponta (kWh) | H1: Consumo Fora Ponta (kWh) | I1: Demanda Ponta (kW) | J1: Demanda Fora Ponta (kW) | K1: Energia Gerada (kWh) | L1: Energia Compensada (kWh) | O1: Energia Sobrando | P1: Energia Gerada Pos reparação | R1: Compensação Fora Ponta
A2: Grupo B | B2: Galpão AE | C2: 03.902.129/0001-83 | D2: 10/169099-9 | E2: B3 - Comercial | F2: 45992 | H2: 518
A3: Grupo B | B3: Galpão AE | C3: 03.902.129/0001-83 | D3: 10/169099-9 | E3: B3 - Comercial | F3: 45962 | H3: 467
A4: Grupo B | B4: Galpão AE | C4: 03.902.129/0001-83 | D4: 10/169099-9 | E4: B3 - Comercial | F4: 45931 | H4: 596
A5: Grupo B | B5: Galpão AE | C5: 03.902.129/0001-83 | D5: 10/169099-9 | E5: B3 - Comercial | F5: 45901 | H5: 523
A6: Grupo B | B6: Galpão AE | C6: 03.902.129/0001-83 | D6: 10/169099-9 | E6: B3 - Comercial | F6: 45870 | H6: 1194
A7: Grupo B | B7: Galpão AE | C7: 03.902.129/0001-83 | D7: 10/169099-9 | E7: B3 - Comercial | F7: 45839 | H7: 1194
A8: Grupo B | B8: Galpão AE | C8: 03.902.129/0001-83 | D8: 10/169099-9 | E8: B3 - Comercial | F8: 45809 | H8: 275
A9: Grupo B | B9: Galpão AE | C9: 03.902.129/0001-83 | D9: 10/169099-9 | E9: B3 - Comercial | F9: 45778 | H9: 272
A10: Grupo B | B10: Galpão AE | C10: 03.902.129/0001-83 | D10: 10/169099-9 | E10: B3 - Comercial | F10: 45748 | H10: 259
A11: Grupo B | B11: Galpão AE | C11: 03.902.129/0001-83 | D11: 10/169099-9 | E11: B3 - Comercial | F11: 45717 | H11: 258
A12: Grupo B | B12: Galpão AE | C12: 03.902.129/0001-83 | D12: 10/169099-9 | E12: B3 - Comercial | F12: 45689 | H12: 305
A13: Grupo B | B13: Galpão AE | C13: 03.902.129/0001-83 | D13: 10/169099-9 | E13: B3 - Comercial | F13: 45658 | H13: 264
... A97: Grupo B | B97: Subestação Fiação | C97: 03.902.129/0015-89 | D97: 10/2418582-9 | E97: B3 - Comercial | F97: 45658 | H97: 1554
A98: A4 Verde | B98: SiIos Novo Horizonte do Sul | C98: 03.902.129/0020-46 | D98: 10/3184070-5 | E98: Verde A4 - Industrial | F98: 45992 | G98: 1502.26 | H98: 7234.75 | I98: 56.45 | J98: 112.3 | K98: 88631.7 | L98: 8737
A99: A4 Verde | B99: SiIos Novo Horizonte do Sul | C99: 03.902.129/0020-46 | D99: 10/3184070-5 | E99: Verde A4 - Industrial | F99: 45962 | G99: 1235.14 | H99: 6608.62 | I99: 102.14 | J99: 108.19 | K99: 91030.5 | L99: 7844
A100: A4 Verde | B100: SiIos Novo Horizonte do Sul | C100: 03.902.129/0020-46 | D100: 10/3184070-5 | E100: Verde A4 - Industrial | F100: 45931 | G100: 1434.05 | H100: 8440.99 | I100: 38.3 | J100: 147.17 | K100: 73160.1 | L100: 9875
A101: A4 Verde | B101: SiIos Novo Horizonte do Sul | C101: 03.902.129/0020-46 | D101: 10/3184070-5 | E101: Verde A4 - Industrial | F101: 45901 | G101: 9308.38 | H101: 66288.6 | I101: 821.18 | J101: 782.88 | K101: 78203 | L101: 75597
A102: A4 Verde | B102: SiIos Novo Horizonte do Sul | C102: 03.902.129/0020-46 | D102: 10/3184070-5 | E102: Verde A4 - Industrial | F102: 45870 | G102: 32243.23 | H102: 262311.67 | I102: 1065.12 | J102: 1015.39 | K102: 79815.6 | L102: 37261
A103: A4 Verde | B103: SiIos Novo Horizonte do Sul | C103: 03.902.129/0020-46 | D103: 10/3184070-5 | E103: Verde A4 - Industrial | F103: 45839 | G103: 39585.5 | H103: 256951.97 | I103: 1024.8 | J103: 993.89 | K103: 76551.2 | L103: 10848
A104: A4 Verde | B104: SiIos Novo Horizonte do Sul | C104: 03.902.129/0020-46 | D104: 10/3184070-5 | E104: Verde A4 - Industrial | F104: 45809 | G104: 16950.02 | H104: 116048.52 | I104: 870.91 | J104: 868.22 | K104: 60380.6 | L104: 24600
A105: A4 Verde | B105: SiIos Novo Horizonte do Sul | C105: 03.902.129/0020-46 | D105: 10/3184070-5 | E105: Verde A4 - Industrial | F105: 45778 | G105: 6013.73 | H105: 51218.33 | I105: 452.93 | J105: 456.96 | K105: 78227.5 | L105: 55127
A106: A4 Verde | B106: SiIos Novo Horizonte do Sul | C106: 03.902.129/0020-46 | D106: 10/3184070-5 | E106: Verde A4 - Industrial | F106: 45748 | G106: 2938.32 | H106: 38550.46 | I106: 441.5 | J106: 485.18 | K106: 62725.4 | L106: 41488
A107: A4 Verde | B107: SiIos Novo Horizonte do Sul | C107: 03.902.129/0020-46 | D107: 10/3184070-5 | E107: Verde A4 - Industrial | F107: 45717 | G107: 17348.35 | H107: 153225.91 | I107: 831.26 | J107: 799.01 | K107: 89858.2 | L107: 32411
A108: A4 Verde | B108: SiIos Novo Horizonte do Sul | C108: 03.902.129/0020-46 | D108: 10/3184070-5 | E108: Verde A4 - Industrial | F108: 45689 | G108: 29874.6 | H108: 172378.75 | I108: 846.05 | J108: 864.19 | K108: 76124.4 | L108: 188910
A109: A4 Verde | B109: SiIos Novo Horizonte do Sul | C109: 03.902.129/0020-46 | D109: 10/3184070-5 | E109: Verde A4 - Industrial | F109: 45658 | G109: 9630.94 | H109: 45354.62 | I109: 605.47 | J109: 516.77 | K109: 83461.9 | L109: 54986
A110: Grupo B | B110: Deposito Irrigação | C110: 03.902.129/0023-99 | D110: 10/2551502-4 | E110: B3 - Comercial | F110: 45992 | H110: 838
A111: Grupo B | B111: Deposito Irrigação | C111: 03.902.129/0023-99 | D111: 10/2551502-4 | E111: B3 - Comercial | F111: 45962 | H111: 925
A112: Grupo B | B112: Deposito Irrigação | C112: 03.902.129/0023-99 | D112: 10/2551502-4 | E112: B3 - Comercial | F112: 45931 | H112: 943
A113: Grupo B | B113: Deposito Irrigação | C113: 03.902.129/0023-99 | D113: 10/2551502-4 | E113: B3 - Comercial | F113: 45901 | H113: 719
A114: Grupo B | B114: Deposito Irrigação | C114: 03.902.129/0023-99 | D114: 10/2551502-4 | E114: B3 - Comercial | F114: 45870 | H114: 816
A115: Grupo B | B115: Deposito Irrigação | C115: 03.902.129/0023-99 | D115: 10/2551502-4 | E115: B3 - Comercial | F115: 45839 | H115: 899
A116: Grupo B | B116: Deposito Irrigação | C116: 03.902.129/0023-99 | D116: 10/2551502-4 | E116: B3 - Comercial | F116: 45809 | H116: 1067
A117: Grupo B | B117: Deposito Irrigação | C117: 03.902.129/0023-99 | D117: 10/2551502-4 | E117: B3 - Comercial | F117: 45778 | H117: 1146
A118: Grupo B | B118: Deposito Irrigação | C118: 03.902.129/0023-99 | D118: 10/2551502-4 | E118: B3 - Comercial | F118: 45748 | H118: 1026
A119: Grupo B | B119: Deposito Irrigação | C119: 03.902.129/0023-99 | D119: 10/2551502-4 | E119: B3 - Comercial | F119: 45717 | H119: 1030
A120: Grupo B | B120: Deposito Irrigação | C120: 03.902.129/0023-99 | D120: 10/2551502-4 | E120: B3 - Comercial | F120: 45689 | H120: 887
A121: Grupo B | B121: Deposito Irrigação | C121: 03.902.129/0023-99 | D121: 10/2551502-4 | E121: B3 - Comercial | F121: 45658 | H121: 876
A122: A3A rural | B122: Silos Amandina | C122: 03.902.129/0025-50 | D122: 10/3267347-7 | E122: Verde A3a - Rural | F122: 45992 | G122: 1514.84 | H122: 15428.7 | I122: 30.24 | J122: 217.98 | K122: 19968.1 | L122: 16944 | O122: =+K122-L122 -> 3024.1 | P122: =+VLOOKUP(F122,Amandina!$H$4:$L$14,5,0)*1000 -> 85283.12 | R122: =+P122-H122 -> 69854.42
A123: A3A rural | B123: Silos Amandina | C123: 03.902.129/0025-50 | D123: 10/3267347-7 | E123: Verde A3a - Rural | F123: 45962 | G123: 1437.03 | H123: 8808.98 | I123: 103.32 | J123: 100.8 | K123: 36462.9 | L123: 10246 | O123: =+K123-L123 -> 26216.9 | P123: =+VLOOKUP(F123,Amandina!$H$4:$L$14,5,0)*1000 -> 86384.48
A124: A3A rural | B124: Silos Amandina | C124: 03.902.129/0025-50 | D124: 10/3267347-7 | E124: Verde A3a - Rural | F124: 45931 | G124: 2102.94 | H124: 11731.55 | I124: 167.58 | J124: 165.06 | K124: 40322 | L124: 13835 | O124: =+K124-L124 -> 26487 | P124: =+VLOOKUP(F124,Amandina!$H$4:$L$14,5,0)*1000 -> 76725.44
A125: A3A rural | B125: Silos Amandina | C125: 03.902.129/0025-50 | D125: 10/3267347-7 | E125: Verde A3a - Rural | F125: 45901 | G125: 2740.19 | H125: 17968.55 | I125: 168.84 | J125: 196.56 | K125: 37738.8 | L125: 20709 | O125: =+K125-L125 -> 17029.8 | P125: =+VLOOKUP(F125,Amandina!$H$4:$L$14,5,0)*1000 -> 75546.72
A126: A3A rural | B126: Silos Amandina | C126: 03.902.129/0025-50 | D126: 10/3267347-7 | E126: Verde A3a - Rural | F126: 45870 | G126: 19255.01 | H126: 130522.46 | I126: 793.8 | J126: 869.4 | K126: 16177.9 | L126: 5142 | O126: =+K126-L126 -> 11035.9 | P126: =+VLOOKUP(F126,Amandina!$H$4:$L$14,5,0)*1000 -> 74466.16
A127: A3A rural | B127: Silos Amandina | C127: 03.902.129/0025-50 | D127: 10/3267347-7 | E127: Verde A3a - Rural | F127: 45839 | G127: 37585.8 | H127: 223302.56 | I127: 904.68 | J127: 916.02 | K127: 37317.8 | L127: 9165 | O127: =+K127-L127 -> 28152.8 | P127: =+VLOOKUP(F127,Amandina!$H$4:$L$14,5,0)*1000 -> 70669.44
A128: A3A rural | B128: Silos Amandina | C128: 03.902.129/0025-50 | D128: 10/3267347-7 | E128: Verde A3a - Rural | F128: 45809 | G128: 19556.78 | H128: 183159.59 | I128: 747.18 | J128: 845.46 | K128: 20798.2 | L128: 7190 | O128: =+K128-L128 -> 13608.2 | P128: =+VLOOKUP(F128,Amandina!$H$4:$L$14,5,0)*1000 -> 57829.52
A129: A3A rural | B129: Silos Amandina | C129: 03.902.129/0025-50 | D129: 10/3267347-7 | E129: Verde A3a - Rural | F129: 45778 | G129: 7312.1 | H129: 106720.74 | I129: 486.36 | J129: 784.98 | K129: 28781.7 | L129: 9127 | O129: =+K129-L129 -> 19654.7 | P129: =+VLOOKUP(F129,Amandina!$H$4:$L$14,5,0)*1000 -> 73293.28
A130: A3A rural | B130: Silos Amandina | C130: 03.902.129/0025-50 | D130: 10/3267347-7 | E130: Verde A3a - Rural | F130: 45748 | G130: 2769.48 | H130: 84395.43 | I130: 110.88 | J130: 560.7 | K130: 23902.8 | L130: 1423 | O130: =+K130-L130 -> 22479.8 | P130: =+VLOOKUP(F130,Amandina!$H$4:$L$14,5,0)*1000 -> 58967.76
A131: A3A rural | B131: Silos Amandina | C131: 03.902.129/0025-50 | D131: 10/3267347-7 | E131: Verde A3a - Rural | F131: 45717 | G131: 14932.89 | H131: 177578.42 | I131: 913.5 | J131: 923.58 | K131: 7913.8 | L131: 419 | O131: =+K131-L131 -> 7494.8 | P131: =+VLOOKUP(F131,Amandina!$H$4:$L$14,5,0)*1000 -> 82449.52
A132: A3A rural | B132: Silos Amandina | C132: 03.902.129/0025-50 | D132: 10/3267347-7 | E132: Verde A3a - Rural | F132: 45689 | G132: 19948.64 | H132: 212798.25 | I132: 763.56 | J132: 790.02 | K132: 190.1 | L132: 0 | O132: =+K132-L132 -> 190.1 | P132: =+Batayporã!J4*80%*1000 -> 72905.52
A133: A3A rural | B133: Silos Amandina | C133: 03.902.129/0025-50 | D133: 10/3267347-7 | E133: Verde A3a - Rural | F133: 45658 | G133: 9264.15 | H133: 72928.49 | I133: 704.34 | J133: 758.52 | K133: 0 | L133: 0 | O133: =+K133-L133 -> 0 | P133: =+Batayporã!J3*80%*1000 -> 91407.2
A134: Grupo B | B134: Escritório Nova Andradina | C134: 03.902.129/0026-31 | D134: 10/3683986-8 | E134: B3 - Comercial | F134: 45992 | H134: 3227
A135: Grupo B | B135: Escritório Nova Andradina | C135: 03.902.129/0026-31 | D135: 10/3683986-8 | E135: B3 - Comercial | F135: 45962 | H135: 2090
A136: Grupo B | B136: Escritório Nova Andradina | C136: 03.902.129/0026-31 | D136: 10/3683986-8 | E136: B3 - Comercial | F136: 45931 | H136: 2593
A137: Grupo B | B137: Escritório Nova Andradina | C137: 03.902.129/0026-31 | D137: 10/3683986-8 | E137: B3 - Comercial | F137: 45901 | H137: 2469
A138: Grupo B | B138: Escritório Nova Andradina | C138: 03.902.129/0026-31 | D138: 10/3683986-8 | E138: B3 - Comercial | F138: 45870 | H138: 1448
A139: Grupo B | B139: Escritório Nova Andradina | C139: 03.902.129/0026-31 | D139: 10/3683986-8 | E139: B3 - Comercial | F139: 45839 | H139: 1317
A140: Grupo B | B140: Escritório Nova Andradina | C140: 03.902.129/0026-31 | D140: 10/3683986-8 | E140: B3 - Comercial | F140: 45809 | H140: 1362
A141: Grupo B | B141: Escritório Nova Andradina | C141: 03.902.129/0026-31 | D141: 10/3683986-8 | E141: B3 - Comercial | F141: 45778 | H141: 2238
A142: Grupo B | B142: Escritório Nova Andradina | C142: 03.902.129/0026-31 | D142: 10/3683986-8 | E142: B3 - Comercial | F142: 45748 | H142: 2511
A143: Grupo B | B143: Escritório Nova Andradina | C143: 03.902.129/0026-31 | D143: 10/3683986-8 | E143: B3 - Comercial | F143: 45717 | H143: 3281
A144: Grupo B | B144: Escritório Nova Andradina | C144: 03.902.129/0026-31 | D144: 10/3683986-8 | E144: B3 - Comercial | F144: 45689 | H144: 3394
A145: Grupo B | B145: Escritório Nova Andradina | C145: 03.902.129/0026-31 | D145: 10/3683986-8 | E145: B3 - Comercial | F145: 45658 | H145: 3370
A146: A4 Verde | B146: Silos Batayporã | C146: 03.902.129/0031-07 | D146: 10/2121803-7 | E146: Verde A4 - Industrial | F146: 45992 | G146: 1093.05 | H146: 4510.8 | I146: 25.2 | J146: 42 | K146: 106603.9 | L146: 5604
A147: A4 Verde | B147: Silos Batayporã | C147: 03.902.129/0031-07 | D147: 10/2121803-7 | E147: Verde A4 - Industrial | F147: 45962 | G147: 1019.55 | H147: 4500.3 | I147: 79.8 | J147: 71.4 | K147: 107980.6 | L147: 5520
A148: A4 Verde | B148: Silos Batayporã | C148: 03.902.129/0031-07 | D148: 10/2121803-7 | E148: Verde A4 - Industrial | F148: 45931 | G148: 1132.95 | H148: 4884.6 | I148: 21 | J148: 46.2 | K148: 95906.8 | L148: 6018
A149: A4 Verde | B149: Silos Batayporã | C149: 03.902.129/0031-07 | D149: 10/2121803-7 | E149: Verde A4 - Industrial | F149: 45901 | G149: 1357.65 | H149: 15868.65 | I149: 142.8 | J149: 151.2 | K149: 94433.4 | L149: 29344
A150: A4 Verde | B150: Silos Batayporã | C150: 03.902.129/0031-07 | D150: 10/2121803-7 | E150: Verde A4 - Industrial | F150: 45870 | G150: 11823 | H150: 47401.2 | I150: 407.4 | J150: 390.6 | K150: 93082.7 | L150: 59224
A151: A4 Verde | B151: Silos Batayporã | C151: 03.902.129/0031-07 | D151: 10/2121803-7 | E151: Verde A4 - Industrial | F151: 45839 | G151: 13474.65 | H151: 50710.8 | I151: 382.2 | J151: 394.8 | K151: 88336.8 | L151: 64186
A152: A4 Verde | B152: Silos Batayporã | C152: 03.902.129/0031-07 | D152: 10/2121803-7 | E152: Verde A4 - Industrial | F152: 45809 | G152: 5230.05 | H152: 31349.85 | I152: 352.8 | J152: 357 | K152: 72286.9 | L152: 36580
A153: A4 Verde | B153: Silos Batayporã | C153: 03.902.129/0031-07 | D153: 10/2121803-7 | E153: Verde A4 - Industrial | F153: 45778 | G153: 1296.75 | H153: 35861.7 | I153: 79.8 | J153: 197.4 | K153: 91616.6 | L153: 37159
A154: A4 Verde | B154: Silos Batayporã | C154: 03.902.129/0031-07 | D154: 10/2121803-7 | E154: Verde A4 - Industrial | F154: 45748 | G154: 1182.3 | H154: 37404.15 | I154: 168 | J154: 197.4 | K154: 73709.7 | L154: 38586
A155: A4 Verde | B155: Silos Batayporã | C155: 03.902.129/0031-07 | D155: 10/2121803-7 | E155: Verde A4 - Industrial | F155: 45717 | G155: 9745.05 | H155: 53952.15 | I155: 378 | J155: 369.6 | K155: 103061.9 | L155: 63697
A156: A4 Verde | B156: Silos Batayporã | C156: 03.902.129/0031-07 | D156: 10/2121803-7 | E156: Verde A4 - Industrial | F156: 45689 | G156: 7965.3 | H156: 28350 | I156: 361.2 | J156: 327.6 | K156: 91131.9 | L156: 36315
A157: A4 Verde | B157: Silos Batayporã | C157: 03.902.129/0031-07 | D157: 10/2121803-7 | E157: Verde A4 - Industrial | F157: 45658 | G157: 1197 | H157: 5588.1 | I157: 25.2 | J157: 25.2 | K157: 114259 | L157: 6785
A158: Grupo B | B158: Irrigação Copasul Campo Grande | C158: 03.902.129/0032-80 | D158: 10/2603357-1 | E158: B3 - Comercial | F158: 45992 | H158: 1260
A159: Grupo B | B159: Irrigação Copasul Campo Grande | C159: 03.902.129/0032-80 | D159: 10/2603357-1 | E159: B3 - Comercial | F159: 45962 | H159: 900
A160: Grupo B | B160: Irrigação Copasul Campo Grande | C160: 03.902.129/0032-80 | D160: 10/2603357-1 | E160: B3 - Comercial | F160: 45931 | H160: 939
A161: Grupo B | B161: Irrigação Copasul Campo Grande | C161: 03.902.129/0032-80 | D161: 10/2603357-1 | E161: B3 - Comercial | F161: 45901 | H161: 750
A162: Grupo B | B162: Irrigação Copasul Campo Grande | C162: 03.902.129/0032-80 | D162: 10/2603357-1 | E162: B3 - Comercial | F162: 45870 | H162: 525
A163: Grupo B | B163: Irrigação Copasul Campo Grande | C163: 03.902.129/0032-80 | D163: 10/2603357-1 | E163: B3 - Comercial | F163: 45839 | H163: 475
A164: Grupo B | B164: Irrigação Copasul Campo Grande | C164: 03.902.129/0032-80 | D164: 10/2603357-1 | E164: B3 - Comercial | F164: 45809 | H164: 554
A165: Grupo B | B165: Irrigação Copasul Campo Grande | C165: 03.902.129/0032-80 | D165: 10/2603357-1 | E165: B3 - Comercial | F165: 45778 | H165: 733
A166: Grupo B | B166: Irrigação Copasul Campo Grande | C166: 03.902.129/0032-80 | D166: 10/2603357-1 | E166: B3 - Comercial | F166: 45748 | H166: 915
A167: Grupo B | B167: Irrigação Copasul Campo Grande | C167: 03.902.129/0032-80 | D167: 10/2603357-1 | E167: B3 - Comercial | F167: 45717 | H167: 1180
A168: Grupo B | B168: Irrigação Copasul Campo Grande | C168: 03.902.129/0032-80 | D168: 10/2603357-1 | E168: B3 - Comercial | F168: 45689 | H168: 1100
A169: Grupo B | B169: Irrigação Copasul Campo Grande | C169: 03.902.129/0032-80 | D169: 10/2603357-1 | E169: B3 - Comercial | F169: 45658 | H169: 1140
... A217: Grupo B | B217: Posto Carreteiro | C217: 48.657.758/0001-23 | D217: 10/2502804-4 | E217: B3 - Comercial | F217: 45658 | H217: 11760

Sheet Dados_Produção_Helexia

Sheet Usinas_Helexia_PR
B3: Código | C3: Nome do Projeto | D3: Data | E3: Mês | F3: Nº Mês | G3: Ano de Exposição Solar | H3: Ano de Geração | I3: Geração (MWh)
B4: HCS01 | C4: Cassilândia 01 | D4: 45383 | E4: Apr | F4: 4 | G4: 2024 | H4: Ano 0 | I4: 37.227
B5: HCS01 | C5: Cassilândia 01 | D5: 45413 | E5: May | F5: 5 | G5: 2024 | H5: Ano 0 | I5: 66.274
B6: HCS01 | C6: Cassilândia 01 | D6: 45444 | E6: Jun | F6: 6 | G6: 2024 | H6: Ano 0 | I6: 54.743
B7: HCS01 | C7: Cassilândia 01 | D7: 45474 | E7: Jul | F7: 7 | G7: 2024 | H7: Ano 0 | I7: 100.242
B8: HCS01 | C8: Cassilândia 01 | D8: 45505 | E8: Aug | F8: 8 | G8: 2024 | H8: Ano 0 | I8: 114.491
B9: HCS01 | C9: Cassilândia 01 | D9: 45536 | E9: Sept | F9: 9 | G9: 2024 | H9: Ano 0 | I9: 101.6523
B10: HCS01 | C10: Cassilândia 01 | D10: 45566 | E10: Oct | F10: 10 | G10: 2024 | H10: Ano 0 | I10: 88.6151
B11: HCS01 | C11: Cassilândia 01 | D11: 45597 | E11: Nov | F11: 11 | G11: 2024 | H11: Ano 0 | I11: 99.3694
B12: HCS01 | C12: Cassilândia 01 | D12: 45627 | E12: Dec | F12: 12 | G12: 2024 | H12: Ano 0 | I12: 77.1956
B13: HCS01 | C13: Cassilândia 01 | D13: 45658 | E13: Jan | F13: 1 | G13: 2024 | H13: Ano 1 | I13: 105.4782
B14: HCS01 | C14: Cassilândia 01 | D14: 45689 | E14: Feb | F14: 2 | G14: 2024 | H14: Ano 1 | I14: 85
B15: HCS01 | C15: Cassilândia 01 | D15: 45717 | E15: Mar | F15: 3 | G15: 2024 | H15: Ano 1 | I15: 100.1787
... B25: HCS01 | C25: Cassilândia 01 | D25: 46023 | E25: Jan | F25: 1 | G25: 2024 | H25: Ano 2 | I25: 106.7224
B29: Código | C29: Nome do Projeto | D29: Data | E29: Mês | F29: Nº Mês | G29: Ano de Exposição Solar | H29: Ano de Geração | I29: Geração (MWh)
B30: HCS02 | C30: Cassilândia 02 | D30: 45383 | E30: Apr | F30: 4 | G30: 2024 | H30: Ano 0 | I30: 32.672
B31: HCS02 | C31: Cassilândia 02 | D31: 45413 | E31: May | F31: 5 | G31: 2024 | H31: Ano 0 | I31: 108.947
B32: HCS02 | C32: Cassilândia 02 | D32: 45444 | E32: Jun | F32: 6 | G32: 2024 | H32: Ano 0 | I32: 92.917
B33: HCS02 | C33: Cassilândia 02 | D33: 45474 | E33: Jul | F33: 7 | G33: 2024 | H33: Ano 0 | I33: 163.0883
B34: HCS02 | C34: Cassilândia 02 | D34: 45505 | E34: Aug | F34: 8 | G34: 2024 | H34: Ano 0 | I34: 189.0879
B35: HCS02 | C35: Cassilândia 02 | D35: 45536 | E35: Sept | F35: 9 | G35: 2024 | H35: Ano 0 | I35: 176.1752
B36: HCS02 | C36: Cassilândia 02 | D36: 45566 | E36: Oct | F36: 10 | G36: 2024 | H36: Ano 0 | I36: 161.1117
B37: HCS02 | C37: Cassilândia 02 | D37: 45597 | E37: Nov | F37: 11 | G37: 2024 | H37: Ano 0 | I37: 169.5114
B38: HCS02 | C38: Cassilândia 02 | D38: 45627 | E38: Dec | F38: 12 | G38: 2024 | H38: Ano 0 | I38: 166.9964
B39: HCS02 | C39: Cassilândia 02 | D39: 45658 | E39: Jan | F39: 1 | G39: 2024 | H39: Ano 1 | I39: 190.9089
B40: HCS02 | C40: Cassilândia 02 | D40: 45689 | E40: Feb | F40: 2 | G40: 2024 | H40: Ano 1 | I40: 166
B41: HCS02 | C41: Cassilândia 02 | D41: 45717 | E41: Mar | F41: 3 | G41: 2024 | H41: Ano 1 | I41: 193.4294
... B51: HCS02 | C51: Cassilândia 02 | D51: 46023 | E51: Jan | F51: 1 | G51: 2024 | H51: Ano 2 | I51: 184.9512
B56: Código | C56: Nome do Projeto | D56: Data | E56: Mês | F56: Nº Mês | G56: Ano de Exposição Solar | H56: Ano de Geração | I56: Geração (MWh)
B57: HCS03 | C57: Cassilândia 03 | D57: 45383 | E57: Apr | F57: 4 | G57: 2024 | H57: Ano 0 | I57: 70.926
B58: HCS03 | C58: Cassilândia 03 | D58: 45413 | E58: May | F58: 5 | G58: 2024 | H58: Ano 0 | I58: 74.153
B59: HCS03 | C59: Cassilândia 03 | D59: 45444 | E59: Jun | F59: 6 | G59: 2024 | H59: Ano 0 | I59: 62.902
B60: HCS03 | C60: Cassilândia 03 | D60: 45474 | E60: Jul | F60: 7 | G60: 2024 | H60: Ano 0 | I60: 107.0881
B61: HCS03 | C61: Cassilândia 03 | D61: 45505 | E61: Aug | F61: 8 | G61: 2024 | H61: Ano 0 | I61: 51.7493
B62: HCS03 | C62: Cassilândia 03 | D62: 45536 | E62: Sept | F62: 9 | G62: 2024 | H62: Ano 0 | I62: 107.0198
B63: HCS03 | C63: Cassilândia 03 | D63: 45566 | E63: Oct | F63: 10 | G63: 2024 | H63: Ano 0 | I63: 98.5846
B64: HCS03 | C64: Cassilândia 03 | D64: 45597 | E64: Nov | F64: 11 | G64: 2024 | H64: Ano 0 | I64: 119.2367
B65: HCS03 | C65: Cassilândia 03 | D65: 45627 | E65: Dec | F65: 12 | G65: 2024 | H65: Ano 0 | I65: 111.1389
B66: HCS03 | C66: Cassilândia 03 | D66: 45658 | E66: Jan | F66: 1 | G66: 2024 | H66: Ano 1 | I66: 143.3821
B67: HCS03 | C67: Cassilândia 03 | D67: 45689 | E67: Feb | F67: 2 | G67: 2024 | H67: Ano 1 | I67: 121
B68: HCS03 | C68: Cassilândia 03 | D68: 45717 | E68: Mar | F68: 3 | G68: 2024 | H68: Ano 1 | I68: 141.1858
... B78: HCS03 | C78: Cassilândia 03 | D78: 46023 | E78: Jan | F78: 1 | G78: 2024 | H78: Ano 2 | I78: 131.6157
B84: Performance Ratio
B85: Código | C85: Nome do Projeto | D85: Data do PR | E85: Mês do PR | F85: Ano do PR | G85: Ano de Exposição Solar | H85: Ano de Geração | I85: PR PVsyst (%) | J85: PR Real (%) | K85: Status
B86: HCS01 | C86: Cassilândia 01 | D86: 45444 | E86: Jun | F86: 2024 | G86: 2024 | H86: Ano 0 | I86: 0 | J86: 0.5467 | K86: Aprovado
B87: HCS01 | C87: Cassilândia 01 | D87: 45536 | E87: Sept | F87: 2024 | G87: 2024 | H87: Ano 0 | I87: 0 | J87: 0.7026 | K87: Aprovado
B88: HCS01 | C88: Cassilândia 01 | D88: 45597 | E88: Nov | F88: 2024 | G88: 2024 | H88: Ano 0 | I88: 0 | J88: 0.731 | K88: Aprovado
B89: HCS01 | C89: Cassilândia 01 | D89: 45717 | E89: Mar | F89: 2025 | G89: 2024 | H89: Ano 1 | I89: 0 | J89: 0.7486 | K89: Aprovado
B93: Código | C93: Nome do Projeto | D93: Data do PR | E93: Mês do PR | F93: Ano do PR | G93: Ano de Exposição Solar | H93: Ano de Geração | I93: PR PVsyst (%) | J93: PR Real (%) | K93: Status
B94: HCS02 | C94: Cassilândia 02 | D94: 45536 | E94: Sept | F94: 2024 | G94: 2024 | H94: Ano 0 | I94: 0 | J94: 0.7175 | K94: Aprovado
B95: HCS02 | C95: Cassilândia 02 | D95: 45597 | E95: Nov | F95: 2024 | G95: 2024 | H95: Ano 0 | I95: 0 | J95: 0.7949 | K95: Aprovado
B96: HCS02 | C96: Cassilândia 02 | D96: 45717 | E96: Mar | F96: 2025 | G96: 2024 | H96: Ano 1 | I96: 0 | J96: 0.799 | K96: Aprovado
B99: Código | C99: Nome do Projeto | D99: Data do PR | E99: Mês do PR | F99: Ano do PR | G99: Ano de Exposição Solar | H99: Ano de Geração | I99: PR PVsyst (%) | J99: PR Real (%) | K99: Status
B100: HCS03 | C100: Cassilândia 03 | D100: 45536 | E100: Sept | F100: 2024 | G100: 2024 | H100: Ano 0 | I100: 0 | J100: 0.5715 | K100: Aprovado
B101: HCS03 | C101: Cassilândia 03 | D101: 45597 | E101: Nov | F101: 2024 | G101: 2024 | H101: Ano 0 | I101: 0 | J101: 0.7971 | K101: Aprovado
B102: HCS03 | C102: Cassilândia 03 | D102: 45717 | E102: Mar | F102: 2025 | G102: 2024 | H102: Ano 1 | I102: 0 | J102: 0.8001 | K102: Aprovado

Sheet PVSYST_Helexia
J2: =+COUNTA($B$5:J5) -> 9 | K2: =+COUNTA($B$5:K5) -> 10 | L2: =+COUNTA($B$5:L5) -> 11 | M2: =+COUNTA($B$5:M5) -> 12 | N2: =+COUNTA($B$5:N5) -> 13 | O2: =+COUNTA($B$5:O5) -> 14 | P2: =+COUNTA($B$5:P5) -> 15 | Q2: =+COUNTA($B$5:Q5) -> 16 | ... U2: =+COUNTA($B$5:U5) -> 20
B3: PV Syst | J3: Jan | K3: Fev | L3: Mar | M3: Abr | N3: Mai | O3: Jun | P3: Jul | Q3: Ago | R3: Set | S3: Out | T3: Nov | U3: Dez
A4: Código | B4: Nome do Projeto | C4: Distribuidora | D4: Status | E4: Cliente | F4: Potência AC (kWac) | G4: Potência DC (kWp) | H4: Ano de Exposição Solar | I4: Ano de Geração | J4: janeiro | K4: fevereiro | L4: março | M4: abril | N4: maio | O4: junho | P4: julho | Q4: agosto | R4: setembro | S4: outubro | T4: novembro | U4: dezembro | V4: Geração P50 Ano 0 (MWh/ano) | W4: Geração P50 Ano Atual (MWh/ano) | X4: Variabilidade Anual (%) | Y4: Geração P90 PVsyst Ano 0 (MWh/ano) | Z4: Geração P90 PVsyst Ano Atual (MWh/ano) | AA4: Geração P90 Ano Atual Real (MWh/ano) | AB4: PR Médio Ano 0 | AC4: PR Médio Ano Atual | AD4: Produção Específica | AE4: Fator de Capacidade | AF4: Versão PVsyst | AG4: Variante PVsyst | AH4: Data PVsyst | AI4: Observação | AJ4: Link Report
A5: HCS01 | B5: Cassilândia 01 | C5: EMS | D5: Entregue | E5: COMERC | F5: 500 | G5: 626.4 | H5: 2024 | I5: 2 | J5: 105.88 | K5: 109.34 | L5: 120.94 | M5: 113.72 | N5: 105.37 | O5: 89.609 | P5: 99.212 | Q5: 121.11 | R5: 114.6 | S5: 118.18 | T5: 107.05 | U5: 116.84 | V5: 1330.553 | W5: 1321.851 | X5: 3.083 | Y5: 1278.0052 | Z5: 1269.6468 | AA5: 1198.2407 | AB5: 0.81885833 | AC5: 0.81344167 | AD5: 2110.2347 | AE5: 0.30179247 | AF5: As Built | AG5: VCH | AH5: 45993 | AI5: Considerando perdas nos cabos e transformador conforme Projeto Executivo. Além de perdas por sujidade e indisponibilidade conforme premissas do O&M | AJ5: Clique Aqui
A6: HCS02 | B6: Cassilândia 02 | C6: EMS | D6: Entregue | E6: COMERC | F6: 875 | G6: 1127.52 | H6: 2024 | I6: 2 | J6: 189.47 | K6: 194.28 | L6: 214.77 | M6: 202.63 | N6: 189.07 | O6: 171.58 | P6: 181 | Q6: 217.01 | R6: 204.19 | S6: 181 | T6: 203.55 | U6: 207.27 | V6: 2369.92 | W6: 2355.82 | X6: 3.083 | Y6: 2276.3242 | Z6: 2262.7811 | AA6: 2135.5202 | AB6: 0.81225 | AC6: 0.80731667 | AD6: 2089.382 | AE6: 0.30734768 | AF6: As Built | AG6: VCI | AH6: 45993 | AI6: Considerando perdas nos cabos e transformador conforme Projeto Executivo. Além de perdas por sujidade e indisponibilidade conforme premissas do O&M | AJ6: Clique Aqui
A7: HCS03 | B7: Cassilândia 03 | C7: EMS | D7: Entregue | E7: COMERC | F7: 625 | G7: 814.32 | H7: 2024 | I7: 2 | J7: 143.14 | K7: 127.55 | L7: 146.3 | M7: 145.98 | N7: 136.62 | O7: 123.99 | P7: 130.51 | Q7: 156.67 | R7: 147.01 | S7: 151.08 | T7: 146.08 | U7: 138.71 | V7: 1703.67 | W7: 1693.64 | X7: 3.083 | Y7: 1636.3866 | Z7: 1626.7527 | AA7: 1535.2626 | AB7: 0.80775 | AC7: 0.80291667 | AD7: 2079.8212 | AE7: 0.30934064 | AF7: As Built | AG7: VCJ | AH7: 45993 | AI7: Considerando perdas nos cabos e transformador conforme Projeto Executivo. Além de perdas por sujidade e indisponibilidade conforme premissas do O&M | AJ7: Clique Aqui
B12: Produçao 2025 | J12: Jan | K12: Fev | L12: Mar | M12: Abr | N12: Mai | O12: Jun | P12: Jul | Q12: Ago | R12: Set | S12: Out | T12: Nov | U12: Dez | V12: Geração Atual Ano 0 (MWh/ano) | W12: January 26 | X12: February 26
A13: Código | B13: Nome do Projeto | C13: Distribuidora | D13: Status | E13: Cliente | F13: Potência AC (kWac) | G13: Potência DC (kWp) | H13: Ano de Exposição Solar | I13: Ano de Geração | J13: janeiro | K13: fevereiro | L13: março | M13: abril | N13: maio | O13: junho | P13: julho | Q13: agosto | R13: setembro | S13: outubro | T13: novembro | U13: dezembro | V13: Geração Atual Ano 0 (MWh/ano)
A14: HCS01 | B14: Cassilândia 01 | C14: EMS | D14: Entregue | E14: COMERC | F14: 500 | G14: 626.4 | H14: 2024 | I14: 2
A15: HCS02 | B15: Cassilândia 02 | C15: EMS | D15: Entregue | E15: COMERC | F15: 875 | G15: 1127.52 | H15: 2024 | I15: 2 | J15: 188.55 | K15: 166 | L15: 193.4294 | M15: 144.1346 | N15: 158.6377 | O15: 128.6395 | P15: 178.3455 | Q15: 190.7348 | R15: 200.2328 | S15: 185.5502 | T15: 215.3495 | U15: 181.5256 | V15: 2131.1296 | W15: 184.9512 | X15: 157.439
A16: HCS03 | B16: Cassilândia 03 | C16: EMS | D16: Entregue | E16: COMERC | F16: 625 | G16: 814.32 | H16: 2024 | I16: 2 | J16: 143.48 | K16: 121 | L16: 141.1858 | M16: 105.1116 | N16: 121.0391 | O16: 99.4716 | P16: 127.0078 | Q16: 134.7817 | R16: 139.8889 | S16: 128.4246 | T16: 153.3072 | U16: 130.3996 | V16: 1545.0979 | W16: 131.6157 | X16: 110.621

Sheet Usinas
A1: Unidade | B1: Pi (kWp) | C1: Pg (kW) | D1: Número de módulos | E1: Potencia (W) | F1: Eficiência | G1: Área do módulo (m²) | H1: Área Total (m²) | I1: Densidade de Potência (W/m²) | J1: Latitude | K1: Longitude | L1: Inclinação | M1: Azimuth
A2: Novo Horizonte do Sul | B2: 621 | C2: 500 | D2: 1800 | E2: 345 | F2: 0.174 | G2: 1.9 | H2: =D2*G2 -> 3420 | I2: =D2*E2/H2 -> 181.57895 | J2: -22.67340908 | K2: -53.84513269 | L2: 22° | M2: 0
A3: Batayporã | B3: 702 | C3: 500 | D3: 1560 | E3: 450 | F3: 0.204 | G3: 2.209184 | H3: =D3*G3 -> 3446.327 | I3: =D3*E3/H3 -> 203.69512 | J3: -22.27609989 | K3: -53.22534149
A4: Amandina | B4: 697 | C4: 500 | D4: 1700 | E4: 410 | F4: 0.203 | G4: 2.022036 | H4: =D4*G4 -> 3437.4612 | I4: =D4*E4/H4 -> 202.76593 | J4: -22.34231564 | K4: -53.58536212
