Workbook

Sheet Resumo
B1: ="SIMULAÇÃO RATEIO FIXO — "&Premissas!$B$13&" × COPASUL | Resumo Executivo" -> SIMULAÇÃO RATEIO FIXO — Cassilândia 03 × COPASUL | Resumo Executivo
B2: ="18 Unidades Consumidoras · Jun/2026–Mai/2031 · Energisa MS · Usina: "&Premissas!$B$13 -> 18 Unidades Consumidoras · Jun/2026–Mai/2031 · Energisa MS · Usina: Cassilândia 03
B4: ⚡ GERAÇÃO INJETADA | D4: 📄 PPA PAGO À HELEXIA | F4: ✅ ECONOMIA LÍQUIDA | H4: 🏦 BANCO RESIDUAL | J4: 🌟 VALOR TOTAL
B5: =Simulacao!B6/1000000 -> 8.3804424 | D5: =Simulacao!B7 -> 4542510.4 | F5: =Simulacao!B252 -> 2673060.5 | H5: =Simulacao!B273*Premissas!$B$17 -> 460824.2 | J5: =Simulacao!B278 -> 3247039.2
B6: 3,375 MWh injetados em 60 meses | D6: Custo total do contrato PPA | F6: Rede evitada menos PPA pago | H6: Banco total Copasul @ PPA | J6: Economia + banco ATRIBUÍVEL a Helexia
B8: A. CUSTO COPASUL — ANÁLISE 24 MESES | I8: B. INDICADORES-CHAVE
B9: COMPONENTE | E9: R$ | F9: % | G9: R$/mês | I9: Usina contratada | K9: =Premissas!$B$13 -> Cassilândia 03
B10: Custo SEM Helexia — baseline 60m | E10: =Simulacao!B249 -> 8246596.4 | F10: =Simulacao!B249/Simulacao!B249 -> 1 | G10: =(Simulacao!B249)/60 -> 137443.27 | I10: Período do contrato | K10: Jun/2026 – Mai/2031 (60 meses)
B11: Custo rede remanescente (COM Helexia) | E11: =Simulacao!B250 -> 1031025.5 | F11: =Simulacao!B250/Simulacao!B249 -> 0.12502437 | G11: =(Simulacao!B250)/60 -> 17183.758 | I11: Potência contratada | K11: =VLOOKUP(Premissas!$B$13,PVSYST_Helexia!$B$5:$F$7,5,0)&" kWac" -> 625 kWac
B12: PPA pago à Helexia | E12: =Simulacao!B7 -> 4542510.4 | F12: =Simulacao!B7/Simulacao!B249 -> 0.55083457 | G12: =(Simulacao!B7)/60 -> 75708.506 | I12: Geração P50 total | K12: =Simulacao!B6/1000 -> 8380.4424
B13: Custo total COM Helexia (rede + PPA) | E13: =Simulacao!B251 -> 5573535.9 | F13: =Simulacao!B251/Simulacao!B249 -> 0.67585894 | G13: =(Simulacao!B251)/60 -> 92892.264 | I13: PPA (R$/kWh) | K13: =Premissas!$B$17 -> 0.4425
B14: ★ ECONOMIA LÍQUIDA (rede − PPA) | E14: =Simulacao!B252 -> 2673060.5 | F14: =Simulacao!B252/Simulacao!B249 -> 0.32414106 | G14: =(Simulacao!B252)/60 -> 44551.009 | I14: Tarifa Grupo A FP | K14: =Premissas!$B$5 -> 0.52647111
B15: + Banco atribuível Helexia @ PPA (net NHS/AMD + Grupo B) | E15: =Simulacao!B285 -> 573978.69 | F15: =IFERROR(Simulacao!B285/Simulacao!B249,0) -> 0.069601889 | G15: =Simulacao!B285/60 -> 9566.3115 | I15: Tarifa Grupo B3 | K15: =Premissas!$B$7 -> 1.1568636
B16: ★ VALOR TOTAL HELEXIA (economia + banco atribuível) | E16: =Simulacao!B278 -> 3247039.2 | F16: =Simulacao!B278/Simulacao!B249 -> 0.39374295 | G16: =(Simulacao!B278)/60 -> 54117.32 | I16: Economia média/mês | K16: =Simulacao!B252/60 -> 44551.009
I17: % redução custo Copasul | K17: =IFERROR(Simulacao!B252/Simulacao!B249,0) -> 0.32414106
I18: Banco residual (kWh) | K18: =Simulacao!B273 -> 1041410.6
B20: C. ANÁLISE VISUAL — ECONOMIA E BANCO DE CRÉDITOS
P22: Mês | Q22: SEM Helexia | R22: PPA | S22: Rede COM | T22: Eco mensal | U22: Eco acumulada
P23: Jun/26 | Q23: =Simulacao!D249 -> 174954.21 | R23: =Simulacao!D7 -> 61449.444 | S23: =Simulacao!D250 -> 144748.07 | T23: =Simulacao!D252 -> -31243.305 | U23: =T23 -> -31243.305
P24: Jul/26 | Q24: =Simulacao!E249 -> 220226.76 | R24: =Simulacao!E7 -> 64680.756 | S24: =Simulacao!E250 -> 186553.14 | T24: =Simulacao!E252 -> -31007.137 | U24: =U23+T24 -> -62250.442
P25: Ago/26 | Q25: =Simulacao!F249 -> 124872.64 | R25: =Simulacao!F7 -> 77645.652 | S25: =Simulacao!F250 -> 86971.897 | T25: =Simulacao!F252 -> -39744.909 | U25: =U24+T25 -> -101995.35
P26: Set/26 | Q26: =Simulacao!G249 -> 47721.487 | R26: =Simulacao!G7 -> 72858.156 | S26: =Simulacao!G250 -> 3013.3082 | T26: =Simulacao!G252 -> -28149.977 | U26: =U25+T26 -> -130145.33
P27: Out/26 | Q27: =Simulacao!H249 -> 48546.433 | R27: =Simulacao!H7 -> 74875.248 | S27: =Simulacao!H250 -> 0 | T27: =Simulacao!H252 -> -26328.815 | U27: =U26+T27 -> -156474.14
P28: Nov/26 | Q28: =Simulacao!I249 -> 48386.833 | R28: =Simulacao!I7 -> 72397.248 | S28: =Simulacao!I250 -> 0 | T28: =Simulacao!I252 -> -24010.415 | U28: =U27+T28 -> -180484.56
P29: Dez/26 | Q29: =Simulacao!J249 -> 50008.847 | R29: =Simulacao!J7 -> 68744.676 | S29: =Simulacao!J250 -> 0 | T29: =Simulacao!J252 -> -18735.829 | U29: =U28+T29 -> -199220.39
P30: Jan/27 | Q30: =Simulacao!K249 -> 47574.253 | R30: =Simulacao!K7 -> 70585.483 | S30: =Simulacao!K250 -> 0 | T30: =Simulacao!K252 -> -23011.23 | U30: =U29+T30 -> -222231.62
P31: Fev/27 | Q31: =Simulacao!L249 -> 50426.883 | R31: =Simulacao!L7 -> 62897.711 | S31: =Simulacao!L250 -> 0 | T31: =Simulacao!L252 -> -12470.828 | U31: =U30+T31 -> -234702.45
P32: Mar/27 | Q32: =Simulacao!M249 -> 45168.521 | R32: =Simulacao!M7 -> 72143.749 | S32: =Simulacao!M250 -> 0 | T32: =Simulacao!M252 -> -26975.227 | U32: =U31+T32 -> -261677.67
P33: Abr/27 | Q33: =Simulacao!N249 -> 39380.616 | R33: =Simulacao!N7 -> 71985.95 | S33: =Simulacao!N250 -> 0 | T33: =Simulacao!N252 -> -32605.333 | U33: =U32+T33 -> -294283.01
P34: Mai/27 | Q34: =Simulacao!O249 -> 36641.224 | R34: =Simulacao!O7 -> 67370.328 | S34: =Simulacao!O250 -> 0 | T34: =Simulacao!O252 -> -30729.103 | U34: =U33+T34 -> -325012.11
P35: Jun/27 | Q35: =Simulacao!P249 -> 136929.15 | R35: =Simulacao!P7 -> 63893.596 | S35: =Simulacao!P250 -> 129586.67 | T35: =Simulacao!P252 -> -56551.124 | U35: =U34+T35 -> -381563.23
P36: Jul/27 | Q36: =Simulacao!Q249 -> 536959.78 | R36: =Simulacao!Q7 -> 67253.433 | S36: =Simulacao!Q250 -> 201204.56 | T36: =Simulacao!Q252 -> 268501.79 | U36: =U35+T36 -> -113061.45
P37: Ago/27 | Q37: =Simulacao!R249 -> 287060.8 | R37: =Simulacao!R7 -> 80734.008 | S37: =Simulacao!R250 -> 94150.865 | T37: =Simulacao!R252 -> 112175.92 | U37: =U36+T37 -> -885.52191
P38: Set/27 | Q38: =Simulacao!S249 -> 51849.395 | R38: =Simulacao!S7 -> 75756.089 | S38: =Simulacao!S250 -> 0 | T38: =Simulacao!S252 -> -23906.694 | U38: =U37+T38 -> -24792.216
P39: Out/27 | Q39: =Simulacao!T249 -> 52745.7 | R39: =Simulacao!T7 -> 77853.411 | S39: =Simulacao!T250 -> 0 | T39: =Simulacao!T252 -> -25107.711 | U39: =U38+T39 -> -49899.927
P40: Nov/27 | Q40: =Simulacao!U249 -> 52572.294 | R40: =Simulacao!U7 -> 75276.849 | S40: =Simulacao!U250 -> 0 | T40: =Simulacao!U252 -> -22704.555 | U40: =U39+T40 -> -72604.482
P41: Dez/27 | Q41: =Simulacao!V249 -> 54334.613 | R41: =Simulacao!V7 -> 71478.995 | S41: =Simulacao!V250 -> 0 | T41: =Simulacao!V252 -> -17144.383 | U41: =U40+T41 -> -89748.864
P42: Jan/28 | Q42: =Simulacao!W249 -> 50428.708 | R42: =Simulacao!W7 -> 73761.83 | S42: =Simulacao!W250 -> 0 | T42: =Simulacao!W252 -> -23333.122 | U42: =U41+T42 -> -113081.99
P43: Fev/28 | Q43: =Simulacao!X249 -> 53452.496 | R43: =Simulacao!X7 -> 65728.108 | S43: =Simulacao!X250 -> 0 | T43: =Simulacao!X252 -> -12275.612 | U43: =U42+T43 -> -125357.6
P44: Mar/28 | Q44: =Simulacao!Y249 -> 252928.82 | R44: =Simulacao!Y7 -> 75390.217 | S44: =Simulacao!Y250 -> 0 | T44: =Simulacao!Y252 -> 177538.6 | U44: =U43+T44 -> 52181.003
B45: D. BANCO DE CRÉDITOS — SALDO FINAL MAI/2028 POR UC | Banco total Copasul (incl. geração própria) | P45: Abr/28 | Q45: =Simulacao!Z249 -> 41743.453 | R45: =Simulacao!Z7 -> 75225.317 | S45: =Simulacao!Z250 -> 0 | T45: =Simulacao!Z252 -> -33481.864 | U45: =U44+T45 -> 18699.139
B46: Unidade Consumidora | C46: Grupo | D46: Saldo (kWh) | E46: Valor @ PPA (R$) | F46: % do banco total | P46: Mai/28 | Q46: =Simulacao!AA249 -> 38839.698 | R46: =Simulacao!AA7 -> 70401.992 | S46: =Simulacao!AA250 -> 0 | T46: =Simulacao!AA252 -> -31562.295 | U46: =U45+T46 -> -12863.156
B47: NHS — Novo Horizonte do Sul | C47: A4V | D47: =Simulacao!B255 -> 412145.7 | E47: =Simulacao!B255*Premissas!$B$17 -> 182374.47 | F47: =IFERROR(Simulacao!B255/Simulacao!B273,0) -> 0.39575715 | P47: Jun/28 | Q47: =Simulacao!AB249 -> 179001.98 | R47: =Simulacao!AB7 -> 66434.963 | S47: =Simulacao!AB250 -> 0 | T47: =Simulacao!AB252 -> 112567.02 | U47: =U46+T47 -> 99703.864
B48: AMD — Amandina | C48: A3A | D48: =Simulacao!B256 -> 596068.37 | E48: =Simulacao!B256*Premissas!$B$17 -> 263760.26 | F48: =IFERROR(Simulacao!B256/Simulacao!B273,0) -> 0.57236632 | P48: Jul/28 | Q48: =Simulacao!AC249 -> 586080.82 | R48: =Simulacao!AC7 -> 69928.438 | S48: =Simulacao!AC250 -> 115571.7 | T48: =Simulacao!AC252 -> 400580.68 | U48: =U47+T48 -> 500284.55
B49: AREC | C49: B3 | D49: =Simulacao!B257 -> 627.07106 | E49: =Simulacao!B257*Premissas!$B$17 -> 277.47895 | F49: =IFERROR(Simulacao!B257/Simulacao!B273,0) -> 0.00060213622 | P49: Ago/28 | Q49: =Simulacao!AD249 -> 310950.82 | R49: =Simulacao!AD7 -> 83945.203 | S49: =Simulacao!AD250 -> 65692.673 | T49: =Simulacao!AD252 -> 161312.94 | U49: =U48+T49 -> 661597.49
B50: Banheiro Motoristas | C50: B3 | D50: =Simulacao!B258 -> 65.992243 | E50: =Simulacao!B258*Premissas!$B$17 -> 29.201568 | F50: =IFERROR(Simulacao!B258/Simulacao!B273,0) -> 6.3368129e-05 | P50: Set/28 | Q50: =Simulacao!AE249 -> 42199.332 | R50: =Simulacao!AE7 -> 78769.288 | S50: =Simulacao!AE250 -> 0 | T50: =Simulacao!AE252 -> -36569.956 | U50: =U49+T50 -> 625027.54
B51: CTC Copasul | C51: B3 | D51: =Simulacao!B259 -> 0 | E51: =Simulacao!B259*Premissas!$B$17 -> 0 | F51: =IFERROR(Simulacao!B259/Simulacao!B273,0) -> 0 | P51: Out/28 | Q51: =Simulacao!AF249 -> 42199.332 | R51: =Simulacao!AF7 -> 80950.03 | S51: =Simulacao!AF250 -> 0 | T51: =Simulacao!AF252 -> -38750.699 | U51: =U50+T51 -> 586276.84
B52: Depósito Irrigação | C52: B3 | D52: =Simulacao!B260 -> 174.63084 | E52: =Simulacao!B260*Premissas!$B$17 -> 77.274148 | F52: =IFERROR(Simulacao!B260/Simulacao!B273,0) -> 0.00016768683 | P52: Nov/28 | Q52: =Simulacao!AG249 -> 42199.332 | R52: =Simulacao!AG7 -> 78270.985 | S52: =Simulacao!AG250 -> 0 | T52: =Simulacao!AG252 -> -36071.654 | U52: =U51+T52 -> 550205.18
B53: Entreposto | C53: B3 | D53: =Simulacao!B261 -> 207.78163 | E53: =Simulacao!B261*Premissas!$B$17 -> 91.943372 | F53: =IFERROR(Simulacao!B261/Simulacao!B273,0) -> 0.00019951941 | P53: Dez/28 | Q53: =Simulacao!AH249 -> 42199.332 | R53: =Simulacao!AH7 -> 74322.073 | S53: =Simulacao!AH250 -> 0 | T53: =Simulacao!AH252 -> -32122.741 | U53: =U52+T53 -> 518082.44
B54: Esc. Deodápolis | C54: B3 | D54: =Simulacao!B262 -> 273.73782 | E54: =Simulacao!B262*Premissas!$B$17 -> 121.12899 | F54: =IFERROR(Simulacao!B262/Simulacao!B273,0) -> 0.00026285292 | P54: Jan/29 | Q54: =Simulacao!AI249 -> 42199.332 | R54: =Simulacao!AI7 -> 76695.707 | S54: =Simulacao!AI250 -> 0 | T54: =Simulacao!AI252 -> -34496.375 | U54: =U53+T54 -> 483586.07
B55: Esc. Nova Andradina | C55: B3 | D55: =Simulacao!B263 -> 228.39983 | E55: =Simulacao!B263*Premissas!$B$17 -> 101.06693 | F55: =IFERROR(Simulacao!B263/Simulacao!B273,0) -> 0.00021931775 | P55: Fev/29 | Q55: =Simulacao!AJ249 -> 42199.332 | R55: =Simulacao!AJ7 -> 68342.444 | S55: =Simulacao!AJ250 -> 0 | T55: =Simulacao!AJ252 -> -26143.112 | U55: =U54+T55 -> 457442.96
B56: Esc. Regional Deodápolis | C56: B3 | D56: =Simulacao!B264 -> 0 | E56: =Simulacao!B264*Premissas!$B$17 -> 0 | F56: =IFERROR(Simulacao!B264/Simulacao!B273,0) -> 0 | P56: Mar/29 | Q56: =Simulacao!AK249 -> 279870.82 | R56: =Simulacao!AK7 -> 78388.863 | S56: =Simulacao!AK250 -> 0 | T56: =Simulacao!AK252 -> 201481.95 | U56: =U55+T56 -> 658924.91
B57: Galpão AE | C57: B3 | D57: =Simulacao!B265 -> 7584.3975 | E57: =Simulacao!B265*Premissas!$B$17 -> 3356.0959 | F57: =IFERROR(Simulacao!B265/Simulacao!B273,0) -> 0.0072828117 | P57: Abr/29 | Q57: =Simulacao!AL249 -> 42199.332 | R57: =Simulacao!AL7 -> 78217.404 | S57: =Simulacao!AL250 -> 0 | T57: =Simulacao!AL252 -> -36018.073 | U57: =U56+T57 -> 622906.84
B58: Irrigação CG | C58: B3 | D58: =Simulacao!B266 -> 0 | E58: =Simulacao!B266*Premissas!$B$17 -> 0 | F58: =IFERROR(Simulacao!B266/Simulacao!B273,0) -> 0 | P58: Mai/29 | Q58: =Simulacao!AM249 -> 42199.332 | R58: =Simulacao!AM7 -> 73202.232 | S58: =Simulacao!AM250 -> 0 | T58: =Simulacao!AM252 -> -31002.9 | U58: =U57+T58 -> 591903.94
B59: Laboratório de Solos | C59: B3 | D59: =Simulacao!B267 -> 14559.877 | E59: =Simulacao!B267*Premissas!$B$17 -> 6442.7457 | F59: =IFERROR(Simulacao!B267/Simulacao!B273,0) -> 0.013980919 | P59: Jun/29 | Q59: =Simulacao!AN249 -> 224172.86 | R59: =Simulacao!AN7 -> 69077.414 | S59: =Simulacao!AN250 -> 0 | T59: =Simulacao!AN252 -> 155095.44 | U59: =U58+T59 -> 746999.38
B60: Posto Carreteiro | C60: B3 | D60: =Simulacao!B268 -> 0 | E60: =Simulacao!B268*Premissas!$B$17 -> 0 | F60: =IFERROR(Simulacao!B268/Simulacao!B273,0) -> 0 | P60: Jul/29 | Q60: =Simulacao!AO249 -> 639858.27 | R60: =Simulacao!AO7 -> 72709.842 | S60: =Simulacao!AO250 -> 0 | T60: =Simulacao!AO252 -> 567148.43 | U60: =U59+T60 -> 1314147.8
B61: Refeitório Deodápolis | C61: B1 | D61: =Simulacao!B269 -> 8759.8746 | E61: =Simulacao!B269*Premissas!$B$17 -> 3876.2445 | F61: =IFERROR(Simulacao!B269/Simulacao!B273,0) -> 0.0084115472 | P61: Ago/29 | Q61: =Simulacao!AP249 -> 341077.32 | R61: =Simulacao!AP7 -> 87284.123 | S61: =Simulacao!AP250 -> 0 | T61: =Simulacao!AP252 -> 253793.19 | U61: =U60+T61 -> 1567941
B62: Subest. Fiação | C62: B3 | D62: =Simulacao!B270 -> 714.79122 | E62: =Simulacao!B270*Premissas!$B$17 -> 316.29512 | F62: =IFERROR(Simulacao!B270/Simulacao!B273,0) -> 0.00068636828 | P62: Set/29 | Q62: =Simulacao!AQ249 -> 45849.574 | R62: =Simulacao!AQ7 -> 81902.336 | S62: =Simulacao!AQ250 -> 0 | T62: =Simulacao!AQ252 -> -36052.762 | U62: =U61+T62 -> 1531888.2
B63: TRR Maracaju | C63: B3 | D63: =Simulacao!B271 -> 0 | E63: =Simulacao!B271*Premissas!$B$17 -> 0 | F63: =IFERROR(Simulacao!B271/Simulacao!B273,0) -> 0 | P63: Out/29 | Q63: =Simulacao!AR249 -> 45849.574 | R63: =Simulacao!AR7 -> 84169.818 | S63: =Simulacao!AR250 -> 0 | T63: =Simulacao!AR252 -> -38320.244 | U63: =U62+T63 -> 1493568
B64: TOTAL — 17 UCs | D64: =Simulacao!B273 -> 1041410.6 | E64: =Simulacao!B273*Premissas!$B$17 -> 460824.2 | F64: =1 -> 1 | P64: Nov/29 | Q64: =Simulacao!AS249 -> 45849.574 | R64: =Simulacao!AS7 -> 81384.214 | S64: =Simulacao!AS250 -> 0 | T64: =Simulacao!AS252 -> -35534.64 | U64: =U63+T64 -> 1458033.4
B65: E. BANCO ATRIBUÍVEL HELEXIA — O QUE A HELEXIA REALMENTE ENTREGA | P65: Dez/29 | Q65: =Simulacao!AT249 -> 45849.574 | R65: =Simulacao!AT7 -> 77278.233 | S65: =Simulacao!AT250 -> 0 | T65: =Simulacao!AT252 -> -31428.659 | U65: =U64+T65 -> 1426604.7
B66: Unidade / Grupo | C66: Banco SEM | D66: Banco COM | E66: Atribuível (kWh) | F66: Atribuível (R$) | P66: Jan/30 | Q66: =Simulacao!AU249 -> 45849.574 | R66: =Simulacao!AU7 -> 79746.278 | S66: =Simulacao!AU250 -> 0 | T66: =Simulacao!AU252 -> -33896.704 | U66: =U65+T66 -> 1392708
B67: NHS — Silos N. Horizonte | C67: =Simulacao!BK34 -> 32298.103 | D67: =Simulacao!BK31 -> 412145.7 | E67: =Simulacao!B281 -> 379847.6 | F67: =Simulacao!B281*Premissas!$B$17 -> 168082.56 | P67: Fev/30 | Q67: =Simulacao!AV249 -> 45849.574 | R67: =Simulacao!AV7 -> 71060.764 | S67: =Simulacao!AV250 -> 0 | T67: =Simulacao!AV252 -> -25211.19 | U67: =U66+T67 -> 1367496.8
B68: AMD — Silos Amandina | C68: =Simulacao!BK52 -> 37933.466 | D68: =Simulacao!BK49 -> 596068.37 | E68: =Simulacao!B282 -> 558134.91 | F68: =Simulacao!B282*Premissas!$B$17 -> 246974.7 | P68: Mar/30 | Q68: =Simulacao!AW249 -> 321769.93 | R68: =Simulacao!AW7 -> 81506.78 | S68: =Simulacao!AW250 -> 0 | T68: =Simulacao!AW252 -> 240263.15 | U68: =U67+T68 -> 1607759.9
B69: Grupo B (15 UCs) | C69: 0 | D69: =Simulacao!BK62+Simulacao!BK75+Simulacao!BK88+Simulacao!BK101+Simulacao!BK114+Simulacao!BK127+Simulacao!BK140+Simulacao!BK153+Simulacao!BK166+Simulacao!BK179+Simulacao!BK192+Simulacao!BK205+Simulacao!BK218+Simulacao!BK230+Simulacao!BK242 -> 33196.554 | E69: =Simulacao!B283 -> 33196.554 | F69: =Simulacao!B283*Premissas!$B$17 -> 14689.475 | P69: Abr/30 | Q69: =Simulacao!AX249 -> 45849.574 | R69: =Simulacao!AX7 -> 81328.502 | S69: =Simulacao!AX250 -> 0 | T69: =Simulacao!AX252 -> -35478.928 | U69: =U68+T69 -> 1572281
B70: TOTAL atribuível Helexia | C70: =C67+C68+C69 -> 70231.569 | D70: =D67+D68+D69 -> 1041410.6 | E70: =Simulacao!B284 -> 971179.06 | F70: =Simulacao!B285 -> 573978.69 | P70: Mai/30 | Q70: =Simulacao!AY249 -> 45849.574 | R70: =Simulacao!AY7 -> 76113.85 | S70: =Simulacao!AY250 -> 0 | T70: =Simulacao!AY252 -> -30264.277 | U70: =U69+T70 -> 1542016.7
P71: Jun/30 | Q71: =Simulacao!AZ249 -> 274874.9 | R71: =Simulacao!AZ7 -> 71824.968 | S71: =Simulacao!AZ250 -> 0 | T71: =Simulacao!AZ252 -> 203049.93 | U71: =U70+T71 -> 1745066.7
P72: Jul/30 | Q72: =Simulacao!BA249 -> 698456.02 | R72: =Simulacao!BA7 -> 75601.876 | S72: =Simulacao!BA250 -> 0 | T72: =Simulacao!BA252 -> 622854.15 | U72: =U71+T72 -> 2367920.8
P73: Ago/30 | Q73: =Simulacao!BB249 -> 373986.4 | R73: =Simulacao!BB7 -> 90755.849 | S73: =Simulacao!BB250 -> 0 | T73: =Simulacao!BB252 -> 283230.55 | U73: =U72+T73 -> 2651151.4
P74: Set/30 | Q74: =Simulacao!BC249 -> 49815.562 | R74: =Simulacao!BC7 -> 85160.001 | S74: =Simulacao!BC250 -> 0 | T74: =Simulacao!BC252 -> -35344.439 | U74: =U73+T74 -> 2615806.9
P75: Out/30 | Q75: =Simulacao!BD249 -> 49815.562 | R75: =Simulacao!BD7 -> 87517.672 | S75: =Simulacao!BD250 -> 0 | T75: =Simulacao!BD252 -> -37702.11 | U75: =U74+T75 -> 2578104.8
P76: Nov/30 | Q76: =Simulacao!BE249 -> 49815.562 | R76: =Simulacao!BE7 -> 84621.271 | S76: =Simulacao!BE250 -> 104.77423 | T76: =Simulacao!BE252 -> -34910.483 | U76: =U75+T76 -> 2543194.3
P77: Dez/30 | Q77: =Simulacao!BF249 -> 49815.562 | R77: =Simulacao!BF7 -> 80351.975 | S77: =Simulacao!BF250 -> 283.34428 | T77: =Simulacao!BF252 -> -30819.757 | U77: =U76+T77 -> 2512374.6
P78: Jan/31 | Q78: =Simulacao!BG249 -> 49815.562 | R78: =Simulacao!BG7 -> 82918.187 | S78: =Simulacao!BG250 -> 253.32355 | T78: =Simulacao!BG252 -> -33355.948 | U78: =U77+T78 -> 2479018.6
P79: Fev/31 | Q79: =Simulacao!BH249 -> 49815.562 | R79: =Simulacao!BH7 -> 73887.206 | S79: =Simulacao!BH250 -> 1518.1386 | T79: =Simulacao!BH252 -> -25589.783 | U79: =U78+T79 -> 2453428.9
P80: Mar/31 | Q80: =Simulacao!BI249 -> 369826.93 | R80: =Simulacao!BI7 -> 84748.712 | S80: =Simulacao!BI250 -> 328.23879 | T80: =Simulacao!BI252 -> 284749.98 | U80: =U79+T80 -> 2738178.8
P81: Abr/31 | Q81: =Simulacao!BJ249 -> 49815.562 | R81: =Simulacao!BJ7 -> 84563.343 | S81: =Simulacao!BJ250 -> 332.90677 | T81: =Simulacao!BJ252 -> -35080.687 | U81: =U80+T81 -> 2703098.1
P82: Mai/31 | Q82: =Simulacao!BK249 -> 49815.562 | R82: =Simulacao!BK7 -> 79141.279 | S82: =Simulacao!BK250 -> 711.88578 | T82: =Simulacao!BK252 -> -30037.603 | U82: =U81+T82 -> 2673060.5
B84: F. BANCO DE CRÉDITOS — SEGREGAÇÃO POR ORIGEM (resposta Weslen 2.2)
B85: Saldo final Mai/2031 decomposto entre banco pré-existente (SEM Helexia) e incremental atribuível à solução Helexia CS3
B87: Unidade / Grupo | C87: Pré-existente (kWh) | D87: Helexia incremental (kWh) | E87: TOTAL Mai/2031 (kWh)
B88: NHS — Silos Novo Horizonte do Sul (A4V) | C88: =Simulacao!BK34 -> 32298.103 | D88: =Simulacao!BK31-Simulacao!BK34 -> 379847.6 | E88: =Simulacao!BK31 -> 412145.7
B89: AMD — Silos Amandina (A3A) | C89: =Simulacao!BK52 -> 37933.466 | D89: =Simulacao!BK49-Simulacao!BK52 -> 558134.91 | E89: =Simulacao!BK49 -> 596068.37
B90: Grupo B — 15 UCs (sem banco próprio) | C90: 0 | D90: =Simulacao!B283 -> 33196.554 | E90: =Simulacao!B283 -> 33196.554
B91: TOTAL banco residual Mai/2031 | C91: =C88+C89+C90 -> 70231.569 | D91: =D88+D89+D90 -> 971179.06 | E91: =E88+E89+E90 -> 1041410.6
B93: Unidade / Grupo | C93: Pré-existente @ PPA (R$) | D93: Helexia incremental @ PPA (R$) | E93: TOTAL @ PPA (R$)
B94: NHS — Silos Novo Horizonte do Sul (A4V) | C94: =C88*Premissas!$B$17*(1+Premissas!$B$123)^4 -> 17043.369 | D94: =D88*Premissas!$B$17*(1+Premissas!$B$123)^4 -> 200441.58 | E94: =E88*Premissas!$B$17*(1+Premissas!$B$123)^4 -> 217484.95
B95: AMD — Silos Amandina (A3A) | C95: =C89*Premissas!$B$17*(1+Premissas!$B$123)^4 -> 20017.091 | D95: =D89*Premissas!$B$17*(1+Premissas!$B$123)^4 -> 294521.92 | E95: =E89*Premissas!$B$17*(1+Premissas!$B$123)^4 -> 314539.01
B96: Grupo B — 15 UCs (sem banco próprio) | C96: 0 | D96: =D90*Premissas!$B$17*(1+Premissas!$B$123)^4 -> 17517.472 | E96: =E90*Premissas!$B$17*(1+Premissas!$B$123)^4 -> 17517.472
B97: TOTAL @ PPA (R$) | C97: =C94+C95+C96 -> 37060.46 | D97: =D94+D95+D96 -> 512480.97 | E97: =E94+E95+E96 -> 549541.43
B100: G. ECONOMIA ANUAL POR UC — RECONCILIAÇÃO COM ECONOMIA LÍQUIDA (resposta Weslen 2.4)
B101: Economia BRUTA de rede por UC (antes do PPA). Reconciliação com Economia Líquida Copasul ao final.
B103: Unidade Consumidora | C103: Y1 (Jun/26–Mai/27) | D103: Y2 (Jun/27–Mai/28) | E103: Y3 (Jun/28–Mai/29) | F103: Y4 (Jun/29–Mai/30) | G103: Y5 (Jun/30–Mai/31) | H103: TOTAL 60m
B104: NHS — Silos Novo Horizonte do Sul (A4V) | C104: =SUM(Simulacao!D37:O37) -> 0 | D104: =SUM(Simulacao!P37:AA37) -> 695609.76 | E104: =SUM(Simulacao!AB37:AM37) -> 780239.69 | F104: =SUM(Simulacao!AN37:AY37) -> 873444.78 | G104: =SUM(Simulacao!AZ37:BK37) -> 977684.64 | H104: =Simulacao!B37 -> 3326978.9
B105: AMD — Silos Amandina (A3A) | C105: =SUM(Simulacao!D55:O55) -> 0 | D105: =SUM(Simulacao!P55:AA55) -> 734.80011 | E105: =SUM(Simulacao!AB55:AM55) -> 225603.06 | F105: =SUM(Simulacao!AN55:AY55) -> 470035.3 | G105: =SUM(Simulacao!AZ55:BK55) -> 540197.36 | H105: =Simulacao!B55 -> 1236570.5
B106: AREC (B3) | C106: =SUM(Simulacao!D68:O68) -> 56778.545 | D106: =SUM(Simulacao!P68:AA68) -> 61505.722 | E106: =SUM(Simulacao!AB68:AM68) -> 59901.098 | F106: =SUM(Simulacao!AN68:AY68) -> 65082.543 | G106: =SUM(Simulacao!AZ68:BK68) -> 70712.183 | H106: =Simulacao!B68 -> 313980.09
B107: Banheiro Motoristas (B3) | C107: =SUM(Simulacao!D81:O81) -> 5576.7434 | D107: =SUM(Simulacao!P81:AA81) -> 6080.4555 | E107: =SUM(Simulacao!AB81:AM81) -> 6606.4149 | F107: =SUM(Simulacao!AN81:AY81) -> 7177.8698 | G107: =SUM(Simulacao!AZ81:BK81) -> 7798.7555 | H107: =Simulacao!B81 -> 33240.239
B108: CTC Copasul (B3) | C108: =SUM(Simulacao!D94:O94) -> 7592.1748 | D108: =SUM(Simulacao!P94:AA94) -> 8154.5665 | E108: =SUM(Simulacao!AB94:AM94) -> 8735.1486 | F108: =SUM(Simulacao!AN94:AY94) -> 9490.739 | G108: =SUM(Simulacao!AZ94:BK94) -> 9540.492 | H108: =Simulacao!B94 -> 43513.121
B109: Depósito Irrigação (B3) | C109: =SUM(Simulacao!D107:O107) -> 11270.078 | D109: =SUM(Simulacao!P107:AA107) -> 12579.787 | E109: =SUM(Simulacao!AB107:AM107) -> 16824.337 | F109: =SUM(Simulacao!AN107:AY107) -> 18279.642 | G109: =SUM(Simulacao!AZ107:BK107) -> 19860.831 | H109: =Simulacao!B107 -> 78814.674
B110: Entreposto (B3) | C110: =SUM(Simulacao!D120:O120) -> 115239.38 | D110: =SUM(Simulacao!P120:AA120) -> 126690.79 | E110: =SUM(Simulacao!AB120:AM120) -> 93869.816 | F110: =SUM(Simulacao!AN120:AY120) -> 101989.55 | G110: =SUM(Simulacao!AZ120:BK120) -> 110811.65 | H110: =Simulacao!B120 -> 548601.2
...

Sheet Premissas
A1: ="PREMISSAS — "&Premissas!$B$13&" × Copasul | Energisa MS" -> PREMISSAS — Cassilândia 03 × Copasul | Energisa MS | M1: 🎯 OTIMIZAÇÃO RATEIO — SOLVER CONFIG
A2: Azul = inputs editáveis | Preto = fórmulas | Verde = links entre abas | M2: Siga o passo a passo abaixo para maximizar Economia Líquida via Excel Solver
A4: A. TARIFAS ENERGISA MS (com tributos ICMS 17% + PIS/COFINS) | M4: ① CÉLULA OBJETIVO (aponte o Solver aqui): | P4: ENDEREÇO | Q4: VALOR ATUAL | R4: OBJETIVO
A5: Tarifa Grupo A FP com tributos (R$/kWh) | B5: 0.52647111 | C5: ← T_AFP: edit here | M5: Economia Líquida Copasul 24m (R$) | P5: Premissas!K5 | Q5: =Simulacao!B252 -> 2673060.5 | R5: ↑ MAXIMIZAR
A6: Tarifa Grupo A Ponta com tributos (R$/kWh) | B6: 2.9723794 | C6: ← T_APT: edit here
A7: Tarifa Grupo B3 com tributos (R$/kWh) | B7: 1.1568636 | C7: ← T_B3: edit here | M7: ② ATIVAR SOLVER (se ainda não estiver ativo) | O7: Arquivo → Opções → Suplementos → Gerenciar: Suplementos do Excel → Ir... → ✓ Solver Add-in → OK
A8: FA = TE_FP / TE_Ponta | B8: 0.60426705 | C8: ← FA: edit here | M8: ③ ABRIR SOLVER | O8: Guia Dados → botão "Solver" (canto direito da faixa de opções)
A9: ICMS (%) | B9: 0.17 | C9: ← ICMS: edit here | M9: ④ CONFIGURAR OBJETIVO | O9: Definir Objetivo: selecione a célula Premissas!K5 → marque ● Máx
A10: PIS + COFINS (%) | B10: 0.0855 | C10: ← PIS_COFINS: edit here | M10: ⑤ DEFINIR CÉLULAS VARIÁVEIS | O10: Alterando Células de Variáveis: Premissas!$B$33:$K$50 (170 variáveis = 17 UCs × 10 períodos)
A11: ICMS isenção autoconsumo remoto ativa? (Art. 23-A RICMS/MS) → 'Sim' = isento | 'Não' = ICMS cobrado sobre kWh compensados pelo CS3 | B11: Sim | C11: =IF($B$11="Sim",0,$B$5*$B$9/(1+$B$9)) -> 0 | D11: =IF($B$11="Sim",0,$B$6*$B$9/(1+$B$9)) -> 0 | E11: =IF($B$11="Sim",0,$B$7*$B$9/(1+$B$9)) -> 0 | F11: ← B=toggle (Sim/Não) | C=ICMS A_FP D=ICMS A_Ponta E=ICMS Grupo B (R$/kWh) — tudo 0 se Sim
A12: B. CONDIÇÕES DO CONTRATO | M12: ⑥ ADICIONAR AS RESTRIÇÕES (Adicionar → preencher cada linha → OK)
A13: Usina | B13: Cassilândia 03 | M13: Célula / Intervalo | O13: Relação | P13: Valor / Restrição | R13: Descrição
A14: Distribuidora | B14: Energisa MS | M14: Premissas!$B$33:$K$50 | O14: >= | P14: 0 | R14: Todos os rateios ≥ 0% (sem valores negativos, P1–P10)
A15: Início do contrato | B15: Jun/2026 | M15: Premissas!$B$51 | O15: = | P15: 1 | R15: Soma P1 = 100% (Jun–Set/26)
A16: Prazo (meses) | B16: 60 | M16: Premissas!$C$51 | O16: = | P16: 1 | R16: Soma P2 = 100% (Out/26–Mar/27)
A17: PPA Helexia CS3 (R$/kWh) | B17: 0.4425 | D17: → PPA Ajustado Y1 (R$/kWh): | E17: =B17*(1+B128) -> 0.4956 | M17: Premissas!$D$51 | O17: = | P17: 1 | R17: Soma P3 = 100% (Abr–Set/27)
A18: H. CENÁRIO CONCORRENTE — ENERGIA ASSINATURA GRUPO B (ex: Plin Energia) | M18: Premissas!$E$51 | O18: = | P18: 1 | R18: Soma P4 = 100% (Out/27–Mai/28)
A19: Grupo B tem contrato Assinatura GD concorrente? | B19: Sim | C19: Desconto (%): | D19: 0.2 | E19: Tarifa B3 SEM efetiva: | F19: =IF(B19="Sim",B7*(1-D19),B7) -> 0.92549092 | M19: Premissas!$F$51 | O19: = | P19: 1 | R19: Soma P5 = 100% (Jun–Nov/28)
A20: C. PREMISSAS DE CRESCIMENTO E DEGRADAÇÃO | M20: Premissas!$G$51 | O20: = | P20: 1 | R20: Soma P6 = 100% (Dez/28–Mai/29)
A21: Crescimento consumo Y2 vs Y1 (%) | B21: 0.025 | C21: ← 2.5% editável | aplica a TODOS os UCs | M21: Premissas!$H$51 | O21: = | P21: 1 | R21: Soma P7 = 100% (Jun–Nov/29)
A22: Crescimento consumo Y3 parcial (Dez/27-Mai/28) (%) | B22: =B21 -> 0.025 | C22: ← mesmo % que Y2 por padrão | M22: Premissas!$I$51 | O22: = | P22: 1 | R22: Soma P8 = 100% (Dez/29–Mai/30)
A23: Degradação geração Y2 (%) | B23: 0.005 | C23: ← 0.5%/ano editável | M23: Premissas!$J$51 | O23: = | P23: 1 | R23: Soma P9 = 100% (Jun–Nov/30)
A24: Usar proxy Batayporã p/ Amandina gen? | B24: Sim | M24: Premissas!$K$51 | O24: = | P24: 1 | R24: Soma P10 = 100% (Dez/30–Mai/31)
A25: D. BANCOS DE CRÉDITOS — SALDO INICIAL (NHS/AMD: demonstrativo Abr/2026 | BAT: demonstrativo Mar/2026 | Conservador: sem projeção Mai-Jun/2026) | M25: Premissas!$B$34:$K$34 | O25: = | P25: 0 | R25: BAT (linha 34) = 0% em todos os períodos (P1–P10)
A26: NHS — Silos Novo Horizonte do Sul (kWh) | B26: 786669 | M26: Premissas!$B$33:$E$50 | O26: <= | P26: 1 | R26: Todos os rateios ≤ 100% (limite superior)
A27: BAT — Silos Batayporã (kWh) [stranded — não transferível CS3] | B27: 791092
A28: AMD — Silos Amandina (kWh) | B28: 0
A29: TOTAL NHS+AMD (kWh) | B29: =B26+B28 -> 786669 | C29: ← BAT stranded bank não incluído no total | M29: ⑦ MÉTODO DE RESOLUÇÃO E OPÇÕES
M30: Método de Resolução: | O30: GRG Não-Linear | P30: O modelo tem funções IF (não-lineares). GRG é o método correto.
A31: ="E. RATEIO FIXO "&INDEX(PVSYST_Helexia!$A$5:$A$7,MATCH(Premissas!$B$13,PVSYST_Helexia!$B$5:$B$7,0))&" — 4 PERÍODOS (edit percentuais — devem somar 100% por período)" -> E. RATEIO FIXO HCS03 — 4 PERÍODOS (edit percentuais — devem somar 100% por período) | F31: Anos 3–5 (estado estacionário) | M31: Opções → Precisão: | O31: 0,000001 | P31: Maior precisão = resultado mais fino.
A32: UC / Planta | B32: P1: Jun–Set/26 | C32: P2: Out/26–Mar/27 | D32: P3: Abr/27–Set/27 | E32: P4: Out/27–Mai/28 | F32: P5: Jun–Nov/28 | G32: P6: Dez/28–Mai/29 | H32: P7: Jun–Nov/29 | I32: P8: Dez/29–Mai/30 | J32: P9: Jun–Nov/30 | K32: P10: Dez/30–Mai/31 | M32: Opções → Iterações: | O32: 1000 | P32: Permite mais buscas antes de parar.
A33: NHS — Silos N. Horizonte (A4V) | B33: 0.738 | C33: 0.5178 | D33: 0.6714 | E33: 0.2592 | F33: 0.4741 | G33: 0.4673 | H33: 0.4724 | I33: 0.4656 | J33: 0.5826 | K33: 0.4621 | M33: Opções → Convergência: | O33: 0,0001 | P33: Critério de parada quando melhoria < este valor.
A34: BAT — Silos Batayporã (A4V) | B34: 0 | C34: 0 | D34: 0 | E34: 0 | F34: 0 | G34: 0 | H34: 0 | I34: 0 | J34: 0 | K34: 0 | M34: ⚠ Otimização local: | O34: Execute 2–3 vezes | P34: GRG pode parar em mínimo local. Rode com rateios iniciais diferentes e fique com o melhor resultado.
A35: AMD — Silos Amandina (A3A) | B35: 0 | C35: 0 | D35: 0.0041 | E35: 0.1561 | F35: 0.3735 | G35: 0.3698 | H35: 0.3726 | I35: 0.3688 | J35: 0.2324 | K35: 0.2925
A36: AREC (B3) | B36: 0.027 | C36: 0.0532 | D36: 0.0311 | E36: 0.0674 | F36: 0.0156 | G36: 0.0171 | H36: 0.016 | I36: 0.0174 | J36: 0.0304 | K36: 0.0322 | M36: ⑧ EXECUTAR → clicar "Resolver" → aceitar "Manter Solução do Solver"
A37: Banheiro Motoristas (B3) | B37: 0.0033 | C37: 0.005 | D37: 0.004 | E37: 0.0045 | F37: 0.0026 | G37: 0.0027 | H37: 0.0026 | I37: 0.0027 | J37: 0.0027 | K37: 0.0034 | M37: Economia Liquida ANTES da otimização (R$): | P37: 670877.66 | Q37: ← valor antes de rodar o Solver (referência)
A38: CTC Copasul (B3) | B38: 0.0031 | C38: 0.0077 | D38: 0.0039 | E38: 0.0072 | F38: 0.0032 | G38: 0.0034 | H38: 0.0032 | I38: 0.0034 | J38: 0.0037 | K38: 0.0043 | M38: Vsalor Banco Residual ANTES da otimização (R$): | P38: =Resumo!H5 -> 460824.2 | Q38: ← valor antes de rodar o Solver (referência)
A39: Depósito Irrigação (B3) | B39: 0.0064 | C39: 0.0114 | D39: 0.0081 | E39: 0.0095 | F39: 0.007 | G39: 0.0075 | H39: 0.0071 | I39: 0.0076 | J39: 0.0098 | K39: 0.0044 | M39: Economia APÓS otimização (R$) — resultado: | P39: =Simulacao!B252 -> 2673060.5 | Q39: ← atualiza automaticamente após o Solver alterar B33:E50
A40: Entreposto (B3) | B40: 0.059 | C40: 0.1067 | D40: 0.0727 | E40: 0.2104 | F40: 0.006 | G40: 0.0064 | H40: 0.0061 | I40: 0.0065 | J40: 0.0075 | K40: 0.0313
A41: Esc. Deodápolis (B3) | B41: 0.0213 | C41: 0.0358 | D41: 0.026 | E41: 0.0439 | F41: 0.0111 | G41: 0.0121 | H41: 0.0113 | I41: 0.0123 | J41: 0.0181 | K41: 0.0212
A42: Esc. Nova Andradina (B3) | B42: 0.0121 | C42: 0.0296 | D42: 0.0159 | E42: 0.0286 | F42: 0.0122 | G42: 0.0133 | H42: 0.0125 | I42: 0.0136 | J42: 0.0137 | K42: 0.0177
A43: Esc. Regional Deodápolis (B3) | B43: 0.0046 | C43: 0.0157 | D43: 0.006 | E43: 0.0147 | F43: 0.0031 | G43: 0.0033 | H43: 0.0031 | I43: 0.0033 | J43: 0.0036 | K43: 0.0048
A44: Galpão AE (B3) | B44: 0.0059 | C44: 0.0043 | D44: 0.0059 | E44: 0.0043 | F44: 0.0025 | G44: 0.0026 | H44: 0.0025 | I44: 0.0027 | J44: 0.0027 | K44: 0.0033
A45: Irrigação CG (B3) | B45: 0.0042 | C45: 0.0114 | D45: 0.0055 | E45: 0.0102 | F45: 0.004 | G45: 0.0042 | H45: 0.004 | I45: 0.0043 | J45: 0.0049 | K45: 0.0043
A46: Lab. Solos (B3) | B46: 0.0234 | C46: 0.0483 | D46: 0.0147 | E46: 0.0267 | F46: 0.0025 | G46: 0.0026 | H46: 0.0025 | I46: 0.0027 | J46: 0.0027 | K46: 0.0033
A47: Posto Carreteiro (B3) | B47: 0.056 | C47: 0.0993 | D47: 0.0824 | E47: 0.1023 | F47: 0.0516 | G47: 0.0531 | H47: 0.052 | I47: 0.0535 | J47: 0.0452 | K47: 0.0699
A48: Refeitório Deodápolis (B1) | B48: 0.0011 | C48: 0.0018 | D48: 0.0014 | E48: 0.0016 | F48: 0.0025 | G48: 0.0026 | H48: 0.0025 | I48: 0.0027 | J48: 0.0027 | K48: 0.0033
A49: Subest. Fiação (B3) | B49: 0.0085 | C49: 0.0153 | D49: 0.0104 | E49: 0.0133 | F49: 0.0073 | G49: 0.008 | H49: 0.0075 | I49: 0.0081 | J49: 0.0101 | K49: 0.0114
A50: TRR Maracaju (B3) | B50: 0.026 | C50: 0.0365 | D50: 0.0367 | E50: 0.0399 | F50: 0.0214 | G50: 0.024 | H50: 0.022 | I50: 0.0246 | J50: 0.0272 | K50: 0.0306
A51: TOTAL (deve = 100%) | B51: =SUM(B33:B50) -> 0.9999 | C51: =SUM(C33:C50) -> 0.9998 | D51: =SUM(D33:D50) -> 1.0002 | E51: =SUM(E33:E50) -> 0.9998 | F51: =SUM(F33:F50) -> 1.0002 | G51: =SUM(G33:G50) -> 1 | H51: =SUM(H33:H50) -> 0.9999 | I51: =SUM(I33:I50) -> 0.9998 | ... K51: =SUM(K33:K50) -> 1
A52: ⚠ Ajuste os percentuais acima para que cada coluna some exatamente 100%. BAT está fixo em 0% — seus créditos futuros entram via mecanismo de rateio próprio (seção F abaixo). A otimização automática maximiza o aproveitamento dos créditos CS3.
A53: ⚠ P5–P10 (Jun/2028–Mai/2031): alocação optimizada (SLSQP, 102 variáveis). NHS ~47–58%, AMD ~29–37%, Posto ~5–7%, TRR ~2–3%, outros GrupoB ~0.3–1.7%. Para re-optimizar P1–P4, use o Solver apenas em B33:E50.
A54: F. RATEIO DO SURPLUS BAT — 2 PERÍODOS (NH 50% / AMD 50% por padrão)
A55: BAT→NHS (%) | B55: 0.5 | C55: ← editável
A56: BAT→AMD (%) | B56: =1-B55 -> 0.5 | C56: ← = 1 − NHS%
A59: ="G. GERAÇÃO "&INDEX(PVSYST_Helexia!$A$5:$A$7,MATCH(Premissas!$B$13,PVSYST_Helexia!$B$5:$B$7,0))&" P50 — PVSYST "&Premissas!$B$13&" (kWh/mês)" -> G. GERAÇÃO HCS03 P50 — PVSYST Cassilândia 03 (kWh/mês)
A60: Degradação Y2 aplicada | B60: =Premissas!$B$23 -> 0.005 | C60: ← Y1: valor direto PVSYST | Y2/Y3: × (1−DEG)
A61: Jun/26 | B61: =INDEX(PVSYST_Helexia!$J$5:$U$7,MATCH(Premissas!$B$13,PVSYST_Helexia!$B$5:$B$7,0),6)*1000 -> 123990 | C61: kWh — CS3 P50 mês 06 (base=136,620 kWh)
A62: Jul/26 | B62: =INDEX(PVSYST_Helexia!$J$5:$U$7,MATCH(Premissas!$B$13,PVSYST_Helexia!$B$5:$B$7,0),7)*1000 -> 130510 | C62: kWh — CS3 P50 mês 07 (base=123,990 kWh)
A63: Ago/26 | B63: =INDEX(PVSYST_Helexia!$J$5:$U$7,MATCH(Premissas!$B$13,PVSYST_Helexia!$B$5:$B$7,0),8)*1000 -> 156670 | C63: kWh — CS3 P50 mês 08 (base=130,510 kWh)
A64: Set/26 | B64: =INDEX(PVSYST_Helexia!$J$5:$U$7,MATCH(Premissas!$B$13,PVSYST_Helexia!$B$5:$B$7,0),9)*1000 -> 147010 | C64: kWh — CS3 P50 mês 09 (base=156,670 kWh)
A65: Out/26 | B65: =INDEX(PVSYST_Helexia!$J$5:$U$7,MATCH(Premissas!$B$13,PVSYST_Helexia!$B$5:$B$7,0),10)*1000 -> 151080 | C65: kWh — CS3 P50 mês 10 (base=147,010 kWh)
A66: Nov/26 | B66: =INDEX(PVSYST_Helexia!$J$5:$U$7,MATCH(Premissas!$B$13,PVSYST_Helexia!$B$5:$B$7,0),11)*1000 -> 146080 | C66: kWh — CS3 P50 mês 11 (base=151,080 kWh)
A67: Dez/26 | B67: =INDEX(PVSYST_Helexia!$J$5:$U$7,MATCH(Premissas!$B$13,PVSYST_Helexia!$B$5:$B$7,0),12)*1000 -> 138710 | C67: kWh — CS3 P50 mês 12 (base=146,080 kWh)
A68: Jan/27 | B68: =INDEX(PVSYST_Helexia!$J$5:$U$7,MATCH(Premissas!$B$13,PVSYST_Helexia!$B$5:$B$7,0),1)*1000*(1-Premissas!$B$23) -> 142424.3 | C68: kWh — CS3 P50 mês 01 (base=2,000 kWh)
A69: Fev/27 | B69: =INDEX(PVSYST_Helexia!$J$5:$U$7,MATCH(Premissas!$B$13,PVSYST_Helexia!$B$5:$B$7,0),2)*1000*(1-Premissas!$B$23) -> 126912.25 | C69: kWh — CS3 P50 mês 02 (base=143,140 kWh)
A70: Mar/27 | B70: =INDEX(PVSYST_Helexia!$J$5:$U$7,MATCH(Premissas!$B$13,PVSYST_Helexia!$B$5:$B$7,0),3)*1000*(1-Premissas!$B$23) -> 145568.5 | C70: kWh — CS3 P50 mês 03 (base=127,550 kWh)
A71: Abr/27 | B71: =INDEX(PVSYST_Helexia!$J$5:$U$7,MATCH(Premissas!$B$13,PVSYST_Helexia!$B$5:$B$7,0),4)*1000*(1-Premissas!$B$23) -> 145250.1 | C71: kWh — CS3 P50 mês 04 (base=146,300 kWh)
A72: Mai/27 | B72: =INDEX(PVSYST_Helexia!$J$5:$U$7,MATCH(Premissas!$B$13,PVSYST_Helexia!$B$5:$B$7,0),5)*1000*(1-Premissas!$B$23) -> 135936.9 | C72: kWh — CS3 P50 mês 05 (base=145,980 kWh)
A73: Jun/27 | B73: =INDEX(PVSYST_Helexia!$J$5:$U$7,MATCH(Premissas!$B$13,PVSYST_Helexia!$B$5:$B$7,0),6)*1000*(1-Premissas!$B$23) -> 123370.05 | C73: kWh — CS3 P50 mês 06 (base=136,620 kWh)
A74: Jul/27 | B74: =INDEX(PVSYST_Helexia!$J$5:$U$7,MATCH(Premissas!$B$13,PVSYST_Helexia!$B$5:$B$7,0),7)*1000*(1-Premissas!$B$23) -> 129857.45 | C74: kWh — CS3 P50 mês 07 (base=123,990 kWh)
A75: Ago/27 | B75: =INDEX(PVSYST_Helexia!$J$5:$U$7,MATCH(Premissas!$B$13,PVSYST_Helexia!$B$5:$B$7,0),8)*1000*(1-Premissas!$B$23) -> 155886.65 | C75: kWh — CS3 P50 mês 08 (base=130,510 kWh)
A76: Set/27 | B76: =INDEX(PVSYST_Helexia!$J$5:$U$7,MATCH(Premissas!$B$13,PVSYST_Helexia!$B$5:$B$7,0),9)*1000*(1-Premissas!$B$23) -> 146274.95 | C76: kWh — CS3 P50 mês 09 (base=156,670 kWh)
A77: Out/27 | B77: =INDEX(PVSYST_Helexia!$J$5:$U$7,MATCH(Premissas!$B$13,PVSYST_Helexia!$B$5:$B$7,0),10)*1000*(1-Premissas!$B$23) -> 150324.6 | C77: kWh — CS3 P50 mês 10 (base=147,010 kWh)
A78: Nov/27 | B78: =INDEX(PVSYST_Helexia!$J$5:$U$7,MATCH(Premissas!$B$13,PVSYST_Helexia!$B$5:$B$7,0),11)*1000*(1-Premissas!$B$23) -> 145349.6 | C78: kWh — CS3 P50 mês 11 (base=151,080 kWh)
A79: Dez/27 | B79: =INDEX(PVSYST_Helexia!$J$5:$U$7,MATCH(Premissas!$B$13,PVSYST_Helexia!$B$5:$B$7,0),12)*1000*(1-Premissas!$B$23) -> 138016.45 | C79: kWh — CS3 P50 mês 12 (base=146,080 kWh)
A80: Jan/28 | B80: =INDEX(PVSYST_Helexia!$J$5:$U$7,MATCH(Premissas!$B$13,PVSYST_Helexia!$B$5:$B$7,0),1)*1000*(1-Premissas!$B$23) -> 142424.3 | C80: kWh — CS3 P50 mês 01 (base=2,000 kWh)
A81: Fev/28 | B81: =INDEX(PVSYST_Helexia!$J$5:$U$7,MATCH(Premissas!$B$13,PVSYST_Helexia!$B$5:$B$7,0),2)*1000*(1-Premissas!$B$23) -> 126912.25 | C81: kWh — CS3 P50 mês 02 (base=143,140 kWh)
A82: Mar/28 | B82: =INDEX(PVSYST_Helexia!$J$5:$U$7,MATCH(Premissas!$B$13,PVSYST_Helexia!$B$5:$B$7,0),3)*1000*(1-Premissas!$B$23) -> 145568.5 | C82: kWh — CS3 P50 mês 03 (base=127,550 kWh)
A83: Abr/28 | B83: =INDEX(PVSYST_Helexia!$J$5:$U$7,MATCH(Premissas!$B$13,PVSYST_Helexia!$B$5:$B$7,0),4)*1000*(1-Premissas!$B$23) -> 145250.1 | C83: kWh — CS3 P50 mês 04 (base=146,300 kWh)
A84: Mai/28 | B84: =INDEX(PVSYST_Helexia!$J$5:$U$7,MATCH(Premissas!$B$13,PVSYST_Helexia!$B$5:$B$7,0),5)*1000*(1-Premissas!$B$23) -> 135936.9 | C84: kWh — CS3 P50 mês 05 (base=145,980 kWh)
A85: Jun/28 | B85: =INDEX(PVSYST_Helexia!$J$5:$U$7,MATCH(Premissas!$B$13,PVSYST_Helexia!$B$5:$B$7,0),6)*1000*(1-Premissas!$B$23)^2 -> 122753.2 | C85: kWh — CS3 P50 mês 06
A86: Jul/28 | B86: =INDEX(PVSYST_Helexia!$J$5:$U$7,MATCH(Premissas!$B$13,PVSYST_Helexia!$B$5:$B$7,0),7)*1000*(1-Premissas!$B$23)^2 -> 129208.16 | C86: kWh — CS3 P50 mês 07
A87: Ago/28 | B87: =INDEX(PVSYST_Helexia!$J$5:$U$7,MATCH(Premissas!$B$13,PVSYST_Helexia!$B$5:$B$7,0),8)*1000*(1-Premissas!$B$23)^2 -> 155107.22 | C87: kWh — CS3 P50 mês 08
A88: Set/28 | B88: =INDEX(PVSYST_Helexia!$J$5:$U$7,MATCH(Premissas!$B$13,PVSYST_Helexia!$B$5:$B$7,0),9)*1000*(1-Premissas!$B$23)^2 -> 145543.58 | C88: kWh — CS3 P50 mês 09
A89: Out/28 | B89: =INDEX(PVSYST_Helexia!$J$5:$U$7,MATCH(Premissas!$B$13,PVSYST_Helexia!$B$5:$B$7,0),10)*1000*(1-Premissas!$B$23)^2 -> 149572.98 | C89: kWh — CS3 P50 mês 10
A90: Nov/28 | B90: =INDEX(PVSYST_Helexia!$J$5:$U$7,MATCH(Premissas!$B$13,PVSYST_Helexia!$B$5:$B$7,0),11)*1000*(1-Premissas!$B$23)^2 -> 144622.85 | C90: kWh — CS3 P50 mês 11
A91: Dez/28 | B91: =INDEX(PVSYST_Helexia!$J$5:$U$7,MATCH(Premissas!$B$13,PVSYST_Helexia!$B$5:$B$7,0),12)*1000*(1-Premissas!$B$23)^2 -> 137326.37 | C91: kWh — CS3 P50 mês 12
A92: Jan/29 | B92: =INDEX(PVSYST_Helexia!$J$5:$U$7,MATCH(Premissas!$B$13,PVSYST_Helexia!$B$5:$B$7,0),1)*1000*(1-Premissas!$B$23)^2 -> 141712.18 | C92: kWh — CS3 P50 mês 01
A93: Fev/29 | B93: =INDEX(PVSYST_Helexia!$J$5:$U$7,MATCH(Premissas!$B$13,PVSYST_Helexia!$B$5:$B$7,0),2)*1000*(1-Premissas!$B$23)^2 -> 126277.69 | C93: kWh — CS3 P50 mês 02
A94: Mar/29 | B94: =INDEX(PVSYST_Helexia!$J$5:$U$7,MATCH(Premissas!$B$13,PVSYST_Helexia!$B$5:$B$7,0),3)*1000*(1-Premissas!$B$23)^2 -> 144840.66 | C94: kWh — CS3 P50 mês 03
A95: Abr/29 | B95: =INDEX(PVSYST_Helexia!$J$5:$U$7,MATCH(Premissas!$B$13,PVSYST_Helexia!$B$5:$B$7,0),4)*1000*(1-Premissas!$B$23)^2 -> 144523.85 | C95: kWh — CS3 P50 mês 04
A96: Mai/29 | B96: =INDEX(PVSYST_Helexia!$J$5:$U$7,MATCH(Premissas!$B$13,PVSYST_Helexia!$B$5:$B$7,0),5)*1000*(1-Premissas!$B$23)^2 -> 135257.22 | C96: kWh — CS3 P50 mês 05
A97: Jun/29 | B97: =INDEX(PVSYST_Helexia!$J$5:$U$7,MATCH(Premissas!$B$13,PVSYST_Helexia!$B$5:$B$7,0),6)*1000*(1-Premissas!$B$23)^3 -> 122139.43 | C97: kWh — CS3 P50 mês 06
A98: Jul/29 | B98: =INDEX(PVSYST_Helexia!$J$5:$U$7,MATCH(Premissas!$B$13,PVSYST_Helexia!$B$5:$B$7,0),7)*1000*(1-Premissas!$B$23)^3 -> 128562.12 | C98: kWh — CS3 P50 mês 07
A99: Ago/29 | B99: =INDEX(PVSYST_Helexia!$J$5:$U$7,MATCH(Premissas!$B$13,PVSYST_Helexia!$B$5:$B$7,0),8)*1000*(1-Premissas!$B$23)^3 -> 154331.68 | C99: kWh — CS3 P50 mês 08
A100: Set/29 | B100: =INDEX(PVSYST_Helexia!$J$5:$U$7,MATCH(Premissas!$B$13,PVSYST_Helexia!$B$5:$B$7,0),9)*1000*(1-Premissas!$B$23)^3 -> 144815.86 | C100: kWh — CS3 P50 mês 09
A101: Out/29 | B101: =INDEX(PVSYST_Helexia!$J$5:$U$7,MATCH(Premissas!$B$13,PVSYST_Helexia!$B$5:$B$7,0),10)*1000*(1-Premissas!$B$23)^3 -> 148825.11 | C101: kWh — CS3 P50 mês 10
A102: Nov/29 | B102: =INDEX(PVSYST_Helexia!$J$5:$U$7,MATCH(Premissas!$B$13,PVSYST_Helexia!$B$5:$B$7,0),11)*1000*(1-Premissas!$B$23)^3 -> 143899.74 | C102: kWh — CS3 P50 mês 11
A103: Dez/29 | B103: =INDEX(PVSYST_Helexia!$J$5:$U$7,MATCH(Premissas!$B$13,PVSYST_Helexia!$B$5:$B$7,0),12)*1000*(1-Premissas!$B$23)^3 -> 136639.74 | C103: kWh — CS3 P50 mês 12
...

Sheet Input_Consumo_GrupoA
A1: INPUT — CONSUMO ORÇADO GRUPO A | Fonte: Consumo_Orçado_2026_GD
A2: Azul = valores editáveis (fonte: arquivo fornecido) | Preto = fórmulas de projeção Y2/Y3
A3: Mês | B3: NHS FP (kWh) | C3: NHS Ponta (kWh) | D3: BAT FP (kWh) | E3: BAT Ponta (kWh) | F3: AMD FP (kWh) | G3: AMD Ponta (kWh)
A4: Jan | B4: 70769.9 | C4: 7863.3 | D4: 113967 | E4: 12663 | F4: 73973.4 | G4: 8219.3
A5: Fev | B5: 243719.7 | C5: 27080 | D5: 125874 | E5: 13986 | F5: 209472.2 | G5: 23274.7
A6: Mar | B6: 331874.1 | C6: 36874.9 | D6: 57499.2 | E6: 6388.8 | F6: 173260.2 | G6: 19251.1
A7: Abr | B7: 102778.3 | C7: 11419.8 | D7: 35640 | E7: 3960 | F7: 78448.4 | G7: 8716.5
A8: Mai | B8: 62814.2 | C8: 6979.4 | D8: 79603.2 | E8: 8844.8 | F8: 102629.5 | G8: 11403.3
A9: Jun | B9: 108694.9 | C9: 12077.2 | D9: 78336 | E9: 8704 | F9: 182444.7 | G9: 20271.6
A10: Jul | B10: 328938.1 | C10: 36548.7 | D10: 115718.4 | E10: 12857.6 | F10: 234799.2 | G10: 26088.8
A11: Ago | B11: 190977.6 | C11: 21219.7 | D11: 23364 | E11: 2596 | F11: 134799.3 | G11: 14977.7
A12: Set | B12: 126478.8 | C12: 14053.2 | D12: 10800 | E12: 1200 | F12: 18637.2 | G12: 2070.8
A13: Out | B13: 28215 | C13: 3135 | D13: 10800 | E13: 1200 | F13: 24382.8 | G13: 2709.2
A14: Nov | B14: 42209.6 | C14: 4690 | D14: 10800 | E14: 1200 | F14: 20225.7 | G14: 2247.3
A15: Dez | B15: 42209.6 | C15: 4690 | D15: 3402 | E15: 378 | F15: 17142.3 | G15: 1904.7
A17: Crescimento Y2 aplicado automaticamente via Premissas!$B$21 (atualmente 2,5%). Altere lá para que todos os 18 UCs sejam atualizados.

Sheet Simulacao
A1: ="SIMULAÇÃO RATEIO FIXO — "&Premissas!$B$13&" × COPASUL | 18 UCs | Jun/2026–Mai/2031" -> SIMULAÇÃO RATEIO FIXO — Cassilândia 03 × COPASUL | 18 UCs | Jun/2026–Mai/2031
A2: Energisa MS · Todas as células são fórmulas · Azul=input Premissas · Verde=link entre abas
A4: INDICADOR / UC | B4: TOTAL 60m ou SALDO FINAL | C4: MÉD/mês ou unidade | D4: Jun/26 | E4: Jul/26 | F4: Ago/26 | G4: Set/26 | H4: Out/26 | I4: Nov/26 | J4: Dez/26 | K4: Jan/27 | L4: Fev/27 | M4: Mar/27 | N4: Abr/27 | O4: Mai/27 | P4: Jun/27 | Q4: Jul/27 | R4: Ago/27 | S4: Set/27 | T4: Out/27 | U4: Nov/27 | V4: Dez/27 | W4: Jan/28 | X4: Fev/28 | Y4: Mar/28 | Z4: Abr/28 | AA4: Mai/28 | AB4: Jun/28 | AC4: Jul/28 | AD4: Ago/28 | AE4: Set/28 | AF4: Out/28 | AG4: Nov/28 | AH4: Dez/28 | AI4: Jan/29 | AJ4: Fev/29 | AK4: Mar/29 | AL4: Abr/29 | AM4: Mai/29 | AN4: Jun/29 | AO4: Jul/29 | AP4: Ago/29 | AQ4: Set/29 | AR4: Out/29 | AS4: Nov/29 | AT4: Dez/29 | AU4: Jan/30 | AV4: Fev/30 | AW4: Mar/30 | AX4: Abr/30 | AY4: Mai/30 | AZ4: Jun/30 | BA4: Jul/30 | BB4: Ago/30 | BC4: Set/30 | BD4: Out/30 | BE4: Nov/30 | BF4: Dez/30 | BG4: Jan/31 | BH4: Fev/31 | BI4: Mar/31 | BJ4: Abr/31 | BK4: Mai/31
A5: ="0. "&Premissas!B13&" — GERAÇÃO E CUSTO PPA" -> 0. Cassilândia 03 — GERAÇÃO E CUSTO PPA
A6: =INDEX(PVSYST_Helexia!$A$5:$A$7,MATCH(Premissas!$B$13,PVSYST_Helexia!$B$5:$B$7,0))&" Geração P50 (kWh)" -> HCS03 Geração P50 (kWh) | B6: =SUM(D6:BQ6) -> 8380442.4 | C6: =B6/60 -> 139674.04 | D6: =Premissas!$B$61 -> 123990 | E6: =Premissas!$B$62 -> 130510 | F6: =Premissas!$B$63 -> 156670 | G6: =Premissas!$B$64 -> 147010 | H6: =Premissas!$B$65 -> 151080 | I6: =Premissas!$B$66 -> 146080 | J6: =Premissas!$B$67 -> 138710 | K6: =Premissas!$B$68 -> 142424.3 | L6: =Premissas!$B$69 -> 126912.25 | M6: =Premissas!$B$70 -> 145568.5 | N6: =Premissas!$B$71 -> 145250.1 | O6: =Premissas!$B$72 -> 135936.9 | P6: =Premissas!$B$73 -> 123370.05 | Q6: =Premissas!$B$74 -> 129857.45 | R6: =Premissas!$B$75 -> 155886.65 | S6: =Premissas!$B$76 -> 146274.95 | T6: =Premissas!$B$77 -> 150324.6 | U6: =Premissas!$B$78 -> 145349.6 | V6: =Premissas!$B$79 -> 138016.45 | W6: =Premissas!$B$80 -> 142424.3 | X6: =Premissas!$B$81 -> 126912.25 | Y6: =Premissas!$B$82 -> 145568.5 | Z6: =Premissas!$B$83 -> 145250.1 | AA6: =Premissas!$B$84 -> 135936.9 | AB6: =Premissas!$B$85 -> 122753.2 | AC6: =Premissas!$B$86 -> 129208.16 | AD6: =Premissas!$B$87 -> 155107.22 | AE6: =Premissas!$B$88 -> 145543.58 | AF6: =Premissas!$B$89 -> 149572.98 | AG6: =Premissas!$B$90 -> 144622.85 | AH6: =Premissas!$B$91 -> 137326.37 | AI6: =Premissas!$B$92 -> 141712.18 | AJ6: =Premissas!$B$93 -> 126277.69 | AK6: =Premissas!$B$94 -> 144840.66 | AL6: =Premissas!$B$95 -> 144523.85 | AM6: =Premissas!$B$96 -> 135257.22 | AN6: =Premissas!$B$97 -> 122139.43 | AO6: =Premissas!$B$98 -> 128562.12 | AP6: =Premissas!$B$99 -> 154331.68 | AQ6: =Premissas!$B$100 -> 144815.86 | AR6: =Premissas!$B$101 -> 148825.11 | AS6: =Premissas!$B$102 -> 143899.74 | AT6: =Premissas!$B$103 -> 136639.74 | AU6: =Premissas!$B$104 -> 141003.62 | AV6: =Premissas!$B$105 -> 125646.3 | AW6: =Premissas!$B$106 -> 144116.45 | AX6: =Premissas!$B$107 -> 143801.23 | AY6: =Premissas!$B$108 -> 134580.93 | AZ6: =Premissas!$B$109 -> 121528.74 | BA6: =Premissas!$B$110 -> 127919.31 | BB6: =Premissas!$B$111 -> 153560.02 | BC6: =Premissas!$B$112 -> 144091.78 | BD6: =Premissas!$B$113 -> 148080.99 | BE6: =Premissas!$B$114 -> 143180.24 | BF6: =Premissas!$B$115 -> 135956.54 | BG6: =Premissas!$B$116 -> 140298.6 | BH6: =Premissas!$B$117 -> 125018.07 | BI6: =Premissas!$B$118 -> 143395.87 | BJ6: =Premissas!$B$119 -> 143082.22 | BK6: =Premissas!$B$120 -> 133908.02
A7: PPA Helexia — custo total (R$) | B7: =SUM(D7:BQ7) -> 4542510.4 | C7: =B7/60 -> 75708.506 | D7: =D6*Premissas!$B$17*(1+Premissas!$B$128)*(1+Premissas!$B$123)^0 -> 61449.444 | E7: =E6*Premissas!$B$17*(1+Premissas!$B$128)*(1+Premissas!$B$123)^0 -> 64680.756 | F7: =F6*Premissas!$B$17*(1+Premissas!$B$128)*(1+Premissas!$B$123)^0 -> 77645.652 | G7: =G6*Premissas!$B$17*(1+Premissas!$B$128)*(1+Premissas!$B$123)^0 -> 72858.156 | H7: =H6*Premissas!$B$17*(1+Premissas!$B$128)*(1+Premissas!$B$123)^0 -> 74875.248 | I7: =I6*Premissas!$B$17*(1+Premissas!$B$128)*(1+Premissas!$B$123)^0 -> 72397.248 | J7: =J6*Premissas!$B$17*(1+Premissas!$B$128)*(1+Premissas!$B$123)^0 -> 68744.676 | K7: =K6*Premissas!$B$17*(1+Premissas!$B$128)*(1+Premissas!$B$123)^0 -> 70585.483 | ... O7: =O6*Premissas!$B$17*(1+Premissas!$B$128)*(1+Premissas!$B$123)^0 -> 67370.328 | P7: =P6*Premissas!$B$17*(1+Premissas!$B$128)*(1+Premissas!$B$123)^1 -> 63893.596 | Q7: =Q6*Premissas!$B$17*(1+Premissas!$B$128)*(1+Premissas!$B$123)^1 -> 67253.433 | R7: =R6*Premissas!$B$17*(1+Premissas!$B$128)*(1+Premissas!$B$123)^1 -> 80734.008 | S7: =S6*Premissas!$B$17*(1+Premissas!$B$128)*(1+Premissas!$B$123)^1 -> 75756.089 | T7: =T6*Premissas!$B$17*(1+Premissas!$B$128)*(1+Premissas!$B$123)^1 -> 77853.411 | U7: =U6*Premissas!$B$17*(1+Premissas!$B$128)*(1+Premissas!$B$123)^1 -> 75276.849 | V7: =V6*Premissas!$B$17*(1+Premissas!$B$128)*(1+Premissas!$B$123)^1 -> 71478.995 | W7: =W6*Premissas!$B$17*(1+Premissas!$B$128)*(1+Premissas!$B$123)^1 -> 73761.83 | ... AA7: =AA6*Premissas!$B$17*(1+Premissas!$B$128)*(1+Premissas!$B$123)^1 -> 70401.992 | AB7: =AB6*Premissas!$B$17*(1+Premissas!$B$128)*(1+Premissas!$B$123)^2 -> 66434.963 | AC7: =AC6*Premissas!$B$17*(1+Premissas!$B$128)*(1+Premissas!$B$123)^2 -> 69928.438 | AD7: =AD6*Premissas!$B$17*(1+Premissas!$B$128)*(1+Premissas!$B$123)^2 -> 83945.203 | AE7: =AE6*Premissas!$B$17*(1+Premissas!$B$128)*(1+Premissas!$B$123)^2 -> 78769.288 | AF7: =AF6*Premissas!$B$17*(1+Premissas!$B$128)*(1+Premissas!$B$123)^2 -> 80950.03 | AG7: =AG6*Premissas!$B$17*(1+Premissas!$B$128)*(1+Premissas!$B$123)^2 -> 78270.985 | AH7: =AH6*Premissas!$B$17*(1+Premissas!$B$128)*(1+Premissas!$B$123)^2 -> 74322.073 | AI7: =AI6*Premissas!$B$17*(1+Premissas!$B$128)*(1+Premissas!$B$123)^2 -> 76695.707 | ... AM7: =AM6*Premissas!$B$17*(1+Premissas!$B$128)*(1+Premissas!$B$123)^2 -> 73202.232 | AN7: =AN6*Premissas!$B$17*(1+Premissas!$B$128)*(1+Premissas!$B$123)^3 -> 69077.414 | AO7: =AO6*Premissas!$B$17*(1+Premissas!$B$128)*(1+Premissas!$B$123)^3 -> 72709.842 | AP7: =AP6*Premissas!$B$17*(1+Premissas!$B$128)*(1+Premissas!$B$123)^3 -> 87284.123 | AQ7: =AQ6*Premissas!$B$17*(1+Premissas!$B$128)*(1+Premissas!$B$123)^3 -> 81902.336 | AR7: =AR6*Premissas!$B$17*(1+Premissas!$B$128)*(1+Premissas!$B$123)^3 -> 84169.818 | AS7: =AS6*Premissas!$B$17*(1+Premissas!$B$128)*(1+Premissas!$B$123)^3 -> 81384.214 | AT7: =AT6*Premissas!$B$17*(1+Premissas!$B$128)*(1+Premissas!$B$123)^3 -> 77278.233 | AU7: =AU6*Premissas!$B$17*(1+Premissas!$B$128)*(1+Premissas!$B$123)^3 -> 79746.278 | ... AY7: =AY6*Premissas!$B$17*(1+Premissas!$B$128)*(1+Premissas!$B$123)^3 -> 76113.85 | AZ7: =AZ6*Premissas!$B$17*(1+Premissas!$B$128)*(1+Premissas!$B$123)^4 -> 71824.968 | BA7: =BA6*Premissas!$B$17*(1+Premissas!$B$128)*(1+Premissas!$B$123)^4 -> 75601.876 | BB7: =BB6*Premissas!$B$17*(1+Premissas!$B$128)*(1+Premissas!$B$123)^4 -> 90755.849 | BC7: =BC6*Premissas!$B$17*(1+Premissas!$B$128)*(1+Premissas!$B$123)^4 -> 85160.001 | BD7: =BD6*Premissas!$B$17*(1+Premissas!$B$128)*(1+Premissas!$B$123)^4 -> 87517.672 | BE7: =BE6*Premissas!$B$17*(1+Premissas!$B$128)*(1+Premissas!$B$123)^4 -> 84621.271 | BF7: =BF6*Premissas!$B$17*(1+Premissas!$B$128)*(1+Premissas!$B$123)^4 -> 80351.975 | BG7: =BG6*Premissas!$B$17*(1+Premissas!$B$128)*(1+Premissas!$B$123)^4 -> 82918.187 | ... BK7: =BK6*Premissas!$B$17*(1+Premissas!$B$128)*(1+Premissas!$B$123)^4 -> 79141.279
A8: 1. BAT — BATAYPORÃ — GERAÇÃO, CONSUMO E SURPLUS
A9: BAT Geração própria (kWh) | B9: =SUM(D9:BQ9) -> 5593986.3 | C9: =B9/60 -> 93233.104 | D9: =+Batayporã!I8 -> 72286.9 | E9: =+Batayporã!I9 -> 88336.8 | F9: =+Batayporã!I10 -> 93082.7 | G9: =+Batayporã!I11 -> 94433.4 | H9: =+Batayporã!I12 -> 95906.8 | I9: =+Batayporã!I13 -> 107980.6 | J9: =+Batayporã!I14 -> 106603.9 | K9: =+Batayporã!I3*(1-Premissas!$B$23) -> 113687.7 | L9: =+Batayporã!I4*(1-Premissas!$B$23) -> 90676.241 | M9: =+Batayporã!I5*(1-Premissas!$B$23) -> 102546.59 | N9: =+Batayporã!I6*(1-Premissas!$B$23) -> 73341.151 | O9: =+Batayporã!I7*(1-Premissas!$B$23) -> 91158.517 | P9: =D9*(1-Premissas!$B$23) -> 71925.465 | Q9: =E9*(1-Premissas!$B$23) -> 87895.116 | R9: =F9*(1-Premissas!$B$23) -> 92617.287 | S9: =G9*(1-Premissas!$B$23) -> 93961.233 | T9: =H9*(1-Premissas!$B$23) -> 95427.266 | U9: =I9*(1-Premissas!$B$23) -> 107440.7 | V9: =J9*(1-Premissas!$B$23) -> 106070.88 | W9: =K9*(1-Premissas!$B$23) -> 113119.27 | ... BK9: =AY9*(1-Premissas!$B$23) -> 89348.975
A10: BAT Consumo FP (kWh) | B10: =SUM(D10:BQ10) -> 3509998.1 | C10: =B10/60 -> 58499.968 | D10: =Input_Consumo_GrupoA!$D$9 -> 78336 | E10: =Input_Consumo_GrupoA!$D$10 -> 115718.4 | F10: =Input_Consumo_GrupoA!$D$11 -> 23364 | G10: =Input_Consumo_GrupoA!$D$12 -> 10800 | H10: =Input_Consumo_GrupoA!$D$13 -> 10800 | I10: =Input_Consumo_GrupoA!$D$14 -> 10800 | J10: =Input_Consumo_GrupoA!$D$15 -> 3402 | K10: =Input_Consumo_GrupoA!$D$4*(1+Premissas!$B$21) -> 116816.17 | L10: =Input_Consumo_GrupoA!$D$5*(1+Premissas!$B$21) -> 129020.85 | M10: =Input_Consumo_GrupoA!$D$6*(1+Premissas!$B$21) -> 58936.68 | N10: =Input_Consumo_GrupoA!$D$7*(1+Premissas!$B$21) -> 36531 | O10: =Input_Consumo_GrupoA!$D$8*(1+Premissas!$B$21) -> 81593.28 | P10: =Input_Consumo_GrupoA!$D$9*(1+Premissas!$B$21) -> 80294.4 | Q10: =Input_Consumo_GrupoA!$D$10*(1+Premissas!$B$21) -> 118611.36 | R10: =Input_Consumo_GrupoA!$D$11*(1+Premissas!$B$21) -> 23948.1 | S10: =Input_Consumo_GrupoA!$D$12*(1+Premissas!$B$21) -> 11070 | T10: =Input_Consumo_GrupoA!$D$13*(1+Premissas!$B$21) -> 11070 | U10: =Input_Consumo_GrupoA!$D$14*(1+Premissas!$B$21) -> 11070 | V10: =Input_Consumo_GrupoA!$D$15*(1+Premissas!$B$21) -> 3487.05 | W10: =Input_Consumo_GrupoA!$D$4*(1+Premissas!$B$21) -> 116816.17 | X10: =Input_Consumo_GrupoA!$D$5*(1+Premissas!$B$21) -> 129020.85 | Y10: =Input_Consumo_GrupoA!$D$6*(1+Premissas!$B$21) -> 58936.68 | Z10: =Input_Consumo_GrupoA!$D$7*(1+Premissas!$B$21) -> 36531 | AA10: =Input_Consumo_GrupoA!$D$8*(1+Premissas!$B$21) -> 81593.28 | AB10: =Input_Consumo_GrupoA!$D$9*(1+Premissas!$B$21)^2 -> 82301.76 | AC10: =Input_Consumo_GrupoA!$D$10*(1+Premissas!$B$21)^2 -> 121576.64 | AD10: =Input_Consumo_GrupoA!$D$11*(1+Premissas!$B$21)^2 -> 24546.802 | AE10: =Input_Consumo_GrupoA!$D$12*(1+Premissas!$B$21)^2 -> 11346.75 | AF10: =Input_Consumo_GrupoA!$D$13*(1+Premissas!$B$21)^2 -> 11346.75 | AG10: =Input_Consumo_GrupoA!$D$14*(1+Premissas!$B$21)^2 -> 11346.75 | AH10: =Input_Consumo_GrupoA!$D$15*(1+Premissas!$B$21)^2 -> 3574.2262 | AI10: =Input_Consumo_GrupoA!$D$4*(1+Premissas!$B$21)^2 -> 119736.58 | AJ10: =Input_Consumo_GrupoA!$D$5*(1+Premissas!$B$21)^2 -> 132246.37 | AK10: =Input_Consumo_GrupoA!$D$6*(1+Premissas!$B$21)^2 -> 60410.097 | AL10: =Input_Consumo_GrupoA!$D$7*(1+Premissas!$B$21)^2 -> 37444.275 | AM10: =Input_Consumo_GrupoA!$D$8*(1+Premissas!$B$21)^2 -> 83633.112 | AN10: =Input_Consumo_GrupoA!$D$9*(1+Premissas!$B$21)^3 -> 84359.304 | AO10: =Input_Consumo_GrupoA!$D$10*(1+Premissas!$B$21)^3 -> 124616.06 | AP10: =Input_Consumo_GrupoA!$D$11*(1+Premissas!$B$21)^3 -> 25160.473 | AQ10: =Input_Consumo_GrupoA!$D$12*(1+Premissas!$B$21)^3 -> 11630.419 | AR10: =Input_Consumo_GrupoA!$D$13*(1+Premissas!$B$21)^3 -> 11630.419 | AS10: =Input_Consumo_GrupoA!$D$14*(1+Premissas!$B$21)^3 -> 11630.419 | AT10: =Input_Consumo_GrupoA!$D$15*(1+Premissas!$B$21)^3 -> 3663.5819 | AU10: =Input_Consumo_GrupoA!$D$4*(1+Premissas!$B$21)^3 -> 122729.99 | AV10: =Input_Consumo_GrupoA!$D$5*(1+Premissas!$B$21)^3 -> 135552.53 | AW10: =Input_Consumo_GrupoA!$D$6*(1+Premissas!$B$21)^3 -> 61920.349 | AX10: =Input_Consumo_GrupoA!$D$7*(1+Premissas!$B$21)^3 -> 38380.382 | AY10: =Input_Consumo_GrupoA!$D$8*(1+Premissas!$B$21)^3 -> 85723.94 | AZ10: =Input_Consumo_GrupoA!$D$9*(1+Premissas!$B$21)^4 -> 86468.287 | BA10: =Input_Consumo_GrupoA!$D$10*(1+Premissas!$B$21)^4 -> 127731.46 | BB10: =Input_Consumo_GrupoA!$D$11*(1+Premissas!$B$21)^4 -> 25789.484 | BC10: =Input_Consumo_GrupoA!$D$12*(1+Premissas!$B$21)^4 -> 11921.179 | BD10: =Input_Consumo_GrupoA!$D$13*(1+Premissas!$B$21)^4 -> 11921.179 | BE10: =Input_Consumo_GrupoA!$D$14*(1+Premissas!$B$21)^4 -> 11921.179 | BF10: =Input_Consumo_GrupoA!$D$15*(1+Premissas!$B$21)^4 -> 3755.1715 | BG10: =Input_Consumo_GrupoA!$D$4*(1+Premissas!$B$21)^4 -> 125798.24 | BH10: =Input_Consumo_GrupoA!$D$5*(1+Premissas!$B$21)^4 -> 138941.34 | BI10: =Input_Consumo_GrupoA!$D$6*(1+Premissas!$B$21)^4 -> 63468.358 | BJ10: =Input_Consumo_GrupoA!$D$7*(1+Premissas!$B$21)^4 -> 39339.891 | BK10: =Input_Consumo_GrupoA!$D$8*(1+Premissas!$B$21)^4 -> 87867.038
A11: BAT Consumo Ponta (kWh) | B11: =SUM(D11:BQ11) -> 389999.79 | C11: =B11/60 -> 6499.9965 | D11: =Input_Consumo_GrupoA!$E$9 -> 8704 | E11: =Input_Consumo_GrupoA!$E$10 -> 12857.6 | F11: =Input_Consumo_GrupoA!$E$11 -> 2596 | G11: =Input_Consumo_GrupoA!$E$12 -> 1200 | H11: =Input_Consumo_GrupoA!$E$13 -> 1200 | I11: =Input_Consumo_GrupoA!$E$14 -> 1200 | J11: =Input_Consumo_GrupoA!$E$15 -> 378 | K11: =Input_Consumo_GrupoA!$E$4*(1+Premissas!$B$21) -> 12979.575 | L11: =Input_Consumo_GrupoA!$E$5*(1+Premissas!$B$21) -> 14335.65 | M11: =Input_Consumo_GrupoA!$E$6*(1+Premissas!$B$21) -> 6548.52 | N11: =Input_Consumo_GrupoA!$E$7*(1+Premissas!$B$21) -> 4059 | O11: =Input_Consumo_GrupoA!$E$8*(1+Premissas!$B$21) -> 9065.92 | P11: =Input_Consumo_GrupoA!$E$9*(1+Premissas!$B$21) -> 8921.6 | Q11: =Input_Consumo_GrupoA!$E$10*(1+Premissas!$B$21) -> 13179.04 | R11: =Input_Consumo_GrupoA!$E$11*(1+Premissas!$B$21) -> 2660.9 | S11: =Input_Consumo_GrupoA!$E$12*(1+Premissas!$B$21) -> 1230 | T11: =Input_Consumo_GrupoA!$E$13*(1+Premissas!$B$21) -> 1230 | U11: =Input_Consumo_GrupoA!$E$14*(1+Premissas!$B$21) -> 1230 | V11: =Input_Consumo_GrupoA!$E$15*(1+Premissas!$B$21) -> 387.45 | W11: =Input_Consumo_GrupoA!$E$4*(1+Premissas!$B$21) -> 12979.575 | X11: =Input_Consumo_GrupoA!$E$5*(1+Premissas!$B$21) -> 14335.65 | Y11: =Input_Consumo_GrupoA!$E$6*(1+Premissas!$B$21) -> 6548.52 | Z11: =Input_Consumo_GrupoA!$E$7*(1+Premissas!$B$21) -> 4059 | AA11: =Input_Consumo_GrupoA!$E$8*(1+Premissas!$B$21) -> 9065.92 | AB11: =Input_Consumo_GrupoA!$E$9*(1+Premissas!$B$21)^2 -> 9144.64 | AC11: =Input_Consumo_GrupoA!$E$10*(1+Premissas!$B$21)^2 -> 13508.516 | AD11: =Input_Consumo_GrupoA!$E$11*(1+Premissas!$B$21)^2 -> 2727.4225 | AE11: =Input_Consumo_GrupoA!$E$12*(1+Premissas!$B$21)^2 -> 1260.75 | AF11: =Input_Consumo_GrupoA!$E$13*(1+Premissas!$B$21)^2 -> 1260.75 | AG11: =Input_Consumo_GrupoA!$E$14*(1+Premissas!$B$21)^2 -> 1260.75 | AH11: =Input_Consumo_GrupoA!$E$15*(1+Premissas!$B$21)^2 -> 397.13625 | AI11: =Input_Consumo_GrupoA!$E$4*(1+Premissas!$B$21)^2 -> 13304.064 | AJ11: =Input_Consumo_GrupoA!$E$5*(1+Premissas!$B$21)^2 -> 14694.041 | AK11: =Input_Consumo_GrupoA!$E$6*(1+Premissas!$B$21)^2 -> 6712.233 | AL11: =Input_Consumo_GrupoA!$E$7*(1+Premissas!$B$21)^2 -> 4160.475 | AM11: =Input_Consumo_GrupoA!$E$8*(1+Premissas!$B$21)^2 -> 9292.568 | AN11: =Input_Consumo_GrupoA!$E$9*(1+Premissas!$B$21)^3 -> 9373.256 | AO11: =Input_Consumo_GrupoA!$E$10*(1+Premissas!$B$21)^3 -> 13846.229 | AP11: =Input_Consumo_GrupoA!$E$11*(1+Premissas!$B$21)^3 -> 2795.6081 | AQ11: =Input_Consumo_GrupoA!$E$12*(1+Premissas!$B$21)^3 -> 1292.2687 | AR11: =Input_Consumo_GrupoA!$E$13*(1+Premissas!$B$21)^3 -> 1292.2687 | AS11: =Input_Consumo_GrupoA!$E$14*(1+Premissas!$B$21)^3 -> 1292.2687 | AT11: =Input_Consumo_GrupoA!$E$15*(1+Premissas!$B$21)^3 -> 407.06466 | AU11: =Input_Consumo_GrupoA!$E$4*(1+Premissas!$B$21)^3 -> 13636.666 | AV11: =Input_Consumo_GrupoA!$E$5*(1+Premissas!$B$21)^3 -> 15061.392 | AW11: =Input_Consumo_GrupoA!$E$6*(1+Premissas!$B$21)^3 -> 6880.0388 | AX11: =Input_Consumo_GrupoA!$E$7*(1+Premissas!$B$21)^3 -> 4264.4869 | AY11: =Input_Consumo_GrupoA!$E$8*(1+Premissas!$B$21)^3 -> 9524.8822 | AZ11: =Input_Consumo_GrupoA!$E$9*(1+Premissas!$B$21)^4 -> 9607.5874 | BA11: =Input_Consumo_GrupoA!$E$10*(1+Premissas!$B$21)^4 -> 14192.385 | BB11: =Input_Consumo_GrupoA!$E$11*(1+Premissas!$B$21)^4 -> 2865.4983 | BC11: =Input_Consumo_GrupoA!$E$12*(1+Premissas!$B$21)^4 -> 1324.5755 | BD11: =Input_Consumo_GrupoA!$E$13*(1+Premissas!$B$21)^4 -> 1324.5755 | BE11: =Input_Consumo_GrupoA!$E$14*(1+Premissas!$B$21)^4 -> 1324.5755 | BF11: =Input_Consumo_GrupoA!$E$15*(1+Premissas!$B$21)^4 -> 417.24127 | BG11: =Input_Consumo_GrupoA!$E$4*(1+Premissas!$B$21)^4 -> 13977.583 | BH11: =Input_Consumo_GrupoA!$E$5*(1+Premissas!$B$21)^4 -> 15437.927 | BI11: =Input_Consumo_GrupoA!$E$6*(1+Premissas!$B$21)^4 -> 7052.0398 | BJ11: =Input_Consumo_GrupoA!$E$7*(1+Premissas!$B$21)^4 -> 4371.099 | BK11: =Input_Consumo_GrupoA!$E$8*(1+Premissas!$B$21)^4 -> 9763.0043
A12: BAT auto-comp. FP (kWh) | B12: =SUM(D12:BQ12) -> 3030085.2 | C12: =B12/60 -> 50501.419 | D12: =MIN(D9,D10) -> 72286.9 | E12: =MIN(E9,E10) -> 88336.8 | F12: =MIN(F9,F10) -> 23364 | G12: =MIN(G9,G10) -> 10800 | H12: =MIN(H9,H10) -> 10800 | I12: =MIN(I9,I10) -> 10800 | J12: =MIN(J9,J10) -> 3402 | K12: =MIN(K9,K10) -> 113687.7 | ... BK12: =MIN(BK9,BK10) -> 87867.038
A13: BAT auto-comp. Ponta via FA (kWh) | B13: =SUM(D13:BQ13) -> 107850.19 | C13: =B13/60 -> 1797.5031 | D13: =MIN((D9-D12)*Premissas!$B$8,D11) -> 0 | E13: =MIN((E9-E12)*Premissas!$B$8,E11) -> 0 | F13: =MIN((F9-F12)*Premissas!$B$8,F11) -> 2596 | G13: =MIN((G9-G12)*Premissas!$B$8,G11) -> 1200 | H13: =MIN((H9-H12)*Premissas!$B$8,H11) -> 1200 | I13: =MIN((I9-I12)*Premissas!$B$8,I11) -> 1200 | J13: =MIN((J9-J12)*Premissas!$B$8,J11) -> 378 | K13: =MIN((K9-K12)*Premissas!$B$8,K11) -> 0 | ... BK13: =MIN((BK9-BK12)*Premissas!$B$8,BK11) -> 895.48547
A14: ★ BAT surplus líquido → rateio (kWh) | B14: =SUM(D14:BQ14) -> 2385420.1 | C14: =B14/60 -> 39757.002 | D14: =MAX(D9-D12-D11/Premissas!$B$8,0) -> 0 | E14: =MAX(E9-E12-E11/Premissas!$B$8,0) -> 0 | F14: =MAX(F9-F12-F11/Premissas!$B$8,0) -> 65422.586 | G14: =MAX(G9-G12-G11/Premissas!$B$8,0) -> 81647.523 | H14: =MAX(H9-H12-H11/Premissas!$B$8,0) -> 83120.923 | I14: =MAX(I9-I12-I11/Premissas!$B$8,0) -> 95194.723 | J14: =MAX(J9-J12-J11/Premissas!$B$8,0) -> 102576.35 | K14: =MAX(K9-K12-K11/Premissas!$B$8,0) -> 0 | ... BK14: =MAX(BK9-BK12-BK11/Premissas!$B$8,0) -> 0
A15: BAT banco stranded — depleção por consumo próprio apenas
A16: BAT banco início mês (kWh) | B16: =AA16 -> 466505.89 | C16: — | D16: =Premissas!$B$27 -> 791092 | E16: =D18 -> 770638.67 | F16: =E18 -> 721979.06 | G16: =F18 -> 721979.06 | H16: =G18 -> 721979.06 | I16: =H18 -> 721979.06 | J16: =I18 -> 721979.06 | K16: =J18 -> 721979.06 | L16: =K18 -> 697370.73 | ... BK16: =BJ18 -> 0
A17: BAT banco draw (kWh) | B17: =SUM(D17:BQ17) -> 791092 | C17: =B17/60 -> 13184.867 | D17: =MIN(D16,MAX(D10-D12,0)+IF(Premissas!$B$8=0,0,MAX(D11-D13,0)/Premissas!$B$8)) -> 20453.327 | E17: =MIN(E16,MAX(E10-E12,0)+IF(Premissas!$B$8=0,0,MAX(E11-E13,0)/Premissas!$B$8)) -> 48659.609 | F17: =MIN(F16,MAX(F10-F12,0)+IF(Premissas!$B$8=0,0,MAX(F11-F13,0)/Premissas!$B$8)) -> 0 | G17: =MIN(G16,MAX(G10-G12,0)+IF(Premissas!$B$8=0,0,MAX(G11-G13,0)/Premissas!$B$8)) -> 0 | H17: =MIN(H16,MAX(H10-H12,0)+IF(Premissas!$B$8=0,0,MAX(H11-H13,0)/Premissas!$B$8)) -> 0 | I17: =MIN(I16,MAX(I10-I12,0)+IF(Premissas!$B$8=0,0,MAX(I11-I13,0)/Premissas!$B$8)) -> 0 | J17: =MIN(J16,MAX(J10-J12,0)+IF(Premissas!$B$8=0,0,MAX(J11-J13,0)/Premissas!$B$8)) -> 0 | K17: =MIN(K16,MAX(K10-K12,0)+IF(Premissas!$B$8=0,0,MAX(K11-K13,0)/Premissas!$B$8)) -> 24608.336 | ... BK17: =MIN(BK16,MAX(BK10-BK12,0)+IF(Premissas!$B$8=0,0,MAX(BK11-BK13,0)/Premissas!$B$8)) -> 0
A18: BAT banco fim mês (kWh) | B18: =AA18 -> 460612.17 | C18: — | D18: =MAX(D16-D17,0) -> 770638.67 | E18: =MAX(E16-E17,0) -> 721979.06 | F18: =MAX(F16-F17,0) -> 721979.06 | G18: =MAX(G16-G17,0) -> 721979.06 | H18: =MAX(H16-H17,0) -> 721979.06 | I18: =MAX(I16-I17,0) -> 721979.06 | J18: =MAX(J16-J17,0) -> 721979.06 | K18: =MAX(K16-K17,0) -> 697370.73 | ... BK18: =MAX(BK16-BK17,0) -> 0
A19: BAT créditos → NHS (kWh, T+1) | B19: =SUM(D19:BQ19) -> 1192710.1 | C19: =B19/60 -> 19878.501 | D19: =0 -> 0 | E19: =D14*Premissas!$B$55 -> 0 | F19: =E14*Premissas!$B$55 -> 0 | G19: =F14*Premissas!$B$55 -> 32711.293 | H19: =G14*Premissas!$B$55 -> 40823.762 | I19: =H14*Premissas!$B$55 -> 41560.462 | J19: =I14*Premissas!$B$55 -> 47597.362 | K19: =J14*Premissas!$B$55 -> 51288.174 | L19: =K14*Premissas!$B$55 -> 0 | ... BK19: =BJ14*Premissas!$B$55 -> 12655.84
A20: BAT créditos → AMD (kWh, T+1) | B20: =SUM(D20:BQ20) -> 1192710.1 | C20: =B20/60 -> 19878.501 | D20: =0 -> 0 | E20: =D14*Premissas!$B$56 -> 0 | F20: =E14*Premissas!$B$56 -> 0 | G20: =F14*Premissas!$B$56 -> 32711.293 | H20: =G14*Premissas!$B$56 -> 40823.762 | I20: =H14*Premissas!$B$56 -> 41560.462 | J20: =I14*Premissas!$B$56 -> 47597.362 | K20: =J14*Premissas!$B$56 -> 51288.174 | L20: =K14*Premissas!$B$56 -> 0 | ... BK20: =BJ14*Premissas!$B$56 -> 12655.84
A21: NHS — N. Horizonte do Sul (A4V)
A22: Consumo FP (kWh) | B22: =SUM(D22:BQ22) -> 8849247.7 | C22: =B22/60 -> 147487.46 | D22: =Input_Consumo_GrupoA!$B$9 -> 108694.9 | E22: =Input_Consumo_GrupoA!$B$10 -> 328938.1 | F22: =Input_Consumo_GrupoA!$B$11 -> 190977.6 | G22: =Input_Consumo_GrupoA!$B$12 -> 126478.8 | H22: =Input_Consumo_GrupoA!$B$13 -> 28215 | I22: =Input_Consumo_GrupoA!$B$14 -> 42209.6 | J22: =Input_Consumo_GrupoA!$B$15 -> 42209.6 | K22: =Input_Consumo_GrupoA!$B$4*(1+Premissas!$B$21) -> 72539.147 | L22: =Input_Consumo_GrupoA!$B$5*(1+Premissas!$B$21) -> 249812.69 | M22: =Input_Consumo_GrupoA!$B$6*(1+Premissas!$B$21) -> 340170.95 | N22: =Input_Consumo_GrupoA!$B$7*(1+Premissas!$B$21) -> 105347.76 | O22: =Input_Consumo_GrupoA!$B$8*(1+Premissas!$B$21) -> 64384.555 | P22: =Input_Consumo_GrupoA!$B$9*(1+Premissas!$B$21) -> 111412.27 | Q22: =Input_Consumo_GrupoA!$B$10*(1+Premissas!$B$21) -> 337161.55 | R22: =Input_Consumo_GrupoA!$B$11*(1+Premissas!$B$21) -> 195752.04 | S22: =Input_Consumo_GrupoA!$B$12*(1+Premissas!$B$21) -> 129640.77 | T22: =Input_Consumo_GrupoA!$B$13*(1+Premissas!$B$21) -> 28920.375 | U22: =Input_Consumo_GrupoA!$B$14*(1+Premissas!$B$21) -> 43264.84 | V22: =Input_Consumo_GrupoA!$B$15*(1+Premissas!$B$21) -> 43264.84 | W22: =Input_Consumo_GrupoA!$B$4*(1+Premissas!$B$21) -> 72539.147 | X22: =Input_Consumo_GrupoA!$B$5*(1+Premissas!$B$21) -> 249812.69 | Y22: =Input_Consumo_GrupoA!$B$6*(1+Premissas!$B$21) -> 340170.95 | Z22: =Input_Consumo_GrupoA!$B$7*(1+Premissas!$B$21) -> 105347.76 | AA22: =Input_Consumo_GrupoA!$B$8*(1+Premissas!$B$21) -> 64384.555 | AB22: =Input_Consumo_GrupoA!$B$9*(1+Premissas!$B$21)^2 -> 114197.58 | AC22: =Input_Consumo_GrupoA!$B$10*(1+Premissas!$B$21)^2 -> 345590.59 | AD22: =Input_Consumo_GrupoA!$B$11*(1+Premissas!$B$21)^2 -> 200645.84 | AE22: =Input_Consumo_GrupoA!$B$12*(1+Premissas!$B$21)^2 -> 132881.79 | AF22: =Input_Consumo_GrupoA!$B$13*(1+Premissas!$B$21)^2 -> 29643.384 | AG22: =Input_Consumo_GrupoA!$B$14*(1+Premissas!$B$21)^2 -> 44346.461 | AH22: =Input_Consumo_GrupoA!$B$15*(1+Premissas!$B$21)^2 -> 44346.461 | AI22: =Input_Consumo_GrupoA!$B$4*(1+Premissas!$B$21)^2 -> 74352.626 | AJ22: =Input_Consumo_GrupoA!$B$5*(1+Premissas!$B$21)^2 -> 256058.01 | AK22: =Input_Consumo_GrupoA!$B$6*(1+Premissas!$B$21)^2 -> 348675.23 | AL22: =Input_Consumo_GrupoA!$B$7*(1+Premissas!$B$21)^2 -> 107981.45 | AM22: =Input_Consumo_GrupoA!$B$8*(1+Premissas!$B$21)^2 -> 65994.169 | AN22: =Input_Consumo_GrupoA!$B$9*(1+Premissas!$B$21)^3 -> 117052.52 | AO22: =Input_Consumo_GrupoA!$B$10*(1+Premissas!$B$21)^3 -> 354230.36 | AP22: =Input_Consumo_GrupoA!$B$11*(1+Premissas!$B$21)^3 -> 205661.99 | AQ22: =Input_Consumo_GrupoA!$B$12*(1+Premissas!$B$21)^3 -> 136203.83 | AR22: =Input_Consumo_GrupoA!$B$13*(1+Premissas!$B$21)^3 -> 30384.469 | AS22: =Input_Consumo_GrupoA!$B$14*(1+Premissas!$B$21)^3 -> 45455.123 | AT22: =Input_Consumo_GrupoA!$B$15*(1+Premissas!$B$21)^3 -> 45455.123 | AU22: =Input_Consumo_GrupoA!$B$4*(1+Premissas!$B$21)^3 -> 76211.442 | AV22: =Input_Consumo_GrupoA!$B$5*(1+Premissas!$B$21)^3 -> 262459.46 | AW22: =Input_Consumo_GrupoA!$B$6*(1+Premissas!$B$21)^3 -> 357392.11 | AX22: =Input_Consumo_GrupoA!$B$7*(1+Premissas!$B$21)^3 -> 110680.99 | AY22: =Input_Consumo_GrupoA!$B$8*(1+Premissas!$B$21)^3 -> 67644.023 | AZ22: =Input_Consumo_GrupoA!$B$9*(1+Premissas!$B$21)^4 -> 119978.83 | BA22: =Input_Consumo_GrupoA!$B$10*(1+Premissas!$B$21)^4 -> 363086.11 | BB22: =Input_Consumo_GrupoA!$B$11*(1+Premissas!$B$21)^4 -> 210803.54 | BC22: =Input_Consumo_GrupoA!$B$12*(1+Premissas!$B$21)^4 -> 139608.93 | BD22: =Input_Consumo_GrupoA!$B$13*(1+Premissas!$B$21)^4 -> 31144.081 | BE22: =Input_Consumo_GrupoA!$B$14*(1+Premissas!$B$21)^4 -> 46591.501 | BF22: =Input_Consumo_GrupoA!$B$15*(1+Premissas!$B$21)^4 -> 46591.501 | BG22: =Input_Consumo_GrupoA!$B$4*(1+Premissas!$B$21)^4 -> 78116.728 | BH22: =Input_Consumo_GrupoA!$B$5*(1+Premissas!$B$21)^4 -> 269020.95 | BI22: =Input_Consumo_GrupoA!$B$6*(1+Premissas!$B$21)^4 -> 366326.91 | BJ22: =Input_Consumo_GrupoA!$B$7*(1+Premissas!$B$21)^4 -> 113448.01 | BK22: =Input_Consumo_GrupoA!$B$8*(1+Premissas!$B$21)^4 -> 69335.124
A23: Consumo Ponta (kWh) [via FA] | B23: =SUM(D23:BQ23) -> 983250.33 | C23: =B23/60 -> 16387.506 | D23: =Input_Consumo_GrupoA!$C$9 -> 12077.2 | E23: =Input_Consumo_GrupoA!$C$10 -> 36548.7 | F23: =Input_Consumo_GrupoA!$C$11 -> 21219.7 | G23: =Input_Consumo_GrupoA!$C$12 -> 14053.2 | H23: =Input_Consumo_GrupoA!$C$13 -> 3135 | I23: =Input_Consumo_GrupoA!$C$14 -> 4690 | J23: =Input_Consumo_GrupoA!$C$15 -> 4690 | K23: =Input_Consumo_GrupoA!$C$4*(1+Premissas!$B$21) -> 8059.8825 | L23: =Input_Consumo_GrupoA!$C$5*(1+Premissas!$B$21) -> 27757 | M23: =Input_Consumo_GrupoA!$C$6*(1+Premissas!$B$21) -> 37796.772 | N23: =Input_Consumo_GrupoA!$C$7*(1+Premissas!$B$21) -> 11705.295 | O23: =Input_Consumo_GrupoA!$C$8*(1+Premissas!$B$21) -> 7153.885 | P23: =Input_Consumo_GrupoA!$C$9*(1+Premissas!$B$21) -> 12379.13 | Q23: =Input_Consumo_GrupoA!$C$10*(1+Premissas!$B$21) -> 37462.417 | R23: =Input_Consumo_GrupoA!$C$11*(1+Premissas!$B$21) -> 21750.192 | S23: =Input_Consumo_GrupoA!$C$12*(1+Premissas!$B$21) -> 14404.53 | T23: =Input_Consumo_GrupoA!$C$13*(1+Premissas!$B$21) -> 3213.375 | U23: =Input_Consumo_GrupoA!$C$14*(1+Premissas!$B$21) -> 4807.25 | V23: =Input_Consumo_GrupoA!$C$15*(1+Premissas!$B$21) -> 4807.25 | W23: =Input_Consumo_GrupoA!$C$4*(1+Premissas!$B$21) -> 8059.8825 | X23: =Input_Consumo_GrupoA!$C$5*(1+Premissas!$B$21) -> 27757 | Y23: =Input_Consumo_GrupoA!$C$6*(1+Premissas!$B$21) -> 37796.772 | Z23: =Input_Consumo_GrupoA!$C$7*(1+Premissas!$B$21) -> 11705.295 | AA23: =Input_Consumo_GrupoA!$C$8*(1+Premissas!$B$21) -> 7153.885 | AB23: =Input_Consumo_GrupoA!$C$9*(1+Premissas!$B$21)^2 -> 12688.608 | AC23: =Input_Consumo_GrupoA!$C$10*(1+Premissas!$B$21)^2 -> 38398.978 | AD23: =Input_Consumo_GrupoA!$C$11*(1+Premissas!$B$21)^2 -> 22293.947 | AE23: =Input_Consumo_GrupoA!$C$12*(1+Premissas!$B$21)^2 -> 14764.643 | AF23: =Input_Consumo_GrupoA!$C$13*(1+Premissas!$B$21)^2 -> 3293.7094 | AG23: =Input_Consumo_GrupoA!$C$14*(1+Premissas!$B$21)^2 -> 4927.4312 | AH23: =Input_Consumo_GrupoA!$C$15*(1+Premissas!$B$21)^2 -> 4927.4312 | AI23: =Input_Consumo_GrupoA!$C$4*(1+Premissas!$B$21)^2 -> 8261.3796 | AJ23: =Input_Consumo_GrupoA!$C$5*(1+Premissas!$B$21)^2 -> 28450.925 | AK23: =Input_Consumo_GrupoA!$C$6*(1+Premissas!$B$21)^2 -> 38741.692 | AL23: =Input_Consumo_GrupoA!$C$7*(1+Premissas!$B$21)^2 -> 11997.927 | AM23: =Input_Consumo_GrupoA!$C$8*(1+Premissas!$B$21)^2 -> 7332.7321 | AN23: =Input_Consumo_GrupoA!$C$9*(1+Premissas!$B$21)^3 -> 13005.823 | AO23: =Input_Consumo_GrupoA!$C$10*(1+Premissas!$B$21)^3 -> 39358.952 | AP23: =Input_Consumo_GrupoA!$C$11*(1+Premissas!$B$21)^3 -> 22851.296 | AQ23: =Input_Consumo_GrupoA!$C$12*(1+Premissas!$B$21)^3 -> 15133.759 | AR23: =Input_Consumo_GrupoA!$C$13*(1+Premissas!$B$21)^3 -> 3376.0521 | AS23: =Input_Consumo_GrupoA!$C$14*(1+Premissas!$B$21)^3 -> 5050.617 | AT23: =Input_Consumo_GrupoA!$C$15*(1+Premissas!$B$21)^3 -> 5050.617 | AU23: =Input_Consumo_GrupoA!$C$4*(1+Premissas!$B$21)^3 -> 8467.9141 | AV23: =Input_Consumo_GrupoA!$C$5*(1+Premissas!$B$21)^3 -> 29162.198 | AW23: =Input_Consumo_GrupoA!$C$6*(1+Premissas!$B$21)^3 -> 39710.234 | AX23: =Input_Consumo_GrupoA!$C$7*(1+Premissas!$B$21)^3 -> 12297.876 | AY23: =Input_Consumo_GrupoA!$C$8*(1+Premissas!$B$21)^3 -> 7516.0504 | AZ23: =Input_Consumo_GrupoA!$C$9*(1+Premissas!$B$21)^4 -> 13330.969 | BA23: =Input_Consumo_GrupoA!$C$10*(1+Premissas!$B$21)^4 -> 40342.926 | BB23: =Input_Consumo_GrupoA!$C$11*(1+Premissas!$B$21)^4 -> 23422.578 | BC23: =Input_Consumo_GrupoA!$C$12*(1+Premissas!$B$21)^4 -> 15512.103 | BD23: =Input_Consumo_GrupoA!$C$13*(1+Premissas!$B$21)^4 -> 3460.4534 | BE23: =Input_Consumo_GrupoA!$C$14*(1+Premissas!$B$21)^4 -> 5176.8825 | BF23: =Input_Consumo_GrupoA!$C$15*(1+Premissas!$B$21)^4 -> 5176.8825 | BG23: =Input_Consumo_GrupoA!$C$4*(1+Premissas!$B$21)^4 -> 8679.6119 | BH23: =Input_Consumo_GrupoA!$C$5*(1+Premissas!$B$21)^4 -> 29891.253 | BI23: =Input_Consumo_GrupoA!$C$6*(1+Premissas!$B$21)^4 -> 40702.99 | BJ23: =Input_Consumo_GrupoA!$C$7*(1+Premissas!$B$21)^4 -> 12605.322 | BK23: =Input_Consumo_GrupoA!$C$8*(1+Premissas!$B$21)^4 -> 7703.9517
A24: Geração própria (kWh) | B24: =SUM(D24:BQ24) -> 4634513.1 | C24: =B24/60 -> 77241.885 | D24: =+'Novo Horizonte do Sul'!I8 -> 60380.6 | E24: =+'Novo Horizonte do Sul'!I9 -> 76551.2 | F24: =+'Novo Horizonte do Sul'!I10 -> 79815.6 | G24: =+'Novo Horizonte do Sul'!I11 -> 78203 | H24: =+'Novo Horizonte do Sul'!I12 -> 73160.1 | I24: =+'Novo Horizonte do Sul'!I13 -> 91030.5 | J24: =+'Novo Horizonte do Sul'!I14 -> 88631.7 | K24: =+'Novo Horizonte do Sul'!I3*(1-Premissas!$B$23) -> 83044.59 | L24: =+'Novo Horizonte do Sul'!I4*(1-Premissas!$B$23) -> 75743.778 | M24: =+'Novo Horizonte do Sul'!I5*(1-Premissas!$B$23) -> 89408.909 | N24: =+'Novo Horizonte do Sul'!I6*(1-Premissas!$B$23) -> 62411.773 | O24: =+'Novo Horizonte do Sul'!I7*(1-Premissas!$B$23) -> 77836.363 | P24: =D24*(1-Premissas!$B$23) -> 60078.697 | Q24: =E24*(1-Premissas!$B$23) -> 76168.444 | R24: =F24*(1-Premissas!$B$23) -> 79416.522 | S24: =G24*(1-Premissas!$B$23) -> 77811.985 | T24: =H24*(1-Premissas!$B$23) -> 72794.299 | U24: =I24*(1-Premissas!$B$23) -> 90575.348 | V24: =J24*(1-Premissas!$B$23) -> 88188.541 | W24: =K24*(1-Premissas!$B$23) -> 82629.368 | ... BK24: =AY24*(1-Premissas!$B$23) -> 76291.272
A25: Auto-comp. FP (kWh) | B25: =SUM(D25:BQ25) -> 3884122.7 | C25: =B25/60 -> 64735.379 | D25: =MIN(D24,D22) -> 60380.6 | E25: =MIN(E24,E22) -> 76551.2 | F25: =MIN(F24,F22) -> 79815.6 | G25: =MIN(G24,G22) -> 78203 | H25: =MIN(H24,H22) -> 28215 | I25: =MIN(I24,I22) -> 42209.6 | J25: =MIN(J24,J22) -> 42209.6 | K25: =MIN(K24,K22) -> 72539.147 | ... BK25: =MIN(BK24,BK22) -> 69335.124
A26: Auto-comp. Ponta via FA (kWh) | B26: =SUM(D26:BQ26) -> 118996.39 | C26: =B26/60 -> 1983.2731 | D26: =MIN((D24-D25)*Premissas!$B$8,D23) -> 0 | E26: =MIN((E24-E25)*Premissas!$B$8,E23) -> 0 | F26: =MIN((F24-F25)*Premissas!$B$8,F23) -> 0 | G26: =MIN((G24-G25)*Premissas!$B$8,G23) -> 0 | H26: =MIN((H24-H25)*Premissas!$B$8,H23) -> 3135 | I26: =MIN((I24-I25)*Premissas!$B$8,I23) -> 4690 | J26: =MIN((J24-J25)*Premissas!$B$8,J23) -> 4690 | K26: =MIN((K24-K25)*Premissas!$B$8,K23) -> 6348.093 | ... BK26: =MIN((BK24-BK25)*Premissas!$B$8,BK23) -> 4203.3711
A27: =" "&INDEX(PVSYST_Helexia!$A$5:$A$7,MATCH(Premissas!$B$13,PVSYST_Helexia!$B$5:$B$7,0))&" créditos recebidos (kWh)" -> HCS03 créditos recebidos (kWh) | B27: =SUM(D27:BQ27) -> 4146923.6 | C27: =B27/60 -> 69115.393 | D27: =D6*Premissas!$B$33 -> 91504.62 | E27: =E6*Premissas!$B$33 -> 96316.38 | F27: =F6*Premissas!$B$33 -> 115622.46 | G27: =G6*Premissas!$B$33 -> 108493.38 | H27: =H6*Premissas!$C$33 -> 78229.224 | I27: =I6*Premissas!$C$33 -> 75640.224 | J27: =J6*Premissas!$C$33 -> 71824.038 | K27: =K6*Premissas!$C$33 -> 73747.303 | L27: =L6*Premissas!$C$33 -> 65715.163 | M27: =M6*Premissas!$C$33 -> 75375.369 | N27: =N6*Premissas!$D$33 -> 97520.917 | O27: =O6*Premissas!$D$33 -> 91268.035 | P27: =P6*Premissas!$D$33 -> 82830.652 | Q27: =Q6*Premissas!$D$33 -> 87186.292 | R27: =R6*Premissas!$D$33 -> 104662.3 | S27: =S6*Premissas!$D$33 -> 98209.001 | T27: =T6*Premissas!$E$33 -> 38964.136 | U27: =U6*Premissas!$E$33 -> 37674.616 | V27: =V6*Premissas!$E$33 -> 35773.864 | W27: =W6*Premissas!$E$33 -> 36916.379 | X27: =X6*Premissas!$E$33 -> 32895.655 | Y27: =Y6*Premissas!$E$33 -> 37731.355 | Z27: =Z6*Premissas!$E$33 -> 37648.826 | AA27: =AA6*Premissas!$E$33 -> 35234.844 | AB27: =AB6*Premissas!$F$33 -> 58197.292 | AC27: =AC6*Premissas!$F$33 -> 61257.59 | AD27: =AD6*Premissas!$F$33 -> 73536.331 | AE27: =AE6*Premissas!$F$33 -> 69002.209 | AF27: =AF6*Premissas!$F$33 -> 70912.548 | AG27: =AG6*Premissas!$F$33 -> 68565.694 | AH27: =AH6*Premissas!$G$33 -> 64172.612 | AI27: =AI6*Premissas!$G$33 -> 66222.101 | AJ27: =AJ6*Premissas!$G$33 -> 59009.564 | AK27: =AK6*Premissas!$G$33 -> 67684.039 | AL27: =AL6*Premissas!$G$33 -> 67535.995 | AM27: =AM6*Premissas!$G$33 -> 63205.697 | AN27: =AN6*Premissas!$H$33 -> 57698.669 | AO27: =AO6*Premissas!$H$33 -> 60732.746 | AP27: =AP6*Premissas!$H$33 -> 72906.286 | AQ27: =AQ6*Premissas!$H$33 -> 68411.011 | AR27: =AR6*Premissas!$H$33 -> 70304.983 | AS27: =AS6*Premissas!$H$33 -> 67978.236 | AT27: =AT6*Premissas!$I$33 -> 63619.461 | AU27: =AU6*Premissas!$I$33 -> 65651.284 | AV27: =AV6*Premissas!$I$33 -> 58500.917 | AW27: =AW6*Premissas!$I$33 -> 67100.621 | AX27: =AX6*Premissas!$I$33 -> 66953.853 | AY27: =AY6*Premissas!$I$33 -> 62660.881 | AZ27: =AZ6*Premissas!$J$33 -> 70802.642 | BA27: =BA6*Premissas!$J$33 -> 74525.791 | BB27: =BB6*Premissas!$J$33 -> 89464.069 | BC27: =BC6*Premissas!$J$33 -> 83947.87 | BD27: =BD6*Premissas!$J$33 -> 86271.983 | BE27: =BE6*Premissas!$J$33 -> 83416.807 | BF27: =BF6*Premissas!$K$33 -> 62825.516 | BG27: =BG6*Premissas!$K$33 -> 64831.983 | BH27: =BH6*Premissas!$K$33 -> 57770.85 | BI27: =BI6*Premissas!$K$33 -> 66263.232 | BJ27: =BJ6*Premissas!$K$33 -> 66118.296 | BK27: =BK6*Premissas!$K$33 -> 61878.898
A28: BAT créditos → NHS (kWh) | B28: =SUM(D28:BQ28) -> 1192710.1 | C28: =B28/60 -> 19878.501 | D28: =D19 -> 0 | E28: =E19 -> 0 | F28: =F19 -> 0 | G28: =G19 -> 32711.293 | H28: =H19 -> 40823.762 | I28: =I19 -> 41560.462 | J28: =J19 -> 47597.362 | K28: =K19 -> 51288.174 | ... BK28: =BK19 -> 12655.84
A29: Banco início mês COM Helexia (kWh) | B29: =AA29 -> 801819.36 | C29: — | D29: =Premissas!$B$26 -> 786669 | E29: =D31 -> 809872.79 | F29: =E31 -> 593317.92 | G29: =F31 -> 562661.95 | H29: =G31 -> 632334.22 | I29: =H31 -> 796332.31 | J29: =I31 -> 962353.89 | K29: =J31 -> 1128197.4 | L29: =K31 -> 1260905.5 | ... BK29: =BJ31 -> 336447.92
A30: Bank draw COM Helexia (kWh) | B30: =SUM(D30:BQ30) -> 4266371 | C30: =B30/60 -> 71106.184 | D30: =MIN(D29,MAX(D22-D24-D27+D28,0)+IF(Premissas!$B$8=0,0,MAX(D23-D26,0)/Premissas!$B$8)) -> 19986.528 | E30: =MIN(E29,MAX(E22-E24-E27+E28,0)+IF(Premissas!$B$8=0,0,MAX(E23-E26,0)/Premissas!$B$8)) -> 216554.87 | F30: =MIN(F29,MAX(F22-F24-F27+F28,0)+IF(Premissas!$B$8=0,0,MAX(F23-F26,0)/Premissas!$B$8)) -> 35116.427 | G30: =MIN(G29,MAX(G22-G24-G27+G28,0)+IF(Premissas!$B$8=0,0,MAX(G23-G26,0)/Premissas!$B$8)) -> 23256.605 | H30: =MIN(H29,MAX(H22-H24-H27+H28,0)+IF(Premissas!$B$8=0,0,MAX(H23-H26,0)/Premissas!$B$8)) -> 0 | I30: =MIN(I29,MAX(I22-I24-I27+I28,0)+IF(Premissas!$B$8=0,0,MAX(I23-I26,0)/Premissas!$B$8)) -> 0 | J30: =MIN(J29,MAX(J22-J24-J27+J28,0)+IF(Premissas!$B$8=0,0,MAX(J23-J26,0)/Premissas!$B$8)) -> 0 | K30: =MIN(K29,MAX(K22-K24-K27+K28,0)+IF(Premissas!$B$8=0,0,MAX(K23-K26,0)/Premissas!$B$8)) -> 2832.836 | ... BK30: =MIN(BK29,MAX(BK22-BK24-BK27+BK28,0)+IF(Premissas!$B$8=0,0,MAX(BK23-BK26,0)/Premissas!$B$8)) -> 5793.1019
A31: ★ Banco fim mês COM Helexia (kWh) | B31: =AA31 -> 864979.94 | C31: — | D31: =MAX(D29-D30,0)+D28+MAX(D27-MAX(D22-D24,0),0)+MAX(D24-D22,0) -> 809872.79 | E31: =MAX(E29-E30,0)+E28+MAX(E27-MAX(E22-E24,0),0)+MAX(E24-E22,0) -> 593317.92 | F31: =MAX(F29-F30,0)+F28+MAX(F27-MAX(F22-F24,0),0)+MAX(F24-F22,0) -> 562661.95 | G31: =MAX(G29-G30,0)+G28+MAX(G27-MAX(G22-G24,0),0)+MAX(G24-G22,0) -> 632334.22 | H31: =MAX(H29-H30,0)+H28+MAX(H27-MAX(H22-H24,0),0)+MAX(H24-H22,0) -> 796332.31 | I31: =MAX(I29-I30,0)+I28+MAX(I27-MAX(I22-I24,0),0)+MAX(I24-I22,0) -> 962353.89 | J31: =MAX(J29-J30,0)+J28+MAX(J27-MAX(J22-J24,0),0)+MAX(J24-J22,0) -> 1128197.4 | K31: =MAX(K29-K30,0)+K28+MAX(K27-MAX(K22-K24,0),0)+MAX(K24-K22,0) -> 1260905.5 | ... BK31: =MAX(BK29-BK30,0)+BK28+MAX(BK27-MAX(BK22-BK24,0),0)+MAX(BK24-BK22,0) -> 412145.7
A32: Banco início mês SEM Helexia (kWh) | B32: =AA32 -> 16130.024 | C32: — | D32: =Premissas!$B$26 -> 786669 | E32: =D34 -> 718368.17 | F32: =E34 -> 405496.92 | G32: =F34 -> 259218.49 | H32: =G34 -> 253108.68 | I32: =H34 -> 338877.54 | J32: =I34 -> 429258.9 | K32: =J34 -> 523278.36 | L32: =K34 -> 585071.98 | ... BK32: =BJ34 -> 12686.114
A33: Bank draw SEM Helexia (kWh) — gen+BAT, no CS3 | B33: =SUM(D33:BQ33) -> 2697471.3 | C33: =B33/60 -> 44957.856 | D33: =MIN(D32,MAX(D22-D24-D28,0)+IF(Premissas!$B$8=0,0,MAX(D23-D26-(IF(Premissas!$B$8>0,MAX(D24-D22,0)*Premissas!$B$8,0)),0)/Premissas!$B$8)) -> 68300.828 | E33: =MIN(E32,MAX(E22-E24-E28,0)+IF(Premissas!$B$8=0,0,MAX(E23-E26-(IF(Premissas!$B$8>0,MAX(E24-E22,0)*Premissas!$B$8,0)),0)/Premissas!$B$8)) -> 312871.25 | F33: =MIN(F32,MAX(F22-F24-F28,0)+IF(Premissas!$B$8=0,0,MAX(F23-F26-(IF(Premissas!$B$8>0,MAX(F24-F22,0)*Premissas!$B$8,0)),0)/Premissas!$B$8)) -> 146278.43 | G33: =MIN(G32,MAX(G22-G24-G28,0)+IF(Premissas!$B$8=0,0,MAX(G23-G26-(IF(Premissas!$B$8>0,MAX(G24-G22,0)*Premissas!$B$8,0)),0)/Premissas!$B$8)) -> 38821.112 | H33: =MIN(H32,MAX(H22-H24-H28,0)+IF(Premissas!$B$8=0,0,MAX(H23-H26-(IF(Premissas!$B$8>0,MAX(H24-H22,0)*Premissas!$B$8,0)),0)/Premissas!$B$8)) -> 0 | I33: =MIN(I32,MAX(I22-I24-I28,0)+IF(Premissas!$B$8=0,0,MAX(I23-I26-(IF(Premissas!$B$8>0,MAX(I24-I22,0)*Premissas!$B$8,0)),0)/Premissas!$B$8)) -> 0 | J33: =MIN(J32,MAX(J22-J24-J28,0)+IF(Premissas!$B$8=0,0,MAX(J23-J26-(IF(Premissas!$B$8>0,MAX(J24-J22,0)*Premissas!$B$8,0)),0)/Premissas!$B$8)) -> 0 | K33: =MIN(K32,MAX(K22-K24-K28,0)+IF(Premissas!$B$8=0,0,MAX(K23-K26-(IF(Premissas!$B$8>0,MAX(K24-K22,0)*Premissas!$B$8,0)),0)/Premissas!$B$8)) -> 0 | ... AA33: =MIN(AA32,MAX(AA22-AA24-AA28,0)+IF(Premissas!$B$8=0,0,MAX(AA23-AA26-(IF(Premissas!$B$8>0,MAX(AA24-AA22,0)*Premissas!$B$8,0)),0)/Premissas!$B$8)) -> 0 | AB33: =MIN(AB32,MAX(AB22-AB24-AB28,0)+IF(Premissas!$B$8=0,0,MAX(AB23-AB26-(IF(Premissas!$B$8>0,MAX(AB24-AB22,0),0))*Premissas!$B$8,0)/Premissas!$B$8)) -> 44055.758 | AC33: =MIN(AC32,MAX(AC22-AC24-AC28,0)+IF(Premissas!$B$8=0,0,MAX(AC23-AC26-(IF(Premissas!$B$8>0,MAX(AC24-AC22,0),0))*Premissas!$B$8,0)/Premissas!$B$8)) -> 0 | AD33: =MIN(AD32,MAX(AD22-AD24-AD28,0)+IF(Premissas!$B$8=0,0,MAX(AD23-AD26-(IF(Premissas!$B$8>0,MAX(AD24-AD22,0),0))*Premissas!$B$8,0)/Premissas!$B$8)) -> 0 | AE33: =MIN(AE32,MAX(AE22-AE24-AE28,0)+IF(Premissas!$B$8=0,0,MAX(AE23-AE26-(IF(Premissas!$B$8>0,MAX(AE24-AE22,0),0))*Premissas!$B$8,0)/Premissas!$B$8)) -> 0 | AF33: =MIN(AF32,MAX(AF22-AF24-AF28,0)+IF(Premissas!$B$8=0,0,MAX(AF23-AF26-(IF(Premissas!$B$8>0,MAX(AF24-AF22,0),0))*Premissas!$B$8,0)/Premissas!$B$8)) -> 0 | AG33: =MIN(AG32,MAX(AG22-AG24-AG28,0)+IF(Premissas!$B$8=0,0,MAX(AG23-AG26-(IF(Premissas!$B$8>0,MAX(AG24-AG22,0),0))*Premissas!$B$8,0)/Premissas!$B$8)) -> 0 | AH33: =MIN(AH32,MAX(AH22-AH24-AH28,0)+IF(Premissas!$B$8=0,0,MAX(AH23-AH26-(IF(Premissas!$B$8>0,MAX(AH24-AH22,0),0))*Premissas!$B$8,0)/Premissas!$B$8)) -> 0 | AI33: =MIN(AI32,MAX(AI22-AI24-AI28,0)+IF(Premissas!$B$8=0,0,MAX(AI23-AI26-(IF(Premissas!$B$8>0,MAX(AI24-AI22,0),0))*Premissas!$B$8,0)/Premissas!$B$8)) -> 0 | ... BK33: =MIN(BK32,MAX(BK22-BK24-BK28,0)+IF(Premissas!$B$8=0,0,MAX(BK23-BK26-(IF(Premissas!$B$8>0,MAX(BK24-BK22,0),0))*Premissas!$B$8,0)/Premissas!$B$8)) -> 0
A34: Banco fim mês SEM Helexia (kWh) — gen+BAT, no CS3 | B34: =AA34 -> 44055.758 | C34: — | D34: =MAX(D32-D33,0)+D28+MAX(D24-D22,0) -> 718368.17 | E34: =MAX(E32-E33,0)+E28+MAX(E24-E22,0) -> 405496.92 | F34: =MAX(F32-F33,0)+F28+MAX(F24-F22,0) -> 259218.49 | G34: =MAX(G32-G33,0)+G28+MAX(G24-G22,0) -> 253108.68 | H34: =MAX(H32-H33,0)+H28+MAX(H24-H22,0) -> 338877.54 | I34: =MAX(I32-I33,0)+I28+MAX(I24-I22,0) -> 429258.9 | J34: =MAX(J32-J33,0)+J28+MAX(J24-J22,0) -> 523278.36 | K34: =MAX(K32-K33,0)+K28+MAX(K24-K22,0) -> 585071.98 | ... BK34: =MAX(BK32-BK33,0)+BK28+MAX(BK24-BK22,0) -> 32298.103
A35: =" Custo SEM Helexia (R$) — só gen própria, sem "&INDEX(PVSYST_Helexia!$A$5:$A$7,MATCH(Premissas!$B$13,PVSYST_Helexia!$B$5:$B$7,0))&"/BAT/banco" -> Custo SEM Helexia (R$) — só gen própria, sem HCS03/BAT/banco | B35: =SUM(D35:BQ35) -> 3326978.9 | C35: =B35/60 -> 55449.648 | D35: =IF(D34>0,0,MAX(D22-D24-D28-D32,0)*Premissas!$B$5*(1+Premissas!$B$126)*(1+Premissas!$B$124)^0+MAX(D23-D26-(IF(Premissas!$B$8>0,MAX(D24+D28+D32-D22,0)*Premissas!$B$8,0)),0)*Premissas!$B$6*(1+Premissas!$B$126)*(1+Premissas!$B$124)^0) -> 0 | E35: =IF(E34>0,0,MAX(E22-E24-E28-E32,0)*Premissas!$B$5*(1+Premissas!$B$126)*(1+Premissas!$B$124)^0+MAX(E23-E26-(IF(Premissas!$B$8>0,MAX(E24+E28+E32-E22,0)*Premissas!$B$8,0)),0)*Premissas!$B$6*(1+Premissas!$B$126)*(1+Premissas!$B$124)^0) -> 0 | F35: =IF(F34>0,0,MAX(F22-F24-F28-F32,0)*Premissas!$B$5*(1+Premissas!$B$126)*(1+Premissas!$B$124)^0+MAX(F23-F26-(IF(Premissas!$B$8>0,MAX(F24+F28+F32-F22,0)*Premissas!$B$8,0)),0)*Premissas!$B$6*(1+Premissas!$B$126)*(1+Premissas!$B$124)^0) -> 0 | G35: =IF(G34>0,0,MAX(G22-G24-G28-G32,0)*Premissas!$B$5*(1+Premissas!$B$126)*(1+Premissas!$B$124)^0+MAX(G23-G26-(IF(Premissas!$B$8>0,MAX(G24+G28+G32-G22,0)*Premissas!$B$8,0)),0)*Premissas!$B$6*(1+Premissas!$B$126)*(1+Premissas!$B$124)^0) -> 0 | H35: =IF(H34>0,0,MAX(H22-H24-H28-H32,0)*Premissas!$B$5*(1+Premissas!$B$126)*(1+Premissas!$B$124)^0+MAX(H23-H26-(IF(Premissas!$B$8>0,MAX(H24+H28+H32-H22,0)*Premissas!$B$8,0)),0)*Premissas!$B$6*(1+Premissas!$B$126)*(1+Premissas!$B$124)^0) -> 0 | I35: =IF(I34>0,0,MAX(I22-I24-I28-I32,0)*Premissas!$B$5*(1+Premissas!$B$126)*(1+Premissas!$B$124)^0+MAX(I23-I26-(IF(Premissas!$B$8>0,MAX(I24+I28+I32-I22,0)*Premissas!$B$8,0)),0)*Premissas!$B$6*(1+Premissas!$B$126)*(1+Premissas!$B$124)^0) -> 0 | J35: =IF(J34>0,0,MAX(J22-J24-J28-J32,0)*Premissas!$B$5*(1+Premissas!$B$126)*(1+Premissas!$B$124)^0+MAX(J23-J26-(IF(Premissas!$B$8>0,MAX(J24+J28+J32-J22,0)*Premissas!$B$8,0)),0)*Premissas!$B$6*(1+Premissas!$B$126)*(1+Premissas!$B$124)^0) -> 0 | K35: =IF(K34>0,0,MAX(K22-K24-K28-K32,0)*Premissas!$B$5*(1+Premissas!$B$126)*(1+Premissas!$B$124)^0+MAX(K23-K26-(IF(Premissas!$B$8>0,MAX(K24+K28+K32-K22,0)*Premissas!$B$8,0)),0)*Premissas!$B$6*(1+Premissas!$B$126)*(1+Premissas!$B$124)^0) -> 0 | ... O35: =IF(O34>0,0,MAX(O22-O24-O28-O32,0)*Premissas!$B$5*(1+Premissas!$B$126)*(1+Premissas!$B$124)^0+MAX(O23-O26-(IF(Premissas!$B$8>0,MAX(O24+O28+O32-O22,0)*Premissas!$B$8,0)),0)*Premissas!$B$6*(1+Premissas!$B$126)*(1+Premissas!$B$124)^0) -> 0 | P35: =IF(P34>0,0,MAX(P22-P24-P28-P32,0)*Premissas!$B$5*(1+Premissas!$B$126)*(1+Premissas!$B$124)^1+MAX(P23-P26-(IF(Premissas!$B$8>0,MAX(P24+P28+P32-P22,0)*Premissas!$B$8,0)),0)*Premissas!$B$6*(1+Premissas!$B$126)*(1+Premissas!$B$124)^1) -> 44220.374 | Q35: =IF(Q34>0,0,MAX(Q22-Q24-Q28-Q32,0)*Premissas!$B$5*(1+Premissas!$B$126)*(1+Premissas!$B$124)^1+MAX(Q23-Q26-(IF(Premissas!$B$8>0,MAX(Q24+Q28+Q32-Q22,0)*Premissas!$B$8,0)),0)*Premissas!$B$6*(1+Premissas!$B$126)*(1+Premissas!$B$124)^1) -> 296353.68 | R35: =IF(R34>0,0,MAX(R22-R24-R28-R32,0)*Premissas!$B$5*(1+Premissas!$B$126)*(1+Premissas!$B$124)^1+MAX(R23-R26-(IF(Premissas!$B$8>0,MAX(R24+R28+R32-R22,0)*Premissas!$B$8,0)),0)*Premissas!$B$6*(1+Premissas!$B$126)*(1+Premissas!$B$124)^1) -> 149985.51 | S35: =IF(S34>0,0,MAX(S22-S24-S28-S32,0)*Premissas!$B$5*(1+Premissas!$B$126)*(1+Premissas!$B$124)^1+MAX(S23-S26-(IF(Premissas!$B$8>0,MAX(S24+S28+S32-S22,0)*Premissas!$B$8,0)),0)*Premissas!$B$6*(1+Premissas!$B$126)*(1+Premissas!$B$124)^1) -> 0 | T35: =IF(T34>0,0,MAX(T22-T24-T28-T32,0)*Premissas!$B$5*(1+Premissas!$B$126)*(1+Premissas!$B$124)^1+MAX(T23-T26-(IF(Premissas!$B$8>0,MAX(T24+T28+T32-T22,0)*Premissas!$B$8,0)),0)*Premissas!$B$6*(1+Premissas!$B$126)*(1+Premissas!$B$124)^1) -> 0 | U35: =IF(U34>0,0,MAX(U22-U24-U28-U32,0)*Premissas!$B$5*(1+Premissas!$B$126)*(1+Premissas!$B$124)^1+MAX(U23-U26-(IF(Premissas!$B$8>0,MAX(U24+U28+U32-U22,0)*Premissas!$B$8,0)),0)*Premissas!$B$6*(1+Premissas!$B$126)*(1+Premissas!$B$124)^1) -> 0 | V35: =IF(V34>0,0,MAX(V22-V24-V28-V32,0)*Premissas!$B$5*(1+Premissas!$B$126)*(1+Premissas!$B$124)^1+MAX(V23-V26-(IF(Premissas!$B$8>0,MAX(V24+V28+V32-V22,0)*Premissas!$B$8,0)),0)*Premissas!$B$6*(1+Premissas!$B$126)*(1+Premissas!$B$124)^1) -> 0 | W35: =IF(W34>0,0,MAX(W22-W24-W28-W32,0)*Premissas!$B$5*(1+Premissas!$B$126)*(1+Premissas!$B$124)^1+MAX(W23-W26-(IF(Premissas!$B$8>0,MAX(W24+W28+W32-W22,0)*Premissas!$B$8,0)),0)*Premissas!$B$6*(1+Premissas!$B$126)*(1+Premissas!$B$124)^1) -> 0 | ... AA35: =IF(AA34>0,0,MAX(AA22-AA24-AA28-AA32,0)*Premissas!$B$5*(1+Premissas!$B$126)*(1+Premissas!$B$124)^1+MAX(AA23-AA26-(IF(Premissas!$B$8>0,MAX(AA24+AA28+AA32-AA22,0)*Premissas!$B$8,0)),0)*Premissas!$B$6*(1+Premissas!$B$126)*(1+Premissas!$B$124)^1) -> 0 | AB35: =IF(AB34>0,0,MAX(AB22-AB24-AB28-AB32,0)*Premissas!$B$5*(1+Premissas!$B$126)*(1+Premissas!$B$124)^2+MAX(AB23-AB26-(IF(Premissas!$B$8>0,MAX(AB24+AB26-AB22-AB23,0)*Premissas!$B$8,0)),0)*Premissas!$B$6*(1+Premissas!$B$126)*(1+Premissas!$B$124)^2) -> 54517.514 | AC35: =IF(AC34>0,0,MAX(AC22-AC24-AC28-AC32,0)*Premissas!$B$5*(1+Premissas!$B$126)*(1+Premissas!$B$124)^2+MAX(AC23-AC26-(IF(Premissas!$B$8>0,MAX(AC24+AC26-AC22-AC23,0)*Premissas!$B$8,0)),0)*Premissas!$B$6*(1+Premissas!$B$126)*(1+Premissas!$B$124)^2) -> 323507.46 | AD35: =IF(AD34>0,0,MAX(AD22-AD24-AD28-AD32,0)*Premissas!$B$5*(1+Premissas!$B$126)*(1+Premissas!$B$124)^2+MAX(AD23-AD26-(IF(Premissas!$B$8>0,MAX(AD24+AD26-AD22-AD23,0)*Premissas!$B$8,0)),0)*Premissas!$B$6*(1+Premissas!$B$126)*(1+Premissas!$B$124)^2) -> 164543.23 | AE35: =IF(AE34>0,0,MAX(AE22-AE24-AE28-AE32,0)*Premissas!$B$5*(1+Premissas!$B$126)*(1+Premissas!$B$124)^2+MAX(AE23-AE26-(IF(Premissas!$B$8>0,MAX(AE24+AE26-AE22-AE23,0)*Premissas!$B$8,0)),0)*Premissas!$B$6*(1+Premissas!$B$126)*(1+Premissas!$B$124)^2) -> 0 | AF35: =IF(AF34>0,0,MAX(AF22-AF24-AF28-AF32,0)*Premissas!$B$5*(1+Premissas!$B$126)*(1+Premissas!$B$124)^2+MAX(AF23-AF26-(IF(Premissas!$B$8>0,MAX(AF24+AF26-AF22-AF23,0)*Premissas!$B$8,0)),0)*Premissas!$B$6*(1+Premissas!$B$126)*(1+Premissas!$B$124)^2) -> 0 | AG35: =IF(AG34>0,0,MAX(AG22-AG24-AG28-AG32,0)*Premissas!$B$5*(1+Premissas!$B$126)*(1+Premissas!$B$124)^2+MAX(AG23-AG26-(IF(Premissas!$B$8>0,MAX(AG24+AG26-AG22-AG23,0)*Premissas!$B$8,0)),0)*Premissas!$B$6*(1+Premissas!$B$126)*(1+Premissas!$B$124)^2) -> 0 | AH35: =IF(AH34>0,0,MAX(AH22-AH24-AH28-AH32,0)*Premissas!$B$5*(1+Premissas!$B$126)*(1+Premissas!$B$124)^2+MAX(AH23-AH26-(IF(Premissas!$B$8>0,MAX(AH24+AH26-AH22-AH23,0)*Premissas!$B$8,0)),0)*Premissas!$B$6*(1+Premissas!$B$126)*(1+Premissas!$B$124)^2) -> 0 | AI35: =IF(AI34>0,0,MAX(AI22-AI24-AI28-AI32,0)*Premissas!$B$5*(1+Premissas!$B$126)*(1+Premissas!$B$124)^2+MAX(AI23-AI26-(IF(Premissas!$B$8>0,MAX(AI24+AI26-AI22-AI23,0)*Premissas!$B$8,0)),0)*Premissas!$B$6*(1+Premissas!$B$126)*(1+Premissas!$B$124)^2) -> 0 | ... AM35: =IF(AM34>0,0,MAX(AM22-AM24-AM28-AM32,0)*Premissas!$B$5*(1+Premissas!$B$126)*(1+Premissas!$B$124)^2+MAX(AM23-AM26-(IF(Premissas!$B$8>0,MAX(AM24+AM26-AM22-AM23,0)*Premissas!$B$8,0)),0)*Premissas!$B$6*(1+Premissas!$B$126)*(1+Premissas!$B$124)^2) -> 0 | AN35: =IF(AN34>0,0,MAX(AN22-AN24-AN28-AN32,0)*Premissas!$B$5*(1+Premissas!$B$126)*(1+Premissas!$B$124)^3+MAX(AN23-AN26-(IF(Premissas!$B$8>0,MAX(AN24+AN26-AN22-AN23,0)*Premissas!$B$8,0)),0)*Premissas!$B$6*(1+Premissas!$B$126)*(1+Premissas!$B$124)^3) -> 63984.458 | AO35: =IF(AO34>0,0,MAX(AO22-AO24-AO28-AO32,0)*Premissas!$B$5*(1+Premissas!$B$126)*(1+Premissas!$B$124)^3+MAX(AO23-AO26-(IF(Premissas!$B$8>0,MAX(AO24+AO26-AO22-AO23,0)*Premissas!$B$8,0)),0)*Premissas!$B$6*(1+Premissas!$B$126)*(1+Premissas!$B$124)^3) -> 353093.14 | AP35: =IF(AP34>0,0,MAX(AP22-AP24-AP28-AP32,0)*Premissas!$B$5*(1+Premissas!$B$126)*(1+Premissas!$B$124)^3+MAX(AP23-AP26-(IF(Premissas!$B$8>0,MAX(AP24+AP26-AP22-AP23,0)*Premissas!$B$8,0)),0)*Premissas!$B$6*(1+Premissas!$B$126)*(1+Premissas!$B$124)^3) -> 180446.82 | AQ35: =IF(AQ34>0,0,MAX(AQ22-AQ24-AQ28-AQ32,0)*Premissas!$B$5*(1+Premissas!$B$126)*(1+Premissas!$B$124)^3+MAX(AQ23-AQ26-(IF(Premissas!$B$8>0,MAX(AQ24+AQ26-AQ22-AQ23,0)*Premissas!$B$8,0)),0)*Premissas!$B$6*(1+Premissas!$B$126)*(1+Premissas!$B$124)^3) -> 0 | AR35: =IF(AR34>0,0,MAX(AR22-AR24-AR28-AR32,0)*Premissas!$B$5*(1+Premissas!$B$126)*(1+Premissas!$B$124)^3+MAX(AR23-AR26-(IF(Premissas!$B$8>0,MAX(AR24+AR26-AR22-AR23,0)*Premissas!$B$8,0)),0)*Premissas!$B$6*(1+Premissas!$B$126)*(1+Premissas!$B$124)^3) -> 0 | AS35: =IF(AS34>0,0,MAX(AS22-AS24-AS28-AS32,0)*Premissas!$B$5*(1+Premissas!$B$126)*(1+Premissas!$B$124)^3+MAX(AS23-AS26-(IF(Premissas!$B$8>0,MAX(AS24+AS26-AS22-AS23,0)*Premissas!$B$8,0)),0)*Premissas!$B$6*(1+Premissas!$B$126)*(1+Premissas!$B$124)^3) -> 0 | AT35: =IF(AT34>0,0,MAX(AT22-AT24-AT28-AT32,0)*Premissas!$B$5*(1+Premissas!$B$126)*(1+Premissas!$B$124)^3+MAX(AT23-AT26-(IF(Premissas!$B$8>0,MAX(AT24+AT26-AT22-AT23,0)*Premissas!$B$8,0)),0)*Premissas!$B$6*(1+Premissas!$B$126)*(1+Premissas!$B$124)^3) -> 0 | AU35: =IF(AU34>0,0,MAX(AU22-AU24-AU28-AU32,0)*Premissas!$B$5*(1+Premissas!$B$126)*(1+Premissas!$B$124)^3+MAX(AU23-AU26-(IF(Premissas!$B$8>0,MAX(AU24+AU26-AU22-AU23,0)*Premissas!$B$8,0)),0)*Premissas!$B$6*(1+Premissas!$B$126)*(1+Premissas!$B$124)^3) -> 0 | ... AY35: =IF(AY34>0,0,MAX(AY22-AY24-AY28-AY32,0)*Premissas!$B$5*(1+Premissas!$B$126)*(1+Premissas!$B$124)^3+MAX(AY23-AY26-(IF(Premissas!$B$8>0,MAX(AY24+AY26-AY22-AY23,0)*Premissas!$B$8,0)),0)*Premissas!$B$6*(1+Premissas!$B$126)*(1+Premissas!$B$124)^3) -> 0 | AZ35: =IF(AZ34>0,0,MAX(AZ22-AZ24-AZ28-AZ32,0)*Premissas!$B$5*(1+Premissas!$B$126)*(1+Premissas!$B$124)^4+MAX(AZ23-AZ26-(IF(Premissas!$B$8>0,MAX(AZ24+AZ26-AZ22-AZ23,0)*Premissas!$B$8,0)),0)*Premissas!$B$6*(1+Premissas!$B$126)*(1+Premissas!$B$124)^4) -> 74530.182 | BA35: =IF(BA34>0,0,MAX(BA22-BA24-BA28-BA32,0)*Premissas!$B$5*(1+Premissas!$B$126)*(1+Premissas!$B$124)^4+MAX(BA23-BA26-(IF(Premissas!$B$8>0,MAX(BA24+BA26-BA22-BA23,0)*Premissas!$B$8,0)),0)*Premissas!$B$6*(1+Premissas!$B$126)*(1+Premissas!$B$124)^4) -> 385325.62 | BB35: =IF(BB34>0,0,MAX(BB22-BB24-BB28-BB32,0)*Premissas!$B$5*(1+Premissas!$B$126)*(1+Premissas!$B$124)^4+MAX(BB23-BB26-(IF(Premissas!$B$8>0,MAX(BB24+BB26-BB22-BB23,0)*Premissas!$B$8,0)),0)*Premissas!$B$6*(1+Premissas!$B$126)*(1+Premissas!$B$124)^4) -> 197817.47 | BC35: =IF(BC34>0,0,MAX(BC22-BC24-BC28-BC32,0)*Premissas!$B$5*(1+Premissas!$B$126)*(1+Premissas!$B$124)^4+MAX(BC23-BC26-(IF(Premissas!$B$8>0,MAX(BC24+BC26-BC22-BC23,0)*Premissas!$B$8,0)),0)*Premissas!$B$6*(1+Premissas!$B$126)*(1+Premissas!$B$124)^4) -> 0 | BD35: =IF(BD34>0,0,MAX(BD22-BD24-BD28-BD32,0)*Premissas!$B$5*(1+Premissas!$B$126)*(1+Premissas!$B$124)^4+MAX(BD23-BD26-(IF(Premissas!$B$8>0,MAX(BD24+BD26-BD22-BD23,0)*Premissas!$B$8,0)),0)*Premissas!$B$6*(1+Premissas!$B$126)*(1+Premissas!$B$124)^4) -> 0 | BE35: =IF(BE34>0,0,MAX(BE22-BE24-BE28-BE32,0)*Premissas!$B$5*(1+Premissas!$B$126)*(1+Premissas!$B$124)^4+MAX(BE23-BE26-(IF(Premissas!$B$8>0,MAX(BE24+BE26-BE22-BE23,0)*Premissas!$B$8,0)),0)*Premissas!$B$6*(1+Premissas!$B$126)*(1+Premissas!$B$124)^4) -> 0 | BF35: =IF(BF34>0,0,MAX(BF22-BF24-BF28-BF32,0)*Premissas!$B$5*(1+Premissas!$B$126)*(1+Premissas!$B$124)^4+MAX(BF23-BF26-(IF(Premissas!$B$8>0,MAX(BF24+BF26-BF22-BF23,0)*Premissas!$B$8,0)),0)*Premissas!$B$6*(1+Premissas!$B$126)*(1+Premissas!$B$124)^4) -> 0 | BG35: =IF(BG34>0,0,MAX(BG22-BG24-BG28-BG32,0)*Premissas!$B$5*(1+Premissas!$B$126)*(1+Premissas!$B$124)^4+MAX(BG23-BG26-(IF(Premissas!$B$8>0,MAX(BG24+BG26-BG22-BG23,0)*Premissas!$B$8,0)),0)*Premissas!$B$6*(1+Premissas!$B$126)*(1+Premissas!$B$124)^4) -> 0 | ... BK35: =IF(BK34>0,0,MAX(BK22-BK24-BK28-BK32,0)*Premissas!$B$5*(1+Premissas!$B$126)*(1+Premissas!$B$124)^4+MAX(BK23-BK26-(IF(Premissas!$B$8>0,MAX(BK24+BK26-BK22-BK23,0)*Premissas!$B$8,0)),0)*Premissas!$B$6*(1+Premissas!$B$126)*(1+Premissas!$B$124)^4) -> 0
A36: Custo COM Helexia — rede remanescente (R$) | B36: =SUM(D36:BQ36) -> 0 | C36: =B36/60 -> 0 | D36: =IF(D31>0,0,MAX(D22-D24-D27+D28-D29,0)*Premissas!$B$5*(1+Premissas!$B$126)*(1+Premissas!$B$124)^0+MAX(D23-D26-(IF(Premissas!$B$8>0,MAX(D24+D27+D28+D29-D22,0)*Premissas!$B$8,0)),0)*Premissas!$B$6*(1+Premissas!$B$126)*(1+Premissas!$B$124)^0) -> 0 | E36: =IF(E31>0,0,MAX(E22-E24-E27+E28-E29,0)*Premissas!$B$5*(1+Premissas!$B$126)*(1+Premissas!$B$124)^0+MAX(E23-E26-(IF(Premissas!$B$8>0,MAX(E24+E27+E28+E29-E22,0)*Premissas!$B$8,0)),0)*Premissas!$B$6*(1+Premissas!$B$126)*(1+Premissas!$B$124)^0) -> 0 | F36: =IF(F31>0,0,MAX(F22-F24-F27+F28-F29,0)*Premissas!$B$5*(1+Premissas!$B$126)*(1+Premissas!$B$124)^0+MAX(F23-F26-(IF(Premissas!$B$8>0,MAX(F24+F27+F28+F29-F22,0)*Premissas!$B$8,0)),0)*Premissas!$B$6*(1+Premissas!$B$126)*(1+Premissas!$B$124)^0) -> 0 | G36: =IF(G31>0,0,MAX(G22-G24-G27+G28-G29,0)*Premissas!$B$5*(1+Premissas!$B$126)*(1+Premissas!$B$124)^0+MAX(G23-G26-(IF(Premissas!$B$8>0,MAX(G24+G27+G28+G29-G22,0)*Premissas!$B$8,0)),0)*Premissas!$B$6*(1+Premissas!$B$126)*(1+Premissas!$B$124)^0) -> 0 | H36: =IF(H31>0,0,MAX(H22-H24-H27+H28-H29,0)*Premissas!$B$5*(1+Premissas!$B$126)*(1+Premissas!$B$124)^0+MAX(H23-H26-(IF(Premissas!$B$8>0,MAX(H24+H27+H28+H29-H22,0)*Premissas!$B$8,0)),0)*Premissas!$B$6*(1+Premissas!$B$126)*(1+Premissas!$B$124)^0) -> 0 | I36: =IF(I31>0,0,MAX(I22-I24-I27+I28-I29,0)*Premissas!$B$5*(1+Premissas!$B$126)*(1+Premissas!$B$124)^0+MAX(I23-I26-(IF(Premissas!$B$8>0,MAX(I24+I27+I28+I29-I22,0)*Premissas!$B$8,0)),0)*Premissas!$B$6*(1+Premissas!$B$126)*(1+Premissas!$B$124)^0) -> 0 | J36: =IF(J31>0,0,MAX(J22-J24-J27+J28-J29,0)*Premissas!$B$5*(1+Premissas!$B$126)*(1+Premissas!$B$124)^0+MAX(J23-J26-(IF(Premissas!$B$8>0,MAX(J24+J27+J28+J29-J22,0)*Premissas!$B$8,0)),0)*Premissas!$B$6*(1+Premissas!$B$126)*(1+Premissas!$B$124)^0) -> 0 | K36: =IF(K31>0,0,MAX(K22-K24-K27+K28-K29,0)*Premissas!$B$5*(1+Premissas!$B$126)*(1+Premissas!$B$124)^0+MAX(K23-K26-(IF(Premissas!$B$8>0,MAX(K24+K27+K28+K29-K22,0)*Premissas!$B$8,0)),0)*Premissas!$B$6*(1+Premissas!$B$126)*(1+Premissas!$B$124)^0) -> 0 | ... O36: =IF(O31>0,0,MAX(O22-O24-O27+O28-O29,0)*Premissas!$B$5*(1+Premissas!$B$126)*(1+Premissas!$B$124)^0+MAX(O23-O26-(IF(Premissas!$B$8>0,MAX(O24+O27+O28+O29-O22,0)*Premissas!$B$8,0)),0)*Premissas!$B$6*(1+Premissas!$B$126)*(1+Premissas!$B$124)^0) -> 0 | P36: =IF(P31>0,0,MAX(P22-P24-P27+P28-P29,0)*Premissas!$B$5*(1+Premissas!$B$126)*(1+Premissas!$B$124)^1+MAX(P23-P26-(IF(Premissas!$B$8>0,MAX(P24+P27+P28+P29-P22,0)*Premissas!$B$8,0)),0)*Premissas!$B$6*(1+Premissas!$B$126)*(1+Premissas!$B$124)^1) -> 0 | Q36: =IF(Q31>0,0,MAX(Q22-Q24-Q27+Q28-Q29,0)*Premissas!$B$5*(1+Premissas!$B$126)*(1+Premissas!$B$124)^1+MAX(Q23-Q26-(IF(Premissas!$B$8>0,MAX(Q24+Q27+Q28+Q29-Q22,0)*Premissas!$B$8,0)),0)*Premissas!$B$6*(1+Premissas!$B$126)*(1+Premissas!$B$124)^1) -> 0 | R36: =IF(R31>0,0,MAX(R22-R24-R27+R28-R29,0)*Premissas!$B$5*(1+Premissas!$B$126)*(1+Premissas!$B$124)^1+MAX(R23-R26-(IF(Premissas!$B$8>0,MAX(R24+R27+R28+R29-R22,0)*Premissas!$B$8,0)),0)*Premissas!$B$6*(1+Premissas!$B$126)*(1+Premissas!$B$124)^1) -> 0 | S36: =IF(S31>0,0,MAX(S22-S24-S27+S28-S29,0)*Premissas!$B$5*(1+Premissas!$B$126)*(1+Premissas!$B$124)^1+MAX(S23-S26-(IF(Premissas!$B$8>0,MAX(S24+S27+S28+S29-S22,0)*Premissas!$B$8,0)),0)*Premissas!$B$6*(1+Premissas!$B$126)*(1+Premissas!$B$124)^1) -> 0 | T36: =IF(T31>0,0,MAX(T22-T24-T27+T28-T29,0)*Premissas!$B$5*(1+Premissas!$B$126)*(1+Premissas!$B$124)^1+MAX(T23-T26-(IF(Premissas!$B$8>0,MAX(T24+T27+T28+T29-T22,0)*Premissas!$B$8,0)),0)*Premissas!$B$6*(1+Premissas!$B$126)*(1+Premissas!$B$124)^1) -> 0 | U36: =IF(U31>0,0,MAX(U22-U24-U27+U28-U29,0)*Premissas!$B$5*(1+Premissas!$B$126)*(1+Premissas!$B$124)^1+MAX(U23-U26-(IF(Premissas!$B$8>0,MAX(U24+U27+U28+U29-U22,0)*Premissas!$B$8,0)),0)*Premissas!$B$6*(1+Premissas!$B$126)*(1+Premissas!$B$124)^1) -> 0 | V36: =IF(V31>0,0,MAX(V22-V24-V27+V28-V29,0)*Premissas!$B$5*(1+Premissas!$B$126)*(1+Premissas!$B$124)^1+MAX(V23-V26-(IF(Premissas!$B$8>0,MAX(V24+V27+V28+V29-V22,0)*Premissas!$B$8,0)),0)*Premissas!$B$6*(1+Premissas!$B$126)*(1+Premissas!$B$124)^1) -> 0 | W36: =IF(W31>0,0,MAX(W22-W24-W27+W28-W29,0)*Premissas!$B$5*(1+Premissas!$B$126)*(1+Premissas!$B$124)^1+MAX(W23-W26-(IF(Premissas!$B$8>0,MAX(W24+W27+W28+W29-W22,0)*Premissas!$B$8,0)),0)*Premissas!$B$6*(1+Premissas!$B$126)*(1+Premissas!$B$124)^1) -> 0 | ... AA36: =IF(AA31>0,0,MAX(AA22-AA24-AA27+AA28-AA29,0)*Premissas!$B$5*(1+Premissas!$B$126)*(1+Premissas!$B$124)^1+MAX(AA23-AA26-(IF(Premissas!$B$8>0,MAX(AA24+AA27+AA28+AA29-AA22,0)*Premissas!$B$8,0)),0)*Premissas!$B$6*(1+Premissas!$B$126)*(1+Premissas!$B$124)^1) -> 0 | AB36: =IF(AB31>0,0,MAX(AB22-AB24-AB27+AB28-AB29,0)*Premissas!$B$5*(1+Premissas!$B$126)*(1+Premissas!$B$124)^2+MAX(AB23-AB26-(IF(Premissas!$B$8>0,MAX(AB24+AB26-AB22-AB23,0)*Premissas!$B$8,0)),0)*Premissas!$B$6*(1+Premissas!$B$126)*(1+Premissas!$B$124)^2) -> 0 | AC36: =IF(AC31>0,0,MAX(AC22-AC24-AC27+AC28-AC29,0)*Premissas!$B$5*(1+Premissas!$B$126)*(1+Premissas!$B$124)^2+MAX(AC23-AC26-(IF(Premissas!$B$8>0,MAX(AC24+AC26-AC22-AC23,0)*Premissas!$B$8,0)),0)*Premissas!$B$6*(1+Premissas!$B$126)*(1+Premissas!$B$124)^2) -> 0 | AD36: =IF(AD31>0,0,MAX(AD22-AD24-AD27+AD28-AD29,0)*Premissas!$B$5*(1+Premissas!$B$126)*(1+Premissas!$B$124)^2+MAX(AD23-AD26-(IF(Premissas!$B$8>0,MAX(AD24+AD26-AD22-AD23,0)*Premissas!$B$8,0)),0)*Premissas!$B$6*(1+Premissas!$B$126)*(1+Premissas!$B$124)^2) -> 0 | AE36: =IF(AE31>0,0,MAX(AE22-AE24-AE27+AE28-AE29,0)*Premissas!$B$5*(1+Premissas!$B$126)*(1+Premissas!$B$124)^2+MAX(AE23-AE26-(IF(Premissas!$B$8>0,MAX(AE24+AE26-AE22-AE23,0)*Premissas!$B$8,0)),0)*Premissas!$B$6*(1+Premissas!$B$126)*(1+Premissas!$B$124)^2) -> 0 | AF36: =IF(AF31>0,0,MAX(AF22-AF24-AF27+AF28-AF29,0)*Premissas!$B$5*(1+Premissas!$B$126)*(1+Premissas!$B$124)^2+MAX(AF23-AF26-(IF(Premissas!$B$8>0,MAX(AF24+AF26-AF22-AF23,0)*Premissas!$B$8,0)),0)*Premissas!$B$6*(1+Premissas!$B$126)*(1+Premissas!$B$124)^2) -> 0 | AG36: =IF(AG31>0,0,MAX(AG22-AG24-AG27+AG28-AG29,0)*Premissas!$B$5*(1+Premissas!$B$126)*(1+Premissas!$B$124)^2+MAX(AG23-AG26-(IF(Premissas!$B$8>0,MAX(AG24+AG26-AG22-AG23,0)*Premissas!$B$8,0)),0)*Premissas!$B$6*(1+Premissas!$B$126)*(1+Premissas!$B$124)^2) -> 0 | AH36: =IF(AH31>0,0,MAX(AH22-AH24-AH27+AH28-AH29,0)*Premissas!$B$5*(1+Premissas!$B$126)*(1+Premissas!$B$124)^2+MAX(AH23-AH26-(IF(Premissas!$B$8>0,MAX(AH24+AH26-AH22-AH23,0)*Premissas!$B$8,0)),0)*Premissas!$B$6*(1+Premissas!$B$126)*(1+Premissas!$B$124)^2) -> 0 | AI36: =IF(AI31>0,0,MAX(AI22-AI24-AI27+AI28-AI29,0)*Premissas!$B$5*(1+Premissas!$B$126)*(1+Premissas!$B$124)^2+MAX(AI23-AI26-(IF(Premissas!$B$8>0,MAX(AI24+AI26-AI22-AI23,0)*Premissas!$B$8,0)),0)*Premissas!$B$6*(1+Premissas!$B$126)*(1+Premissas!$B$124)^2) -> 0 | ... AM36: =IF(AM31>0,0,MAX(AM22-AM24-AM27+AM28-AM29,0)*Premissas!$B$5*(1+Premissas!$B$126)*(1+Premissas!$B$124)^2+MAX(AM23-AM26-(IF(Premissas!$B$8>0,MAX(AM24+AM26-AM22-AM23,0)*Premissas!$B$8,0)),0)*Premissas!$B$6*(1+Premissas!$B$126)*(1+Premissas!$B$124)^2) -> 0 | AN36: =IF(AN31>0,0,MAX(AN22-AN24-AN27+AN28-AN29,0)*Premissas!$B$5*(1+Premissas!$B$126)*(1+Premissas!$B$124)^3+MAX(AN23-AN26-(IF(Premissas!$B$8>0,MAX(AN24+AN26-AN22-AN23,0)*Premissas!$B$8,0)),0)*Premissas!$B$6*(1+Premissas!$B$126)*(1+Premissas!$B$124)^3) -> 0 | AO36: =IF(AO31>0,0,MAX(AO22-AO24-AO27+AO28-AO29,0)*Premissas!$B$5*(1+Premissas!$B$126)*(1+Premissas!$B$124)^3+MAX(AO23-AO26-(IF(Premissas!$B$8>0,MAX(AO24+AO26-AO22-AO23,0)*Premissas!$B$8,0)),0)*Premissas!$B$6*(1+Premissas!$B$126)*(1+Premissas!$B$124)^3) -> 0 | AP36: =IF(AP31>0,0,MAX(AP22-AP24-AP27+AP28-AP29,0)*Premissas!$B$5*(1+Premissas!$B$126)*(1+Premissas!$B$124)^3+MAX(AP23-AP26-(IF(Premissas!$B$8>0,MAX(AP24+AP26-AP22-AP23,0)*Premissas!$B$8,0)),0)*Premissas!$B$6*(1+Premissas!$B$126)*(1+Premissas!$B$124)^3) -> 0 | AQ36: =IF(AQ31>0,0,MAX(AQ22-AQ24-AQ27+AQ28-AQ29,0)*Premissas!$B$5*(1+Premissas!$B$126)*(1+Premissas!$B$124)^3+MAX(AQ23-AQ26-(IF(Premissas!$B$8>0,MAX(AQ24+AQ26-AQ22-AQ23,0)*Premissas!$B$8,0)),0)*Premissas!$B$6*(1+Premissas!$B$126)*(1+Premissas!$B$124)^3) -> 0 | AR36: =IF(AR31>0,0,MAX(AR22-AR24-AR27+AR28-AR29,0)*Premissas!$B$5*(1+Premissas!$B$126)*(1+Premissas!$B$124)^3+MAX(AR23-AR26-(IF(Premissas!$B$8>0,MAX(AR24+AR26-AR22-AR23,0)*Premissas!$B$8,0)),0)*Premissas!$B$6*(1+Premissas!$B$126)*(1+Premissas!$B$124)^3) -> 0 | AS36: =IF(AS31>0,0,MAX(AS22-AS24-AS27+AS28-AS29,0)*Premissas!$B$5*(1+Premissas!$B$126)*(1+Premissas!$B$124)^3+MAX(AS23-AS26-(IF(Premissas!$B$8>0,MAX(AS24+AS26-AS22-AS23,0)*Premissas!$B$8,0)),0)*Premissas!$B$6*(1+Premissas!$B$126)*(1+Premissas!$B$124)^3) -> 0 | AT36: =IF(AT31>0,0,MAX(AT22-AT24-AT27+AT28-AT29,0)*Premissas!$B$5*(1+Premissas!$B$126)*(1+Premissas!$B$124)^3+MAX(AT23-AT26-(IF(Premissas!$B$8>0,MAX(AT24+AT26-AT22-AT23,0)*Premissas!$B$8,0)),0)*Premissas!$B$6*(1+Premissas!$B$126)*(1+Premissas!$B$124)^3) -> 0 | AU36: =IF(AU31>0,0,MAX(AU22-AU24-AU27+AU28-AU29,0)*Premissas!$B$5*(1+Premissas!$B$126)*(1+Premissas!$B$124)^3+MAX(AU23-AU26-(IF(Premissas!$B$8>0,MAX(AU24+AU26-AU22-AU23,0)*Premissas!$B$8,0)),0)*Premissas!$B$6*(1+Premissas!$B$126)*(1+Premissas!$B$124)^3) -> 0 | ... AY36: =IF(AY31>0,0,MAX(AY22-AY24-AY27+AY28-AY29,0)*Premissas!$B$5*(1+Premissas!$B$126)*(1+Premissas!$B$124)^3+MAX(AY23-AY26-(IF(Premissas!$B$8>0,MAX(AY24+AY26-AY22-AY23,0)*Premissas!$B$8,0)),0)*Premissas!$B$6*(1+Premissas!$B$126)*(1+Premissas!$B$124)^3) -> 0 | AZ36: =IF(AZ31>0,0,MAX(AZ22-AZ24-AZ27+AZ28-AZ29,0)*Premissas!$B$5*(1+Premissas!$B$126)*(1+Premissas!$B$124)^4+MAX(AZ23-AZ26-(IF(Premissas!$B$8>0,MAX(AZ24+AZ26-AZ22-AZ23,0)*Premissas!$B$8,0)),0)*Premissas!$B$6*(1+Premissas!$B$126)*(1+Premissas!$B$124)^4) -> 0 | BA36: =IF(BA31>0,0,MAX(BA22-BA24-BA27+BA28-BA29,0)*Premissas!$B$5*(1+Premissas!$B$126)*(1+Premissas!$B$124)^4+MAX(BA23-BA26-(IF(Premissas!$B$8>0,MAX(BA24+BA26-BA22-BA23,0)*Premissas!$B$8,0)),0)*Premissas!$B$6*(1+Premissas!$B$126)*(1+Premissas!$B$124)^4) -> 0 | BB36: =IF(BB31>0,0,MAX(BB22-BB24-BB27+BB28-BB29,0)*Premissas!$B$5*(1+Premissas!$B$126)*(1+Premissas!$B$124)^4+MAX(BB23-BB26-(IF(Premissas!$B$8>0,MAX(BB24+BB26-BB22-BB23,0)*Premissas!$B$8,0)),0)*Premissas!$B$6*(1+Premissas!$B$126)*(1+Premissas!$B$124)^4) -> 0 | BC36: =IF(BC31>0,0,MAX(BC22-BC24-BC27+BC28-BC29,0)*Premissas!$B$5*(1+Premissas!$B$126)*(1+Premissas!$B$124)^4+MAX(BC23-BC26-(IF(Premissas!$B$8>0,MAX(BC24+BC26-BC22-BC23,0)*Premissas!$B$8,0)),0)*Premissas!$B$6*(1+Premissas!$B$126)*(1+Premissas!$B$124)^4) -> 0 | BD36: =IF(BD31>0,0,MAX(BD22-BD24-BD27+BD28-BD29,0)*Premissas!$B$5*(1+Premissas!$B$126)*(1+Premissas!$B$124)^4+MAX(BD23-BD26-(IF(Premissas!$B$8>0,MAX(BD24+BD26-BD22-BD23,0)*Premissas!$B$8,0)),0)*Premissas!$B$6*(1+Premissas!$B$126)*(1+Premissas!$B$124)^4) -> 0 | BE36: =IF(BE31>0,0,MAX(BE22-BE24-BE27+BE28-BE29,0)*Premissas!$B$5*(1+Premissas!$B$126)*(1+Premissas!$B$124)^4+MAX(BE23-BE26-(IF(Premissas!$B$8>0,MAX(BE24+BE26-BE22-BE23,0)*Premissas!$B$8,0)),0)*Premissas!$B$6*(1+Premissas!$B$126)*(1+Premissas!$B$124)^4) -> 0 | BF36: =IF(BF31>0,0,MAX(BF22-BF24-BF27+BF28-BF29,0)*Premissas!$B$5*(1+Premissas!$B$126)*(1+Premissas!$B$124)^4+MAX(BF23-BF26-(IF(Premissas!$B$8>0,MAX(BF24+BF26-BF22-BF23,0)*Premissas!$B$8,0)),0)*Premissas!$B$6*(1+Premissas!$B$126)*(1+Premissas!$B$124)^4) -> 0 | BG36: =IF(BG31>0,0,MAX(BG22-BG24-BG27+BG28-BG29,0)*Premissas!$B$5*(1+Premissas!$B$126)*(1+Premissas!$B$124)^4+MAX(BG23-BG26-(IF(Premissas!$B$8>0,MAX(BG24+BG26-BG22-BG23,0)*Premissas!$B$8,0)),0)*Premissas!$B$6*(1+Premissas!$B$126)*(1+Premissas!$B$124)^4) -> 0 | ... BK36: =IF(BK31>0,0,MAX(BK22-BK24-BK27+BK28-BK29,0)*Premissas!$B$5*(1+Premissas!$B$126)*(1+Premissas!$B$124)^4+MAX(BK23-BK26-(IF(Premissas!$B$8>0,MAX(BK24+BK26-BK22-BK23,0)*Premissas!$B$8,0)),0)*Premissas!$B$6*(1+Premissas!$B$126)*(1+Premissas!$B$124)^4) -> 0
A37: ★ Economia mensal (R$) | B37: =SUM(D37:BQ37) -> 3326978.9 | C37: =B37/60 -> 55449.648 | D37: =MAX(D35-D36,0) -> 0 | E37: =MAX(E35-E36,0) -> 0 | F37: =MAX(F35-F36,0) -> 0 | G37: =MAX(G35-G36,0) -> 0 | H37: =MAX(H35-H36,0) -> 0 | I37: =MAX(I35-I36,0) -> 0 | J37: =MAX(J35-J36,0) -> 0 | K37: =MAX(K35-K36,0) -> 0 | ... BK37: =MAX(BK35-BK36,0) -> 0
A39: AMD — Amandina (A3A)
A40: Consumo FP (kWh) | B40: =SUM(D40:BQ40) -> 6692611.4 | C40: =B40/60 -> 111543.52 | D40: =Input_Consumo_GrupoA!$F$9 -> 182444.7 | E40: =Input_Consumo_GrupoA!$F$10 -> 234799.2 | F40: =Input_Consumo_GrupoA!$F$11 -> 134799.3 | G40: =Input_Consumo_GrupoA!$F$12 -> 18637.2 | H40: =Input_Consumo_GrupoA!$F$13 -> 24382.8 | I40: =Input_Consumo_GrupoA!$F$14 -> 20225.7 | J40: =Input_Consumo_GrupoA!$F$15 -> 17142.3 | K40: =Input_Consumo_GrupoA!$F$4*(1+Premissas!$B$21) -> 75822.735 | L40: =Input_Consumo_GrupoA!$F$5*(1+Premissas!$B$21) -> 214709.01 | M40: =Input_Consumo_GrupoA!$F$6*(1+Premissas!$B$21) -> 177591.7 | N40: =Input_Consumo_GrupoA!$F$7*(1+Premissas!$B$21) -> 80409.61 | O40: =Input_Consumo_GrupoA!$F$8*(1+Premissas!$B$21) -> 105195.24 | P40: =Input_Consumo_GrupoA!$F$9*(1+Premissas!$B$21) -> 187005.82 | Q40: =Input_Consumo_GrupoA!$F$10*(1+Premissas!$B$21) -> 240669.18 | R40: =Input_Consumo_GrupoA!$F$11*(1+Premissas!$B$21) -> 138169.28 | S40: =Input_Consumo_GrupoA!$F$12*(1+Premissas!$B$21) -> 19103.13 | T40: =Input_Consumo_GrupoA!$F$13*(1+Premissas!$B$21) -> 24992.37 | U40: =Input_Consumo_GrupoA!$F$14*(1+Premissas!$B$21) -> 20731.342 | V40: =Input_Consumo_GrupoA!$F$15*(1+Premissas!$B$21) -> 17570.857 | W40: =Input_Consumo_GrupoA!$F$4*(1+Premissas!$B$21) -> 75822.735 | X40: =Input_Consumo_GrupoA!$F$5*(1+Premissas!$B$21) -> 214709.01 | Y40: =Input_Consumo_GrupoA!$F$6*(1+Premissas!$B$21) -> 177591.7 | Z40: =Input_Consumo_GrupoA!$F$7*(1+Premissas!$B$21) -> 80409.61 | AA40: =Input_Consumo_GrupoA!$F$8*(1+Premissas!$B$21) -> 105195.24 | AB40: =Input_Consumo_GrupoA!$F$9*(1+Premissas!$B$21)^2 -> 191680.96 | AC40: =Input_Consumo_GrupoA!$F$10*(1+Premissas!$B$21)^2 -> 246685.91 | AD40: =Input_Consumo_GrupoA!$F$11*(1+Premissas!$B$21)^2 -> 141623.51 | AE40: =Input_Consumo_GrupoA!$F$12*(1+Premissas!$B$21)^2 -> 19580.708 | AF40: =Input_Consumo_GrupoA!$F$13*(1+Premissas!$B$21)^2 -> 25617.179 | AG40: =Input_Consumo_GrupoA!$F$14*(1+Premissas!$B$21)^2 -> 21249.626 | AH40: =Input_Consumo_GrupoA!$F$15*(1+Premissas!$B$21)^2 -> 18010.129 | AI40: =Input_Consumo_GrupoA!$F$4*(1+Premissas!$B$21)^2 -> 77718.303 | AJ40: =Input_Consumo_GrupoA!$F$5*(1+Premissas!$B$21)^2 -> 220076.73 | AK40: =Input_Consumo_GrupoA!$F$6*(1+Premissas!$B$21)^2 -> 182031.5 | AL40: =Input_Consumo_GrupoA!$F$7*(1+Premissas!$B$21)^2 -> 82419.85 | AM40: =Input_Consumo_GrupoA!$F$8*(1+Premissas!$B$21)^2 -> 107825.12 | AN40: =Input_Consumo_GrupoA!$F$9*(1+Premissas!$B$21)^3 -> 196472.99 | AO40: =Input_Consumo_GrupoA!$F$10*(1+Premissas!$B$21)^3 -> 252853.06 | AP40: =Input_Consumo_GrupoA!$F$11*(1+Premissas!$B$21)^3 -> 145164.1 | AQ40: =Input_Consumo_GrupoA!$F$12*(1+Premissas!$B$21)^3 -> 20070.226 | AR40: =Input_Consumo_GrupoA!$F$13*(1+Premissas!$B$21)^3 -> 26257.609 | AS40: =Input_Consumo_GrupoA!$F$14*(1+Premissas!$B$21)^3 -> 21780.867 | AT40: =Input_Consumo_GrupoA!$F$15*(1+Premissas!$B$21)^3 -> 18460.382 | AU40: =Input_Consumo_GrupoA!$F$4*(1+Premissas!$B$21)^3 -> 79661.261 | AV40: =Input_Consumo_GrupoA!$F$5*(1+Premissas!$B$21)^3 -> 225578.65 | AW40: =Input_Consumo_GrupoA!$F$6*(1+Premissas!$B$21)^3 -> 186582.29 | AX40: =Input_Consumo_GrupoA!$F$7*(1+Premissas!$B$21)^3 -> 84480.347 | AY40: =Input_Consumo_GrupoA!$F$8*(1+Premissas!$B$21)^3 -> 110520.75 | AZ40: =Input_Consumo_GrupoA!$F$9*(1+Premissas!$B$21)^4 -> 201384.81 | BA40: =Input_Consumo_GrupoA!$F$10*(1+Premissas!$B$21)^4 -> 259174.38 | BB40: =Input_Consumo_GrupoA!$F$11*(1+Premissas!$B$21)^4 -> 148793.2 | BC40: =Input_Consumo_GrupoA!$F$12*(1+Premissas!$B$21)^4 -> 20571.982 | BD40: =Input_Consumo_GrupoA!$F$13*(1+Premissas!$B$21)^4 -> 26914.049 | BE40: =Input_Consumo_GrupoA!$F$14*(1+Premissas!$B$21)^4 -> 22325.388 | BF40: =Input_Consumo_GrupoA!$F$15*(1+Premissas!$B$21)^4 -> 18921.892 | BG40: =Input_Consumo_GrupoA!$F$4*(1+Premissas!$B$21)^4 -> 81652.792 | BH40: =Input_Consumo_GrupoA!$F$5*(1+Premissas!$B$21)^4 -> 231218.11 | BI40: =Input_Consumo_GrupoA!$F$6*(1+Premissas!$B$21)^4 -> 191246.84 | BJ40: =Input_Consumo_GrupoA!$F$7*(1+Premissas!$B$21)^4 -> 86592.355 | BK40: =Input_Consumo_GrupoA!$F$8*(1+Premissas!$B$21)^4 -> 113283.77
A41: Consumo Ponta (kWh) [via FA] | B41: =SUM(D41:BQ41) -> 743623.55 | C41: =B41/60 -> 12393.726 | D41: =Input_Consumo_GrupoA!$G$9 -> 20271.6 | E41: =Input_Consumo_GrupoA!$G$10 -> 26088.8 | F41: =Input_Consumo_GrupoA!$G$11 -> 14977.7 | G41: =Input_Consumo_GrupoA!$G$12 -> 2070.8 | H41: =Input_Consumo_GrupoA!$G$13 -> 2709.2 | I41: =Input_Consumo_GrupoA!$G$14 -> 2247.3 | J41: =Input_Consumo_GrupoA!$G$15 -> 1904.7 | K41: =Input_Consumo_GrupoA!$G$4*(1+Premissas!$B$21) -> 8424.7825 | L41: =Input_Consumo_GrupoA!$G$5*(1+Premissas!$B$21) -> 23856.567 | M41: =Input_Consumo_GrupoA!$G$6*(1+Premissas!$B$21) -> 19732.377 | N41: =Input_Consumo_GrupoA!$G$7*(1+Premissas!$B$21) -> 8934.4125 | O41: =Input_Consumo_GrupoA!$G$8*(1+Premissas!$B$21) -> 11688.382 | P41: =Input_Consumo_GrupoA!$G$9*(1+Premissas!$B$21) -> 20778.39 | Q41: =Input_Consumo_GrupoA!$G$10*(1+Premissas!$B$21) -> 26741.02 | R41: =Input_Consumo_GrupoA!$G$11*(1+Premissas!$B$21) -> 15352.142 | S41: =Input_Consumo_GrupoA!$G$12*(1+Premissas!$B$21) -> 2122.57 | T41: =Input_Consumo_GrupoA!$G$13*(1+Premissas!$B$21) -> 2776.93 | U41: =Input_Consumo_GrupoA!$G$14*(1+Premissas!$B$21) -> 2303.4825 | V41: =Input_Consumo_GrupoA!$G$15*(1+Premissas!$B$21) -> 1952.3175 | W41: =Input_Consumo_GrupoA!$G$4*(1+Premissas!$B$21) -> 8424.7825 | X41: =Input_Consumo_GrupoA!$G$5*(1+Premissas!$B$21) -> 23856.567 | Y41: =Input_Consumo_GrupoA!$G$6*(1+Premissas!$B$21) -> 19732.377 | Z41: =Input_Consumo_GrupoA!$G$7*(1+Premissas!$B$21) -> 8934.4125 | AA41: =Input_Consumo_GrupoA!$G$8*(1+Premissas!$B$21) -> 11688.382 | AB41: =Input_Consumo_GrupoA!$G$9*(1+Premissas!$B$21)^2 -> 21297.85 | AC41: =Input_Consumo_GrupoA!$G$10*(1+Premissas!$B$21)^2 -> 27409.545 | AD41: =Input_Consumo_GrupoA!$G$11*(1+Premissas!$B$21)^2 -> 15735.946 | AE41: =Input_Consumo_GrupoA!$G$12*(1+Premissas!$B$21)^2 -> 2175.6343 | AF41: =Input_Consumo_GrupoA!$G$13*(1+Premissas!$B$21)^2 -> 2846.3532 | AG41: =Input_Consumo_GrupoA!$G$14*(1+Premissas!$B$21)^2 -> 2361.0696 | AH41: =Input_Consumo_GrupoA!$G$15*(1+Premissas!$B$21)^2 -> 2001.1254 | AI41: =Input_Consumo_GrupoA!$G$4*(1+Premissas!$B$21)^2 -> 8635.4021 | AJ41: =Input_Consumo_GrupoA!$G$5*(1+Premissas!$B$21)^2 -> 24452.982 | AK41: =Input_Consumo_GrupoA!$G$6*(1+Premissas!$B$21)^2 -> 20225.687 | AL41: =Input_Consumo_GrupoA!$G$7*(1+Premissas!$B$21)^2 -> 9157.7728 | AM41: =Input_Consumo_GrupoA!$G$8*(1+Premissas!$B$21)^2 -> 11980.592 | AN41: =Input_Consumo_GrupoA!$G$9*(1+Premissas!$B$21)^3 -> 21830.296 | AO41: =Input_Consumo_GrupoA!$G$10*(1+Premissas!$B$21)^3 -> 28094.784 | AP41: =Input_Consumo_GrupoA!$G$11*(1+Premissas!$B$21)^3 -> 16129.345 | AQ41: =Input_Consumo_GrupoA!$G$12*(1+Premissas!$B$21)^3 -> 2230.0251 | AR41: =Input_Consumo_GrupoA!$G$13*(1+Premissas!$B$21)^3 -> 2917.5121 | AS41: =Input_Consumo_GrupoA!$G$14*(1+Premissas!$B$21)^3 -> 2420.0963 | AT41: =Input_Consumo_GrupoA!$G$15*(1+Premissas!$B$21)^3 -> 2051.1536 | AU41: =Input_Consumo_GrupoA!$G$4*(1+Premissas!$B$21)^3 -> 8851.2871 | AV41: =Input_Consumo_GrupoA!$G$5*(1+Premissas!$B$21)^3 -> 25064.306 | AW41: =Input_Consumo_GrupoA!$G$6*(1+Premissas!$B$21)^3 -> 20731.329 | AX41: =Input_Consumo_GrupoA!$G$7*(1+Premissas!$B$21)^3 -> 9386.7171 | AY41: =Input_Consumo_GrupoA!$G$8*(1+Premissas!$B$21)^3 -> 12280.107 | AZ41: =Input_Consumo_GrupoA!$G$9*(1+Premissas!$B$21)^4 -> 22376.053 | BA41: =Input_Consumo_GrupoA!$G$10*(1+Premissas!$B$21)^4 -> 28797.154 | BB41: =Input_Consumo_GrupoA!$G$11*(1+Premissas!$B$21)^4 -> 16532.578 | BC41: =Input_Consumo_GrupoA!$G$12*(1+Premissas!$B$21)^4 -> 2285.7757 | BD41: =Input_Consumo_GrupoA!$G$13*(1+Premissas!$B$21)^4 -> 2990.4499 | BE41: =Input_Consumo_GrupoA!$G$14*(1+Premissas!$B$21)^4 -> 2480.5987 | BF41: =Input_Consumo_GrupoA!$G$15*(1+Premissas!$B$21)^4 -> 2102.4324 | BG41: =Input_Consumo_GrupoA!$G$4*(1+Premissas!$B$21)^4 -> 9072.5693 | BH41: =Input_Consumo_GrupoA!$G$5*(1+Premissas!$B$21)^4 -> 25690.914 | BI41: =Input_Consumo_GrupoA!$G$6*(1+Premissas!$B$21)^4 -> 21249.612 | BJ41: =Input_Consumo_GrupoA!$G$7*(1+Premissas!$B$21)^4 -> 9621.3851 | BK41: =Input_Consumo_GrupoA!$G$8*(1+Premissas!$B$21)^4 -> 12587.11
A42: Geração própria (kWh) | B42: =SUM(D42:BQ42) -> 4482675.2 | C42: =B42/60 -> 74711.253 | D42: =IF(Premissas!$B$24="Sim",Amandina!$L$8*1000,Amandina!$I$8) -> 57829.52 | E42: =IF(Premissas!$B$24="Sim",Amandina!$L$9*1000,Amandina!$I$9) -> 70669.44 | F42: =IF(Premissas!$B$24="Sim",Amandina!$L$10*1000,Amandina!$I$10) -> 74466.16 | G42: =IF(Premissas!$B$24="Sim",Amandina!$L$11*1000,Amandina!$I$11) -> 75546.72 | H42: =IF(Premissas!$B$24="Sim",Amandina!$L$12*1000,Amandina!$I$12) -> 76725.44 | I42: =IF(Premissas!$B$24="Sim",Amandina!$L$13*1000,Amandina!$I$13) -> 86384.48 | J42: =IF(Premissas!$B$24="Sim",Amandina!$L$14*1000,Amandina!$I$14) -> 85283.12 | K42: =IF(Premissas!$B$24="Sim",Amandina!$L$3*1000*(1-Premissas!$B$23),Amandina!$I$3*(1-Premissas!$B$23)) -> 90950.164 | L42: =IF(Premissas!$B$24="Sim",Amandina!$L$4*1000*(1-Premissas!$B$23),Amandina!$I$4*(1-Premissas!$B$23)) -> 72540.992 | M42: =IF(Premissas!$B$24="Sim",Amandina!$L$5*1000*(1-Premissas!$B$23),Amandina!$I$5*(1-Premissas!$B$23)) -> 82037.272 | N42: =IF(Premissas!$B$24="Sim",Amandina!$L$6*1000*(1-Premissas!$B$23),Amandina!$I$6*(1-Premissas!$B$23)) -> 58672.921 | O42: =IF(Premissas!$B$24="Sim",Amandina!$L$7*1000*(1-Premissas!$B$23),Amandina!$I$7*(1-Premissas!$B$23)) -> 72926.814 | P42: =IF(Premissas!$B$24="Sim",Amandina!$L$8*1000*(1-Premissas!$B$23),Amandina!$I$8*(1-Premissas!$B$23)) -> 57540.372 | Q42: =IF(Premissas!$B$24="Sim",Amandina!$L$9*1000*(1-Premissas!$B$23),Amandina!$I$9*(1-Premissas!$B$23)) -> 70316.093 | R42: =IF(Premissas!$B$24="Sim",Amandina!$L$10*1000*(1-Premissas!$B$23),Amandina!$I$10*(1-Premissas!$B$23)) -> 74093.829 | S42: =IF(Premissas!$B$24="Sim",Amandina!$L$11*1000*(1-Premissas!$B$23),Amandina!$I$11*(1-Premissas!$B$23)) -> 75168.986 | T42: =IF(Premissas!$B$24="Sim",Amandina!$L$12*1000*(1-Premissas!$B$23),Amandina!$I$12*(1-Premissas!$B$23)) -> 76341.813 | U42: =IF(Premissas!$B$24="Sim",Amandina!$L$13*1000*(1-Premissas!$B$23),Amandina!$I$13*(1-Premissas!$B$23)) -> 85952.558 | V42: =IF(Premissas!$B$24="Sim",Amandina!$L$14*1000*(1-Premissas!$B$23),Amandina!$I$14*(1-Premissas!$B$23)) -> 84856.704 | W42: =IF(Premissas!$B$24="Sim",Amandina!$L$3*1000*(1-Premissas!$B$23),Amandina!$I$3*(1-Premissas!$B$23)) -> 90950.164 | X42: =IF(Premissas!$B$24="Sim",Amandina!$L$4*1000*(1-Premissas!$B$23),Amandina!$I$4*(1-Premissas!$B$23)) -> 72540.992 | Y42: =IF(Premissas!$B$24="Sim",Amandina!$L$5*1000*(1-Premissas!$B$23),Amandina!$I$5*(1-Premissas!$B$23)) -> 82037.272 | Z42: =IF(Premissas!$B$24="Sim",Amandina!$L$6*1000*(1-Premissas!$B$23),Amandina!$I$6*(1-Premissas!$B$23)) -> 58672.921 | AA42: =IF(Premissas!$B$24="Sim",Amandina!$L$7*1000*(1-Premissas!$B$23),Amandina!$I$7*(1-Premissas!$B$23)) -> 72926.814 | AB42: =P42*(1-Premissas!$B$23) -> 57252.671 | AC42: =Q42*(1-Premissas!$B$23) -> 69964.512 | AD42: =R42*(1-Premissas!$B$23) -> 73723.36 | AE42: =S42*(1-Premissas!$B$23) -> 74793.141 | AF42: =T42*(1-Premissas!$B$23) -> 75960.104 | AG42: =U42*(1-Premissas!$B$23) -> 85522.795 | AH42: =V42*(1-Premissas!$B$23) -> 84432.421 | AI42: =W42*(1-Premissas!$B$23) -> 90495.413 | ... BK42: =AY42*(1-Premissas!$B$23) -> 71838.372
A43: Auto-comp. FP (kWh) | B43: =SUM(D43:BQ43) -> 3240284.8 | C43: =B43/60 -> 54004.746 | D43: =MIN(D42,D40) -> 57829.52 | E43: =MIN(E42,E40) -> 70669.44 | F43: =MIN(F42,F40) -> 74466.16 | G43: =MIN(G42,G40) -> 18637.2 | H43: =MIN(H42,H40) -> 24382.8 | I43: =MIN(I42,I40) -> 20225.7 | J43: =MIN(J42,J40) -> 17142.3 | K43: =MIN(K42,K40) -> 75822.735 | ... BK43: =MIN(BK42,BK40) -> 71838.372
A44: Auto-comp. Ponta via FA (kWh) | B44: =SUM(D44:BQ44) -> 82591.019 | C44: =B44/60 -> 1376.517 | D44: =MIN((D42-D43)*Premissas!$B$8,D41) -> 0 | E44: =MIN((E42-E43)*Premissas!$B$8,E41) -> 0 | F44: =MIN((F42-F43)*Premissas!$B$8,F41) -> 0 | G44: =MIN((G42-G43)*Premissas!$B$8,G41) -> 2070.8 | H44: =MIN((H42-H43)*Premissas!$B$8,H41) -> 2709.2 | I44: =MIN((I42-I43)*Premissas!$B$8,I41) -> 2247.3 | J44: =MIN((J42-J43)*Premissas!$B$8,J41) -> 1904.7 | K44: =MIN((K42-K43)*Premissas!$B$8,K41) -> 8424.7825 | ... BK44: =MIN((BK42-BK43)*Premissas!$B$8,BK41) -> 0
A45: =" "&INDEX(PVSYST_Helexia!$A$5:$A$7,MATCH(Premissas!$B$13,PVSYST_Helexia!$B$5:$B$7,0))&" créditos recebidos (kWh)" -> HCS03 créditos recebidos (kWh) | B45: =SUM(D45:BQ45) -> 1856647.1 | C45: =B45/60 -> 30944.119 | D45: =D6*Premissas!$B$35 -> 0 | E45: =E6*Premissas!$B$35 -> 0 | F45: =F6*Premissas!$B$35 -> 0 | G45: =G6*Premissas!$B$35 -> 0 | H45: =H6*Premissas!$C$35 -> 0 | I45: =I6*Premissas!$C$35 -> 0 | J45: =J6*Premissas!$C$35 -> 0 | K45: =K6*Premissas!$C$35 -> 0 | L45: =L6*Premissas!$C$35 -> 0 | M45: =M6*Premissas!$C$35 -> 0 | N45: =N6*Premissas!$D$35 -> 595.52541 | O45: =O6*Premissas!$D$35 -> 557.34129 | P45: =P6*Premissas!$D$35 -> 505.81721 | Q45: =Q6*Premissas!$D$35 -> 532.41554 | R45: =R6*Premissas!$D$35 -> 639.13527 | S45: =S6*Premissas!$D$35 -> 599.7273 | T45: =T6*Premissas!$E$35 -> 23465.67 | U45: =U6*Premissas!$E$35 -> 22689.073 | V45: =V6*Premissas!$E$35 -> 21544.368 | W45: =W6*Premissas!$E$35 -> 22232.433 | X45: =X6*Premissas!$E$35 -> 19811.002 | Y45: =Y6*Premissas!$E$35 -> 22723.243 | Z45: =Z6*Premissas!$E$35 -> 22673.541 | AA45: =AA6*Premissas!$E$35 -> 21219.75 | AB45: =AB6*Premissas!$F$35 -> 45848.32 | AC45: =AC6*Premissas!$F$35 -> 48259.249 | AD45: =AD6*Premissas!$F$35 -> 57932.545 | AE45: =AE6*Premissas!$F$35 -> 54360.525 | AF45: =AF6*Premissas!$F$35 -> 55865.507 | AG45: =AG6*Premissas!$F$35 -> 54016.635 | AH45: =AH6*Premissas!$G$35 -> 50783.291 | AI45: =AI6*Premissas!$G$35 -> 52405.164 | AJ45: =AJ6*Premissas!$G$35 -> 46697.489 | AK45: =AK6*Premissas!$G$35 -> 53562.075 | AL45: =AL6*Premissas!$G$35 -> 53444.92 | AM45: =AM6*Premissas!$G$35 -> 50018.118 | AN45: =AN6*Premissas!$H$35 -> 45509.153 | AO45: =AO6*Premissas!$H$35 -> 47902.247 | AP45: =AP6*Premissas!$H$35 -> 57503.984 | AQ45: =AQ6*Premissas!$H$35 -> 53958.388 | AR45: =AR6*Premissas!$H$35 -> 55452.237 | AS45: =AS6*Premissas!$H$35 -> 53617.042 | AT45: =AT6*Premissas!$I$35 -> 50392.735 | AU45: =AU6*Premissas!$I$35 -> 52002.134 | AV45: =AV6*Premissas!$I$35 -> 46338.356 | AW45: =AW6*Premissas!$I$35 -> 53150.148 | AX45: =AX6*Premissas!$I$35 -> 53033.894 | AY45: =AY6*Premissas!$I$35 -> 49633.447 | AZ45: =AZ6*Premissas!$J$35 -> 28243.278 | BA45: =BA6*Premissas!$J$35 -> 29728.448 | BB45: =BB6*Premissas!$J$35 -> 35687.349 | BC45: =BC6*Premissas!$J$35 -> 33486.929 | BD45: =BD6*Premissas!$J$35 -> 34414.021 | BE45: =BE6*Premissas!$J$35 -> 33275.088 | BF45: =BF6*Premissas!$K$35 -> 39767.287 | BG45: =BG6*Premissas!$K$35 -> 41037.34 | BH45: =BH6*Premissas!$K$35 -> 36567.785 | BI45: =BI6*Premissas!$K$35 -> 41943.293 | BJ45: =BJ6*Premissas!$K$35 -> 41851.551 | BK45: =BK6*Premissas!$K$35 -> 39168.097
A46: BAT créditos → AMD (kWh) | B46: =SUM(D46:BQ46) -> 1192710.1 | C46: =B46/60 -> 19878.501 | D46: =D20 -> 0 | E46: =E20 -> 0 | F46: =F20 -> 0 | G46: =G20 -> 32711.293 | H46: =H20 -> 40823.762 | I46: =I20 -> 41560.462 | J46: =J20 -> 47597.362 | K46: =K20 -> 51288.174 | ... BK46: =BK20 -> 12655.84
A47: Banco início mês COM Helexia (kWh) | B47: =AA47 -> 263594.8 | C47: — | D47: =Premissas!$B$28 -> 0 | E47: =D49 -> 0 | F47: =E49 -> 0 | G47: =F49 -> 0 | H47: =G49 -> 89620.813 | I47: =H49 -> 182787.21 | J47: =I49 -> 290506.46 | K47: =J49 -> 406244.64 | L47: =K49 -> 436499.5 | ... BK47: =BJ49 -> 619176.04
A48: Bank draw COM Helexia (kWh) | B48: =SUM(D48:BQ48) -> 2740504.1 | C48: =B48/60 -> 45675.068 | D48: =MIN(D47,MAX(D40-D42-D45+D46,0)+IF(Premissas!$B$8=0,0,MAX(D41-D44,0)/Premissas!$B$8)) -> 0 | E48: =MIN(E47,MAX(E40-E42-E45+E46,0)+IF(Premissas!$B$8=0,0,MAX(E41-E44,0)/Premissas!$B$8)) -> 0 | F48: =MIN(F47,MAX(F40-F42-F45+F46,0)+IF(Premissas!$B$8=0,0,MAX(F41-F44,0)/Premissas!$B$8)) -> 0 | G48: =MIN(G47,MAX(G40-G42-G45+G46,0)+IF(Premissas!$B$8=0,0,MAX(G41-G44,0)/Premissas!$B$8)) -> 0 | H48: =MIN(H47,MAX(H40-H42-H45+H46,0)+IF(Premissas!$B$8=0,0,MAX(H41-H44,0)/Premissas!$B$8)) -> 0 | I48: =MIN(I47,MAX(I40-I42-I45+I46,0)+IF(Premissas!$B$8=0,0,MAX(I41-I44,0)/Premissas!$B$8)) -> 0 | J48: =MIN(J47,MAX(J40-J42-J45+J46,0)+IF(Premissas!$B$8=0,0,MAX(J41-J44,0)/Premissas!$B$8)) -> 0 | K48: =MIN(K47,MAX(K40-K42-K45+K46,0)+IF(Premissas!$B$8=0,0,MAX(K41-K44,0)/Premissas!$B$8)) -> 36160.745 | ... BK48: =MIN(BK47,MAX(BK40-BK42-BK45+BK46,0)+IF(Premissas!$B$8=0,0,MAX(BK41-BK44,0)/Premissas!$B$8)) -> 35763.512
A49: ★ Banco fim mês COM Helexia (kWh) | B49: =AA49 -> 233203.06 | C49: — | D49: =MAX(D47-D48,0)+D46+MAX(D45-MAX(D40-D42,0),0)+MAX(D42-D40,0) -> 0 | E49: =MAX(E47-E48,0)+E46+MAX(E45-MAX(E40-E42,0),0)+MAX(E42-E40,0) -> 0 | F49: =MAX(F47-F48,0)+F46+MAX(F45-MAX(F40-F42,0),0)+MAX(F42-F40,0) -> 0 | G49: =MAX(G47-G48,0)+G46+MAX(G45-MAX(G40-G42,0),0)+MAX(G42-G40,0) -> 89620.813 | H49: =MAX(H47-H48,0)+H46+MAX(H45-MAX(H40-H42,0),0)+MAX(H42-H40,0) -> 182787.21 | I49: =MAX(I47-I48,0)+I46+MAX(I45-MAX(I40-I42,0),0)+MAX(I42-I40,0) -> 290506.46 | J49: =MAX(J47-J48,0)+J46+MAX(J45-MAX(J40-J42,0),0)+MAX(J42-J40,0) -> 406244.64 | K49: =MAX(K47-K48,0)+K46+MAX(K45-MAX(K40-K42,0),0)+MAX(K42-K40,0) -> 436499.5 | ... BK49: =MAX(BK47-BK48,0)+BK46+MAX(BK45-MAX(BK40-BK42,0),0)+MAX(BK42-BK40,0) -> 596068.37
A50: Banco início mês SEM Helexia (kWh) | B50: =AA50 -> 152790.4 | C50: — | D50: =Premissas!$B$28 -> 0 | E50: =D52 -> 0 | F50: =E52 -> 0 | G50: =F52 -> 0 | H50: =G52 -> 89620.813 | I50: =H52 -> 182787.21 | J50: =I52 -> 290506.46 | K50: =J52 -> 406244.64 | L50: =K52 -> 472660.24 | ... BK50: =BJ52 -> 74897.553
A51: Bank draw SEM Helexia (kWh) — gen+BAT, no CS3 | B51: =SUM(D51:BQ51) -> 2397167 | C51: =B51/60 -> 39952.784 | D51: =MIN(D50,MAX(D40-D42-D46,0)+IF(Premissas!$B$8=0,0,MAX(D41-D44-(IF(Premissas!$B$8>0,MAX(D42-D40,0)*Premissas!$B$8,0)),0)/Premissas!$B$8)) -> 0 | E51: =MIN(E50,MAX(E40-E42-E46,0)+IF(Premissas!$B$8=0,0,MAX(E41-E44-(IF(Premissas!$B$8>0,MAX(E42-E40,0)*Premissas!$B$8,0)),0)/Premissas!$B$8)) -> 0 | F51: =MIN(F50,MAX(F40-F42-F46,0)+IF(Premissas!$B$8=0,0,MAX(F41-F44-(IF(Premissas!$B$8>0,MAX(F42-F40,0)*Premissas!$B$8,0)),0)/Premissas!$B$8)) -> 0 | G51: =MIN(G50,MAX(G40-G42-G46,0)+IF(Premissas!$B$8=0,0,MAX(G41-G44-(IF(Premissas!$B$8>0,MAX(G42-G40,0)*Premissas!$B$8,0)),0)/Premissas!$B$8)) -> 0 | H51: =MIN(H50,MAX(H40-H42-H46,0)+IF(Premissas!$B$8=0,0,MAX(H41-H44-(IF(Premissas!$B$8>0,MAX(H42-H40,0)*Premissas!$B$8,0)),0)/Premissas!$B$8)) -> 0 | I51: =MIN(I50,MAX(I40-I42-I46,0)+IF(Premissas!$B$8=0,0,MAX(I41-I44-(IF(Premissas!$B$8>0,MAX(I42-I40,0)*Premissas!$B$8,0)),0)/Premissas!$B$8)) -> 0 | J51: =MIN(J50,MAX(J40-J42-J46,0)+IF(Premissas!$B$8=0,0,MAX(J41-J44-(IF(Premissas!$B$8>0,MAX(J42-J40,0)*Premissas!$B$8,0)),0)/Premissas!$B$8)) -> 0 | K51: =MIN(K50,MAX(K40-K42-K46,0)+IF(Premissas!$B$8=0,0,MAX(K41-K44-(IF(Premissas!$B$8>0,MAX(K42-K40,0)*Premissas!$B$8,0)),0)/Premissas!$B$8)) -> 0 | ... AA51: =MIN(AA50,MAX(AA40-AA42-AA46,0)+IF(Premissas!$B$8=0,0,MAX(AA41-AA44-(IF(Premissas!$B$8>0,MAX(AA42-AA40,0)*Premissas!$B$8,0)),0)/Premissas!$B$8)) -> 36748.39 | AB51: =MIN(AB50,MAX(AB40-AB42-AB46,0)+IF(Premissas!$B$8=0,0,MAX(AB41-AB44-(IF(Premissas!$B$8>0,MAX(AB42-AB40,0),0))*Premissas!$B$8,0)/Premissas!$B$8)) -> 130905.12 | AC51: =MIN(AC50,MAX(AC40-AC42-AC46,0)+IF(Premissas!$B$8=0,0,MAX(AC41-AC44-(IF(Premissas!$B$8>0,MAX(AC42-AC40,0),0))*Premissas!$B$8,0)/Premissas!$B$8)) -> 0 | AD51: =MIN(AD50,MAX(AD40-AD42-AD46,0)+IF(Premissas!$B$8=0,0,MAX(AD41-AD44-(IF(Premissas!$B$8>0,MAX(AD42-AD40,0),0))*Premissas!$B$8,0)/Premissas!$B$8)) -> 0 | AE51: =MIN(AE50,MAX(AE40-AE42-AE46,0)+IF(Premissas!$B$8=0,0,MAX(AE41-AE44-(IF(Premissas!$B$8>0,MAX(AE42-AE40,0),0))*Premissas!$B$8,0)/Premissas!$B$8)) -> 0 | AF51: =MIN(AF50,MAX(AF40-AF42-AF46,0)+IF(Premissas!$B$8=0,0,MAX(AF41-AF44-(IF(Premissas!$B$8>0,MAX(AF42-AF40,0),0))*Premissas!$B$8,0)/Premissas!$B$8)) -> 0 | AG51: =MIN(AG50,MAX(AG40-AG42-AG46,0)+IF(Premissas!$B$8=0,0,MAX(AG41-AG44-(IF(Premissas!$B$8>0,MAX(AG42-AG40,0),0))*Premissas!$B$8,0)/Premissas!$B$8)) -> 0 | AH51: =MIN(AH50,MAX(AH40-AH42-AH46,0)+IF(Premissas!$B$8=0,0,MAX(AH41-AH44-(IF(Premissas!$B$8>0,MAX(AH42-AH40,0),0))*Premissas!$B$8,0)/Premissas!$B$8)) -> 0 | AI51: =MIN(AI50,MAX(AI40-AI42-AI46,0)+IF(Premissas!$B$8=0,0,MAX(AI41-AI44-(IF(Premissas!$B$8>0,MAX(AI42-AI40,0),0))*Premissas!$B$8,0)/Premissas!$B$8)) -> 0 | ... BK51: =MIN(BK50,MAX(BK40-BK42-BK46,0)+IF(Premissas!$B$8=0,0,MAX(BK41-BK44-(IF(Premissas!$B$8>0,MAX(BK42-BK40,0),0))*Premissas!$B$8,0)/Premissas!$B$8)) -> 49619.928
A52: Banco fim mês SEM Helexia (kWh) — gen+BAT, no CS3 | B52: =AA52 -> 130905.12 | C52: — | D52: =MAX(D50-D51,0)+D46+MAX(D42-D40,0) -> 0 | E52: =MAX(E50-E51,0)+E46+MAX(E42-E40,0) -> 0 | F52: =MAX(F50-F51,0)+F46+MAX(F42-F40,0) -> 0 | G52: =MAX(G50-G51,0)+G46+MAX(G42-G40,0) -> 89620.813 | H52: =MAX(H50-H51,0)+H46+MAX(H42-H40,0) -> 182787.21 | I52: =MAX(I50-I51,0)+I46+MAX(I42-I40,0) -> 290506.46 | J52: =MAX(J50-J51,0)+J46+MAX(J42-J40,0) -> 406244.64 | K52: =MAX(K50-K51,0)+K46+MAX(K42-K40,0) -> 472660.24 | ... BK52: =MAX(BK50-BK51,0)+BK46+MAX(BK42-BK40,0) -> 37933.466
A53: =" Custo SEM Helexia (R$) — só gen própria, sem "&INDEX(PVSYST_Helexia!$A$5:$A$7,MATCH(Premissas!$B$13,PVSYST_Helexia!$B$5:$B$7,0))&"/BAT/banco" -> Custo SEM Helexia (R$) — só gen própria, sem HCS03/BAT/banco | B53: =SUM(D53:BQ53) -> 2180962 | C53: =B53/60 -> 36349.366 | D53: =IF(D52>0,0,MAX(D40-D42-D46-D50,0)*Premissas!$B$5*(1+Premissas!$B$126)*(1+Premissas!$B$124)^0+MAX(D41-D44-(IF(Premissas!$B$8>0,MAX(D42+D46+D50-D40,0)*Premissas!$B$8,0)),0)*Premissas!$B$6*(1+Premissas!$B$126)*(1+Premissas!$B$124)^0) -> 141455.38 | E53: =IF(E52>0,0,MAX(E40-E42-E46-E50,0)*Premissas!$B$5*(1+Premissas!$B$126)*(1+Premissas!$B$124)^0+MAX(E41-E44-(IF(Premissas!$B$8>0,MAX(E42+E46+E50-E40,0)*Premissas!$B$8,0)),0)*Premissas!$B$6*(1+Premissas!$B$126)*(1+Premissas!$B$124)^0) -> 184269.46 | F53: =IF(F52>0,0,MAX(F40-F42-F46-F50,0)*Premissas!$B$5*(1+Premissas!$B$126)*(1+Premissas!$B$124)^0+MAX(F41-F44-(IF(Premissas!$B$8>0,MAX(F42+F46+F50-F40,0)*Premissas!$B$8,0)),0)*Premissas!$B$6*(1+Premissas!$B$126)*(1+Premissas!$B$124)^0) -> 85734.534 | G53: =IF(G52>0,0,MAX(G40-G42-G46-G50,0)*Premissas!$B$5*(1+Premissas!$B$126)*(1+Premissas!$B$124)^0+MAX(G41-G44-(IF(Premissas!$B$8>0,MAX(G42+G46+G50-G40,0)*Premissas!$B$8,0)),0)*Premissas!$B$6*(1+Premissas!$B$126)*(1+Premissas!$B$124)^0) -> 0 | H53: =IF(H52>0,0,MAX(H40-H42-H46-H50,0)*Premissas!$B$5*(1+Premissas!$B$126)*(1+Premissas!$B$124)^0+MAX(H41-H44-(IF(Premissas!$B$8>0,MAX(H42+H46+H50-H40,0)*Premissas!$B$8,0)),0)*Premissas!$B$6*(1+Premissas!$B$126)*(1+Premissas!$B$124)^0) -> 0 | I53: =IF(I52>0,0,MAX(I40-I42-I46-I50,0)*Premissas!$B$5*(1+Premissas!$B$126)*(1+Premissas!$B$124)^0+MAX(I41-I44-(IF(Premissas!$B$8>0,MAX(I42+I46+I50-I40,0)*Premissas!$B$8,0)),0)*Premissas!$B$6*(1+Premissas!$B$126)*(1+Premissas!$B$124)^0) -> 0 | J53: =IF(J52>0,0,MAX(J40-J42-J46-J50,0)*Premissas!$B$5*(1+Premissas!$B$126)*(1+Premissas!$B$124)^0+MAX(J41-J44-(IF(Premissas!$B$8>0,MAX(J42+J46+J50-J40,0)*Premissas!$B$8,0)),0)*Premissas!$B$6*(1+Premissas!$B$126)*(1+Premissas!$B$124)^0) -> 0 | K53: =IF(K52>0,0,MAX(K40-K42-K46-K50,0)*Premissas!$B$5*(1+Premissas!$B$126)*(1+Premissas!$B$124)^0+MAX(K41-K44-(IF(Premissas!$B$8>0,MAX(K42+K46+K50-K40,0)*Premissas!$B$8,0)),0)*Premissas!$B$6*(1+Premissas!$B$126)*(1+Premissas!$B$124)^0) -> 0 | ... O53: =IF(O52>0,0,MAX(O40-O42-O46-O50,0)*Premissas!$B$5*(1+Premissas!$B$126)*(1+Premissas!$B$124)^0+MAX(O41-O44-(IF(Premissas!$B$8>0,MAX(O42+O46+O50-O40,0)*Premissas!$B$8,0)),0)*Premissas!$B$6*(1+Premissas!$B$126)*(1+Premissas!$B$124)^0) -> 0 | P53: =IF(P52>0,0,MAX(P40-P42-P46-P50,0)*Premissas!$B$5*(1+Premissas!$B$126)*(1+Premissas!$B$124)^1+MAX(P41-P44-(IF(Premissas!$B$8>0,MAX(P42+P46+P50-P40,0)*Premissas!$B$8,0)),0)*Premissas!$B$6*(1+Premissas!$B$126)*(1+Premissas!$B$124)^1) -> 56312.291 | Q53: =IF(Q52>0,0,MAX(Q40-Q42-Q46-Q50,0)*Premissas!$B$5*(1+Premissas!$B$126)*(1+Premissas!$B$124)^1+MAX(Q41-Q44-(IF(Premissas!$B$8>0,MAX(Q42+Q46+Q50-Q40,0)*Premissas!$B$8,0)),0)*Premissas!$B$6*(1+Premissas!$B$126)*(1+Premissas!$B$124)^1) -> 201538.49 | R53: =IF(R52>0,0,MAX(R40-R42-R46-R50,0)*Premissas!$B$5*(1+Premissas!$B$126)*(1+Premissas!$B$124)^1+MAX(R41-R44-(IF(Premissas!$B$8>0,MAX(R42+R46+R50-R40,0)*Premissas!$B$8,0)),0)*Premissas!$B$6*(1+Premissas!$B$126)*(1+Premissas!$B$124)^1) -> 94551.733 | S53: =IF(S52>0,0,MAX(S40-S42-S46-S50,0)*Premissas!$B$5*(1+Premissas!$B$126)*(1+Premissas!$B$124)^1+MAX(S41-S44-(IF(Premissas!$B$8>0,MAX(S42+S46+S50-S40,0)*Premissas!$B$8,0)),0)*Premissas!$B$6*(1+Premissas!$B$126)*(1+Premissas!$B$124)^1) -> 0 | T53: =IF(T52>0,0,MAX(T40-T42-T46-T50,0)*Premissas!$B$5*(1+Premissas!$B$126)*(1+Premissas!$B$124)^1+MAX(T41-T44-(IF(Premissas!$B$8>0,MAX(T42+T46+T50-T40,0)*Premissas!$B$8,0)),0)*Premissas!$B$6*(1+Premissas!$B$126)*(1+Premissas!$B$124)^1) -> 0 | U53: =IF(U52>0,0,MAX(U40-U42-U46-U50,0)*Premissas!$B$5*(1+Premissas!$B$126)*(1+Premissas!$B$124)^1+MAX(U41-U44-(IF(Premissas!$B$8>0,MAX(U42+U46+U50-U40,0)*Premissas!$B$8,0)),0)*Premissas!$B$6*(1+Premissas!$B$126)*(1+Premissas!$B$124)^1) -> 0 | V53: =IF(V52>0,0,MAX(V40-V42-V46-V50,0)*Premissas!$B$5*(1+Premissas!$B$126)*(1+Premissas!$B$124)^1+MAX(V41-V44-(IF(Premissas!$B$8>0,MAX(V42+V46+V50-V40,0)*Premissas!$B$8,0)),0)*Premissas!$B$6*(1+Premissas!$B$126)*(1+Premissas!$B$124)^1) -> 0 | W53: =IF(W52>0,0,MAX(W40-W42-W46-W50,0)*Premissas!$B$5*(1+Premissas!$B$126)*(1+Premissas!$B$124)^1+MAX(W41-W44-(IF(Premissas!$B$8>0,MAX(W42+W46+W50-W40,0)*Premissas!$B$8,0)),0)*Premissas!$B$6*(1+Premissas!$B$126)*(1+Premissas!$B$124)^1) -> 0 | ... AA53: =IF(AA52>0,0,MAX(AA40-AA42-AA46-AA50,0)*Premissas!$B$5*(1+Premissas!$B$126)*(1+Premissas!$B$124)^1+MAX(AA41-AA44-(IF(Premissas!$B$8>0,MAX(AA42+AA46+AA50-AA40,0)*Premissas!$B$8,0)),0)*Premissas!$B$6*(1+Premissas!$B$126)*(1+Premissas!$B$124)^1) -> 0 | AB53: =IF(AB52>0,0,MAX(AB40-AB42-AB46-AB50,0)*Premissas!$B$5*(1+Premissas!$B$126)*(1+Premissas!$B$124)^2+MAX(AB41-AB44-(IF(Premissas!$B$8>0,MAX(AB42+AB44-AB40-AB41,0)*Premissas!$B$8,0)),0)*Premissas!$B$6*(1+Premissas!$B$126)*(1+Premissas!$B$124)^2) -> 82285.137 | AC53: =IF(AC52>0,0,MAX(AC40-AC42-AC46-AC50,0)*Premissas!$B$5*(1+Premissas!$B$126)*(1+Premissas!$B$124)^2+MAX(AC41-AC44-(IF(Premissas!$B$8>0,MAX(AC42+AC44-AC40-AC41,0)*Premissas!$B$8,0)),0)*Premissas!$B$6*(1+Premissas!$B$126)*(1+Premissas!$B$124)^2) -> 220374.03 | AD53: =IF(AD52>0,0,MAX(AD40-AD42-AD46-AD50,0)*Premissas!$B$5*(1+Premissas!$B$126)*(1+Premissas!$B$124)^2+MAX(AD41-AD44-(IF(Premissas!$B$8>0,MAX(AD42+AD44-AD40-AD41,0)*Premissas!$B$8,0)),0)*Premissas!$B$6*(1+Premissas!$B$126)*(1+Premissas!$B$124)^2) -> 104208.26 | AE53: =IF(AE52>0,0,MAX(AE40-AE42-AE46-AE50,0)*Premissas!$B$5*(1+Premissas!$B$126)*(1+Premissas!$B$124)^2+MAX(AE41-AE44-(IF(Premissas!$B$8>0,MAX(AE42+AE44-AE40-AE41,0)*Premissas!$B$8,0)),0)*Premissas!$B$6*(1+Premissas!$B$126)*(1+Premissas!$B$124)^2) -> 0 | AF53: =IF(AF52>0,0,MAX(AF40-AF42-AF46-AF50,0)*Premissas!$B$5*(1+Premissas!$B$126)*(1+Premissas!$B$124)^2+MAX(AF41-AF44-(IF(Premissas!$B$8>0,MAX(AF42+AF44-AF40-AF41,0)*Premissas!$B$8,0)),0)*Premissas!$B$6*(1+Premissas!$B$126)*(1+Premissas!$B$124)^2) -> 0 | AG53: =IF(AG52>0,0,MAX(AG40-AG42-AG46-AG50,0)*Premissas!$B$5*(1+Premissas!$B$126)*(1+Premissas!$B$124)^2+MAX(AG41-AG44-(IF(Premissas!$B$8>0,MAX(AG42+AG44-AG40-AG41,0)*Premissas!$B$8,0)),0)*Premissas!$B$6*(1+Premissas!$B$126)*(1+Premissas!$B$124)^2) -> 0 | AH53: =IF(AH52>0,0,MAX(AH40-AH42-AH46-AH50,0)*Premissas!$B$5*(1+Premissas!$B$126)*(1+Premissas!$B$124)^2+MAX(AH41-AH44-(IF(Premissas!$B$8>0,MAX(AH42+AH44-AH40-AH41,0)*Premissas!$B$8,0)),0)*Premissas!$B$6*(1+Premissas!$B$126)*(1+Premissas!$B$124)^2) -> 0 | AI53: =IF(AI52>0,0,MAX(AI40-AI42-AI46-AI50,0)*Premissas!$B$5*(1+Premissas!$B$126)*(1+Premissas!$B$124)^2+MAX(AI41-AI44-(IF(Premissas!$B$8>0,MAX(AI42+AI44-AI40-AI41,0)*Premissas!$B$8,0)),0)*Premissas!$B$6*(1+Premissas!$B$126)*(1+Premissas!$B$124)^2) -> 0 | ... AM53: =IF(AM52>0,0,MAX(AM40-AM42-AM46-AM50,0)*Premissas!$B$5*(1+Premissas!$B$126)*(1+Premissas!$B$124)^2+MAX(AM41-AM44-(IF(Premissas!$B$8>0,MAX(AM42+AM44-AM40-AM41,0)*Premissas!$B$8,0)),0)*Premissas!$B$6*(1+Premissas!$B$126)*(1+Premissas!$B$124)^2) -> 0 | AN53: =IF(AN52>0,0,MAX(AN40-AN42-AN46-AN50,0)*Premissas!$B$5*(1+Premissas!$B$126)*(1+Premissas!$B$124)^3+MAX(AN41-AN44-(IF(Premissas!$B$8>0,MAX(AN42+AN44-AN40-AN41,0)*Premissas!$B$8,0)),0)*Premissas!$B$6*(1+Premissas!$B$126)*(1+Premissas!$B$124)^3) -> 114338.82 | AO53: =IF(AO52>0,0,MAX(AO40-AO42-AO46-AO50,0)*Premissas!$B$5*(1+Premissas!$B$126)*(1+Premissas!$B$124)^3+MAX(AO41-AO44-(IF(Premissas!$B$8>0,MAX(AO42+AO44-AO40-AO41,0)*Premissas!$B$8,0)),0)*Premissas!$B$6*(1+Premissas!$B$126)*(1+Premissas!$B$124)^3) -> 240915.56 | AP53: =IF(AP52>0,0,MAX(AP40-AP42-AP46-AP50,0)*Premissas!$B$5*(1+Premissas!$B$126)*(1+Premissas!$B$124)^3+MAX(AP41-AP44-(IF(Premissas!$B$8>0,MAX(AP42+AP44-AP40-AP41,0)*Premissas!$B$8,0)),0)*Premissas!$B$6*(1+Premissas!$B$126)*(1+Premissas!$B$124)^3) -> 114780.92 | AQ53: =IF(AQ52>0,0,MAX(AQ40-AQ42-AQ46-AQ50,0)*Premissas!$B$5*(1+Premissas!$B$126)*(1+Premissas!$B$124)^3+MAX(AQ41-AQ44-(IF(Premissas!$B$8>0,MAX(AQ42+AQ44-AQ40-AQ41,0)*Premissas!$B$8,0)),0)*Premissas!$B$6*(1+Premissas!$B$126)*(1+Premissas!$B$124)^3) -> 0 | AR53: =IF(AR52>0,0,MAX(AR40-AR42-AR46-AR50,0)*Premissas!$B$5*(1+Premissas!$B$126)*(1+Premissas!$B$124)^3+MAX(AR41-AR44-(IF(Premissas!$B$8>0,MAX(AR42+AR44-AR40-AR41,0)*Premissas!$B$8,0)),0)*Premissas!$B$6*(1+Premissas!$B$126)*(1+Premissas!$B$124)^3) -> 0 | AS53: =IF(AS52>0,0,MAX(AS40-AS42-AS46-AS50,0)*Premissas!$B$5*(1+Premissas!$B$126)*(1+Premissas!$B$124)^3+MAX(AS41-AS44-(IF(Premissas!$B$8>0,MAX(AS42+AS44-AS40-AS41,0)*Premissas!$B$8,0)),0)*Premissas!$B$6*(1+Premissas!$B$126)*(1+Premissas!$B$124)^3) -> 0 | AT53: =IF(AT52>0,0,MAX(AT40-AT42-AT46-AT50,0)*Premissas!$B$5*(1+Premissas!$B$126)*(1+Premissas!$B$124)^3+MAX(AT41-AT44-(IF(Premissas!$B$8>0,MAX(AT42+AT44-AT40-AT41,0)*Premissas!$B$8,0)),0)*Premissas!$B$6*(1+Premissas!$B$126)*(1+Premissas!$B$124)^3) -> 0 | AU53: =IF(AU52>0,0,MAX(AU40-AU42-AU46-AU50,0)*Premissas!$B$5*(1+Premissas!$B$126)*(1+Premissas!$B$124)^3+MAX(AU41-AU44-(IF(Premissas!$B$8>0,MAX(AU42+AU44-AU40-AU41,0)*Premissas!$B$8,0)),0)*Premissas!$B$6*(1+Premissas!$B$126)*(1+Premissas!$B$124)^3) -> 0 | ... AY53: =IF(AY52>0,0,MAX(AY40-AY42-AY46-AY50,0)*Premissas!$B$5*(1+Premissas!$B$126)*(1+Premissas!$B$124)^3+MAX(AY41-AY44-(IF(Premissas!$B$8>0,MAX(AY42+AY44-AY40-AY41,0)*Premissas!$B$8,0)),0)*Premissas!$B$6*(1+Premissas!$B$126)*(1+Premissas!$B$124)^3) -> 0 | AZ53: =IF(AZ52>0,0,MAX(AZ40-AZ42-AZ46-AZ50,0)*Premissas!$B$5*(1+Premissas!$B$126)*(1+Premissas!$B$124)^4+MAX(AZ41-AZ44-(IF(Premissas!$B$8>0,MAX(AZ42+AZ44-AZ40-AZ41,0)*Premissas!$B$8,0)),0)*Premissas!$B$6*(1+Premissas!$B$126)*(1+Premissas!$B$124)^4) -> 150529.16 | BA53: =IF(BA52>0,0,MAX(BA40-BA42-BA46-BA50,0)*Premissas!$B$5*(1+Premissas!$B$126)*(1+Premissas!$B$124)^4+MAX(BA41-BA44-(IF(Premissas!$B$8>0,MAX(BA42+BA44-BA40-BA41,0)*Premissas!$B$8,0)),0)*Premissas!$B$6*(1+Premissas!$B$126)*(1+Premissas!$B$124)^4) -> 263314.84 | BB53: =IF(BB52>0,0,MAX(BB40-BB42-BB46-BB50,0)*Premissas!$B$5*(1+Premissas!$B$126)*(1+Premissas!$B$124)^4+MAX(BB41-BB44-(IF(Premissas!$B$8>0,MAX(BB42+BB44-BB40-BB41,0)*Premissas!$B$8,0)),0)*Premissas!$B$6*(1+Premissas!$B$126)*(1+Premissas!$B$124)^4) -> 126353.37 | BC53: =IF(BC52>0,0,MAX(BC40-BC42-BC46-BC50,0)*Premissas!$B$5*(1+Premissas!$B$126)*(1+Premissas!$B$124)^4+MAX(BC41-BC44-(IF(Premissas!$B$8>0,MAX(BC42+BC44-BC40-BC41,0)*Premissas!$B$8,0)),0)*Premissas!$B$6*(1+Premissas!$B$126)*(1+Premissas!$B$124)^4) -> 0 | BD53: =IF(BD52>0,0,MAX(BD40-BD42-BD46-BD50,0)*Premissas!$B$5*(1+Premissas!$B$126)*(1+Premissas!$B$124)^4+MAX(BD41-BD44-(IF(Premissas!$B$8>0,MAX(BD42+BD44-BD40-BD41,0)*Premissas!$B$8,0)),0)*Premissas!$B$6*(1+Premissas!$B$126)*(1+Premissas!$B$124)^4) -> 0 | BE53: =IF(BE52>0,0,MAX(BE40-BE42-BE46-BE50,0)*Premissas!$B$5*(1+Premissas!$B$126)*(1+Premissas!$B$124)^4+MAX(BE41-BE44-(IF(Premissas!$B$8>0,MAX(BE42+BE44-BE40-BE41,0)*Premissas!$B$8,0)),0)*Premissas!$B$6*(1+Premissas!$B$126)*(1+Premissas!$B$124)^4) -> 0 | BF53: =IF(BF52>0,0,MAX(BF40-BF42-BF46-BF50,0)*Premissas!$B$5*(1+Premissas!$B$126)*(1+Premissas!$B$124)^4+MAX(BF41-BF44-(IF(Premissas!$B$8>0,MAX(BF42+BF44-BF40-BF41,0)*Premissas!$B$8,0)),0)*Premissas!$B$6*(1+Premissas!$B$126)*(1+Premissas!$B$124)^4) -> 0 | BG53: =IF(BG52>0,0,MAX(BG40-BG42-BG46-BG50,0)*Premissas!$B$5*(1+Premissas!$B$126)*(1+Premissas!$B$124)^4+MAX(BG41-BG44-(IF(Premissas!$B$8>0,MAX(BG42+BG44-BG40-BG41,0)*Premissas!$B$8,0)),0)*Premissas!$B$6*(1+Premissas!$B$126)*(1+Premissas!$B$124)^4) -> 0 | ... BK53: =IF(BK52>0,0,MAX(BK40-BK42-BK46-BK50,0)*Premissas!$B$5*(1+Premissas!$B$126)*(1+Premissas!$B$124)^4+MAX(BK41-BK44-(IF(Premissas!$B$8>0,MAX(BK42+BK44-BK40-BK41,0)*Premissas!$B$8,0)),0)*Premissas!$B$6*(1+Premissas!$B$126)*(1+Premissas!$B$124)^4) -> 0
A54: Custo COM Helexia — rede remanescente (R$) | B54: =SUM(D54:BQ54) -> 1017665.8 | C54: =B54/60 -> 16961.097 | D54: =IF(D49>0,0,MAX(D40-D42-D45+D46-D47,0)*Premissas!$B$5*(1+Premissas!$B$126)*(1+Premissas!$B$124)^0+MAX(D41-D44-(IF(Premissas!$B$8>0,MAX(D42+D45+D46+D47-D40,0)*Premissas!$B$8,0)),0)*Premissas!$B$6*(1+Premissas!$B$126)*(1+Premissas!$B$124)^0) -> 141455.38 | E54: =IF(E49>0,0,MAX(E40-E42-E45+E46-E47,0)*Premissas!$B$5*(1+Premissas!$B$126)*(1+Premissas!$B$124)^0+MAX(E41-E44-(IF(Premissas!$B$8>0,MAX(E42+E45+E46+E47-E40,0)*Premissas!$B$8,0)),0)*Premissas!$B$6*(1+Premissas!$B$126)*(1+Premissas!$B$124)^0) -> 184269.46 | F54: =IF(F49>0,0,MAX(F40-F42-F45+F46-F47,0)*Premissas!$B$5*(1+Premissas!$B$126)*(1+Premissas!$B$124)^0+MAX(F41-F44-(IF(Premissas!$B$8>0,MAX(F42+F45+F46+F47-F40,0)*Premissas!$B$8,0)),0)*Premissas!$B$6*(1+Premissas!$B$126)*(1+Premissas!$B$124)^0) -> 85734.534 | G54: =IF(G49>0,0,MAX(G40-G42-G45+G46-G47,0)*Premissas!$B$5*(1+Premissas!$B$126)*(1+Premissas!$B$124)^0+MAX(G41-G44-(IF(Premissas!$B$8>0,MAX(G42+G45+G46+G47-G40,0)*Premissas!$B$8,0)),0)*Premissas!$B$6*(1+Premissas!$B$126)*(1+Premissas!$B$124)^0) -> 0 | H54: =IF(H49>0,0,MAX(H40-H42-H45+H46-H47,0)*Premissas!$B$5*(1+Premissas!$B$126)*(1+Premissas!$B$124)^0+MAX(H41-H44-(IF(Premissas!$B$8>0,MAX(H42+H45+H46+H47-H40,0)*Premissas!$B$8,0)),0)*Premissas!$B$6*(1+Premissas!$B$126)*(1+Premissas!$B$124)^0) -> 0 | I54: =IF(I49>0,0,MAX(I40-I42-I45+I46-I47,0)*Premissas!$B$5*(1+Premissas!$B$126)*(1+Premissas!$B$124)^0+MAX(I41-I44-(IF(Premissas!$B$8>0,MAX(I42+I45+I46+I47-I40,0)*Premissas!$B$8,0)),0)*Premissas!$B$6*(1+Premissas!$B$126)*(1+Premissas!$B$124)^0) -> 0 | J54: =IF(J49>0,0,MAX(J40-J42-J45+J46-J47,0)*Premissas!$B$5*(1+Premissas!$B$126)*(1+Premissas!$B$124)^0+MAX(J41-J44-(IF(Premissas!$B$8>0,MAX(J42+J45+J46+J47-J40,0)*Premissas!$B$8,0)),0)*Premissas!$B$6*(1+Premissas!$B$126)*(1+Premissas!$B$124)^0) -> 0 | K54: =IF(K49>0,0,MAX(K40-K42-K45+K46-K47,0)*Premissas!$B$5*(1+Premissas!$B$126)*(1+Premissas!$B$124)^0+MAX(K41-K44-(IF(Premissas!$B$8>0,MAX(K42+K45+K46+K47-K40,0)*Premissas!$B$8,0)),0)*Premissas!$B$6*(1+Premissas!$B$126)*(1+Premissas!$B$124)^0) -> 0 | ... O54: =IF(O49>0,0,MAX(O40-O42-O45+O46-O47,0)*Premissas!$B$5*(1+Premissas!$B$126)*(1+Premissas!$B$124)^0+MAX(O41-O44-(IF(Premissas!$B$8>0,MAX(O42+O45+O46+O47-O40,0)*Premissas!$B$8,0)),0)*Premissas!$B$6*(1+Premissas!$B$126)*(1+Premissas!$B$124)^0) -> 0 | P54: =IF(P49>0,0,MAX(P40-P42-P45+P46-P47,0)*Premissas!$B$5*(1+Premissas!$B$126)*(1+Premissas!$B$124)^1+MAX(P41-P44-(IF(Premissas!$B$8>0,MAX(P42+P45+P46+P47-P40,0)*Premissas!$B$8,0)),0)*Premissas!$B$6*(1+Premissas!$B$126)*(1+Premissas!$B$124)^1) -> 129586.67 | Q54: =IF(Q49>0,0,MAX(Q40-Q42-Q45+Q46-Q47,0)*Premissas!$B$5*(1+Premissas!$B$126)*(1+Premissas!$B$124)^1+MAX(Q41-Q44-(IF(Premissas!$B$8>0,MAX(Q42+Q45+Q46+Q47-Q40,0)*Premissas!$B$8,0)),0)*Premissas!$B$6*(1+Premissas!$B$126)*(1+Premissas!$B$124)^1) -> 201204.56 | R54: =IF(R49>0,0,MAX(R40-R42-R45+R46-R47,0)*Premissas!$B$5*(1+Premissas!$B$126)*(1+Premissas!$B$124)^1+MAX(R41-R44-(IF(Premissas!$B$8>0,MAX(R42+R45+R46+R47-R40,0)*Premissas!$B$8,0)),0)*Premissas!$B$6*(1+Premissas!$B$126)*(1+Premissas!$B$124)^1) -> 94150.865 | S54: =IF(S49>0,0,MAX(S40-S42-S45+S46-S47,0)*Premissas!$B$5*(1+Premissas!$B$126)*(1+Premissas!$B$124)^1+MAX(S41-S44-(IF(Premissas!$B$8>0,MAX(S42+S45+S46+S47-S40,0)*Premissas!$B$8,0)),0)*Premissas!$B$6*(1+Premissas!$B$126)*(1+Premissas!$B$124)^1) -> 0 | T54: =IF(T49>0,0,MAX(T40-T42-T45+T46-T47,0)*Premissas!$B$5*(1+Premissas!$B$126)*(1+Premissas!$B$124)^1+MAX(T41-T44-(IF(Premissas!$B$8>0,MAX(T42+T45+T46+T47-T40,0)*Premissas!$B$8,0)),0)*Premissas!$B$6*(1+Premissas!$B$126)*(1+Premissas!$B$124)^1) -> 0 | U54: =IF(U49>0,0,MAX(U40-U42-U45+U46-U47,0)*Premissas!$B$5*(1+Premissas!$B$126)*(1+Premissas!$B$124)^1+MAX(U41-U44-(IF(Premissas!$B$8>0,MAX(U42+U45+U46+U47-U40,0)*Premissas!$B$8,0)),0)*Premissas!$B$6*(1+Premissas!$B$126)*(1+Premissas!$B$124)^1) -> 0 | V54: =IF(V49>0,0,MAX(V40-V42-V45+V46-V47,0)*Premissas!$B$5*(1+Premissas!$B$126)*(1+Premissas!$B$124)^1+MAX(V41-V44-(IF(Premissas!$B$8>0,MAX(V42+V45+V46+V47-V40,0)*Premissas!$B$8,0)),0)*Premissas!$B$6*(1+Premissas!$B$126)*(1+Premissas!$B$124)^1) -> 0 | W54: =IF(W49>0,0,MAX(W40-W42-W45+W46-W47,0)*Premissas!$B$5*(1+Premissas!$B$126)*(1+Premissas!$B$124)^1+MAX(W41-W44-(IF(Premissas!$B$8>0,MAX(W42+W45+W46+W47-W40,0)*Premissas!$B$8,0)),0)*Premissas!$B$6*(1+Premissas!$B$126)*(1+Premissas!$B$124)^1) -> 0 | ... AA54: =IF(AA49>0,0,MAX(AA40-AA42-AA45+AA46-AA47,0)*Premissas!$B$5*(1+Premissas!$B$126)*(1+Premissas!$B$124)^1+MAX(AA41-AA44-(IF(Premissas!$B$8>0,MAX(AA42+AA45+AA46+AA47-AA40,0)*Premissas!$B$8,0)),0)*Premissas!$B$6*(1+Premissas!$B$126)*(1+Premissas!$B$124)^1) -> 0 | AB54: =IF(AB49>0,0,MAX(AB40-AB42-AB45+AB46-AB47,0)*Premissas!$B$5*(1+Premissas!$B$126)*(1+Premissas!$B$124)^2+MAX(AB41-AB44-(IF(Premissas!$B$8>0,MAX(AB42+AB44-AB40-AB41,0)*Premissas!$B$8,0)),0)*Premissas!$B$6*(1+Premissas!$B$126)*(1+Premissas!$B$124)^2) -> 0 | AC54: =IF(AC49>0,0,MAX(AC40-AC42-AC45+AC46-AC47,0)*Premissas!$B$5*(1+Premissas!$B$126)*(1+Premissas!$B$124)^2+MAX(AC41-AC44-(IF(Premissas!$B$8>0,MAX(AC42+AC44-AC40-AC41,0)*Premissas!$B$8,0)),0)*Premissas!$B$6*(1+Premissas!$B$126)*(1+Premissas!$B$124)^2) -> 115571.7 | AD54: =IF(AD49>0,0,MAX(AD40-AD42-AD45+AD46-AD47,0)*Premissas!$B$5*(1+Premissas!$B$126)*(1+Premissas!$B$124)^2+MAX(AD41-AD44-(IF(Premissas!$B$8>0,MAX(AD42+AD44-AD40-AD41,0)*Premissas!$B$8,0)),0)*Premissas!$B$6*(1+Premissas!$B$126)*(1+Premissas!$B$124)^2) -> 65692.673 | AE54: =IF(AE49>0,0,MAX(AE40-AE42-AE45+AE46-AE47,0)*Premissas!$B$5*(1+Premissas!$B$126)*(1+Premissas!$B$124)^2+MAX(AE41-AE44-(IF(Premissas!$B$8>0,MAX(AE42+AE44-AE40-AE41,0)*Premissas!$B$8,0)),0)*Premissas!$B$6*(1+Premissas!$B$126)*(1+Premissas!$B$124)^2) -> 0 | AF54: =IF(AF49>0,0,MAX(AF40-AF42-AF45+AF46-AF47,0)*Premissas!$B$5*(1+Premissas!$B$126)*(1+Premissas!$B$124)^2+MAX(AF41-AF44-(IF(Premissas!$B$8>0,MAX(AF42+AF44-AF40-AF41,0)*Premissas!$B$8,0)),0)*Premissas!$B$6*(1+Premissas!$B$126)*(1+Premissas!$B$124)^2) -> 0 | AG54: =IF(AG49>0,0,MAX(AG40-AG42-AG45+AG46-AG47,0)*Premissas!$B$5*(1+Premissas!$B$126)*(1+Premissas!$B$124)^2+MAX(AG41-AG44-(IF(Premissas!$B$8>0,MAX(AG42+AG44-AG40-AG41,0)*Premissas!$B$8,0)),0)*Premissas!$B$6*(1+Premissas!$B$126)*(1+Premissas!$B$124)^2) -> 0 | AH54: =IF(AH49>0,0,MAX(AH40-AH42-AH45+AH46-AH47,0)*Premissas!$B$5*(1+Premissas!$B$126)*(1+Premissas!$B$124)^2+MAX(AH41-AH44-(IF(Premissas!$B$8>0,MAX(AH42+AH44-AH40-AH41,0)*Premissas!$B$8,0)),0)*Premissas!$B$6*(1+Premissas!$B$126)*(1+Premissas!$B$124)^2) -> 0 | AI54: =IF(AI49>0,0,MAX(AI40-AI42-AI45+AI46-AI47,0)*Premissas!$B$5*(1+Premissas!$B$126)*(1+Premissas!$B$124)^2+MAX(AI41-AI44-(IF(Premissas!$B$8>0,MAX(AI42+AI44-AI40-AI41,0)*Premissas!$B$8,0)),0)*Premissas!$B$6*(1+Premissas!$B$126)*(1+Premissas!$B$124)^2) -> 0 | ... AM54: =IF(AM49>0,0,MAX(AM40-AM42-AM45+AM46-AM47,0)*Premissas!$B$5*(1+Premissas!$B$126)*(1+Premissas!$B$124)^2+MAX(AM41-AM44-(IF(Premissas!$B$8>0,MAX(AM42+AM44-AM40-AM41,0)*Premissas!$B$8,0)),0)*Premissas!$B$6*(1+Premissas!$B$126)*(1+Premissas!$B$124)^2) -> 0 | AN54: =IF(AN49>0,0,MAX(AN40-AN42-AN45+AN46-AN47,0)*Premissas!$B$5*(1+Premissas!$B$126)*(1+Premissas!$B$124)^3+MAX(AN41-AN44-(IF(Premissas!$B$8>0,MAX(AN42+AN44-AN40-AN41,0)*Premissas!$B$8,0)),0)*Premissas!$B$6*(1+Premissas!$B$126)*(1+Premissas!$B$124)^3) -> 0 | AO54: =IF(AO49>0,0,MAX(AO40-AO42-AO45+AO46-AO47,0)*Premissas!$B$5*(1+Premissas!$B$126)*(1+Premissas!$B$124)^3+MAX(AO41-AO44-(IF(Premissas!$B$8>0,MAX(AO42+AO44-AO40-AO41,0)*Premissas!$B$8,0)),0)*Premissas!$B$6*(1+Premissas!$B$126)*(1+Premissas!$B$124)^3) -> 0 | AP54: =IF(AP49>0,0,MAX(AP40-AP42-AP45+AP46-AP47,0)*Premissas!$B$5*(1+Premissas!$B$126)*(1+Premissas!$B$124)^3+MAX(AP41-AP44-(IF(Premissas!$B$8>0,MAX(AP42+AP44-AP40-AP41,0)*Premissas!$B$8,0)),0)*Premissas!$B$6*(1+Premissas!$B$126)*(1+Premissas!$B$124)^3) -> 0 | AQ54: =IF(AQ49>0,0,MAX(AQ40-AQ42-AQ45+AQ46-AQ47,0)*Premissas!$B$5*(1+Premissas!$B$126)*(1+Premissas!$B$124)^3+MAX(AQ41-AQ44-(IF(Premissas!$B$8>0,MAX(AQ42+AQ44-AQ40-AQ41,0)*Premissas!$B$8,0)),0)*Premissas!$B$6*(1+Premissas!$B$126)*(1+Premissas!$B$124)^3) -> 0 | AR54: =IF(AR49>0,0,MAX(AR40-AR42-AR45+AR46-AR47,0)*Premissas!$B$5*(1+Premissas!$B$126)*(1+Premissas!$B$124)^3+MAX(AR41-AR44-(IF(Premissas!$B$8>0,MAX(AR42+AR44-AR40-AR41,0)*Premissas!$B$8,0)),0)*Premissas!$B$6*(1+Premissas!$B$126)*(1+Premissas!$B$124)^3) -> 0 | AS54: =IF(AS49>0,0,MAX(AS40-AS42-AS45+AS46-AS47,0)*Premissas!$B$5*(1+Premissas!$B$126)*(1+Premissas!$B$124)^3+MAX(AS41-AS44-(IF(Premissas!$B$8>0,MAX(AS42+AS44-AS40-AS41,0)*Premissas!$B$8,0)),0)*Premissas!$B$6*(1+Premissas!$B$126)*(1+Premissas!$B$124)^3) -> 0 | AT54: =IF(AT49>0,0,MAX(AT40-AT42-AT45+AT46-AT47,0)*Premissas!$B$5*(1+Premissas!$B$126)*(1+Premissas!$B$124)^3+MAX(AT41-AT44-(IF(Premissas!$B$8>0,MAX(AT42+AT44-AT40-AT41,0)*Premissas!$B$8,0)),0)*Premissas!$B$6*(1+Premissas!$B$126)*(1+Premissas!$B$124)^3) -> 0 | AU54: =IF(AU49>0,0,MAX(AU40-AU42-AU45+AU46-AU47,0)*Premissas!$B$5*(1+Premissas!$B$126)*(1+Premissas!$B$124)^3+MAX(AU41-AU44-(IF(Premissas!$B$8>0,MAX(AU42+AU44-AU40-AU41,0)*Premissas!$B$8,0)),0)*Premissas!$B$6*(1+Premissas!$B$126)*(1+Premissas!$B$124)^3) -> 0 | ... AY54: =IF(AY49>0,0,MAX(AY40-AY42-AY45+AY46-AY47,0)*Premissas!$B$5*(1+Premissas!$B$126)*(1+Premissas!$B$124)^3+MAX(AY41-AY44-(IF(Premissas!$B$8>0,MAX(AY42+AY44-AY40-AY41,0)*Premissas!$B$8,0)),0)*Premissas!$B$6*(1+Premissas!$B$126)*(1+Premissas!$B$124)^3) -> 0 | AZ54: =IF(AZ49>0,0,MAX(AZ40-AZ42-AZ45+AZ46-AZ47,0)*Premissas!$B$5*(1+Premissas!$B$126)*(1+Premissas!$B$124)^4+MAX(AZ41-AZ44-(IF(Premissas!$B$8>0,MAX(AZ42+AZ44-AZ40-AZ41,0)*Premissas!$B$8,0)),0)*Premissas!$B$6*(1+Premissas!$B$126)*(1+Premissas!$B$124)^4) -> 0 | BA54: =IF(BA49>0,0,MAX(BA40-BA42-BA45+BA46-BA47,0)*Premissas!$B$5*(1+Premissas!$B$126)*(1+Premissas!$B$124)^4+MAX(BA41-BA44-(IF(Premissas!$B$8>0,MAX(BA42+BA44-BA40-BA41,0)*Premissas!$B$8,0)),0)*Premissas!$B$6*(1+Premissas!$B$126)*(1+Premissas!$B$124)^4) -> 0 | BB54: =IF(BB49>0,0,MAX(BB40-BB42-BB45+BB46-BB47,0)*Premissas!$B$5*(1+Premissas!$B$126)*(1+Premissas!$B$124)^4+MAX(BB41-BB44-(IF(Premissas!$B$8>0,MAX(BB42+BB44-BB40-BB41,0)*Premissas!$B$8,0)),0)*Premissas!$B$6*(1+Premissas!$B$126)*(1+Premissas!$B$124)^4) -> 0 | BC54: =IF(BC49>0,0,MAX(BC40-BC42-BC45+BC46-BC47,0)*Premissas!$B$5*(1+Premissas!$B$126)*(1+Premissas!$B$124)^4+MAX(BC41-BC44-(IF(Premissas!$B$8>0,MAX(BC42+BC44-BC40-BC41,0)*Premissas!$B$8,0)),0)*Premissas!$B$6*(1+Premissas!$B$126)*(1+Premissas!$B$124)^4) -> 0 | BD54: =IF(BD49>0,0,MAX(BD40-BD42-BD45+BD46-BD47,0)*Premissas!$B$5*(1+Premissas!$B$126)*(1+Premissas!$B$124)^4+MAX(BD41-BD44-(IF(Premissas!$B$8>0,MAX(BD42+BD44-BD40-BD41,0)*Premissas!$B$8,0)),0)*Premissas!$B$6*(1+Premissas!$B$126)*(1+Premissas!$B$124)^4) -> 0 | BE54: =IF(BE49>0,0,MAX(BE40-BE42-BE45+BE46-BE47,0)*Premissas!$B$5*(1+Premissas!$B$126)*(1+Premissas!$B$124)^4+MAX(BE41-BE44-(IF(Premissas!$B$8>0,MAX(BE42+BE44-BE40-BE41,0)*Premissas!$B$8,0)),0)*Premissas!$B$6*(1+Premissas!$B$126)*(1+Premissas!$B$124)^4) -> 0 | BF54: =IF(BF49>0,0,MAX(BF40-BF42-BF45+BF46-BF47,0)*Premissas!$B$5*(1+Premissas!$B$126)*(1+Premissas!$B$124)^4+MAX(BF41-BF44-(IF(Premissas!$B$8>0,MAX(BF42+BF44-BF40-BF41,0)*Premissas!$B$8,0)),0)*Premissas!$B$6*(1+Premissas!$B$126)*(1+Premissas!$B$124)^4) -> 0 | BG54: =IF(BG49>0,0,MAX(BG40-BG42-BG45+BG46-BG47,0)*Premissas!$B$5*(1+Premissas!$B$126)*(1+Premissas!$B$124)^4+MAX(BG41-BG44-(IF(Premissas!$B$8>0,MAX(BG42+BG44-BG40-BG41,0)*Premissas!$B$8,0)),0)*Premissas!$B$6*(1+Premissas!$B$126)*(1+Premissas!$B$124)^4) -> 0 | ... BK54: =IF(BK49>0,0,MAX(BK40-BK42-BK45+BK46-BK47,0)*Premissas!$B$5*(1+Premissas!$B$126)*(1+Premissas!$B$124)^4+MAX(BK41-BK44-(IF(Premissas!$B$8>0,MAX(BK42+BK44-BK40-BK41,0)*Premissas!$B$8,0)),0)*Premissas!$B$6*(1+Premissas!$B$126)*(1+Premissas!$B$124)^4) -> 0
A55: ★ Economia mensal (R$) | B55: =SUM(D55:BQ55) -> 1236570.5 | C55: =B55/60 -> 20609.509 | D55: =MAX(D53-D54,0) -> 0 | E55: =MAX(E53-E54,0) -> 0 | F55: =MAX(F53-F54,0) -> 0 | G55: =MAX(G53-G54,0) -> 0 | H55: =MAX(H53-H54,0) -> 0 | I55: =MAX(I53-I54,0) -> 0 | J55: =MAX(J53-J54,0) -> 0 | K55: =MAX(K53-K54,0) -> 0 | ... BK55: =MAX(BK53-BK54,0) -> 0
A57: AREC (B3)
A58: Consumo FP (kWh) | B58: =SUM(D58:BQ58) -> 269375.21 | C58: =B58/60 -> 4489.5869 | D58: 3657.4 | E58: 3450.6 | F58: 3408.8 | G58: 4205 | H58: 5428 | I58: 6374 | J58: 6073.1 | K58: =4121.3*(1+Premissas!$B$21) -> 4224.3325 | L58: =4332.7*(1+Premissas!$B$21) -> 4441.0175 | M58: =5075.6*(1+Premissas!$B$21) -> 5202.49 | N58: =4416*(1+Premissas!$B$21) -> 4526.4 | O58: =4080.2*(1+Premissas!$B$21) -> 4182.205 | P58: =3657.4*(1+Premissas!$B$21) -> 3748.835 | Q58: =3450.6*(1+Premissas!$B$21) -> 3536.865 | R58: =3408.8*(1+Premissas!$B$21) -> 3494.02 | S58: =4205*(1+Premissas!$B$21) -> 4310.125 | T58: =5428*(1+Premissas!$B$21) -> 5563.7 | U58: =6374*(1+Premissas!$B$21) -> 6533.35 | V58: =6073.1*(1+Premissas!$B$21) -> 6224.9275 | W58: =4121.3*(1+Premissas!$B$21) -> 4224.3325 | X58: =4332.7*(1+Premissas!$B$21) -> 4441.0175 | Y58: =5075.6*(1+Premissas!$B$21) -> 5202.49 | Z58: =4416*(1+Premissas!$B$21) -> 4526.4 | AA58: =4080.2*(1+Premissas!$B$21) -> 4182.205 | AB58: =4080.2*(1+Premissas!$B$21)^2 -> 4286.7601 | AC58: =4080.2*(1+Premissas!$B$21)^2 -> 4286.7601 | AD58: =4080.2*(1+Premissas!$B$21)^2 -> 4286.7601 | AE58: =4080.2*(1+Premissas!$B$21)^2 -> 4286.7601 | AF58: =4080.2*(1+Premissas!$B$21)^2 -> 4286.7601 | AG58: =4080.2*(1+Premissas!$B$21)^2 -> 4286.7601 | AH58: =4080.2*(1+Premissas!$B$21)^2 -> 4286.7601 | AI58: =4080.2*(1+Premissas!$B$21)^2 -> 4286.7601 | ... AM58: =4080.2*(1+Premissas!$B$21)^2 -> 4286.7601 | AN58: =4080.2*(1+Premissas!$B$21)^3 -> 4393.9291 | AO58: =4080.2*(1+Premissas!$B$21)^3 -> 4393.9291 | AP58: =4080.2*(1+Premissas!$B$21)^3 -> 4393.9291 | AQ58: =4080.2*(1+Premissas!$B$21)^3 -> 4393.9291 | AR58: =4080.2*(1+Premissas!$B$21)^3 -> 4393.9291 | AS58: =4080.2*(1+Premissas!$B$21)^3 -> 4393.9291 | AT58: =4080.2*(1+Premissas!$B$21)^3 -> 4393.9291 | AU58: =4080.2*(1+Premissas!$B$21)^3 -> 4393.9291 | ... AY58: =4080.2*(1+Premissas!$B$21)^3 -> 4393.9291 | AZ58: =4080.2*(1+Premissas!$B$21)^4 -> 4503.7774 | BA58: =4080.2*(1+Premissas!$B$21)^4 -> 4503.7774 | BB58: =4080.2*(1+Premissas!$B$21)^4 -> 4503.7774 | BC58: =4080.2*(1+Premissas!$B$21)^4 -> 4503.7774 | BD58: =4080.2*(1+Premissas!$B$21)^4 -> 4503.7774 | BE58: =4080.2*(1+Premissas!$B$21)^4 -> 4503.7774 | BF58: =4080.2*(1+Premissas!$B$21)^4 -> 4503.7774 | BG58: =4080.2*(1+Premissas!$B$21)^4 -> 4503.7774 | ... BK58: =4080.2*(1+Premissas!$B$21)^4 -> 4503.7774
A59: =" "&INDEX(PVSYST_Helexia!$A$5:$A$7,MATCH(Premissas!$B$13,PVSYST_Helexia!$B$5:$B$7,0))&" créditos recebidos (kWh)" -> HCS03 créditos recebidos (kWh) | B59: =SUM(D59:BQ59) -> 269692.61 | C59: =B59/60 -> 4494.8769 | D59: =D6*Premissas!$B$36 -> 3347.73 | E59: =E6*Premissas!$B$36 -> 3523.77 | F59: =F6*Premissas!$B$36 -> 4230.09 | G59: =G6*Premissas!$B$36 -> 3969.27 | H59: =H6*Premissas!$C$36 -> 8037.456 | I59: =I6*Premissas!$C$36 -> 7771.456 | J59: =J6*Premissas!$C$36 -> 7379.372 | K59: =K6*Premissas!$C$36 -> 7576.9728 | L59: =L6*Premissas!$C$36 -> 6751.7317 | M59: =M6*Premissas!$C$36 -> 7744.2442 | N59: =N6*Premissas!$D$36 -> 4517.2781 | O59: =O6*Premissas!$D$36 -> 4227.6376 | P59: =P6*Premissas!$D$36 -> 3836.8086 | Q59: =Q6*Premissas!$D$36 -> 4038.5667 | R59: =R6*Premissas!$D$36 -> 4848.0748 | S59: =S6*Premissas!$D$36 -> 4549.1509 | T59: =T6*Premissas!$E$36 -> 10131.878 | U59: =U6*Premissas!$E$36 -> 9796.563 | V59: =V6*Premissas!$E$36 -> 9302.3087 | W59: =W6*Premissas!$E$36 -> 9599.3978 | X59: =X6*Premissas!$E$36 -> 8553.8857 | Y59: =Y6*Premissas!$E$36 -> 9811.3169 | Z59: =Z6*Premissas!$E$36 -> 9789.8567 | AA59: =AA6*Premissas!$E$36 -> 9162.1471 | AB59: =AB6*Premissas!$F$36 -> 1914.9499 | AC59: =AC6*Premissas!$F$36 -> 2015.6473 | AD59: =AD6*Premissas!$F$36 -> 2419.6726 | AE59: =AE6*Premissas!$F$36 -> 2270.4798 | AF59: =AF6*Premissas!$F$36 -> 2333.3384 | AG59: =AG6*Premissas!$F$36 -> 2256.1165 | AH59: =AH6*Premissas!$G$36 -> 2348.2809 | AI59: =AI6*Premissas!$G$36 -> 2423.2783 | AJ59: =AJ6*Premissas!$G$36 -> 2159.3485 | AK59: =AK6*Premissas!$G$36 -> 2476.7752 | AL59: =AL6*Premissas!$G$36 -> 2471.3578 | AM59: =AM6*Premissas!$G$36 -> 2312.8984 | AN59: =AN6*Premissas!$H$36 -> 1954.2309 | AO59: =AO6*Premissas!$H$36 -> 2056.994 | AP59: =AP6*Premissas!$H$36 -> 2469.3069 | AQ59: =AQ6*Premissas!$H$36 -> 2317.0537 | AR59: =AR6*Premissas!$H$36 -> 2381.2018 | AS59: =AS6*Premissas!$H$36 -> 2302.3958 | AT59: =AT6*Premissas!$I$36 -> 2377.5314 | AU59: =AU6*Premissas!$I$36 -> 2453.4629 | AV59: =AV6*Premissas!$I$36 -> 2186.2456 | AW59: =AW6*Premissas!$I$36 -> 2507.6263 | AX59: =AX6*Premissas!$I$36 -> 2502.1414 | AY59: =AY6*Premissas!$I$36 -> 2341.7082 | AZ59: =AZ6*Premissas!$J$36 -> 3694.4736 | BA59: =BA6*Premissas!$J$36 -> 3888.7471 | BB59: =BB6*Premissas!$J$36 -> 4668.2247 | BC59: =BC6*Premissas!$J$36 -> 4380.3901 | BD59: =BD6*Premissas!$J$36 -> 4501.662 | BE59: =BE6*Premissas!$J$36 -> 4352.6793 | BF59: =BF6*Premissas!$K$36 -> 4377.8005 | BG59: =BG6*Premissas!$K$36 -> 4517.6149 | BH59: =BH6*Premissas!$K$36 -> 4025.5818 | BI59: =BI6*Premissas!$K$36 -> 4617.3471 | BJ59: =BJ6*Premissas!$K$36 -> 4607.2476 | BK59: =BK6*Premissas!$K$36 -> 4311.8384
A60: Banco início mês COM Helexia (kWh) | B60: =AA60 -> 46665.079 | C60: — | D60: =0 -> 0 | E60: =D62 -> 0 | F60: =E62 -> 73.17 | G60: =F62 -> 894.46 | H60: =G62 -> 658.73 | I60: =H62 -> 3268.186 | J60: =I62 -> 4665.642 | K60: =J62 -> 5971.914 | L60: =K62 -> 9324.5543 | ... BK60: =BJ62 -> 819.01002
A61: Bank draw COM Helexia (kWh) | B61: =SUM(D61:BQ61) -> 51658.127 | C61: =B61/60 -> 860.96878 | D61: =MIN(D60,MAX(D58-D59,0)) -> 0 | E61: =MIN(E60,MAX(E58-E59,0)) -> 0 | F61: =MIN(F60,MAX(F58-F59,0)) -> 0 | G61: =MIN(G60,MAX(G58-G59,0)) -> 235.73 | H61: =MIN(H60,MAX(H58-H59,0)) -> 0 | I61: =MIN(I60,MAX(I58-I59,0)) -> 0 | J61: =MIN(J60,MAX(J58-J59,0)) -> 0 | K61: =MIN(K60,MAX(K58-K59,0)) -> 0 | ... BK61: =MIN(BK60,MAX(BK58-BK59,0)) -> 191.93896
A62: ★ Banco fim mês COM Helexia (kWh) | B62: =AA62 -> 51645.021 | C62: — | D62: =MAX(D60-D61,0)+MAX(D59-D58,0) -> 0 | E62: =MAX(E60-E61,0)+MAX(E59-E58,0) -> 73.17 | F62: =MAX(F60-F61,0)+MAX(F59-F58,0) -> 894.46 | G62: =MAX(G60-G61,0)+MAX(G59-G58,0) -> 658.73 | H62: =MAX(H60-H61,0)+MAX(H59-H58,0) -> 3268.186 | I62: =MAX(I60-I61,0)+MAX(I59-I58,0) -> 4665.642 | J62: =MAX(J60-J61,0)+MAX(J59-J58,0) -> 5971.914 | K62: =MAX(K60-K61,0)+MAX(K59-K58,0) -> 9324.5543 | ... BK62: =MAX(BK60-BK61,0)+MAX(BK59-BK58,0) -> 627.07106
A63: Banco início mês SEM Helexia (kWh) | B63: =AA63 -> 0 | C63: — | D63: =0 -> 0 | E63: =D65 -> 0 | F63: =E65 -> 0 | G63: =F65 -> 0 | H63: =G65 -> 0 | I63: =H65 -> 0 | J63: =I65 -> 0 | K63: =J65 -> 0 | L63: =K65 -> 0 | ... BK63: =BJ65 -> 0
A64: Bank draw SEM Helexia (kWh) | B64: =SUM(D64:BQ64) -> 0 | C64: =B64/60 -> 0 | D64: =MIN(D63,D58) -> 0 | E64: =MIN(E63,E58) -> 0 | F64: =MIN(F63,F58) -> 0 | G64: =MIN(G63,G58) -> 0 | H64: =MIN(H63,H58) -> 0 | I64: =MIN(I63,I58) -> 0 | J64: =MIN(J63,J58) -> 0 | K64: =MIN(K63,K58) -> 0 | ... BK64: =MIN(BK63,BK58) -> 0
A65: Banco fim mês SEM Helexia (kWh) | B65: =AA65 -> 0 | C65: — | D65: =MAX(D63-D64,0) -> 0 | E65: =MAX(E63-E64,0) -> 0 | F65: =MAX(F63-F64,0) -> 0 | G65: =MAX(G63-G64,0) -> 0 | H65: =MAX(H63-H64,0) -> 0 | I65: =MAX(I63-I64,0) -> 0 | J65: =MAX(J63-J64,0) -> 0 | K65: =MAX(K63-K64,0) -> 0 | ... BK65: =MAX(BK63-BK64,0) -> 0
A66: =" Custo SEM Helexia (R$) — só gen própria, sem "&INDEX(PVSYST_Helexia!$A$5:$A$7,MATCH(Premissas!$B$13,PVSYST_Helexia!$B$5:$B$7,0))&"/BAT/banco" -> Custo SEM Helexia (R$) — só gen própria, sem HCS03/BAT/banco | B66: =SUM(D66:BQ66) -> 314381.25 | C66: =B66/60 -> 5239.6876 | D66: =D58*Premissas!$F$19*(1+Premissas!$B$127)*(1+Premissas!$B$124)^0 -> 3790.4004 | E66: =E58*Premissas!$F$19*(1+Premissas!$B$127)*(1+Premissas!$B$124)^0 -> 3576.0801 | F66: =F58*Premissas!$F$19*(1+Premissas!$B$127)*(1+Premissas!$B$124)^0 -> 3532.7601 | G66: =G58*Premissas!$F$19*(1+Premissas!$B$127)*(1+Premissas!$B$124)^0 -> 4357.9137 | H66: =H58*Premissas!$F$19*(1+Premissas!$B$127)*(1+Premissas!$B$124)^0 -> 5625.3878 | I66: =I58*Premissas!$F$19*(1+Premissas!$B$127)*(1+Premissas!$B$124)^0 -> 6605.7888 | J66: =J58*Premissas!$F$19*(1+Premissas!$B$127)*(1+Premissas!$B$124)^0 -> 6293.9467 | K66: =K58*Premissas!$F$19*(1+Premissas!$B$127)*(1+Premissas!$B$124)^0 -> 4377.9492 | ... O66: =O58*Premissas!$F$19*(1+Premissas!$B$127)*(1+Premissas!$B$124)^0 -> 4334.2898 | P66: =P58*Premissas!$F$19*(1+Premissas!$B$127)*(1+Premissas!$B$124)^1 -> 4118.27 | Q66: =Q58*Premissas!$F$19*(1+Premissas!$B$127)*(1+Premissas!$B$124)^1 -> 3885.4111 | R66: =R58*Premissas!$F$19*(1+Premissas!$B$127)*(1+Premissas!$B$124)^1 -> 3838.3438 | S66: =S58*Premissas!$F$19*(1+Premissas!$B$127)*(1+Premissas!$B$124)^1 -> 4734.8732 | T66: =T58*Premissas!$F$19*(1+Premissas!$B$127)*(1+Premissas!$B$124)^1 -> 6111.9838 | U66: =U58*Premissas!$F$19*(1+Premissas!$B$127)*(1+Premissas!$B$124)^1 -> 7177.1895 | V66: =V58*Premissas!$F$19*(1+Premissas!$B$127)*(1+Premissas!$B$124)^1 -> 6838.373 | W66: =W58*Premissas!$F$19*(1+Premissas!$B$127)*(1+Premissas!$B$124)^1 -> 4640.6262 | ... AA66: =AA58*Premissas!$F$19*(1+Premissas!$B$127)*(1+Premissas!$B$124)^1 -> 4594.3471 | AB66: =AB58*Premissas!$F$19*(1+Premissas!$B$127)*(1+Premissas!$B$124)^2 -> 4991.7582 | AC66: =AC58*Premissas!$F$19*(1+Premissas!$B$127)*(1+Premissas!$B$124)^2 -> 4991.7582 | AD66: =AD58*Premissas!$F$19*(1+Premissas!$B$127)*(1+Premissas!$B$124)^2 -> 4991.7582 | AE66: =AE58*Premissas!$F$19*(1+Premissas!$B$127)*(1+Premissas!$B$124)^2 -> 4991.7582 | AF66: =AF58*Premissas!$F$19*(1+Premissas!$B$127)*(1+Premissas!$B$124)^2 -> 4991.7582 | AG66: =AG58*Premissas!$F$19*(1+Premissas!$B$127)*(1+Premissas!$B$124)^2 -> 4991.7582 | AH66: =AH58*Premissas!$F$19*(1+Premissas!$B$127)*(1+Premissas!$B$124)^2 -> 4991.7582 | AI66: =AI58*Premissas!$F$19*(1+Premissas!$B$127)*(1+Premissas!$B$124)^2 -> 4991.7582 | ... AM66: =AM58*Premissas!$F$19*(1+Premissas!$B$127)*(1+Premissas!$B$124)^2 -> 4991.7582 | AN66: =AN58*Premissas!$F$19*(1+Premissas!$B$127)*(1+Premissas!$B$124)^3 -> 5423.5453 | AO66: =AO58*Premissas!$F$19*(1+Premissas!$B$127)*(1+Premissas!$B$124)^3 -> 5423.5453 | AP66: =AP58*Premissas!$F$19*(1+Premissas!$B$127)*(1+Premissas!$B$124)^3 -> 5423.5453 | AQ66: =AQ58*Premissas!$F$19*(1+Premissas!$B$127)*(1+Premissas!$B$124)^3 -> 5423.5453 | AR66: =AR58*Premissas!$F$19*(1+Premissas!$B$127)*(1+Premissas!$B$124)^3 -> 5423.5453 | AS66: =AS58*Premissas!$F$19*(1+Premissas!$B$127)*(1+Premissas!$B$124)^3 -> 5423.5453 | AT66: =AT58*Premissas!$F$19*(1+Premissas!$B$127)*(1+Premissas!$B$124)^3 -> 5423.5453 | AU66: =AU58*Premissas!$F$19*(1+Premissas!$B$127)*(1+Premissas!$B$124)^3 -> 5423.5453 | ... AY66: =AY58*Premissas!$F$19*(1+Premissas!$B$127)*(1+Premissas!$B$124)^3 -> 5423.5453 | AZ66: =AZ58*Premissas!$F$19*(1+Premissas!$B$127)*(1+Premissas!$B$124)^4 -> 5892.6819 | BA66: =BA58*Premissas!$F$19*(1+Premissas!$B$127)*(1+Premissas!$B$124)^4 -> 5892.6819 | BB66: =BB58*Premissas!$F$19*(1+Premissas!$B$127)*(1+Premissas!$B$124)^4 -> 5892.6819 | BC66: =BC58*Premissas!$F$19*(1+Premissas!$B$127)*(1+Premissas!$B$124)^4 -> 5892.6819 | BD66: =BD58*Premissas!$F$19*(1+Premissas!$B$127)*(1+Premissas!$B$124)^4 -> 5892.6819 | BE66: =BE58*Premissas!$F$19*(1+Premissas!$B$127)*(1+Premissas!$B$124)^4 -> 5892.6819 | BF66: =BF58*Premissas!$F$19*(1+Premissas!$B$127)*(1+Premissas!$B$124)^4 -> 5892.6819 | BG66: =BG58*Premissas!$F$19*(1+Premissas!$B$127)*(1+Premissas!$B$124)^4 -> 5892.6819 | ... BK66: =BK58*Premissas!$F$19*(1+Premissas!$B$127)*(1+Premissas!$B$124)^4 -> 5892.6819
A67: Custo COM Helexia — rede remanescente (R$) | B67: =SUM(D67:BQ67) -> 401.16383 | C67: =B67/60 -> 6.6860639 | D67: =IF(D62>0,0,MAX(D58-D59-D60,0)*Premissas!$B$7*(1+Premissas!$B$127)*(1+Premissas!$B$124)^0) -> 401.16383 | E67: =IF(E62>0,0,MAX(E58-E59-E60,0)*Premissas!$B$7*(1+Premissas!$B$127)*(1+Premissas!$B$124)^0) -> 0 | F67: =IF(F62>0,0,MAX(F58-F59-F60,0)*Premissas!$B$7*(1+Premissas!$B$127)*(1+Premissas!$B$124)^0) -> 0 | G67: =IF(G62>0,0,MAX(G58-G59-G60,0)*Premissas!$B$7*(1+Premissas!$B$127)*(1+Premissas!$B$124)^0) -> 0 | H67: =IF(H62>0,0,MAX(H58-H59-H60,0)*Premissas!$B$7*(1+Premissas!$B$127)*(1+Premissas!$B$124)^0) -> 0 | I67: =IF(I62>0,0,MAX(I58-I59-I60,0)*Premissas!$B$7*(1+Premissas!$B$127)*(1+Premissas!$B$124)^0) -> 0 | J67: =IF(J62>0,0,MAX(J58-J59-J60,0)*Premissas!$B$7*(1+Premissas!$B$127)*(1+Premissas!$B$124)^0) -> 0 | K67: =IF(K62>0,0,MAX(K58-K59-K60,0)*Premissas!$B$7*(1+Premissas!$B$127)*(1+Premissas!$B$124)^0) -> 0 | ... O67: =IF(O62>0,0,MAX(O58-O59-O60,0)*Premissas!$B$7*(1+Premissas!$B$127)*(1+Premissas!$B$124)^0) -> 0 | P67: =IF(P62>0,0,MAX(P58-P59-P60,0)*Premissas!$B$7*(1+Premissas!$B$127)*(1+Premissas!$B$124)^1) -> 0 | Q67: =IF(Q62>0,0,MAX(Q58-Q59-Q60,0)*Premissas!$B$7*(1+Premissas!$B$127)*(1+Premissas!$B$124)^1) -> 0 | R67: =IF(R62>0,0,MAX(R58-R59-R60,0)*Premissas!$B$7*(1+Premissas!$B$127)*(1+Premissas!$B$124)^1) -> 0 | S67: =IF(S62>0,0,MAX(S58-S59-S60,0)*Premissas!$B$7*(1+Premissas!$B$127)*(1+Premissas!$B$124)^1) -> 0 | T67: =IF(T62>0,0,MAX(T58-T59-T60,0)*Premissas!$B$7*(1+Premissas!$B$127)*(1+Premissas!$B$124)^1) -> 0 | U67: =IF(U62>0,0,MAX(U58-U59-U60,0)*Premissas!$B$7*(1+Premissas!$B$127)*(1+Premissas!$B$124)^1) -> 0 | V67: =IF(V62>0,0,MAX(V58-V59-V60,0)*Premissas!$B$7*(1+Premissas!$B$127)*(1+Premissas!$B$124)^1) -> 0 | W67: =IF(W62>0,0,MAX(W58-W59-W60,0)*Premissas!$B$7*(1+Premissas!$B$127)*(1+Premissas!$B$124)^1) -> 0 | ... AA67: =IF(AA62>0,0,MAX(AA58-AA59-AA60,0)*Premissas!$B$7*(1+Premissas!$B$127)*(1+Premissas!$B$124)^1) -> 0 | AB67: =IF(AB62>0,0,MAX(AB58-AB59-AB60,0)*Premissas!$B$7*(1+Premissas!$B$127)*(1+Premissas!$B$124)^2) -> 0 | AC67: =IF(AC62>0,0,MAX(AC58-AC59-AC60,0)*Premissas!$B$7*(1+Premissas!$B$127)*(1+Premissas!$B$124)^2) -> 0 | AD67: =IF(AD62>0,0,MAX(AD58-AD59-AD60,0)*Premissas!$B$7*(1+Premissas!$B$127)*(1+Premissas!$B$124)^2) -> 0 | AE67: =IF(AE62>0,0,MAX(AE58-AE59-AE60,0)*Premissas!$B$7*(1+Premissas!$B$127)*(1+Premissas!$B$124)^2) -> 0 | AF67: =IF(AF62>0,0,MAX(AF58-AF59-AF60,0)*Premissas!$B$7*(1+Premissas!$B$127)*(1+Premissas!$B$124)^2) -> 0 | AG67: =IF(AG62>0,0,MAX(AG58-AG59-AG60,0)*Premissas!$B$7*(1+Premissas!$B$127)*(1+Premissas!$B$124)^2) -> 0 | AH67: =IF(AH62>0,0,MAX(AH58-AH59-AH60,0)*Premissas!$B$7*(1+Premissas!$B$127)*(1+Premissas!$B$124)^2) -> 0 | AI67: =IF(AI62>0,0,MAX(AI58-AI59-AI60,0)*Premissas!$B$7*(1+Premissas!$B$127)*(1+Premissas!$B$124)^2) -> 0 | ... AM67: =IF(AM62>0,0,MAX(AM58-AM59-AM60,0)*Premissas!$B$7*(1+Premissas!$B$127)*(1+Premissas!$B$124)^2) -> 0 | AN67: =IF(AN62>0,0,MAX(AN58-AN59-AN60,0)*Premissas!$B$7*(1+Premissas!$B$127)*(1+Premissas!$B$124)^3) -> 0 | AO67: =IF(AO62>0,0,MAX(AO58-AO59-AO60,0)*Premissas!$B$7*(1+Premissas!$B$127)*(1+Premissas!$B$124)^3) -> 0 | AP67: =IF(AP62>0,0,MAX(AP58-AP59-AP60,0)*Premissas!$B$7*(1+Premissas!$B$127)*(1+Premissas!$B$124)^3) -> 0 | AQ67: =IF(AQ62>0,0,MAX(AQ58-AQ59-AQ60,0)*Premissas!$B$7*(1+Premissas!$B$127)*(1+Premissas!$B$124)^3) -> 0 | AR67: =IF(AR62>0,0,MAX(AR58-AR59-AR60,0)*Premissas!$B$7*(1+Premissas!$B$127)*(1+Premissas!$B$124)^3) -> 0 | AS67: =IF(AS62>0,0,MAX(AS58-AS59-AS60,0)*Premissas!$B$7*(1+Premissas!$B$127)*(1+Premissas!$B$124)^3) -> 0 | AT67: =IF(AT62>0,0,MAX(AT58-AT59-AT60,0)*Premissas!$B$7*(1+Premissas!$B$127)*(1+Premissas!$B$124)^3) -> 0 | AU67: =IF(AU62>0,0,MAX(AU58-AU59-AU60,0)*Premissas!$B$7*(1+Premissas!$B$127)*(1+Premissas!$B$124)^3) -> 0 | ... AY67: =IF(AY62>0,0,MAX(AY58-AY59-AY60,0)*Premissas!$B$7*(1+Premissas!$B$127)*(1+Premissas!$B$124)^3) -> 0 | AZ67: =IF(AZ62>0,0,MAX(AZ58-AZ59-AZ60,0)*Premissas!$B$7*(1+Premissas!$B$127)*(1+Premissas!$B$124)^4) -> 0 | BA67: =IF(BA62>0,0,MAX(BA58-BA59-BA60,0)*Premissas!$B$7*(1+Premissas!$B$127)*(1+Premissas!$B$124)^4) -> 0 | BB67: =IF(BB62>0,0,MAX(BB58-BB59-BB60,0)*Premissas!$B$7*(1+Premissas!$B$127)*(1+Premissas!$B$124)^4) -> 0 | BC67: =IF(BC62>0,0,MAX(BC58-BC59-BC60,0)*Premissas!$B$7*(1+Premissas!$B$127)*(1+Premissas!$B$124)^4) -> 0 | BD67: =IF(BD62>0,0,MAX(BD58-BD59-BD60,0)*Premissas!$B$7*(1+Premissas!$B$127)*(1+Premissas!$B$124)^4) -> 0 | BE67: =IF(BE62>0,0,MAX(BE58-BE59-BE60,0)*Premissas!$B$7*(1+Premissas!$B$127)*(1+Premissas!$B$124)^4) -> 0 | BF67: =IF(BF62>0,0,MAX(BF58-BF59-BF60,0)*Premissas!$B$7*(1+Premissas!$B$127)*(1+Premissas!$B$124)^4) -> 0 | BG67: =IF(BG62>0,0,MAX(BG58-BG59-BG60,0)*Premissas!$B$7*(1+Premissas!$B$127)*(1+Premissas!$B$124)^4) -> 0 | ... BK67: =IF(BK62>0,0,MAX(BK58-BK59-BK60,0)*Premissas!$B$7*(1+Premissas!$B$127)*(1+Premissas!$B$124)^4) -> 0
A68: ★ Economia mensal (R$) | B68: =SUM(D68:BQ68) -> 313980.09 | C68: =B68/60 -> 5233.0015 | D68: =MAX(D66-D67,0) -> 3389.2365 | E68: =MAX(E66-E67,0) -> 3576.0801 | F68: =MAX(F66-F67,0) -> 3532.7601 | G68: =MAX(G66-G67,0) -> 4357.9137 | H68: =MAX(H66-H67,0) -> 5625.3878 | I68: =MAX(I66-I67,0) -> 6605.7888 | J68: =MAX(J66-J67,0) -> 6293.9467 | K68: =MAX(K66-K67,0) -> 4377.9492 | ... BK68: =MAX(BK66-BK67,0) -> 5892.6819
A70: Banheiro Motoristas (B3)
A71: Consumo FP (kWh) | B71: =SUM(D71:BQ71) -> 28440.424 | C71: =B71/60 -> 474.00707 | D71: 450 | E71: 450 | F71: 450 | G71: 450 | H71: 450 | I71: 450 | J71: 450 | K71: =450*(1+Premissas!$B$21) -> 461.25 | L71: =450*(1+Premissas!$B$21) -> 461.25 | M71: =450*(1+Premissas!$B$21) -> 461.25 | N71: =450*(1+Premissas!$B$21) -> 461.25 | O71: =450*(1+Premissas!$B$21) -> 461.25 | P71: =450*(1+Premissas!$B$21) -> 461.25 | Q71: =450*(1+Premissas!$B$21) -> 461.25 | R71: =450*(1+Premissas!$B$21) -> 461.25 | ... AA71: =450*(1+Premissas!$B$21) -> 461.25 | AB71: =450*(1+Premissas!$B$21)^2 -> 472.78125 | AC71: =450*(1+Premissas!$B$21)^2 -> 472.78125 | AD71: =450*(1+Premissas!$B$21)^2 -> 472.78125 | AE71: =450*(1+Premissas!$B$21)^2 -> 472.78125 | AF71: =450*(1+Premissas!$B$21)^2 -> 472.78125 | AG71: =450*(1+Premissas!$B$21)^2 -> 472.78125 | AH71: =450*(1+Premissas!$B$21)^2 -> 472.78125 | AI71: =450*(1+Premissas!$B$21)^2 -> 472.78125 | ... AM71: =450*(1+Premissas!$B$21)^2 -> 472.78125 | AN71: =450*(1+Premissas!$B$21)^3 -> 484.60078 | AO71: =450*(1+Premissas!$B$21)^3 -> 484.60078 | AP71: =450*(1+Premissas!$B$21)^3 -> 484.60078 | AQ71: =450*(1+Premissas!$B$21)^3 -> 484.60078 | AR71: =450*(1+Premissas!$B$21)^3 -> 484.60078 | AS71: =450*(1+Premissas!$B$21)^3 -> 484.60078 | AT71: =450*(1+Premissas!$B$21)^3 -> 484.60078 | AU71: =450*(1+Premissas!$B$21)^3 -> 484.60078 | ... AY71: =450*(1+Premissas!$B$21)^3 -> 484.60078 | AZ71: =450*(1+Premissas!$B$21)^4 -> 496.7158 | BA71: =450*(1+Premissas!$B$21)^4 -> 496.7158 | BB71: =450*(1+Premissas!$B$21)^4 -> 496.7158 | BC71: =450*(1+Premissas!$B$21)^4 -> 496.7158 | BD71: =450*(1+Premissas!$B$21)^4 -> 496.7158 | BE71: =450*(1+Premissas!$B$21)^4 -> 496.7158 | BF71: =450*(1+Premissas!$B$21)^4 -> 496.7158 | BG71: =450*(1+Premissas!$B$21)^4 -> 496.7158 | ... BK71: =450*(1+Premissas!$B$21)^4 -> 496.7158
A72: =" "&INDEX(PVSYST_Helexia!$A$5:$A$7,MATCH(Premissas!$B$13,PVSYST_Helexia!$B$5:$B$7,0))&" créditos recebidos (kWh)" -> HCS03 créditos recebidos (kWh) | B72: =SUM(D72:BQ72) -> 28446.266 | C72: =B72/60 -> 474.10444 | D72: =D6*Premissas!$B$37 -> 409.167 | E72: =E6*Premissas!$B$37 -> 430.683 | F72: =F6*Premissas!$B$37 -> 517.011 | G72: =G6*Premissas!$B$37 -> 485.133 | H72: =H6*Premissas!$C$37 -> 755.4 | I72: =I6*Premissas!$C$37 -> 730.4 | J72: =J6*Premissas!$C$37 -> 693.55 | K72: =K6*Premissas!$C$37 -> 712.1215 | L72: =L6*Premissas!$C$37 -> 634.56125 | M72: =M6*Premissas!$C$37 -> 727.8425 | N72: =N6*Premissas!$D$37 -> 581.0004 | O72: =O6*Premissas!$D$37 -> 543.7476 | P72: =P6*Premissas!$D$37 -> 493.4802 | Q72: =Q6*Premissas!$D$37 -> 519.4298 | R72: =R6*Premissas!$D$37 -> 623.5466 | S72: =S6*Premissas!$D$37 -> 585.0998 | T72: =T6*Premissas!$E$37 -> 676.4607 | U72: =U6*Premissas!$E$37 -> 654.0732 | V72: =V6*Premissas!$E$37 -> 621.07403 | W72: =W6*Premissas!$E$37 -> 640.90935 | X72: =X6*Premissas!$E$37 -> 571.10512 | Y72: =Y6*Premissas!$E$37 -> 655.05825 | Z72: =Z6*Premissas!$E$37 -> 653.62545 | AA72: =AA6*Premissas!$E$37 -> 611.71605 | AB72: =AB6*Premissas!$F$37 -> 319.15832 | AC72: =AC6*Premissas!$F$37 -> 335.94122 | AD72: =AD6*Premissas!$F$37 -> 403.27876 | AE72: =AE6*Premissas!$F$37 -> 378.4133 | AF72: =AF6*Premissas!$F$37 -> 388.88974 | AG72: =AG6*Premissas!$F$37 -> 376.01942 | AH72: =AH6*Premissas!$G$37 -> 370.78119 | AI72: =AI6*Premissas!$G$37 -> 382.62288 | AJ72: =AJ6*Premissas!$G$37 -> 340.94976 | AK72: =AK6*Premissas!$G$37 -> 391.06978 | AL72: =AL6*Premissas!$G$37 -> 390.21439 | AM72: =AM6*Premissas!$G$37 -> 365.19448 | AN72: =AN6*Premissas!$H$37 -> 317.56253 | AO72: =AO6*Premissas!$H$37 -> 334.26152 | AP72: =AP6*Premissas!$H$37 -> 401.26237 | AQ72: =AQ6*Premissas!$H$37 -> 376.52123 | AR72: =AR6*Premissas!$H$37 -> 386.94529 | AS72: =AS6*Premissas!$H$37 -> 374.13932 | AT72: =AT6*Premissas!$I$37 -> 368.92729 | AU72: =AU6*Premissas!$I$37 -> 380.70977 | AV72: =AV6*Premissas!$I$37 -> 339.24501 | AW72: =AW6*Premissas!$I$37 -> 389.11443 | AX72: =AX6*Premissas!$I$37 -> 388.26332 | AY72: =AY6*Premissas!$I$37 -> 363.36851 | AZ72: =AZ6*Premissas!$J$37 -> 328.12759 | BA72: =BA6*Premissas!$J$37 -> 345.38214 | BB72: =BB6*Premissas!$J$37 -> 414.61206 | BC72: =BC6*Premissas!$J$37 -> 389.0478 | BD72: =BD6*Premissas!$J$37 -> 399.81866 | BE72: =BE6*Premissas!$J$37 -> 386.58665 | BF72: =BF6*Premissas!$K$37 -> 462.25223 | BG72: =BG6*Premissas!$K$37 -> 477.01524 | BH72: =BH6*Premissas!$K$37 -> 425.06143 | BI72: =BI6*Premissas!$K$37 -> 487.54596 | BJ72: =BJ6*Premissas!$K$37 -> 486.47956 | BK72: =BK6*Premissas!$K$37 -> 455.28728
A73: Banco início mês COM Helexia (kWh) | B73: =AA73 -> 3444.6298 | C73: — | D73: =0 -> 0 | E73: =D75 -> 0 | F73: =E75 -> 0 | G73: =F75 -> 67.011 | H73: =G75 -> 102.144 | I73: =H75 -> 407.544 | J73: =I75 -> 687.944 | K73: =J75 -> 931.494 | L73: =K75 -> 1182.3655 | ... BK73: =BJ75 -> 107.42076
A74: Bank draw COM Helexia (kWh) | B74: =SUM(D74:BQ74) -> 3529.1036 | C74: =B74/60 -> 58.818393 | D74: =MIN(D73,MAX(D71-D72,0)) -> 0 | E74: =MIN(E73,MAX(E71-E72,0)) -> 0 | F74: =MIN(F73,MAX(F71-F72,0)) -> 0 | G74: =MIN(G73,MAX(G71-G72,0)) -> 0 | H74: =MIN(H73,MAX(H71-H72,0)) -> 0 | I74: =MIN(I73,MAX(I71-I72,0)) -> 0 | J74: =MIN(J73,MAX(J71-J72,0)) -> 0 | K74: =MIN(K73,MAX(K71-K72,0)) -> 0 | ... BK74: =MIN(BK73,MAX(BK71-BK72,0)) -> 41.428517
A75: ★ Banco fim mês COM Helexia (kWh) | B75: =AA75 -> 3595.0958 | C75: — | D75: =MAX(D73-D74,0)+MAX(D72-D71,0) -> 0 | E75: =MAX(E73-E74,0)+MAX(E72-E71,0) -> 0 | F75: =MAX(F73-F74,0)+MAX(F72-F71,0) -> 67.011 | G75: =MAX(G73-G74,0)+MAX(G72-G71,0) -> 102.144 | H75: =MAX(H73-H74,0)+MAX(H72-H71,0) -> 407.544 | I75: =MAX(I73-I74,0)+MAX(I72-I71,0) -> 687.944 | J75: =MAX(J73-J74,0)+MAX(J72-J71,0) -> 931.494 | K75: =MAX(K73-K74,0)+MAX(K72-K71,0) -> 1182.3655 | ... BK75: =MAX(BK73-BK74,0)+MAX(BK72-BK71,0) -> 65.992243
A76: Banco início mês SEM Helexia (kWh) | B76: =AA76 -> 0 | C76: — | D76: =0 -> 0 | E76: =D78 -> 0 | F76: =E78 -> 0 | G76: =F78 -> 0 | H76: =G78 -> 0 | I76: =H78 -> 0 | J76: =I78 -> 0 | K76: =J78 -> 0 | L76: =K78 -> 0 | ... BK76: =BJ78 -> 0
A77: Bank draw SEM Helexia (kWh) | B77: =SUM(D77:BQ77) -> 0 | C77: =B77/60 -> 0 | D77: =MIN(D76,D71) -> 0 | E77: =MIN(E76,E71) -> 0 | F77: =MIN(F76,F71) -> 0 | G77: =MIN(G76,G71) -> 0 | H77: =MIN(H76,H71) -> 0 | I77: =MIN(I76,I71) -> 0 | J77: =MIN(J76,J71) -> 0 | K77: =MIN(K76,K71) -> 0 | ... BK77: =MIN(BK76,BK71) -> 0
A78: Banco fim mês SEM Helexia (kWh) | B78: =AA78 -> 0 | C78: — | D78: =MAX(D76-D77,0) -> 0 | E78: =MAX(E76-E77,0) -> 0 | F78: =MAX(F76-F77,0) -> 0 | G78: =MAX(G76-G77,0) -> 0 | H78: =MAX(H76-H77,0) -> 0 | I78: =MAX(I76-I77,0) -> 0 | J78: =MAX(J76-J77,0) -> 0 | K78: =MAX(K76-K77,0) -> 0 | ... BK78: =MAX(BK76-BK77,0) -> 0
A79: =" Custo SEM Helexia (R$) — só gen própria, sem "&INDEX(PVSYST_Helexia!$A$5:$A$7,MATCH(Premissas!$B$13,PVSYST_Helexia!$B$5:$B$7,0))&"/BAT/banco" -> Custo SEM Helexia (R$) — só gen própria, sem HCS03/BAT/banco | B79: =SUM(D79:BQ79) -> 33318.161 | C79: =B79/60 -> 555.30268 | D79: =D71*Premissas!$F$19*(1+Premissas!$B$127)*(1+Premissas!$B$124)^0 -> 466.36413 | E79: =E71*Premissas!$F$19*(1+Premissas!$B$127)*(1+Premissas!$B$124)^0 -> 466.36413 | F79: =F71*Premissas!$F$19*(1+Premissas!$B$127)*(1+Premissas!$B$124)^0 -> 466.36413 | G79: =G71*Premissas!$F$19*(1+Premissas!$B$127)*(1+Premissas!$B$124)^0 -> 466.36413 | H79: =H71*Premissas!$F$19*(1+Premissas!$B$127)*(1+Premissas!$B$124)^0 -> 466.36413 | I79: =I71*Premissas!$F$19*(1+Premissas!$B$127)*(1+Premissas!$B$124)^0 -> 466.36413 | J79: =J71*Premissas!$F$19*(1+Premissas!$B$127)*(1+Premissas!$B$124)^0 -> 466.36413 | K79: =K71*Premissas!$F$19*(1+Premissas!$B$127)*(1+Premissas!$B$124)^0 -> 478.02323 | ... O79: =O71*Premissas!$F$19*(1+Premissas!$B$127)*(1+Premissas!$B$124)^0 -> 478.02323 | P79: =P71*Premissas!$F$19*(1+Premissas!$B$127)*(1+Premissas!$B$124)^1 -> 506.70463 | Q79: =Q71*Premissas!$F$19*(1+Premissas!$B$127)*(1+Premissas!$B$124)^1 -> 506.70463 | R79: =R71*Premissas!$F$19*(1+Premissas!$B$127)*(1+Premissas!$B$124)^1 -> 506.70463 | S79: =S71*Premissas!$F$19*(1+Premissas!$B$127)*(1+Premissas!$B$124)^1 -> 506.70463 | T79: =T71*Premissas!$F$19*(1+Premissas!$B$127)*(1+Premissas!$B$124)^1 -> 506.70463 | U79: =U71*Premissas!$F$19*(1+Premissas!$B$127)*(1+Premissas!$B$124)^1 -> 506.70463 | V79: =V71*Premissas!$F$19*(1+Premissas!$B$127)*(1+Premissas!$B$124)^1 -> 506.70463 | W79: =W71*Premissas!$F$19*(1+Premissas!$B$127)*(1+Premissas!$B$124)^1 -> 506.70463 | ... AA79: =AA71*Premissas!$F$19*(1+Premissas!$B$127)*(1+Premissas!$B$124)^1 -> 506.70463 | AB79: =AB71*Premissas!$F$19*(1+Premissas!$B$127)*(1+Premissas!$B$124)^2 -> 550.53458 | AC79: =AC71*Premissas!$F$19*(1+Premissas!$B$127)*(1+Premissas!$B$124)^2 -> 550.53458 | AD79: =AD71*Premissas!$F$19*(1+Premissas!$B$127)*(1+Premissas!$B$124)^2 -> 550.53458 | AE79: =AE71*Premissas!$F$19*(1+Premissas!$B$127)*(1+Premissas!$B$124)^2 -> 550.53458 | AF79: =AF71*Premissas!$F$19*(1+Premissas!$B$127)*(1+Premissas!$B$124)^2 -> 550.53458 | AG79: =AG71*Premissas!$F$19*(1+Premissas!$B$127)*(1+Premissas!$B$124)^2 -> 550.53458 | AH79: =AH71*Premissas!$F$19*(1+Premissas!$B$127)*(1+Premissas!$B$124)^2 -> 550.53458 | AI79: =AI71*Premissas!$F$19*(1+Premissas!$B$127)*(1+Premissas!$B$124)^2 -> 550.53458 | ... AM79: =AM71*Premissas!$F$19*(1+Premissas!$B$127)*(1+Premissas!$B$124)^2 -> 550.53458 | AN79: =AN71*Premissas!$F$19*(1+Premissas!$B$127)*(1+Premissas!$B$124)^3 -> 598.15582 | AO79: =AO71*Premissas!$F$19*(1+Premissas!$B$127)*(1+Premissas!$B$124)^3 -> 598.15582 | AP79: =AP71*Premissas!$F$19*(1+Premissas!$B$127)*(1+Premissas!$B$124)^3 -> 598.15582 | AQ79: =AQ71*Premissas!$F$19*(1+Premissas!$B$127)*(1+Premissas!$B$124)^3 -> 598.15582 | AR79: =AR71*Premissas!$F$19*(1+Premissas!$B$127)*(1+Premissas!$B$124)^3 -> 598.15582 | AS79: =AS71*Premissas!$F$19*(1+Premissas!$B$127)*(1+Premissas!$B$124)^3 -> 598.15582 | AT79: =AT71*Premissas!$F$19*(1+Premissas!$B$127)*(1+Premissas!$B$124)^3 -> 598.15582 | AU79: =AU71*Premissas!$F$19*(1+Premissas!$B$127)*(1+Premissas!$B$124)^3 -> 598.15582 | ... AY79: =AY71*Premissas!$F$19*(1+Premissas!$B$127)*(1+Premissas!$B$124)^3 -> 598.15582 | AZ79: =AZ71*Premissas!$F$19*(1+Premissas!$B$127)*(1+Premissas!$B$124)^4 -> 649.8963 | BA79: =BA71*Premissas!$F$19*(1+Premissas!$B$127)*(1+Premissas!$B$124)^4 -> 649.8963 | BB79: =BB71*Premissas!$F$19*(1+Premissas!$B$127)*(1+Premissas!$B$124)^4 -> 649.8963 | BC79: =BC71*Premissas!$F$19*(1+Premissas!$B$127)*(1+Premissas!$B$124)^4 -> 649.8963 | BD79: =BD71*Premissas!$F$19*(1+Premissas!$B$127)*(1+Premissas!$B$124)^4 -> 649.8963 | BE79: =BE71*Premissas!$F$19*(1+Premissas!$B$127)*(1+Premissas!$B$124)^4 -> 649.8963 | BF79: =BF71*Premissas!$F$19*(1+Premissas!$B$127)*(1+Premissas!$B$124)^4 -> 649.8963 | BG79: =BG71*Premissas!$F$19*(1+Premissas!$B$127)*(1+Premissas!$B$124)^4 -> 649.8963 | ... BK79: =BK71*Premissas!$F$19*(1+Premissas!$B$127)*(1+Premissas!$B$124)^4 -> 649.8963
A80: Custo COM Helexia — rede remanescente (R$) | B80: =SUM(D80:BQ80) -> 77.921673 | C80: =B80/60 -> 1.2986946 | D80: =IF(D75>0,0,MAX(D71-D72-D73,0)*Premissas!$B$7*(1+Premissas!$B$127)*(1+Premissas!$B$124)^0) -> 52.897351 | E80: =IF(E75>0,0,MAX(E71-E72-E73,0)*Premissas!$B$7*(1+Premissas!$B$127)*(1+Premissas!$B$124)^0) -> 25.024322 | F80: =IF(F75>0,0,MAX(F71-F72-F73,0)*Premissas!$B$7*(1+Premissas!$B$127)*(1+Premissas!$B$124)^0) -> 0 | G80: =IF(G75>0,0,MAX(G71-G72-G73,0)*Premissas!$B$7*(1+Premissas!$B$127)*(1+Premissas!$B$124)^0) -> 0 | H80: =IF(H75>0,0,MAX(H71-H72-H73,0)*Premissas!$B$7*(1+Premissas!$B$127)*(1+Premissas!$B$124)^0) -> 0 | I80: =IF(I75>0,0,MAX(I71-I72-I73,0)*Premissas!$B$7*(1+Premissas!$B$127)*(1+Premissas!$B$124)^0) -> 0 | J80: =IF(J75>0,0,MAX(J71-J72-J73,0)*Premissas!$B$7*(1+Premissas!$B$127)*(1+Premissas!$B$124)^0) -> 0 | K80: =IF(K75>0,0,MAX(K71-K72-K73,0)*Premissas!$B$7*(1+Premissas!$B$127)*(1+Premissas!$B$124)^0) -> 0 | ... O80: =IF(O75>0,0,MAX(O71-O72-O73,0)*Premissas!$B$7*(1+Premissas!$B$127)*(1+Premissas!$B$124)^0) -> 0 | P80: =IF(P75>0,0,MAX(P71-P72-P73,0)*Premissas!$B$7*(1+Premissas!$B$127)*(1+Premissas!$B$124)^1) -> 0 | Q80: =IF(Q75>0,0,MAX(Q71-Q72-Q73,0)*Premissas!$B$7*(1+Premissas!$B$127)*(1+Premissas!$B$124)^1) -> 0 | R80: =IF(R75>0,0,MAX(R71-R72-R73,0)*Premissas!$B$7*(1+Premissas!$B$127)*(1+Premissas!$B$124)^1) -> 0 | S80: =IF(S75>0,0,MAX(S71-S72-S73,0)*Premissas!$B$7*(1+Premissas!$B$127)*(1+Premissas!$B$124)^1) -> 0 | T80: =IF(T75>0,0,MAX(T71-T72-T73,0)*Premissas!$B$7*(1+Premissas!$B$127)*(1+Premissas!$B$124)^1) -> 0 | U80: =IF(U75>0,0,MAX(U71-U72-U73,0)*Premissas!$B$7*(1+Premissas!$B$127)*(1+Premissas!$B$124)^1) -> 0 | V80: =IF(V75>0,0,MAX(V71-V72-V73,0)*Premissas!$B$7*(1+Premissas!$B$127)*(1+Premissas!$B$124)^1) -> 0 | W80: =IF(W75>0,0,MAX(W71-W72-W73,0)*Premissas!$B$7*(1+Premissas!$B$127)*(1+Premissas!$B$124)^1) -> 0 | ... AA80: =IF(AA75>0,0,MAX(AA71-AA72-AA73,0)*Premissas!$B$7*(1+Premissas!$B$127)*(1+Premissas!$B$124)^1) -> 0 | AB80: =IF(AB75>0,0,MAX(AB71-AB72-AB73,0)*Premissas!$B$7*(1+Premissas!$B$127)*(1+Premissas!$B$124)^2) -> 0 | AC80: =IF(AC75>0,0,MAX(AC71-AC72-AC73,0)*Premissas!$B$7*(1+Premissas!$B$127)*(1+Premissas!$B$124)^2) -> 0 | AD80: =IF(AD75>0,0,MAX(AD71-AD72-AD73,0)*Premissas!$B$7*(1+Premissas!$B$127)*(1+Premissas!$B$124)^2) -> 0 | AE80: =IF(AE75>0,0,MAX(AE71-AE72-AE73,0)*Premissas!$B$7*(1+Premissas!$B$127)*(1+Premissas!$B$124)^2) -> 0 | AF80: =IF(AF75>0,0,MAX(AF71-AF72-AF73,0)*Premissas!$B$7*(1+Premissas!$B$127)*(1+Premissas!$B$124)^2) -> 0 | AG80: =IF(AG75>0,0,MAX(AG71-AG72-AG73,0)*Premissas!$B$7*(1+Premissas!$B$127)*(1+Premissas!$B$124)^2) -> 0 | AH80: =IF(AH75>0,0,MAX(AH71-AH72-AH73,0)*Premissas!$B$7*(1+Premissas!$B$127)*(1+Premissas!$B$124)^2) -> 0 | AI80: =IF(AI75>0,0,MAX(AI71-AI72-AI73,0)*Premissas!$B$7*(1+Premissas!$B$127)*(1+Premissas!$B$124)^2) -> 0 | ... AM80: =IF(AM75>0,0,MAX(AM71-AM72-AM73,0)*Premissas!$B$7*(1+Premissas!$B$127)*(1+Premissas!$B$124)^2) -> 0 | AN80: =IF(AN75>0,0,MAX(AN71-AN72-AN73,0)*Premissas!$B$7*(1+Premissas!$B$127)*(1+Premissas!$B$124)^3) -> 0 | AO80: =IF(AO75>0,0,MAX(AO71-AO72-AO73,0)*Premissas!$B$7*(1+Premissas!$B$127)*(1+Premissas!$B$124)^3) -> 0 | AP80: =IF(AP75>0,0,MAX(AP71-AP72-AP73,0)*Premissas!$B$7*(1+Premissas!$B$127)*(1+Premissas!$B$124)^3) -> 0 | AQ80: =IF(AQ75>0,0,MAX(AQ71-AQ72-AQ73,0)*Premissas!$B$7*(1+Premissas!$B$127)*(1+Premissas!$B$124)^3) -> 0 | AR80: =IF(AR75>0,0,MAX(AR71-AR72-AR73,0)*Premissas!$B$7*(1+Premissas!$B$127)*(1+Premissas!$B$124)^3) -> 0 | AS80: =IF(AS75>0,0,MAX(AS71-AS72-AS73,0)*Premissas!$B$7*(1+Premissas!$B$127)*(1+Premissas!$B$124)^3) -> 0 | AT80: =IF(AT75>0,0,MAX(AT71-AT72-AT73,0)*Premissas!$B$7*(1+Premissas!$B$127)*(1+Premissas!$B$124)^3) -> 0 | AU80: =IF(AU75>0,0,MAX(AU71-AU72-AU73,0)*Premissas!$B$7*(1+Premissas!$B$127)*(1+Premissas!$B$124)^3) -> 0 | ... AY80: =IF(AY75>0,0,MAX(AY71-AY72-AY73,0)*Premissas!$B$7*(1+Premissas!$B$127)*(1+Premissas!$B$124)^3) -> 0 | AZ80: =IF(AZ75>0,0,MAX(AZ71-AZ72-AZ73,0)*Premissas!$B$7*(1+Premissas!$B$127)*(1+Premissas!$B$124)^4) -> 0 | BA80: =IF(BA75>0,0,MAX(BA71-BA72-BA73,0)*Premissas!$B$7*(1+Premissas!$B$127)*(1+Premissas!$B$124)^4) -> 0 | BB80: =IF(BB75>0,0,MAX(BB71-BB72-BB73,0)*Premissas!$B$7*(1+Premissas!$B$127)*(1+Premissas!$B$124)^4) -> 0 | BC80: =IF(BC75>0,0,MAX(BC71-BC72-BC73,0)*Premissas!$B$7*(1+Premissas!$B$127)*(1+Premissas!$B$124)^4) -> 0 | BD80: =IF(BD75>0,0,MAX(BD71-BD72-BD73,0)*Premissas!$B$7*(1+Premissas!$B$127)*(1+Premissas!$B$124)^4) -> 0 | BE80: =IF(BE75>0,0,MAX(BE71-BE72-BE73,0)*Premissas!$B$7*(1+Premissas!$B$127)*(1+Premissas!$B$124)^4) -> 0 | BF80: =IF(BF75>0,0,MAX(BF71-BF72-BF73,0)*Premissas!$B$7*(1+Premissas!$B$127)*(1+Premissas!$B$124)^4) -> 0 | BG80: =IF(BG75>0,0,MAX(BG71-BG72-BG73,0)*Premissas!$B$7*(1+Premissas!$B$127)*(1+Premissas!$B$124)^4) -> 0 | ... BK80: =IF(BK75>0,0,MAX(BK71-BK72-BK73,0)*Premissas!$B$7*(1+Premissas!$B$127)*(1+Premissas!$B$124)^4) -> 0
A81: ★ Economia mensal (R$) | B81: =SUM(D81:BQ81) -> 33240.239 | C81: =B81/60 -> 554.00399 | D81: =MAX(D79-D80,0) -> 413.46678 | E81: =MAX(E79-E80,0) -> 441.33981 | F81: =MAX(F79-F80,0) -> 466.36413 | G81: =MAX(G79-G80,0) -> 466.36413 | H81: =MAX(H79-H80,0) -> 466.36413 | I81: =MAX(I79-I80,0) -> 466.36413 | J81: =MAX(J79-J80,0) -> 466.36413 | K81: =MAX(K79-K80,0) -> 478.02323 | ... BK81: =MAX(BK79-BK80,0) -> 649.8963
A83: CTC Copasul (B3)
A84: Consumo FP (kWh) | B84: =SUM(D84:BQ84) -> 37820.511 | C84: =B84/60 -> 630.34184 | D84: 364 | E84: 293 | F84: 369 | G84: 674 | H84: 752 | I84: 769 | J84: 670 | K84: =389*(1+Premissas!$B$21) -> 398.725 | L84: =895*(1+Premissas!$B$21) -> 917.375 | M84: =944*(1+Premissas!$B$21) -> 967.6 | N84: =528*(1+Premissas!$B$21) -> 541.2 | O84: =595*(1+Premissas!$B$21) -> 609.875 | P84: =364*(1+Premissas!$B$21) -> 373.1 | Q84: =293*(1+Premissas!$B$21) -> 300.325 | R84: =369*(1+Premissas!$B$21) -> 378.225 | S84: =674*(1+Premissas!$B$21) -> 690.85 | T84: =752*(1+Premissas!$B$21) -> 770.8 | U84: =769*(1+Premissas!$B$21) -> 788.225 | V84: =670*(1+Premissas!$B$21) -> 686.75 | W84: =389*(1+Premissas!$B$21) -> 398.725 | X84: =895*(1+Premissas!$B$21) -> 917.375 | Y84: =944*(1+Premissas!$B$21) -> 967.6 | Z84: =528*(1+Premissas!$B$21) -> 541.2 | AA84: =595*(1+Premissas!$B$21) -> 609.875 | AB84: =595*(1+Premissas!$B$21)^2 -> 625.12187 | AC84: =595*(1+Premissas!$B$21)^2 -> 625.12187 | AD84: =595*(1+Premissas!$B$21)^2 -> 625.12187 | AE84: =595*(1+Premissas!$B$21)^2 -> 625.12187 | AF84: =595*(1+Premissas!$B$21)^2 -> 625.12187 | AG84: =595*(1+Premissas!$B$21)^2 -> 625.12187 | AH84: =595*(1+Premissas!$B$21)^2 -> 625.12187 | AI84: =595*(1+Premissas!$B$21)^2 -> 625.12187 | ... AM84: =595*(1+Premissas!$B$21)^2 -> 625.12187 | AN84: =595*(1+Premissas!$B$21)^3 -> 640.74992 | AO84: =595*(1+Premissas!$B$21)^3 -> 640.74992 | AP84: =595*(1+Premissas!$B$21)^3 -> 640.74992 | AQ84: =595*(1+Premissas!$B$21)^3 -> 640.74992 | AR84: =595*(1+Premissas!$B$21)^3 -> 640.74992 | AS84: =595*(1+Premissas!$B$21)^3 -> 640.74992 | AT84: =595*(1+Premissas!$B$21)^3 -> 640.74992 | AU84: =595*(1+Premissas!$B$21)^3 -> 640.74992 | ... AY84: =595*(1+Premissas!$B$21)^3 -> 640.74992 | AZ84: =595*(1+Premissas!$B$21)^4 -> 656.76867 | BA84: =595*(1+Premissas!$B$21)^4 -> 656.76867 | BB84: =595*(1+Premissas!$B$21)^4 -> 656.76867 | BC84: =595*(1+Premissas!$B$21)^4 -> 656.76867 | BD84: =595*(1+Premissas!$B$21)^4 -> 656.76867 | BE84: =595*(1+Premissas!$B$21)^4 -> 656.76867 | BF84: =595*(1+Premissas!$B$21)^4 -> 656.76867 | BG84: =595*(1+Premissas!$B$21)^4 -> 656.76867 | ... BK84: =595*(1+Premissas!$B$21)^4 -> 656.76867
A85: =" "&INDEX(PVSYST_Helexia!$A$5:$A$7,MATCH(Premissas!$B$13,PVSYST_Helexia!$B$5:$B$7,0))&" créditos recebidos (kWh)" -> HCS03 créditos recebidos (kWh) | B85: =SUM(D85:BQ85) -> 37348.971 | C85: =B85/60 -> 622.48284 | D85: =D6*Premissas!$B$38 -> 384.369 | E85: =E6*Premissas!$B$38 -> 404.581 | F85: =F6*Premissas!$B$38 -> 485.677 | G85: =G6*Premissas!$B$38 -> 455.731 | H85: =H6*Premissas!$C$38 -> 1163.316 | I85: =I6*Premissas!$C$38 -> 1124.816 | J85: =J6*Premissas!$C$38 -> 1068.067 | K85: =K6*Premissas!$C$38 -> 1096.6671 | L85: =L6*Premissas!$C$38 -> 977.22433 | M85: =M6*Premissas!$C$38 -> 1120.8774 | N85: =N6*Premissas!$D$38 -> 566.47539 | O85: =O6*Premissas!$D$38 -> 530.15391 | P85: =P6*Premissas!$D$38 -> 481.14319 | Q85: =Q6*Premissas!$D$38 -> 506.44405 | R85: =R6*Premissas!$D$38 -> 607.95793 | S85: =S6*Premissas!$D$38 -> 570.47231 | T85: =T6*Premissas!$E$38 -> 1082.3371 | U85: =U6*Premissas!$E$38 -> 1046.5171 | V85: =V6*Premissas!$E$38 -> 993.71844 | W85: =W6*Premissas!$E$38 -> 1025.455 | X85: =X6*Premissas!$E$38 -> 913.7682 | Y85: =Y6*Premissas!$E$38 -> 1048.0932 | Z85: =Z6*Premissas!$E$38 -> 1045.8007 | AA85: =AA6*Premissas!$E$38 -> 978.74568 | AB85: =AB6*Premissas!$F$38 -> 392.81024 | AC85: =AC6*Premissas!$F$38 -> 413.46612 | AD85: =AD6*Premissas!$F$38 -> 496.34309 | AE85: =AE6*Premissas!$F$38 -> 465.73944 | AF85: =AF6*Premissas!$F$38 -> 478.63353 | AG85: =AG6*Premissas!$F$38 -> 462.79313 | AH85: =AH6*Premissas!$G$38 -> 466.90965 | AI85: =AI6*Premissas!$G$38 -> 481.82141 | AJ85: =AJ6*Premissas!$G$38 -> 429.34414 | AK85: =AK6*Premissas!$G$38 -> 492.45824 | AL85: =AL6*Premissas!$G$38 -> 491.38109 | AM85: =AM6*Premissas!$G$38 -> 459.87453 | AN85: =AN6*Premissas!$H$38 -> 390.84619 | AO85: =AO6*Premissas!$H$38 -> 411.39879 | AP85: =AP6*Premissas!$H$38 -> 493.86138 | AQ85: =AQ6*Premissas!$H$38 -> 463.41074 | AR85: =AR6*Premissas!$H$38 -> 476.24036 | AS85: =AS6*Premissas!$H$38 -> 460.47916 | AT85: =AT6*Premissas!$I$38 -> 464.5751 | AU85: =AU6*Premissas!$I$38 -> 479.4123 | AV85: =AV6*Premissas!$I$38 -> 427.19742 | AW85: =AW6*Premissas!$I$38 -> 489.99594 | AX85: =AX6*Premissas!$I$38 -> 488.92418 | AY85: =AY6*Premissas!$I$38 -> 457.57516 | AZ85: =AZ6*Premissas!$J$38 -> 449.65633 | BA85: =BA6*Premissas!$J$38 -> 473.30145 | BB85: =BB6*Premissas!$J$38 -> 568.17208 | BC85: =BC6*Premissas!$J$38 -> 533.13958 | BD85: =BD6*Premissas!$J$38 -> 547.89965 | BE85: =BE6*Premissas!$J$38 -> 529.76688 | BF85: =BF6*Premissas!$K$38 -> 584.61311 | BG85: =BG6*Premissas!$K$38 -> 603.28398 | BH85: =BH6*Premissas!$K$38 -> 537.5777 | BI85: =BI6*Premissas!$K$38 -> 616.60225 | BJ85: =BJ6*Premissas!$K$38 -> 615.25356 | BK85: =BK6*Premissas!$K$38 -> 575.80451
A86: Banco início mês COM Helexia (kWh) | B86: =AA86 -> 4560.7124 | C86: — | D86: =0 -> 0 | E86: =D88 -> 20.369 | F86: =E88 -> 131.95 | G86: =F88 -> 248.627 | H86: =G88 -> 30.358 | I86: =H88 -> 441.674 | J86: =I88 -> 797.49 | K86: =J88 -> 1195.557 | L86: =K88 -> 1893.4991 | ... BK86: =BJ88 -> 0
A87: Bank draw COM Helexia (kWh) | B87: =SUM(D87:BQ87) -> 5351.5577 | C87: =B87/60 -> 89.192628 | D87: =MIN(D86,MAX(D84-D85,0)) -> 0 | E87: =MIN(E86,MAX(E84-E85,0)) -> 0 | F87: =MIN(F86,MAX(F84-F85,0)) -> 0 | G87: =MIN(G86,MAX(G84-G85,0)) -> 218.269 | H87: =MIN(H86,MAX(H84-H85,0)) -> 0 | I87: =MIN(I86,MAX(I84-I85,0)) -> 0 | J87: =MIN(J86,MAX(J84-J85,0)) -> 0 | K87: =MIN(K86,MAX(K84-K85,0)) -> 0 | ... BK87: =MIN(BK86,MAX(BK84-BK85,0)) -> 0
A88: ★ Banco fim mês COM Helexia (kWh) | B88: =AA88 -> 4929.5831 | C88: — | D88: =MAX(D86-D87,0)+MAX(D85-D84,0) -> 20.369 | E88: =MAX(E86-E87,0)+MAX(E85-E84,0) -> 131.95 | F88: =MAX(F86-F87,0)+MAX(F85-F84,0) -> 248.627 | G88: =MAX(G86-G87,0)+MAX(G85-G84,0) -> 30.358 | H88: =MAX(H86-H87,0)+MAX(H85-H84,0) -> 441.674 | I88: =MAX(I86-I87,0)+MAX(I85-I84,0) -> 797.49 | J88: =MAX(J86-J87,0)+MAX(J85-J84,0) -> 1195.557 | K88: =MAX(K86-K87,0)+MAX(K85-K84,0) -> 1893.4991 | ... BK88: =MAX(BK86-BK87,0)+MAX(BK85-BK84,0) -> 0
A89: Banco início mês SEM Helexia (kWh) | B89: =AA89 -> 0 | C89: — | D89: =0 -> 0 | E89: =D91 -> 0 | F89: =E91 -> 0 | G89: =F91 -> 0 | H89: =G91 -> 0 | I89: =H91 -> 0 | J89: =I91 -> 0 | K89: =J91 -> 0 | L89: =K91 -> 0 | ... BK89: =BJ91 -> 0
A90: Bank draw SEM Helexia (kWh) | B90: =SUM(D90:BQ90) -> 0 | C90: =B90/60 -> 0 | D90: =MIN(D89,D84) -> 0 | E90: =MIN(E89,E84) -> 0 | F90: =MIN(F89,F84) -> 0 | G90: =MIN(G89,G84) -> 0 | H90: =MIN(H89,H84) -> 0 | I90: =MIN(I89,I84) -> 0 | J90: =MIN(J89,J84) -> 0 | K90: =MIN(K89,K84) -> 0 | ... BK90: =MIN(BK89,BK84) -> 0
A91: Banco fim mês SEM Helexia (kWh) | B91: =AA91 -> 0 | C91: — | D91: =MAX(D89-D90,0) -> 0 | E91: =MAX(E89-E90,0) -> 0 | F91: =MAX(F89-F90,0) -> 0 | G91: =MAX(G89-G90,0) -> 0 | H91: =MAX(H89-H90,0) -> 0 | I91: =MAX(I89-I90,0) -> 0 | J91: =MAX(J89-J90,0) -> 0 | K91: =MAX(K89-K90,0) -> 0 | ... BK91: =MAX(BK89-BK90,0) -> 0
A92: =" Custo SEM Helexia (R$) — só gen própria, sem "&INDEX(PVSYST_Helexia!$A$5:$A$7,MATCH(Premissas!$B$13,PVSYST_Helexia!$B$5:$B$7,0))&"/BAT/banco" -> Custo SEM Helexia (R$) — só gen própria, sem HCS03/BAT/banco | B92: =SUM(D92:BQ92) -> 44284.317 | C92: =B92/60 -> 738.07195 | D92: =D84*Premissas!$F$19*(1+Premissas!$B$127)*(1+Premissas!$B$124)^0 -> 377.23676 | E92: =E84*Premissas!$F$19*(1+Premissas!$B$127)*(1+Premissas!$B$124)^0 -> 303.65487 | F92: =F84*Premissas!$F$19*(1+Premissas!$B$127)*(1+Premissas!$B$124)^0 -> 382.41859 | G92: =G84*Premissas!$F$19*(1+Premissas!$B$127)*(1+Premissas!$B$124)^0 -> 698.50983 | H92: =H84*Premissas!$F$19*(1+Premissas!$B$127)*(1+Premissas!$B$124)^0 -> 779.34628 | I92: =I84*Premissas!$F$19*(1+Premissas!$B$127)*(1+Premissas!$B$124)^0 -> 796.96448 | J92: =J84*Premissas!$F$19*(1+Premissas!$B$127)*(1+Premissas!$B$124)^0 -> 694.36437 | K92: =K84*Premissas!$F$19*(1+Premissas!$B$127)*(1+Premissas!$B$124)^0 -> 413.22453 | ... O92: =O84*Premissas!$F$19*(1+Premissas!$B$127)*(1+Premissas!$B$124)^0 -> 632.05294 | P92: =P84*Premissas!$F$19*(1+Premissas!$B$127)*(1+Premissas!$B$124)^1 -> 409.86774 | Q92: =Q84*Premissas!$F$19*(1+Premissas!$B$127)*(1+Premissas!$B$124)^1 -> 329.92101 | R92: =R84*Premissas!$F$19*(1+Premissas!$B$127)*(1+Premissas!$B$124)^1 -> 415.49779 | S92: =S84*Premissas!$F$19*(1+Premissas!$B$127)*(1+Premissas!$B$124)^1 -> 758.93093 | T92: =T84*Premissas!$F$19*(1+Premissas!$B$127)*(1+Premissas!$B$124)^1 -> 846.75973 | U92: =U84*Premissas!$F$19*(1+Premissas!$B$127)*(1+Premissas!$B$124)^1 -> 865.90191 | V92: =V84*Premissas!$F$19*(1+Premissas!$B$127)*(1+Premissas!$B$124)^1 -> 754.42689 | W92: =W84*Premissas!$F$19*(1+Premissas!$B$127)*(1+Premissas!$B$124)^1 -> 438.018 | ... AA92: =AA84*Premissas!$F$19*(1+Premissas!$B$127)*(1+Premissas!$B$124)^1 -> 669.97612 | AB92: =AB84*Premissas!$F$19*(1+Premissas!$B$127)*(1+Premissas!$B$124)^2 -> 727.92905 | AC92: =AC84*Premissas!$F$19*(1+Premissas!$B$127)*(1+Premissas!$B$124)^2 -> 727.92905 | AD92: =AD84*Premissas!$F$19*(1+Premissas!$B$127)*(1+Premissas!$B$124)^2 -> 727.92905 | AE92: =AE84*Premissas!$F$19*(1+Premissas!$B$127)*(1+Premissas!$B$124)^2 -> 727.92905 | AF92: =AF84*Premissas!$F$19*(1+Premissas!$B$127)*(1+Premissas!$B$124)^2 -> 727.92905 | AG92: =AG84*Premissas!$F$19*(1+Premissas!$B$127)*(1+Premissas!$B$124)^2 -> 727.92905 | AH92: =AH84*Premissas!$F$19*(1+Premissas!$B$127)*(1+Premissas!$B$124)^2 -> 727.92905 | AI92: =AI84*Premissas!$F$19*(1+Premissas!$B$127)*(1+Premissas!$B$124)^2 -> 727.92905 | ... AM92: =AM84*Premissas!$F$19*(1+Premissas!$B$127)*(1+Premissas!$B$124)^2 -> 727.92905 | AN92: =AN84*Premissas!$F$19*(1+Premissas!$B$127)*(1+Premissas!$B$124)^3 -> 790.89491 | AO92: =AO84*Premissas!$F$19*(1+Premissas!$B$127)*(1+Premissas!$B$124)^3 -> 790.89491 | AP92: =AP84*Premissas!$F$19*(1+Premissas!$B$127)*(1+Premissas!$B$124)^3 -> 790.89491 | AQ92: =AQ84*Premissas!$F$19*(1+Premissas!$B$127)*(1+Premissas!$B$124)^3 -> 790.89491 | AR92: =AR84*Premissas!$F$19*(1+Premissas!$B$127)*(1+Premissas!$B$124)^3 -> 790.89491 | AS92: =AS84*Premissas!$F$19*(1+Premissas!$B$127)*(1+Premissas!$B$124)^3 -> 790.89491 | AT92: =AT84*Premissas!$F$19*(1+Premissas!$B$127)*(1+Premissas!$B$124)^3 -> 790.89491 | AU92: =AU84*Premissas!$F$19*(1+Premissas!$B$127)*(1+Premissas!$B$124)^3 -> 790.89491 | ... AY92: =AY84*Premissas!$F$19*(1+Premissas!$B$127)*(1+Premissas!$B$124)^3 -> 790.89491 | AZ92: =AZ84*Premissas!$F$19*(1+Premissas!$B$127)*(1+Premissas!$B$124)^4 -> 859.30732 | BA92: =BA84*Premissas!$F$19*(1+Premissas!$B$127)*(1+Premissas!$B$124)^4 -> 859.30732 | BB92: =BB84*Premissas!$F$19*(1+Premissas!$B$127)*(1+Premissas!$B$124)^4 -> 859.30732 | BC92: =BC84*Premissas!$F$19*(1+Premissas!$B$127)*(1+Premissas!$B$124)^4 -> 859.30732 | BD92: =BD84*Premissas!$F$19*(1+Premissas!$B$127)*(1+Premissas!$B$124)^4 -> 859.30732 | BE92: =BE84*Premissas!$F$19*(1+Premissas!$B$127)*(1+Premissas!$B$124)^4 -> 859.30732 | BF92: =BF84*Premissas!$F$19*(1+Premissas!$B$127)*(1+Premissas!$B$124)^4 -> 859.30732 | BG92: =BG84*Premissas!$F$19*(1+Premissas!$B$127)*(1+Premissas!$B$124)^4 -> 859.30732 | ... BK92: =BK84*Premissas!$F$19*(1+Premissas!$B$127)*(1+Premissas!$B$124)^4 -> 859.30732
A93: Custo COM Helexia — rede remanescente (R$) | B93: =SUM(D93:BQ93) -> 771.1959 | C93: =B93/60 -> 12.853265 | D93: =IF(D88>0,0,MAX(D84-D85-D86,0)*Premissas!$B$7*(1+Premissas!$B$127)*(1+Premissas!$B$124)^0) -> 0 | E93: =IF(E88>0,0,MAX(E84-E85-E86,0)*Premissas!$B$7*(1+Premissas!$B$127)*(1+Premissas!$B$124)^0) -> 0 | F93: =IF(F88>0,0,MAX(F84-F85-F86,0)*Premissas!$B$7*(1+Premissas!$B$127)*(1+Premissas!$B$124)^0) -> 0 | G93: =IF(G88>0,0,MAX(G84-G85-G86,0)*Premissas!$B$7*(1+Premissas!$B$127)*(1+Premissas!$B$124)^0) -> 0 | H93: =IF(H88>0,0,MAX(H84-H85-H86,0)*Premissas!$B$7*(1+Premissas!$B$127)*(1+Premissas!$B$124)^0) -> 0 | I93: =IF(I88>0,0,MAX(I84-I85-I86,0)*Premissas!$B$7*(1+Premissas!$B$127)*(1+Premissas!$B$124)^0) -> 0 | J93: =IF(J88>0,0,MAX(J84-J85-J86,0)*Premissas!$B$7*(1+Premissas!$B$127)*(1+Premissas!$B$124)^0) -> 0 | K93: =IF(K88>0,0,MAX(K84-K85-K86,0)*Premissas!$B$7*(1+Premissas!$B$127)*(1+Premissas!$B$124)^0) -> 0 | ... O93: =IF(O88>0,0,MAX(O84-O85-O86,0)*Premissas!$B$7*(1+Premissas!$B$127)*(1+Premissas!$B$124)^0) -> 0 | P93: =IF(P88>0,0,MAX(P84-P85-P86,0)*Premissas!$B$7*(1+Premissas!$B$127)*(1+Premissas!$B$124)^1) -> 0 | Q93: =IF(Q88>0,0,MAX(Q84-Q85-Q86,0)*Premissas!$B$7*(1+Premissas!$B$127)*(1+Premissas!$B$124)^1) -> 0 | R93: =IF(R88>0,0,MAX(R84-R85-R86,0)*Premissas!$B$7*(1+Premissas!$B$127)*(1+Premissas!$B$124)^1) -> 0 | S93: =IF(S88>0,0,MAX(S84-S85-S86,0)*Premissas!$B$7*(1+Premissas!$B$127)*(1+Premissas!$B$124)^1) -> 0 | T93: =IF(T88>0,0,MAX(T84-T85-T86,0)*Premissas!$B$7*(1+Premissas!$B$127)*(1+Premissas!$B$124)^1) -> 0 | U93: =IF(U88>0,0,MAX(U84-U85-U86,0)*Premissas!$B$7*(1+Premissas!$B$127)*(1+Premissas!$B$124)^1) -> 0 | V93: =IF(V88>0,0,MAX(V84-V85-V86,0)*Premissas!$B$7*(1+Premissas!$B$127)*(1+Premissas!$B$124)^1) -> 0 | W93: =IF(W88>0,0,MAX(W84-W85-W86,0)*Premissas!$B$7*(1+Premissas!$B$127)*(1+Premissas!$B$124)^1) -> 0 | ... AA93: =IF(AA88>0,0,MAX(AA84-AA85-AA86,0)*Premissas!$B$7*(1+Premissas!$B$127)*(1+Premissas!$B$124)^1) -> 0 | AB93: =IF(AB88>0,0,MAX(AB84-AB85-AB86,0)*Premissas!$B$7*(1+Premissas!$B$127)*(1+Premissas!$B$124)^2) -> 0 | AC93: =IF(AC88>0,0,MAX(AC84-AC85-AC86,0)*Premissas!$B$7*(1+Premissas!$B$127)*(1+Premissas!$B$124)^2) -> 0 | AD93: =IF(AD88>0,0,MAX(AD84-AD85-AD86,0)*Premissas!$B$7*(1+Premissas!$B$127)*(1+Premissas!$B$124)^2) -> 0 | AE93: =IF(AE88>0,0,MAX(AE84-AE85-AE86,0)*Premissas!$B$7*(1+Premissas!$B$127)*(1+Premissas!$B$124)^2) -> 0 | AF93: =IF(AF88>0,0,MAX(AF84-AF85-AF86,0)*Premissas!$B$7*(1+Premissas!$B$127)*(1+Premissas!$B$124)^2) -> 0 | AG93: =IF(AG88>0,0,MAX(AG84-AG85-AG86,0)*Premissas!$B$7*(1+Premissas!$B$127)*(1+Premissas!$B$124)^2) -> 0 | AH93: =IF(AH88>0,0,MAX(AH84-AH85-AH86,0)*Premissas!$B$7*(1+Premissas!$B$127)*(1+Premissas!$B$124)^2) -> 0 | AI93: =IF(AI88>0,0,MAX(AI84-AI85-AI86,0)*Premissas!$B$7*(1+Premissas!$B$127)*(1+Premissas!$B$124)^2) -> 0 | ... AM93: =IF(AM88>0,0,MAX(AM84-AM85-AM86,0)*Premissas!$B$7*(1+Premissas!$B$127)*(1+Premissas!$B$124)^2) -> 0 | AN93: =IF(AN88>0,0,MAX(AN84-AN85-AN86,0)*Premissas!$B$7*(1+Premissas!$B$127)*(1+Premissas!$B$124)^3) -> 0 | AO93: =IF(AO88>0,0,MAX(AO84-AO85-AO86,0)*Premissas!$B$7*(1+Premissas!$B$127)*(1+Premissas!$B$124)^3) -> 0 | AP93: =IF(AP88>0,0,MAX(AP84-AP85-AP86,0)*Premissas!$B$7*(1+Premissas!$B$127)*(1+Premissas!$B$124)^3) -> 0 | AQ93: =IF(AQ88>0,0,MAX(AQ84-AQ85-AQ86,0)*Premissas!$B$7*(1+Premissas!$B$127)*(1+Premissas!$B$124)^3) -> 0 | AR93: =IF(AR88>0,0,MAX(AR84-AR85-AR86,0)*Premissas!$B$7*(1+Premissas!$B$127)*(1+Premissas!$B$124)^3) -> 0 | AS93: =IF(AS88>0,0,MAX(AS84-AS85-AS86,0)*Premissas!$B$7*(1+Premissas!$B$127)*(1+Premissas!$B$124)^3) -> 0 | AT93: =IF(AT88>0,0,MAX(AT84-AT85-AT86,0)*Premissas!$B$7*(1+Premissas!$B$127)*(1+Premissas!$B$124)^3) -> 0 | AU93: =IF(AU88>0,0,MAX(AU84-AU85-AU86,0)*Premissas!$B$7*(1+Premissas!$B$127)*(1+Premissas!$B$124)^3) -> 0 | ... AY93: =IF(AY88>0,0,MAX(AY84-AY85-AY86,0)*Premissas!$B$7*(1+Premissas!$B$127)*(1+Premissas!$B$124)^3) -> 0 | AZ93: =IF(AZ88>0,0,MAX(AZ84-AZ85-AZ86,0)*Premissas!$B$7*(1+Premissas!$B$127)*(1+Premissas!$B$124)^4) -> 0 | BA93: =IF(BA88>0,0,MAX(BA84-BA85-BA86,0)*Premissas!$B$7*(1+Premissas!$B$127)*(1+Premissas!$B$124)^4) -> 0 | BB93: =IF(BB88>0,0,MAX(BB84-BB85-BB86,0)*Premissas!$B$7*(1+Premissas!$B$127)*(1+Premissas!$B$124)^4) -> 0 | BC93: =IF(BC88>0,0,MAX(BC84-BC85-BC86,0)*Premissas!$B$7*(1+Premissas!$B$127)*(1+Premissas!$B$124)^4) -> 0 | BD93: =IF(BD88>0,0,MAX(BD84-BD85-BD86,0)*Premissas!$B$7*(1+Premissas!$B$127)*(1+Premissas!$B$124)^4) -> 0 | BE93: =IF(BE88>0,0,MAX(BE84-BE85-BE86,0)*Premissas!$B$7*(1+Premissas!$B$127)*(1+Premissas!$B$124)^4) -> 104.77423 | BF93: =IF(BF88>0,0,MAX(BF84-BF85-BF86,0)*Premissas!$B$7*(1+Premissas!$B$127)*(1+Premissas!$B$124)^4) -> 118.00921 | BG93: =IF(BG88>0,0,MAX(BG84-BG85-BG86,0)*Premissas!$B$7*(1+Premissas!$B$127)*(1+Premissas!$B$124)^4) -> 87.473318 | ... BK93: =IF(BK88>0,0,MAX(BK84-BK85-BK86,0)*Premissas!$B$7*(1+Premissas!$B$127)*(1+Premissas!$B$124)^4) -> 132.41553
