Workbook

Sheet Resumo
B1: ="SIMULAÇÃO RATEIO FIXO — "&Premissas!$B$13&" × COPASUL | Resumo Executivo" -> SIMULAÇÃO RATEIO FIXO — Cassilândia 03 × COPASUL | Resumo Executivo
B2: ="18 Unidades Consumidoras · Jun/2026–Mai/2028 · Energisa MS · Usina: "&Premissas!$B$13 -> 18 Unidades Consumidoras · Jun/2026–Mai/2028 · Energisa MS · Usina: Cassilândia 03
B4: ⚡ GERAÇÃO INJETADA | D4: 📄 PPA PAGO À HELEXIA | F4: ✅ ECONOMIA LÍQUIDA | H4: 🏦 BANCO RESIDUAL | J4: 🌟 VALOR TOTAL
B5: =Simulacao!B6/1000000 -> 3.3753139 | D5: =Simulacao!B7 -> 1493576.4 | F5: =Simulacao!B252 -> 435907.06 | H5: =Simulacao!B273*Premissas!$B$17 -> 510604.46 | J5: =Simulacao!B278 -> 776149.85
B6: 3,375 MWh injetados em 24 meses | D6: Custo total do contrato PPA | F6: Rede evitada menos PPA pago | H6: Banco total Copasul @ PPA | J6: Economia + banco ATRIBUÍVEL a Helexia
B8: A. CUSTO COPASUL — ANÁLISE 24 MESES | I8: B. INDICADORES-CHAVE
B9: COMPONENTE | E9: R$ | F9: % | G9: R$/mês | I9: Usina contratada | K9: =Premissas!$B$13 -> Cassilândia 03
B10: Custo SEM Helexia — baseline 24m | E10: =Simulacao!B249 -> 2015923 | F10: =Simulacao!B249/Simulacao!B249 -> 1 | G10: =(Simulacao!B249)/24 -> 83996.79 | I10: Período do contrato | K10: Jun/2026 – Mai/2028 (24 meses)
B11: Custo rede remanescente (COM Helexia) | E11: =Simulacao!B250 -> 86439.528 | F11: =Simulacao!B250/Simulacao!B249 -> 0.042878389 | G11: =(Simulacao!B250)/24 -> 3601.647 | I11: Potência contratada | K11: =VLOOKUP(Premissas!$B$13,PVSYST_Helexia!$B$5:$F$7,5,0)&" kWac" -> 625 kWac
B12: PPA pago à Helexia | E12: =Simulacao!B7 -> 1493576.4 | F12: =Simulacao!B7/Simulacao!B249 -> 0.74088961 | G12: =(Simulacao!B7)/24 -> 62232.349 | I12: Geração P50 total | K12: =Simulacao!B6/1000 -> 3375.3139
B13: Custo total COM Helexia (rede + PPA) | E13: =Simulacao!B251 -> 1580015.9 | F13: =Simulacao!B251/Simulacao!B249 -> 0.783768 | G13: =(Simulacao!B251)/24 -> 65833.996 | I13: PPA (R$/kWh) | K13: =Premissas!$B$17 -> 0.4425
B14: ★ ECONOMIA LÍQUIDA (rede − PPA) | E14: =Simulacao!B252 -> 435907.06 | F14: =Simulacao!B252/Simulacao!B249 -> 0.216232 | G14: =(Simulacao!B252)/24 -> 18162.794 | I14: Tarifa Grupo A FP | K14: =Premissas!$B$5 -> 0.52647111
B15: + Banco atribuível Helexia @ PPA (net NHS/AMD + Grupo B) | E15: =Simulacao!B285 -> 340242.8 | F15: =IFERROR(Simulacao!B285/Simulacao!B249,0) -> 0.16877768 | G15: =Simulacao!B285/24 -> 14176.783 | I15: Tarifa Grupo B3 | K15: =Premissas!$B$7 -> 1.1568636
B16: ★ VALOR TOTAL HELEXIA (economia + banco atribuível) | E16: =Simulacao!B278 -> 776149.85 | F16: =Simulacao!B278/Simulacao!B249 -> 0.38500968 | G16: =(Simulacao!B278)/24 -> 32339.577 | I16: Economia média/mês | K16: =Simulacao!B252/24 -> 18162.794
I17: % redução custo Copasul | K17: =IFERROR(Simulacao!B252/Simulacao!B249,0) -> 0.216232
I18: Banco residual (kWh) | K18: =Simulacao!B273 -> 1153908.4
B20: C. ANÁLISE VISUAL — ECONOMIA E BANCO DE CRÉDITOS
P22: Mês | Q22: SEM Helexia | R22: PPA | S22: Rede COM | T22: Eco mensal | U22: Eco acumulada
P23: Jun/26 | Q23: =Simulacao!D249 -> 29915.013 | R23: =Simulacao!D7 -> 54865.575 | S23: =Simulacao!D250 -> 2915.1861 | T23: =Simulacao!D252 -> -27865.748 | U23: =T23 -> -27865.748
P24: Jul/26 | Q24: =Simulacao!E249 -> 231390.51 | R24: =Simulacao!E7 -> 57750.675 | S24: =Simulacao!E250 -> 83523.678 | T24: =Simulacao!E252 -> 90116.154 | U24: =U23+T24 -> 62250.406
P25: Ago/26 | Q25: =Simulacao!F249 -> 156547.56 | R25: =Simulacao!F7 -> 69326.475 | S25: =Simulacao!F250 -> 0.54126728 | T25: =Simulacao!F252 -> 87220.544 | U25: =U24+T25 -> 149470.95
P26: Set/26 | Q26: =Simulacao!G249 -> 42616.08 | R26: =Simulacao!G7 -> 65051.925 | S26: =Simulacao!G250 -> 0.12303998 | T26: =Simulacao!G252 -> -22435.968 | U26: =U25+T26 -> 127034.98
P27: Out/26 | Q27: =Simulacao!H249 -> 43352.771 | R27: =Simulacao!H7 -> 66852.9 | S27: =Simulacao!H250 -> 0 | T27: =Simulacao!H252 -> -23500.129 | U27: =U26+T27 -> 103534.85
P28: Nov/26 | Q28: =Simulacao!I249 -> 43210.246 | R28: =Simulacao!I7 -> 64640.4 | S28: =Simulacao!I250 -> 0 | T28: =Simulacao!I252 -> -21430.154 | U28: =U27+T28 -> 82104.699
P29: Dez/26 | Q29: =Simulacao!J249 -> 44658.731 | R29: =Simulacao!J7 -> 61379.175 | S29: =Simulacao!J250 -> 0 | T29: =Simulacao!J252 -> -16720.444 | U29: =U28+T29 -> 65384.255
P30: Jan/27 | Q30: =Simulacao!K249 -> 42484.598 | R30: =Simulacao!K7 -> 63022.753 | S30: =Simulacao!K250 -> 0 | T30: =Simulacao!K252 -> -20538.155 | U30: =U29+T30 -> 44846.1
P31: Fev/27 | Q31: =Simulacao!L249 -> 45032.044 | R31: =Simulacao!L7 -> 56158.671 | S31: =Simulacao!L250 -> 0 | T31: =Simulacao!L252 -> -11126.626 | U31: =U30+T31 -> 33719.474
P32: Mar/27 | Q32: =Simulacao!M249 -> 208536.62 | R32: =Simulacao!M7 -> 64414.061 | S32: =Simulacao!M250 -> 0 | T32: =Simulacao!M252 -> 144122.56 | U32: =U31+T32 -> 177842.03
P33: Abr/27 | Q33: =Simulacao!N249 -> 35167.544 | R33: =Simulacao!N7 -> 64273.169 | S33: =Simulacao!N250 -> 0 | T33: =Simulacao!N252 -> -29105.625 | U33: =U32+T33 -> 148736.41
P34: Mai/27 | Q34: =Simulacao!O249 -> 32721.222 | R34: =Simulacao!O7 -> 60152.078 | S34: =Simulacao!O250 -> 0 | T34: =Simulacao!O252 -> -27430.856 | U34: =U33+T34 -> 121305.55
P35: Jun/27 | Q35: =Simulacao!P249 -> 70853.527 | R35: =Simulacao!P7 -> 54591.247 | S35: =Simulacao!P250 -> 0 | T35: =Simulacao!P252 -> 16262.28 | U35: =U34+T35 -> 137567.83
P36: Jul/27 | Q36: =Simulacao!Q249 -> 281671.07 | R36: =Simulacao!Q7 -> 57461.922 | S36: =Simulacao!Q250 -> 0 | T36: =Simulacao!Q252 -> 224209.15 | U36: =U35+T36 -> 361776.98
P37: Ago/27 | Q37: =Simulacao!R249 -> 161721.87 | R37: =Simulacao!R7 -> 68979.843 | S37: =Simulacao!R250 -> 0 | T37: =Simulacao!R252 -> 92742.025 | U37: =U36+T37 -> 454519.01
P38: Set/27 | Q38: =Simulacao!S249 -> 43681.482 | R38: =Simulacao!S7 -> 64726.665 | S38: =Simulacao!S250 -> 0 | T38: =Simulacao!S252 -> -21045.183 | U38: =U37+T38 -> 433473.83
P39: Out/27 | Q39: =Simulacao!T249 -> 44436.59 | R39: =Simulacao!T7 -> 66518.636 | S39: =Simulacao!T250 -> 0 | T39: =Simulacao!T252 -> -22082.045 | U39: =U38+T39 -> 411391.78
P40: Nov/27 | Q40: =Simulacao!U249 -> 44290.502 | R40: =Simulacao!U7 -> 64317.198 | S40: =Simulacao!U250 -> 0 | T40: =Simulacao!U252 -> -20026.696 | U40: =U39+T40 -> 391365.09
P41: Dez/27 | Q41: =Simulacao!V249 -> 45775.2 | R41: =Simulacao!V7 -> 61072.279 | S41: =Simulacao!V250 -> 0 | T41: =Simulacao!V252 -> -15297.079 | U41: =U40+T41 -> 376068.01
P42: Jan/28 | Q42: =Simulacao!W249 -> 42484.598 | R42: =Simulacao!W7 -> 63022.753 | S42: =Simulacao!W250 -> 0 | T42: =Simulacao!W252 -> -20538.155 | U42: =U41+T42 -> 355529.85
P43: Fev/28 | Q43: =Simulacao!X249 -> 45032.044 | R43: =Simulacao!X7 -> 56158.671 | S43: =Simulacao!X250 -> 0 | T43: =Simulacao!X252 -> -11126.626 | U43: =U42+T43 -> 344403.22
P44: Mar/28 | Q44: =Simulacao!Y249 -> 212454.37 | R44: =Simulacao!Y7 -> 64414.061 | S44: =Simulacao!Y250 -> 0 | T44: =Simulacao!Y252 -> 148040.31 | U44: =U43+T44 -> 492443.54
B45: D. BANCO DE CRÉDITOS — SALDO FINAL MAI/2028 POR UC | Banco total Copasul (incl. geração própria) | P45: Abr/28 | Q45: =Simulacao!Z249 -> 35167.544 | R45: =Simulacao!Z7 -> 64273.169 | S45: =Simulacao!Z250 -> 0 | T45: =Simulacao!Z252 -> -29105.625 | U45: =U44+T45 -> 463337.91
B46: Unidade Consumidora | C46: Grupo | D46: Saldo (kWh) | E46: Valor @ PPA (R$) | F46: % do banco total | P46: Mai/28 | Q46: =Simulacao!AA249 -> 32721.222 | R46: =Simulacao!AA7 -> 60152.078 | S46: =Simulacao!AA250 -> 0 | T46: =Simulacao!AA252 -> -27430.856 | U46: =U45+T46 -> 435907.06
B47: NHS — Novo Horizonte do Sul | C47: A4V | D47: =Simulacao!B255 -> 363392.8 | E47: =Simulacao!B255*Premissas!$B$17 -> 160801.31 | F47: =IFERROR(Simulacao!B255/Simulacao!B273,0) -> 0.31492344
B48: AMD — Amandina | C48: A3A | D48: =Simulacao!B256 -> 347056.55 | E48: =Simulacao!B256*Premissas!$B$17 -> 153572.52 | F48: =IFERROR(Simulacao!B256/Simulacao!B273,0) -> 0.30076612
B49: AREC | C49: B3 | D49: =Simulacao!B257 -> 48227.228 | E49: =Simulacao!B257*Premissas!$B$17 -> 21340.548 | F49: =IFERROR(Simulacao!B257/Simulacao!B273,0) -> 0.041794676
B50: Banheiro Motoristas | C50: B3 | D50: =Simulacao!B258 -> 3516.0366 | E50: =Simulacao!B258*Premissas!$B$17 -> 1555.8462 | F50: =IFERROR(Simulacao!B258/Simulacao!B273,0) -> 0.0030470673
B51: CTC Copasul | C51: B3 | D51: =Simulacao!B259 -> 4931.6829 | E51: =Simulacao!B259*Premissas!$B$17 -> 2182.2697 | F51: =IFERROR(Simulacao!B259/Simulacao!B273,0) -> 0.0042738946
B52: Depósito Irrigação | C52: B3 | D52: =Simulacao!B260 -> 8017.1096 | E52: =Simulacao!B260*Premissas!$B$17 -> 3547.571 | F52: =IFERROR(Simulacao!B260/Simulacao!B273,0) -> 0.0069477869
B53: Entreposto | C53: B3 | D53: =Simulacao!B261 -> 174669.21 | E53: =Simulacao!B261*Premissas!$B$17 -> 77291.125 | F53: =IFERROR(Simulacao!B261/Simulacao!B273,0) -> 0.15137182
B54: Esc. Deodápolis | C54: B3 | D54: =Simulacao!B262 -> 30697.169 | E54: =Simulacao!B262*Premissas!$B$17 -> 13583.497 | F54: =IFERROR(Simulacao!B262/Simulacao!B273,0) -> 0.026602778
B55: Esc. Nova Andradina | C55: B3 | D55: =Simulacao!B263 -> 17019.809 | E55: =Simulacao!B263*Premissas!$B$17 -> 7531.2655 | F55: =IFERROR(Simulacao!B263/Simulacao!B273,0) -> 0.014749706
B56: Esc. Regional Deodápolis | C56: B3 | D56: =Simulacao!B264 -> 11109.969 | E56: =Simulacao!B264*Premissas!$B$17 -> 4916.1613 | F56: =IFERROR(Simulacao!B264/Simulacao!B273,0) -> 0.0096281205
B57: Galpão AE | C57: B3 | D57: =Simulacao!B265 -> 4588.771 | E57: =Simulacao!B265*Premissas!$B$17 -> 2030.5312 | F57: =IFERROR(Simulacao!B265/Simulacao!B273,0) -> 0.0039767204
B58: Irrigação CG | C58: B3 | D58: =Simulacao!B266 -> 6783.8623 | E58: =Simulacao!B266*Premissas!$B$17 -> 3001.8591 | F58: =IFERROR(Simulacao!B266/Simulacao!B273,0) -> 0.0058790302
B59: Laboratório de Solos | C59: B3 | D59: =Simulacao!B267 -> 32892.006 | E59: =Simulacao!B267*Premissas!$B$17 -> 14554.712 | F59: =IFERROR(Simulacao!B267/Simulacao!B273,0) -> 0.028504867
B60: Posto Carreteiro | C60: B3 | D60: =Simulacao!B268 -> 65098.388 | E60: =Simulacao!B268*Premissas!$B$17 -> 28806.037 | F60: =IFERROR(Simulacao!B268/Simulacao!B273,0) -> 0.05641556
B61: Refeitório Deodápolis | C61: B1 | D61: =Simulacao!B269 -> 1320.3387 | E61: =Simulacao!B269*Premissas!$B$17 -> 584.24988 | F61: =IFERROR(Simulacao!B269/Simulacao!B273,0) -> 0.0011442318
B62: Subest. Fiação | C62: B3 | D62: =Simulacao!B270 -> 10010.107 | E62: =Simulacao!B270*Premissas!$B$17 -> 4429.4722 | F62: =IFERROR(Simulacao!B270/Simulacao!B273,0) -> 0.0086749579
B63: TRR Maracaju | C63: B3 | D63: =Simulacao!B271 -> 24577.359 | E63: =Simulacao!B271*Premissas!$B$17 -> 10875.481 | F63: =IFERROR(Simulacao!B271/Simulacao!B273,0) -> 0.021299229
B64: TOTAL — 17 UCs | D64: =Simulacao!B273 -> 1153908.4 | E64: =Simulacao!B273*Premissas!$B$17 -> 510604.46 | F64: =1 -> 1
B65: E. BANCO ATRIBUÍVEL HELEXIA — O QUE A HELEXIA REALMENTE ENTREGA
B66: Unidade / Grupo | C66: Banco SEM | D66: Banco COM | E66: Atribuível (kWh) | F66: Atribuível (R$)
B67: NHS — Novo Horizonte do Sul (A4V) | C67: =Simulacao!AA34 -> 44055.758 | D67: =Simulacao!AA31 -> 363392.8 | E67: =Simulacao!B281 -> 319337.04 | F67: =Simulacao!B281*Premissas!$B$17 -> 141306.64
B68: AMD — Amandina (A3A) | C68: =Simulacao!AA52 -> 340942.36 | D68: =Simulacao!AA49 -> 347056.55 | E68: =Simulacao!B282 -> 6114.1902 | F68: =Simulacao!B282*Premissas!$B$17 -> 2705.5292
B69: Grupo B — 15 UCs (SEM banco próprio = zero) | C69: 0 | D69: =Simulacao!B283 -> 443459.04 | E69: =Simulacao!B283 -> 443459.04 | F69: =Simulacao!B283*Premissas!$B$17 -> 196230.63
B70: ★ BANCO ATRIBUÍVEL TOTAL HELEXIA | C70: — | D70: — | E70: =Simulacao!B284 -> 768910.28 | F70: =Simulacao!B285 -> 340242.8
B71: * Banco COM = saldo que Copasul terá em Mai/2028. Banco SEM = projeção sem CS3. Atribuível = diferença gerada pela Helexia (Grupo B: 100%; NHS/AMD: COM−SEM).
B72: ="Modelo V4_d · Usina: "&Premissas!$B$13&" · PPA: R$"&TEXT(Premissas!$B$17,"0.0000")&"/kWh"&" · Jun/2026–Mai/2028" -> Modelo V4_d · Usina: Cassilândia 03 · PPA: R$00.000/kWh · Jun/2026–Mai/2028

Sheet Premissas
A1: ="PREMISSAS — "&Premissas!$B$13&" × Copasul | Energisa MS" -> PREMISSAS — Cassilândia 03 × Copasul | Energisa MS | G1: 🎯 OTIMIZAÇÃO RATEIO — SOLVER CONFIG
A2: Azul = inputs editáveis | Preto = fórmulas | Verde = links entre abas | G2: Siga o passo a passo abaixo para maximizar Economia Líquida via Excel Solver
A4: A. TARIFAS ENERGISA MS (com tributos ICMS 17% + PIS/COFINS) | G4: ① CÉLULA OBJETIVO (aponte o Solver aqui): | J4: ENDEREÇO | K4: VALOR ATUAL | L4: OBJETIVO
A5: Tarifa Grupo A FP com tributos (R$/kWh) | B5: 0.52647111 | C5: ← T_AFP: edit here | G5: Economia Líquida Copasul 24m (R$) | J5: Premissas!K5 | K5: =Simulacao!B252 -> 435907.06 | L5: ↑ MAXIMIZAR
A6: Tarifa Grupo A Ponta com tributos (R$/kWh) | B6: 2.9723794 | C6: ← T_APT: edit here
A7: Tarifa Grupo B3 com tributos (R$/kWh) | B7: 1.1568636 | C7: ← T_B3: edit here | D7: =(592+286.02)/(1-B10)/(1-B9) -> 1156.7583 | G7: ② ATIVAR SOLVER (se ainda não estiver ativo) | I7: Arquivo → Opções → Suplementos → Gerenciar: Suplementos do Excel → Ir... → ✓ Solver Add-in → OK
A8: FA = TE_FP / TE_Ponta | B8: 0.60426705 | C8: ← FA: edit here | G8: ③ ABRIR SOLVER | I8: Guia Dados → botão "Solver" (canto direito da faixa de opções)
A9: ICMS (%) | B9: 0.17 | C9: ← ICMS: edit here | G9: ④ CONFIGURAR OBJETIVO | I9: Definir Objetivo: selecione a célula Premissas!K5 → marque ● Máx
A10: PIS + COFINS (%) | B10: 0.0855 | C10: ← PIS_COFINS: edit here | G10: ⑤ DEFINIR CÉLULAS VARIÁVEIS | I10: Alterando Células de Variáveis: Premissas!$B$33:$E$50 (68 variáveis = 17 UCs × 4 períodos)
A11: ICMS isenção autoconsumo remoto ativa? (Art. 23-A RICMS/MS) → 'Sim' = isento | 'Não' = ICMS cobrado sobre kWh compensados pelo CS3 | B11: Sim | C11: =IF($B$11="Sim",0,$B$5*$B$9/(1+$B$9)) -> 0 | D11: =IF($B$11="Sim",0,$B$6*$B$9/(1+$B$9)) -> 0 | E11: =IF($B$11="Sim",0,$B$7*$B$9/(1+$B$9)) -> 0 | F11: ← B=toggle (Sim/Não) | C=ICMS A_FP D=ICMS A_Ponta E=ICMS Grupo B (R$/kWh) — tudo 0 se Sim
A12: B. CONDIÇÕES DO CONTRATO | G12: ⑥ ADICIONAR AS RESTRIÇÕES (Adicionar → preencher cada linha → OK)
A13: Usina | B13: Cassilândia 03 | G13: Célula / Intervalo | I13: Relação | J13: Valor / Restrição | L13: Descrição
A14: Distribuidora | B14: Energisa MS | G14: Premissas!$B$33:$E$50 | I14: >= | J14: 0 | L14: Todos os rateios ≥ 0% (sem valores negativos)
A15: Início do contrato | B15: Jun/2026 | G15: Premissas!$B$51 | I15: = | J15: 1 | L15: Soma P1 = 100% (Jun–Set/26)
A16: Prazo (meses) | B16: 24 | G16: Premissas!$C$51 | I16: = | J16: 1 | L16: Soma P2 = 100% (Out/26–Mar/27)
A17: PPA Helexia CS3 (R$/kWh) | B17: 0.4425 | G17: Premissas!$D$51 | I17: = | J17: 1 | L17: Soma P3 = 100% (Abr–Set/27)
A18: H. CENÁRIO CONCORRENTE — ENERGIA ASSINATURA GRUPO B (ex: Plin Energia) | G18: Premissas!$E$51 | I18: = | J18: 1 | L18: Soma P4 = 100% (Out/27–Mai/28)
A19: Grupo B tem contrato Assinatura GD concorrente? | B19: Sim | C19: Desconto (%): | D19: 0.2 | E19: Tarifa B3 SEM efetiva: | F19: =IF(B19="Sim",B7*(1-D19),B7) -> 0.92549092 | G19: Premissas!$B$34:$E$34 | I19: = | J19: 0 | L19: BAT (linha 34) = 0% em todos os períodos
A20: C. PREMISSAS DE CRESCIMENTO E DEGRADAÇÃO | G20: Premissas!$B$33:$E$50 | I20: <= | J20: 1 | L20: Todos os rateios ≤ 100% (limite superior)
A21: Crescimento consumo Y2 vs Y1 (%) | B21: 0.025 | C21: ← 2.5% editável | aplica a TODOS os UCs
A22: Crescimento consumo Y3 parcial (Dez/27-Mai/28) (%) | B22: =B21 -> 0.025 | C22: ← mesmo % que Y2 por padrão | G22: ⑦ MÉTODO DE RESOLUÇÃO E OPÇÕES
A23: Degradação geração Y2 (%) | B23: 0.005 | C23: ← 0.5%/ano editável | G23: Método de Resolução: | I23: GRG Não-Linear | J23: O modelo tem funções IF (não-lineares). GRG é o método correto.
A24: Usar proxy Batayporã p/ Amandina gen? | B24: Sim | G24: Opções → Precisão: | I24: 0,000001 | J24: Maior precisão = resultado mais fino.
A25: D. BANCOS DE CRÉDITOS — SALDO INICIAL (Mai/2026, FPt GD I) | G25: Opções → Iterações: | I25: 1000 | J25: Permite mais buscas antes de parar.
A26: NHS — Silos Novo Horizonte do Sul (kWh) | B26: 148516 | G26: Opções → Convergência: | I26: 0,0001 | J26: Critério de parada quando melhoria < este valor.
A27: BAT — Silos Batayporã (kWh) [stranded — não transferível CS3] | B27: 906739 | G27: ⚠ Otimização local: | I27: Execute 2–3 vezes | J27: GRG pode parar em mínimo local. Rode com rateios iniciais diferentes e fique com o melhor resultado.
A28: AMD — Silos Amandina (kWh) | B28: 991029
A29: TOTAL NHS+AMD (kWh) | B29: =B26+B28 -> 1139545 | C29: ← BAT stranded bank não incluído no total | G29: ⑧ EXECUTAR → clicar "Resolver" → aceitar "Manter Solução do Solver"
G30: Economia Liquida ANTES da otimização (R$): | J30: 670877.66 | K30: ← valor antes de rodar o Solver (referência)
A31: ="E. RATEIO FIXO "&INDEX(PVSYST_Helexia!$A$5:$A$7,MATCH(Premissas!$B$13,PVSYST_Helexia!$B$5:$B$7,0))&" — 4 PERÍODOS (edit percentuais — devem somar 100% por período)" -> E. RATEIO FIXO HCS03 — 4 PERÍODOS (edit percentuais — devem somar 100% por período) | G31: Vsalor Banco Residual ANTES da otimização (R$): | J31: =Resumo!H5 -> 510604.46 | K31: ← valor antes de rodar o Solver (referência)
A32: UC / Planta | B32: P1: Jun–Set/26 | C32: P2: Out/26–Mar/27 | D32: P3: Abr/27–Set/27 | E32: P4: Out/27–Mai/28 | G32: Economia APÓS otimização (R$) — resultado: | J32: =Simulacao!B252 -> 435907.06 | K32: ← atualiza automaticamente após o Solver alterar B33:E50
A33: NHS — Silos N. Horizonte (A4V) | B33: 0.73507401 | C33: 0.52568024 | D33: 0.67565005 | E33: 0.2812
A34: BAT — Silos Batayporã (A4V) | B34: 0 | C34: 0 | D34: 0 | E34: 0
A35: AMD — Silos Amandina (A3A) | B35: 0 | C35: 0 | D35: 0.0040543277 | E35: 0.15613575
A36: AREC (B3) | B36: 0.02507178 | C36: 0.052438168 | D36: 0.030810666 | E36: 0.065745819
A37: Banheiro Motoristas (B3) | B37: 0.0029636272 | C37: 0.0050152416 | D37: 0.0040120941 | E37: 0.0045
A38: CTC Copasul (B3) | B38: 0.0030456113 | C38: 0.0077143316 | D38: 0.0039240548 | E38: 0.0072001249
A39: Depósito Irrigação (B3) | B39: 0.005207938 | C39: 0.011390137 | D39: 0.0081206428 | E39: 0.0095
A40: Entreposto (B3) | B40: 0.062427819 | C40: 0.10355391 | D40: 0.071218793 | E40: 0.19566197
A41: Esc. Deodápolis (B3) | B41: 0.020366818 | C41: 0.035456452 | D41: 0.025789767 | E41: 0.043215414
A42: Esc. Nova Andradina (B3) | B42: 0.011816973 | C42: 0.029312076 | D42: 0.015796921 | E42: 0.0283
A43: Esc. Regional Deodápolis (B3) | B43: 0.004459102 | C43: 0.015652924 | D43: 0.0059948465 | E43: 0.014661144
A44: Galpão AE (B3) | B44: 0.0064756968 | C44: 0.0043347698 | D44: 0.0058696517 | E44: 0.0042596948
... A50: TRR Maracaju (B3) | B50: 0.02990357 | C50: 0.036122273 | D50: 0.03634439 | E50: 0.039303738
A51: TOTAL (deve = 100%) | B51: =SUM(B33:B50) -> 0.99999999 | C51: =SUM(C33:C50) -> 1 | D51: =SUM(D33:D50) -> 1 | E51: =SUM(E33:E50) -> 1
A52: ⚠ Ajuste os percentuais acima para que cada coluna some exatamente 100%. BAT está fixo em 0% — seus créditos futuros entram via mecanismo de rateio próprio (seção F abaixo). A otimização automática maximiza o aproveitamento dos créditos CS3.
A54: F. RATEIO DO SURPLUS BAT — 2 PERÍODOS (NH 39% / AMD 61% por padrão)
A55: BAT→NHS (%) | B55: 0.5 | C55: ← editável
A56: BAT→AMD (%) | B56: =1-B55 -> 0.5 | C56: ← = 1 − NHS%
A59: ="G. GERAÇÃO "&INDEX(PVSYST_Helexia!$A$5:$A$7,MATCH(Premissas!$B$13,PVSYST_Helexia!$B$5:$B$7,0))&" P50 — PVSYST "&Premissas!$B$13&" (kWh/mês)" -> G. GERAÇÃO HCS03 P50 — PVSYST Cassilândia 03 (kWh/mês)
A60: Degradação Y2 aplicada | B60: =Premissas!$B$23 -> 0.005 | C60: ← Y1: valor direto PVSYST | Y2/Y3: × (1−DEG)
A61: Jun/26 | B61: =INDEX(PVSYST_Helexia!$J$5:$U$7,MATCH(Premissas!$B$13,PVSYST_Helexia!$B$5:$B$7,0),6)*1000 -> 123990 | C61: kWh — CS3 P50 mês 06 (base=136,620 kWh)
A62: Jul/26 | B62: =INDEX(PVSYST_Helexia!$J$5:$U$7,MATCH(Premissas!$B$13,PVSYST_Helexia!$B$5:$B$7,0),7)*1000 -> 130510 | C62: kWh — CS3 P50 mês 07 (base=123,990 kWh)
A63: Ago/26 | B63: =INDEX(PVSYST_Helexia!$J$5:$U$7,MATCH(Premissas!$B$13,PVSYST_Helexia!$B$5:$B$7,0),8)*1000 -> 156670 | C63: kWh — CS3 P50 mês 08 (base=130,510 kWh)
A64: Set/26 | B64: =INDEX(PVSYST_Helexia!$J$5:$U$7,MATCH(Premissas!$B$13,PVSYST_Helexia!$B$5:$B$7,0),9)*1000 -> 147010 | C64: kWh — CS3 P50 mês 09 (base=156,670 kWh)
A65: Out/26 | B65: =INDEX(PVSYST_Helexia!$J$5:$U$7,MATCH(Premissas!$B$13,PVSYST_Helexia!$B$5:$B$7,0),10)*1000 -> 151080 | C65: kWh — CS3 P50 mês 10 (base=147,010 kWh)
A66: Nov/26 | B66: =INDEX(PVSYST_Helexia!$J$5:$U$7,MATCH(Premissas!$B$13,PVSYST_Helexia!$B$5:$B$7,0),11)*1000 -> 146080 | C66: kWh — CS3 P50 mês 11 (base=151,080 kWh)
A67: Dez/26 | B67: =INDEX(PVSYST_Helexia!$J$5:$U$7,MATCH(Premissas!$B$13,PVSYST_Helexia!$B$5:$B$7,0),12)*1000 -> 138710 | C67: kWh — CS3 P50 mês 12 (base=146,080 kWh)
A68: Jan/27 | B68: =INDEX(PVSYST_Helexia!$J$5:$U$7,MATCH(Premissas!$B$13,PVSYST_Helexia!$B$5:$B$7,0),1)*1000*(1-Premissas!$B$23) -> 142424.3 | C68: kWh — CS3 P50 mês 01 (base=2,000 kWh)
A69: Fev/27 | B69: =INDEX(PVSYST_Helexia!$J$5:$U$7,MATCH(Premissas!$B$13,PVSYST_Helexia!$B$5:$B$7,0),2)*1000*(1-Premissas!$B$23) -> 126912.25 | C69: kWh — CS3 P50 mês 02 (base=143,140 kWh)
A70: Mar/27 | B70: =INDEX(PVSYST_Helexia!$J$5:$U$7,MATCH(Premissas!$B$13,PVSYST_Helexia!$B$5:$B$7,0),3)*1000*(1-Premissas!$B$23) -> 145568.5 | C70: kWh — CS3 P50 mês 03 (base=127,550 kWh)
A71: Abr/27 | B71: =INDEX(PVSYST_Helexia!$J$5:$U$7,MATCH(Premissas!$B$13,PVSYST_Helexia!$B$5:$B$7,0),4)*1000*(1-Premissas!$B$23) -> 145250.1 | C71: kWh — CS3 P50 mês 04 (base=146,300 kWh)
A72: Mai/27 | B72: =INDEX(PVSYST_Helexia!$J$5:$U$7,MATCH(Premissas!$B$13,PVSYST_Helexia!$B$5:$B$7,0),5)*1000*(1-Premissas!$B$23) -> 135936.9 | C72: kWh — CS3 P50 mês 05 (base=145,980 kWh)
A73: Jun/27 | B73: =INDEX(PVSYST_Helexia!$J$5:$U$7,MATCH(Premissas!$B$13,PVSYST_Helexia!$B$5:$B$7,0),6)*1000*(1-Premissas!$B$23) -> 123370.05 | C73: kWh — CS3 P50 mês 06 (base=136,620 kWh)
A74: Jul/27 | B74: =INDEX(PVSYST_Helexia!$J$5:$U$7,MATCH(Premissas!$B$13,PVSYST_Helexia!$B$5:$B$7,0),7)*1000*(1-Premissas!$B$23) -> 129857.45 | C74: kWh — CS3 P50 mês 07 (base=123,990 kWh)
A75: Ago/27 | B75: =INDEX(PVSYST_Helexia!$J$5:$U$7,MATCH(Premissas!$B$13,PVSYST_Helexia!$B$5:$B$7,0),8)*1000*(1-Premissas!$B$23) -> 155886.65 | C75: kWh — CS3 P50 mês 08 (base=130,510 kWh)
A76: Set/27 | B76: =INDEX(PVSYST_Helexia!$J$5:$U$7,MATCH(Premissas!$B$13,PVSYST_Helexia!$B$5:$B$7,0),9)*1000*(1-Premissas!$B$23) -> 146274.95 | C76: kWh — CS3 P50 mês 09 (base=156,670 kWh)
A77: Out/27 | B77: =INDEX(PVSYST_Helexia!$J$5:$U$7,MATCH(Premissas!$B$13,PVSYST_Helexia!$B$5:$B$7,0),10)*1000*(1-Premissas!$B$23) -> 150324.6 | C77: kWh — CS3 P50 mês 10 (base=147,010 kWh)
A78: Nov/27 | B78: =INDEX(PVSYST_Helexia!$J$5:$U$7,MATCH(Premissas!$B$13,PVSYST_Helexia!$B$5:$B$7,0),11)*1000*(1-Premissas!$B$23) -> 145349.6 | C78: kWh — CS3 P50 mês 11 (base=151,080 kWh)
A79: Dez/27 | B79: =INDEX(PVSYST_Helexia!$J$5:$U$7,MATCH(Premissas!$B$13,PVSYST_Helexia!$B$5:$B$7,0),12)*1000*(1-Premissas!$B$23) -> 138016.45 | C79: kWh — CS3 P50 mês 12 (base=146,080 kWh)
A80: Jan/28 | B80: =INDEX(PVSYST_Helexia!$J$5:$U$7,MATCH(Premissas!$B$13,PVSYST_Helexia!$B$5:$B$7,0),1)*1000*(1-Premissas!$B$23) -> 142424.3 | C80: kWh — CS3 P50 mês 01 (base=2,000 kWh)
A81: Fev/28 | B81: =INDEX(PVSYST_Helexia!$J$5:$U$7,MATCH(Premissas!$B$13,PVSYST_Helexia!$B$5:$B$7,0),2)*1000*(1-Premissas!$B$23) -> 126912.25 | C81: kWh — CS3 P50 mês 02 (base=143,140 kWh)
A82: Mar/28 | B82: =INDEX(PVSYST_Helexia!$J$5:$U$7,MATCH(Premissas!$B$13,PVSYST_Helexia!$B$5:$B$7,0),3)*1000*(1-Premissas!$B$23) -> 145568.5 | C82: kWh — CS3 P50 mês 03 (base=127,550 kWh)
A83: Abr/28 | B83: =INDEX(PVSYST_Helexia!$J$5:$U$7,MATCH(Premissas!$B$13,PVSYST_Helexia!$B$5:$B$7,0),4)*1000*(1-Premissas!$B$23) -> 145250.1 | C83: kWh — CS3 P50 mês 04 (base=146,300 kWh)
A84: Mai/28 | B84: =INDEX(PVSYST_Helexia!$J$5:$U$7,MATCH(Premissas!$B$13,PVSYST_Helexia!$B$5:$B$7,0),5)*1000*(1-Premissas!$B$23) -> 135936.9 | C84: kWh — CS3 P50 mês 05 (base=145,980 kWh)

Sheet Input_Consumo_GrupoA
A1: INPUT — CONSUMO ORÇADO GRUPO A | Fonte: Consumo_Orçado_2026_GD
A2: Azul = valores editáveis (fonte: arquivo fornecido) | Preto = fórmulas de projeção Y2/Y3
A3: Mês | B3: NHS FP (kWh) | C3: NHS Ponta (kWh) | D3: BAT FP (kWh) | E3: BAT Ponta (kWh) | F3: AMD FP (kWh) | G3: AMD Ponta (kWh)
A4: Jan | B4: 70769.9 | C4: 7863.3 | D4: 113967 | E4: 12663 | F4: 73973.4 | G4: 8219.3
A5: Fev | B5: 243719.7 | C5: 27080 | D5: 125874 | E5: 13986 | F5: 209472.2 | G5: 23274.7
A6: Mar | B6: 331874.1 | C6: 36874.9 | D6: 57499.2 | E6: 6388.8 | F6: 173260.2 | G6: 19251.1
A7: Abr | B7: 102778.3 | C7: 11419.8 | D7: 35640 | E7: 3960 | F7: 78448.4 | G7: 8716.5
A8: Mai | B8: 62814.2 | C8: 6979.4 | D8: 79603.2 | E8: 8844.8 | F8: 102629.5 | G8: 11403.3
A9: Jun | B9: 108694.9 | C9: 12077.2 | D9: 78336 | E9: 8704 | F9: 182444.7 | G9: 20271.6
A10: Jul | B10: 328938.1 | C10: 36548.7 | D10: 115718.4 | E10: 12857.6 | F10: 234799.2 | G10: 26088.8
A11: Ago | B11: 190977.6 | C11: 21219.7 | D11: 23364 | E11: 2596 | F11: 134799.3 | G11: 14977.7
A12: Set | B12: 126478.8 | C12: 14053.2 | D12: 10800 | E12: 1200 | F12: 18637.2 | G12: 2070.8
A13: Out | B13: 28215 | C13: 3135 | D13: 10800 | E13: 1200 | F13: 24382.8 | G13: 2709.2
A14: Nov | B14: 42209.6 | C14: 4690 | D14: 10800 | E14: 1200 | F14: 20225.7 | G14: 2247.3
A15: Dez | B15: 42209.6 | C15: 4690 | D15: 3402 | E15: 378 | F15: 17142.3 | G15: 1904.7
A17: Crescimento Y2 aplicado automaticamente via Premissas!$B$21 (atualmente 2,5%). Altere lá para que todos os 18 UCs sejam atualizados.

Sheet Simulacao
A1: ="SIMULAÇÃO RATEIO FIXO — "&Premissas!$B$13&" × COPASUL | 18 UCs | Jun/2026–Mai/2028" -> SIMULAÇÃO RATEIO FIXO — Cassilândia 03 × COPASUL | 18 UCs | Jun/2026–Mai/2028
A2: Energisa MS · Todas as células são fórmulas · Azul=input Premissas · Verde=link entre abas
A4: INDICADOR / UC | B4: TOTAL 24m ou SALDO FINAL | C4: MÉD/mês ou unidade | D4: Jun/26 | E4: Jul/26 | F4: Ago/26 | G4: Set/26 | H4: Out/26 | I4: Nov/26 | J4: Dez/26 | K4: Jan/27 | L4: Fev/27 | M4: Mar/27 | N4: Abr/27 | O4: Mai/27 | P4: Jun/27 | Q4: Jul/27 | R4: Ago/27 | S4: Set/27 | T4: Out/27 | U4: Nov/27 | V4: Dez/27 | W4: Jan/28 | X4: Fev/28 | Y4: Mar/28 | Z4: Abr/28 | AA4: Mai/28
A5: ="0. "&Premissas!B13&" — GERAÇÃO E CUSTO PPA" -> 0. Cassilândia 03 — GERAÇÃO E CUSTO PPA
A6: =INDEX(PVSYST_Helexia!$A$5:$A$7,MATCH(Premissas!$B$13,PVSYST_Helexia!$B$5:$B$7,0))&" Geração P50 (kWh)" -> HCS03 Geração P50 (kWh) | B6: =SUM(D6:AA6) -> 3375313.9 | C6: =B6/24 -> 140638.08 | D6: =Premissas!$B$61 -> 123990 | E6: =Premissas!$B$62 -> 130510 | F6: =Premissas!$B$63 -> 156670 | G6: =Premissas!$B$64 -> 147010 | H6: =Premissas!$B$65 -> 151080 | I6: =Premissas!$B$66 -> 146080 | J6: =Premissas!$B$67 -> 138710 | K6: =Premissas!$B$68 -> 142424.3 | L6: =Premissas!$B$69 -> 126912.25 | M6: =Premissas!$B$70 -> 145568.5 | N6: =Premissas!$B$71 -> 145250.1 | O6: =Premissas!$B$72 -> 135936.9 | P6: =Premissas!$B$73 -> 123370.05 | Q6: =Premissas!$B$74 -> 129857.45 | R6: =Premissas!$B$75 -> 155886.65 | S6: =Premissas!$B$76 -> 146274.95 | T6: =Premissas!$B$77 -> 150324.6 | U6: =Premissas!$B$78 -> 145349.6 | V6: =Premissas!$B$79 -> 138016.45 | W6: =Premissas!$B$80 -> 142424.3 | X6: =Premissas!$B$81 -> 126912.25 | Y6: =Premissas!$B$82 -> 145568.5 | Z6: =Premissas!$B$83 -> 145250.1 | AA6: =Premissas!$B$84 -> 135936.9
A7: PPA Helexia — custo total (R$) | B7: =SUM(D7:AA7) -> 1493576.4 | C7: =B7/24 -> 62232.349 | D7: =D6*Premissas!$B$17 -> 54865.575 | E7: =E6*Premissas!$B$17 -> 57750.675 | F7: =F6*Premissas!$B$17 -> 69326.475 | G7: =G6*Premissas!$B$17 -> 65051.925 | H7: =H6*Premissas!$B$17 -> 66852.9 | I7: =I6*Premissas!$B$17 -> 64640.4 | J7: =J6*Premissas!$B$17 -> 61379.175 | K7: =K6*Premissas!$B$17 -> 63022.753 | ... AA7: =AA6*Premissas!$B$17 -> 60152.078
A8: 1. BAT — BATAYPORÃ — GERAÇÃO, CONSUMO E SURPLUS
A9: BAT Geração própria (kWh) | B9: =SUM(D9:AA9) -> 2254432.4 | C9: =B9/24 -> 93934.683 | D9: =+Batayporã!I8 -> 72286.9 | E9: =+Batayporã!I9 -> 88336.8 | F9: =+Batayporã!I10 -> 93082.7 | G9: =+Batayporã!I11 -> 94433.4 | H9: =+Batayporã!I12 -> 95906.8 | I9: =+Batayporã!I13 -> 107980.6 | J9: =+Batayporã!I14 -> 106603.9 | K9: =+Batayporã!I3*(1-Premissas!$B$23) -> 113687.7 | L9: =+Batayporã!I4*(1-Premissas!$B$23) -> 90676.241 | M9: =+Batayporã!I5*(1-Premissas!$B$23) -> 102546.59 | N9: =+Batayporã!I6*(1-Premissas!$B$23) -> 73341.151 | O9: =+Batayporã!I7*(1-Premissas!$B$23) -> 91158.517 | P9: =D9*(1-Premissas!$B$23) -> 71925.465 | Q9: =E9*(1-Premissas!$B$23) -> 87895.116 | R9: =F9*(1-Premissas!$B$23) -> 92617.287 | S9: =G9*(1-Premissas!$B$23) -> 93961.233 | T9: =H9*(1-Premissas!$B$23) -> 95427.266 | U9: =I9*(1-Premissas!$B$23) -> 107440.7 | V9: =J9*(1-Premissas!$B$23) -> 106070.88 | W9: =K9*(1-Premissas!$B$23) -> 113119.27 | ... AA9: =O9*(1-Premissas!$B$23) -> 90702.724
A10: BAT Consumo FP (kWh) | B10: =SUM(D10:AA10) -> 1358567.3 | C10: =B10/24 -> 56606.97 | D10: =Input_Consumo_GrupoA!$D$9 -> 78336 | E10: =Input_Consumo_GrupoA!$D$10 -> 115718.4 | F10: =Input_Consumo_GrupoA!$D$11 -> 23364 | G10: =Input_Consumo_GrupoA!$D$12 -> 10800 | H10: =Input_Consumo_GrupoA!$D$13 -> 10800 | I10: =Input_Consumo_GrupoA!$D$14 -> 10800 | J10: =Input_Consumo_GrupoA!$D$15 -> 3402 | K10: =Input_Consumo_GrupoA!$D$4*(1+Premissas!$B$21) -> 116816.17 | L10: =Input_Consumo_GrupoA!$D$5*(1+Premissas!$B$21) -> 129020.85 | M10: =Input_Consumo_GrupoA!$D$6*(1+Premissas!$B$21) -> 58936.68 | N10: =Input_Consumo_GrupoA!$D$7*(1+Premissas!$B$21) -> 36531 | O10: =Input_Consumo_GrupoA!$D$8*(1+Premissas!$B$21) -> 81593.28 | P10: =Input_Consumo_GrupoA!$D$9*(1+Premissas!$B$21) -> 80294.4 | Q10: =Input_Consumo_GrupoA!$D$10*(1+Premissas!$B$21) -> 118611.36 | R10: =Input_Consumo_GrupoA!$D$11*(1+Premissas!$B$21) -> 23948.1 | S10: =Input_Consumo_GrupoA!$D$12*(1+Premissas!$B$21) -> 11070 | T10: =Input_Consumo_GrupoA!$D$13*(1+Premissas!$B$21) -> 11070 | U10: =Input_Consumo_GrupoA!$D$14*(1+Premissas!$B$21) -> 11070 | V10: =Input_Consumo_GrupoA!$D$15*(1+Premissas!$B$21) -> 3487.05 | W10: =Input_Consumo_GrupoA!$D$4*(1+Premissas!$B$21) -> 116816.17 | X10: =Input_Consumo_GrupoA!$D$5*(1+Premissas!$B$21) -> 129020.85 | Y10: =Input_Consumo_GrupoA!$D$6*(1+Premissas!$B$21) -> 58936.68 | Z10: =Input_Consumo_GrupoA!$D$7*(1+Premissas!$B$21) -> 36531 | AA10: =Input_Consumo_GrupoA!$D$8*(1+Premissas!$B$21) -> 81593.28
A11: BAT Consumo Ponta (kWh) | B11: =SUM(D11:AA11) -> 150951.92 | C11: =B11/24 -> 6289.6633 | D11: =Input_Consumo_GrupoA!$E$9 -> 8704 | E11: =Input_Consumo_GrupoA!$E$10 -> 12857.6 | F11: =Input_Consumo_GrupoA!$E$11 -> 2596 | G11: =Input_Consumo_GrupoA!$E$12 -> 1200 | H11: =Input_Consumo_GrupoA!$E$13 -> 1200 | I11: =Input_Consumo_GrupoA!$E$14 -> 1200 | J11: =Input_Consumo_GrupoA!$E$15 -> 378 | K11: =Input_Consumo_GrupoA!$E$4*(1+Premissas!$B$21) -> 12979.575 | L11: =Input_Consumo_GrupoA!$E$5*(1+Premissas!$B$21) -> 14335.65 | M11: =Input_Consumo_GrupoA!$E$6*(1+Premissas!$B$21) -> 6548.52 | N11: =Input_Consumo_GrupoA!$E$7*(1+Premissas!$B$21) -> 4059 | O11: =Input_Consumo_GrupoA!$E$8*(1+Premissas!$B$21) -> 9065.92 | P11: =Input_Consumo_GrupoA!$E$9*(1+Premissas!$B$21) -> 8921.6 | Q11: =Input_Consumo_GrupoA!$E$10*(1+Premissas!$B$21) -> 13179.04 | R11: =Input_Consumo_GrupoA!$E$11*(1+Premissas!$B$21) -> 2660.9 | S11: =Input_Consumo_GrupoA!$E$12*(1+Premissas!$B$21) -> 1230 | T11: =Input_Consumo_GrupoA!$E$13*(1+Premissas!$B$21) -> 1230 | U11: =Input_Consumo_GrupoA!$E$14*(1+Premissas!$B$21) -> 1230 | V11: =Input_Consumo_GrupoA!$E$15*(1+Premissas!$B$21) -> 387.45 | W11: =Input_Consumo_GrupoA!$E$4*(1+Premissas!$B$21) -> 12979.575 | X11: =Input_Consumo_GrupoA!$E$5*(1+Premissas!$B$21) -> 14335.65 | Y11: =Input_Consumo_GrupoA!$E$6*(1+Premissas!$B$21) -> 6548.52 | Z11: =Input_Consumo_GrupoA!$E$7*(1+Premissas!$B$21) -> 4059 | AA11: =Input_Consumo_GrupoA!$E$8*(1+Premissas!$B$21) -> 9065.92
A12: BAT auto-comp. FP (kWh) | B12: =SUM(D12:AA12) -> 1202083.4 | C12: =B12/24 -> 50086.809 | D12: =MIN(D9,D10) -> 72286.9 | E12: =MIN(E9,E10) -> 88336.8 | F12: =MIN(F9,F10) -> 23364 | G12: =MIN(G9,G10) -> 10800 | H12: =MIN(H9,H10) -> 10800 | I12: =MIN(I9,I10) -> 10800 | J12: =MIN(J9,J10) -> 3402 | K12: =MIN(K9,K10) -> 113687.7 | ... AA12: =MIN(AA9,AA10) -> 81593.28
A13: BAT auto-comp. Ponta via FA (kWh) | B13: =SUM(D13:AA13) -> 45811.885 | C13: =B13/24 -> 1908.8285 | D13: =MIN((D9-D12)*Premissas!$B$8,D11) -> 0 | E13: =MIN((E9-E12)*Premissas!$B$8,E11) -> 0 | F13: =MIN((F9-F12)*Premissas!$B$8,F11) -> 2596 | G13: =MIN((G9-G12)*Premissas!$B$8,G11) -> 1200 | H13: =MIN((H9-H12)*Premissas!$B$8,H11) -> 1200 | I13: =MIN((I9-I12)*Premissas!$B$8,I11) -> 1200 | J13: =MIN((J9-J12)*Premissas!$B$8,J11) -> 378 | K13: =MIN((K9-K12)*Premissas!$B$8,K11) -> 0 | ... AA13: =MIN((AA9-AA12)*Premissas!$B$8,AA11) -> 5504.5371
A14: ★ BAT surplus líquido → rateio (kWh) | B14: =SUM(D14:AA14) -> 976535.01 | C14: =B14/24 -> 40688.959 | D14: =MAX(D9-D12-D11/Premissas!$B$8,0) -> 0 | E14: =MAX(E9-E12-E11/Premissas!$B$8,0) -> 0 | F14: =MAX(F9-F12-F11/Premissas!$B$8,0) -> 65422.586 | G14: =MAX(G9-G12-G11/Premissas!$B$8,0) -> 81647.523 | H14: =MAX(H9-H12-H11/Premissas!$B$8,0) -> 83120.923 | I14: =MAX(I9-I12-I11/Premissas!$B$8,0) -> 95194.723 | J14: =MAX(J9-J12-J11/Premissas!$B$8,0) -> 102576.35 | K14: =MAX(K9-K12-K11/Premissas!$B$8,0) -> 0 | ... AA14: =MAX(AA9-AA12-AA11/Premissas!$B$8,0) -> 0
A15: BAT banco stranded — depleção por consumo próprio apenas
A16: BAT banco início mês (kWh) | B16: =AA16 -> 582152.89 | C16: — | D16: =Premissas!$B$27 -> 906739 | E16: =D18 -> 886285.67 | F16: =E18 -> 837626.06 | G16: =F18 -> 837626.06 | H16: =G18 -> 837626.06 | I16: =H18 -> 837626.06 | J16: =I18 -> 837626.06 | K16: =J18 -> 837626.06 | L16: =K18 -> 813017.73 | ... AA16: =Z18 -> 582152.89
A17: BAT banco draw (kWh) | B17: =SUM(D17:AA17) -> 330479.83 | C17: =B17/24 -> 13769.993 | D17: =MIN(D16,MAX(D10-D12,0)+IF(Premissas!$B$8=0,0,MAX(D11-D13,0)/Premissas!$B$8)) -> 20453.327 | E17: =MIN(E16,MAX(E10-E12,0)+IF(Premissas!$B$8=0,0,MAX(E11-E13,0)/Premissas!$B$8)) -> 48659.609 | F17: =MIN(F16,MAX(F10-F12,0)+IF(Premissas!$B$8=0,0,MAX(F11-F13,0)/Premissas!$B$8)) -> 0 | G17: =MIN(G16,MAX(G10-G12,0)+IF(Premissas!$B$8=0,0,MAX(G11-G13,0)/Premissas!$B$8)) -> 0 | H17: =MIN(H16,MAX(H10-H12,0)+IF(Premissas!$B$8=0,0,MAX(H11-H13,0)/Premissas!$B$8)) -> 0 | I17: =MIN(I16,MAX(I10-I12,0)+IF(Premissas!$B$8=0,0,MAX(I11-I13,0)/Premissas!$B$8)) -> 0 | J17: =MIN(J16,MAX(J10-J12,0)+IF(Premissas!$B$8=0,0,MAX(J11-J13,0)/Premissas!$B$8)) -> 0 | K17: =MIN(K16,MAX(K10-K12,0)+IF(Premissas!$B$8=0,0,MAX(K11-K13,0)/Premissas!$B$8)) -> 24608.336 | ... AA17: =MIN(AA16,MAX(AA10-AA12,0)+IF(Premissas!$B$8=0,0,MAX(AA11-AA13,0)/Premissas!$B$8)) -> 5893.7235
A18: BAT banco fim mês (kWh) | B18: =AA18 -> 576259.17 | C18: — | D18: =MAX(D16-D17,0) -> 886285.67 | E18: =MAX(E16-E17,0) -> 837626.06 | F18: =MAX(F16-F17,0) -> 837626.06 | G18: =MAX(G16-G17,0) -> 837626.06 | H18: =MAX(H16-H17,0) -> 837626.06 | I18: =MAX(I16-I17,0) -> 837626.06 | J18: =MAX(J16-J17,0) -> 837626.06 | K18: =MAX(K16-K17,0) -> 813017.73 | ... AA18: =MAX(AA16-AA17,0) -> 576259.17
A19: BAT créditos → NHS (kWh, T+1) | B19: =SUM(D19:AA19) -> 488267.5 | C19: =B19/24 -> 20344.479 | D19: =0 -> 0 | E19: =D14*Premissas!$B$55 -> 0 | F19: =E14*Premissas!$B$55 -> 0 | G19: =F14*Premissas!$B$55 -> 32711.293 | H19: =G14*Premissas!$B$55 -> 40823.762 | I19: =H14*Premissas!$B$55 -> 41560.462 | J19: =I14*Premissas!$B$55 -> 47597.362 | K19: =J14*Premissas!$B$55 -> 51288.174 | L19: =K14*Premissas!$B$55 -> 0 | ... AA19: =Z14*Premissas!$B$55 -> 14863.108
A20: BAT créditos → AMD (kWh, T+1) | B20: =SUM(D20:AA20) -> 488267.5 | C20: =B20/24 -> 20344.479 | D20: =0 -> 0 | E20: =D14*Premissas!$B$56 -> 0 | F20: =E14*Premissas!$B$56 -> 0 | G20: =F14*Premissas!$B$56 -> 32711.293 | H20: =G14*Premissas!$B$56 -> 40823.762 | I20: =H14*Premissas!$B$56 -> 41560.462 | J20: =I14*Premissas!$B$56 -> 47597.362 | K20: =J14*Premissas!$B$56 -> 51288.174 | L20: =K14*Premissas!$B$56 -> 0 | ... AA20: =Z14*Premissas!$B$56 -> 14863.108
A21: NHS — N. Horizonte do Sul (A4V)
A22: Consumo FP (kWh) | B22: =SUM(D22:AA22) -> 3421650.5 | C22: =B22/24 -> 142568.77 | D22: =Input_Consumo_GrupoA!$B$9 -> 108694.9 | E22: =Input_Consumo_GrupoA!$B$10 -> 328938.1 | F22: =Input_Consumo_GrupoA!$B$11 -> 190977.6 | G22: =Input_Consumo_GrupoA!$B$12 -> 126478.8 | H22: =Input_Consumo_GrupoA!$B$13 -> 28215 | I22: =Input_Consumo_GrupoA!$B$14 -> 42209.6 | J22: =Input_Consumo_GrupoA!$B$15 -> 42209.6 | K22: =Input_Consumo_GrupoA!$B$4*(1+Premissas!$B$21) -> 72539.147 | L22: =Input_Consumo_GrupoA!$B$5*(1+Premissas!$B$21) -> 249812.69 | M22: =Input_Consumo_GrupoA!$B$6*(1+Premissas!$B$21) -> 340170.95 | N22: =Input_Consumo_GrupoA!$B$7*(1+Premissas!$B$21) -> 105347.76 | O22: =Input_Consumo_GrupoA!$B$8*(1+Premissas!$B$21) -> 64384.555 | P22: =Input_Consumo_GrupoA!$B$9*(1+Premissas!$B$21) -> 111412.27 | Q22: =Input_Consumo_GrupoA!$B$10*(1+Premissas!$B$21) -> 337161.55 | R22: =Input_Consumo_GrupoA!$B$11*(1+Premissas!$B$21) -> 195752.04 | S22: =Input_Consumo_GrupoA!$B$12*(1+Premissas!$B$21) -> 129640.77 | T22: =Input_Consumo_GrupoA!$B$13*(1+Premissas!$B$21) -> 28920.375 | U22: =Input_Consumo_GrupoA!$B$14*(1+Premissas!$B$21) -> 43264.84 | V22: =Input_Consumo_GrupoA!$B$15*(1+Premissas!$B$21) -> 43264.84 | W22: =Input_Consumo_GrupoA!$B$4*(1+Premissas!$B$21) -> 72539.147 | X22: =Input_Consumo_GrupoA!$B$5*(1+Premissas!$B$21) -> 249812.69 | Y22: =Input_Consumo_GrupoA!$B$6*(1+Premissas!$B$21) -> 340170.95 | Z22: =Input_Consumo_GrupoA!$B$7*(1+Premissas!$B$21) -> 105347.76 | AA22: =Input_Consumo_GrupoA!$B$8*(1+Premissas!$B$21) -> 64384.555
A23: Consumo Ponta (kWh) [via FA] | B23: =SUM(D23:AA23) -> 380183.62 | C23: =B23/24 -> 15840.984 | D23: =Input_Consumo_GrupoA!$C$9 -> 12077.2 | E23: =Input_Consumo_GrupoA!$C$10 -> 36548.7 | F23: =Input_Consumo_GrupoA!$C$11 -> 21219.7 | G23: =Input_Consumo_GrupoA!$C$12 -> 14053.2 | H23: =Input_Consumo_GrupoA!$C$13 -> 3135 | I23: =Input_Consumo_GrupoA!$C$14 -> 4690 | J23: =Input_Consumo_GrupoA!$C$15 -> 4690 | K23: =Input_Consumo_GrupoA!$C$4*(1+Premissas!$B$21) -> 8059.8825 | L23: =Input_Consumo_GrupoA!$C$5*(1+Premissas!$B$21) -> 27757 | M23: =Input_Consumo_GrupoA!$C$6*(1+Premissas!$B$21) -> 37796.772 | N23: =Input_Consumo_GrupoA!$C$7*(1+Premissas!$B$21) -> 11705.295 | O23: =Input_Consumo_GrupoA!$C$8*(1+Premissas!$B$21) -> 7153.885 | P23: =Input_Consumo_GrupoA!$C$9*(1+Premissas!$B$21) -> 12379.13 | Q23: =Input_Consumo_GrupoA!$C$10*(1+Premissas!$B$21) -> 37462.417 | R23: =Input_Consumo_GrupoA!$C$11*(1+Premissas!$B$21) -> 21750.192 | S23: =Input_Consumo_GrupoA!$C$12*(1+Premissas!$B$21) -> 14404.53 | T23: =Input_Consumo_GrupoA!$C$13*(1+Premissas!$B$21) -> 3213.375 | U23: =Input_Consumo_GrupoA!$C$14*(1+Premissas!$B$21) -> 4807.25 | V23: =Input_Consumo_GrupoA!$C$15*(1+Premissas!$B$21) -> 4807.25 | W23: =Input_Consumo_GrupoA!$C$4*(1+Premissas!$B$21) -> 8059.8825 | X23: =Input_Consumo_GrupoA!$C$5*(1+Premissas!$B$21) -> 27757 | Y23: =Input_Consumo_GrupoA!$C$6*(1+Premissas!$B$21) -> 37796.772 | Z23: =Input_Consumo_GrupoA!$C$7*(1+Premissas!$B$21) -> 11705.295 | AA23: =Input_Consumo_GrupoA!$C$8*(1+Premissas!$B$21) -> 7153.885
A24: Geração própria (kWh) | B24: =SUM(D24:AA24) -> 1867755.1 | C24: =B24/24 -> 77823.131 | D24: =+'Novo Horizonte do Sul'!I8 -> 60380.6 | E24: =+'Novo Horizonte do Sul'!I9 -> 76551.2 | F24: =+'Novo Horizonte do Sul'!I10 -> 79815.6 | G24: =+'Novo Horizonte do Sul'!I11 -> 78203 | H24: =+'Novo Horizonte do Sul'!I12 -> 73160.1 | I24: =+'Novo Horizonte do Sul'!I13 -> 91030.5 | J24: =+'Novo Horizonte do Sul'!I14 -> 88631.7 | K24: =+'Novo Horizonte do Sul'!I3*(1-Premissas!$B$23) -> 83044.59 | L24: =+'Novo Horizonte do Sul'!I4*(1-Premissas!$B$23) -> 75743.778 | M24: =+'Novo Horizonte do Sul'!I5*(1-Premissas!$B$23) -> 89408.909 | N24: =+'Novo Horizonte do Sul'!I6*(1-Premissas!$B$23) -> 62411.773 | O24: =+'Novo Horizonte do Sul'!I7*(1-Premissas!$B$23) -> 77836.363 | P24: =D24*(1-Premissas!$B$23) -> 60078.697 | Q24: =E24*(1-Premissas!$B$23) -> 76168.444 | R24: =F24*(1-Premissas!$B$23) -> 79416.522 | S24: =G24*(1-Premissas!$B$23) -> 77811.985 | T24: =H24*(1-Premissas!$B$23) -> 72794.299 | U24: =I24*(1-Premissas!$B$23) -> 90575.348 | V24: =J24*(1-Premissas!$B$23) -> 88188.541 | W24: =K24*(1-Premissas!$B$23) -> 82629.368 | ... AA24: =O24*(1-Premissas!$B$23) -> 77447.181
A25: Auto-comp. FP (kWh) | B25: =SUM(D25:AA25) -> 1544348.8 | C25: =B25/24 -> 64347.867 | D25: =MIN(D24,D22) -> 60380.6 | E25: =MIN(E24,E22) -> 76551.2 | F25: =MIN(F24,F22) -> 79815.6 | G25: =MIN(G24,G22) -> 78203 | H25: =MIN(H24,H22) -> 28215 | I25: =MIN(I24,I22) -> 42209.6 | J25: =MIN(J24,J22) -> 42209.6 | K25: =MIN(K24,K22) -> 72539.147 | ... AA25: =MIN(AA24,AA22) -> 64384.555
A26: Auto-comp. Ponta via FA (kWh) | B26: =SUM(D26:AA26) -> 52095.926 | C26: =B26/24 -> 2170.6636 | D26: =MIN((D24-D25)*Premissas!$B$8,D23) -> 0 | E26: =MIN((E24-E25)*Premissas!$B$8,E23) -> 0 | F26: =MIN((F24-F25)*Premissas!$B$8,F23) -> 0 | G26: =MIN((G24-G25)*Premissas!$B$8,G23) -> 0 | H26: =MIN((H24-H25)*Premissas!$B$8,H23) -> 3135 | I26: =MIN((I24-I25)*Premissas!$B$8,I23) -> 4690 | J26: =MIN((J24-J25)*Premissas!$B$8,J23) -> 4690 | K26: =MIN((K24-K25)*Premissas!$B$8,K23) -> 6348.093 | ... AA26: =MIN((AA24-AA25)*Premissas!$B$8,AA23) -> 7153.885
A27: =" "&INDEX(PVSYST_Helexia!$A$5:$A$7,MATCH(Premissas!$B$13,PVSYST_Helexia!$B$5:$B$7,0))&" créditos recebidos (kWh)" -> HCS03 créditos recebidos (kWh) | B27: =SUM(D27:AA27) -> 1740466.8 | C27: =B27/24 -> 72519.451 | D27: =D6*Premissas!$B$33 -> 91141.827 | E27: =E6*Premissas!$B$33 -> 95934.51 | F27: =F6*Premissas!$B$33 -> 115164.05 | G27: =G6*Premissas!$B$33 -> 108063.23 | H27: =H6*Premissas!$C$33 -> 79419.771 | I27: =I6*Premissas!$C$33 -> 76791.37 | J27: =J6*Premissas!$C$33 -> 72917.106 | K27: =K6*Premissas!$C$33 -> 74869.64 | L27: =L6*Premissas!$C$33 -> 66715.262 | M27: =M6*Premissas!$C$33 -> 76522.484 | N27: =N6*Premissas!$D$33 -> 98138.237 | O27: =O6*Premissas!$D$33 -> 91845.773 | P27: =P6*Premissas!$D$33 -> 83354.98 | Q27: =Q6*Premissas!$D$33 -> 87738.192 | R27: =R6*Premissas!$D$33 -> 105324.82 | S27: =S6*Premissas!$D$33 -> 98830.677 | T27: =T6*Premissas!$E$33 -> 42271.278 | U27: =U6*Premissas!$E$33 -> 40872.308 | V27: =V6*Premissas!$E$33 -> 38810.226 | W27: =W6*Premissas!$E$33 -> 40049.713 | X27: =X6*Premissas!$E$33 -> 35687.725 | Y27: =Y6*Premissas!$E$33 -> 40933.862 | Z27: =Z6*Premissas!$E$33 -> 40844.328 | AA27: =AA6*Premissas!$E$33 -> 38225.456
A28: BAT créditos → NHS (kWh) | B28: =SUM(D28:AA28) -> 488267.5 | C28: =B28/24 -> 20344.479 | D28: =D19 -> 0 | E28: =E19 -> 0 | F28: =F19 -> 0 | G28: =G19 -> 32711.293 | H28: =H19 -> 40823.762 | I28: =I19 -> 41560.462 | J28: =J19 -> 47597.362 | K28: =K19 -> 51288.174 | ... AA28: =AA19 -> 14863.108
A29: Banco início mês COM Helexia (kWh) | B29: =AA29 -> 297241.61 | C29: — | D29: =Premissas!$B$26 -> 148516 | E29: =D31 -> 171357 | F29: =E31 -> 0 | G29: =F31 -> 4002.0458 | H29: =G31 -> 92498.724 | I29: =H31 -> 257687.36 | J29: =I31 -> 424860.09 | K29: =J31 -> 591796.66 | L29: =K31 -> 725627.08 | ... AA29: =Z31 -> 297241.61
A30: Bank draw COM Helexia (kWh) | B30: =SUM(D30:AA30) -> 1433712.2 | C30: =B30/24 -> 59738.009 | D30: =MIN(D29,MAX(D22-D24-D27+D28,0)+IF(Premissas!$B$8=0,0,MAX(D23-D26,0)/Premissas!$B$8)) -> 19986.528 | E30: =MIN(E29,MAX(E22-E24-E27+E28,0)+IF(Premissas!$B$8=0,0,MAX(E23-E26,0)/Premissas!$B$8)) -> 171357 | F30: =MIN(F29,MAX(F22-F24-F27+F28,0)+IF(Premissas!$B$8=0,0,MAX(F23-F26,0)/Premissas!$B$8)) -> 0 | G30: =MIN(G29,MAX(G22-G24-G27+G28,0)+IF(Premissas!$B$8=0,0,MAX(G23-G26,0)/Premissas!$B$8)) -> 4002.0458 | H30: =MIN(H29,MAX(H22-H24-H27+H28,0)+IF(Premissas!$B$8=0,0,MAX(H23-H26,0)/Premissas!$B$8)) -> 0 | I30: =MIN(I29,MAX(I22-I24-I27+I28,0)+IF(Premissas!$B$8=0,0,MAX(I23-I26,0)/Premissas!$B$8)) -> 0 | J30: =MIN(J29,MAX(J22-J24-J27+J28,0)+IF(Premissas!$B$8=0,0,MAX(J23-J26,0)/Premissas!$B$8)) -> 0 | K30: =MIN(K29,MAX(K22-K24-K27+K28,0)+IF(Premissas!$B$8=0,0,MAX(K23-K26,0)/Premissas!$B$8)) -> 2832.836 | ... AA30: =MIN(AA29,MAX(AA22-AA24-AA27+AA28,0)+IF(Premissas!$B$8=0,0,MAX(AA23-AA26,0)/Premissas!$B$8)) -> 0
A31: ★ Banco fim mês COM Helexia (kWh) | B31: =AA31 -> 363392.8 | C31: — | D31: =MAX(D29-D30,0)+D28+MAX(D27-MAX(D22-D24,0),0)+MAX(D24-D22,0) -> 171357 | E31: =MAX(E29-E30,0)+E28+MAX(E27-MAX(E22-E24,0),0)+MAX(E24-E22,0) -> 0 | F31: =MAX(F29-F30,0)+F28+MAX(F27-MAX(F22-F24,0),0)+MAX(F24-F22,0) -> 4002.0458 | G31: =MAX(G29-G30,0)+G28+MAX(G27-MAX(G22-G24,0),0)+MAX(G24-G22,0) -> 92498.724 | H31: =MAX(H29-H30,0)+H28+MAX(H27-MAX(H22-H24,0),0)+MAX(H24-H22,0) -> 257687.36 | I31: =MAX(I29-I30,0)+I28+MAX(I27-MAX(I22-I24,0),0)+MAX(I24-I22,0) -> 424860.09 | J31: =MAX(J29-J30,0)+J28+MAX(J27-MAX(J22-J24,0),0)+MAX(J24-J22,0) -> 591796.66 | K31: =MAX(K29-K30,0)+K28+MAX(K27-MAX(K22-K24,0),0)+MAX(K24-K22,0) -> 725627.08 | ... AA31: =MAX(AA29-AA30,0)+AA28+MAX(AA27-MAX(AA22-AA24,0),0)+MAX(AA24-AA22,0) -> 363392.8
A32: Banco início mês SEM Helexia (kWh) | B32: =AA32 -> 16130.024 | C32: — | D32: =Premissas!$B$26 -> 148516 | E32: =D34 -> 80215.172 | F32: =E34 -> 0 | G32: =F34 -> 0 | H32: =G34 -> 32711.293 | I32: =H34 -> 118480.15 | J32: =I34 -> 208861.52 | K32: =J34 -> 302880.98 | L32: =K34 -> 364674.6 | ... AA32: =Z34 -> 16130.024
A33: Bank draw SEM Helexia (kWh) — gen+BAT, no CS3 | B33: =SUM(D33:AA33) -> 916134.08 | C33: =B33/24 -> 38172.253 | D33: =MIN(D32,MAX(D22-D24-D28,0)+IF(Premissas!$B$8=0,0,MAX(D23-D26-(IF(Premissas!$B$8>0,MAX(D24-D22,0)*Premissas!$B$8,0)),0)/Premissas!$B$8)) -> 68300.828 | E33: =MIN(E32,MAX(E22-E24-E28,0)+IF(Premissas!$B$8=0,0,MAX(E23-E26-(IF(Premissas!$B$8>0,MAX(E24-E22,0)*Premissas!$B$8,0)),0)/Premissas!$B$8)) -> 80215.172 | F33: =MIN(F32,MAX(F22-F24-F28,0)+IF(Premissas!$B$8=0,0,MAX(F23-F26-(IF(Premissas!$B$8>0,MAX(F24-F22,0)*Premissas!$B$8,0)),0)/Premissas!$B$8)) -> 0 | G33: =MIN(G32,MAX(G22-G24-G28,0)+IF(Premissas!$B$8=0,0,MAX(G23-G26-(IF(Premissas!$B$8>0,MAX(G24-G22,0)*Premissas!$B$8,0)),0)/Premissas!$B$8)) -> 0 | H33: =MIN(H32,MAX(H22-H24-H28,0)+IF(Premissas!$B$8=0,0,MAX(H23-H26-(IF(Premissas!$B$8>0,MAX(H24-H22,0)*Premissas!$B$8,0)),0)/Premissas!$B$8)) -> 0 | I33: =MIN(I32,MAX(I22-I24-I28,0)+IF(Premissas!$B$8=0,0,MAX(I23-I26-(IF(Premissas!$B$8>0,MAX(I24-I22,0)*Premissas!$B$8,0)),0)/Premissas!$B$8)) -> 0 | J33: =MIN(J32,MAX(J22-J24-J28,0)+IF(Premissas!$B$8=0,0,MAX(J23-J26-(IF(Premissas!$B$8>0,MAX(J24-J22,0)*Premissas!$B$8,0)),0)/Premissas!$B$8)) -> 0 | K33: =MIN(K32,MAX(K22-K24-K28,0)+IF(Premissas!$B$8=0,0,MAX(K23-K26-(IF(Premissas!$B$8>0,MAX(K24-K22,0)*Premissas!$B$8,0)),0)/Premissas!$B$8)) -> 0 | ... AA33: =MIN(AA32,MAX(AA22-AA24-AA28,0)+IF(Premissas!$B$8=0,0,MAX(AA23-AA26-(IF(Premissas!$B$8>0,MAX(AA24-AA22,0)*Premissas!$B$8,0)),0)/Premissas!$B$8)) -> 0
A34: Banco fim mês SEM Helexia (kWh) — gen+BAT, no CS3 | B34: =AA34 -> 44055.758 | C34: — | D34: =MAX(D32-D33,0)+D28+MAX(D24-D22,0) -> 80215.172 | E34: =MAX(E32-E33,0)+E28+MAX(E24-E22,0) -> 0 | F34: =MAX(F32-F33,0)+F28+MAX(F24-F22,0) -> 0 | G34: =MAX(G32-G33,0)+G28+MAX(G24-G22,0) -> 32711.293 | H34: =MAX(H32-H33,0)+H28+MAX(H24-H22,0) -> 118480.15 | I34: =MAX(I32-I33,0)+I28+MAX(I24-I22,0) -> 208861.52 | J34: =MAX(J32-J33,0)+J28+MAX(J24-J22,0) -> 302880.98 | K34: =MAX(K32-K33,0)+K28+MAX(K24-K22,0) -> 364674.6 | ... AA34: =MAX(AA32-AA33,0)+AA28+MAX(AA24-AA22,0) -> 44055.758
A35: =" Custo SEM Helexia (R$) — só gen própria, sem "&INDEX(PVSYST_Helexia!$A$5:$A$7,MATCH(Premissas!$B$13,PVSYST_Helexia!$B$5:$B$7,0))&"/BAT/banco" -> Custo SEM Helexia (R$) — só gen própria, sem HCS03/BAT/banco | B35: =SUM(D35:AA35) -> 1076040.7 | C35: =B35/24 -> 44835.031 | D35: =IF(D34>0,0,MAX(D22-D24-D28-D32,0)*Premissas!$B$5+MAX(D23-D26-(IF(Premissas!$B$8>0,MAX(D24+D28+D32-D22,0)*Premissas!$B$8,0)),0)*Premissas!$B$6) -> 0 | E35: =IF(E34>0,0,MAX(E22-E24-E28-E32,0)*Premissas!$B$5+MAX(E23-E26-(IF(Premissas!$B$8>0,MAX(E24+E28+E32-E22,0)*Premissas!$B$8,0)),0)*Premissas!$B$6) -> 199280.04 | F35: =IF(F34>0,0,MAX(F22-F24-F28-F32,0)*Premissas!$B$5+MAX(F23-F26-(IF(Premissas!$B$8>0,MAX(F24+F28+F32-F22,0)*Premissas!$B$8,0)),0)*Premissas!$B$6) -> 121596.58 | G35: =IF(G34>0,0,MAX(G22-G24-G28-G32,0)*Premissas!$B$5+MAX(G23-G26-(IF(Premissas!$B$8>0,MAX(G24+G28+G32-G22,0)*Premissas!$B$8,0)),0)*Premissas!$B$6) -> 0 | H35: =IF(H34>0,0,MAX(H22-H24-H28-H32,0)*Premissas!$B$5+MAX(H23-H26-(IF(Premissas!$B$8>0,MAX(H24+H28+H32-H22,0)*Premissas!$B$8,0)),0)*Premissas!$B$6) -> 0 | I35: =IF(I34>0,0,MAX(I22-I24-I28-I32,0)*Premissas!$B$5+MAX(I23-I26-(IF(Premissas!$B$8>0,MAX(I24+I28+I32-I22,0)*Premissas!$B$8,0)),0)*Premissas!$B$6) -> 0 | J35: =IF(J34>0,0,MAX(J22-J24-J28-J32,0)*Premissas!$B$5+MAX(J23-J26-(IF(Premissas!$B$8>0,MAX(J24+J28+J32-J22,0)*Premissas!$B$8,0)),0)*Premissas!$B$6) -> 0 | K35: =IF(K34>0,0,MAX(K22-K24-K28-K32,0)*Premissas!$B$5+MAX(K23-K26-(IF(Premissas!$B$8>0,MAX(K24+K28+K32-K22,0)*Premissas!$B$8,0)),0)*Premissas!$B$6) -> 0 | ... AA35: =IF(AA34>0,0,MAX(AA22-AA24-AA28-AA32,0)*Premissas!$B$5+MAX(AA23-AA26-(IF(Premissas!$B$8>0,MAX(AA24+AA28+AA32-AA22,0)*Premissas!$B$8,0)),0)*Premissas!$B$6) -> 0
A36: Custo COM Helexia — rede remanescente (R$) | B36: =SUM(D36:AA36) -> 81866.272 | C36: =B36/24 -> 3411.0947 | D36: =IF(D31>0,0,MAX(D22-D24-D27+D28-D29,0)*Premissas!$B$5+MAX(D23-D26-(IF(Premissas!$B$8>0,MAX(D24+D27+D28+D29-D22,0)*Premissas!$B$8,0)),0)*Premissas!$B$6) -> 0 | E36: =IF(E31>0,0,MAX(E22-E24-E27+E28-E29,0)*Premissas!$B$5+MAX(E23-E26-(IF(Premissas!$B$8>0,MAX(E24+E27+E28+E29-E22,0)*Premissas!$B$8,0)),0)*Premissas!$B$6) -> 81866.272 | F36: =IF(F31>0,0,MAX(F22-F24-F27+F28-F29,0)*Premissas!$B$5+MAX(F23-F26-(IF(Premissas!$B$8>0,MAX(F24+F27+F28+F29-F22,0)*Premissas!$B$8,0)),0)*Premissas!$B$6) -> 0 | G36: =IF(G31>0,0,MAX(G22-G24-G27+G28-G29,0)*Premissas!$B$5+MAX(G23-G26-(IF(Premissas!$B$8>0,MAX(G24+G27+G28+G29-G22,0)*Premissas!$B$8,0)),0)*Premissas!$B$6) -> 0 | H36: =IF(H31>0,0,MAX(H22-H24-H27+H28-H29,0)*Premissas!$B$5+MAX(H23-H26-(IF(Premissas!$B$8>0,MAX(H24+H27+H28+H29-H22,0)*Premissas!$B$8,0)),0)*Premissas!$B$6) -> 0 | I36: =IF(I31>0,0,MAX(I22-I24-I27+I28-I29,0)*Premissas!$B$5+MAX(I23-I26-(IF(Premissas!$B$8>0,MAX(I24+I27+I28+I29-I22,0)*Premissas!$B$8,0)),0)*Premissas!$B$6) -> 0 | J36: =IF(J31>0,0,MAX(J22-J24-J27+J28-J29,0)*Premissas!$B$5+MAX(J23-J26-(IF(Premissas!$B$8>0,MAX(J24+J27+J28+J29-J22,0)*Premissas!$B$8,0)),0)*Premissas!$B$6) -> 0 | K36: =IF(K31>0,0,MAX(K22-K24-K27+K28-K29,0)*Premissas!$B$5+MAX(K23-K26-(IF(Premissas!$B$8>0,MAX(K24+K27+K28+K29-K22,0)*Premissas!$B$8,0)),0)*Premissas!$B$6) -> 0 | ... AA36: =IF(AA31>0,0,MAX(AA22-AA24-AA27+AA28-AA29,0)*Premissas!$B$5+MAX(AA23-AA26-(IF(Premissas!$B$8>0,MAX(AA24+AA27+AA28+AA29-AA22,0)*Premissas!$B$8,0)),0)*Premissas!$B$6) -> 0
A37: ★ Economia mensal (R$) | B37: =SUM(D37:AA37) -> 994174.47 | C37: =B37/24 -> 41423.936 | D37: =MAX(D35-D36,0) -> 0 | E37: =MAX(E35-E36,0) -> 117413.77 | F37: =MAX(F35-F36,0) -> 121596.58 | G37: =MAX(G35-G36,0) -> 0 | H37: =MAX(H35-H36,0) -> 0 | I37: =MAX(I35-I36,0) -> 0 | J37: =MAX(J35-J36,0) -> 0 | K37: =MAX(K35-K36,0) -> 0 | ... AA37: =MAX(AA35-AA36,0) -> 0
A39: AMD — Amandina (A3A)
A40: Consumo FP (kWh) | B40: =SUM(D40:AA40) -> 2588129.8 | C40: =B40/24 -> 107838.74 | D40: =Input_Consumo_GrupoA!$F$9 -> 182444.7 | E40: =Input_Consumo_GrupoA!$F$10 -> 234799.2 | F40: =Input_Consumo_GrupoA!$F$11 -> 134799.3 | G40: =Input_Consumo_GrupoA!$F$12 -> 18637.2 | H40: =Input_Consumo_GrupoA!$F$13 -> 24382.8 | I40: =Input_Consumo_GrupoA!$F$14 -> 20225.7 | J40: =Input_Consumo_GrupoA!$F$15 -> 17142.3 | K40: =Input_Consumo_GrupoA!$F$4*(1+Premissas!$B$21) -> 75822.735 | L40: =Input_Consumo_GrupoA!$F$5*(1+Premissas!$B$21) -> 214709.01 | M40: =Input_Consumo_GrupoA!$F$6*(1+Premissas!$B$21) -> 177591.7 | N40: =Input_Consumo_GrupoA!$F$7*(1+Premissas!$B$21) -> 80409.61 | O40: =Input_Consumo_GrupoA!$F$8*(1+Premissas!$B$21) -> 105195.24 | P40: =Input_Consumo_GrupoA!$F$9*(1+Premissas!$B$21) -> 187005.82 | Q40: =Input_Consumo_GrupoA!$F$10*(1+Premissas!$B$21) -> 240669.18 | R40: =Input_Consumo_GrupoA!$F$11*(1+Premissas!$B$21) -> 138169.28 | S40: =Input_Consumo_GrupoA!$F$12*(1+Premissas!$B$21) -> 19103.13 | T40: =Input_Consumo_GrupoA!$F$13*(1+Premissas!$B$21) -> 24992.37 | U40: =Input_Consumo_GrupoA!$F$14*(1+Premissas!$B$21) -> 20731.342 | V40: =Input_Consumo_GrupoA!$F$15*(1+Premissas!$B$21) -> 17570.857 | W40: =Input_Consumo_GrupoA!$F$4*(1+Premissas!$B$21) -> 75822.735 | X40: =Input_Consumo_GrupoA!$F$5*(1+Premissas!$B$21) -> 214709.01 | Y40: =Input_Consumo_GrupoA!$F$6*(1+Premissas!$B$21) -> 177591.7 | Z40: =Input_Consumo_GrupoA!$F$7*(1+Premissas!$B$21) -> 80409.61 | AA40: =Input_Consumo_GrupoA!$F$8*(1+Premissas!$B$21) -> 105195.24
A41: Consumo Ponta (kWh) [via FA] | B41: =SUM(D41:AA41) -> 287570 | C41: =B41/24 -> 11982.083 | D41: =Input_Consumo_GrupoA!$G$9 -> 20271.6 | E41: =Input_Consumo_GrupoA!$G$10 -> 26088.8 | F41: =Input_Consumo_GrupoA!$G$11 -> 14977.7 | G41: =Input_Consumo_GrupoA!$G$12 -> 2070.8 | H41: =Input_Consumo_GrupoA!$G$13 -> 2709.2 | I41: =Input_Consumo_GrupoA!$G$14 -> 2247.3 | J41: =Input_Consumo_GrupoA!$G$15 -> 1904.7 | K41: =Input_Consumo_GrupoA!$G$4*(1+Premissas!$B$21) -> 8424.7825 | L41: =Input_Consumo_GrupoA!$G$5*(1+Premissas!$B$21) -> 23856.567 | M41: =Input_Consumo_GrupoA!$G$6*(1+Premissas!$B$21) -> 19732.377 | N41: =Input_Consumo_GrupoA!$G$7*(1+Premissas!$B$21) -> 8934.4125 | O41: =Input_Consumo_GrupoA!$G$8*(1+Premissas!$B$21) -> 11688.382 | P41: =Input_Consumo_GrupoA!$G$9*(1+Premissas!$B$21) -> 20778.39 | Q41: =Input_Consumo_GrupoA!$G$10*(1+Premissas!$B$21) -> 26741.02 | R41: =Input_Consumo_GrupoA!$G$11*(1+Premissas!$B$21) -> 15352.142 | S41: =Input_Consumo_GrupoA!$G$12*(1+Premissas!$B$21) -> 2122.57 | T41: =Input_Consumo_GrupoA!$G$13*(1+Premissas!$B$21) -> 2776.93 | U41: =Input_Consumo_GrupoA!$G$14*(1+Premissas!$B$21) -> 2303.4825 | V41: =Input_Consumo_GrupoA!$G$15*(1+Premissas!$B$21) -> 1952.3175 | W41: =Input_Consumo_GrupoA!$G$4*(1+Premissas!$B$21) -> 8424.7825 | X41: =Input_Consumo_GrupoA!$G$5*(1+Premissas!$B$21) -> 23856.567 | Y41: =Input_Consumo_GrupoA!$G$6*(1+Premissas!$B$21) -> 19732.377 | Z41: =Input_Consumo_GrupoA!$G$7*(1+Premissas!$B$21) -> 8934.4125 | AA41: =Input_Consumo_GrupoA!$G$8*(1+Premissas!$B$21) -> 11688.382
A42: Geração própria (kWh) | B42: =SUM(D42:AA42) -> 1805431.6 | C42: =B42/24 -> 75226.315 | D42: =IF(Premissas!$B$24="Sim",Amandina!$L$8*1000,Amandina!$I$8) -> 57829.52 | E42: =IF(Premissas!$B$24="Sim",Amandina!$L$9*1000,Amandina!$I$9) -> 70669.44 | F42: =IF(Premissas!$B$24="Sim",Amandina!$L$10*1000,Amandina!$I$10) -> 74466.16 | G42: =IF(Premissas!$B$24="Sim",Amandina!$L$11*1000,Amandina!$I$11) -> 75546.72 | H42: =IF(Premissas!$B$24="Sim",Amandina!$L$12*1000,Amandina!$I$12) -> 76725.44 | I42: =IF(Premissas!$B$24="Sim",Amandina!$L$13*1000,Amandina!$I$13) -> 86384.48 | J42: =IF(Premissas!$B$24="Sim",Amandina!$L$14*1000,Amandina!$I$14) -> 85283.12 | K42: =IF(Premissas!$B$24="Sim",Amandina!$L$3*1000*(1-Premissas!$B$23),Amandina!$I$3*(1-Premissas!$B$23)) -> 90950.164 | L42: =IF(Premissas!$B$24="Sim",Amandina!$L$4*1000*(1-Premissas!$B$23),Amandina!$I$4*(1-Premissas!$B$23)) -> 72540.992 | M42: =IF(Premissas!$B$24="Sim",Amandina!$L$5*1000*(1-Premissas!$B$23),Amandina!$I$5*(1-Premissas!$B$23)) -> 82037.272 | N42: =IF(Premissas!$B$24="Sim",Amandina!$L$6*1000*(1-Premissas!$B$23),Amandina!$I$6*(1-Premissas!$B$23)) -> 58672.921 | O42: =IF(Premissas!$B$24="Sim",Amandina!$L$7*1000*(1-Premissas!$B$23),Amandina!$I$7*(1-Premissas!$B$23)) -> 72926.814 | P42: =IF(Premissas!$B$24="Sim",Amandina!$L$8*1000*(1-Premissas!$B$23),Amandina!$I$8*(1-Premissas!$B$23)) -> 57540.372 | Q42: =IF(Premissas!$B$24="Sim",Amandina!$L$9*1000*(1-Premissas!$B$23),Amandina!$I$9*(1-Premissas!$B$23)) -> 70316.093 | R42: =IF(Premissas!$B$24="Sim",Amandina!$L$10*1000*(1-Premissas!$B$23),Amandina!$I$10*(1-Premissas!$B$23)) -> 74093.829 | S42: =IF(Premissas!$B$24="Sim",Amandina!$L$11*1000*(1-Premissas!$B$23),Amandina!$I$11*(1-Premissas!$B$23)) -> 75168.986 | T42: =IF(Premissas!$B$24="Sim",Amandina!$L$12*1000*(1-Premissas!$B$23),Amandina!$I$12*(1-Premissas!$B$23)) -> 76341.813 | U42: =IF(Premissas!$B$24="Sim",Amandina!$L$13*1000*(1-Premissas!$B$23),Amandina!$I$13*(1-Premissas!$B$23)) -> 85952.558 | V42: =IF(Premissas!$B$24="Sim",Amandina!$L$14*1000*(1-Premissas!$B$23),Amandina!$I$14*(1-Premissas!$B$23)) -> 84856.704 | W42: =IF(Premissas!$B$24="Sim",Amandina!$L$3*1000*(1-Premissas!$B$23),Amandina!$I$3*(1-Premissas!$B$23)) -> 90950.164 | X42: =IF(Premissas!$B$24="Sim",Amandina!$L$4*1000*(1-Premissas!$B$23),Amandina!$I$4*(1-Premissas!$B$23)) -> 72540.992 | Y42: =IF(Premissas!$B$24="Sim",Amandina!$L$5*1000*(1-Premissas!$B$23),Amandina!$I$5*(1-Premissas!$B$23)) -> 82037.272 | Z42: =IF(Premissas!$B$24="Sim",Amandina!$L$6*1000*(1-Premissas!$B$23),Amandina!$I$6*(1-Premissas!$B$23)) -> 58672.921 | AA42: =IF(Premissas!$B$24="Sim",Amandina!$L$7*1000*(1-Premissas!$B$23),Amandina!$I$7*(1-Premissas!$B$23)) -> 72926.814
A43: Auto-comp. FP (kWh) | B43: =SUM(D43:AA43) -> 1291702.6 | C43: =B43/24 -> 53820.941 | D43: =MIN(D42,D40) -> 57829.52 | E43: =MIN(E42,E40) -> 70669.44 | F43: =MIN(F42,F40) -> 74466.16 | G43: =MIN(G42,G40) -> 18637.2 | H43: =MIN(H42,H40) -> 24382.8 | I43: =MIN(I42,I40) -> 20225.7 | J43: =MIN(J42,J40) -> 17142.3 | K43: =MIN(K42,K40) -> 75822.735 | ... AA43: =MIN(AA42,AA40) -> 72926.814
A44: Auto-comp. Ponta via FA (kWh) | B44: =SUM(D44:AA44) -> 34936.865 | C44: =B44/24 -> 1455.7027 | D44: =MIN((D42-D43)*Premissas!$B$8,D41) -> 0 | E44: =MIN((E42-E43)*Premissas!$B$8,E41) -> 0 | F44: =MIN((F42-F43)*Premissas!$B$8,F41) -> 0 | G44: =MIN((G42-G43)*Premissas!$B$8,G41) -> 2070.8 | H44: =MIN((H42-H43)*Premissas!$B$8,H41) -> 2709.2 | I44: =MIN((I42-I43)*Premissas!$B$8,I41) -> 2247.3 | J44: =MIN((J42-J43)*Premissas!$B$8,J41) -> 1904.7 | K44: =MIN((K42-K43)*Premissas!$B$8,K41) -> 8424.7825 | ... AA44: =MIN((AA42-AA43)*Premissas!$B$8,AA41) -> 0
A45: =" "&INDEX(PVSYST_Helexia!$A$5:$A$7,MATCH(Premissas!$B$13,PVSYST_Helexia!$B$5:$B$7,0))&" créditos recebidos (kWh)" -> HCS03 créditos recebidos (kWh) | B45: =SUM(D45:AA45) -> 179791.23 | C45: =B45/24 -> 7491.3011 | D45: =D6*Premissas!$B$35 -> 0 | E45: =E6*Premissas!$B$35 -> 0 | F45: =F6*Premissas!$B$35 -> 0 | G45: =G6*Premissas!$B$35 -> 0 | H45: =H6*Premissas!$C$35 -> 0 | I45: =I6*Premissas!$C$35 -> 0 | J45: =J6*Premissas!$C$35 -> 0 | K45: =K6*Premissas!$C$35 -> 0 | L45: =L6*Premissas!$C$35 -> 0 | M45: =M6*Premissas!$C$35 -> 0 | N45: =N6*Premissas!$D$35 -> 588.89151 | O45: =O6*Premissas!$D$35 -> 551.13274 | P45: =P6*Premissas!$D$35 -> 500.18261 | Q45: =Q6*Premissas!$D$35 -> 526.48466 | R45: =R6*Premissas!$D$35 -> 632.01557 | S45: =S6*Premissas!$D$35 -> 593.04659 | T45: =T6*Premissas!$E$35 -> 23471.045 | U45: =U6*Premissas!$E$35 -> 22694.269 | V45: =V6*Premissas!$E$35 -> 21549.302 | W45: =W6*Premissas!$E$35 -> 22237.525 | X45: =X6*Premissas!$E$35 -> 19815.54 | Y45: =Y6*Premissas!$E$35 -> 22728.447 | Z45: =Z6*Premissas!$E$35 -> 22678.734 | AA45: =AA6*Premissas!$E$35 -> 21224.61
A46: BAT créditos → AMD (kWh) | B46: =SUM(D46:AA46) -> 488267.5 | C46: =B46/24 -> 20344.479 | D46: =D20 -> 0 | E46: =E20 -> 0 | F46: =F20 -> 0 | G46: =G20 -> 32711.293 | H46: =H20 -> 40823.762 | I46: =I20 -> 41560.462 | J46: =J20 -> 47597.362 | K46: =K20 -> 51288.174 | ... AA46: =AA20 -> 14863.108
A47: Banco início mês COM Helexia (kWh) | B47: =AA47 -> 377443.44 | C47: — | D47: =Premissas!$B$28 -> 991029 | E47: =D49 -> 832866.4 | F47: =E49 -> 625562.35 | G47: =F49 -> 540442.65 | H47: =G49 -> 630063.47 | I47: =H49 -> 723229.87 | J47: =I49 -> 830949.11 | K47: =J49 -> 946687.29 | L47: =K49 -> 976942.15 | ... AA47: =Z49 -> 377443.44
A48: Bank draw COM Helexia (kWh) | B48: =SUM(D48:AA48) -> 1737456.2 | C48: =B48/24 -> 72394.007 | D48: =MIN(D47,MAX(D40-D42-D45+D46,0)+IF(Premissas!$B$8=0,0,MAX(D41-D44,0)/Premissas!$B$8)) -> 158162.6 | E48: =MIN(E47,MAX(E40-E42-E45+E46,0)+IF(Premissas!$B$8=0,0,MAX(E41-E44,0)/Premissas!$B$8)) -> 207304.05 | F48: =MIN(F47,MAX(F40-F42-F45+F46,0)+IF(Premissas!$B$8=0,0,MAX(F41-F44,0)/Premissas!$B$8)) -> 85119.698 | G48: =MIN(G47,MAX(G40-G42-G45+G46,0)+IF(Premissas!$B$8=0,0,MAX(G41-G44,0)/Premissas!$B$8)) -> 0 | H48: =MIN(H47,MAX(H40-H42-H45+H46,0)+IF(Premissas!$B$8=0,0,MAX(H41-H44,0)/Premissas!$B$8)) -> 0 | I48: =MIN(I47,MAX(I40-I42-I45+I46,0)+IF(Premissas!$B$8=0,0,MAX(I41-I44,0)/Premissas!$B$8)) -> 0 | J48: =MIN(J47,MAX(J40-J42-J45+J46,0)+IF(Premissas!$B$8=0,0,MAX(J41-J44,0)/Premissas!$B$8)) -> 0 | K48: =MIN(K47,MAX(K40-K42-K45+K46,0)+IF(Premissas!$B$8=0,0,MAX(K41-K44,0)/Premissas!$B$8)) -> 36160.745 | ... AA48: =MIN(AA47,MAX(AA40-AA42-AA45+AA46,0)+IF(Premissas!$B$8=0,0,MAX(AA41-AA44,0)/Premissas!$B$8)) -> 45249.997
A49: ★ Banco fim mês COM Helexia (kWh) | B49: =AA49 -> 347056.55 | C49: — | D49: =MAX(D47-D48,0)+D46+MAX(D45-MAX(D40-D42,0),0)+MAX(D42-D40,0) -> 832866.4 | E49: =MAX(E47-E48,0)+E46+MAX(E45-MAX(E40-E42,0),0)+MAX(E42-E40,0) -> 625562.35 | F49: =MAX(F47-F48,0)+F46+MAX(F45-MAX(F40-F42,0),0)+MAX(F42-F40,0) -> 540442.65 | G49: =MAX(G47-G48,0)+G46+MAX(G45-MAX(G40-G42,0),0)+MAX(G42-G40,0) -> 630063.47 | H49: =MAX(H47-H48,0)+H46+MAX(H45-MAX(H40-H42,0),0)+MAX(H42-H40,0) -> 723229.87 | I49: =MAX(I47-I48,0)+I46+MAX(I45-MAX(I40-I42,0),0)+MAX(I42-I40,0) -> 830949.11 | J49: =MAX(J47-J48,0)+J46+MAX(J45-MAX(J40-J42,0),0)+MAX(J42-J40,0) -> 946687.29 | K49: =MAX(K47-K48,0)+K46+MAX(K45-MAX(K40-K42,0),0)+MAX(K42-K40,0) -> 976942.15 | ... AA49: =MAX(AA47-AA48,0)+AA46+MAX(AA45-MAX(AA40-AA42,0),0)+MAX(AA42-AA40,0) -> 347056.55
A50: Banco início mês SEM Helexia (kWh) | B50: =AA50 -> 362827.64 | C50: — | D50: =Premissas!$B$28 -> 991029 | E50: =D52 -> 832866.4 | F50: =E52 -> 625562.35 | G50: =F52 -> 540442.65 | H50: =G52 -> 630063.47 | I50: =H52 -> 723229.87 | J50: =I52 -> 830949.11 | K50: =J52 -> 946687.29 | L50: =K52 -> 1013102.9 | ... AA50: =Z52 -> 362827.64
A51: Bank draw SEM Helexia (kWh) — gen+BAT, no CS3 | B51: =SUM(D51:AA51) -> 1652083.1 | C51: =B51/24 -> 68836.797 | D51: =MIN(D50,MAX(D40-D42-D46,0)+IF(Premissas!$B$8=0,0,MAX(D41-D44-(IF(Premissas!$B$8>0,MAX(D42-D40,0)*Premissas!$B$8,0)),0)/Premissas!$B$8)) -> 158162.6 | E51: =MIN(E50,MAX(E40-E42-E46,0)+IF(Premissas!$B$8=0,0,MAX(E41-E44-(IF(Premissas!$B$8>0,MAX(E42-E40,0)*Premissas!$B$8,0)),0)/Premissas!$B$8)) -> 207304.05 | F51: =MIN(F50,MAX(F40-F42-F46,0)+IF(Premissas!$B$8=0,0,MAX(F41-F44-(IF(Premissas!$B$8>0,MAX(F42-F40,0)*Premissas!$B$8,0)),0)/Premissas!$B$8)) -> 85119.698 | G51: =MIN(G50,MAX(G40-G42-G46,0)+IF(Premissas!$B$8=0,0,MAX(G41-G44-(IF(Premissas!$B$8>0,MAX(G42-G40,0)*Premissas!$B$8,0)),0)/Premissas!$B$8)) -> 0 | H51: =MIN(H50,MAX(H40-H42-H46,0)+IF(Premissas!$B$8=0,0,MAX(H41-H44-(IF(Premissas!$B$8>0,MAX(H42-H40,0)*Premissas!$B$8,0)),0)/Premissas!$B$8)) -> 0 | I51: =MIN(I50,MAX(I40-I42-I46,0)+IF(Premissas!$B$8=0,0,MAX(I41-I44-(IF(Premissas!$B$8>0,MAX(I42-I40,0)*Premissas!$B$8,0)),0)/Premissas!$B$8)) -> 0 | J51: =MIN(J50,MAX(J40-J42-J46,0)+IF(Premissas!$B$8=0,0,MAX(J41-J44-(IF(Premissas!$B$8>0,MAX(J42-J40,0)*Premissas!$B$8,0)),0)/Premissas!$B$8)) -> 0 | K51: =MIN(K50,MAX(K40-K42-K46,0)+IF(Premissas!$B$8=0,0,MAX(K41-K44-(IF(Premissas!$B$8>0,MAX(K42-K40,0)*Premissas!$B$8,0)),0)/Premissas!$B$8)) -> 0 | ... AA51: =MIN(AA50,MAX(AA40-AA42-AA46,0)+IF(Premissas!$B$8=0,0,MAX(AA41-AA44-(IF(Premissas!$B$8>0,MAX(AA42-AA40,0)*Premissas!$B$8,0)),0)/Premissas!$B$8)) -> 36748.39
A52: Banco fim mês SEM Helexia (kWh) — gen+BAT, no CS3 | B52: =AA52 -> 340942.36 | C52: — | D52: =MAX(D50-D51,0)+D46+MAX(D42-D40,0) -> 832866.4 | E52: =MAX(E50-E51,0)+E46+MAX(E42-E40,0) -> 625562.35 | F52: =MAX(F50-F51,0)+F46+MAX(F42-F40,0) -> 540442.65 | G52: =MAX(G50-G51,0)+G46+MAX(G42-G40,0) -> 630063.47 | H52: =MAX(H50-H51,0)+H46+MAX(H42-H40,0) -> 723229.87 | I52: =MAX(I50-I51,0)+I46+MAX(I42-I40,0) -> 830949.11 | J52: =MAX(J50-J51,0)+J46+MAX(J42-J40,0) -> 946687.29 | K52: =MAX(K50-K51,0)+K46+MAX(K42-K40,0) -> 1013102.9 | ... AA52: =MAX(AA50-AA51,0)+AA46+MAX(AA42-AA40,0) -> 340942.36
A53: =" Custo SEM Helexia (R$) — só gen própria, sem "&INDEX(PVSYST_Helexia!$A$5:$A$7,MATCH(Premissas!$B$13,PVSYST_Helexia!$B$5:$B$7,0))&"/BAT/banco" -> Custo SEM Helexia (R$) — só gen própria, sem HCS03/BAT/banco | B53: =SUM(D53:AA53) -> 0 | C53: =B53/24 -> 0 | D53: =IF(D52>0,0,MAX(D40-D42-D46-D50,0)*Premissas!$B$5+MAX(D41-D44-(IF(Premissas!$B$8>0,MAX(D42+D46+D50-D40,0)*Premissas!$B$8,0)),0)*Premissas!$B$6) -> 0 | E53: =IF(E52>0,0,MAX(E40-E42-E46-E50,0)*Premissas!$B$5+MAX(E41-E44-(IF(Premissas!$B$8>0,MAX(E42+E46+E50-E40,0)*Premissas!$B$8,0)),0)*Premissas!$B$6) -> 0 | F53: =IF(F52>0,0,MAX(F40-F42-F46-F50,0)*Premissas!$B$5+MAX(F41-F44-(IF(Premissas!$B$8>0,MAX(F42+F46+F50-F40,0)*Premissas!$B$8,0)),0)*Premissas!$B$6) -> 0 | G53: =IF(G52>0,0,MAX(G40-G42-G46-G50,0)*Premissas!$B$5+MAX(G41-G44-(IF(Premissas!$B$8>0,MAX(G42+G46+G50-G40,0)*Premissas!$B$8,0)),0)*Premissas!$B$6) -> 0 | H53: =IF(H52>0,0,MAX(H40-H42-H46-H50,0)*Premissas!$B$5+MAX(H41-H44-(IF(Premissas!$B$8>0,MAX(H42+H46+H50-H40,0)*Premissas!$B$8,0)),0)*Premissas!$B$6) -> 0 | I53: =IF(I52>0,0,MAX(I40-I42-I46-I50,0)*Premissas!$B$5+MAX(I41-I44-(IF(Premissas!$B$8>0,MAX(I42+I46+I50-I40,0)*Premissas!$B$8,0)),0)*Premissas!$B$6) -> 0 | J53: =IF(J52>0,0,MAX(J40-J42-J46-J50,0)*Premissas!$B$5+MAX(J41-J44-(IF(Premissas!$B$8>0,MAX(J42+J46+J50-J40,0)*Premissas!$B$8,0)),0)*Premissas!$B$6) -> 0 | K53: =IF(K52>0,0,MAX(K40-K42-K46-K50,0)*Premissas!$B$5+MAX(K41-K44-(IF(Premissas!$B$8>0,MAX(K42+K46+K50-K40,0)*Premissas!$B$8,0)),0)*Premissas!$B$6) -> 0 | ... AA53: =IF(AA52>0,0,MAX(AA40-AA42-AA46-AA50,0)*Premissas!$B$5+MAX(AA41-AA44-(IF(Premissas!$B$8>0,MAX(AA42+AA46+AA50-AA40,0)*Premissas!$B$8,0)),0)*Premissas!$B$6) -> 0
A54: Custo COM Helexia — rede remanescente (R$) | B54: =SUM(D54:AA54) -> 0 | C54: =B54/24 -> 0 | D54: =IF(D49>0,0,MAX(D40-D42-D45+D46-D47,0)*Premissas!$B$5+MAX(D41-D44-(IF(Premissas!$B$8>0,MAX(D42+D45+D46+D47-D40,0)*Premissas!$B$8,0)),0)*Premissas!$B$6) -> 0 | E54: =IF(E49>0,0,MAX(E40-E42-E45+E46-E47,0)*Premissas!$B$5+MAX(E41-E44-(IF(Premissas!$B$8>0,MAX(E42+E45+E46+E47-E40,0)*Premissas!$B$8,0)),0)*Premissas!$B$6) -> 0 | F54: =IF(F49>0,0,MAX(F40-F42-F45+F46-F47,0)*Premissas!$B$5+MAX(F41-F44-(IF(Premissas!$B$8>0,MAX(F42+F45+F46+F47-F40,0)*Premissas!$B$8,0)),0)*Premissas!$B$6) -> 0 | G54: =IF(G49>0,0,MAX(G40-G42-G45+G46-G47,0)*Premissas!$B$5+MAX(G41-G44-(IF(Premissas!$B$8>0,MAX(G42+G45+G46+G47-G40,0)*Premissas!$B$8,0)),0)*Premissas!$B$6) -> 0 | H54: =IF(H49>0,0,MAX(H40-H42-H45+H46-H47,0)*Premissas!$B$5+MAX(H41-H44-(IF(Premissas!$B$8>0,MAX(H42+H45+H46+H47-H40,0)*Premissas!$B$8,0)),0)*Premissas!$B$6) -> 0 | I54: =IF(I49>0,0,MAX(I40-I42-I45+I46-I47,0)*Premissas!$B$5+MAX(I41-I44-(IF(Premissas!$B$8>0,MAX(I42+I45+I46+I47-I40,0)*Premissas!$B$8,0)),0)*Premissas!$B$6) -> 0 | J54: =IF(J49>0,0,MAX(J40-J42-J45+J46-J47,0)*Premissas!$B$5+MAX(J41-J44-(IF(Premissas!$B$8>0,MAX(J42+J45+J46+J47-J40,0)*Premissas!$B$8,0)),0)*Premissas!$B$6) -> 0 | K54: =IF(K49>0,0,MAX(K40-K42-K45+K46-K47,0)*Premissas!$B$5+MAX(K41-K44-(IF(Premissas!$B$8>0,MAX(K42+K45+K46+K47-K40,0)*Premissas!$B$8,0)),0)*Premissas!$B$6) -> 0 | ... AA54: =IF(AA49>0,0,MAX(AA40-AA42-AA45+AA46-AA47,0)*Premissas!$B$5+MAX(AA41-AA44-(IF(Premissas!$B$8>0,MAX(AA42+AA45+AA46+AA47-AA40,0)*Premissas!$B$8,0)),0)*Premissas!$B$6) -> 0
A55: ★ Economia mensal (R$) | B55: =SUM(D55:AA55) -> 0 | C55: =B55/24 -> 0 | D55: =MAX(D53-D54,0) -> 0 | E55: =MAX(E53-E54,0) -> 0 | F55: =MAX(F53-F54,0) -> 0 | G55: =MAX(G53-G54,0) -> 0 | H55: =MAX(H53-H54,0) -> 0 | I55: =MAX(I53-I54,0) -> 0 | J55: =MAX(J53-J54,0) -> 0 | K55: =MAX(K53-K54,0) -> 0 | ... AA55: =MAX(AA53-AA54,0) -> 0
A57: AREC (B3)
A58: Consumo FP (kWh) | B58: =SUM(D58:AA58) -> 111161.61 | C58: =B58/24 -> 4631.7339 | D58: 3657.4 | E58: 3450.6 | F58: 3408.8 | G58: 4205 | H58: 5428 | I58: 6374 | J58: 6073.1 | K58: =4121.3*(1+Premissas!$B$21) -> 4224.3325 | L58: =4332.7*(1+Premissas!$B$21) -> 4441.0175 | M58: =5075.6*(1+Premissas!$B$21) -> 5202.49 | N58: =4416*(1+Premissas!$B$21) -> 4526.4 | O58: =4080.2*(1+Premissas!$B$21) -> 4182.205 | P58: =3657.4*(1+Premissas!$B$21) -> 3748.835 | Q58: =3450.6*(1+Premissas!$B$21) -> 3536.865 | R58: =3408.8*(1+Premissas!$B$21) -> 3494.02 | S58: =4205*(1+Premissas!$B$21) -> 4310.125 | T58: =5428*(1+Premissas!$B$21) -> 5563.7 | U58: =6374*(1+Premissas!$B$21) -> 6533.35 | V58: =6073.1*(1+Premissas!$B$21) -> 6224.9275 | W58: =4121.3*(1+Premissas!$B$21) -> 4224.3325 | X58: =4332.7*(1+Premissas!$B$21) -> 4441.0175 | Y58: =5075.6*(1+Premissas!$B$21) -> 5202.49 | Z58: =4416*(1+Premissas!$B$21) -> 4526.4 | AA58: =4080.2*(1+Premissas!$B$21) -> 4182.205
A59: =" "&INDEX(PVSYST_Helexia!$A$5:$A$7,MATCH(Premissas!$B$13,PVSYST_Helexia!$B$5:$B$7,0))&" créditos recebidos (kWh)" -> HCS03 créditos recebidos (kWh) | B59: =SUM(D59:AA59) -> 158661.61 | C59: =B59/24 -> 6610.9003 | D59: =D6*Premissas!$B$36 -> 3108.65 | E59: =E6*Premissas!$B$36 -> 3272.118 | F59: =F6*Premissas!$B$36 -> 3927.9957 | G59: =G6*Premissas!$B$36 -> 3685.8023 | H59: =H6*Premissas!$C$36 -> 7922.3584 | I59: =I6*Premissas!$C$36 -> 7660.1675 | J59: =J6*Premissas!$C$36 -> 7273.6982 | K59: =K6*Premissas!$C$36 -> 7468.4693 | L59: =L6*Premissas!$C$36 -> 6655.0458 | M59: =M6*Premissas!$C$36 -> 7633.3454 | N59: =N6*Premissas!$D$36 -> 4475.2523 | O59: =O6*Premissas!$D$36 -> 4188.3064 | P59: =P6*Premissas!$D$36 -> 3801.1134 | Q59: =Q6*Premissas!$D$36 -> 4000.9945 | R59: =R6*Premissas!$D$36 -> 4802.9715 | S59: =S6*Premissas!$D$36 -> 4506.8287 | T59: =T6*Premissas!$E$36 -> 9883.2139 | U59: =U6*Premissas!$E$36 -> 9556.1284 | V59: =V6*Premissas!$E$36 -> 9074.0045 | W59: =W6*Premissas!$E$36 -> 9363.8022 | X59: =X6*Premissas!$E$36 -> 8343.9498 | Y59: =Y6*Premissas!$E$36 -> 9570.5202 | Z59: =Z6*Premissas!$E$36 -> 9549.5867 | AA59: =AA6*Premissas!$E$36 -> 8937.2828
A60: Banco início mês COM Helexia (kWh) | B60: =AA60 -> 43472.15 | C60: — | D60: =0 -> 0 | E60: =D62 -> 0 | F60: =E62 -> 0 | G60: =F62 -> 519.19573 | H60: =G62 -> 0 | I60: =H62 -> 2494.3584 | J60: =I62 -> 3780.5259 | K60: =J62 -> 4981.1242 | L60: =K62 -> 8225.261 | ... AA60: =Z62 -> 43472.15
A61: Bank draw COM Helexia (kWh) | B61: =SUM(D61:AA61) -> 570.34338 | C61: =B61/24 -> 23.764308 | D61: =MIN(D60,MAX(D58-D59,0)) -> 0 | E61: =MIN(E60,MAX(E58-E59,0)) -> 0 | F61: =MIN(F60,MAX(F58-F59,0)) -> 0 | G61: =MIN(G60,MAX(G58-G59,0)) -> 519.19573 | H61: =MIN(H60,MAX(H58-H59,0)) -> 0 | I61: =MIN(I60,MAX(I58-I59,0)) -> 0 | J61: =MIN(J60,MAX(J58-J59,0)) -> 0 | K61: =MIN(K60,MAX(K58-K59,0)) -> 0 | ... AA61: =MIN(AA60,MAX(AA58-AA59,0)) -> 0
A62: ★ Banco fim mês COM Helexia (kWh) | B62: =AA62 -> 48227.228 | C62: — | D62: =MAX(D60-D61,0)+MAX(D59-D58,0) -> 0 | E62: =MAX(E60-E61,0)+MAX(E59-E58,0) -> 0 | F62: =MAX(F60-F61,0)+MAX(F59-F58,0) -> 519.19573 | G62: =MAX(G60-G61,0)+MAX(G59-G58,0) -> 0 | H62: =MAX(H60-H61,0)+MAX(H59-H58,0) -> 2494.3584 | I62: =MAX(I60-I61,0)+MAX(I59-I58,0) -> 3780.5259 | J62: =MAX(J60-J61,0)+MAX(J59-J58,0) -> 4981.1242 | K62: =MAX(K60-K61,0)+MAX(K59-K58,0) -> 8225.261 | ... AA62: =MAX(AA60-AA61,0)+MAX(AA59-AA58,0) -> 48227.228
A63: Banco início mês SEM Helexia (kWh) | B63: =AA63 -> 0 | C63: — | D63: =0 -> 0 | E63: =D65 -> 0 | F63: =E65 -> 0 | G63: =F65 -> 0 | H63: =G65 -> 0 | I63: =H65 -> 0 | J63: =I65 -> 0 | K63: =J65 -> 0 | L63: =K65 -> 0 | ... AA63: =Z65 -> 0
A64: Bank draw SEM Helexia (kWh) | B64: =SUM(D64:AA64) -> 0 | C64: =B64/24 -> 0 | D64: =MIN(D63,D58) -> 0 | E64: =MIN(E63,E58) -> 0 | F64: =MIN(F63,F58) -> 0 | G64: =MIN(G63,G58) -> 0 | H64: =MIN(H63,H58) -> 0 | I64: =MIN(I63,I58) -> 0 | J64: =MIN(J63,J58) -> 0 | K64: =MIN(K63,K58) -> 0 | ... AA64: =MIN(AA63,AA58) -> 0
A65: Banco fim mês SEM Helexia (kWh) | B65: =AA65 -> 0 | C65: — | D65: =MAX(D63-D64,0) -> 0 | E65: =MAX(E63-E64,0) -> 0 | F65: =MAX(F63-F64,0) -> 0 | G65: =MAX(G63-G64,0) -> 0 | H65: =MAX(H63-H64,0) -> 0 | I65: =MAX(I63-I64,0) -> 0 | J65: =MAX(J63-J64,0) -> 0 | K65: =MAX(K63-K64,0) -> 0 | ... AA65: =MAX(AA63-AA64,0) -> 0
A66: =" Custo SEM Helexia (R$) — só gen própria, sem "&INDEX(PVSYST_Helexia!$A$5:$A$7,MATCH(Premissas!$B$13,PVSYST_Helexia!$B$5:$B$7,0))&"/BAT/banco" -> Custo SEM Helexia (R$) — só gen própria, sem HCS03/BAT/banco | B66: =SUM(D66:AA66) -> 102879.06 | C66: =B66/24 -> 4286.6276 | D66: =D58*Premissas!$F$19 -> 3384.8905 | E66: =E58*Premissas!$F$19 -> 3193.499 | F66: =F58*Premissas!$F$19 -> 3154.8134 | G66: =G58*Premissas!$F$19 -> 3891.6893 | H66: =H58*Premissas!$F$19 -> 5023.5647 | I66: =I58*Premissas!$F$19 -> 5899.0791 | J66: =J58*Premissas!$F$19 -> 5620.5989 | K66: =K58*Premissas!$F$19 -> 3909.5814 | ... AA66: =AA58*Premissas!$F$19 -> 3870.5928
A67: Custo COM Helexia — rede remanescente (R$) | B67: =SUM(D67:AA67) -> 841.31059 | C67: =B67/24 -> 35.054608 | D67: =IF(D62>0,0,MAX(D58-D59-D60,0)*Premissas!$B$7) -> 634.82897 | E67: =IF(E62>0,0,MAX(E58-E59-E60,0)*Premissas!$B$7) -> 206.47937 | F67: =IF(F62>0,0,MAX(F58-F59-F60,0)*Premissas!$B$7) -> 0 | G67: =IF(G62>0,0,MAX(G58-G59-G60,0)*Premissas!$B$7) -> 0.0022460108 | H67: =IF(H62>0,0,MAX(H58-H59-H60,0)*Premissas!$B$7) -> 0 | I67: =IF(I62>0,0,MAX(I58-I59-I60,0)*Premissas!$B$7) -> 0 | J67: =IF(J62>0,0,MAX(J58-J59-J60,0)*Premissas!$B$7) -> 0 | K67: =IF(K62>0,0,MAX(K58-K59-K60,0)*Premissas!$B$7) -> 0 | ... AA67: =IF(AA62>0,0,MAX(AA58-AA59-AA60,0)*Premissas!$B$7) -> 0
A68: ★ Economia mensal (R$) | B68: =SUM(D68:AA68) -> 102037.75 | C68: =B68/24 -> 4251.573 | D68: =MAX(D66-D67,0) -> 2750.0615 | E68: =MAX(E66-E67,0) -> 2987.0196 | F68: =MAX(F66-F67,0) -> 3154.8134 | G68: =MAX(G66-G67,0) -> 3891.6871 | H68: =MAX(H66-H67,0) -> 5023.5647 | I68: =MAX(I66-I67,0) -> 5899.0791 | J68: =MAX(J66-J67,0) -> 5620.5989 | K68: =MAX(K66-K67,0) -> 3909.5814 | ... AA68: =MAX(AA66-AA67,0) -> 3870.5928
A70: Banheiro Motoristas (B3)
A71: Consumo FP (kWh) | B71: =SUM(D71:AA71) -> 10991.25 | C71: =B71/24 -> 457.96875 | D71: 450 | E71: 450 | F71: 450 | G71: 450 | H71: 450 | I71: 450 | J71: 450 | K71: =450*(1+Premissas!$B$21) -> 461.25 | L71: =450*(1+Premissas!$B$21) -> 461.25 | M71: =450*(1+Premissas!$B$21) -> 461.25 | N71: =450*(1+Premissas!$B$21) -> 461.25 | O71: =450*(1+Premissas!$B$21) -> 461.25 | P71: =450*(1+Premissas!$B$21) -> 461.25 | Q71: =450*(1+Premissas!$B$21) -> 461.25 | R71: =450*(1+Premissas!$B$21) -> 461.25 | ... AA71: =450*(1+Premissas!$B$21) -> 461.25
A72: =" "&INDEX(PVSYST_Helexia!$A$5:$A$7,MATCH(Premissas!$B$13,PVSYST_Helexia!$B$5:$B$7,0))&" créditos recebidos (kWh)" -> HCS03 créditos recebidos (kWh) | B72: =SUM(D72:AA72) -> 14361.524 | C72: =B72/24 -> 598.39683 | D72: =D6*Premissas!$B$37 -> 367.46014 | E72: =E6*Premissas!$B$37 -> 386.78299 | F72: =F6*Premissas!$B$37 -> 464.31147 | G72: =G6*Premissas!$B$37 -> 435.68283 | H72: =H6*Premissas!$C$37 -> 757.7027 | I72: =I6*Premissas!$C$37 -> 732.62649 | J72: =J6*Premissas!$C$37 -> 695.66416 | K72: =K6*Premissas!$C$37 -> 714.29227 | L72: =L6*Premissas!$C$37 -> 636.49559 | M72: =M6*Premissas!$C$37 -> 730.06119 | N72: =N6*Premissas!$D$37 -> 582.75706 | O72: =O6*Premissas!$D$37 -> 545.39163 | P72: =P6*Premissas!$D$37 -> 494.97225 | Q72: =Q6*Premissas!$D$37 -> 521.0003 | R72: =R6*Premissas!$D$37 -> 625.4319 | S72: =S6*Premissas!$D$37 -> 586.86886 | T72: =T6*Premissas!$E$37 -> 676.4607 | U72: =U6*Premissas!$E$37 -> 654.0732 | V72: =V6*Premissas!$E$37 -> 621.07403 | W72: =W6*Premissas!$E$37 -> 640.90935 | X72: =X6*Premissas!$E$37 -> 571.10512 | Y72: =Y6*Premissas!$E$37 -> 655.05825 | Z72: =Z6*Premissas!$E$37 -> 653.62545 | AA72: =AA6*Premissas!$E$37 -> 611.71605
A73: Banco início mês COM Helexia (kWh) | B73: =AA73 -> 3365.5705 | C73: — | D73: =0 -> 0 | E73: =D75 -> 0 | F73: =E75 -> 0 | G73: =F75 -> 14.311473 | H73: =G75 -> 0 | I73: =H75 -> 307.7027 | J73: =I75 -> 590.32919 | K73: =J75 -> 835.99335 | L73: =K75 -> 1089.0356 | ... AA73: =Z75 -> 3365.5705
A74: Bank draw COM Helexia (kWh) | B74: =SUM(D74:AA74) -> 14.311473 | C74: =B74/24 -> 0.59631139 | D74: =MIN(D73,MAX(D71-D72,0)) -> 0 | E74: =MIN(E73,MAX(E71-E72,0)) -> 0 | F74: =MIN(F73,MAX(F71-F72,0)) -> 0 | G74: =MIN(G73,MAX(G71-G72,0)) -> 14.311473 | H74: =MIN(H73,MAX(H71-H72,0)) -> 0 | I74: =MIN(I73,MAX(I71-I72,0)) -> 0 | J74: =MIN(J73,MAX(J71-J72,0)) -> 0 | K74: =MIN(K73,MAX(K71-K72,0)) -> 0 | ... AA74: =MIN(AA73,MAX(AA71-AA72,0)) -> 0
A75: ★ Banco fim mês COM Helexia (kWh) | B75: =AA75 -> 3516.0366 | C75: — | D75: =MAX(D73-D74,0)+MAX(D72-D71,0) -> 0 | E75: =MAX(E73-E74,0)+MAX(E72-E71,0) -> 0 | F75: =MAX(F73-F74,0)+MAX(F72-F71,0) -> 14.311473 | G75: =MAX(G73-G74,0)+MAX(G72-G71,0) -> 0 | H75: =MAX(H73-H74,0)+MAX(H72-H71,0) -> 307.7027 | I75: =MAX(I73-I74,0)+MAX(I72-I71,0) -> 590.32919 | J75: =MAX(J73-J74,0)+MAX(J72-J71,0) -> 835.99335 | K75: =MAX(K73-K74,0)+MAX(K72-K71,0) -> 1089.0356 | ... AA75: =MAX(AA73-AA74,0)+MAX(AA72-AA71,0) -> 3516.0366
A76: Banco início mês SEM Helexia (kWh) | B76: =AA76 -> 0 | C76: — | D76: =0 -> 0 | E76: =D78 -> 0 | F76: =E78 -> 0 | G76: =F78 -> 0 | H76: =G78 -> 0 | I76: =H78 -> 0 | J76: =I78 -> 0 | K76: =J78 -> 0 | L76: =K78 -> 0 | ... AA76: =Z78 -> 0
A77: Bank draw SEM Helexia (kWh) | B77: =SUM(D77:AA77) -> 0 | C77: =B77/24 -> 0 | D77: =MIN(D76,D71) -> 0 | E77: =MIN(E76,E71) -> 0 | F77: =MIN(F76,F71) -> 0 | G77: =MIN(G76,G71) -> 0 | H77: =MIN(H76,H71) -> 0 | I77: =MIN(I76,I71) -> 0 | J77: =MIN(J76,J71) -> 0 | K77: =MIN(K76,K71) -> 0 | ... AA77: =MIN(AA76,AA71) -> 0
A78: Banco fim mês SEM Helexia (kWh) | B78: =AA78 -> 0 | C78: — | D78: =MAX(D76-D77,0) -> 0 | E78: =MAX(E76-E77,0) -> 0 | F78: =MAX(F76-F77,0) -> 0 | G78: =MAX(G76-G77,0) -> 0 | H78: =MAX(H76-H77,0) -> 0 | I78: =MAX(I76-I77,0) -> 0 | J78: =MAX(J76-J77,0) -> 0 | K78: =MAX(K76-K77,0) -> 0 | ... AA78: =MAX(AA76-AA77,0) -> 0
A79: =" Custo SEM Helexia (R$) — só gen própria, sem "&INDEX(PVSYST_Helexia!$A$5:$A$7,MATCH(Premissas!$B$13,PVSYST_Helexia!$B$5:$B$7,0))&"/BAT/banco" -> Custo SEM Helexia (R$) — só gen própria, sem HCS03/BAT/banco | B79: =SUM(D79:AA79) -> 10172.302 | C79: =B79/24 -> 423.84592 | D79: =D71*Premissas!$F$19 -> 416.47091 | E79: =E71*Premissas!$F$19 -> 416.47091 | F79: =F71*Premissas!$F$19 -> 416.47091 | G79: =G71*Premissas!$F$19 -> 416.47091 | H79: =H71*Premissas!$F$19 -> 416.47091 | I79: =I71*Premissas!$F$19 -> 416.47091 | J79: =J71*Premissas!$F$19 -> 416.47091 | K79: =K71*Premissas!$F$19 -> 426.88269 | ... AA79: =AA71*Premissas!$F$19 -> 426.88269
A80: Custo COM Helexia — rede remanescente (R$) | B80: =SUM(D80:AA80) -> 168.62742 | C80: =B80/24 -> 7.0261424 | D80: =IF(D75>0,0,MAX(D71-D72-D73,0)*Premissas!$B$7) -> 95.487368 | E80: =IF(E75>0,0,MAX(E71-E72-E73,0)*Premissas!$B$7) -> 73.133466 | F80: =IF(F75>0,0,MAX(F71-F72-F73,0)*Premissas!$B$7) -> 0 | G80: =IF(G75>0,0,MAX(G71-G72-G73,0)*Premissas!$B$7) -> 0.0065847393 | H80: =IF(H75>0,0,MAX(H71-H72-H73,0)*Premissas!$B$7) -> 0 | I80: =IF(I75>0,0,MAX(I71-I72-I73,0)*Premissas!$B$7) -> 0 | J80: =IF(J75>0,0,MAX(J71-J72-J73,0)*Premissas!$B$7) -> 0 | K80: =IF(K75>0,0,MAX(K71-K72-K73,0)*Premissas!$B$7) -> 0 | ... AA80: =IF(AA75>0,0,MAX(AA71-AA72-AA73,0)*Premissas!$B$7) -> 0
A81: ★ Economia mensal (R$) | B81: =SUM(D81:AA81) -> 10003.675 | C81: =B81/24 -> 416.81978 | D81: =MAX(D79-D80,0) -> 320.98355 | E81: =MAX(E79-E80,0) -> 343.33745 | F81: =MAX(F79-F80,0) -> 416.47091 | G81: =MAX(G79-G80,0) -> 416.46433 | H81: =MAX(H79-H80,0) -> 416.47091 | I81: =MAX(I79-I80,0) -> 416.47091 | J81: =MAX(J79-J80,0) -> 416.47091 | K81: =MAX(K79-K80,0) -> 426.88269 | ... AA81: =MAX(AA79-AA80,0) -> 426.88269
A83: CTC Copasul (B3)
A84: Consumo FP (kWh) | B84: =SUM(D84:AA84) -> 14748.825 | C84: =B84/24 -> 614.53438 | D84: 364 | E84: 293 | F84: 369 | G84: 674 | H84: 752 | I84: 769 | J84: 670 | K84: =389*(1+Premissas!$B$21) -> 398.725 | L84: =895*(1+Premissas!$B$21) -> 917.375 | M84: =944*(1+Premissas!$B$21) -> 967.6 | N84: =528*(1+Premissas!$B$21) -> 541.2 | O84: =595*(1+Premissas!$B$21) -> 609.875 | P84: =364*(1+Premissas!$B$21) -> 373.1 | Q84: =293*(1+Premissas!$B$21) -> 300.325 | R84: =369*(1+Premissas!$B$21) -> 378.225 | S84: =674*(1+Premissas!$B$21) -> 690.85 | T84: =752*(1+Premissas!$B$21) -> 770.8 | U84: =769*(1+Premissas!$B$21) -> 788.225 | V84: =670*(1+Premissas!$B$21) -> 686.75 | W84: =389*(1+Premissas!$B$21) -> 398.725 | X84: =895*(1+Premissas!$B$21) -> 917.375 | Y84: =944*(1+Premissas!$B$21) -> 967.6 | Z84: =528*(1+Premissas!$B$21) -> 541.2 | AA84: =595*(1+Premissas!$B$21) -> 609.875
A85: =" "&INDEX(PVSYST_Helexia!$A$5:$A$7,MATCH(Premissas!$B$13,PVSYST_Helexia!$B$5:$B$7,0))&" créditos recebidos (kWh)" -> HCS03 créditos recebidos (kWh) | B85: =SUM(D85:AA85) -> 19680.507 | C85: =B85/24 -> 820.02113 | D85: =D6*Premissas!$B$38 -> 377.62534 | E85: =E6*Premissas!$B$38 -> 397.48273 | F85: =F6*Premissas!$B$38 -> 477.15592 | G85: =G6*Premissas!$B$38 -> 447.73531 | H85: =H6*Premissas!$C$38 -> 1165.4812 | I85: =I6*Premissas!$C$38 -> 1126.9096 | J85: =J6*Premissas!$C$38 -> 1070.0549 | K85: =K6*Premissas!$C$38 -> 1098.7083 | L85: =L6*Premissas!$C$38 -> 979.04318 | M85: =M6*Premissas!$C$38 -> 1122.9637 | N85: =N6*Premissas!$D$38 -> 569.96935 | O85: =O6*Premissas!$D$38 -> 533.42384 | P85: =P6*Premissas!$D$38 -> 484.11083 | Q85: =Q6*Premissas!$D$38 -> 509.56775 | R85: =R6*Premissas!$D$38 -> 611.70775 | S85: =S6*Premissas!$D$38 -> 573.99091 | T85: =T6*Premissas!$E$38 -> 1082.3559 | U85: =U6*Premissas!$E$38 -> 1046.5353 | V85: =V6*Premissas!$E$38 -> 993.73568 | W85: =W6*Premissas!$E$38 -> 1025.4728 | X85: =X6*Premissas!$E$38 -> 913.78406 | Y85: =Y6*Premissas!$E$38 -> 1048.1114 | Z85: =Z6*Premissas!$E$38 -> 1045.8189 | AA85: =AA6*Premissas!$E$38 -> 978.76267
A86: Banco início mês COM Helexia (kWh) | B86: =AA86 -> 4562.7952 | C86: — | D86: =0 -> 0 | E86: =D88 -> 13.625342 | F86: =E88 -> 118.10807 | G86: =F88 -> 226.26399 | H86: =G88 -> 0 | I86: =H88 -> 413.48122 | J86: =I88 -> 771.39078 | K86: =J88 -> 1171.4457 | L86: =K88 -> 1871.429 | ... AA86: =Z88 -> 4562.7952
A87: Bank draw COM Helexia (kWh) | B87: =SUM(D87:AA87) -> 423.16518 | C87: =B87/24 -> 17.631882 | D87: =MIN(D86,MAX(D84-D85,0)) -> 0 | E87: =MIN(E86,MAX(E84-E85,0)) -> 0 | F87: =MIN(F86,MAX(F84-F85,0)) -> 0 | G87: =MIN(G86,MAX(G84-G85,0)) -> 226.26399 | H87: =MIN(H86,MAX(H84-H85,0)) -> 0 | I87: =MIN(I86,MAX(I84-I85,0)) -> 0 | J87: =MIN(J86,MAX(J84-J85,0)) -> 0 | K87: =MIN(K86,MAX(K84-K85,0)) -> 0 | ... AA87: =MIN(AA86,MAX(AA84-AA85,0)) -> 0
A88: ★ Banco fim mês COM Helexia (kWh) | B88: =AA88 -> 4931.6829 | C88: — | D88: =MAX(D86-D87,0)+MAX(D85-D84,0) -> 13.625342 | E88: =MAX(E86-E87,0)+MAX(E85-E84,0) -> 118.10807 | F88: =MAX(F86-F87,0)+MAX(F85-F84,0) -> 226.26399 | G88: =MAX(G86-G87,0)+MAX(G85-G84,0) -> 0 | H88: =MAX(H86-H87,0)+MAX(H85-H84,0) -> 413.48122 | I88: =MAX(I86-I87,0)+MAX(I85-I84,0) -> 771.39078 | J88: =MAX(J86-J87,0)+MAX(J85-J84,0) -> 1171.4457 | K88: =MAX(K86-K87,0)+MAX(K85-K84,0) -> 1871.429 | ... AA88: =MAX(AA86-AA87,0)+MAX(AA85-AA84,0) -> 4931.6829
A89: Banco início mês SEM Helexia (kWh) | B89: =AA89 -> 0 | C89: — | D89: =0 -> 0 | E89: =D91 -> 0 | F89: =E91 -> 0 | G89: =F91 -> 0 | H89: =G91 -> 0 | I89: =H91 -> 0 | J89: =I91 -> 0 | K89: =J91 -> 0 | L89: =K91 -> 0 | ... AA89: =Z91 -> 0
A90: Bank draw SEM Helexia (kWh) | B90: =SUM(D90:AA90) -> 0 | C90: =B90/24 -> 0 | D90: =MIN(D89,D84) -> 0 | E90: =MIN(E89,E84) -> 0 | F90: =MIN(F89,F84) -> 0 | G90: =MIN(G89,G84) -> 0 | H90: =MIN(H89,H84) -> 0 | I90: =MIN(I89,I84) -> 0 | J90: =MIN(J89,J84) -> 0 | K90: =MIN(K89,K84) -> 0 | ... AA90: =MIN(AA89,AA84) -> 0
A91: Banco fim mês SEM Helexia (kWh) | B91: =AA91 -> 0 | C91: — | D91: =MAX(D89-D90,0) -> 0 | E91: =MAX(E89-E90,0) -> 0 | F91: =MAX(F89-F90,0) -> 0 | G91: =MAX(G89-G90,0) -> 0 | H91: =MAX(H89-H90,0) -> 0 | I91: =MAX(I89-I90,0) -> 0 | J91: =MAX(J89-J90,0) -> 0 | K91: =MAX(K89-K90,0) -> 0 | ... AA91: =MAX(AA89-AA90,0) -> 0
A92: =" Custo SEM Helexia (R$) — só gen própria, sem "&INDEX(PVSYST_Helexia!$A$5:$A$7,MATCH(Premissas!$B$13,PVSYST_Helexia!$B$5:$B$7,0))&"/BAT/banco" -> Custo SEM Helexia (R$) — só gen própria, sem HCS03/BAT/banco | B92: =SUM(D92:AA92) -> 13649.904 | C92: =B92/24 -> 568.74598 | D92: =D84*Premissas!$F$19 -> 336.87869 | E92: =E84*Premissas!$F$19 -> 271.16884 | F92: =F84*Premissas!$F$19 -> 341.50615 | G92: =G84*Premissas!$F$19 -> 623.78088 | H92: =H84*Premissas!$F$19 -> 695.96917 | I92: =I84*Premissas!$F$19 -> 711.70252 | J92: =J84*Premissas!$F$19 -> 620.07892 | K92: =K84*Premissas!$F$19 -> 369.01637 | ... AA92: =AA84*Premissas!$F$19 -> 564.43377
A93: Custo COM Helexia — rede remanescente (R$) | B93: =SUM(D93:AA93) -> 0.00080667785 | C93: =B93/24 -> 3.3611577e-05 | D93: =IF(D88>0,0,MAX(D84-D85-D86,0)*Premissas!$B$7) -> 0 | E93: =IF(E88>0,0,MAX(E84-E85-E86,0)*Premissas!$B$7) -> 0 | F93: =IF(F88>0,0,MAX(F84-F85-F86,0)*Premissas!$B$7) -> 0 | G93: =IF(G88>0,0,MAX(G84-G85-G86,0)*Premissas!$B$7) -> 0.00080667785 | H93: =IF(H88>0,0,MAX(H84-H85-H86,0)*Premissas!$B$7) -> 0 | I93: =IF(I88>0,0,MAX(I84-I85-I86,0)*Premissas!$B$7) -> 0 | J93: =IF(J88>0,0,MAX(J84-J85-J86,0)*Premissas!$B$7) -> 0 | K93: =IF(K88>0,0,MAX(K84-K85-K86,0)*Premissas!$B$7) -> 0 | ... AA93: =IF(AA88>0,0,MAX(AA84-AA85-AA86,0)*Premissas!$B$7) -> 0
A94: ★ Economia mensal (R$) | B94: =SUM(D94:AA94) -> 13649.903 | C94: =B94/24 -> 568.74595 | D94: =MAX(D92-D93,0) -> 336.87869 | E94: =MAX(E92-E93,0) -> 271.16884 | F94: =MAX(F92-F93,0) -> 341.50615 | G94: =MAX(G92-G93,0) -> 623.78007 | H94: =MAX(H92-H93,0) -> 695.96917 | I94: =MAX(I92-I93,0) -> 711.70252 | J94: =MAX(J92-J93,0) -> 620.07892 | K94: =MAX(K92-K93,0) -> 369.01637 | ... AA94: =MAX(AA92-AA93,0) -> 564.43377
A96: Depósito Irrigação (B3)
A97: Consumo FP (kWh) | B97: =SUM(D97:AA97) -> 22747.425 | C97: =B97/24 -> 947.80938 | D97: 1067 | E97: 899 | F97: 816 | G97: 719 | H97: 943 | I97: 925 | J97: 838 | K97: =876*(1+Premissas!$B$21) -> 897.9 | L97: =887*(1+Premissas!$B$21) -> 909.175 | M97: =1030*(1+Premissas!$B$21) -> 1055.75 | N97: =1026*(1+Premissas!$B$21) -> 1051.65 | O97: =1146*(1+Premissas!$B$21) -> 1174.65 | P97: =1067*(1+Premissas!$B$21) -> 1093.675 | Q97: =899*(1+Premissas!$B$21) -> 921.475 | R97: =816*(1+Premissas!$B$21) -> 836.4 | S97: =719*(1+Premissas!$B$21) -> 736.975 | T97: =943*(1+Premissas!$B$21) -> 966.575 | U97: =925*(1+Premissas!$B$21) -> 948.125 | V97: =838*(1+Premissas!$B$21) -> 858.95 | W97: =876*(1+Premissas!$B$21) -> 897.9 | X97: =887*(1+Premissas!$B$21) -> 909.175 | Y97: =1030*(1+Premissas!$B$21) -> 1055.75 | Z97: =1026*(1+Premissas!$B$21) -> 1051.65 | AA97: =1146*(1+Premissas!$B$21) -> 1174.65
A98: =" "&INDEX(PVSYST_Helexia!$A$5:$A$7,MATCH(Premissas!$B$13,PVSYST_Helexia!$B$5:$B$7,0))&" créditos recebidos (kWh)" -> HCS03 créditos recebidos (kWh) | B98: =SUM(D98:AA98) -> 30123.882 | C98: =B98/24 -> 1255.1618 | D98: =D6*Premissas!$B$39 -> 645.73223 | E98: =E6*Premissas!$B$39 -> 679.68799 | F98: =F6*Premissas!$B$39 -> 815.92764 | G98: =G6*Premissas!$B$39 -> 765.61896 | H98: =H6*Premissas!$C$39 -> 1720.8219 | I98: =I6*Premissas!$C$39 -> 1663.8712 | J98: =J6*Premissas!$C$39 -> 1579.9259 | K98: =K6*Premissas!$C$39 -> 1622.2323 | L98: =L6*Premissas!$C$39 -> 1445.5479 | M98: =M6*Premissas!$C$39 -> 1658.0451 | N98: =N6*Premissas!$D$39 -> 1179.5242 | O98: =O6*Premissas!$D$39 -> 1103.895 | P98: =P6*Premissas!$D$39 -> 1001.8441 | Q98: =Q6*Premissas!$D$39 -> 1054.526 | R98: =R6*Premissas!$D$39 -> 1265.8998 | S98: =S6*Premissas!$D$39 -> 1187.8466 | T98: =T6*Premissas!$E$39 -> 1428.0837 | U98: =U6*Premissas!$E$39 -> 1380.8212 | V98: =V6*Premissas!$E$39 -> 1311.1563 | W98: =W6*Premissas!$E$39 -> 1353.0308 | X98: =X6*Premissas!$E$39 -> 1205.6664 | Y98: =Y6*Premissas!$E$39 -> 1382.9008 | Z98: =Z6*Premissas!$E$39 -> 1379.876 | AA98: =AA6*Premissas!$E$39 -> 1291.4005
A99: Banco início mês COM Helexia (kWh) | B99: =AA99 -> 7900.3591 | C99: — | D99: =0 -> 0 | E99: =D101 -> 0 | F99: =E101 -> 0 | G99: =F101 -> 0 | H99: =G101 -> 46.618963 | I99: =H101 -> 824.44085 | J99: =I101 -> 1563.3121 | K99: =J101 -> 2305.2379 | L99: =K101 -> 3029.5702 | ... AA99: =Z101 -> 7900.3591
A100: Bank draw COM Helexia (kWh) | B100: =SUM(D100:AA100) -> 162.58588 | C100: =B100/24 -> 6.7744117 | D100: =MIN(D99,MAX(D97-D98,0)) -> 0 | E100: =MIN(E99,MAX(E97-E98,0)) -> 0 | F100: =MIN(F99,MAX(F97-F98,0)) -> 0 | G100: =MIN(G99,MAX(G97-G98,0)) -> 0 | H100: =MIN(H99,MAX(H97-H98,0)) -> 0 | I100: =MIN(I99,MAX(I97-I98,0)) -> 0 | J100: =MIN(J99,MAX(J97-J98,0)) -> 0 | K100: =MIN(K99,MAX(K97-K98,0)) -> 0 | ... AA100: =MIN(AA99,MAX(AA97-AA98,0)) -> 0
A101: ★ Banco fim mês COM Helexia (kWh) | B101: =AA101 -> 8017.1096 | C101: — | D101: =MAX(D99-D100,0)+MAX(D98-D97,0) -> 0 | E101: =MAX(E99-E100,0)+MAX(E98-E97,0) -> 0 | F101: =MAX(F99-F100,0)+MAX(F98-F97,0) -> 0 | G101: =MAX(G99-G100,0)+MAX(G98-G97,0) -> 46.618963 | H101: =MAX(H99-H100,0)+MAX(H98-H97,0) -> 824.44085 | I101: =MAX(I99-I100,0)+MAX(I98-I97,0) -> 1563.3121 | J101: =MAX(J99-J100,0)+MAX(J98-J97,0) -> 2305.2379 | K101: =MAX(K99-K100,0)+MAX(K98-K97,0) -> 3029.5702 | ... AA101: =MAX(AA99-AA100,0)+MAX(AA98-AA97,0) -> 8017.1096
A102: Banco início mês SEM Helexia (kWh) | B102: =AA102 -> 0 | C102: — | D102: =0 -> 0 | E102: =D104 -> 0 | F102: =E104 -> 0 | G102: =F104 -> 0 | H102: =G104 -> 0 | I102: =H104 -> 0 | J102: =I104 -> 0 | K102: =J104 -> 0 | L102: =K104 -> 0 | ... AA102: =Z104 -> 0
A103: Bank draw SEM Helexia (kWh) | B103: =SUM(D103:AA103) -> 0 | C103: =B103/24 -> 0 | D103: =MIN(D102,D97) -> 0 | E103: =MIN(E102,E97) -> 0 | F103: =MIN(F102,F97) -> 0 | G103: =MIN(G102,G97) -> 0 | H103: =MIN(H102,H97) -> 0 | I103: =MIN(I102,I97) -> 0 | J103: =MIN(J102,J97) -> 0 | K103: =MIN(K102,K97) -> 0 | ... AA103: =MIN(AA102,AA97) -> 0
A104: Banco fim mês SEM Helexia (kWh) | B104: =AA104 -> 0 | C104: — | D104: =MAX(D102-D103,0) -> 0 | E104: =MAX(E102-E103,0) -> 0 | F104: =MAX(F102-F103,0) -> 0 | G104: =MAX(G102-G103,0) -> 0 | H104: =MAX(H102-H103,0) -> 0 | I104: =MAX(I102-I103,0) -> 0 | J104: =MAX(J102-J103,0) -> 0 | K104: =MAX(K102-K103,0) -> 0 | ... AA104: =MAX(AA102-AA103,0) -> 0
A105: =" Custo SEM Helexia (R$) — só gen própria, sem "&INDEX(PVSYST_Helexia!$A$5:$A$7,MATCH(Premissas!$B$13,PVSYST_Helexia!$B$5:$B$7,0))&"/BAT/banco" -> Custo SEM Helexia (R$) — só gen própria, sem HCS03/BAT/banco | B105: =SUM(D105:AA105) -> 21052.535 | C105: =B105/24 -> 877.18897 | D105: =D97*Premissas!$F$19 -> 987.49881 | E105: =E97*Premissas!$F$19 -> 832.01634 | F105: =F97*Premissas!$F$19 -> 755.20059 | G105: =G97*Premissas!$F$19 -> 665.42797 | H105: =H97*Premissas!$F$19 -> 872.73794 | I105: =I97*Premissas!$F$19 -> 856.0791 | J105: =J97*Premissas!$F$19 -> 775.56139 | K105: =K97*Premissas!$F$19 -> 830.9983 | ... AA105: =AA97*Premissas!$F$19 -> 1087.1279
A106: Custo COM Helexia — rede remanescente (R$) | B106: =SUM(D106:AA106) -> 741.14717 | C106: =B106/24 -> 30.881132 | D106: =IF(D101>0,0,MAX(D97-D98-D99,0)*Premissas!$B$7) -> 487.34937 | E106: =IF(E101>0,0,MAX(E97-E98-E99,0)*Premissas!$B$7) -> 253.7141 | F106: =IF(F101>0,0,MAX(F97-F98-F99,0)*Premissas!$B$7) -> 0.083706065 | G106: =IF(G101>0,0,MAX(G97-G98-G99,0)*Premissas!$B$7) -> 0 | H106: =IF(H101>0,0,MAX(H97-H98-H99,0)*Premissas!$B$7) -> 0 | I106: =IF(I101>0,0,MAX(I97-I98-I99,0)*Premissas!$B$7) -> 0 | J106: =IF(J101>0,0,MAX(J97-J98-J99,0)*Premissas!$B$7) -> 0 | K106: =IF(K101>0,0,MAX(K97-K98-K99,0)*Premissas!$B$7) -> 0 | ... AA106: =IF(AA101>0,0,MAX(AA97-AA98-AA99,0)*Premissas!$B$7) -> 0
...

Sheet Dados_Produção_Copasul

Sheet Amandina
A1: Unidade | B1: Data | C1: Geração (kWh) | D1: Yf Diário (kWh/kWp)
A2: Amandina | B2: 45716 | C2: 190.1 | D2: =IFERROR(C2/VLOOKUP(A2,Usinas!$A:$B,2,FALSE()),"") -> 0.27274032 | F2: Geração Mensal | H2: Mês | I2: Kwh | J2: MWh | L2: Proxi Bataypora | P2: proxy Rate | Q2: 0.8
A3: Amandina | B3: 45717 | C3: 249.5 | D3: =IFERROR(C3/VLOOKUP(A3,Usinas!$A:$B,2,FALSE()),"") -> 0.3579627 | F3: 45658 | G3: =+F3+30 -> 45688 | H3: =+F3 -> 45658 | I3: 0 | J3: 0 | L3: =+Batayporã!J3*Amandina!$Q$2 -> 91.4072
A4: Amandina | B4: 45718 | C4: 295.9 | D4: =IFERROR(C4/VLOOKUP(A4,Usinas!$A:$B,2,FALSE()),"") -> 0.42453372 | F4: =+B2 -> 45716 | G4: =+F4 -> 45716 | H4: =+F4 -> 45716 | I4: =SUMIFS($C$1:$C$366, $B$1:$B$366, ">="&F4, $B$1:$B$366, "<="&G4) -> 190.1 | J4: =+I4/1000 -> 0.1901 | L4: =+Batayporã!J4*Amandina!$Q$2 -> 72.90552
A5: Amandina | B5: 45719 | C5: 250.2 | D5: =IFERROR(C5/VLOOKUP(A5,Usinas!$A:$B,2,FALSE()),"") -> 0.358967 | F5: =+G4+1 -> 45717 | G5: =+F5+30 -> 45747 | H5: =+F5 -> 45717 | I5: =SUMIFS($C$1:$C$366, $B$1:$B$366, ">="&F5, $B$1:$B$366, "<="&G5) -> 7913.8 | J5: =+I5/1000 -> 7.9138 | L5: =+Batayporã!J5*Amandina!$Q$2 -> 82.44952
A6: Amandina | B6: 45720 | C6: 256.6 | D6: =IFERROR(C6/VLOOKUP(A6,Usinas!$A:$B,2,FALSE()),"") -> 0.36814921 | F6: =+G5+1 -> 45748 | G6: =+F6+29 -> 45777 | H6: =+F6 -> 45748 | I6: =SUMIFS($C$1:$C$366, $B$1:$B$366, ">="&F6, $B$1:$B$366, "<="&G6) -> 23902.8 | J6: =+I6/1000 -> 23.9028 | L6: =+Batayporã!J6*Amandina!$Q$2 -> 58.96776
A7: Amandina | B7: 45721 | C7: 241 | D7: =IFERROR(C7/VLOOKUP(A7,Usinas!$A:$B,2,FALSE()),"") -> 0.34576758 | F7: =+G6+1 -> 45778 | G7: =+F7+30 -> 45808 | H7: =+F7 -> 45778 | I7: =SUMIFS($C$1:$C$366, $B$1:$B$366, ">="&F7, $B$1:$B$366, "<="&G7) -> 28781.7 | J7: =+I7/1000 -> 28.7817 | L7: =+Batayporã!J7*Amandina!$Q$2 -> 73.29328
A8: Amandina | B8: 45722 | C8: 194.3 | D8: =IFERROR(C8/VLOOKUP(A8,Usinas!$A:$B,2,FALSE()),"") -> 0.27876614 | F8: =+G7+1 -> 45809 | G8: =+F8+29 -> 45838 | H8: =+F8 -> 45809 | I8: =SUMIFS($C$1:$C$366, $B$1:$B$366, ">="&F8, $B$1:$B$366, "<="&G8) -> 20798.2 | J8: =+I8/1000 -> 20.7982 | L8: =+Batayporã!J8*Amandina!$Q$2 -> 57.82952
A9: Amandina | B9: 45723 | C9: 89.9 | D9: =IFERROR(C9/VLOOKUP(A9,Usinas!$A:$B,2,FALSE()),"") -> 0.12898135 | F9: =+G8+1 -> 45839 | G9: =+F9+30 -> 45869 | H9: =+F9 -> 45839 | I9: =SUMIFS($C$1:$C$366, $B$1:$B$366, ">="&F9, $B$1:$B$366, "<="&G9) -> 37317.8 | J9: =+I9/1000 -> 37.3178 | L9: =+Batayporã!J9*Amandina!$Q$2 -> 70.66944
A10: Amandina | B10: 45724 | C10: 357.6 | D10: =IFERROR(C10/VLOOKUP(A10,Usinas!$A:$B,2,FALSE()),"") -> 0.51305595 | F10: =+G9+1 -> 45870 | G10: =+F10+30 -> 45900 | H10: =+F10 -> 45870 | I10: =SUMIFS($C$1:$C$366, $B$1:$B$366, ">="&F10, $B$1:$B$366, "<="&G10) -> 16177.9 | J10: =+I10/1000 -> 16.1779 | L10: =+Batayporã!J10*Amandina!$Q$2 -> 74.46616
A11: Amandina | B11: 45725 | C11: 287 | D11: =IFERROR(C11/VLOOKUP(A11,Usinas!$A:$B,2,FALSE()),"") -> 0.41176471 | F11: =+G10+1 -> 45901 | G11: =+F11+29 -> 45930 | H11: =+F11 -> 45901 | I11: =SUMIFS($C$1:$C$366, $B$1:$B$366, ">="&F11, $B$1:$B$366, "<="&G11) -> 37738.8 | J11: =+I11/1000 -> 37.7388 | L11: =+Batayporã!J11*Amandina!$Q$2 -> 75.54672
A12: Amandina | B12: 45726 | C12: 248.1 | D12: =IFERROR(C12/VLOOKUP(A12,Usinas!$A:$B,2,FALSE()),"") -> 0.35595409 | F12: =+G11+1 -> 45931 | G12: =+F12+30 -> 45961 | H12: =+F12 -> 45931 | I12: =SUMIFS($C$1:$C$366, $B$1:$B$366, ">="&F12, $B$1:$B$366, "<="&G12) -> 40322 | J12: =+I12/1000 -> 40.322 | L12: =+Batayporã!J12*Amandina!$Q$2 -> 76.72544
A13: Amandina | B13: 45727 | C13: 142.1 | D13: =IFERROR(C13/VLOOKUP(A13,Usinas!$A:$B,2,FALSE()),"") -> 0.20387374 | F13: =+G12+1 -> 45962 | G13: =+F13+29 -> 45991 | H13: =+F13 -> 45962 | I13: =SUMIFS($C$1:$C$366, $B$1:$B$366, ">="&F13, $B$1:$B$366, "<="&G13) -> 36462.9 | J13: =+I13/1000 -> 36.4629 | L13: =+Batayporã!J13*Amandina!$Q$2 -> 86.38448
A14: Amandina | B14: 45728 | C14: 224.8 | D14: =IFERROR(C14/VLOOKUP(A14,Usinas!$A:$B,2,FALSE()),"") -> 0.32252511 | F14: =+G13+1 -> 45992 | G14: =+F14+30 -> 46022 | H14: =+F14 -> 45992 | I14: =SUMIFS($C$1:$C$366, $B$1:$B$366, ">="&F14, $B$1:$B$366, "<="&G14) -> 19968.1 | J14: =+I14/1000 -> 19.9681 | L14: =+Batayporã!J14*Amandina!$Q$2 -> 85.28312
A15: Amandina | B15: 45729 | C15: 242.3 | D15: =IFERROR(C15/VLOOKUP(A15,Usinas!$A:$B,2,FALSE()),"") -> 0.34763271
A16: Amandina | B16: 45730 | C16: 288.4 | D16: =IFERROR(C16/VLOOKUP(A16,Usinas!$A:$B,2,FALSE()),"") -> 0.41377331
A17: Amandina | B17: 45731 | C17: 347.5 | D17: =IFERROR(C17/VLOOKUP(A17,Usinas!$A:$B,2,FALSE()),"") -> 0.49856528 | L17: =+SUM(L2:L14) -> 905.92816
A18: Amandina | B18: 45732 | C18: 310.4 | D18: =IFERROR(C18/VLOOKUP(A18,Usinas!$A:$B,2,FALSE()),"") -> 0.44533716
A19: Amandina | B19: 45733 | C19: 278 | D19: =IFERROR(C19/VLOOKUP(A19,Usinas!$A:$B,2,FALSE()),"") -> 0.39885222
A20: Amandina | B20: 45734 | C20: 222.1 | D20: =IFERROR(C20/VLOOKUP(A20,Usinas!$A:$B,2,FALSE()),"") -> 0.31865136
A21: Amandina | B21: 45735 | C21: 332.3 | D21: =IFERROR(C21/VLOOKUP(A21,Usinas!$A:$B,2,FALSE()),"") -> 0.47675753
A22: Amandina | B22: 45736 | C22: 318.3 | D22: =IFERROR(C22/VLOOKUP(A22,Usinas!$A:$B,2,FALSE()),"") -> 0.45667145
A23: Amandina | B23: 45737 | C23: 321.4 | D23: =IFERROR(C23/VLOOKUP(A23,Usinas!$A:$B,2,FALSE()),"") -> 0.46111908
A24: Amandina | B24: 45738 | C24: 272.8 | D24: =IFERROR(C24/VLOOKUP(A24,Usinas!$A:$B,2,FALSE()),"") -> 0.39139168
A25: Amandina | B25: 45739 | C25: 250.5 | D25: =IFERROR(C25/VLOOKUP(A25,Usinas!$A:$B,2,FALSE()),"") -> 0.35939742
A26: Amandina | B26: 45740 | C26: 281.2 | D26: =IFERROR(C26/VLOOKUP(A26,Usinas!$A:$B,2,FALSE()),"") -> 0.40344333
A27: Amandina | B27: 45741 | C27: 264.2 | D27: =IFERROR(C27/VLOOKUP(A27,Usinas!$A:$B,2,FALSE()),"") -> 0.37905308
A28: Amandina | B28: 45742 | C28: 275 | D28: =IFERROR(C28/VLOOKUP(A28,Usinas!$A:$B,2,FALSE()),"") -> 0.39454806
A29: Amandina | B29: 45743 | C29: 297 | D29: =IFERROR(C29/VLOOKUP(A29,Usinas!$A:$B,2,FALSE()),"") -> 0.42611191
... A356: Amandina | B356: 46022 | C356: 990.9 | D356: =IFERROR(C356/VLOOKUP(A356,Usinas!$A:$B,2,FALSE()),"") -> 1.4216643

Sheet Batayporã
A1: Unidade | B1: Data | C1: Geração (kWh) | D1: Yf Diário (kWh/kWp)
A2: Batayporã | B2: 45658 | C2: 3715.4 | D2: =IFERROR(C2/VLOOKUP(A2,Usinas!$A:$B,2,FALSE()),"") -> 5.2925926 | F2: Geração Mensal | H2: Mês | I2: Kwh | J2: MWh
A3: Batayporã | B3: 45659 | C3: 2498.6 | D3: =IFERROR(C3/VLOOKUP(A3,Usinas!$A:$B,2,FALSE()),"") -> 3.5592593 | F3: =+B2 -> 45658 | G3: =+B32 -> 45688 | H3: =+F3 -> 45658 | I3: =SUMIFS($C$1:$C$366, $B$1:$B$366, ">="&F3, $B$1:$B$366, "<="&G3) -> 114259 | J3: =+I3/1000 -> 114.259
A4: Batayporã | B4: 45660 | C4: 4061.9 | D4: =IFERROR(C4/VLOOKUP(A4,Usinas!$A:$B,2,FALSE()),"") -> 5.7861823 | F4: =+B33 -> 45689 | G4: =+F4+27 -> 45716 | H4: =+F4 -> 45689 | I4: =SUMIFS($C$1:$C$366, $B$1:$B$366, ">="&F4, $B$1:$B$366, "<="&G4) -> 91131.9 | J4: =+I4/1000 -> 91.1319
A5: Batayporã | B5: 45661 | C5: 3262.5 | D5: =IFERROR(C5/VLOOKUP(A5,Usinas!$A:$B,2,FALSE()),"") -> 4.6474359 | F5: =+G4+1 -> 45717 | G5: =+F5+30 -> 45747 | H5: =+F5 -> 45717 | I5: =SUMIFS($C$1:$C$366, $B$1:$B$366, ">="&F5, $B$1:$B$366, "<="&G5) -> 103061.9 | J5: =+I5/1000 -> 103.0619
A6: Batayporã | B6: 45662 | C6: 4061 | D6: =IFERROR(C6/VLOOKUP(A6,Usinas!$A:$B,2,FALSE()),"") -> 5.7849003 | F6: =+G5+1 -> 45748 | G6: =+F6+29 -> 45777 | H6: =+F6 -> 45748 | I6: =SUMIFS($C$1:$C$366, $B$1:$B$366, ">="&F6, $B$1:$B$366, "<="&G6) -> 73709.7 | J6: =+I6/1000 -> 73.7097
A7: Batayporã | B7: 45663 | C7: 4431.9 | D7: =IFERROR(C7/VLOOKUP(A7,Usinas!$A:$B,2,FALSE()),"") -> 6.3132479 | F7: =+G6+1 -> 45778 | G7: =+F7+30 -> 45808 | H7: =+F7 -> 45778 | I7: =SUMIFS($C$1:$C$366, $B$1:$B$366, ">="&F7, $B$1:$B$366, "<="&G7) -> 91616.6 | J7: =+I7/1000 -> 91.6166
A8: Batayporã | B8: 45664 | C8: 4460 | D8: =IFERROR(C8/VLOOKUP(A8,Usinas!$A:$B,2,FALSE()),"") -> 6.3532764 | F8: =+G7+1 -> 45809 | G8: =+F8+29 -> 45838 | H8: =+F8 -> 45809 | I8: =SUMIFS($C$1:$C$366, $B$1:$B$366, ">="&F8, $B$1:$B$366, "<="&G8) -> 72286.9 | J8: =+I8/1000 -> 72.2869
A9: Batayporã | B9: 45665 | C9: 3524.3 | D9: =IFERROR(C9/VLOOKUP(A9,Usinas!$A:$B,2,FALSE()),"") -> 5.0203704 | F9: =+G8+1 -> 45839 | G9: =+F9+30 -> 45869 | H9: =+F9 -> 45839 | I9: =SUMIFS($C$1:$C$366, $B$1:$B$366, ">="&F9, $B$1:$B$366, "<="&G9) -> 88336.8 | J9: =+I9/1000 -> 88.3368
A10: Batayporã | B10: 45666 | C10: 4744.5 | D10: =IFERROR(C10/VLOOKUP(A10,Usinas!$A:$B,2,FALSE()),"") -> 6.758547 | F10: =+G9+1 -> 45870 | G10: =+F10+30 -> 45900 | H10: =+F10 -> 45870 | I10: =SUMIFS($C$1:$C$366, $B$1:$B$366, ">="&F10, $B$1:$B$366, "<="&G10) -> 93082.7 | J10: =+I10/1000 -> 93.0827
A11: Batayporã | B11: 45667 | C11: 3305 | D11: =IFERROR(C11/VLOOKUP(A11,Usinas!$A:$B,2,FALSE()),"") -> 4.7079772 | F11: =+G10+1 -> 45901 | G11: =+F11+29 -> 45930 | H11: =+F11 -> 45901 | I11: =SUMIFS($C$1:$C$366, $B$1:$B$366, ">="&F11, $B$1:$B$366, "<="&G11) -> 94433.4 | J11: =+I11/1000 -> 94.4334
A12: Batayporã | B12: 45668 | C12: 4671.1 | D12: =IFERROR(C12/VLOOKUP(A12,Usinas!$A:$B,2,FALSE()),"") -> 6.6539886 | F12: =+G11+1 -> 45931 | G12: =+F12+30 -> 45961 | H12: =+F12 -> 45931 | I12: =SUMIFS($C$1:$C$366, $B$1:$B$366, ">="&F12, $B$1:$B$366, "<="&G12) -> 95906.8 | J12: =+I12/1000 -> 95.9068
A13: Batayporã | B13: 45669 | C13: 4211.9 | D13: =IFERROR(C13/VLOOKUP(A13,Usinas!$A:$B,2,FALSE()),"") -> 5.9998575 | F13: =+G12+1 -> 45962 | G13: =+F13+29 -> 45991 | H13: =+F13 -> 45962 | I13: =SUMIFS($C$1:$C$366, $B$1:$B$366, ">="&F13, $B$1:$B$366, "<="&G13) -> 107980.6 | J13: =+I13/1000 -> 107.9806
A14: Batayporã | B14: 45670 | C14: 4327.1 | D14: =IFERROR(C14/VLOOKUP(A14,Usinas!$A:$B,2,FALSE()),"") -> 6.1639601 | F14: =+G13+1 -> 45992 | G14: =+F14+30 -> 46022 | H14: =+F14 -> 45992 | I14: =SUMIFS($C$1:$C$366, $B$1:$B$366, ">="&F14, $B$1:$B$366, "<="&G14) -> 106603.9 | J14: =+I14/1000 -> 106.6039
A15: Batayporã | B15: 45671 | C15: 4370 | D15: =IFERROR(C15/VLOOKUP(A15,Usinas!$A:$B,2,FALSE()),"") -> 6.2250712
A16: Batayporã | B16: 45672 | C16: 4324 | D16: =IFERROR(C16/VLOOKUP(A16,Usinas!$A:$B,2,FALSE()),"") -> 6.1595442
A17: Batayporã | B17: 45673 | C17: 4173.6 | D17: =IFERROR(C17/VLOOKUP(A17,Usinas!$A:$B,2,FALSE()),"") -> 5.9452991
A18: Batayporã | B18: 45674 | C18: 2490.4 | D18: =IFERROR(C18/VLOOKUP(A18,Usinas!$A:$B,2,FALSE()),"") -> 3.5475783
A19: Batayporã | B19: 45675 | C19: 2419.1 | D19: =IFERROR(C19/VLOOKUP(A19,Usinas!$A:$B,2,FALSE()),"") -> 3.4460114
A20: Batayporã | B20: 45676 | C20: 3206.2 | D20: =IFERROR(C20/VLOOKUP(A20,Usinas!$A:$B,2,FALSE()),"") -> 4.5672365
A21: Batayporã | B21: 45677 | C21: 2768 | D21: =IFERROR(C21/VLOOKUP(A21,Usinas!$A:$B,2,FALSE()),"") -> 3.9430199
A22: Batayporã | B22: 45678 | C22: 3998.4 | D22: =IFERROR(C22/VLOOKUP(A22,Usinas!$A:$B,2,FALSE()),"") -> 5.6957265
A23: Batayporã | B23: 45679 | C23: 2927.9 | D23: =IFERROR(C23/VLOOKUP(A23,Usinas!$A:$B,2,FALSE()),"") -> 4.1707977
A24: Batayporã | B24: 45680 | C24: 3035.9 | D24: =IFERROR(C24/VLOOKUP(A24,Usinas!$A:$B,2,FALSE()),"") -> 4.3246439
A25: Batayporã | B25: 45681 | C25: 4013.7 | D25: =IFERROR(C25/VLOOKUP(A25,Usinas!$A:$B,2,FALSE()),"") -> 5.7175214
A26: Batayporã | B26: 45682 | C26: 3852.9 | D26: =IFERROR(C26/VLOOKUP(A26,Usinas!$A:$B,2,FALSE()),"") -> 5.4884615
... A366: Batayporã | B366: 46022 | C366: 3694.2 | D366: =IFERROR(C366/VLOOKUP(A366,Usinas!$A:$B,2,FALSE()),"") -> 5.2623932

Sheet Novo Horizonte do Sul
A1: Unidade | B1: Data | C1: Geração (kWh) | D1: Yf Diário (kWh/kWp)
A2: Novo Horizonte do Sul | B2: 45659 | C2: 1838.7 | D2: =IFERROR(C2/VLOOKUP(A2,Usinas!$A:$B,2,FALSE()),"") -> 2.9608696 | F2: Geração Mensal | H2: Mês | I2: Kwh | J2: MWh
A3: Novo Horizonte do Sul | B3: 45660 | C3: 2731.7 | D3: =IFERROR(C3/VLOOKUP(A3,Usinas!$A:$B,2,FALSE()),"") -> 4.3988728 | F3: =+B2 -> 45659 | G3: =+F3+29 -> 45688 | H3: =+F3 -> 45659 | I3: =SUMIFS($C$1:$C$366, $B$1:$B$366, ">="&F3, $B$1:$B$366, "<="&G3) -> 83461.9 | J3: =+I3/1000 -> 83.4619
A4: Novo Horizonte do Sul | B4: 45661 | C4: 3144 | D4: =IFERROR(C4/VLOOKUP(A4,Usinas!$A:$B,2,FALSE()),"") -> 5.0628019 | F4: =+G3+1 -> 45689 | G4: =+F4+27 -> 45716 | H4: =+F4 -> 45689 | I4: =SUMIFS($C$1:$C$366, $B$1:$B$366, ">="&F4, $B$1:$B$366, "<="&G4) -> 76124.4 | J4: =+I4/1000 -> 76.1244
A5: Novo Horizonte do Sul | B5: 45662 | C5: 3472.1 | D5: =IFERROR(C5/VLOOKUP(A5,Usinas!$A:$B,2,FALSE()),"") -> 5.5911433 | F5: =+G4+1 -> 45717 | G5: =+F5+30 -> 45747 | H5: =+F5 -> 45717 | I5: =SUMIFS($C$1:$C$366, $B$1:$B$366, ">="&F5, $B$1:$B$366, "<="&G5) -> 89858.2 | J5: =+I5/1000 -> 89.8582
A6: Novo Horizonte do Sul | B6: 45663 | C6: 3397.4 | D6: =IFERROR(C6/VLOOKUP(A6,Usinas!$A:$B,2,FALSE()),"") -> 5.4708535 | F6: =+G5+1 -> 45748 | G6: =+F6+29 -> 45777 | H6: =+F6 -> 45748 | I6: =SUMIFS($C$1:$C$366, $B$1:$B$366, ">="&F6, $B$1:$B$366, "<="&G6) -> 62725.4 | J6: =+I6/1000 -> 62.7254
A7: Novo Horizonte do Sul | B7: 45664 | C7: 3375.8 | D7: =IFERROR(C7/VLOOKUP(A7,Usinas!$A:$B,2,FALSE()),"") -> 5.4360709 | F7: =+G6+1 -> 45778 | G7: =+F7+30 -> 45808 | H7: =+F7 -> 45778 | I7: =SUMIFS($C$1:$C$366, $B$1:$B$366, ">="&F7, $B$1:$B$366, "<="&G7) -> 78227.5 | J7: =+I7/1000 -> 78.2275
A8: Novo Horizonte do Sul | B8: 45665 | C8: 3146.5 | D8: =IFERROR(C8/VLOOKUP(A8,Usinas!$A:$B,2,FALSE()),"") -> 5.0668277 | F8: =+G7+1 -> 45809 | G8: =+F8+29 -> 45838 | H8: =+F8 -> 45809 | I8: =SUMIFS($C$1:$C$366, $B$1:$B$366, ">="&F8, $B$1:$B$366, "<="&G8) -> 60380.6 | J8: =+I8/1000 -> 60.3806
A9: Novo Horizonte do Sul | B9: 45666 | C9: 3235.6 | D9: =IFERROR(C9/VLOOKUP(A9,Usinas!$A:$B,2,FALSE()),"") -> 5.210306 | F9: =+G8+1 -> 45839 | G9: =+F9+30 -> 45869 | H9: =+F9 -> 45839 | I9: =SUMIFS($C$1:$C$366, $B$1:$B$366, ">="&F9, $B$1:$B$366, "<="&G9) -> 76551.2 | J9: =+I9/1000 -> 76.5512
A10: Novo Horizonte do Sul | B10: 45667 | C10: 2990.9 | D10: =IFERROR(C10/VLOOKUP(A10,Usinas!$A:$B,2,FALSE()),"") -> 4.8162641 | F10: =+G9+1 -> 45870 | G10: =+F10+30 -> 45900 | H10: =+F10 -> 45870 | I10: =SUMIFS($C$1:$C$366, $B$1:$B$366, ">="&F10, $B$1:$B$366, "<="&G10) -> 79815.6 | J10: =+I10/1000 -> 79.8156
A11: Novo Horizonte do Sul | B11: 45668 | C11: 3034 | D11: =IFERROR(C11/VLOOKUP(A11,Usinas!$A:$B,2,FALSE()),"") -> 4.8856683 | F11: =+G10+1 -> 45901 | G11: =+F11+29 -> 45930 | H11: =+F11 -> 45901 | I11: =SUMIFS($C$1:$C$366, $B$1:$B$366, ">="&F11, $B$1:$B$366, "<="&G11) -> 78203 | J11: =+I11/1000 -> 78.203
A12: Novo Horizonte do Sul | B12: 45669 | C12: 3316.5 | D12: =IFERROR(C12/VLOOKUP(A12,Usinas!$A:$B,2,FALSE()),"") -> 5.3405797 | F12: =+G11+1 -> 45931 | G12: =+F12+30 -> 45961 | H12: =+F12 -> 45931 | I12: =SUMIFS($C$1:$C$366, $B$1:$B$366, ">="&F12, $B$1:$B$366, "<="&G12) -> 73160.1 | J12: =+I12/1000 -> 73.1601
A13: Novo Horizonte do Sul | B13: 45670 | C13: 3271.8 | D13: =IFERROR(C13/VLOOKUP(A13,Usinas!$A:$B,2,FALSE()),"") -> 5.268599 | F13: =+G12+1 -> 45962 | G13: =+F13+29 -> 45991 | H13: =+F13 -> 45962 | I13: =SUMIFS($C$1:$C$366, $B$1:$B$366, ">="&F13, $B$1:$B$366, "<="&G13) -> 91030.5 | J13: =+I13/1000 -> 91.0305
A14: Novo Horizonte do Sul | B14: 45671 | C14: 2991 | D14: =IFERROR(C14/VLOOKUP(A14,Usinas!$A:$B,2,FALSE()),"") -> 4.8164251 | F14: =+G13+1 -> 45992 | G14: =+F14+30 -> 46022 | H14: =+F14 -> 45992 | I14: =SUMIFS($C$1:$C$366, $B$1:$B$366, ">="&F14, $B$1:$B$366, "<="&G14) -> 88631.7 | J14: =+I14/1000 -> 88.6317
A15: Novo Horizonte do Sul | B15: 45672 | C15: 3157.2 | D15: =IFERROR(C15/VLOOKUP(A15,Usinas!$A:$B,2,FALSE()),"") -> 5.084058
A16: Novo Horizonte do Sul | B16: 45673 | C16: 3240.1 | D16: =IFERROR(C16/VLOOKUP(A16,Usinas!$A:$B,2,FALSE()),"") -> 5.2175523
A17: Novo Horizonte do Sul | B17: 45674 | C17: 2894.7 | D17: =IFERROR(C17/VLOOKUP(A17,Usinas!$A:$B,2,FALSE()),"") -> 4.6613527 | J17: =+SUM(J3:J14) -> 938.1701
A18: Novo Horizonte do Sul | B18: 45675 | C18: 1963.6 | D18: =IFERROR(C18/VLOOKUP(A18,Usinas!$A:$B,2,FALSE()),"") -> 3.1619968
A19: Novo Horizonte do Sul | B19: 45676 | C19: 2656 | D19: =IFERROR(C19/VLOOKUP(A19,Usinas!$A:$B,2,FALSE()),"") -> 4.2769726
A20: Novo Horizonte do Sul | B20: 45677 | C20: 1379.4 | D20: =IFERROR(C20/VLOOKUP(A20,Usinas!$A:$B,2,FALSE()),"") -> 2.221256
A21: Novo Horizonte do Sul | B21: 45678 | C21: 2442.7 | D21: =IFERROR(C21/VLOOKUP(A21,Usinas!$A:$B,2,FALSE()),"") -> 3.9334944
A22: Novo Horizonte do Sul | B22: 45679 | C22: 2855.3 | D22: =IFERROR(C22/VLOOKUP(A22,Usinas!$A:$B,2,FALSE()),"") -> 4.5979066
A23: Novo Horizonte do Sul | B23: 45680 | C23: 1825.6 | D23: =IFERROR(C23/VLOOKUP(A23,Usinas!$A:$B,2,FALSE()),"") -> 2.9397746
A24: Novo Horizonte do Sul | B24: 45681 | C24: 3219.2 | D24: =IFERROR(C24/VLOOKUP(A24,Usinas!$A:$B,2,FALSE()),"") -> 5.1838969
A25: Novo Horizonte do Sul | B25: 45682 | C25: 2932.2 | D25: =IFERROR(C25/VLOOKUP(A25,Usinas!$A:$B,2,FALSE()),"") -> 4.7217391
A26: Novo Horizonte do Sul | B26: 45683 | C26: 2721.4 | D26: =IFERROR(C26/VLOOKUP(A26,Usinas!$A:$B,2,FALSE()),"") -> 4.3822866
A27: Novo Horizonte do Sul | B27: 45684 | C27: 2272 | D27: =IFERROR(C27/VLOOKUP(A27,Usinas!$A:$B,2,FALSE()),"") -> 3.6586151
A28: Novo Horizonte do Sul | B28: 45685 | C28: 2223.6 | D28: =IFERROR(C28/VLOOKUP(A28,Usinas!$A:$B,2,FALSE()),"") -> 3.5806763
A29: Novo Horizonte do Sul | B29: 45686 | C29: 2824.9 | D29: =IFERROR(C29/VLOOKUP(A29,Usinas!$A:$B,2,FALSE()),"") -> 4.5489533
... A364: Novo Horizonte do Sul | B364: 46022 | C364: 2728.3 | D364: =IFERROR(C364/VLOOKUP(A364,Usinas!$A:$B,2,FALSE()),"") -> 4.3933977

Sheet Dados_Consumo_Copasul

Sheet Formula Dados Copasul
D4: 45658 | E4: 45689 | F4: 45717 | G4: 45748 | H4: 45778 | I4: 45809 | J4: 45839 | K4: 45870 | L4: 45901 | M4: 45931 | N4: 45962 | O4: 45992 | Q4: Total | S4: Meia Mensal
A5: Grupo B | B5: Consomo Fora Ponta Grupo B (kWh) | D5: =+SUMIFS('Memória de Massa - 2025'!$H$1:$H$217,'Memória de Massa - 2025'!$A$1:$A$217,'Formula Dados Copasul'!$A5,'Memória de Massa - 2025'!$F$1:$F$217,'Formula Dados Copasul'!D$4) -> 44785.32 | E5: =+SUMIFS('Memória de Massa - 2025'!$H$1:$H$217,'Memória de Massa - 2025'!$A$1:$A$217,'Formula Dados Copasul'!$A5,'Memória de Massa - 2025'!$F$1:$F$217,'Formula Dados Copasul'!E$4) -> 47470.69 | F5: =+SUMIFS('Memória de Massa - 2025'!$H$1:$H$217,'Memória de Massa - 2025'!$A$1:$A$217,'Formula Dados Copasul'!$A5,'Memória de Massa - 2025'!$F$1:$F$217,'Formula Dados Copasul'!F$4) -> 42520.65 | G5: =+SUMIFS('Memória de Massa - 2025'!$H$1:$H$217,'Memória de Massa - 2025'!$A$1:$A$217,'Formula Dados Copasul'!$A5,'Memória de Massa - 2025'!$F$1:$F$217,'Formula Dados Copasul'!G$4) -> 37072.04 | H5: =+SUMIFS('Memória de Massa - 2025'!$H$1:$H$217,'Memória de Massa - 2025'!$A$1:$A$217,'Formula Dados Copasul'!$A5,'Memória de Massa - 2025'!$F$1:$F$217,'Formula Dados Copasul'!H$4) -> 34493.16 | I5: =+SUMIFS('Memória de Massa - 2025'!$H$1:$H$217,'Memória de Massa - 2025'!$A$1:$A$217,'Formula Dados Copasul'!$A5,'Memória de Massa - 2025'!$F$1:$F$217,'Formula Dados Copasul'!I$4) -> 32323.4 | J5: =+SUMIFS('Memória de Massa - 2025'!$H$1:$H$217,'Memória de Massa - 2025'!$A$1:$A$217,'Formula Dados Copasul'!$A5,'Memória de Massa - 2025'!$F$1:$F$217,'Formula Dados Copasul'!J$4) -> 34695.56 | K5: =+SUMIFS('Memória de Massa - 2025'!$H$1:$H$217,'Memória de Massa - 2025'!$A$1:$A$217,'Formula Dados Copasul'!$A5,'Memória de Massa - 2025'!$F$1:$F$217,'Formula Dados Copasul'!K$4) -> 37764.79 | ... O5: =+SUMIFS('Memória de Massa - 2025'!$H$1:$H$217,'Memória de Massa - 2025'!$A$1:$A$217,'Formula Dados Copasul'!$A5,'Memória de Massa - 2025'!$F$1:$F$217,'Formula Dados Copasul'!O$4) -> 48254.06 | Q5: =+SUM(D5:O5) -> 498958.69 | S5: =+Q5/12 -> 41579.891
A6: A4 Verde | B6: Consumo Fora Ponta Grupo A (kWh) | D6: =+SUMIFS('Memória de Massa - 2025'!$H$1:$H$217,'Memória de Massa - 2025'!$A$1:$A$217,'Formula Dados Copasul'!$A6,'Memória de Massa - 2025'!$F$1:$F$217,'Formula Dados Copasul'!D$4) -> 50942.72 | E6: =+SUMIFS('Memória de Massa - 2025'!$H$1:$H$217,'Memória de Massa - 2025'!$A$1:$A$217,'Formula Dados Copasul'!$A6,'Memória de Massa - 2025'!$F$1:$F$217,'Formula Dados Copasul'!E$4) -> 200728.75 | F6: =+SUMIFS('Memória de Massa - 2025'!$H$1:$H$217,'Memória de Massa - 2025'!$A$1:$A$217,'Formula Dados Copasul'!$A6,'Memória de Massa - 2025'!$F$1:$F$217,'Formula Dados Copasul'!F$4) -> 207178.06 | G6: =+SUMIFS('Memória de Massa - 2025'!$H$1:$H$217,'Memória de Massa - 2025'!$A$1:$A$217,'Formula Dados Copasul'!$A6,'Memória de Massa - 2025'!$F$1:$F$217,'Formula Dados Copasul'!G$4) -> 75954.61 | H6: =+SUMIFS('Memória de Massa - 2025'!$H$1:$H$217,'Memória de Massa - 2025'!$A$1:$A$217,'Formula Dados Copasul'!$A6,'Memória de Massa - 2025'!$F$1:$F$217,'Formula Dados Copasul'!H$4) -> 87080.03 | I6: =+SUMIFS('Memória de Massa - 2025'!$H$1:$H$217,'Memória de Massa - 2025'!$A$1:$A$217,'Formula Dados Copasul'!$A6,'Memória de Massa - 2025'!$F$1:$F$217,'Formula Dados Copasul'!I$4) -> 147398.37 | J6: =+SUMIFS('Memória de Massa - 2025'!$H$1:$H$217,'Memória de Massa - 2025'!$A$1:$A$217,'Formula Dados Copasul'!$A6,'Memória de Massa - 2025'!$F$1:$F$217,'Formula Dados Copasul'!J$4) -> 307662.77 | K6: =+SUMIFS('Memória de Massa - 2025'!$H$1:$H$217,'Memória de Massa - 2025'!$A$1:$A$217,'Formula Dados Copasul'!$A6,'Memória de Massa - 2025'!$F$1:$F$217,'Formula Dados Copasul'!K$4) -> 309712.87 | ... O6: =+SUMIFS('Memória de Massa - 2025'!$H$1:$H$217,'Memória de Massa - 2025'!$A$1:$A$217,'Formula Dados Copasul'!$A6,'Memória de Massa - 2025'!$F$1:$F$217,'Formula Dados Copasul'!O$4) -> 11745.55 | Q6: =+SUM(D6:O6) -> 1504995.5 | S6: =+Q6/12 -> 125416.29
A7: A3A rural | B7: Consumo Fora Ponta Grupo A3A Rural (kWh) | D7: =+SUMIFS('Memória de Massa - 2025'!$H$1:$H$217,'Memória de Massa - 2025'!$A$1:$A$217,'Formula Dados Copasul'!$A7,'Memória de Massa - 2025'!$F$1:$F$217,'Formula Dados Copasul'!D$4) -> 72928.49 | E7: =+SUMIFS('Memória de Massa - 2025'!$H$1:$H$217,'Memória de Massa - 2025'!$A$1:$A$217,'Formula Dados Copasul'!$A7,'Memória de Massa - 2025'!$F$1:$F$217,'Formula Dados Copasul'!E$4) -> 212798.25 | F7: =+SUMIFS('Memória de Massa - 2025'!$H$1:$H$217,'Memória de Massa - 2025'!$A$1:$A$217,'Formula Dados Copasul'!$A7,'Memória de Massa - 2025'!$F$1:$F$217,'Formula Dados Copasul'!F$4) -> 177578.42 | G7: =+SUMIFS('Memória de Massa - 2025'!$H$1:$H$217,'Memória de Massa - 2025'!$A$1:$A$217,'Formula Dados Copasul'!$A7,'Memória de Massa - 2025'!$F$1:$F$217,'Formula Dados Copasul'!G$4) -> 84395.43 | H7: =+SUMIFS('Memória de Massa - 2025'!$H$1:$H$217,'Memória de Massa - 2025'!$A$1:$A$217,'Formula Dados Copasul'!$A7,'Memória de Massa - 2025'!$F$1:$F$217,'Formula Dados Copasul'!H$4) -> 106720.74 | I7: =+SUMIFS('Memória de Massa - 2025'!$H$1:$H$217,'Memória de Massa - 2025'!$A$1:$A$217,'Formula Dados Copasul'!$A7,'Memória de Massa - 2025'!$F$1:$F$217,'Formula Dados Copasul'!I$4) -> 183159.59 | J7: =+SUMIFS('Memória de Massa - 2025'!$H$1:$H$217,'Memória de Massa - 2025'!$A$1:$A$217,'Formula Dados Copasul'!$A7,'Memória de Massa - 2025'!$F$1:$F$217,'Formula Dados Copasul'!J$4) -> 223302.56 | K7: =+SUMIFS('Memória de Massa - 2025'!$H$1:$H$217,'Memória de Massa - 2025'!$A$1:$A$217,'Formula Dados Copasul'!$A7,'Memória de Massa - 2025'!$F$1:$F$217,'Formula Dados Copasul'!K$4) -> 130522.46 | ... O7: =+SUMIFS('Memória de Massa - 2025'!$H$1:$H$217,'Memória de Massa - 2025'!$A$1:$A$217,'Formula Dados Copasul'!$A7,'Memória de Massa - 2025'!$F$1:$F$217,'Formula Dados Copasul'!O$4) -> 15428.7 | Q7: =+SUM(D7:O7) -> 1245343.7 | S7: =+Q7/12 -> 103778.64
B9: Total Fora Ponta (kWh) | D9: =+SUM(D5:D7) -> 168656.53 | E9: =+SUM(E5:E7) -> 460997.69 | F9: =+SUM(F5:F7) -> 427277.13 | G9: =+SUM(G5:G7) -> 197422.08 | H9: =+SUM(H5:H7) -> 228293.93 | I9: =+SUM(I5:I7) -> 362881.36 | J9: =+SUM(J5:J7) -> 565660.89 | K9: =+SUM(K5:K7) -> 478000.12 | ... O9: =+SUM(O5:O7) -> 75428.31 | Q9: =+SUM(D9:O9) -> 3249297.9 | S9: =+Q9/12 -> 270774.83
A11: A4 Verde | B11: Consumo Ponta Grupo A (kWh) | D11: =+SUMIFS('Memória de Massa - 2025'!$G$1:$G$217,'Memória de Massa - 2025'!$A$1:$A$217,'Formula Dados Copasul'!$A11,'Memória de Massa - 2025'!$F$1:$F$217,'Formula Dados Copasul'!D$4) -> 10827.94 | E11: =+SUMIFS('Memória de Massa - 2025'!$G$1:$G$217,'Memória de Massa - 2025'!$A$1:$A$217,'Formula Dados Copasul'!$A11,'Memória de Massa - 2025'!$F$1:$F$217,'Formula Dados Copasul'!E$4) -> 37839.9 | F11: =+SUMIFS('Memória de Massa - 2025'!$G$1:$G$217,'Memória de Massa - 2025'!$A$1:$A$217,'Formula Dados Copasul'!$A11,'Memória de Massa - 2025'!$F$1:$F$217,'Formula Dados Copasul'!F$4) -> 27093.4 | G11: =+SUMIFS('Memória de Massa - 2025'!$G$1:$G$217,'Memória de Massa - 2025'!$A$1:$A$217,'Formula Dados Copasul'!$A11,'Memória de Massa - 2025'!$F$1:$F$217,'Formula Dados Copasul'!G$4) -> 4120.62 | H11: =+SUMIFS('Memória de Massa - 2025'!$G$1:$G$217,'Memória de Massa - 2025'!$A$1:$A$217,'Formula Dados Copasul'!$A11,'Memória de Massa - 2025'!$F$1:$F$217,'Formula Dados Copasul'!H$4) -> 7310.48 | I11: =+SUMIFS('Memória de Massa - 2025'!$G$1:$G$217,'Memória de Massa - 2025'!$A$1:$A$217,'Formula Dados Copasul'!$A11,'Memória de Massa - 2025'!$F$1:$F$217,'Formula Dados Copasul'!I$4) -> 22180.07 | J11: =+SUMIFS('Memória de Massa - 2025'!$G$1:$G$217,'Memória de Massa - 2025'!$A$1:$A$217,'Formula Dados Copasul'!$A11,'Memória de Massa - 2025'!$F$1:$F$217,'Formula Dados Copasul'!J$4) -> 53060.15 | K11: =+SUMIFS('Memória de Massa - 2025'!$G$1:$G$217,'Memória de Massa - 2025'!$A$1:$A$217,'Formula Dados Copasul'!$A11,'Memória de Massa - 2025'!$F$1:$F$217,'Formula Dados Copasul'!K$4) -> 44066.23 | ... O11: =+SUMIFS('Memória de Massa - 2025'!$G$1:$G$217,'Memória de Massa - 2025'!$A$1:$A$217,'Formula Dados Copasul'!$A11,'Memória de Massa - 2025'!$F$1:$F$217,'Formula Dados Copasul'!O$4) -> 2595.31 | Q11: =+SUM(D11:O11) -> 224581.82 | S11: =+Q11/12 -> 18715.152
A12: A3A rural | B12: Consumo Ponta Grupo A3A (kWh) | D12: =+SUMIFS('Memória de Massa - 2025'!$G$1:$G$217,'Memória de Massa - 2025'!$A$1:$A$217,'Formula Dados Copasul'!$A12,'Memória de Massa - 2025'!$F$1:$F$217,'Formula Dados Copasul'!D$4) -> 9264.15 | E12: =+SUMIFS('Memória de Massa - 2025'!$G$1:$G$217,'Memória de Massa - 2025'!$A$1:$A$217,'Formula Dados Copasul'!$A12,'Memória de Massa - 2025'!$F$1:$F$217,'Formula Dados Copasul'!E$4) -> 19948.64 | F12: =+SUMIFS('Memória de Massa - 2025'!$G$1:$G$217,'Memória de Massa - 2025'!$A$1:$A$217,'Formula Dados Copasul'!$A12,'Memória de Massa - 2025'!$F$1:$F$217,'Formula Dados Copasul'!F$4) -> 14932.89 | G12: =+SUMIFS('Memória de Massa - 2025'!$G$1:$G$217,'Memória de Massa - 2025'!$A$1:$A$217,'Formula Dados Copasul'!$A12,'Memória de Massa - 2025'!$F$1:$F$217,'Formula Dados Copasul'!G$4) -> 2769.48 | H12: =+SUMIFS('Memória de Massa - 2025'!$G$1:$G$217,'Memória de Massa - 2025'!$A$1:$A$217,'Formula Dados Copasul'!$A12,'Memória de Massa - 2025'!$F$1:$F$217,'Formula Dados Copasul'!H$4) -> 7312.1 | I12: =+SUMIFS('Memória de Massa - 2025'!$G$1:$G$217,'Memória de Massa - 2025'!$A$1:$A$217,'Formula Dados Copasul'!$A12,'Memória de Massa - 2025'!$F$1:$F$217,'Formula Dados Copasul'!I$4) -> 19556.78 | J12: =+SUMIFS('Memória de Massa - 2025'!$G$1:$G$217,'Memória de Massa - 2025'!$A$1:$A$217,'Formula Dados Copasul'!$A12,'Memória de Massa - 2025'!$F$1:$F$217,'Formula Dados Copasul'!J$4) -> 37585.8 | K12: =+SUMIFS('Memória de Massa - 2025'!$G$1:$G$217,'Memória de Massa - 2025'!$A$1:$A$217,'Formula Dados Copasul'!$A12,'Memória de Massa - 2025'!$F$1:$F$217,'Formula Dados Copasul'!K$4) -> 19255.01 | ... O12: =+SUMIFS('Memória de Massa - 2025'!$G$1:$G$217,'Memória de Massa - 2025'!$A$1:$A$217,'Formula Dados Copasul'!$A12,'Memória de Massa - 2025'!$F$1:$F$217,'Formula Dados Copasul'!O$4) -> 1514.84 | Q12: =+SUM(D12:O12) -> 138419.85 | S12: =+Q12/12 -> 11534.988
B14: Total Ponta (kWh) | D14: =+SUM(D11:D12) -> 20092.09 | E14: =+SUM(E11:E12) -> 57788.54 | F14: =+SUM(F11:F12) -> 42026.29 | G14: =+SUM(G11:G12) -> 6890.1 | H14: =+SUM(H11:H12) -> 14622.58 | I14: =+SUM(I11:I12) -> 41736.85 | J14: =+SUM(J11:J12) -> 90645.95 | K14: =+SUM(K11:K12) -> 63321.24 | ... O14: =+SUM(O11:O12) -> 4110.15 | Q14: =+SUM(D14:O14) -> 363001.67 | S14: =+Q14/12 -> 30250.139
B17: Total Consumo (kWh) | D17: =+SUM(D14,D9) -> 188748.62 | E17: =+SUM(E14,E9) -> 518786.23 | F17: =+SUM(F14,F9) -> 469303.42 | G17: =+SUM(G14,G9) -> 204312.18 | H17: =+SUM(H14,H9) -> 242916.51 | I17: =+SUM(I14,I9) -> 404618.21 | J17: =+SUM(J14,J9) -> 656306.84 | K17: =+SUM(K14,K9) -> 541321.36 | ... O17: =+SUM(O14,O9) -> 79538.46 | Q17: =+SUM(Q14,Q9) -> 3612299.6 | S17: =+Q17/12 -> 301024.96
A20: SiIos Novo Horizonte do Sul | B20: Produçao Usina 1 | D20: =+SUMIFS('Memória de Massa - 2025'!$K$1:$K$217,'Memória de Massa - 2025'!$B$1:$B$217,$A20,'Memória de Massa - 2025'!$F$1:$F$217,'Formula Dados Copasul'!D$4) -> 83461.9 | E20: =+SUMIFS('Memória de Massa - 2025'!$K$1:$K$217,'Memória de Massa - 2025'!$B$1:$B$217,$A20,'Memória de Massa - 2025'!$F$1:$F$217,'Formula Dados Copasul'!E$4) -> 76124.4 | F20: =+SUMIFS('Memória de Massa - 2025'!$K$1:$K$217,'Memória de Massa - 2025'!$B$1:$B$217,$A20,'Memória de Massa - 2025'!$F$1:$F$217,'Formula Dados Copasul'!F$4) -> 89858.2 | G20: =+SUMIFS('Memória de Massa - 2025'!$K$1:$K$217,'Memória de Massa - 2025'!$B$1:$B$217,$A20,'Memória de Massa - 2025'!$F$1:$F$217,'Formula Dados Copasul'!G$4) -> 62725.4 | H20: =+SUMIFS('Memória de Massa - 2025'!$K$1:$K$217,'Memória de Massa - 2025'!$B$1:$B$217,$A20,'Memória de Massa - 2025'!$F$1:$F$217,'Formula Dados Copasul'!H$4) -> 78227.5 | I20: =+SUMIFS('Memória de Massa - 2025'!$K$1:$K$217,'Memória de Massa - 2025'!$B$1:$B$217,$A20,'Memória de Massa - 2025'!$F$1:$F$217,'Formula Dados Copasul'!I$4) -> 60380.6 | J20: =+SUMIFS('Memória de Massa - 2025'!$K$1:$K$217,'Memória de Massa - 2025'!$B$1:$B$217,$A20,'Memória de Massa - 2025'!$F$1:$F$217,'Formula Dados Copasul'!J$4) -> 76551.2 | K20: =+SUMIFS('Memória de Massa - 2025'!$K$1:$K$217,'Memória de Massa - 2025'!$B$1:$B$217,$A20,'Memória de Massa - 2025'!$F$1:$F$217,'Formula Dados Copasul'!K$4) -> 79815.6 | ... O20: =+SUMIFS('Memória de Massa - 2025'!$K$1:$K$217,'Memória de Massa - 2025'!$B$1:$B$217,$A20,'Memória de Massa - 2025'!$F$1:$F$217,'Formula Dados Copasul'!O$4) -> 88631.7 | Q20: =+SUM(D20:O20) -> 938170.1 | S20: =+Q20/12 -> 78180.842
A21: Silos Batayporã | B21: Produção Usina 2 | D21: =+SUMIFS('Memória de Massa - 2025'!$K$1:$K$217,'Memória de Massa - 2025'!$B$1:$B$217,$A21,'Memória de Massa - 2025'!$F$1:$F$217,'Formula Dados Copasul'!D$4) -> 114259 | E21: =+SUMIFS('Memória de Massa - 2025'!$K$1:$K$217,'Memória de Massa - 2025'!$B$1:$B$217,$A21,'Memória de Massa - 2025'!$F$1:$F$217,'Formula Dados Copasul'!E$4) -> 91131.9 | F21: =+SUMIFS('Memória de Massa - 2025'!$K$1:$K$217,'Memória de Massa - 2025'!$B$1:$B$217,$A21,'Memória de Massa - 2025'!$F$1:$F$217,'Formula Dados Copasul'!F$4) -> 103061.9 | G21: =+SUMIFS('Memória de Massa - 2025'!$K$1:$K$217,'Memória de Massa - 2025'!$B$1:$B$217,$A21,'Memória de Massa - 2025'!$F$1:$F$217,'Formula Dados Copasul'!G$4) -> 73709.7 | H21: =+SUMIFS('Memória de Massa - 2025'!$K$1:$K$217,'Memória de Massa - 2025'!$B$1:$B$217,$A21,'Memória de Massa - 2025'!$F$1:$F$217,'Formula Dados Copasul'!H$4) -> 91616.6 | I21: =+SUMIFS('Memória de Massa - 2025'!$K$1:$K$217,'Memória de Massa - 2025'!$B$1:$B$217,$A21,'Memória de Massa - 2025'!$F$1:$F$217,'Formula Dados Copasul'!I$4) -> 72286.9 | J21: =+SUMIFS('Memória de Massa - 2025'!$K$1:$K$217,'Memória de Massa - 2025'!$B$1:$B$217,$A21,'Memória de Massa - 2025'!$F$1:$F$217,'Formula Dados Copasul'!J$4) -> 88336.8 | K21: =+SUMIFS('Memória de Massa - 2025'!$K$1:$K$217,'Memória de Massa - 2025'!$B$1:$B$217,$A21,'Memória de Massa - 2025'!$F$1:$F$217,'Formula Dados Copasul'!K$4) -> 93082.7 | ... O21: =+SUMIFS('Memória de Massa - 2025'!$K$1:$K$217,'Memória de Massa - 2025'!$B$1:$B$217,$A21,'Memória de Massa - 2025'!$F$1:$F$217,'Formula Dados Copasul'!O$4) -> 106603.9 | Q21: =+SUM(D21:O21) -> 1132410.2 | S21: =+Q21/12 -> 94367.517
A22: Silos Amandina | B22: Produção Usina 3 | D22: =+SUMIFS('Memória de Massa - 2025'!$K$1:$K$217,'Memória de Massa - 2025'!$B$1:$B$217,$A22,'Memória de Massa - 2025'!$F$1:$F$217,'Formula Dados Copasul'!D$4) -> 0 | E22: =+SUMIFS('Memória de Massa - 2025'!$K$1:$K$217,'Memória de Massa - 2025'!$B$1:$B$217,$A22,'Memória de Massa - 2025'!$F$1:$F$217,'Formula Dados Copasul'!E$4) -> 190.1 | F22: =+SUMIFS('Memória de Massa - 2025'!$K$1:$K$217,'Memória de Massa - 2025'!$B$1:$B$217,$A22,'Memória de Massa - 2025'!$F$1:$F$217,'Formula Dados Copasul'!F$4) -> 7913.8 | G22: =+SUMIFS('Memória de Massa - 2025'!$K$1:$K$217,'Memória de Massa - 2025'!$B$1:$B$217,$A22,'Memória de Massa - 2025'!$F$1:$F$217,'Formula Dados Copasul'!G$4) -> 23902.8 | H22: =+SUMIFS('Memória de Massa - 2025'!$K$1:$K$217,'Memória de Massa - 2025'!$B$1:$B$217,$A22,'Memória de Massa - 2025'!$F$1:$F$217,'Formula Dados Copasul'!H$4) -> 28781.7 | I22: =+SUMIFS('Memória de Massa - 2025'!$K$1:$K$217,'Memória de Massa - 2025'!$B$1:$B$217,$A22,'Memória de Massa - 2025'!$F$1:$F$217,'Formula Dados Copasul'!I$4) -> 20798.2 | J22: =+SUMIFS('Memória de Massa - 2025'!$K$1:$K$217,'Memória de Massa - 2025'!$B$1:$B$217,$A22,'Memória de Massa - 2025'!$F$1:$F$217,'Formula Dados Copasul'!J$4) -> 37317.8 | K22: =+SUMIFS('Memória de Massa - 2025'!$K$1:$K$217,'Memória de Massa - 2025'!$B$1:$B$217,$A22,'Memória de Massa - 2025'!$F$1:$F$217,'Formula Dados Copasul'!K$4) -> 16177.9 | ... O22: =+SUMIFS('Memória de Massa - 2025'!$K$1:$K$217,'Memória de Massa - 2025'!$B$1:$B$217,$A22,'Memória de Massa - 2025'!$F$1:$F$217,'Formula Dados Copasul'!O$4) -> 19968.1 | Q22: =+SUM(D22:O22) -> 269574.1 | S22: =+Q22/12 -> 22464.508
B24: Total Produção (kWH) | D24: =+SUM(D20:D22) -> 197720.9 | E24: =+SUM(E20:E22) -> 167446.4 | F24: =+SUM(F20:F22) -> 200833.9 | G24: =+SUM(G20:G22) -> 160337.9 | H24: =+SUM(H20:H22) -> 198625.8 | I24: =+SUM(I20:I22) -> 153465.7 | J24: =+SUM(J20:J22) -> 202205.8 | K24: =+SUM(K20:K22) -> 189076.2 | ... O24: =+SUM(O20:O22) -> 215203.7 | Q24: =+SUM(Q20:Q22) -> 2340154.4 | S24: =+SUM(S20:S22) -> 195012.87
A26: SiIos Novo Horizonte do Sul | B26: Compensão usina 1 | D26: =+SUMIFS('Memória de Massa - 2025'!$L$1:$L$217,'Memória de Massa - 2025'!$B$1:$B$217,$A26,'Memória de Massa - 2025'!$F$1:$F$217,'Formula Dados Copasul'!D$4) -> 54986 | E26: =+SUMIFS('Memória de Massa - 2025'!$L$1:$L$217,'Memória de Massa - 2025'!$B$1:$B$217,$A26,'Memória de Massa - 2025'!$F$1:$F$217,'Formula Dados Copasul'!E$4) -> 188910 | F26: =+SUMIFS('Memória de Massa - 2025'!$L$1:$L$217,'Memória de Massa - 2025'!$B$1:$B$217,$A26,'Memória de Massa - 2025'!$F$1:$F$217,'Formula Dados Copasul'!F$4) -> 32411 | G26: =+SUMIFS('Memória de Massa - 2025'!$L$1:$L$217,'Memória de Massa - 2025'!$B$1:$B$217,$A26,'Memória de Massa - 2025'!$F$1:$F$217,'Formula Dados Copasul'!G$4) -> 41488 | H26: =+SUMIFS('Memória de Massa - 2025'!$L$1:$L$217,'Memória de Massa - 2025'!$B$1:$B$217,$A26,'Memória de Massa - 2025'!$F$1:$F$217,'Formula Dados Copasul'!H$4) -> 55127 | I26: =+SUMIFS('Memória de Massa - 2025'!$L$1:$L$217,'Memória de Massa - 2025'!$B$1:$B$217,$A26,'Memória de Massa - 2025'!$F$1:$F$217,'Formula Dados Copasul'!I$4) -> 24600 | J26: =+SUMIFS('Memória de Massa - 2025'!$L$1:$L$217,'Memória de Massa - 2025'!$B$1:$B$217,$A26,'Memória de Massa - 2025'!$F$1:$F$217,'Formula Dados Copasul'!J$4) -> 10848 | K26: =+SUMIFS('Memória de Massa - 2025'!$L$1:$L$217,'Memória de Massa - 2025'!$B$1:$B$217,$A26,'Memória de Massa - 2025'!$F$1:$F$217,'Formula Dados Copasul'!K$4) -> 37261 | ... O26: =+SUMIFS('Memória de Massa - 2025'!$L$1:$L$217,'Memória de Massa - 2025'!$B$1:$B$217,$A26,'Memória de Massa - 2025'!$F$1:$F$217,'Formula Dados Copasul'!O$4) -> 8737 | Q26: =+SUM(D26:O26) -> 547684 | S26: =+Q26/12 -> 45640.333
A27: Silos Batayporã | B27: Compensão usina 2 | D27: =+SUMIFS('Memória de Massa - 2025'!$L$1:$L$217,'Memória de Massa - 2025'!$B$1:$B$217,$A27,'Memória de Massa - 2025'!$F$1:$F$217,'Formula Dados Copasul'!D$4) -> 6785 | E27: =+SUMIFS('Memória de Massa - 2025'!$L$1:$L$217,'Memória de Massa - 2025'!$B$1:$B$217,$A27,'Memória de Massa - 2025'!$F$1:$F$217,'Formula Dados Copasul'!E$4) -> 36315 | F27: =+SUMIFS('Memória de Massa - 2025'!$L$1:$L$217,'Memória de Massa - 2025'!$B$1:$B$217,$A27,'Memória de Massa - 2025'!$F$1:$F$217,'Formula Dados Copasul'!F$4) -> 63697 | G27: =+SUMIFS('Memória de Massa - 2025'!$L$1:$L$217,'Memória de Massa - 2025'!$B$1:$B$217,$A27,'Memória de Massa - 2025'!$F$1:$F$217,'Formula Dados Copasul'!G$4) -> 38586 | H27: =+SUMIFS('Memória de Massa - 2025'!$L$1:$L$217,'Memória de Massa - 2025'!$B$1:$B$217,$A27,'Memória de Massa - 2025'!$F$1:$F$217,'Formula Dados Copasul'!H$4) -> 37159 | I27: =+SUMIFS('Memória de Massa - 2025'!$L$1:$L$217,'Memória de Massa - 2025'!$B$1:$B$217,$A27,'Memória de Massa - 2025'!$F$1:$F$217,'Formula Dados Copasul'!I$4) -> 36580 | J27: =+SUMIFS('Memória de Massa - 2025'!$L$1:$L$217,'Memória de Massa - 2025'!$B$1:$B$217,$A27,'Memória de Massa - 2025'!$F$1:$F$217,'Formula Dados Copasul'!J$4) -> 64186 | K27: =+SUMIFS('Memória de Massa - 2025'!$L$1:$L$217,'Memória de Massa - 2025'!$B$1:$B$217,$A27,'Memória de Massa - 2025'!$F$1:$F$217,'Formula Dados Copasul'!K$4) -> 59224 | ... O27: =+SUMIFS('Memória de Massa - 2025'!$L$1:$L$217,'Memória de Massa - 2025'!$B$1:$B$217,$A27,'Memória de Massa - 2025'!$F$1:$F$217,'Formula Dados Copasul'!O$4) -> 5604 | Q27: =+SUM(D27:O27) -> 389018 | S27: =+Q27/12 -> 32418.167
A28: Silos Amandina | B28: Compensão usina 3 | D28: =+SUMIFS('Memória de Massa - 2025'!$L$1:$L$217,'Memória de Massa - 2025'!$B$1:$B$217,$A28,'Memória de Massa - 2025'!$F$1:$F$217,'Formula Dados Copasul'!D$4) -> 0 | E28: =+SUMIFS('Memória de Massa - 2025'!$L$1:$L$217,'Memória de Massa - 2025'!$B$1:$B$217,$A28,'Memória de Massa - 2025'!$F$1:$F$217,'Formula Dados Copasul'!E$4) -> 0 | F28: =+SUMIFS('Memória de Massa - 2025'!$L$1:$L$217,'Memória de Massa - 2025'!$B$1:$B$217,$A28,'Memória de Massa - 2025'!$F$1:$F$217,'Formula Dados Copasul'!F$4) -> 419 | G28: =+SUMIFS('Memória de Massa - 2025'!$L$1:$L$217,'Memória de Massa - 2025'!$B$1:$B$217,$A28,'Memória de Massa - 2025'!$F$1:$F$217,'Formula Dados Copasul'!G$4) -> 1423 | H28: =+SUMIFS('Memória de Massa - 2025'!$L$1:$L$217,'Memória de Massa - 2025'!$B$1:$B$217,$A28,'Memória de Massa - 2025'!$F$1:$F$217,'Formula Dados Copasul'!H$4) -> 9127 | I28: =+SUMIFS('Memória de Massa - 2025'!$L$1:$L$217,'Memória de Massa - 2025'!$B$1:$B$217,$A28,'Memória de Massa - 2025'!$F$1:$F$217,'Formula Dados Copasul'!I$4) -> 7190 | J28: =+SUMIFS('Memória de Massa - 2025'!$L$1:$L$217,'Memória de Massa - 2025'!$B$1:$B$217,$A28,'Memória de Massa - 2025'!$F$1:$F$217,'Formula Dados Copasul'!J$4) -> 9165 | K28: =+SUMIFS('Memória de Massa - 2025'!$L$1:$L$217,'Memória de Massa - 2025'!$B$1:$B$217,$A28,'Memória de Massa - 2025'!$F$1:$F$217,'Formula Dados Copasul'!K$4) -> 5142 | ... O28: =+SUMIFS('Memória de Massa - 2025'!$L$1:$L$217,'Memória de Massa - 2025'!$B$1:$B$217,$A28,'Memória de Massa - 2025'!$F$1:$F$217,'Formula Dados Copasul'!O$4) -> 16944 | Q28: =+SUM(D28:O28) -> 94200 | S28: =+Q28/12 -> 7850
B30: Total Compensação (kWH) | D30: =+SUM(D26:D28) -> 61771 | E30: =+SUM(E26:E28) -> 225225 | F30: =+SUM(F26:F28) -> 96527 | G30: =+SUM(G26:G28) -> 81497 | H30: =+SUM(H26:H28) -> 101413 | I30: =+SUM(I26:I28) -> 68370 | J30: =+SUM(J26:J28) -> 84199 | K30: =+SUM(K26:K28) -> 101627 | ... O30: =+SUM(O26:O28) -> 31285 | Q30: =+SUM(Q26:Q28) -> 1030902 | S30: =+SUM(S26:S28) -> 85908.5

Sheet Memória de Massa - 2025
B1: Nome | C1: CNPJ | D1: UC | E1: Grupo | F1: Mês | G1: Consumo Ponta (kWh) | H1: Consumo Fora Ponta (kWh) | I1: Demanda Ponta (kW) | J1: Demanda Fora Ponta (kW) | K1: Energia Gerada (kWh) | L1: Energia Compensada (kWh) | O1: Energia Sobrando | P1: Energia Gerada Pos reparação | R1: Compensação Fora Ponta
A2: Grupo B | B2: Galpão AE | C2: 03.902.129/0001-83 | D2: 10/169099-9 | E2: B3 - Comercial | F2: 45992 | H2: 518
A3: Grupo B | B3: Galpão AE | C3: 03.902.129/0001-83 | D3: 10/169099-9 | E3: B3 - Comercial | F3: 45962 | H3: 467
A4: Grupo B | B4: Galpão AE | C4: 03.902.129/0001-83 | D4: 10/169099-9 | E4: B3 - Comercial | F4: 45931 | H4: 596
A5: Grupo B | B5: Galpão AE | C5: 03.902.129/0001-83 | D5: 10/169099-9 | E5: B3 - Comercial | F5: 45901 | H5: 523
A6: Grupo B | B6: Galpão AE | C6: 03.902.129/0001-83 | D6: 10/169099-9 | E6: B3 - Comercial | F6: 45870 | H6: 1194
A7: Grupo B | B7: Galpão AE | C7: 03.902.129/0001-83 | D7: 10/169099-9 | E7: B3 - Comercial | F7: 45839 | H7: 1194
A8: Grupo B | B8: Galpão AE | C8: 03.902.129/0001-83 | D8: 10/169099-9 | E8: B3 - Comercial | F8: 45809 | H8: 275
A9: Grupo B | B9: Galpão AE | C9: 03.902.129/0001-83 | D9: 10/169099-9 | E9: B3 - Comercial | F9: 45778 | H9: 272
A10: Grupo B | B10: Galpão AE | C10: 03.902.129/0001-83 | D10: 10/169099-9 | E10: B3 - Comercial | F10: 45748 | H10: 259
A11: Grupo B | B11: Galpão AE | C11: 03.902.129/0001-83 | D11: 10/169099-9 | E11: B3 - Comercial | F11: 45717 | H11: 258
A12: Grupo B | B12: Galpão AE | C12: 03.902.129/0001-83 | D12: 10/169099-9 | E12: B3 - Comercial | F12: 45689 | H12: 305
A13: Grupo B | B13: Galpão AE | C13: 03.902.129/0001-83 | D13: 10/169099-9 | E13: B3 - Comercial | F13: 45658 | H13: 264
... A97: Grupo B | B97: Subestação Fiação | C97: 03.902.129/0015-89 | D97: 10/2418582-9 | E97: B3 - Comercial | F97: 45658 | H97: 1554
A98: A4 Verde | B98: SiIos Novo Horizonte do Sul | C98: 03.902.129/0020-46 | D98: 10/3184070-5 | E98: Verde A4 - Industrial | F98: 45992 | G98: 1502.26 | H98: 7234.75 | I98: 56.45 | J98: 112.3 | K98: 88631.7 | L98: 8737
A99: A4 Verde | B99: SiIos Novo Horizonte do Sul | C99: 03.902.129/0020-46 | D99: 10/3184070-5 | E99: Verde A4 - Industrial | F99: 45962 | G99: 1235.14 | H99: 6608.62 | I99: 102.14 | J99: 108.19 | K99: 91030.5 | L99: 7844
A100: A4 Verde | B100: SiIos Novo Horizonte do Sul | C100: 03.902.129/0020-46 | D100: 10/3184070-5 | E100: Verde A4 - Industrial | F100: 45931 | G100: 1434.05 | H100: 8440.99 | I100: 38.3 | J100: 147.17 | K100: 73160.1 | L100: 9875
A101: A4 Verde | B101: SiIos Novo Horizonte do Sul | C101: 03.902.129/0020-46 | D101: 10/3184070-5 | E101: Verde A4 - Industrial | F101: 45901 | G101: 9308.38 | H101: 66288.6 | I101: 821.18 | J101: 782.88 | K101: 78203 | L101: 75597
A102: A4 Verde | B102: SiIos Novo Horizonte do Sul | C102: 03.902.129/0020-46 | D102: 10/3184070-5 | E102: Verde A4 - Industrial | F102: 45870 | G102: 32243.23 | H102: 262311.67 | I102: 1065.12 | J102: 1015.39 | K102: 79815.6 | L102: 37261
A103: A4 Verde | B103: SiIos Novo Horizonte do Sul | C103: 03.902.129/0020-46 | D103: 10/3184070-5 | E103: Verde A4 - Industrial | F103: 45839 | G103: 39585.5 | H103: 256951.97 | I103: 1024.8 | J103: 993.89 | K103: 76551.2 | L103: 10848
A104: A4 Verde | B104: SiIos Novo Horizonte do Sul | C104: 03.902.129/0020-46 | D104: 10/3184070-5 | E104: Verde A4 - Industrial | F104: 45809 | G104: 16950.02 | H104: 116048.52 | I104: 870.91 | J104: 868.22 | K104: 60380.6 | L104: 24600
A105: A4 Verde | B105: SiIos Novo Horizonte do Sul | C105: 03.902.129/0020-46 | D105: 10/3184070-5 | E105: Verde A4 - Industrial | F105: 45778 | G105: 6013.73 | H105: 51218.33 | I105: 452.93 | J105: 456.96 | K105: 78227.5 | L105: 55127
A106: A4 Verde | B106: SiIos Novo Horizonte do Sul | C106: 03.902.129/0020-46 | D106: 10/3184070-5 | E106: Verde A4 - Industrial | F106: 45748 | G106: 2938.32 | H106: 38550.46 | I106: 441.5 | J106: 485.18 | K106: 62725.4 | L106: 41488
A107: A4 Verde | B107: SiIos Novo Horizonte do Sul | C107: 03.902.129/0020-46 | D107: 10/3184070-5 | E107: Verde A4 - Industrial | F107: 45717 | G107: 17348.35 | H107: 153225.91 | I107: 831.26 | J107: 799.01 | K107: 89858.2 | L107: 32411
A108: A4 Verde | B108: SiIos Novo Horizonte do Sul | C108: 03.902.129/0020-46 | D108: 10/3184070-5 | E108: Verde A4 - Industrial | F108: 45689 | G108: 29874.6 | H108: 172378.75 | I108: 846.05 | J108: 864.19 | K108: 76124.4 | L108: 188910
A109: A4 Verde | B109: SiIos Novo Horizonte do Sul | C109: 03.902.129/0020-46 | D109: 10/3184070-5 | E109: Verde A4 - Industrial | F109: 45658 | G109: 9630.94 | H109: 45354.62 | I109: 605.47 | J109: 516.77 | K109: 83461.9 | L109: 54986
A110: Grupo B | B110: Deposito Irrigação | C110: 03.902.129/0023-99 | D110: 10/2551502-4 | E110: B3 - Comercial | F110: 45992 | H110: 838
A111: Grupo B | B111: Deposito Irrigação | C111: 03.902.129/0023-99 | D111: 10/2551502-4 | E111: B3 - Comercial | F111: 45962 | H111: 925
A112: Grupo B | B112: Deposito Irrigação | C112: 03.902.129/0023-99 | D112: 10/2551502-4 | E112: B3 - Comercial | F112: 45931 | H112: 943
A113: Grupo B | B113: Deposito Irrigação | C113: 03.902.129/0023-99 | D113: 10/2551502-4 | E113: B3 - Comercial | F113: 45901 | H113: 719
A114: Grupo B | B114: Deposito Irrigação | C114: 03.902.129/0023-99 | D114: 10/2551502-4 | E114: B3 - Comercial | F114: 45870 | H114: 816
A115: Grupo B | B115: Deposito Irrigação | C115: 03.902.129/0023-99 | D115: 10/2551502-4 | E115: B3 - Comercial | F115: 45839 | H115: 899
A116: Grupo B | B116: Deposito Irrigação | C116: 03.902.129/0023-99 | D116: 10/2551502-4 | E116: B3 - Comercial | F116: 45809 | H116: 1067
A117: Grupo B | B117: Deposito Irrigação | C117: 03.902.129/0023-99 | D117: 10/2551502-4 | E117: B3 - Comercial | F117: 45778 | H117: 1146
A118: Grupo B | B118: Deposito Irrigação | C118: 03.902.129/0023-99 | D118: 10/2551502-4 | E118: B3 - Comercial | F118: 45748 | H118: 1026
A119: Grupo B | B119: Deposito Irrigação | C119: 03.902.129/0023-99 | D119: 10/2551502-4 | E119: B3 - Comercial | F119: 45717 | H119: 1030
A120: Grupo B | B120: Deposito Irrigação | C120: 03.902.129/0023-99 | D120: 10/2551502-4 | E120: B3 - Comercial | F120: 45689 | H120: 887
A121: Grupo B | B121: Deposito Irrigação | C121: 03.902.129/0023-99 | D121: 10/2551502-4 | E121: B3 - Comercial | F121: 45658 | H121: 876
A122: A3A rural | B122: Silos Amandina | C122: 03.902.129/0025-50 | D122: 10/3267347-7 | E122: Verde A3a - Rural | F122: 45992 | G122: 1514.84 | H122: 15428.7 | I122: 30.24 | J122: 217.98 | K122: 19968.1 | L122: 16944 | O122: =+K122-L122 -> 3024.1 | P122: =+VLOOKUP(F122,Amandina!$H$4:$L$14,5,0)*1000 -> 85283.12 | R122: =+P122-H122 -> 69854.42
A123: A3A rural | B123: Silos Amandina | C123: 03.902.129/0025-50 | D123: 10/3267347-7 | E123: Verde A3a - Rural | F123: 45962 | G123: 1437.03 | H123: 8808.98 | I123: 103.32 | J123: 100.8 | K123: 36462.9 | L123: 10246 | O123: =+K123-L123 -> 26216.9 | P123: =+VLOOKUP(F123,Amandina!$H$4:$L$14,5,0)*1000 -> 86384.48
A124: A3A rural | B124: Silos Amandina | C124: 03.902.129/0025-50 | D124: 10/3267347-7 | E124: Verde A3a - Rural | F124: 45931 | G124: 2102.94 | H124: 11731.55 | I124: 167.58 | J124: 165.06 | K124: 40322 | L124: 13835 | O124: =+K124-L124 -> 26487 | P124: =+VLOOKUP(F124,Amandina!$H$4:$L$14,5,0)*1000 -> 76725.44
A125: A3A rural | B125: Silos Amandina | C125: 03.902.129/0025-50 | D125: 10/3267347-7 | E125: Verde A3a - Rural | F125: 45901 | G125: 2740.19 | H125: 17968.55 | I125: 168.84 | J125: 196.56 | K125: 37738.8 | L125: 20709 | O125: =+K125-L125 -> 17029.8 | P125: =+VLOOKUP(F125,Amandina!$H$4:$L$14,5,0)*1000 -> 75546.72
A126: A3A rural | B126: Silos Amandina | C126: 03.902.129/0025-50 | D126: 10/3267347-7 | E126: Verde A3a - Rural | F126: 45870 | G126: 19255.01 | H126: 130522.46 | I126: 793.8 | J126: 869.4 | K126: 16177.9 | L126: 5142 | O126: =+K126-L126 -> 11035.9 | P126: =+VLOOKUP(F126,Amandina!$H$4:$L$14,5,0)*1000 -> 74466.16
A127: A3A rural | B127: Silos Amandina | C127: 03.902.129/0025-50 | D127: 10/3267347-7 | E127: Verde A3a - Rural | F127: 45839 | G127: 37585.8 | H127: 223302.56 | I127: 904.68 | J127: 916.02 | K127: 37317.8 | L127: 9165 | O127: =+K127-L127 -> 28152.8 | P127: =+VLOOKUP(F127,Amandina!$H$4:$L$14,5,0)*1000 -> 70669.44
A128: A3A rural | B128: Silos Amandina | C128: 03.902.129/0025-50 | D128: 10/3267347-7 | E128: Verde A3a - Rural | F128: 45809 | G128: 19556.78 | H128: 183159.59 | I128: 747.18 | J128: 845.46 | K128: 20798.2 | L128: 7190 | O128: =+K128-L128 -> 13608.2 | P128: =+VLOOKUP(F128,Amandina!$H$4:$L$14,5,0)*1000 -> 57829.52
A129: A3A rural | B129: Silos Amandina | C129: 03.902.129/0025-50 | D129: 10/3267347-7 | E129: Verde A3a - Rural | F129: 45778 | G129: 7312.1 | H129: 106720.74 | I129: 486.36 | J129: 784.98 | K129: 28781.7 | L129: 9127 | O129: =+K129-L129 -> 19654.7 | P129: =+VLOOKUP(F129,Amandina!$H$4:$L$14,5,0)*1000 -> 73293.28
A130: A3A rural | B130: Silos Amandina | C130: 03.902.129/0025-50 | D130: 10/3267347-7 | E130: Verde A3a - Rural | F130: 45748 | G130: 2769.48 | H130: 84395.43 | I130: 110.88 | J130: 560.7 | K130: 23902.8 | L130: 1423 | O130: =+K130-L130 -> 22479.8 | P130: =+VLOOKUP(F130,Amandina!$H$4:$L$14,5,0)*1000 -> 58967.76
A131: A3A rural | B131: Silos Amandina | C131: 03.902.129/0025-50 | D131: 10/3267347-7 | E131: Verde A3a - Rural | F131: 45717 | G131: 14932.89 | H131: 177578.42 | I131: 913.5 | J131: 923.58 | K131: 7913.8 | L131: 419 | O131: =+K131-L131 -> 7494.8 | P131: =+VLOOKUP(F131,Amandina!$H$4:$L$14,5,0)*1000 -> 82449.52
A132: A3A rural | B132: Silos Amandina | C132: 03.902.129/0025-50 | D132: 10/3267347-7 | E132: Verde A3a - Rural | F132: 45689 | G132: 19948.64 | H132: 212798.25 | I132: 763.56 | J132: 790.02 | K132: 190.1 | L132: 0 | O132: =+K132-L132 -> 190.1 | P132: =+Batayporã!J4*80%*1000 -> 72905.52
A133: A3A rural | B133: Silos Amandina | C133: 03.902.129/0025-50 | D133: 10/3267347-7 | E133: Verde A3a - Rural | F133: 45658 | G133: 9264.15 | H133: 72928.49 | I133: 704.34 | J133: 758.52 | K133: 0 | L133: 0 | O133: =+K133-L133 -> 0 | P133: =+Batayporã!J3*80%*1000 -> 91407.2
A134: Grupo B | B134: Escritório Nova Andradina | C134: 03.902.129/0026-31 | D134: 10/3683986-8 | E134: B3 - Comercial | F134: 45992 | H134: 3227
A135: Grupo B | B135: Escritório Nova Andradina | C135: 03.902.129/0026-31 | D135: 10/3683986-8 | E135: B3 - Comercial | F135: 45962 | H135: 2090
A136: Grupo B | B136: Escritório Nova Andradina | C136: 03.902.129/0026-31 | D136: 10/3683986-8 | E136: B3 - Comercial | F136: 45931 | H136: 2593
A137: Grupo B | B137: Escritório Nova Andradina | C137: 03.902.129/0026-31 | D137: 10/3683986-8 | E137: B3 - Comercial | F137: 45901 | H137: 2469
A138: Grupo B | B138: Escritório Nova Andradina | C138: 03.902.129/0026-31 | D138: 10/3683986-8 | E138: B3 - Comercial | F138: 45870 | H138: 1448
A139: Grupo B | B139: Escritório Nova Andradina | C139: 03.902.129/0026-31 | D139: 10/3683986-8 | E139: B3 - Comercial | F139: 45839 | H139: 1317
A140: Grupo B | B140: Escritório Nova Andradina | C140: 03.902.129/0026-31 | D140: 10/3683986-8 | E140: B3 - Comercial | F140: 45809 | H140: 1362
A141: Grupo B | B141: Escritório Nova Andradina | C141: 03.902.129/0026-31 | D141: 10/3683986-8 | E141: B3 - Comercial | F141: 45778 | H141: 2238
A142: Grupo B | B142: Escritório Nova Andradina | C142: 03.902.129/0026-31 | D142: 10/3683986-8 | E142: B3 - Comercial | F142: 45748 | H142: 2511
A143: Grupo B | B143: Escritório Nova Andradina | C143: 03.902.129/0026-31 | D143: 10/3683986-8 | E143: B3 - Comercial | F143: 45717 | H143: 3281
A144: Grupo B | B144: Escritório Nova Andradina | C144: 03.902.129/0026-31 | D144: 10/3683986-8 | E144: B3 - Comercial | F144: 45689 | H144: 3394
A145: Grupo B | B145: Escritório Nova Andradina | C145: 03.902.129/0026-31 | D145: 10/3683986-8 | E145: B3 - Comercial | F145: 45658 | H145: 3370
A146: A4 Verde | B146: Silos Batayporã | C146: 03.902.129/0031-07 | D146: 10/2121803-7 | E146: Verde A4 - Industrial | F146: 45992 | G146: 1093.05 | H146: 4510.8 | I146: 25.2 | J146: 42 | K146: 106603.9 | L146: 5604
A147: A4 Verde | B147: Silos Batayporã | C147: 03.902.129/0031-07 | D147: 10/2121803-7 | E147: Verde A4 - Industrial | F147: 45962 | G147: 1019.55 | H147: 4500.3 | I147: 79.8 | J147: 71.4 | K147: 107980.6 | L147: 5520
A148: A4 Verde | B148: Silos Batayporã | C148: 03.902.129/0031-07 | D148: 10/2121803-7 | E148: Verde A4 - Industrial | F148: 45931 | G148: 1132.95 | H148: 4884.6 | I148: 21 | J148: 46.2 | K148: 95906.8 | L148: 6018
A149: A4 Verde | B149: Silos Batayporã | C149: 03.902.129/0031-07 | D149: 10/2121803-7 | E149: Verde A4 - Industrial | F149: 45901 | G149: 1357.65 | H149: 15868.65 | I149: 142.8 | J149: 151.2 | K149: 94433.4 | L149: 29344
A150: A4 Verde | B150: Silos Batayporã | C150: 03.902.129/0031-07 | D150: 10/2121803-7 | E150: Verde A4 - Industrial | F150: 45870 | G150: 11823 | H150: 47401.2 | I150: 407.4 | J150: 390.6 | K150: 93082.7 | L150: 59224
A151: A4 Verde | B151: Silos Batayporã | C151: 03.902.129/0031-07 | D151: 10/2121803-7 | E151: Verde A4 - Industrial | F151: 45839 | G151: 13474.65 | H151: 50710.8 | I151: 382.2 | J151: 394.8 | K151: 88336.8 | L151: 64186
A152: A4 Verde | B152: Silos Batayporã | C152: 03.902.129/0031-07 | D152: 10/2121803-7 | E152: Verde A4 - Industrial | F152: 45809 | G152: 5230.05 | H152: 31349.85 | I152: 352.8 | J152: 357 | K152: 72286.9 | L152: 36580
A153: A4 Verde | B153: Silos Batayporã | C153: 03.902.129/0031-07 | D153: 10/2121803-7 | E153: Verde A4 - Industrial | F153: 45778 | G153: 1296.75 | H153: 35861.7 | I153: 79.8 | J153: 197.4 | K153: 91616.6 | L153: 37159
A154: A4 Verde | B154: Silos Batayporã | C154: 03.902.129/0031-07 | D154: 10/2121803-7 | E154: Verde A4 - Industrial | F154: 45748 | G154: 1182.3 | H154: 37404.15 | I154: 168 | J154: 197.4 | K154: 73709.7 | L154: 38586
A155: A4 Verde | B155: Silos Batayporã | C155: 03.902.129/0031-07 | D155: 10/2121803-7 | E155: Verde A4 - Industrial | F155: 45717 | G155: 9745.05 | H155: 53952.15 | I155: 378 | J155: 369.6 | K155: 103061.9 | L155: 63697
A156: A4 Verde | B156: Silos Batayporã | C156: 03.902.129/0031-07 | D156: 10/2121803-7 | E156: Verde A4 - Industrial | F156: 45689 | G156: 7965.3 | H156: 28350 | I156: 361.2 | J156: 327.6 | K156: 91131.9 | L156: 36315
A157: A4 Verde | B157: Silos Batayporã | C157: 03.902.129/0031-07 | D157: 10/2121803-7 | E157: Verde A4 - Industrial | F157: 45658 | G157: 1197 | H157: 5588.1 | I157: 25.2 | J157: 25.2 | K157: 114259 | L157: 6785
A158: Grupo B | B158: Irrigação Copasul Campo Grande | C158: 03.902.129/0032-80 | D158: 10/2603357-1 | E158: B3 - Comercial | F158: 45992 | H158: 1260
A159: Grupo B | B159: Irrigação Copasul Campo Grande | C159: 03.902.129/0032-80 | D159: 10/2603357-1 | E159: B3 - Comercial | F159: 45962 | H159: 900
A160: Grupo B | B160: Irrigação Copasul Campo Grande | C160: 03.902.129/0032-80 | D160: 10/2603357-1 | E160: B3 - Comercial | F160: 45931 | H160: 939
A161: Grupo B | B161: Irrigação Copasul Campo Grande | C161: 03.902.129/0032-80 | D161: 10/2603357-1 | E161: B3 - Comercial | F161: 45901 | H161: 750
A162: Grupo B | B162: Irrigação Copasul Campo Grande | C162: 03.902.129/0032-80 | D162: 10/2603357-1 | E162: B3 - Comercial | F162: 45870 | H162: 525
A163: Grupo B | B163: Irrigação Copasul Campo Grande | C163: 03.902.129/0032-80 | D163: 10/2603357-1 | E163: B3 - Comercial | F163: 45839 | H163: 475
A164: Grupo B | B164: Irrigação Copasul Campo Grande | C164: 03.902.129/0032-80 | D164: 10/2603357-1 | E164: B3 - Comercial | F164: 45809 | H164: 554
A165: Grupo B | B165: Irrigação Copasul Campo Grande | C165: 03.902.129/0032-80 | D165: 10/2603357-1 | E165: B3 - Comercial | F165: 45778 | H165: 733
A166: Grupo B | B166: Irrigação Copasul Campo Grande | C166: 03.902.129/0032-80 | D166: 10/2603357-1 | E166: B3 - Comercial | F166: 45748 | H166: 915
A167: Grupo B | B167: Irrigação Copasul Campo Grande | C167: 03.902.129/0032-80 | D167: 10/2603357-1 | E167: B3 - Comercial | F167: 45717 | H167: 1180
A168: Grupo B | B168: Irrigação Copasul Campo Grande | C168: 03.902.129/0032-80 | D168: 10/2603357-1 | E168: B3 - Comercial | F168: 45689 | H168: 1100
A169: Grupo B | B169: Irrigação Copasul Campo Grande | C169: 03.902.129/0032-80 | D169: 10/2603357-1 | E169: B3 - Comercial | F169: 45658 | H169: 1140
... A217: Grupo B | B217: Posto Carreteiro | C217: 48.657.758/0001-23 | D217: 10/2502804-4 | E217: B3 - Comercial | F217: 45658 | H217: 11760

Sheet Dados_Produção_Helexia

Sheet Usinas_Helexia_PR
B3: Código | C3: Nome do Projeto | D3: Data | E3: Mês | F3: Nº Mês | G3: Ano de Exposição Solar | H3: Ano de Geração | I3: Geração (MWh)
B4: HCS01 | C4: Cassilândia 01 | D4: 45383 | E4: Apr | F4: 4 | G4: 2024 | H4: Ano 0 | I4: 37.227
B5: HCS01 | C5: Cassilândia 01 | D5: 45413 | E5: May | F5: 5 | G5: 2024 | H5: Ano 0 | I5: 66.274
B6: HCS01 | C6: Cassilândia 01 | D6: 45444 | E6: Jun | F6: 6 | G6: 2024 | H6: Ano 0 | I6: 54.743
B7: HCS01 | C7: Cassilândia 01 | D7: 45474 | E7: Jul | F7: 7 | G7: 2024 | H7: Ano 0 | I7: 100.242
B8: HCS01 | C8: Cassilândia 01 | D8: 45505 | E8: Aug | F8: 8 | G8: 2024 | H8: Ano 0 | I8: 114.491
B9: HCS01 | C9: Cassilândia 01 | D9: 45536 | E9: Sept | F9: 9 | G9: 2024 | H9: Ano 0 | I9: 101.6523
B10: HCS01 | C10: Cassilândia 01 | D10: 45566 | E10: Oct | F10: 10 | G10: 2024 | H10: Ano 0 | I10: 88.6151
B11: HCS01 | C11: Cassilândia 01 | D11: 45597 | E11: Nov | F11: 11 | G11: 2024 | H11: Ano 0 | I11: 99.3694
B12: HCS01 | C12: Cassilândia 01 | D12: 45627 | E12: Dec | F12: 12 | G12: 2024 | H12: Ano 0 | I12: 77.1956
B13: HCS01 | C13: Cassilândia 01 | D13: 45658 | E13: Jan | F13: 1 | G13: 2024 | H13: Ano 1 | I13: 105.4782
B14: HCS01 | C14: Cassilândia 01 | D14: 45689 | E14: Feb | F14: 2 | G14: 2024 | H14: Ano 1 | I14: 85
B15: HCS01 | C15: Cassilândia 01 | D15: 45717 | E15: Mar | F15: 3 | G15: 2024 | H15: Ano 1 | I15: 100.1787
... B25: HCS01 | C25: Cassilândia 01 | D25: 46023 | E25: Jan | F25: 1 | G25: 2024 | H25: Ano 2 | I25: 106.7224
B29: Código | C29: Nome do Projeto | D29: Data | E29: Mês | F29: Nº Mês | G29: Ano de Exposição Solar | H29: Ano de Geração | I29: Geração (MWh)
B30: HCS02 | C30: Cassilândia 02 | D30: 45383 | E30: Apr | F30: 4 | G30: 2024 | H30: Ano 0 | I30: 32.672
B31: HCS02 | C31: Cassilândia 02 | D31: 45413 | E31: May | F31: 5 | G31: 2024 | H31: Ano 0 | I31: 108.947
B32: HCS02 | C32: Cassilândia 02 | D32: 45444 | E32: Jun | F32: 6 | G32: 2024 | H32: Ano 0 | I32: 92.917
B33: HCS02 | C33: Cassilândia 02 | D33: 45474 | E33: Jul | F33: 7 | G33: 2024 | H33: Ano 0 | I33: 163.0883
B34: HCS02 | C34: Cassilândia 02 | D34: 45505 | E34: Aug | F34: 8 | G34: 2024 | H34: Ano 0 | I34: 189.0879
B35: HCS02 | C35: Cassilândia 02 | D35: 45536 | E35: Sept | F35: 9 | G35: 2024 | H35: Ano 0 | I35: 176.1752
B36: HCS02 | C36: Cassilândia 02 | D36: 45566 | E36: Oct | F36: 10 | G36: 2024 | H36: Ano 0 | I36: 161.1117
B37: HCS02 | C37: Cassilândia 02 | D37: 45597 | E37: Nov | F37: 11 | G37: 2024 | H37: Ano 0 | I37: 169.5114
B38: HCS02 | C38: Cassilândia 02 | D38: 45627 | E38: Dec | F38: 12 | G38: 2024 | H38: Ano 0 | I38: 166.9964
B39: HCS02 | C39: Cassilândia 02 | D39: 45658 | E39: Jan | F39: 1 | G39: 2024 | H39: Ano 1 | I39: 190.9089
B40: HCS02 | C40: Cassilândia 02 | D40: 45689 | E40: Feb | F40: 2 | G40: 2024 | H40: Ano 1 | I40: 166
B41: HCS02 | C41: Cassilândia 02 | D41: 45717 | E41: Mar | F41: 3 | G41: 2024 | H41: Ano 1 | I41: 193.4294
... B51: HCS02 | C51: Cassilândia 02 | D51: 46023 | E51: Jan | F51: 1 | G51: 2024 | H51: Ano 2 | I51: 184.9512
B56: Código | C56: Nome do Projeto | D56: Data | E56: Mês | F56: Nº Mês | G56: Ano de Exposição Solar | H56: Ano de Geração | I56: Geração (MWh)
B57: HCS03 | C57: Cassilândia 03 | D57: 45383 | E57: Apr | F57: 4 | G57: 2024 | H57: Ano 0 | I57: 70.926
B58: HCS03 | C58: Cassilândia 03 | D58: 45413 | E58: May | F58: 5 | G58: 2024 | H58: Ano 0 | I58: 74.153
B59: HCS03 | C59: Cassilândia 03 | D59: 45444 | E59: Jun | F59: 6 | G59: 2024 | H59: Ano 0 | I59: 62.902
B60: HCS03 | C60: Cassilândia 03 | D60: 45474 | E60: Jul | F60: 7 | G60: 2024 | H60: Ano 0 | I60: 107.0881
B61: HCS03 | C61: Cassilândia 03 | D61: 45505 | E61: Aug | F61: 8 | G61: 2024 | H61: Ano 0 | I61: 51.7493
B62: HCS03 | C62: Cassilândia 03 | D62: 45536 | E62: Sept | F62: 9 | G62: 2024 | H62: Ano 0 | I62: 107.0198
B63: HCS03 | C63: Cassilândia 03 | D63: 45566 | E63: Oct | F63: 10 | G63: 2024 | H63: Ano 0 | I63: 98.5846
B64: HCS03 | C64: Cassilândia 03 | D64: 45597 | E64: Nov | F64: 11 | G64: 2024 | H64: Ano 0 | I64: 119.2367
B65: HCS03 | C65: Cassilândia 03 | D65: 45627 | E65: Dec | F65: 12 | G65: 2024 | H65: Ano 0 | I65: 111.1389
B66: HCS03 | C66: Cassilândia 03 | D66: 45658 | E66: Jan | F66: 1 | G66: 2024 | H66: Ano 1 | I66: 143.3821
B67: HCS03 | C67: Cassilândia 03 | D67: 45689 | E67: Feb | F67: 2 | G67: 2024 | H67: Ano 1 | I67: 121
B68: HCS03 | C68: Cassilândia 03 | D68: 45717 | E68: Mar | F68: 3 | G68: 2024 | H68: Ano 1 | I68: 141.1858
... B78: HCS03 | C78: Cassilândia 03 | D78: 46023 | E78: Jan | F78: 1 | G78: 2024 | H78: Ano 2 | I78: 131.6157
B84: Performance Ratio
B85: Código | C85: Nome do Projeto | D85: Data do PR | E85: Mês do PR | F85: Ano do PR | G85: Ano de Exposição Solar | H85: Ano de Geração | I85: PR PVsyst (%) | J85: PR Real (%) | K85: Status
B86: HCS01 | C86: Cassilândia 01 | D86: 45444 | E86: Jun | F86: 2024 | G86: 2024 | H86: Ano 0 | I86: 0 | J86: 0.5467 | K86: Aprovado
B87: HCS01 | C87: Cassilândia 01 | D87: 45536 | E87: Sept | F87: 2024 | G87: 2024 | H87: Ano 0 | I87: 0 | J87: 0.7026 | K87: Aprovado
B88: HCS01 | C88: Cassilândia 01 | D88: 45597 | E88: Nov | F88: 2024 | G88: 2024 | H88: Ano 0 | I88: 0 | J88: 0.731 | K88: Aprovado
B89: HCS01 | C89: Cassilândia 01 | D89: 45717 | E89: Mar | F89: 2025 | G89: 2024 | H89: Ano 1 | I89: 0 | J89: 0.7486 | K89: Aprovado
B93: Código | C93: Nome do Projeto | D93: Data do PR | E93: Mês do PR | F93: Ano do PR | G93: Ano de Exposição Solar | H93: Ano de Geração | I93: PR PVsyst (%) | J93: PR Real (%) | K93: Status
B94: HCS02 | C94: Cassilândia 02 | D94: 45536 | E94: Sept | F94: 2024 | G94: 2024 | H94: Ano 0 | I94: 0 | J94: 0.7175 | K94: Aprovado
B95: HCS02 | C95: Cassilândia 02 | D95: 45597 | E95: Nov | F95: 2024 | G95: 2024 | H95: Ano 0 | I95: 0 | J95: 0.7949 | K95: Aprovado
B96: HCS02 | C96: Cassilândia 02 | D96: 45717 | E96: Mar | F96: 2025 | G96: 2024 | H96: Ano 1 | I96: 0 | J96: 0.799 | K96: Aprovado
B99: Código | C99: Nome do Projeto | D99: Data do PR | E99: Mês do PR | F99: Ano do PR | G99: Ano de Exposição Solar | H99: Ano de Geração | I99: PR PVsyst (%) | J99: PR Real (%) | K99: Status
B100: HCS03 | C100: Cassilândia 03 | D100: 45536 | E100: Sept | F100: 2024 | G100: 2024 | H100: Ano 0 | I100: 0 | J100: 0.5715 | K100: Aprovado
B101: HCS03 | C101: Cassilândia 03 | D101: 45597 | E101: Nov | F101: 2024 | G101: 2024 | H101: Ano 0 | I101: 0 | J101: 0.7971 | K101: Aprovado
B102: HCS03 | C102: Cassilândia 03 | D102: 45717 | E102: Mar | F102: 2025 | G102: 2024 | H102: Ano 1 | I102: 0 | J102: 0.8001 | K102: Aprovado

Sheet PVSYST_Helexia
J2: =+COUNTA($B$5:J5) -> 9 | K2: =+COUNTA($B$5:K5) -> 10 | L2: =+COUNTA($B$5:L5) -> 11 | M2: =+COUNTA($B$5:M5) -> 12 | N2: =+COUNTA($B$5:N5) -> 13 | O2: =+COUNTA($B$5:O5) -> 14 | P2: =+COUNTA($B$5:P5) -> 15 | Q2: =+COUNTA($B$5:Q5) -> 16 | ... U2: =+COUNTA($B$5:U5) -> 20
B3: PV Syst | J3: Jan | K3: Fev | L3: Mar | M3: Abr | N3: Mai | O3: Jun | P3: Jul | Q3: Ago | R3: Set | S3: Out | T3: Nov | U3: Dez
A4: Código | B4: Nome do Projeto | C4: Distribuidora | D4: Status | E4: Cliente | F4: Potência AC (kWac) | G4: Potência DC (kWp) | H4: Ano de Exposição Solar | I4: Ano de Geração | J4: janeiro | K4: fevereiro | L4: março | M4: abril | N4: maio | O4: junho | P4: julho | Q4: agosto | R4: setembro | S4: outubro | T4: novembro | U4: dezembro | V4: Geração P50 Ano 0 (MWh/ano) | W4: Geração P50 Ano Atual (MWh/ano) | X4: Variabilidade Anual (%) | Y4: Geração P90 PVsyst Ano 0 (MWh/ano) | Z4: Geração P90 PVsyst Ano Atual (MWh/ano) | AA4: Geração P90 Ano Atual Real (MWh/ano) | AB4: PR Médio Ano 0 | AC4: PR Médio Ano Atual | AD4: Produção Específica | AE4: Fator de Capacidade | AF4: Versão PVsyst | AG4: Variante PVsyst | AH4: Data PVsyst | AI4: Observação | AJ4: Link Report
A5: HCS01 | B5: Cassilândia 01 | C5: EMS | D5: Entregue | E5: COMERC | F5: 500 | G5: 626.4 | H5: 2024 | I5: 2 | J5: 105.88 | K5: 109.34 | L5: 120.94 | M5: 113.72 | N5: 105.37 | O5: 89.609 | P5: 99.212 | Q5: 121.11 | R5: 114.6 | S5: 118.18 | T5: 107.05 | U5: 116.84 | V5: 1330.553 | W5: 1321.851 | X5: 3.083 | Y5: 1278.0052 | Z5: 1269.6468 | AA5: 1198.2407 | AB5: 0.81885833 | AC5: 0.81344167 | AD5: 2110.2347 | AE5: 0.30179247 | AF5: As Built | AG5: VCH | AH5: 45993 | AI5: Considerando perdas nos cabos e transformador conforme Projeto Executivo. Além de perdas por sujidade e indisponibilidade conforme premissas do O&M | AJ5: Clique Aqui
A6: HCS02 | B6: Cassilândia 02 | C6: EMS | D6: Entregue | E6: COMERC | F6: 875 | G6: 1127.52 | H6: 2024 | I6: 2 | J6: 189.47 | K6: 194.28 | L6: 214.77 | M6: 202.63 | N6: 189.07 | O6: 171.58 | P6: 181 | Q6: 217.01 | R6: 204.19 | S6: 181 | T6: 203.55 | U6: 207.27 | V6: 2369.92 | W6: 2355.82 | X6: 3.083 | Y6: 2276.3242 | Z6: 2262.7811 | AA6: 2135.5202 | AB6: 0.81225 | AC6: 0.80731667 | AD6: 2089.382 | AE6: 0.30734768 | AF6: As Built | AG6: VCI | AH6: 45993 | AI6: Considerando perdas nos cabos e transformador conforme Projeto Executivo. Além de perdas por sujidade e indisponibilidade conforme premissas do O&M | AJ6: Clique Aqui
A7: HCS03 | B7: Cassilândia 03 | C7: EMS | D7: Entregue | E7: COMERC | F7: 625 | G7: 814.32 | H7: 2024 | I7: 2 | J7: 143.14 | K7: 127.55 | L7: 146.3 | M7: 145.98 | N7: 136.62 | O7: 123.99 | P7: 130.51 | Q7: 156.67 | R7: 147.01 | S7: 151.08 | T7: 146.08 | U7: 138.71 | V7: 1703.67 | W7: 1693.64 | X7: 3.083 | Y7: 1636.3866 | Z7: 1626.7527 | AA7: 1535.2626 | AB7: 0.80775 | AC7: 0.80291667 | AD7: 2079.8212 | AE7: 0.30934064 | AF7: As Built | AG7: VCJ | AH7: 45993 | AI7: Considerando perdas nos cabos e transformador conforme Projeto Executivo. Além de perdas por sujidade e indisponibilidade conforme premissas do O&M | AJ7: Clique Aqui
B12: Produçao 2025 | J12: Jan | K12: Fev | L12: Mar | M12: Abr | N12: Mai | O12: Jun | P12: Jul | Q12: Ago | R12: Set | S12: Out | T12: Nov | U12: Dez | V12: Geração Atual Ano 0 (MWh/ano) | W12: January 26 | X12: February 26
A13: Código | B13: Nome do Projeto | C13: Distribuidora | D13: Status | E13: Cliente | F13: Potência AC (kWac) | G13: Potência DC (kWp) | H13: Ano de Exposição Solar | I13: Ano de Geração | J13: janeiro | K13: fevereiro | L13: março | M13: abril | N13: maio | O13: junho | P13: julho | Q13: agosto | R13: setembro | S13: outubro | T13: novembro | U13: dezembro | V13: Geração Atual Ano 0 (MWh/ano)
A14: HCS01 | B14: Cassilândia 01 | C14: EMS | D14: Entregue | E14: COMERC | F14: 500 | G14: 626.4 | H14: 2024 | I14: 2
A15: HCS02 | B15: Cassilândia 02 | C15: EMS | D15: Entregue | E15: COMERC | F15: 875 | G15: 1127.52 | H15: 2024 | I15: 2 | J15: 188.55 | K15: 166 | L15: 193.4294 | M15: 144.1346 | N15: 158.6377 | O15: 128.6395 | P15: 178.3455 | Q15: 190.7348 | R15: 200.2328 | S15: 185.5502 | T15: 215.3495 | U15: 181.5256 | V15: 2131.1296 | W15: 184.9512 | X15: 157.439
A16: HCS03 | B16: Cassilândia 03 | C16: EMS | D16: Entregue | E16: COMERC | F16: 625 | G16: 814.32 | H16: 2024 | I16: 2 | J16: 143.48 | K16: 121 | L16: 141.1858 | M16: 105.1116 | N16: 121.0391 | O16: 99.4716 | P16: 127.0078 | Q16: 134.7817 | R16: 139.8889 | S16: 128.4246 | T16: 153.3072 | U16: 130.3996 | V16: 1545.0979 | W16: 131.6157 | X16: 110.621

Sheet Usinas
A1: Unidade | B1: Pi (kWp) | C1: Pg (kW) | D1: Número de módulos | E1: Potencia (W) | F1: Eficiência | G1: Área do módulo (m²) | H1: Área Total (m²) | I1: Densidade de Potência (W/m²) | J1: Latitude | K1: Longitude | L1: Inclinação | M1: Azimuth
A2: Novo Horizonte do Sul | B2: 621 | C2: 500 | D2: 1800 | E2: 345 | F2: 0.174 | G2: 1.9 | H2: =D2*G2 -> 3420 | I2: =D2*E2/H2 -> 181.57895 | J2: -22.67340908 | K2: -53.84513269 | L2: 22° | M2: 0
A3: Batayporã | B3: 702 | C3: 500 | D3: 1560 | E3: 450 | F3: 0.204 | G3: 2.209184 | H3: =D3*G3 -> 3446.327 | I3: =D3*E3/H3 -> 203.69512 | J3: -22.27609989 | K3: -53.22534149
A4: Amandina | B4: 697 | C4: 500 | D4: 1700 | E4: 410 | F4: 0.203 | G4: 2.022036 | H4: =D4*G4 -> 3437.4612 | I4: =D4*E4/H4 -> 202.76593 | J4: -22.34231564 | K4: -53.58536212
