Workbook

Sheet Resumo
B1: SIMULAÇÃO RATEIO FIXO — Cassilândia 03 × COPASUL | Resumo Executivo
B2: 18 Unidades Consumidoras · Jun/2026–Mai/2036 · Energisa MS · Usina: Cassilândia 03 · 120 meses
B4: ⚡ GERAÇÃO INJETADA | D4: 📄 PPA PAGO À HELEXIA | F4: ✅ ECONOMIA LÍQUIDA | H4: 🏦 BANCO RESIDUAL | J4: 🌟 VALOR TOTAL
B5: =Simulacao!B6 -> 9214611.7 | D5: =Simulacao!B7 -> 7326414.9 | F5: =Simulacao!B252 -> 3109848.7 | H5: =Simulacao!B273*Premissas!B17 -> 484986.05 | J5: =Simulacao!B278 -> 3579197.5
B6: 16556.870 MWh injetados em 120 meses | D6: Custo total do contrato PPA | F6: Rede evitada menos PPA pago | H6: Banco total Copasul @ PPA | J6: Economia + banco ATRIBUÍVEL a Helexia
B8: A. CUSTO COPASUL — ANÁLISE 120 MESES | I8: B. INDICADORES-CHAVE
B9: COMPONENTE | E9: R$ | F9: % | G9: R$/mês | I9: Usina contratada | K9: =Premissas!$B$13 -> Cassilândia 03
B10: Custo SEM Helexia — baseline 60m | E10: 13004941 | F10: 1 | G10: 108375 | I10: Período do contrato | K10: Jun/2026 – Mai/2036 (120 meses)
B11: Custo rede remanescente (COM Helexia) | E11: 1922842 | F11: 0.14785476 | G11: 16024 | I11: Potência contratada | K11: =VLOOKUP(Premissas!$B$13,PVSYST_Helexia!$B$5:$F$7,5,0)&" kWac" -> 625 kWac
B12: PPA pago à Helexia | E12: =Simulacao!B7 -> 7326414.9 | F12: 0.56335624 | G12: 61053 | I12: Geração P50 total | K12: 16556.87
B13: Custo total COM Helexia (rede + PPA) | E13: 9249257 | F13: 0.711211 | G13: 77077 | I13: PPA (R$/kWh) | K13: =Premissas!$B$17 -> 0.4425
B14: ★ ECONOMIA LÍQUIDA (rede − PPA) | E14: =Simulacao!B252 -> 3109848.7 | F14: 0.288789 | G14: 31297 | I14: Tarifa Grupo A FP | K14: =Premissas!$B$5 -> 0.52647111
B15: + Banco atribuível Helexia @ PPA (net NHS/AMD + Grupo B) | E15: =Simulacao!B285 -> 469348.85 | F15: 0.08868991 | G15: 9612 | I15: Tarifa Grupo B3 | K15: =Premissas!$B$7 -> 1.1568636
B16: ★ VALOR TOTAL HELEXIA (economia + banco atribuível) | E16: =Simulacao!B278 -> 3579197.5 | F16: 0.37747891 | G16: 40909 | I16: Economia média/mês | K16: =Simulacao!B252/60 -> 51830.811
I17: % redução custo Copasul | K17: =IFERROR(Simulacao!B252/Simulacao!B249,0) -> 0.40926307
I18: Banco residual (kWh) | K18: =Simulacao!B273 -> 1096013.7
B20: C. ANÁLISE VISUAL — ECONOMIA E BANCO DE CRÉDITOS
P22: Mês | Q22: SEM Helexia | R22: PPA | S22: Rede COM | T22: Eco mensal | U22: Eco acumulada | Y22: Eco acumulada
P23: Jun/26 | Q23: =Simulacao!D249 -> 29914.643 | R23: =Simulacao!D7 -> 54865.575 | S23: =Simulacao!D250 -> 2939.9665 | T23: =Simulacao!D252 -> -27890.899 | U23: =T23 -> -27890.899 | X23: Jun/26 | Y23: -27890.991
P24: Jul/26 | Q24: =Simulacao!E249 -> 231391.59 | R24: =Simulacao!E7 -> 57750.675 | S24: =Simulacao!E250 -> 82568.433 | T24: =Simulacao!E252 -> 91072.486 | U24: =U23+T24 -> 63181.588 | X24: Jul/26 | Y24: 63180.705
P25: Ago/26 | Q25: =Simulacao!F249 -> 156548.85 | R25: =Simulacao!F7 -> 69326.475 | S25: =Simulacao!F250 -> 1104.9864 | T25: =Simulacao!F252 -> 86117.386 | U25: =U24+T25 -> 149298.97 | X25: Ago/26 | Y25: 149296.8
P26: Set/26 | Q26: =Simulacao!G249 -> 42616.08 | R26: =Simulacao!G7 -> 65051.925 | S26: =Simulacao!G250 -> 2690.9343 | T26: =Simulacao!G252 -> -25126.779 | U26: =U25+T26 -> 124172.2 | X26: Set/26 | Y26: 124170.02
P27: Out/26 | Q27: =Simulacao!H249 -> 43352.771 | R27: =Simulacao!H7 -> 66852.9 | S27: =Simulacao!H250 -> 0 | T27: =Simulacao!H252 -> -23500.129 | U27: =U26+T27 -> 100672.07 | X27: Out/26 | Y27: 100669.9
P28: Nov/26 | Q28: =Simulacao!I249 -> 43210.246 | R28: =Simulacao!I7 -> 64640.4 | S28: =Simulacao!I250 -> 0 | T28: =Simulacao!I252 -> -21430.154 | U28: =U27+T28 -> 79241.912 | X28: Nov/26 | Y28: 79239.741
P29: Dez/26 | Q29: =Simulacao!J249 -> 44658.639 | R29: =Simulacao!J7 -> 61379.175 | S29: =Simulacao!J250 -> 0 | T29: =Simulacao!J252 -> -16720.536 | U29: =U28+T29 -> 62521.376 | X29: Dez/26 | Y29: 62519.298
P30: Jan/27 | Q30: =Simulacao!K249 -> 42485.586 | R30: =Simulacao!K7 -> 63022.753 | S30: =Simulacao!K250 -> 0 | T30: =Simulacao!K252 -> -20537.167 | U30: =U29+T30 -> 41984.209 | X30: Jan/27 | Y30: 41981.143
P31: Fev/27 | Q31: =Simulacao!L249 -> 45032.537 | R31: =Simulacao!L7 -> 56158.671 | S31: =Simulacao!L250 -> 0 | T31: =Simulacao!L252 -> -11126.133 | U31: =U30+T31 -> 30858.076 | X31: Fev/27 | Y31: 30854.517
P32: Mar/27 | Q32: =Simulacao!M249 -> 208537.26 | R32: =Simulacao!M7 -> 64414.061 | S32: =Simulacao!M250 -> 0 | T32: =Simulacao!M252 -> 144123.2 | U32: =U31+T32 -> 174981.27 | X32: Mar/27 | Y32: 174977.08
P33: Abr/27 | Q33: =Simulacao!N249 -> 35167.729 | R33: =Simulacao!N7 -> 64273.169 | S33: =Simulacao!N250 -> 0 | T33: =Simulacao!N252 -> -29105.44 | U33: =U32+T33 -> 145875.83 | X33: Abr/27 | Y33: 145871.45
P34: Mai/27 | Q34: =Simulacao!O249 -> 32721.657 | R34: =Simulacao!O7 -> 60152.078 | S34: =Simulacao!O250 -> 0 | T34: =Simulacao!O252 -> -27430.421 | U34: =U33+T34 -> 118445.41 | X34: Mai/27 | Y34: 118440.59
P35: Jun/27 | Q35: =Simulacao!P249 -> 70854.002 | R35: =Simulacao!P7 -> 54591.247 | S35: =Simulacao!P250 -> 0 | T35: =Simulacao!P252 -> 16262.755 | U35: =U34+T35 -> 134708.17 | X35: Jun/27 | Y35: 134702.87
P36: Jul/27 | Q36: =Simulacao!Q249 -> 281668.23 | R36: =Simulacao!Q7 -> 57461.922 | S36: =Simulacao!Q250 -> 0 | T36: =Simulacao!Q252 -> 224206.31 | U36: =U35+T36 -> 358914.47 | X36: Jul/27 | Y36: 358912.03
P37: Ago/27 | Q37: =Simulacao!R249 -> 161720.42 | R37: =Simulacao!R7 -> 68979.843 | S37: =Simulacao!R250 -> 0 | T37: =Simulacao!R252 -> 92740.58 | U37: =U36+T37 -> 451655.05 | X37: Ago/27 | Y37: 451654.05
P38: Set/27 | Q38: =Simulacao!S249 -> 43683.171 | R38: =Simulacao!S7 -> 64726.665 | S38: =Simulacao!S250 -> 0 | T38: =Simulacao!S252 -> -21043.494 | U38: =U37+T38 -> 430611.56 | X38: Set/27 | Y38: 430608.87
P39: Out/27 | Q39: =Simulacao!T249 -> 44437.446 | R39: =Simulacao!T7 -> 66518.636 | S39: =Simulacao!T250 -> 0 | T39: =Simulacao!T252 -> -22081.189 | U39: =U38+T39 -> 408530.37 | X39: Out/27 | Y39: 408526.82
P40: Nov/27 | Q40: =Simulacao!U249 -> 44288.442 | R40: =Simulacao!U7 -> 64317.198 | S40: =Simulacao!U250 -> 0 | T40: =Simulacao!U252 -> -20028.756 | U40: =U39+T40 -> 388501.61 | X40: Nov/27 | Y40: 388500.13
P41: Dez/27 | Q41: =Simulacao!V249 -> 45776.632 | R41: =Simulacao!V7 -> 61072.279 | S41: =Simulacao!V250 -> 0 | T41: =Simulacao!V252 -> -15295.647 | U41: =U40+T41 -> 373205.97 | X41: Dez/27 | Y41: 373203.05
P42: Jan/28 | Q42: =Simulacao!W249 -> 42485.586 | R42: =Simulacao!W7 -> 63022.753 | S42: =Simulacao!W250 -> 0 | T42: =Simulacao!W252 -> -20537.167 | U42: =U41+T42 -> 352668.8 | X42: Jan/28 | Y42: 352664.89
P43: Fev/28 | Q43: =Simulacao!X249 -> 45032.537 | R43: =Simulacao!X7 -> 56158.671 | S43: =Simulacao!X250 -> 0 | T43: =Simulacao!X252 -> -11126.133 | U43: =U42+T43 -> 341542.67 | X43: Fev/28 | Y43: 341538.27
P44: Mar/28 | Q44: =Simulacao!Y249 -> 212454.37 | R44: =Simulacao!Y7 -> 64414.061 | S44: =Simulacao!Y250 -> 0 | T44: =Simulacao!Y252 -> 148040.31 | U44: =U43+T44 -> 489582.97 | X44: Mar/28 | Y44: 489578.58
B45: D. BANCO DE CRÉDITOS — SALDO FINAL MAI/2036 POR UC | Banco total Copasul (incluindo NHS/AMD atribuíveis) | P45: Abr/28 | Q45: =Simulacao!Z249 -> 35167.729 | R45: =Simulacao!Z7 -> 64273.169 | S45: =Simulacao!Z250 -> 0 | T45: =Simulacao!Z252 -> -29105.44 | U45: =U44+T45 -> 460477.53 | X45: Abr/28 | Y45: 460472.96
B46: Unidade Consumidora | C46: Grupo | D46: Saldo (kWh) | E46: Valor @ PPA (R$) | F46: % do banco total | P46: Mai/28 | Q46: =Simulacao!AA249 -> 32721.657 | R46: =Simulacao!AA7 -> 60152.078 | S46: =Simulacao!AA250 -> 0 | T46: =Simulacao!AA252 -> -27430.421 | U46: =U45+T46 -> 433047.11 | X46: Mai/28 | Y46: 433042.1
B47: NHS — Novo Horizonte do Sul | C47: A4V | D47: =Simulacao!DS31 -> 56648.321 | E47: =Simulacao!DS31*Premissas!B17 -> 25066.882 | F47: =Simulacao!DS31/Simulacao!B273 -> 0.05168578 | P47: Jun/28 | Q47: =Simulacao!AB249 -> 74598.212 | R47: =Simulacao!AB7 -> 54318.291 | S47: =Simulacao!AB250 -> 0 | T47: =Simulacao!AB252 -> 20279.921 | U47: =U46+T47 -> 453327.03 | X47: Jun/28 | Y47: 455434.51
B48: AMD — Amandina | C48: A3A | D48: =Simulacao!DS49 -> 158023.28 | E48: =Simulacao!DS49*Premissas!B17 -> 69925.303 | F48: =Simulacao!DS49/Simulacao!B273 -> 0.14418003 | P48: Jul/28 | Q48: =Simulacao!AC249 -> 374262.47 | R48: =Simulacao!AC7 -> 57174.612 | S48: =Simulacao!AC250 -> 0 | T48: =Simulacao!AC252 -> 317087.85 | U48: =U47+T48 -> 770414.89 | X48: Jul/28 | Y48: 772321.42
B49: AREC | C49: B3 | D49: =Simulacao!DS62 -> 0 | E49: =Simulacao!DS62*Premissas!B17 -> 0 | F49: =Simulacao!DS62/Simulacao!B273 -> 0 | P49: Ago/28 | Q49: =Simulacao!AD249 -> 249540.36 | R49: =Simulacao!AD7 -> 68634.943 | S49: =Simulacao!AD250 -> 72494.149 | T49: =Simulacao!AD252 -> 108411.27 | U49: =U48+T49 -> 878826.16 | X49: Ago/28 | Y49: 877552.31
B50: Banheiro Motoristas | C50: B3 | D50: =Simulacao!DS75 -> 127936.29 | E50: =Simulacao!DS75*Premissas!B17 -> 56611.808 | F50: =Simulacao!DS75/Simulacao!B273 -> 0.11672873 | P50: Set/28 | Q50: =Simulacao!AE249 -> 44773.4 | R50: =Simulacao!AE7 -> 64403.032 | S50: =Simulacao!AE250 -> 0 | T50: =Simulacao!AE252 -> -19629.632 | U50: =U49+T50 -> 859196.52 | X50: Set/28 | Y50: 846688.53
B51: CTC Copasul | C51: B3 | D51: =Simulacao!DS88 -> 116816.29 | E51: =Simulacao!DS88*Premissas!B17 -> 51691.208 | F51: =Simulacao!DS88/Simulacao!B273 -> 0.10658288 | P51: Out/28 | Q51: =Simulacao!AF249 -> 45548.036 | R51: =Simulacao!AF7 -> 66186.042 | S51: =Simulacao!AF250 -> 0 | T51: =Simulacao!AF252 -> -20638.007 | U51: =U50+T51 -> 838558.52 | X51: Out/28 | Y51: 814041.75
B52: Depósito Irrigação | C52: B3 | D52: =Simulacao!DS101 -> 101306.57 | E52: =Simulacao!DS101*Premissas!B17 -> 44828.159 | F52: =Simulacao!DS101/Simulacao!B273 -> 0.092431853 | P52: Nov/28 | Q52: =Simulacao!AG249 -> 45399.957 | R52: =Simulacao!AG7 -> 63995.612 | S52: =Simulacao!AG250 -> 0 | T52: =Simulacao!AG252 -> -18595.655 | U52: =U51+T52 -> 819962.86 | X52: Nov/28 | Y52: 783585.39
B53: Entreposto | C53: B3 | D53: =Simulacao!DS114 -> 0 | E53: =Simulacao!DS114*Premissas!B17 -> 0 | F53: =Simulacao!DS114/Simulacao!B273 -> 0 | P53: Dez/28 | Q53: =Simulacao!AH249 -> 46918.688 | R53: =Simulacao!AH7 -> 60766.918 | S53: =Simulacao!AH250 -> 0 | T53: =Simulacao!AH252 -> -13848.23 | U53: =U52+T53 -> 806114.63 | X53: Dez/28 | Y53: 756357.72
B54: Esc. Deodápolis | C54: B3 | D54: =Simulacao!DS127 -> 0 | E54: =Simulacao!DS127*Premissas!B17 -> 0 | F54: =Simulacao!DS127/Simulacao!B273 -> 0 | P54: Jan/29 | Q54: =Simulacao!AI249 -> 44635.502 | R54: =Simulacao!AI7 -> 62707.639 | S54: =Simulacao!AI250 -> 0 | T54: =Simulacao!AI252 -> -18072.137 | U54: =U53+T54 -> 788042.49 | X54: Jan/29 | Y54: 727189.33
B55: Esc. Nova Andradina | C55: B3 | D55: =Simulacao!DS140 -> 0 | E55: =Simulacao!DS140*Premissas!B17 -> 0 | F55: =Simulacao!DS140/Simulacao!B273 -> 0 | P55: Fev/29 | Q55: =Simulacao!AJ249 -> 47311.096 | R55: =Simulacao!AJ7 -> 55877.877 | S55: =Simulacao!AJ250 -> 0 | T55: =Simulacao!AJ252 -> -8566.7815 | U55: =U54+T55 -> 779475.71 | X55: Fev/29 | Y55: 704850.71
B56: Esc. Regional Deodápolis | C56: B3 | D56: =Simulacao!DS153 -> 82696.28 | E56: =Simulacao!DS153*Premissas!B17 -> 36593.104 | F56: =Simulacao!DS153/Simulacao!B273 -> 0.075451869 | P56: Mar/29 | Q56: =Simulacao!AK249 -> 244075.16 | R56: =Simulacao!AK7 -> 64091.991 | S56: =Simulacao!AK250 -> 0 | T56: =Simulacao!AK252 -> 179983.17 | U56: =U55+T56 -> 959458.89 | X56: Mar/29 | Y56: 862505.8
B57: Galpão AE | C57: B3 | D57: =Simulacao!DS166 -> 124482.1 | E57: =Simulacao!DS166*Premissas!B17 -> 55083.329 | F57: =Simulacao!DS166/Simulacao!B273 -> 0.11357714 | P57: Abr/29 | Q57: =Simulacao!AL249 -> 36945.598 | R57: =Simulacao!AL7 -> 63951.803 | S57: =Simulacao!AL250 -> 0 | T57: =Simulacao!AL252 -> -27006.206 | U57: =U56+T57 -> 932452.68 | X57: Abr/29 | Y57: 832093.25
B58: Irrigação CG | C58: B3 | D58: =Simulacao!DS179 -> 97346.289 | E58: =Simulacao!DS179*Premissas!B17 -> 43075.733 | F58: =Simulacao!DS179/Simulacao!B273 -> 0.088818498 | P58: Mai/29 | Q58: =Simulacao!AM249 -> 34378.286 | R58: =Simulacao!AM7 -> 59851.318 | S58: =Simulacao!AM250 -> 0 | T58: =Simulacao!AM252 -> -25473.032 | U58: =U57+T58 -> 906979.65 | X58: Mai/29 | Y58: 805781.18
B59: Laboratório de Solos | C59: B3 | D59: =Simulacao!DS192 -> 0 | E59: =Simulacao!DS192*Premissas!B17 -> 0 | F59: =Simulacao!DS192/Simulacao!B273 -> 0 | P59: Jun/29 | Q59: =Simulacao!AN249 -> 178845.24 | R59: =Simulacao!AN7 -> 54046.699 | S59: =Simulacao!AN250 -> 0 | T59: =Simulacao!AN252 -> 124798.54 | U59: =U58+T59 -> 1031778.2 | X59: Jun/29 | Y59: 919330.18
B60: Posto Carreteiro | C60: B3 | D60: =Simulacao!DS205 -> 0 | E60: =Simulacao!DS205*Premissas!B17 -> 0 | F60: =Simulacao!DS205/Simulacao!B273 -> 0 | P60: Jul/29 | Q60: =Simulacao!AO249 -> 478339.98 | R60: =Simulacao!AO7 -> 56888.739 | S60: =Simulacao!AO250 -> 116989.88 | T60: =Simulacao!AO252 -> 304461.36 | U60: =U59+T60 -> 1336239.6 | X60: Jul/29 | Y60: 1340578.5
B61: Refeitório Deodápolis | C61: B1 | D61: =Simulacao!DS218 -> 157904.56 | E61: =Simulacao!DS218*Premissas!B17 -> 69872.769 | F61: =Simulacao!DS218/Simulacao!B273 -> 0.14407171 | P61: Ago/29 | Q61: =Simulacao!AP249 -> 258195.24 | R61: =Simulacao!AP7 -> 68291.769 | S61: =Simulacao!AP250 -> 96803.846 | T61: =Simulacao!AP252 -> 93099.626 | U61: =U60+T61 -> 1429339.2 | X61: Ago/29 | Y61: 1431133
B62: Subest. Fiação | C62: B3 | D62: =Simulacao!DS230 -> 72853.683 | E62: =Simulacao!DS230*Premissas!B17 -> 32237.755 | F62: =Simulacao!DS230/Simulacao!B273 -> 0.066471509 | P62: Set/29 | Q62: =Simulacao!AQ249 -> 45893.244 | R62: =Simulacao!AQ7 -> 64081.017 | S62: =Simulacao!AQ250 -> 8594.2942 | T62: =Simulacao!AQ252 -> -26782.067 | U62: =U61+T62 -> 1402557.1 | X62: Set/29 | Y62: 1401429.7
B63: TRR Maracaju | C63: B3 | D63: =Simulacao!DS242 -> 0 | E63: =Simulacao!DS242*Premissas!B17 -> 0 | F63: =Simulacao!DS242/Simulacao!B273 -> 0 | P63: Out/29 | Q63: =Simulacao!AR249 -> 46687.315 | R63: =Simulacao!AR7 -> 65855.112 | S63: =Simulacao!AR250 -> 6345.3245 | T63: =Simulacao!AR252 -> -25513.122 | U63: =U62+T63 -> 1377044 | X63: Out/29 | Y63: 1369952.3
B64: TOTAL — 17 UCs | D64: =Simulacao!B273 -> 1096013.7 | E64: =Simulacao!B273*Premissas!B17 -> 484986.05 | F64: 1 | P64: Nov/29 | Q64: =Simulacao!AS249 -> 46532.758 | R64: =Simulacao!AS7 -> 63675.634 | S64: =Simulacao!AS250 -> 6049.3296 | T64: =Simulacao!AS252 -> -23192.206 | U64: =U63+T64 -> 1353851.8 | X64: Nov/29 | Y64: 1340654.4
B65: E. BANCO ATRIBUÍVEL HELEXIA — O QUE A HELEXIA REALMENTE ENTREGA | P65: Dez/29 | Q65: =Simulacao!AT249 -> 48092.21 | R65: =Simulacao!AT7 -> 60463.083 | S65: =Simulacao!AT250 -> 8390.3014 | T65: =Simulacao!AT252 -> -20761.174 | U65: =U64+T65 -> 1333090.6 | X65: Dez/29 | Y65: 1314569
B66: Unidade / Grupo | C66: Banco SEM | D66: Banco COM | E66: Atribuível (kWh) | F66: Atribuível (R$) | P66: Jan/30 | Q66: =Simulacao!AU249 -> 45752.569 | R66: =Simulacao!AU7 -> 62394.101 | S66: =Simulacao!AU250 -> 5867.3685 | T66: =Simulacao!AU252 -> -22508.9 | U66: =U65+T66 -> 1310581.7 | X66: Jan/30 | Y66: 1286552.7
B67: NHS — Silos N. Horizonte | C67: =Simulacao!DS34 -> 17669.15 | D67: =Simulacao!DS31 -> 56648.321 | E67: =Simulacao!B281 -> 38979.171 | F67: =Simulacao!B281*Premissas!B17 -> 17248.283 | P67: Fev/30 | Q67: =Simulacao!AV249 -> 48494.799 | R67: =Simulacao!AV7 -> 55598.488 | S67: =Simulacao!AV250 -> 14388.288 | T67: =Simulacao!AV252 -> -21491.977 | U67: =U66+T67 -> 1289089.7 | X67: Fev/30 | Y67: 1265331.9
B68: AMD — Silos Amandina | C68: =Simulacao!DS52 -> 17669.15 | D68: =Simulacao!DS49 -> 158023.28 | E68: =Simulacao!B282 -> 140354.13 | F68: =Simulacao!B282*Premissas!B17 -> 62106.704 | P68: Mar/30 | Q68: =Simulacao!AW249 -> 264503.61 | R68: =Simulacao!AW7 -> 63771.531 | S68: =Simulacao!AW250 -> 20039.413 | T68: =Simulacao!AW252 -> 180692.67 | U68: =U67+T68 -> 1469782.4 | X68: Mar/30 | Y68: 1442066.8
B69: Grupo B (15 UCs) | C69: 0 | D69: =Simulacao!B283 -> 881342.07 | E69: =Simulacao!B283 -> 881342.07 | F69: =Simulacao!B283*Premissas!B17 -> 389993.86 | P69: Abr/30 | Q69: =Simulacao!AX249 -> 37871.088 | R69: =Simulacao!AX7 -> 63632.044 | S69: =Simulacao!AX250 -> 16574.449 | T69: =Simulacao!AX252 -> -42335.405 | U69: =U68+T69 -> 1427447 | X69: Abr/30 | Y69: 1412812.5
B70: TOTAL atribuível Helexia | C70: =C67+C68+C69 -> 35338.3 | D70: =D67+D68+D69 -> 1096013.7 | E70: =Simulacao!B284 -> 1060675.4 | F70: =Simulacao!B284*Premissas!B17 -> 469348.85 | P70: Mai/30 | Q70: =Simulacao!AY249 -> 35238.067 | R70: =Simulacao!AY7 -> 59552.061 | S70: =Simulacao!AY250 -> 14406.418 | T70: =Simulacao!AY252 -> -38720.412 | U70: =U69+T70 -> 1388726.6 | X70: Mai/30 | Y70: 1387638.2
P71: Jun/30 | Q71: =Simulacao!AZ249 -> 205381.48 | R71: =Simulacao!AZ7 -> 53776.466 | S71: =Simulacao!AZ250 -> 11649.255 | T71: =Simulacao!AZ252 -> 139955.76 | U71: =U70+T71 -> 1528682.3 | X71: Jun/30 | Y71: 1527714.5
P72: Jul/30 | Q72: =Simulacao!BA249 -> 492586.9 | R72: =Simulacao!BA7 -> 56604.295 | S72: =Simulacao!BA250 -> 134255.49 | T72: =Simulacao!BA252 -> 301727.11 | U72: =U71+T72 -> 1830409.4 | X72: Jul/30 | Y72: 1843576.8
P73: Ago/30 | Q73: =Simulacao!BB249 -> 267048.38 | R73: =Simulacao!BB7 -> 67950.31 | S73: =Simulacao!BB250 -> 110057.34 | T73: =Simulacao!BB252 -> 89040.726 | U73: =U72+T73 -> 1919450.2 | X73: Ago/30 | Y73: 1947014.3
P74: Set/30 | Q74: =Simulacao!BC249 -> 47040.852 | R74: =Simulacao!BC7 -> 63760.612 | S74: =Simulacao!BC250 -> 27528.935 | T74: =Simulacao!BC252 -> -44248.695 | U74: =U73+T74 -> 1875201.5 | X74: Set/30 | Y74: 1918490.8
P75: Out/30 | Q75: =Simulacao!BD249 -> 47852.508 | R75: =Simulacao!BD7 -> 65525.837 | S75: =Simulacao!BD250 -> 27454.038 | T75: =Simulacao!BD252 -> -45127.366 | U75: =U74+T75 -> 1830074.1 | X75: Out/30 | Y75: 1888202.2
P76: Nov/30 | Q76: =Simulacao!BE249 -> 47695.175 | R76: =Simulacao!BE7 -> 63357.256 | S76: =Simulacao!BE250 -> 29825.156 | T76: =Simulacao!BE252 -> -45487.238 | U76: =U75+T76 -> 1784586.9 | X76: Nov/30 | Y76: 1860008
P77: Dez/30 | Q77: =Simulacao!BF249 -> 49295.348 | R77: =Simulacao!BF7 -> 60160.768 | S77: =Simulacao!BF250 -> 23194.605 | T77: =Simulacao!BF252 -> -34060.024 | U77: =U76+T77 -> 1750526.9 | X77: Dez/30 | Y77: 1834884
P78: Jan/31 | Q78: =Simulacao!BG249 -> 46896.476 | R78: =Simulacao!BG7 -> 62082.13 | S78: =Simulacao!BG250 -> 19091.058 | T78: =Simulacao!BG252 -> -34276.712 | U78: =U77+T78 -> 1716250.1 | X78: Jan/31 | Y78: 1807859.8
P79: Fev/31 | Q79: =Simulacao!BH249 -> 49705.341 | R79: =Simulacao!BH7 -> 55320.495 | S79: =Simulacao!BH250 -> 25268.979 | T79: =Simulacao!BH252 -> -30884.133 | U79: =U78+T79 -> 1685366 | X79: Fev/31 | Y79: 1786702.6
P80: Mar/31 | Q80: =Simulacao!BI249 -> 285370.02 | R80: =Simulacao!BI7 -> 63452.673 | S80: =Simulacao!BI250 -> 14961.294 | T80: =Simulacao!BI252 -> 206956.05 | U80: =U79+T80 -> 1892322.1 | X80: Mar/31 | Y80: 1983790.1
P81: Abr/31 | Q81: =Simulacao!BJ249 -> 38818.791 | R81: =Simulacao!BJ7 -> 63313.884 | S81: =Simulacao!BJ250 -> 8234.8258 | T81: =Simulacao!BJ252 -> -32729.919 | U81: =U80+T81 -> 1859592.1 | X81: Abr/31 | Y81: 1955477.9
P82: Mai/31 | Q82: =Simulacao!BK249 -> 36119.134 | R82: =Simulacao!BK7 -> 59254.301 | S82: =Simulacao!BK250 -> 6436.8208 | T82: =Simulacao!BK252 -> -29571.988 | U82: =U81+T82 -> 1830020.1 | X82: Mai/31 | Y82: 1930957.3
P83: Jun/31 | Q83: =Simulacao!BL249 -> 217802.41 | R83: =Simulacao!BL7 -> 53507.584 | S83: =Simulacao!BL250 -> 0 | T83: =Simulacao!BL252 -> 164294.83 | U83: =Resumo!U82+Resumo!T83 -> 1994315 | X83: Jun/31 | Y83: 1955256.7
P84: Jul/31 | Q84: =Simulacao!BM249 -> 504785.95 | R84: =Simulacao!BM7 -> 56321.274 | S84: =Simulacao!BM250 -> 189249.48 | T84: =Simulacao!BM252 -> 259215.19 | U84: =Resumo!U83+Resumo!T84 -> 2253530.2 | X84: Jul/31 | Y84: 1996713.4
P85: Ago/31 | Q85: =Simulacao!BN249 -> 277338.71 | R85: =Simulacao!BN7 -> 67610.558 | S85: =Simulacao!BN250 -> 139398.81 | T85: =Simulacao!BN252 -> 70329.343 | U85: =Resumo!U84+Resumo!T85 -> 2323859.5 | X85: Ago/31 | Y85: 2026880.8
P86: Set/31 | Q86: =Simulacao!BO249 -> 48217.151 | R86: =Simulacao!BO7 -> 63441.809 | S86: =Simulacao!BO250 -> 0 | T86: =Simulacao!BO252 -> -15224.657 | U86: =Resumo!U85+Resumo!T86 -> 2308634.9 | X86: Set/31 | Y86: 2061216.9
P87: Out/31 | Q87: =Simulacao!BP249 -> 49050.093 | R87: =Simulacao!BP7 -> 65198.207 | S87: =Simulacao!BP250 -> 1603.3338 | T87: =Simulacao!BP252 -> -17751.448 | U87: =Resumo!U86+Resumo!T87 -> 2290883.4 | X87: Out/31 | Y87: 2093796.6
P88: Nov/31 | Q88: =Simulacao!BQ249 -> 48889.058 | R88: =Simulacao!BQ7 -> 63040.47 | S88: =Simulacao!BQ250 -> 729.68086 | T88: =Simulacao!BQ252 -> -14881.093 | U88: =Resumo!U87+Resumo!T88 -> 2276002.3 | X88: Nov/31 | Y88: 2128534.1
P89: Dez/31 | Q89: =Simulacao!BR249 -> 50527.177 | R89: =Simulacao!BR7 -> 59859.964 | S89: =Simulacao!BR250 -> 2010.5972 | T89: =Simulacao!BR252 -> -11343.384 | U89: =Resumo!U88+Resumo!T89 -> 2264658.9 | X89: Dez/31 | Y89: 2166452
P90: Jan/32 | Q90: =Simulacao!BS249 -> 48069.073 | R90: =Simulacao!BS7 -> 61771.72 | S90: =Simulacao!BS250 -> 0 | T90: =Simulacao!BS252 -> -13702.647 | U90: =Resumo!U89+Resumo!T90 -> 2250956.3 | X90: Jan/32 | Y90: 2202458.2
P91: Fev/32 | Q91: =Simulacao!BT249 -> 50951.052 | R91: =Simulacao!BT7 -> 55043.893 | S91: =Simulacao!BT250 -> 918.539 | T91: =Simulacao!BT252 -> -5011.3804 | U91: =Resumo!U90+Resumo!T91 -> 2245944.9 | X91: Fev/32 | Y91: 2245192.3
P92: Mar/32 | Q92: =Simulacao!BU249 -> 395367.32 | R92: =Simulacao!BU7 -> 63135.41 | S92: =Simulacao!BU250 -> 275953.4 | T92: =Simulacao!BU252 -> 56278.519 | U92: =Resumo!U91+Resumo!T92 -> 2302223.4 | X92: Mar/32 | Y92: 2279834.8
P93: Abr/32 | Q93: =Simulacao!BV249 -> 39789.631 | R93: =Simulacao!BV7 -> 62997.315 | S93: =Simulacao!BV250 -> 0 | T93: =Simulacao!BV252 -> -23207.684 | U93: =Resumo!U92+Resumo!T93 -> 2279015.7 | X93: Abr/32 | Y93: 2314615.4
P94: Mai/32 | Q94: =Simulacao!BW249 -> 37021.488 | R94: =Simulacao!BW7 -> 58958.029 | S94: =Simulacao!BW250 -> 0 | T94: =Simulacao!BW252 -> -21936.542 | U94: =Resumo!U93+Resumo!T94 -> 2257079.2 | X94: Mai/32 | Y94: 2353435.3
P95: Jun/32 | Q95: =Simulacao!BX249 -> 222874.85 | R95: =Simulacao!BX7 -> 53240.046 | S95: =Simulacao!BX250 -> 46003.912 | T95: =Simulacao!BX252 -> 123630.89 | U95: =Resumo!U94+Resumo!T95 -> 2380710.1 | X95: Jun/32 | Y95: 2401363.2
P96: Jul/32 | Q96: =Simulacao!BY249 -> 519357.34 | R96: =Simulacao!BY7 -> 56039.667 | S96: =Simulacao!BY250 -> 282020.24 | T96: =Simulacao!BY252 -> 181297.44 | U96: =Resumo!U95+Resumo!T96 -> 2562007.5 | X96: Jul/32 | Y96: 2446491.4
P97: Ago/32 | Q97: =Simulacao!BZ249 -> 286226.18 | R97: =Simulacao!BZ7 -> 67272.506 | S97: =Simulacao!BZ250 -> 144020.9 | T97: =Simulacao!BZ252 -> 74932.769 | U97: =Resumo!U96+Resumo!T97 -> 2636940.3 | X97: Ago/32 | Y97: 2480386.8
P98: Set/32 | Q98: =Simulacao!CA249 -> 49422.141 | R98: =Simulacao!CA7 -> 63124.6 | S98: =Simulacao!CA250 -> 0 | T98: =Simulacao!CA252 -> -13702.459 | U98: =Resumo!U97+Resumo!T98 -> 2623237.8 | X98: Set/32 | Y98: 2518430.1
P99: Out/32 | Q99: =Simulacao!CB249 -> 50276.369 | R99: =Simulacao!CB7 -> 64872.216 | S99: =Simulacao!CB250 -> 0 | T99: =Simulacao!CB252 -> -14595.848 | U99: =Resumo!U98+Resumo!T99 -> 2608642 | X99: Out/32 | Y99: 2554725.8
P100: Nov/32 | Q100: =Simulacao!CC249 -> 50111.631 | R100: =Simulacao!CC7 -> 62725.267 | S100: =Simulacao!CC250 -> 0 | T100: =Simulacao!CC252 -> -12613.636 | U100: =Resumo!U99+Resumo!T100 -> 2596028.4 | X100: Nov/32 | Y100: 2593168.4
P101: Dez/32 | Q101: =Simulacao!CD249 -> 51790.472 | R101: =Simulacao!CD7 -> 59560.664 | S101: =Simulacao!CD250 -> 0 | T101: =Simulacao!CD252 -> -7770.1922 | U101: =Resumo!U100+Resumo!T101 -> 2588258.2 | X101: Dez/32 | Y101: 2634775.7
P102: Jan/33 | Q102: =Simulacao!CE249 -> 49271.286 | R102: =Simulacao!CE7 -> 61462.861 | S102: =Simulacao!CE250 -> 0 | T102: =Simulacao!CE252 -> -12191.575 | U102: =Resumo!U101+Resumo!T102 -> 2576066.6 | X102: Jan/33 | Y102: 2674480.7
B103: NHS — Novo Horizonte do Sul (A4V) | C103: =Simulacao!BQ34 -> 176812.44 | D103: =Simulacao!BQ31 -> 196820.65 | E103: =Simulacao!B281 -> 38979.171 | F103: =Simulacao!B281*Premissas!$B$17 -> 17248.283 | P103: Fev/33 | Q103: =Simulacao!CF249 -> 147903.57 | R103: =Simulacao!CF7 -> 54768.674 | S103: =Simulacao!CF250 -> 96459.371 | T103: =Simulacao!CF252 -> -3324.4754 | U103: =Resumo!U102+Resumo!T103 -> 2572742.1 | X103: Fev/33 | Y103: 2720879.9
B104: AMD — Amandina (A3A) | C104: =Simulacao!BQ52 -> 247868.01 | D104: =Simulacao!BQ49 -> 541957.61 | E104: =Simulacao!B282 -> 140354.13 | F104: =Simulacao!B282*Premissas!$B$17 -> 62106.704 | P104: Mar/33 | Q104: =Simulacao!CG249 -> 412607.82 | R104: =Simulacao!CG7 -> 62819.733 | S104: =Simulacao!CG250 -> 292749.22 | T104: =Simulacao!CG252 -> 57038.871 | U104: =Resumo!U103+Resumo!T104 -> 2629781 | X104: Mar/33 | Y104: 2759228.1
...

Sheet Premissas
A1: ="PREMISSAS — "&Premissas!$B$13&" × Copasul | Energisa MS" -> PREMISSAS — Cassilândia 03 × Copasul | Energisa MS | M1: 🎯 OTIMIZAÇÃO RATEIO — SOLVER CONFIG
A2: Azul = inputs editáveis | Preto = fórmulas | Verde = links entre abas | M2: Siga o passo a passo abaixo para maximizar Economia Líquida via Excel Solver
A4: A. TARIFAS ENERGISA MS (com tributos ICMS 17% + PIS/COFINS) | M4: ① CÉLULA OBJETIVO (aponte o Solver aqui): | P4: ENDEREÇO | Q4: VALOR ATUAL | R4: OBJETIVO
A5: Tarifa Grupo A FP com tributos (R$/kWh) | B5: 0.52647111 | C5: ← T_AFP: edit here | M5: Economia Líquida Copasul 24m (R$) | P5: Premissas!K5 | Q5: =Simulacao!B252 -> 3109848.7 | R5: ↑ MAXIMIZAR
A6: Tarifa Grupo A Ponta com tributos (R$/kWh) | B6: 2.9723794 | C6: ← T_APT: edit here | M6: ② ATIVAR SOLVER (se ainda não estiver ativo) | O6: Arquivo → Opções → Suplementos → Gerenciar: Suplementos do Excel → Ir... → ✓ Solver Add-in → OK
A7: Tarifa Grupo B3 com tributos (R$/kWh) | B7: 1.1568636 | C7: ← T_B3: edit here | M7: ③ ABRIR SOLVER | O7: Guia Dados → botão "Solver" (canto direito da faixa de opções)
A8: FA = TE_FP / TE_Ponta | B8: 0.60426705 | C8: ← FA: edit here | M8: ④ CONFIGURAR OBJETIVO | O8: Definir Objetivo: selecione a célula Premissas!K5 → marque ● Máx
A9: ICMS (%) | B9: 0.17 | C9: ← ICMS: edit here | M9: ⑤ DEFINIR CÉLULAS VARIÁVEIS | O9: Alterando Células de Variáveis: Premissas!$B$33:$K$50 (170 variáveis = 17 UCs × 10 períodos)
A10: PIS + COFINS (%) | B10: 0.0855 | C10: ← PIS_COFINS: edit here | M10: ⑥ ADICIONAR AS RESTRIÇÕES (Adicionar → preencher cada linha → OK)
A11: ICMS isenção autoconsumo remoto ativa? (Art. 23-A RICMS/MS) → 'Sim' = isento | 'Não' = ICMS cobrado sobre kWh compensados pelo CS3 | B11: Sim | C11: =IF($B$11="Sim",0,$B$5*$B$9/(1+$B$9)) -> 0 | D11: =IF($B$11="Sim",0,$B$6*$B$9/(1+$B$9)) -> 0 | E11: =IF($B$11="Sim",0,$B$7*$B$9/(1+$B$9)) -> 0 | F11: ← B=toggle (Sim/Não) | C=ICMS A_FP D=ICMS A_Ponta E=ICMS Grupo B (R$/kWh) — tudo 0 se Sim | M11: Célula / Intervalo | O11: Relação | P11: Valor / Restrição | Q11: Descrição
A12: B. CONDIÇÕES DO CONTRATO | M12: Premissas!$B$33:$K$50 | O12: >= | P12: 0 | Q12: Todos os rateios ≥ 0% (sem valores negativos, P1–P10)
A13: Usina | B13: Cassilândia 03 | M13: Premissas!$B$51 | O13: = | P13: 1 | Q13: Soma P1 = 100% (Jun–Set/26)
A14: Distribuidora | B14: Energisa MS | M14: Premissas!$C$51 | O14: = | P14: 1 | Q14: Soma P2 = 100% (Out/26–Mar/27)
A15: Início do contrato | B15: Jun/2026 | M15: Premissas!$D$51 | O15: = | P15: 1 | R15: Soma P3 = 100% (Abr–Set/27)
A16: Prazo (meses) | B16: 120 | M16: Premissas!$E$51 | O16: = | P16: 1 | Q16: Soma P4 = 100% (Out/27–Mai/28)
A17: PPA Helexia CS3 (R$/kWh) | B17: 0.4425 | M17: Premissas!$F$51 | O17: = | P17: 1 | Q17: Soma P5 = 100% (Jun–Nov/28)
A18: H. CENÁRIO CONCORRENTE — ENERGIA ASSINATURA GRUPO B (ex: Plin Energia) | M18: Premissas!$G$51 | O18: = | P18: 1 | Q18: Soma P6 = 100% (Dez/28–Mai/29)
A19: Grupo B tem contrato Assinatura GD concorrente? | B19: Sim | C19: Desconto (%): | D19: 0.2 | E19: Tarifa B3 SEM efetiva: | F19: =IF(B19="Sim",B7*(1-D19),B7) -> 0.92549092 | M19: Premissas!$H$51 | O19: = | P19: 1 | Q19: Soma P7 = 100% (Jun–Nov/29)
A20: C. PREMISSAS DE CRESCIMENTO E DEGRADAÇÃO | M20: Premissas!$I$51 | O20: = | P20: 1 | Q20: Soma P8 = 100% (Dez/29–Mai/30)
A21: Crescimento consumo Y2 vs Y1 (%) | B21: 0.025 | C21: ← 2.5% editável | aplica a TODOS os UCs | M21: Premissas!$J$51 | O21: = | P21: 1 | Q21: Soma P9 = 100% (Jun–Nov/30)
A22: Crescimento consumo Y3 parcial (Dez/27-Mai/28) (%) | B22: 0.025 | C22: ← mesmo % que Y2 por padrão | M22: Premissas!$K$51 | O22: = | P22: 1 | Q22: Soma P10 = 100% (Dez/30–Mai/31)
A23: Degradação geração Y2 (%) | B23: 0.005 | C23: ← 0.5%/ano editável | M23: Premissas!$B$34:$K$34 | O23: = | P23: 0 | Q23: BAT (linha 34) = 0% em todos os períodos (P1–P10)
A24: Usar proxy Batayporã p/ Amandina gen? | B24: Sim | M24: Premissas!$B$33:$E$50 | O24: <= | P24: 1 | Q24: Todos os rateios ≤ 100% (limite superior)
A25: D. BANCOS DE CRÉDITOS — SALDO INICIAL (Mai/2026, FPt GD I) | M25: ⑦ MÉTODO DE RESOLUÇÃO E OPÇÕES
A26: NHS — Silos Novo Horizonte do Sul (kWh) | B26: 148516 | M26: Método de Resolução: | O26: GRG Não-Linear | P26: O modelo tem funções IF (não-lineares). GRG é o método correto.
A27: BAT — Silos Batayporã (kWh) [stranded — não transferível CS3] | B27: 906739 | M27: Opções → Precisão: | O27: 0,000001 | P27: Maior precisão = resultado mais fino.
A28: AMD — Silos Amandina (kWh) | B28: 991029
A29: TOTAL NHS+AMD (kWh) | B29: =B26+B28 -> 1139545 | C29: ← BAT stranded bank não incluído no total
A31: ="E. RATEIO FIXO "&INDEX(PVSYST_Helexia!$A$5:$A$7,MATCH(Premissas!$B$13,PVSYST_Helexia!$B$5:$B$7,0))&" — 4 PERÍODOS (edit percentuais — devem somar 100% por período)" -> E. RATEIO FIXO HCS03 — 4 PERÍODOS (edit percentuais — devem somar 100% por período) | F31: Anos 3–10 (estado estacionário)
A32: UC / Planta | B32: P1: Jun–Set/26 | C32: P2: Out/26–Mar/27 | D32: P3: Abr/27–Set/27 | E32: P4: Out/27–Mai/28 | F32: P5: Jun–Nov/28 | G32: P6: Dez/28–Mai/29 | H32: P7: Jun–Nov/29 | I32: P8: Dez/29–Mai/30 | J32: P9: Jun–Nov/30 | K32: P10: Dez/30–Mai/31 | L32: P11: Jun–Nov/31 | M32: P12: Dez/31–Mai/32 | N32: P13: Jun–Nov/32 | O32: P14: Dez/32–Mai/33 | P32: P15: Jun–Nov/33 | Q32: P16: Dez/33–Mai/34 | R32: P17: Jun–Nov/34 | S32: P18: Dez/34–Mai/35 | T32: P19: Jun–Nov/35 | U32: P20: Dez/35–Mai/36
A33: NHS — Silos N. Horizonte (A4V) | B33: 0.738 | C33: 0.5178 | D33: 0.6714 | E33: 0.2592 | F33: 0.4741 | G33: 0.4673 | H33: 0.4724 | I33: 0.4656 | J33: 0.5826 | K33: 0.4621 | L33: 0.06904028 | M33: 0.07085343 | N33: 0.06949093 | O33: 0.07130672 | P33: 0.06994228 | Q33: 0.07176061 | R33: 0.07039425 | S33: 0.33 | T33: 0.33 | U33: 0.33
A34: BAT — Silos Batayporã (A4V) | B34: 0 | C34: 0 | D34: 0 | E34: 0 | F34: 0 | G34: 0 | H34: 0 | I34: 0 | J34: 0 | K34: 0 | L34: 0 | M34: 0 | N34: 0 | O34: 0 | P34: 0 | Q34: 0 | R34: 0 | S34: 0.33 | T34: 0.33 | U34: 0.33
A35: AMD — Silos Amandina (A3A) | B35: 0 | C35: 0 | D35: 0.0041 | E35: 0.1561 | F35: 0.3735 | G35: 0.3698 | H35: 0.3726 | I35: 0.3688 | J35: 0.2324 | K35: 0.2925 | L35: 0.34288312 | M35: 0.34120903 | N35: 0.34246707 | O35: 0.3407905 | P35: 0.34205034 | Q35: 0.34037116 | R35: 0.34163316 | S35: 0.33953066 | T35: 0.33953066 | U35: 0.33953066
A36: AREC (B3) | B36: 0.027 | C36: 0.0532 | D36: 0.0311 | E36: 0.0674 | F36: 0.0156 | G36: 0.0171 | H36: 0.016 | I36: 0.0174 | J36: 0.0304 | K36: 0.0322 | L36: 0.04656421 | M36: 0.04669989 | N36: 0.04659958 | O36: 0.04673106 | P36: 0.04663391 | Q36: 0.04676128 | R36: 0.04666718 | S36: 0 | T36: 0 | U36: 0
A37: Banheiro Motoristas (B3) | B37: 0.0033 | C37: 0.005 | D37: 0.004 | E37: 0.0045 | F37: 0.0026 | G37: 0.0027 | H37: 0.0026 | I37: 0.0027 | J37: 0.0027 | K37: 0.0034 | L37: 0.027707 | M37: 0.02794292 | N37: 0.02776621 | O37: 0.02800095 | P37: 0.02782513 | Q37: 0.02805869 | R37: 0.02788375 | S37: 0 | T37: 0 | U37: 0
A38: CTC Copasul (B3) | B38: 0.0031 | C38: 0.0077 | D38: 0.0039 | E38: 0.0072 | F38: 0.0032 | G38: 0.0034 | H38: 0.0032 | I38: 0.0034 | J38: 0.0037 | K38: 0.0043 | L38: 0.027707 | M38: 0.02794292 | N38: 0.02776621 | O38: 0.02800095 | P38: 0.02782513 | Q38: 0.02805869 | R38: 0.02788375 | S38: 0 | T38: 0 | U38: 0
A39: Depósito Irrigação (B3) | B39: 0.0064 | C39: 0.0114 | D39: 0.0081 | E39: 0.0095 | F39: 0.007 | G39: 0.0075 | H39: 0.0071 | I39: 0.0076 | J39: 0.0098 | K39: 0.0044 | L39: 0.027707 | M39: 0.02794292 | N39: 0.02776621 | O39: 0.02800095 | P39: 0.02782513 | Q39: 0.02805869 | R39: 0.02788375 | S39: 0 | T39: 0 | U39: 0
A40: Entreposto (B3) | B40: 0.059 | C40: 0.1067 | D40: 0.0727 | E40: 0.2104 | F40: 0.006 | G40: 0.0064 | H40: 0.0061 | I40: 0.0065 | J40: 0.0075 | K40: 0.0313 | L40: 0.09508557 | M40: 0.0935828 | N40: 0.09470727 | O40: 0.09321513 | P40: 0.09433155 | Q40: 0.09285003 | R40: 0.0939585 | S40: 0 | T40: 0 | U40: 0
A41: Esc. Deodápolis (B3) | B41: 0.0213 | C41: 0.0358 | D41: 0.026 | E41: 0.0439 | F41: 0.0111 | G41: 0.0121 | H41: 0.0113 | I41: 0.0123 | J41: 0.0181 | K41: 0.0212 | L41: 0.027707 | M41: 0.02794292 | N41: 0.02776621 | O41: 0.02800095 | P41: 0.02782513 | Q41: 0.02805869 | R41: 0.02788375 | S41: 0 | T41: 0 | U41: 0
A42: Esc. Nova Andradina (B3) | B42: 0.0121 | C42: 0.0296 | D42: 0.0159 | E42: 0.0286 | F42: 0.0122 | G42: 0.0133 | H42: 0.0125 | I42: 0.0136 | J42: 0.0137 | K42: 0.0177 | L42: 0.027707 | M42: 0.02794292 | N42: 0.02776621 | O42: 0.02800094 | P42: 0.02782513 | Q42: 0.02805869 | R42: 0.02788375 | S42: 0 | T42: 0 | U42: 0
A43: Esc. Regional Deodápolis (B3) | B43: 0.0046 | C43: 0.0157 | D43: 0.006 | E43: 0.0147 | F43: 0.0031 | G43: 0.0033 | H43: 0.0031 | I43: 0.0033 | J43: 0.0036 | K43: 0.0048 | L43: 0.027707 | M43: 0.02794292 | N43: 0.02776621 | O43: 0.02800094 | P43: 0.02782513 | Q43: 0.02805869 | R43: 0.02788375 | S43: 0 | T43: 0 | U43: 0
A44: Galpão AE (B3) | B44: 0.0059 | C44: 0.0043 | D44: 0.0059 | E44: 0.0043 | F44: 0.0025 | G44: 0.0026 | H44: 0.0025 | I44: 0.0027 | J44: 0.0027 | K44: 0.0033 | L44: 0.027707 | M44: 0.02794292 | N44: 0.02776621 | O44: 0.02800094 | P44: 0.02782513 | Q44: 0.02805869 | R44: 0.02788375 | S44: 0 | T44: 0 | U44: 0
... A50: TRR Maracaju (B3) | B50: 0.026 | C50: 0.0365 | D50: 0.0367 | E50: 0.0399 | F50: 0.0214 | G50: 0.024 | H50: 0.022 | I50: 0.0246 | J50: 0.0272 | K50: 0.0306 | L50: 0.04656421 | M50: 0.04669989 | N50: 0.04659958 | O50: 0.04673106 | P50: 0.04663392 | Q50: 0.04676128 | R50: 0.04666718 | S50: 0 | T50: 0 | U50: 0
A51: TOTAL (deve = 100%) | B51: =SUM(B33:B50) -> 0.9999 | C51: =SUM(C33:C50) -> 0.9998 | D51: =SUM(D33:D50) -> 1.0002 | E51: =SUM(E33:E50) -> 0.9998 | F51: =SUM(F33:F50) -> 1.0002 | G51: =SUM(G33:G50) -> 1 | H51: =SUM(H33:H50) -> 0.9999 | I51: =SUM(I33:I50) -> 0.9998 | ... U51: =SUM(U33:U50) -> 0.99953066
A52: ⚠ Ajuste os percentuais acima para que cada coluna some exatamente 100%. BAT está fixo em 0% — seus créditos futuros entram via mecanismo de rateio próprio (seção F abaixo). A otimização automática maximiza o aproveitamento dos créditos CS3.
A53: ⚠ P5–P20 (Jun/2028–Mai/2036): alocação optimizada (SLSQP, Python).
A54: F. RATEIO DO SURPLUS BAT — 2 PERÍODOS (NH 39% / AMD 61% por padrão)
A55: BAT→NHS (%) | B55: 0.5 | C55: ← editável
A56: BAT→AMD (%) | B56: =1-B55 -> 0.5 | C56: ← = 1 − NHS%
A59: ="G. GERAÇÃO "&INDEX(PVSYST_Helexia!$A$5:$A$7,MATCH(Premissas!$B$13,PVSYST_Helexia!$B$5:$B$7,0))&" P50 — PVSYST "&Premissas!$B$13&" (kWh/mês)" -> G. GERAÇÃO HCS03 P50 — PVSYST Cassilândia 03 (kWh/mês)
A60: Degradação Y2 aplicada | B60: =Premissas!$B$23 -> 0.005 | C60: ← Y1: valor direto PVSYST | Y2/Y3: × (1−DEG)
A61: Jun/26 | B61: =INDEX(PVSYST_Helexia!$J$5:$U$7,MATCH(Premissas!$B$13,PVSYST_Helexia!$B$5:$B$7,0),6)*1000 -> 123990 | C61: kWh — CS3 P50 mês 06 (base=136,620 kWh)
A62: Jul/26 | B62: =INDEX(PVSYST_Helexia!$J$5:$U$7,MATCH(Premissas!$B$13,PVSYST_Helexia!$B$5:$B$7,0),7)*1000 -> 130510 | C62: kWh — CS3 P50 mês 07 (base=123,990 kWh)
A63: Ago/26 | B63: =INDEX(PVSYST_Helexia!$J$5:$U$7,MATCH(Premissas!$B$13,PVSYST_Helexia!$B$5:$B$7,0),8)*1000 -> 156670 | C63: kWh — CS3 P50 mês 08 (base=130,510 kWh)
A64: Set/26 | B64: =INDEX(PVSYST_Helexia!$J$5:$U$7,MATCH(Premissas!$B$13,PVSYST_Helexia!$B$5:$B$7,0),9)*1000 -> 147010 | C64: kWh — CS3 P50 mês 09 (base=156,670 kWh)
A65: Out/26 | B65: =INDEX(PVSYST_Helexia!$J$5:$U$7,MATCH(Premissas!$B$13,PVSYST_Helexia!$B$5:$B$7,0),10)*1000 -> 151080 | C65: kWh — CS3 P50 mês 10 (base=147,010 kWh)
A66: Nov/26 | B66: =INDEX(PVSYST_Helexia!$J$5:$U$7,MATCH(Premissas!$B$13,PVSYST_Helexia!$B$5:$B$7,0),11)*1000 -> 146080 | C66: kWh — CS3 P50 mês 11 (base=151,080 kWh)
A67: Dez/26 | B67: =INDEX(PVSYST_Helexia!$J$5:$U$7,MATCH(Premissas!$B$13,PVSYST_Helexia!$B$5:$B$7,0),12)*1000 -> 138710 | C67: kWh — CS3 P50 mês 12 (base=146,080 kWh)
A68: Jan/27 | B68: =INDEX(PVSYST_Helexia!$J$5:$U$7,MATCH(Premissas!$B$13,PVSYST_Helexia!$B$5:$B$7,0),1)*1000*(1-Premissas!$B$23) -> 142424.3 | C68: kWh — CS3 P50 mês 01 (base=2,000 kWh)
A69: Fev/27 | B69: =INDEX(PVSYST_Helexia!$J$5:$U$7,MATCH(Premissas!$B$13,PVSYST_Helexia!$B$5:$B$7,0),2)*1000*(1-Premissas!$B$23) -> 126912.25 | C69: kWh — CS3 P50 mês 02 (base=143,140 kWh)
A70: Mar/27 | B70: =INDEX(PVSYST_Helexia!$J$5:$U$7,MATCH(Premissas!$B$13,PVSYST_Helexia!$B$5:$B$7,0),3)*1000*(1-Premissas!$B$23) -> 145568.5 | C70: kWh — CS3 P50 mês 03 (base=127,550 kWh)
A71: Abr/27 | B71: =INDEX(PVSYST_Helexia!$J$5:$U$7,MATCH(Premissas!$B$13,PVSYST_Helexia!$B$5:$B$7,0),4)*1000*(1-Premissas!$B$23) -> 145250.1 | C71: kWh — CS3 P50 mês 04 (base=146,300 kWh)
A72: Mai/27 | B72: =INDEX(PVSYST_Helexia!$J$5:$U$7,MATCH(Premissas!$B$13,PVSYST_Helexia!$B$5:$B$7,0),5)*1000*(1-Premissas!$B$23) -> 135936.9 | C72: kWh — CS3 P50 mês 05 (base=145,980 kWh)
A73: Jun/27 | B73: =INDEX(PVSYST_Helexia!$J$5:$U$7,MATCH(Premissas!$B$13,PVSYST_Helexia!$B$5:$B$7,0),6)*1000*(1-Premissas!$B$23) -> 123370.05 | C73: kWh — CS3 P50 mês 06 (base=136,620 kWh)
A74: Jul/27 | B74: =INDEX(PVSYST_Helexia!$J$5:$U$7,MATCH(Premissas!$B$13,PVSYST_Helexia!$B$5:$B$7,0),7)*1000*(1-Premissas!$B$23) -> 129857.45 | C74: kWh — CS3 P50 mês 07 (base=123,990 kWh)
A75: Ago/27 | B75: =INDEX(PVSYST_Helexia!$J$5:$U$7,MATCH(Premissas!$B$13,PVSYST_Helexia!$B$5:$B$7,0),8)*1000*(1-Premissas!$B$23) -> 155886.65 | C75: kWh — CS3 P50 mês 08 (base=130,510 kWh)
A76: Set/27 | B76: =INDEX(PVSYST_Helexia!$J$5:$U$7,MATCH(Premissas!$B$13,PVSYST_Helexia!$B$5:$B$7,0),9)*1000*(1-Premissas!$B$23) -> 146274.95 | C76: kWh — CS3 P50 mês 09 (base=156,670 kWh)
A77: Out/27 | B77: =INDEX(PVSYST_Helexia!$J$5:$U$7,MATCH(Premissas!$B$13,PVSYST_Helexia!$B$5:$B$7,0),10)*1000*(1-Premissas!$B$23) -> 150324.6 | C77: kWh — CS3 P50 mês 10 (base=147,010 kWh)
A78: Nov/27 | B78: =INDEX(PVSYST_Helexia!$J$5:$U$7,MATCH(Premissas!$B$13,PVSYST_Helexia!$B$5:$B$7,0),11)*1000*(1-Premissas!$B$23) -> 145349.6 | C78: kWh — CS3 P50 mês 11 (base=151,080 kWh)
A79: Dez/27 | B79: =INDEX(PVSYST_Helexia!$J$5:$U$7,MATCH(Premissas!$B$13,PVSYST_Helexia!$B$5:$B$7,0),12)*1000*(1-Premissas!$B$23) -> 138016.45 | C79: kWh — CS3 P50 mês 12 (base=146,080 kWh)
A80: Jan/28 | B80: =INDEX(PVSYST_Helexia!$J$5:$U$7,MATCH(Premissas!$B$13,PVSYST_Helexia!$B$5:$B$7,0),1)*1000*(1-Premissas!$B$23) -> 142424.3 | C80: kWh — CS3 P50 mês 01 (base=2,000 kWh)
A81: Fev/28 | B81: =INDEX(PVSYST_Helexia!$J$5:$U$7,MATCH(Premissas!$B$13,PVSYST_Helexia!$B$5:$B$7,0),2)*1000*(1-Premissas!$B$23) -> 126912.25 | C81: kWh — CS3 P50 mês 02 (base=143,140 kWh)
A82: Mar/28 | B82: =INDEX(PVSYST_Helexia!$J$5:$U$7,MATCH(Premissas!$B$13,PVSYST_Helexia!$B$5:$B$7,0),3)*1000*(1-Premissas!$B$23) -> 145568.5 | C82: kWh — CS3 P50 mês 03 (base=127,550 kWh)
A83: Abr/28 | B83: =INDEX(PVSYST_Helexia!$J$5:$U$7,MATCH(Premissas!$B$13,PVSYST_Helexia!$B$5:$B$7,0),4)*1000*(1-Premissas!$B$23) -> 145250.1 | C83: kWh — CS3 P50 mês 04 (base=146,300 kWh)
A84: Mai/28 | B84: =INDEX(PVSYST_Helexia!$J$5:$U$7,MATCH(Premissas!$B$13,PVSYST_Helexia!$B$5:$B$7,0),5)*1000*(1-Premissas!$B$23) -> 135936.9 | C84: kWh — CS3 P50 mês 05 (base=145,980 kWh)
A85: Jun/28 | B85: =INDEX(PVSYST_Helexia!$J$5:$U$7,MATCH(Premissas!$B$13,PVSYST_Helexia!$B$5:$B$7,0),6)*1000*(1-Premissas!$B$23)^2 -> 122753.2 | C85: kWh — CS3 P50 mês 06
A86: Jul/28 | B86: =INDEX(PVSYST_Helexia!$J$5:$U$7,MATCH(Premissas!$B$13,PVSYST_Helexia!$B$5:$B$7,0),7)*1000*(1-Premissas!$B$23)^2 -> 129208.16 | C86: kWh — CS3 P50 mês 07
A87: Ago/28 | B87: =INDEX(PVSYST_Helexia!$J$5:$U$7,MATCH(Premissas!$B$13,PVSYST_Helexia!$B$5:$B$7,0),8)*1000*(1-Premissas!$B$23)^2 -> 155107.22 | C87: kWh — CS3 P50 mês 08
A88: Set/28 | B88: =INDEX(PVSYST_Helexia!$J$5:$U$7,MATCH(Premissas!$B$13,PVSYST_Helexia!$B$5:$B$7,0),9)*1000*(1-Premissas!$B$23)^2 -> 145543.58 | C88: kWh — CS3 P50 mês 09
A89: Out/28 | B89: =INDEX(PVSYST_Helexia!$J$5:$U$7,MATCH(Premissas!$B$13,PVSYST_Helexia!$B$5:$B$7,0),10)*1000*(1-Premissas!$B$23)^2 -> 149572.98 | C89: kWh — CS3 P50 mês 10
A90: Nov/28 | B90: =INDEX(PVSYST_Helexia!$J$5:$U$7,MATCH(Premissas!$B$13,PVSYST_Helexia!$B$5:$B$7,0),11)*1000*(1-Premissas!$B$23)^2 -> 144622.85 | C90: kWh — CS3 P50 mês 11
A91: Dez/28 | B91: =INDEX(PVSYST_Helexia!$J$5:$U$7,MATCH(Premissas!$B$13,PVSYST_Helexia!$B$5:$B$7,0),12)*1000*(1-Premissas!$B$23)^2 -> 137326.37 | C91: kWh — CS3 P50 mês 12
A92: Jan/29 | B92: =INDEX(PVSYST_Helexia!$J$5:$U$7,MATCH(Premissas!$B$13,PVSYST_Helexia!$B$5:$B$7,0),1)*1000*(1-Premissas!$B$23)^2 -> 141712.18 | C92: kWh — CS3 P50 mês 01
A93: Fev/29 | B93: =INDEX(PVSYST_Helexia!$J$5:$U$7,MATCH(Premissas!$B$13,PVSYST_Helexia!$B$5:$B$7,0),2)*1000*(1-Premissas!$B$23)^2 -> 126277.69 | C93: kWh — CS3 P50 mês 02
A94: Mar/29 | B94: =INDEX(PVSYST_Helexia!$J$5:$U$7,MATCH(Premissas!$B$13,PVSYST_Helexia!$B$5:$B$7,0),3)*1000*(1-Premissas!$B$23)^2 -> 144840.66 | C94: kWh — CS3 P50 mês 03
A95: Abr/29 | B95: =INDEX(PVSYST_Helexia!$J$5:$U$7,MATCH(Premissas!$B$13,PVSYST_Helexia!$B$5:$B$7,0),4)*1000*(1-Premissas!$B$23)^2 -> 144523.85 | C95: kWh — CS3 P50 mês 04
A96: Mai/29 | B96: =INDEX(PVSYST_Helexia!$J$5:$U$7,MATCH(Premissas!$B$13,PVSYST_Helexia!$B$5:$B$7,0),5)*1000*(1-Premissas!$B$23)^2 -> 135257.22 | C96: kWh — CS3 P50 mês 05
A97: Jun/29 | B97: =INDEX(PVSYST_Helexia!$J$5:$U$7,MATCH(Premissas!$B$13,PVSYST_Helexia!$B$5:$B$7,0),6)*1000*(1-Premissas!$B$23)^3 -> 122139.43 | C97: kWh — CS3 P50 mês 06
A98: Jul/29 | B98: =INDEX(PVSYST_Helexia!$J$5:$U$7,MATCH(Premissas!$B$13,PVSYST_Helexia!$B$5:$B$7,0),7)*1000*(1-Premissas!$B$23)^3 -> 128562.12 | C98: kWh — CS3 P50 mês 07
A99: Ago/29 | B99: =INDEX(PVSYST_Helexia!$J$5:$U$7,MATCH(Premissas!$B$13,PVSYST_Helexia!$B$5:$B$7,0),8)*1000*(1-Premissas!$B$23)^3 -> 154331.68 | C99: kWh — CS3 P50 mês 08
A100: Set/29 | B100: =INDEX(PVSYST_Helexia!$J$5:$U$7,MATCH(Premissas!$B$13,PVSYST_Helexia!$B$5:$B$7,0),9)*1000*(1-Premissas!$B$23)^3 -> 144815.86 | C100: kWh — CS3 P50 mês 09
A101: Out/29 | B101: =INDEX(PVSYST_Helexia!$J$5:$U$7,MATCH(Premissas!$B$13,PVSYST_Helexia!$B$5:$B$7,0),10)*1000*(1-Premissas!$B$23)^3 -> 148825.11 | C101: kWh — CS3 P50 mês 10
A102: Nov/29 | B102: =INDEX(PVSYST_Helexia!$J$5:$U$7,MATCH(Premissas!$B$13,PVSYST_Helexia!$B$5:$B$7,0),11)*1000*(1-Premissas!$B$23)^3 -> 143899.74 | C102: kWh — CS3 P50 mês 11
A103: Dez/29 | B103: =INDEX(PVSYST_Helexia!$J$5:$U$7,MATCH(Premissas!$B$13,PVSYST_Helexia!$B$5:$B$7,0),12)*1000*(1-Premissas!$B$23)^3 -> 136639.74 | C103: kWh — CS3 P50 mês 12
A104: Jan/30 | B104: =INDEX(PVSYST_Helexia!$J$5:$U$7,MATCH(Premissas!$B$13,PVSYST_Helexia!$B$5:$B$7,0),1)*1000*(1-Premissas!$B$23)^3 -> 141003.62 | C104: kWh — CS3 P50 mês 01
A105: Fev/30 | B105: =INDEX(PVSYST_Helexia!$J$5:$U$7,MATCH(Premissas!$B$13,PVSYST_Helexia!$B$5:$B$7,0),2)*1000*(1-Premissas!$B$23)^3 -> 125646.3 | C105: kWh — CS3 P50 mês 02
A106: Mar/30 | B106: =INDEX(PVSYST_Helexia!$J$5:$U$7,MATCH(Premissas!$B$13,PVSYST_Helexia!$B$5:$B$7,0),3)*1000*(1-Premissas!$B$23)^3 -> 144116.45 | C106: kWh — CS3 P50 mês 03
A107: Abr/30 | B107: =INDEX(PVSYST_Helexia!$J$5:$U$7,MATCH(Premissas!$B$13,PVSYST_Helexia!$B$5:$B$7,0),4)*1000*(1-Premissas!$B$23)^3 -> 143801.23 | C107: kWh — CS3 P50 mês 04
A108: Mai/30 | B108: =INDEX(PVSYST_Helexia!$J$5:$U$7,MATCH(Premissas!$B$13,PVSYST_Helexia!$B$5:$B$7,0),5)*1000*(1-Premissas!$B$23)^3 -> 134580.93 | C108: kWh — CS3 P50 mês 05
A109: Jun/30 | B109: =INDEX(PVSYST_Helexia!$J$5:$U$7,MATCH(Premissas!$B$13,PVSYST_Helexia!$B$5:$B$7,0),6)*1000*(1-Premissas!$B$23)^4 -> 121528.74 | C109: kWh — CS3 P50 mês 06
...

Sheet Input_Consumo_GrupoA
A1: INPUT — CONSUMO ORÇADO GRUPO A | Fonte: Consumo_Orçado_2026_GD
A2: Azul = valores editáveis (fonte: arquivo fornecido) | Preto = fórmulas de projeção Y2/Y3
A3: Mês | B3: NHS FP (kWh) | C3: NHS Ponta (kWh) | D3: BAT FP (kWh) | E3: BAT Ponta (kWh) | F3: AMD FP (kWh) | G3: AMD Ponta (kWh)
A4: Jan | B4: 70769.9 | C4: 7863.3 | D4: 113967 | E4: 12663 | F4: 73973.4 | G4: 8219.3
A5: Fev | B5: 243719.7 | C5: 27080 | D5: 125874 | E5: 13986 | F5: 209472.2 | G5: 23274.7
A6: Mar | B6: 331874.1 | C6: 36874.9 | D6: 57499.2 | E6: 6388.8 | F6: 173260.2 | G6: 19251.1
A7: Abr | B7: 102778.3 | C7: 11419.8 | D7: 35640 | E7: 3960 | F7: 78448.4 | G7: 8716.5
A8: Mai | B8: 62814.2 | C8: 6979.4 | D8: 79603.2 | E8: 8844.8 | F8: 102629.5 | G8: 11403.3
A9: Jun | B9: 108694.9 | C9: 12077.2 | D9: 78336 | E9: 8704 | F9: 182444.7 | G9: 20271.6
A10: Jul | B10: 328938.1 | C10: 36548.7 | D10: 115718.4 | E10: 12857.6 | F10: 234799.2 | G10: 26088.8
A11: Ago | B11: 190977.6 | C11: 21219.7 | D11: 23364 | E11: 2596 | F11: 134799.3 | G11: 14977.7
A12: Set | B12: 126478.8 | C12: 14053.2 | D12: 10800 | E12: 1200 | F12: 18637.2 | G12: 2070.8
A13: Out | B13: 28215 | C13: 3135 | D13: 10800 | E13: 1200 | F13: 24382.8 | G13: 2709.2
A14: Nov | B14: 42209.6 | C14: 4690 | D14: 10800 | E14: 1200 | F14: 20225.7 | G14: 2247.3
A15: Dez | B15: 42209.6 | C15: 4690 | D15: 3402 | E15: 378 | F15: 17142.3 | G15: 1904.7
A17: Crescimento Y2 aplicado automaticamente via Premissas!$B$21 (atualmente 2,5%). Altere lá para que todos os 18 UCs sejam atualizados.

Sheet Simulacao
A1: ="SIMULAÇÃO RATEIO FIXO — "&Premissas!$B$13&" × COPASUL | 18 UCs | Jun/2026–Mai/2031" -> SIMULAÇÃO RATEIO FIXO — Cassilândia 03 × COPASUL | 18 UCs | Jun/2026–Mai/2031
A2: Energisa MS · Todas as células são fórmulas · Azul=input Premissas · Verde=link entre abas
A4: INDICADOR / UC | B4: TOTAL 60m ou SALDO FINAL | C4: MÉD/mês ou unidade | D4: Jun/26 | E4: Jul/26 | F4: Ago/26 | G4: Set/26 | H4: Out/26 | I4: Nov/26 | J4: Dez/26 | K4: Jan/27 | L4: Fev/27 | M4: Mar/27 | N4: Abr/27 | O4: Mai/27 | P4: Jun/27 | Q4: Jul/27 | R4: Ago/27 | S4: Set/27 | T4: Out/27 | U4: Nov/27 | V4: Dez/27 | W4: Jan/28 | X4: Fev/28 | Y4: Mar/28 | Z4: Abr/28 | AA4: Mai/28 | AB4: Jun/28 | AC4: Jul/28 | AD4: Ago/28 | AE4: Set/28 | AF4: Out/28 | AG4: Nov/28 | AH4: Dez/28 | AI4: Jan/29 | AJ4: Fev/29 | AK4: Mar/29 | AL4: Abr/29 | AM4: Mai/29 | AN4: Jun/29 | AO4: Jul/29 | AP4: Ago/29 | AQ4: Set/29 | AR4: Out/29 | AS4: Nov/29 | AT4: Dez/29 | AU4: Jan/30 | AV4: Fev/30 | AW4: Mar/30 | AX4: Abr/30 | AY4: Mai/30 | AZ4: Jun/30 | BA4: Jul/30 | BB4: Ago/30 | BC4: Set/30 | BD4: Out/30 | BE4: Nov/30 | BF4: Dez/30 | BG4: Jan/31 | BH4: Fev/31 | BI4: Mar/31 | BJ4: Abr/31 | BK4: Mai/31 | BL4: Jun/31 | BM4: Jul/31 | BN4: Ago/31 | BO4: Set/31 | BP4: Out/31 | BQ4: Nov/31 | BR4: Dez/31 | BS4: Jan/32 | BT4: Fev/32 | BU4: Mar/32 | BV4: Abr/32 | BW4: Mai/32 | BX4: Jun/32 | BY4: Jul/32 | BZ4: Ago/32 | CA4: Set/32 | CB4: Out/32 | CC4: Nov/32 | CD4: Dez/32 | CE4: Jan/33 | CF4: Fev/33 | CG4: Mar/33 | CH4: Abr/33 | CI4: Mai/33 | CJ4: Jun/33 | CK4: Jul/33 | CL4: Ago/33 | CM4: Set/33 | CN4: Out/33 | CO4: Nov/33 | CP4: Dez/33 | CQ4: Jan/34 | CR4: Fev/34 | CS4: Mar/34 | CT4: Abr/34 | CU4: Mai/34 | CV4: Jun/34 | CW4: Jul/34 | CX4: Ago/34 | CY4: Set/34 | CZ4: Out/34 | DA4: Nov/34 | DB4: Dez/34 | DC4: Jan/35 | DD4: Fev/35 | DE4: Mar/35 | DF4: Abr/35 | DG4: Mai/35 | DH4: Jun/35 | DI4: Jul/35 | DJ4: Ago/35 | DK4: Set/35 | DL4: Out/35 | DM4: Nov/35 | DN4: Dez/35 | DO4: Jan/36 | DP4: Fev/36 | DQ4: Mar/36 | DR4: Abr/36 | DS4: Mai/36
A5: ="0. "&Premissas!B13&" — GERAÇÃO E CUSTO PPA" -> 0. Cassilândia 03 — GERAÇÃO E CUSTO PPA
A6: =INDEX(PVSYST_Helexia!$A$5:$A$7,MATCH(Premissas!$B$13,PVSYST_Helexia!$B$5:$B$7,0))&" Geração P50 (kWh)" -> HCS03 Geração P50 (kWh) | B6: =SUM(D6:BQ6) -> 9214611.7 | C6: =B6/60 -> 153576.86 | D6: =Premissas!$B$61 -> 123990 | E6: =Premissas!$B$62 -> 130510 | F6: =Premissas!$B$63 -> 156670 | G6: =Premissas!$B$64 -> 147010 | H6: =Premissas!$B$65 -> 151080 | I6: =Premissas!$B$66 -> 146080 | J6: =Premissas!$B$67 -> 138710 | K6: =Premissas!$B$68 -> 142424.3 | L6: =Premissas!$B$69 -> 126912.25 | M6: =Premissas!$B$70 -> 145568.5 | N6: =Premissas!$B$71 -> 145250.1 | O6: =Premissas!$B$72 -> 135936.9 | P6: =Premissas!$B$73 -> 123370.05 | Q6: =Premissas!$B$74 -> 129857.45 | R6: =Premissas!$B$75 -> 155886.65 | S6: =Premissas!$B$76 -> 146274.95 | T6: =Premissas!$B$77 -> 150324.6 | U6: =Premissas!$B$78 -> 145349.6 | V6: =Premissas!$B$79 -> 138016.45 | W6: =Premissas!$B$80 -> 142424.3 | X6: =Premissas!$B$81 -> 126912.25 | Y6: =Premissas!$B$82 -> 145568.5 | Z6: =Premissas!$B$83 -> 145250.1 | AA6: =Premissas!$B$84 -> 135936.9 | AB6: =Premissas!$B$85 -> 122753.2 | AC6: =Premissas!$B$86 -> 129208.16 | AD6: =Premissas!$B$87 -> 155107.22 | AE6: =Premissas!$B$88 -> 145543.58 | AF6: =Premissas!$B$89 -> 149572.98 | AG6: =Premissas!$B$90 -> 144622.85 | AH6: =Premissas!$B$91 -> 137326.37 | AI6: =Premissas!$B$92 -> 141712.18 | AJ6: =Premissas!$B$93 -> 126277.69 | AK6: =Premissas!$B$94 -> 144840.66 | AL6: =Premissas!$B$95 -> 144523.85 | AM6: =Premissas!$B$96 -> 135257.22 | AN6: =Premissas!$B$97 -> 122139.43 | AO6: =Premissas!$B$98 -> 128562.12 | AP6: =Premissas!$B$99 -> 154331.68 | AQ6: =Premissas!$B$100 -> 144815.86 | AR6: =Premissas!$B$101 -> 148825.11 | AS6: =Premissas!$B$102 -> 143899.74 | AT6: =Premissas!$B$103 -> 136639.74 | AU6: =Premissas!$B$104 -> 141003.62 | AV6: =Premissas!$B$105 -> 125646.3 | AW6: =Premissas!$B$106 -> 144116.45 | AX6: =Premissas!$B$107 -> 143801.23 | AY6: =Premissas!$B$108 -> 134580.93 | AZ6: =Premissas!$B$109 -> 121528.74 | BA6: =Premissas!$B$110 -> 127919.31 | BB6: =Premissas!$B$111 -> 153560.02 | BC6: =Premissas!$B$112 -> 144091.78 | BD6: =Premissas!$B$113 -> 148080.99 | BE6: =Premissas!$B$114 -> 143180.24 | BF6: =Premissas!$B$115 -> 135956.54 | BG6: =Premissas!$B$116 -> 140298.6 | BH6: =Premissas!$B$117 -> 125018.07 | BI6: =Premissas!$B$118 -> 143395.87 | BJ6: =Premissas!$B$119 -> 143082.22 | BK6: =Premissas!$B$120 -> 133908.02 | BL6: =Premissas!$B$121 -> 120921.09 | BM6: =Premissas!$B$122 -> 127279.71 | BN6: =Premissas!$B$123 -> 152792.22 | BO6: =Premissas!$B$124 -> 143371.32 | BP6: =Premissas!$B$125 -> 147340.58 | BQ6: =Premissas!$B$126 -> 142464.34 | BR6: =Premissas!$B$127 -> 135276.75 | BS6: =Premissas!$B$128 -> 139597.11 | BT6: =Premissas!$B$129 -> 124392.98 | BU6: =Premissas!$B$130 -> 142678.89 | BV6: =Premissas!$B$131 -> 142366.81 | BW6: =Premissas!$B$132 -> 133238.48 | BX6: =Premissas!$B$133 -> 120316.49 | BY6: =Premissas!$B$134 -> 126643.32 | BZ6: =Premissas!$B$135 -> 152028.26 | CA6: =Premissas!$B$136 -> 142654.46 | CB6: =Premissas!$B$137 -> 146603.88 | CC6: =Premissas!$B$138 -> 141752.02 | CD6: =Premissas!$B$139 -> 134600.37 | CE6: =Premissas!$B$140 -> 138899.12 | CF6: =Premissas!$B$141 -> 123771.01 | CG6: =Premissas!$B$142 -> 141965.5 | CH6: =Premissas!$B$143 -> 141654.98 | CI6: =Premissas!$B$144 -> 132572.29 | CJ6: =Premissas!$B$145 -> 119714.9 | CK6: =Premissas!$B$146 -> 126010.1 | CL6: =Premissas!$B$147 -> 151268.12 | CM6: =Premissas!$B$148 -> 141941.19 | CN6: =Premissas!$B$149 -> 145870.86 | CO6: =Premissas!$B$150 -> 141043.26 | CP6: =Premissas!$B$151 -> 133927.37 | CQ6: =Premissas!$B$152 -> 138204.63 | CR6: =Premissas!$B$153 -> 123152.16 | CS6: =Premissas!$B$154 -> 141255.67 | CT6: =Premissas!$B$155 -> 140946.7 | CU6: =Premissas!$B$156 -> 131909.43 | CV6: =Premissas!$B$157 -> 119116.33 | CW6: =Premissas!$B$158 -> 125380.05 | CX6: =Premissas!$B$159 -> 150511.78 | CY6: =Premissas!$B$160 -> 141231.48 | CZ6: =Premissas!$B$161 -> 145141.51 | DA6: =Premissas!$B$162 -> 140338.04 | DB6: =Premissas!$B$163 -> 133257.73 | DC6: =Premissas!$B$164 -> 137513.6 | DD6: =Premissas!$B$165 -> 122536.4 | DE6: =Premissas!$B$166 -> 140549.39 | DF6: =Premissas!$B$167 -> 140241.97 | DG6: =Premissas!$B$168 -> 131249.88 | DH6: =Premissas!$B$169 -> 118520.75 | DI6: =Premissas!$B$170 -> 124753.15 | DJ6: =Premissas!$B$171 -> 149759.22 | DK6: =Premissas!$B$172 -> 140525.33 | DL6: =Premissas!$B$173 -> 144415.8 | DM6: =Premissas!$B$174 -> 139636.35 | DN6: =Premissas!$B$175 -> 132591.44 | DO6: =Premissas!$B$176 -> 136826.03 | DP6: =Premissas!$B$177 -> 121923.72 | DQ6: =Premissas!$B$178 -> 139846.65 | DR6: =Premissas!$B$179 -> 139540.76 | DS6: =Premissas!$B$180 -> 130593.63
A7: PPA Helexia — custo total (R$) | B7: =SUM(D7:DS7) -> 7326414.9 | C7: =B7/60 -> 122106.91 | D7: =D6*Premissas!$B$17 -> 54865.575 | E7: =E6*Premissas!$B$17 -> 57750.675 | F7: =F6*Premissas!$B$17 -> 69326.475 | G7: =G6*Premissas!$B$17 -> 65051.925 | H7: =H6*Premissas!$B$17 -> 66852.9 | I7: =I6*Premissas!$B$17 -> 64640.4 | J7: =J6*Premissas!$B$17 -> 61379.175 | K7: =K6*Premissas!$B$17 -> 63022.753 | ... DS7: =DS6*Premissas!$B$17 -> 57787.683
A8: 1. BAT — BATAYPORÃ — GERAÇÃO, CONSUMO E SURPLUS
A9: BAT Geração própria (kWh) | B9: =SUM(D9:BQ9) -> 6130080.1 | C9: =B9/60 -> 102168 | D9: =+Batayporã!I8 -> 72286.9 | E9: =+Batayporã!I9 -> 88336.8 | F9: =+Batayporã!I10 -> 93082.7 | G9: =+Batayporã!I11 -> 94433.4 | H9: =+Batayporã!I12 -> 95906.8 | I9: =+Batayporã!I13 -> 107980.6 | J9: =+Batayporã!I14 -> 106603.9 | K9: =+Batayporã!I3*(1-Premissas!$B$23) -> 113687.7 | L9: =+Batayporã!I4*(1-Premissas!$B$23) -> 90676.241 | M9: =+Batayporã!I5*(1-Premissas!$B$23) -> 102546.59 | N9: =+Batayporã!I6*(1-Premissas!$B$23) -> 73341.151 | O9: =+Batayporã!I7*(1-Premissas!$B$23) -> 91158.517 | P9: =D9*(1-Premissas!$B$23) -> 71925.465 | Q9: =E9*(1-Premissas!$B$23) -> 87895.116 | R9: =F9*(1-Premissas!$B$23) -> 92617.287 | S9: =G9*(1-Premissas!$B$23) -> 93961.233 | T9: =H9*(1-Premissas!$B$23) -> 95427.266 | U9: =I9*(1-Premissas!$B$23) -> 107440.7 | V9: =J9*(1-Premissas!$B$23) -> 106070.88 | W9: =K9*(1-Premissas!$B$23) -> 113119.27 | ... BK9: =AY9*(1-Premissas!$B$23) -> 89348.975 | BL9: =AY9*(1-Premissas!$B$23) -> 89348.975 | BM9: =AY9*(1-Premissas!$B$23) -> 89348.975 | BN9: =AY9*(1-Premissas!$B$23) -> 89348.975 | BO9: =AY9*(1-Premissas!$B$23) -> 89348.975 | BP9: =AY9*(1-Premissas!$B$23) -> 89348.975 | BQ9: =AY9*(1-Premissas!$B$23) -> 89348.975 | BR9: =AY9*(1-Premissas!$B$23) -> 89348.975 | BS9: =AY9*(1-Premissas!$B$23) -> 89348.975 | BT9: =AY9*(1-Premissas!$B$23) -> 89348.975 | BU9: =AY9*(1-Premissas!$B$23) -> 89348.975 | BV9: =AY9*(1-Premissas!$B$23) -> 89348.975 | BW9: =AY9*(1-Premissas!$B$23) -> 89348.975 | BX9: =AY9*(1-Premissas!$B$23) -> 89348.975 | BY9: =AY9*(1-Premissas!$B$23) -> 89348.975 | BZ9: =AY9*(1-Premissas!$B$23) -> 89348.975 | CA9: =AY9*(1-Premissas!$B$23) -> 89348.975 | CB9: =AY9*(1-Premissas!$B$23) -> 89348.975 | CC9: =AY9*(1-Premissas!$B$23) -> 89348.975 | CD9: =AY9*(1-Premissas!$B$23) -> 89348.975 | CE9: =AY9*(1-Premissas!$B$23) -> 89348.975 | CF9: =AY9*(1-Premissas!$B$23) -> 89348.975 | CG9: =AY9*(1-Premissas!$B$23) -> 89348.975 | CH9: =AY9*(1-Premissas!$B$23) -> 89348.975 | CI9: =AY9*(1-Premissas!$B$23) -> 89348.975 | CJ9: =AY9*(1-Premissas!$B$23) -> 89348.975 | CK9: =AY9*(1-Premissas!$B$23) -> 89348.975 | CL9: =AY9*(1-Premissas!$B$23) -> 89348.975 | CM9: =AY9*(1-Premissas!$B$23) -> 89348.975 | CN9: =AY9*(1-Premissas!$B$23) -> 89348.975 | CO9: =AY9*(1-Premissas!$B$23) -> 89348.975 | CP9: =AY9*(1-Premissas!$B$23) -> 89348.975 | CQ9: =AY9*(1-Premissas!$B$23) -> 89348.975 | CR9: =AY9*(1-Premissas!$B$23) -> 89348.975 | CS9: =AY9*(1-Premissas!$B$23) -> 89348.975 | CT9: =AY9*(1-Premissas!$B$23) -> 89348.975 | CU9: =AY9*(1-Premissas!$B$23) -> 89348.975 | CV9: =AY9*(1-Premissas!$B$23) -> 89348.975 | CW9: =AY9*(1-Premissas!$B$23) -> 89348.975 | CX9: =AY9*(1-Premissas!$B$23) -> 89348.975 | CY9: =AY9*(1-Premissas!$B$23) -> 89348.975 | CZ9: =AY9*(1-Premissas!$B$23) -> 89348.975 | DA9: =AY9*(1-Premissas!$B$23) -> 89348.975 | DB9: =AY9*(1-Premissas!$B$23) -> 89348.975 | DC9: =AY9*(1-Premissas!$B$23) -> 89348.975 | DD9: =AY9*(1-Premissas!$B$23) -> 89348.975 | DE9: =AY9*(1-Premissas!$B$23) -> 89348.975 | DF9: =AY9*(1-Premissas!$B$23) -> 89348.975 | DG9: =AY9*(1-Premissas!$B$23) -> 89348.975 | DH9: =AY9*(1-Premissas!$B$23) -> 89348.975 | DI9: =AY9*(1-Premissas!$B$23) -> 89348.975 | DJ9: =AY9*(1-Premissas!$B$23) -> 89348.975 | DK9: =AY9*(1-Premissas!$B$23) -> 89348.975 | DL9: =AY9*(1-Premissas!$B$23) -> 89348.975 | DM9: =AY9*(1-Premissas!$B$23) -> 89348.975 | DN9: =AY9*(1-Premissas!$B$23) -> 89348.975 | DO9: =AY9*(1-Premissas!$B$23) -> 89348.975 | DP9: =AY9*(1-Premissas!$B$23) -> 89348.975 | DQ9: =AY9*(1-Premissas!$B$23) -> 89348.975 | DR9: =AY9*(1-Premissas!$B$23) -> 89348.975 | DS9: =AY9*(1-Premissas!$B$23) -> 89348.975
A10: BAT Consumo FP (kWh) | B10: =SUM(D10:BQ10) -> 3825969 | C10: =B10/60 -> 63766.15 | D10: 78336 | E10: 115718 | F10: 23364 | G10: 10800 | H10: 10800 | I10: 10800 | J10: 3402 | K10: 116816 | L10: 129021 | M10: 58937 | N10: 36531 | O10: 81593 | P10: 80294 | Q10: 118611 | R10: 23948 | S10: 11070 | T10: 11070 | U10: 11070 | V10: 3487 | W10: 116816 | X10: 129021 | Y10: 58937 | Z10: 36531 | AA10: 81593 | AB10: 82302 | AC10: 121576 | AD10: 24547 | AE10: 11347 | AF10: 11347 | AG10: 11347 | AH10: 3574 | AI10: 122730 | AJ10: 135553 | AK10: 61921 | AL10: 38380 | AM10: 85724 | AN10: 84359 | AO10: 124616 | AP10: 25160 | AQ10: 11630 | AR10: 11630 | AS10: 11630 | AT10: 3664 | AU10: 125798 | AV10: 138942 | AW10: 63469 | AX10: 39340 | AY10: 87867 | AZ10: 86468 | BA10: 127731 | BB10: 25789 | BC10: 11921 | BD10: 11921 | BE10: 11921 | BF10: 3755 | BG10: 128943 | BH10: 142415 | BI10: 65055 | BJ10: 40323 | BK10: 90063 | BL10: 88630 | BM10: 130924 | BN10: 26434 | BO10: 12219 | BP10: 12219 | BQ10: 12219 | BR10: 3849 | BS10: 132167 | BT10: 145975 | BU10: 66682 | BV10: 41331 | BW10: 92315 | BX10: 90846 | BY10: 134197 | BZ10: 27095 | CA10: 12525 | CB10: 12525 | CC10: 12525 | CD10: 3945 | CE10: 135471 | CF10: 149625 | CG10: 68349 | CH10: 42365 | CI10: 94623 | CJ10: 93117 | CK10: 137552 | CL10: 27772 | CM10: 12838 | CN10: 12838 | CO10: 12838 | CP10: 4044 | CQ10: 138858 | CR10: 153365 | CS10: 70058 | CT10: 43424 | CU10: 96988 | CV10: 95445 | CW10: 140991 | CX10: 28467 | CY10: 13159 | CZ10: 13159 | DA10: 13159 | DB10: 4145 | DC10: 142329 | DD10: 157200 | DE10: 71809 | DF10: 44509 | DG10: 99413 | DH10: 97831 | DI10: 144516 | DJ10: 29178 | DK10: 13488 | DL10: 13488 | DM10: 13488 | DN10: 4249 | DO10: 145887 | DP10: 161130 | DQ10: 73604 | DR10: 45622 | DS10: 101898
A11: BAT Consumo Ponta (kWh) | B11: =SUM(D11:BQ11) -> 425119 | C11: =B11/60 -> 7085.3167 | D11: 8704 | E11: 12858 | F11: 2596 | G11: 1200 | H11: 1200 | I11: 1200 | J11: 378 | K11: 12980 | L11: 14336 | M11: 6549 | N11: 4059 | O11: 9066 | P11: 8922 | Q11: 13179 | R11: 2661 | S11: 1230 | T11: 1230 | U11: 1230 | V11: 387 | W11: 12980 | X11: 14336 | Y11: 6549 | Z11: 4059 | AA11: 9066 | AB11: 9145 | AC11: 13509 | AD11: 2727 | AE11: 1261 | AF11: 1261 | AG11: 1261 | AH11: 397 | AI11: 13637 | AJ11: 15062 | AK11: 6881 | AL11: 4264 | AM11: 9525 | AN11: 9373 | AO11: 13847 | AP11: 2796 | AQ11: 1292 | AR11: 1292 | AS11: 1292 | AT11: 407 | AU11: 13978 | AV11: 15438 | AW11: 7053 | AX11: 4371 | AY11: 9763 | AZ11: 9608 | BA11: 14193 | BB11: 2865 | BC11: 1325 | BD11: 1325 | BE11: 1325 | BF11: 417 | BG11: 14327 | BH11: 15824 | BI11: 7229 | BJ11: 4480 | BK11: 10007 | BL11: 9848 | BM11: 14548 | BN11: 2937 | BO11: 1358 | BP11: 1358 | BQ11: 1358 | BR11: 428 | BS11: 14686 | BT11: 16220 | BU11: 7410 | BV11: 4592 | BW11: 10257 | BX11: 10094 | BY11: 14911 | BZ11: 3011 | CA11: 1392 | CB11: 1392 | CC11: 1392 | CD11: 438 | CE11: 15053 | CF11: 16625 | CG11: 7595 | CH11: 4707 | CI11: 10514 | CJ11: 10346 | CK11: 15284 | CL11: 3086 | CM11: 1426 | CN11: 1426 | CO11: 1426 | CP11: 449 | CQ11: 15429 | CR11: 17041 | CS11: 7785 | CT11: 4825 | CU11: 10777 | CV11: 10605 | CW11: 15666 | CX11: 3163 | CY11: 1462 | CZ11: 1462 | DA11: 1462 | DB11: 461 | DC11: 15815 | DD11: 17467 | DE11: 7979 | DF11: 4945 | DG11: 11046 | DH11: 10870 | DI11: 16058 | DJ11: 3242 | DK11: 1499 | DL11: 1499 | DM11: 1499 | DN11: 472 | DO11: 16210 | DP11: 17904 | DQ11: 8179 | DR11: 5069 | DS11: 11322
A12: BAT auto-comp. FP (kWh) | B12: =SUM(D12:BQ12) -> 3284393.8 | C12: =B12/60 -> 54739.897 | D12: =MIN(D9,D10) -> 72286.9 | E12: =MIN(E9,E10) -> 88336.8 | F12: =MIN(F9,F10) -> 23364 | G12: =MIN(G9,G10) -> 10800 | H12: =MIN(H9,H10) -> 10800 | I12: =MIN(I9,I10) -> 10800 | J12: =MIN(J9,J10) -> 3402 | K12: =MIN(K9,K10) -> 113687.7 | ... DS12: =MIN(DS9,DS10) -> 89348.975
A13: BAT auto-comp. Ponta via FA (kWh) | B13: =SUM(D13:BQ13) -> 112680.54 | C13: =B13/60 -> 1878.009 | D13: =MIN((D9-D12)*Premissas!$B$8,D11) -> 0 | E13: =MIN((E9-E12)*Premissas!$B$8,E11) -> 0 | F13: =MIN((F9-F12)*Premissas!$B$8,F11) -> 2596 | G13: =MIN((G9-G12)*Premissas!$B$8,G11) -> 1200 | H13: =MIN((H9-H12)*Premissas!$B$8,H11) -> 1200 | I13: =MIN((I9-I12)*Premissas!$B$8,I11) -> 1200 | J13: =MIN((J9-J12)*Premissas!$B$8,J11) -> 378 | K13: =MIN((K9-K12)*Premissas!$B$8,K11) -> 0 | ... DS13: =MIN((DS9-DS12)*Premissas!$B$8,DS11) -> 0
A14: ★ BAT surplus líquido → rateio (kWh) | B14: =SUM(D14:BQ14) -> 2659211.6 | C14: =B14/60 -> 44320.193 | D14: =MAX(D9-D12-D11/Premissas!$B$8,0) -> 0 | E14: =MAX(E9-E12-E11/Premissas!$B$8,0) -> 0 | F14: =MAX(F9-F12-F11/Premissas!$B$8,0) -> 65422.586 | G14: =MAX(G9-G12-G11/Premissas!$B$8,0) -> 81647.523 | H14: =MAX(H9-H12-H11/Premissas!$B$8,0) -> 83120.923 | I14: =MAX(I9-I12-I11/Premissas!$B$8,0) -> 95194.723 | J14: =MAX(J9-J12-J11/Premissas!$B$8,0) -> 102576.35 | K14: =MAX(K9-K12-K11/Premissas!$B$8,0) -> 0 | ... DS14: =MAX(DS9-DS12-DS11/Premissas!$B$8,0) -> 0
A15: BAT banco stranded — depleção por consumo próprio apenas
A16: BAT banco início mês (kWh) | B16: =AA16 -> 582150.42 | C16: — | D16: =Premissas!$B$27 -> 906739 | E16: =D18 -> 886285.67 | F16: =E18 -> 837625.8 | G16: =F18 -> 837625.8 | H16: =G18 -> 837625.8 | I16: =H18 -> 837625.8 | J16: =I18 -> 837625.8 | K16: =J18 -> 837625.8 | L16: =K18 -> 813016.94 | ... DS16: =DR18 -> 0
A17: BAT banco draw (kWh) | B17: =SUM(D17:BQ17) -> 906739 | C17: =B17/60 -> 15112.317 | D17: =MIN(D16,MAX(D10-D12,0)+IF(Premissas!$B$8=0,0,MAX(D11-D13,0)/Premissas!$B$8)) -> 20453.327 | E17: =MIN(E16,MAX(E10-E12,0)+IF(Premissas!$B$8=0,0,MAX(E11-E13,0)/Premissas!$B$8)) -> 48659.871 | F17: =MIN(F16,MAX(F10-F12,0)+IF(Premissas!$B$8=0,0,MAX(F11-F13,0)/Premissas!$B$8)) -> 0 | G17: =MIN(G16,MAX(G10-G12,0)+IF(Premissas!$B$8=0,0,MAX(G11-G13,0)/Premissas!$B$8)) -> 0 | H17: =MIN(H16,MAX(H10-H12,0)+IF(Premissas!$B$8=0,0,MAX(H11-H13,0)/Premissas!$B$8)) -> 0 | I17: =MIN(I16,MAX(I10-I12,0)+IF(Premissas!$B$8=0,0,MAX(I11-I13,0)/Premissas!$B$8)) -> 0 | J17: =MIN(J16,MAX(J10-J12,0)+IF(Premissas!$B$8=0,0,MAX(J11-J13,0)/Premissas!$B$8)) -> 0 | K17: =MIN(K16,MAX(K10-K12,0)+IF(Premissas!$B$8=0,0,MAX(K11-K13,0)/Premissas!$B$8)) -> 24608.864 | ... DS17: =MIN(DS16,MAX(DS10-DS12,0)+IF(Premissas!$B$8=0,0,MAX(DS11-DS13,0)/Premissas!$B$8)) -> 0
A18: BAT banco fim mês (kWh) | B18: =AA18 -> 576256.85 | C18: — | D18: =MAX(D16-D17,0) -> 886285.67 | E18: =MAX(E16-E17,0) -> 837625.8 | F18: =MAX(F16-F17,0) -> 837625.8 | G18: =MAX(G16-G17,0) -> 837625.8 | H18: =MAX(H16-H17,0) -> 837625.8 | I18: =MAX(I16-I17,0) -> 837625.8 | J18: =MAX(J16-J17,0) -> 837625.8 | K18: =MAX(K16-K17,0) -> 813016.94 | ... DS18: =MAX(DS16-DS17,0) -> 0
A19: BAT créditos → NHS (kWh, T+1) | B19: =SUM(D19:BQ19) -> 1292164.5 | C19: =B19/60 -> 21536.074 | D19: =0 -> 0 | E19: =D14*Premissas!$B$55 -> 0 | F19: =E14*Premissas!$B$55 -> 0 | G19: =F14*Premissas!$B$55 -> 32711.293 | H19: =G14*Premissas!$B$55 -> 40823.762 | I19: =H14*Premissas!$B$55 -> 41560.462 | J19: =I14*Premissas!$B$55 -> 47597.362 | K19: =J14*Premissas!$B$55 -> 51288.174 | L19: =K14*Premissas!$B$55 -> 0 | ... DS19: =DR14*Premissas!$B$55 -> 17669.15
A20: BAT créditos → AMD (kWh, T+1) | B20: =SUM(D20:BQ20) -> 1292164.5 | C20: =B20/60 -> 21536.074 | D20: =0 -> 0 | E20: =D14*Premissas!$B$56 -> 0 | F20: =E14*Premissas!$B$56 -> 0 | G20: =F14*Premissas!$B$56 -> 32711.293 | H20: =G14*Premissas!$B$56 -> 40823.762 | I20: =H14*Premissas!$B$56 -> 41560.462 | J20: =I14*Premissas!$B$56 -> 47597.362 | K20: =J14*Premissas!$B$56 -> 51288.174 | L20: =K14*Premissas!$B$56 -> 0 | ... DS20: =DR14*Premissas!$B$56 -> 17669.15
A21: NHS — N. Horizonte do Sul (A4V)
A22: Consumo FP (kWh) | B22: =SUM(D22:BQ22) -> 9848843 | C22: =B22/60 -> 164147.38 | D22: 108695 | E22: 328938 | F22: 190978 | G22: 126479 | H22: 28215 | I22: 42210 | J22: 42210 | K22: 72539 | L22: 249813 | M22: 340171 | N22: 105348 | O22: 64385 | P22: 111412 | Q22: 337162 | R22: 195752 | S22: 129641 | T22: 28920 | U22: 43265 | V22: 43265 | W22: 72539 | X22: 249813 | Y22: 340171 | Z22: 105348 | AA22: 64385 | AB22: 114198 | AC22: 345590 | AD22: 200646 | AE22: 132882 | AF22: 29643 | AG22: 44347 | AH22: 44347 | AI22: 76211 | AJ22: 262460 | AK22: 357392 | AL22: 110681 | AM22: 67644 | AN22: 117053 | AO22: 354230 | AP22: 205662 | AQ22: 136204 | AR22: 30384 | AS22: 45456 | AT22: 45456 | AU22: 78117 | AV22: 269021 | AW22: 366327 | AX22: 113448 | AY22: 69336 | AZ22: 119979 | BA22: 363086 | BB22: 210804 | BC22: 139609 | BD22: 31144 | BE22: 46592 | BF22: 46592 | BG22: 80069 | BH22: 275747 | BI22: 375485 | BJ22: 116284 | BK22: 71069 | BL22: 122978 | BM22: 372163 | BN22: 216074 | BO22: 143099 | BP22: 31923 | BQ22: 47757 | BR22: 47757 | BS22: 82071 | BT22: 282640 | BU22: 384872 | BV22: 119192 | BW22: 72846 | BX22: 126053 | BY22: 381467 | BZ22: 221476 | CA22: 146677 | CB22: 32721 | CC22: 48951 | CD22: 48951 | CE22: 84123 | CF22: 289706 | CG22: 394494 | CH22: 122171 | CI22: 74667 | CJ22: 129204 | CK22: 391004 | CL22: 227013 | CM22: 150344 | CN22: 33539 | CO22: 50174 | CP22: 50174 | CQ22: 86226 | CR22: 296949 | CS22: 404356 | CT22: 125226 | CU22: 76534 | CV22: 132434 | CW22: 400779 | CX22: 232688 | CY22: 154102 | CZ22: 34377 | DA22: 51429 | DB22: 51429 | DC22: 88382 | DD22: 304373 | DE22: 414465 | DF22: 128356 | DG22: 78447 | DH22: 135745 | DI22: 410798 | DJ22: 238505 | DK22: 157955 | DL22: 35237 | DM22: 52715 | DN22: 52715 | DO22: 90591 | DP22: 311982 | DQ22: 424827 | DR22: 131565 | DS22: 80408
A23: Consumo Ponta (kWh) [via FA] | B23: =SUM(D23:BQ23) -> 1094316 | C23: =B23/60 -> 18238.6 | D23: 12077 | E23: 36549 | F23: 21220 | G23: 14053 | H23: 3135 | I23: 4690 | J23: 4690 | K23: 8060 | L23: 27757 | M23: 37797 | N23: 11705 | O23: 7154 | P23: 12379 | Q23: 37462 | R23: 21750 | S23: 14405 | T23: 3213 | U23: 4807 | V23: 4807 | W23: 8060 | X23: 27757 | Y23: 37797 | Z23: 11705 | AA23: 7154 | AB23: 12688 | AC23: 38399 | AD23: 22294 | AE23: 14764 | AF23: 3294 | AG23: 4927 | AH23: 4927 | AI23: 8468 | AJ23: 29162 | AK23: 39710 | AL23: 12298 | AM23: 7516 | AN23: 13006 | AO23: 39359 | AP23: 22852 | AQ23: 15134 | AR23: 3376 | AS23: 5051 | AT23: 5051 | AU23: 8680 | AV23: 29891 | AW23: 40703 | AX23: 12605 | AY23: 7704 | AZ23: 13331 | BA23: 40343 | BB23: 23423 | BC23: 15512 | BD23: 3460 | BE23: 5177 | BF23: 5177 | BG23: 8897 | BH23: 30639 | BI23: 41721 | BJ23: 12920 | BK23: 7897 | BL23: 13664 | BM23: 41352 | BN23: 24008 | BO23: 15900 | BP23: 3547 | BQ23: 5306 | BR23: 5306 | BS23: 9119 | BT23: 31404 | BU23: 42764 | BV23: 13243 | BW23: 8094 | BX23: 14006 | BY23: 42386 | BZ23: 24609 | CA23: 16297 | CB23: 3636 | CC23: 5439 | CD23: 5439 | CE23: 9347 | CF23: 32190 | CG23: 43833 | CH23: 13574 | CI23: 8296 | CJ23: 14356 | CK23: 43445 | CL23: 25224 | CM23: 16705 | CN23: 3727 | CO23: 5575 | CP23: 5575 | CQ23: 9581 | CR23: 32994 | CS23: 44929 | CT23: 13914 | CU23: 8504 | CV23: 14715 | CW23: 44531 | CX23: 25855 | CY23: 17122 | CZ23: 3820 | DA23: 5714 | DB23: 5714 | DC23: 9820 | DD23: 33819 | DE23: 46052 | DF23: 14261 | DG23: 8716 | DH23: 15083 | DI23: 45645 | DJ23: 26501 | DK23: 17550 | DL23: 3915 | DM23: 5857 | DN23: 5857 | DO23: 10066 | DP23: 34665 | DQ23: 47203 | DR23: 14618 | DS23: 8934
A24: Geração própria (kWh) | B24: =SUM(D24:BQ24) -> 5092260.8 | C24: =B24/60 -> 84871.013 | D24: =+'Novo Horizonte do Sul'!I8 -> 60380.6 | E24: =+'Novo Horizonte do Sul'!I9 -> 76551.2 | F24: =+'Novo Horizonte do Sul'!I10 -> 79815.6 | G24: =+'Novo Horizonte do Sul'!I11 -> 78203 | H24: =+'Novo Horizonte do Sul'!I12 -> 73160.1 | I24: =+'Novo Horizonte do Sul'!I13 -> 91030.5 | J24: =+'Novo Horizonte do Sul'!I14 -> 88631.7 | K24: =+'Novo Horizonte do Sul'!I3*(1-Premissas!$B$23) -> 83044.59 | L24: =+'Novo Horizonte do Sul'!I4*(1-Premissas!$B$23) -> 75743.778 | M24: =+'Novo Horizonte do Sul'!I5*(1-Premissas!$B$23) -> 89408.909 | N24: =+'Novo Horizonte do Sul'!I6*(1-Premissas!$B$23) -> 62411.773 | O24: =+'Novo Horizonte do Sul'!I7*(1-Premissas!$B$23) -> 77836.363 | P24: =D24*(1-Premissas!$B$23) -> 60078.697 | Q24: =E24*(1-Premissas!$B$23) -> 76168.444 | R24: =F24*(1-Premissas!$B$23) -> 79416.522 | S24: =G24*(1-Premissas!$B$23) -> 77811.985 | T24: =H24*(1-Premissas!$B$23) -> 72794.299 | U24: =I24*(1-Premissas!$B$23) -> 90575.348 | V24: =J24*(1-Premissas!$B$23) -> 88188.541 | W24: =K24*(1-Premissas!$B$23) -> 82629.368 | ... BK24: =AY24*(1-Premissas!$B$23) -> 76291.272 | BL24: =AY24*(1-Premissas!$B$23) -> 76291.272 | BM24: =AY24*(1-Premissas!$B$23) -> 76291.272 | BN24: =AY24*(1-Premissas!$B$23) -> 76291.272 | BO24: =AY24*(1-Premissas!$B$23) -> 76291.272 | BP24: =AY24*(1-Premissas!$B$23) -> 76291.272 | BQ24: =AY24*(1-Premissas!$B$23) -> 76291.272 | BR24: =AY24*(1-Premissas!$B$23) -> 76291.272 | BS24: =AY24*(1-Premissas!$B$23) -> 76291.272 | BT24: =AY24*(1-Premissas!$B$23) -> 76291.272 | BU24: =AY24*(1-Premissas!$B$23) -> 76291.272 | BV24: =AY24*(1-Premissas!$B$23) -> 76291.272 | BW24: =AY24*(1-Premissas!$B$23) -> 76291.272 | BX24: =AY24*(1-Premissas!$B$23) -> 76291.272 | BY24: =AY24*(1-Premissas!$B$23) -> 76291.272 | BZ24: =AY24*(1-Premissas!$B$23) -> 76291.272 | CA24: =AY24*(1-Premissas!$B$23) -> 76291.272 | CB24: =AY24*(1-Premissas!$B$23) -> 76291.272 | CC24: =AY24*(1-Premissas!$B$23) -> 76291.272 | CD24: =AY24*(1-Premissas!$B$23) -> 76291.272 | CE24: =AY24*(1-Premissas!$B$23) -> 76291.272 | CF24: =AY24*(1-Premissas!$B$23) -> 76291.272 | CG24: =AY24*(1-Premissas!$B$23) -> 76291.272 | CH24: =AY24*(1-Premissas!$B$23) -> 76291.272 | CI24: =AY24*(1-Premissas!$B$23) -> 76291.272 | CJ24: =AY24*(1-Premissas!$B$23) -> 76291.272 | CK24: =AY24*(1-Premissas!$B$23) -> 76291.272 | CL24: =AY24*(1-Premissas!$B$23) -> 76291.272 | CM24: =AY24*(1-Premissas!$B$23) -> 76291.272 | CN24: =AY24*(1-Premissas!$B$23) -> 76291.272 | CO24: =AY24*(1-Premissas!$B$23) -> 76291.272 | CP24: =AY24*(1-Premissas!$B$23) -> 76291.272 | CQ24: =AY24*(1-Premissas!$B$23) -> 76291.272 | CR24: =AY24*(1-Premissas!$B$23) -> 76291.272 | CS24: =AY24*(1-Premissas!$B$23) -> 76291.272 | CT24: =AY24*(1-Premissas!$B$23) -> 76291.272 | CU24: =AY24*(1-Premissas!$B$23) -> 76291.272 | CV24: =AY24*(1-Premissas!$B$23) -> 76291.272 | CW24: =AY24*(1-Premissas!$B$23) -> 76291.272 | CX24: =AY24*(1-Premissas!$B$23) -> 76291.272 | CY24: =AY24*(1-Premissas!$B$23) -> 76291.272 | CZ24: =AY24*(1-Premissas!$B$23) -> 76291.272 | DA24: =AY24*(1-Premissas!$B$23) -> 76291.272 | DB24: =AY24*(1-Premissas!$B$23) -> 76291.272 | DC24: =AY24*(1-Premissas!$B$23) -> 76291.272 | DD24: =AY24*(1-Premissas!$B$23) -> 76291.272 | DE24: =AY24*(1-Premissas!$B$23) -> 76291.272 | DF24: =AY24*(1-Premissas!$B$23) -> 76291.272 | DG24: =AY24*(1-Premissas!$B$23) -> 76291.272 | DH24: =AY24*(1-Premissas!$B$23) -> 76291.272 | DI24: =AY24*(1-Premissas!$B$23) -> 76291.272 | DJ24: =AY24*(1-Premissas!$B$23) -> 76291.272 | DK24: =AY24*(1-Premissas!$B$23) -> 76291.272 | DL24: =AY24*(1-Premissas!$B$23) -> 76291.272 | DM24: =AY24*(1-Premissas!$B$23) -> 76291.272 | DN24: =AY24*(1-Premissas!$B$23) -> 76291.272 | DO24: =AY24*(1-Premissas!$B$23) -> 76291.272 | DP24: =AY24*(1-Premissas!$B$23) -> 76291.272 | DQ24: =AY24*(1-Premissas!$B$23) -> 76291.272 | DR24: =AY24*(1-Premissas!$B$23) -> 76291.272 | DS24: =AY24*(1-Premissas!$B$23) -> 76291.272
A25: Auto-comp. FP (kWh) | B25: =SUM(D25:BQ25) -> 4279763.9 | C25: =B25/60 -> 71329.399 | D25: =MIN(D24,D22) -> 60380.6 | E25: =MIN(E24,E22) -> 76551.2 | F25: =MIN(F24,F22) -> 79815.6 | G25: =MIN(G24,G22) -> 78203 | H25: =MIN(H24,H22) -> 28215 | I25: =MIN(I24,I22) -> 42210 | J25: =MIN(J24,J22) -> 42210 | K25: =MIN(K24,K22) -> 72539 | ... DS25: =MIN(DS24,DS22) -> 76291.272
A26: Auto-comp. Ponta via FA (kWh) | B26: =SUM(D26:BQ26) -> 121327.66 | C26: =B26/60 -> 2022.1277 | D26: =MIN((D24-D25)*Premissas!$B$8,D23) -> 0 | E26: =MIN((E24-E25)*Premissas!$B$8,E23) -> 0 | F26: =MIN((F24-F25)*Premissas!$B$8,F23) -> 0 | G26: =MIN((G24-G25)*Premissas!$B$8,G23) -> 0 | H26: =MIN((H24-H25)*Premissas!$B$8,H23) -> 3135 | I26: =MIN((I24-I25)*Premissas!$B$8,I23) -> 4690 | J26: =MIN((J24-J25)*Premissas!$B$8,J23) -> 4690 | K26: =MIN((K24-K25)*Premissas!$B$8,K23) -> 6348.1822 | ... DS26: =MIN((DS24-DS25)*Premissas!$B$8,DS23) -> 0
A27: =" "&INDEX(PVSYST_Helexia!$A$5:$A$7,MATCH(Premissas!$B$13,PVSYST_Helexia!$B$5:$B$7,0))&" créditos recebidos (kWh)" -> HCS03 créditos recebidos (kWh) | B27: =SUM(D27:BQ27) -> 4204514.9 | C27: =B27/60 -> 70075.248 | D27: =D6*Premissas!$B$33 -> 91504.62 | E27: =E6*Premissas!$B$33 -> 96316.38 | F27: =F6*Premissas!$B$33 -> 115622.46 | G27: =G6*Premissas!$B$33 -> 108493.38 | H27: =H6*Premissas!$C$33 -> 78229.224 | I27: =I6*Premissas!$C$33 -> 75640.224 | J27: =J6*Premissas!$C$33 -> 71824.038 | K27: =K6*Premissas!$C$33 -> 73747.303 | L27: =L6*Premissas!$C$33 -> 65715.163 | M27: =M6*Premissas!$C$33 -> 75375.369 | N27: =N6*Premissas!$D$33 -> 97520.917 | O27: =O6*Premissas!$D$33 -> 91268.035 | P27: =P6*Premissas!$D$33 -> 82830.652 | Q27: =Q6*Premissas!$D$33 -> 87186.292 | R27: =R6*Premissas!$D$33 -> 104662.3 | S27: =S6*Premissas!$D$33 -> 98209.001 | T27: =T6*Premissas!$E$33 -> 38964.136 | U27: =U6*Premissas!$E$33 -> 37674.616 | V27: =V6*Premissas!$E$33 -> 35773.864 | W27: =W6*Premissas!$E$33 -> 36916.379 | X27: =X6*Premissas!$E$33 -> 32895.655 | Y27: =Y6*Premissas!$E$33 -> 37731.355 | Z27: =Z6*Premissas!$E$33 -> 37648.826 | AA27: =AA6*Premissas!$E$33 -> 35234.844 | AB27: =AB6*Premissas!$F$33 -> 58197.292 | AC27: =AC6*Premissas!$F$33 -> 61257.59 | AD27: =AD6*Premissas!$F$33 -> 73536.331 | AE27: =AE6*Premissas!$F$33 -> 69002.209 | AF27: =AF6*Premissas!$F$33 -> 70912.548 | AG27: =AG6*Premissas!$F$33 -> 68565.694 | AH27: =AH6*Premissas!$G$33 -> 64172.612 | AI27: =AI6*Premissas!$G$33 -> 66222.101 | AJ27: =AJ6*Premissas!$G$33 -> 59009.564 | AK27: =AK6*Premissas!$G$33 -> 67684.039 | AL27: =AL6*Premissas!$G$33 -> 67535.995 | AM27: =AM6*Premissas!$G$33 -> 63205.697 | AN27: =AN6*Premissas!$H$33 -> 57698.669 | AO27: =AO6*Premissas!$H$33 -> 60732.746 | AP27: =AP6*Premissas!$H$33 -> 72906.286 | AQ27: =AQ6*Premissas!$H$33 -> 68411.011 | AR27: =AR6*Premissas!$H$33 -> 70304.983 | AS27: =AS6*Premissas!$H$33 -> 67978.236 | AT27: =AT6*Premissas!$I$33 -> 63619.461 | AU27: =AU6*Premissas!$I$33 -> 65651.284 | AV27: =AV6*Premissas!$I$33 -> 58500.917 | AW27: =AW6*Premissas!$I$33 -> 67100.621 | AX27: =AX6*Premissas!$I$33 -> 66953.853 | AY27: =AY6*Premissas!$I$33 -> 62660.881 | AZ27: =AZ6*Premissas!$J$33 -> 70802.642 | BA27: =BA6*Premissas!$J$33 -> 74525.791 | BB27: =BB6*Premissas!$J$33 -> 89464.069 | BC27: =BC6*Premissas!$J$33 -> 83947.87 | BD27: =BD6*Premissas!$J$33 -> 86271.983 | BE27: =BE6*Premissas!$J$33 -> 83416.807 | BF27: =BF6*Premissas!$K$33 -> 62825.516 | BG27: =BG6*Premissas!$K$33 -> 64831.983 | BH27: =BH6*Premissas!$K$33 -> 57770.85 | BI27: =BI6*Premissas!$K$33 -> 66263.232 | BJ27: =BJ6*Premissas!$K$33 -> 66118.296 | BK27: =BK6*Premissas!$K$33 -> 61878.898 | BL27: =BL6*Premissas!$L$33 -> 8348.4261 | BM27: =BM6*Premissas!$L$33 -> 8787.4271 | BN27: =BN6*Premissas!$L$33 -> 10548.818 | BO27: =BO6*Premissas!$L$33 -> 9898.396 | BP27: =BP6*Premissas!$L$33 -> 10172.435 | BQ27: =BQ6*Premissas!$L$33 -> 9835.7778 | BR27: =BR6*Premissas!$M$33 -> 9584.8221 | BS27: =BS6*Premissas!$M$33 -> 9890.9338 | BT27: =BT6*Premissas!$M$33 -> 8813.6692 | BU27: =BU6*Premissas!$M$33 -> 10109.289 | BV27: =BV6*Premissas!$M$33 -> 10087.177 | BW27: =BW6*Premissas!$M$33 -> 9440.4036 | BX27: =BX6*Premissas!$N$33 -> 8360.9046 | BY27: =BY6*Premissas!$N$33 -> 8800.5618 | BZ27: =BZ6*Premissas!$N$33 -> 10564.585 | CA27: =CA6*Premissas!$N$33 -> 9913.1913 | CB27: =CB6*Premissas!$N$33 -> 10187.64 | CC27: =CC6*Premissas!$N$33 -> 9850.4794 | CD27: =CD6*Premissas!$O$33 -> 9597.911 | CE27: =CE6*Premissas!$O$33 -> 9904.4407 | CF27: =CF6*Premissas!$O$33 -> 8825.705 | CG27: =CG6*Premissas!$O$33 -> 10123.094 | CH27: =CH6*Premissas!$O$33 -> 10100.952 | CI27: =CI6*Premissas!$O$33 -> 9453.2953 | CJ27: =CJ6*Premissas!$P$33 -> 8373.1334 | CK27: =CK6*Premissas!$P$33 -> 8813.4337 | CL27: =CL6*Premissas!$P$33 -> 10580.037 | CM27: =CM6*Premissas!$P$33 -> 9927.6905 | CN27: =CN6*Premissas!$P$33 -> 10202.54 | CO27: =CO6*Premissas!$P$33 -> 9864.8869 | CP27: =CP6*Premissas!$Q$33 -> 9610.7097 | CQ27: =CQ6*Premissas!$Q$33 -> 9917.6482 | CR27: =CR6*Premissas!$Q$33 -> 8837.474 | CS27: =CS6*Premissas!$Q$33 -> 10136.593 | CT27: =CT6*Premissas!$Q$33 -> 10114.421 | CU27: =CU6*Premissas!$Q$33 -> 9465.9012 | CV27: =CV6*Premissas!$R$33 -> 8385.1047 | CW27: =CW6*Premissas!$R$33 -> 8826.0345 | CX27: =CX6*Premissas!$R$33 -> 10595.164 | CY27: =CY6*Premissas!$R$33 -> 9941.8844 | CZ27: =CZ6*Premissas!$R$33 -> 10217.127 | DA27: =DA6*Premissas!$R$33 -> 9878.9911 | DB27: =DB6*Premissas!$S$33 -> 43975.052 | DC27: =DC6*Premissas!$S$33 -> 45379.489 | DD27: =DD6*Premissas!$S$33 -> 40437.011 | DE27: =DE6*Premissas!$S$33 -> 46381.299 | DF27: =DF6*Premissas!$S$33 -> 46279.85 | DG27: =DG6*Premissas!$S$33 -> 43312.462 | DH27: =DH6*Premissas!$T$33 -> 39111.847 | DI27: =DI6*Premissas!$T$33 -> 41168.539 | DJ27: =DJ6*Premissas!$T$33 -> 49420.543 | DK27: =DK6*Premissas!$T$33 -> 46373.358 | DL27: =DL6*Premissas!$T$33 -> 47657.213 | DM27: =DM6*Premissas!$T$33 -> 46079.995 | DN27: =DN6*Premissas!$U$33 -> 43755.176 | DO27: =DO6*Premissas!$U$33 -> 45152.591 | DP27: =DP6*Premissas!$U$33 -> 40234.826 | DQ27: =DQ6*Premissas!$U$33 -> 46149.393 | DR27: =DR6*Premissas!$U$33 -> 46048.451 | DS27: =DS6*Premissas!$U$33 -> 43095.899
A28: BAT créditos → NHS (kWh) | B28: =SUM(D28:BQ28) -> 1292164.5 | C28: =B28/60 -> 21536.074 | D28: =D19 -> 0 | E28: =E19 -> 0 | F28: =F19 -> 0 | G28: =G19 -> 32711.293 | H28: =H19 -> 40823.762 | I28: =I19 -> 41560.462 | J28: =J19 -> 47597.362 | K28: =K19 -> 51288.174 | ... DS28: =DS19 -> 17669.15
A29: Banco início mês COM Helexia (kWh) | B29: =AA29 -> 262411.49 | C29: — | D29: =Premissas!$B$26 -> 148516 | E29: =D31 -> 171720.02 | F29: =E31 -> 0 | G29: =F31 -> 4460.06 | H29: =G31 -> 92928.673 | I29: =H31 -> 256926.76 | J29: =I31 -> 422947.94 | K29: =J31 -> 588791.04 | L29: =K31 -> 721499.23 | ... DS29: =DR31 -> 1104.7843
A30: Bank draw COM Helexia (kWh) | B30: =SUM(D30:BQ30) -> 4016807.2 | C30: =B30/60 -> 66946.786 | D30: =MIN(D29,MAX(D22-D24-D27+D28,0)+IF(Premissas!$B$8=0,0,MAX(D23-D26,0)/Premissas!$B$8)) -> 19986.197 | E30: =MIN(E29,MAX(E22-E24-E27+E28,0)+IF(Premissas!$B$8=0,0,MAX(E23-E26,0)/Premissas!$B$8)) -> 171720.02 | F30: =MIN(F29,MAX(F22-F24-F27+F28,0)+IF(Premissas!$B$8=0,0,MAX(F23-F26,0)/Premissas!$B$8)) -> 0 | G30: =MIN(G29,MAX(G22-G24-G27+G28,0)+IF(Premissas!$B$8=0,0,MAX(G23-G26,0)/Premissas!$B$8)) -> 4460.06 | H30: =MIN(H29,MAX(H22-H24-H27+H28,0)+IF(Premissas!$B$8=0,0,MAX(H23-H26,0)/Premissas!$B$8)) -> 0 | I30: =MIN(I29,MAX(I22-I24-I27+I28,0)+IF(Premissas!$B$8=0,0,MAX(I23-I26,0)/Premissas!$B$8)) -> 0 | J30: =MIN(J29,MAX(J22-J24-J27+J28,0)+IF(Premissas!$B$8=0,0,MAX(J23-J26,0)/Premissas!$B$8)) -> 0 | K30: =MIN(K29,MAX(K22-K24-K27+K28,0)+IF(Premissas!$B$8=0,0,MAX(K23-K26,0)/Premissas!$B$8)) -> 2832.883 | ... DS30: =MIN(DS29,MAX(DS22-DS24-DS27+DS28,0)+IF(Premissas!$B$8=0,0,MAX(DS23-DS26,0)/Premissas!$B$8)) -> 1104.7843
A31: ★ Banco fim mês COM Helexia (kWh) | B31: =AA31 -> 325571.63 | C31: — | D31: =MAX(D29-D30,0)+D28+MAX(D27-MAX(D22-D24,0),0)+MAX(D24-D22,0) -> 171720.02 | E31: =MAX(E29-E30,0)+E28+MAX(E27-MAX(E22-E24,0),0)+MAX(E24-E22,0) -> 0 | F31: =MAX(F29-F30,0)+F28+MAX(F27-MAX(F22-F24,0),0)+MAX(F24-F22,0) -> 4460.06 | G31: =MAX(G29-G30,0)+G28+MAX(G27-MAX(G22-G24,0),0)+MAX(G24-G22,0) -> 92928.673 | H31: =MAX(H29-H30,0)+H28+MAX(H27-MAX(H22-H24,0),0)+MAX(H24-H22,0) -> 256926.76 | I31: =MAX(I29-I30,0)+I28+MAX(I27-MAX(I22-I24,0),0)+MAX(I24-I22,0) -> 422947.94 | J31: =MAX(J29-J30,0)+J28+MAX(J27-MAX(J22-J24,0),0)+MAX(J24-J22,0) -> 588791.04 | K31: =MAX(K29-K30,0)+K28+MAX(K27-MAX(K22-K24,0),0)+MAX(K24-K22,0) -> 721499.23 | ... DS31: =MAX(DS29-DS30,0)+DS28+MAX(DS27-MAX(DS22-DS24,0),0)+MAX(DS24-DS22,0) -> 56648.321
A32: Banco início mês SEM Helexia (kWh) | B32: =AA32 -> 16129.467 | C32: — | D32: =Premissas!$B$26 -> 148516 | E32: =D34 -> 80215.403 | F32: =E34 -> 0 | G32: =F34 -> 0 | H32: =G34 -> 32711.293 | I32: =H34 -> 118480.15 | J32: =I34 -> 208861.12 | K32: =J34 -> 302880.18 | L32: =K34 -> 364673.94 | ... DS32: =DR34 -> 1104.7843
A33: Bank draw SEM Helexia (kWh) — gen+BAT, no CS3 | B33: =SUM(D33:BQ33) -> 2076364.8 | C33: =B33/60 -> 34606.081 | D33: =MIN(D32,MAX(D22-D24-D28,0)+IF(Premissas!$B$8=0,0,MAX(D23-D26-(IF(Premissas!$B$8>0,MAX(D24-D22,0)*Premissas!$B$8,0)),0)/Premissas!$B$8)) -> 68300.597 | E33: =MIN(E32,MAX(E22-E24-E28,0)+IF(Premissas!$B$8=0,0,MAX(E23-E26-(IF(Premissas!$B$8>0,MAX(E24-E22,0)*Premissas!$B$8,0)),0)/Premissas!$B$8)) -> 80215.403 | F33: =MIN(F32,MAX(F22-F24-F28,0)+IF(Premissas!$B$8=0,0,MAX(F23-F26-(IF(Premissas!$B$8>0,MAX(F24-F22,0)*Premissas!$B$8,0)),0)/Premissas!$B$8)) -> 0 | G33: =MIN(G32,MAX(G22-G24-G28,0)+IF(Premissas!$B$8=0,0,MAX(G23-G26-(IF(Premissas!$B$8>0,MAX(G24-G22,0)*Premissas!$B$8,0)),0)/Premissas!$B$8)) -> 0 | H33: =MIN(H32,MAX(H22-H24-H28,0)+IF(Premissas!$B$8=0,0,MAX(H23-H26-(IF(Premissas!$B$8>0,MAX(H24-H22,0)*Premissas!$B$8,0)),0)/Premissas!$B$8)) -> 0 | I33: =MIN(I32,MAX(I22-I24-I28,0)+IF(Premissas!$B$8=0,0,MAX(I23-I26-(IF(Premissas!$B$8>0,MAX(I24-I22,0)*Premissas!$B$8,0)),0)/Premissas!$B$8)) -> 0 | J33: =MIN(J32,MAX(J22-J24-J28,0)+IF(Premissas!$B$8=0,0,MAX(J23-J26-(IF(Premissas!$B$8>0,MAX(J24-J22,0)*Premissas!$B$8,0)),0)/Premissas!$B$8)) -> 0 | K33: =MIN(K32,MAX(K22-K24-K28,0)+IF(Premissas!$B$8=0,0,MAX(K23-K26-(IF(Premissas!$B$8>0,MAX(K24-K22,0)*Premissas!$B$8,0)),0)/Premissas!$B$8)) -> 0 | ... AA33: =MIN(AA32,MAX(AA22-AA24-AA28,0)+IF(Premissas!$B$8=0,0,MAX(AA23-AA26-(IF(Premissas!$B$8>0,MAX(AA24-AA22,0)*Premissas!$B$8,0)),0)/Premissas!$B$8)) -> 0 | AB33: =MIN(AB32,MAX(AB22-AB24-AB28,0)+IF(Premissas!$B$8=0,0,MAX(AB23-AB26-(IF(Premissas!$B$8>0,MAX(AB24-AB22,0),0))*Premissas!$B$8,0)/Premissas!$B$8)) -> 44054.756 | AC33: =MIN(AC32,MAX(AC22-AC24-AC28,0)+IF(Premissas!$B$8=0,0,MAX(AC23-AC26-(IF(Premissas!$B$8>0,MAX(AC24-AC22,0),0))*Premissas!$B$8,0)/Premissas!$B$8)) -> 0 | AD33: =MIN(AD32,MAX(AD22-AD24-AD28,0)+IF(Premissas!$B$8=0,0,MAX(AD23-AD26-(IF(Premissas!$B$8>0,MAX(AD24-AD22,0),0))*Premissas!$B$8,0)/Premissas!$B$8)) -> 0 | AE33: =MIN(AE32,MAX(AE22-AE24-AE28,0)+IF(Premissas!$B$8=0,0,MAX(AE23-AE26-(IF(Premissas!$B$8>0,MAX(AE24-AE22,0),0))*Premissas!$B$8,0)/Premissas!$B$8)) -> 0 | AF33: =MIN(AF32,MAX(AF22-AF24-AF28,0)+IF(Premissas!$B$8=0,0,MAX(AF23-AF26-(IF(Premissas!$B$8>0,MAX(AF24-AF22,0),0))*Premissas!$B$8,0)/Premissas!$B$8)) -> 0 | AG33: =MIN(AG32,MAX(AG22-AG24-AG28,0)+IF(Premissas!$B$8=0,0,MAX(AG23-AG26-(IF(Premissas!$B$8>0,MAX(AG24-AG22,0),0))*Premissas!$B$8,0)/Premissas!$B$8)) -> 0 | AH33: =MIN(AH32,MAX(AH22-AH24-AH28,0)+IF(Premissas!$B$8=0,0,MAX(AH23-AH26-(IF(Premissas!$B$8>0,MAX(AH24-AH22,0),0))*Premissas!$B$8,0)/Premissas!$B$8)) -> 0 | AI33: =MIN(AI32,MAX(AI22-AI24-AI28,0)+IF(Premissas!$B$8=0,0,MAX(AI23-AI26-(IF(Premissas!$B$8>0,MAX(AI24-AI22,0),0))*Premissas!$B$8,0)/Premissas!$B$8)) -> 2003.2302 | ... DS33: =MIN(DS32,MAX(DS22-DS24-DS28,0)+IF(Premissas!$B$8=0,0,MAX(DS23-DS26-(IF(Premissas!$B$8>0,MAX(DS24-DS22,0),0))*Premissas!$B$8,0)/Premissas!$B$8)) -> 1104.7843
A34: Banco fim mês SEM Helexia (kWh) — gen+BAT, no CS3 | B34: =AA34 -> 44054.756 | C34: — | D34: =MAX(D32-D33,0)+D28+MAX(D24-D22,0) -> 80215.403 | E34: =MAX(E32-E33,0)+E28+MAX(E24-E22,0) -> 0 | F34: =MAX(F32-F33,0)+F28+MAX(F24-F22,0) -> 0 | G34: =MAX(G32-G33,0)+G28+MAX(G24-G22,0) -> 32711.293 | H34: =MAX(H32-H33,0)+H28+MAX(H24-H22,0) -> 118480.15 | I34: =MAX(I32-I33,0)+I28+MAX(I24-I22,0) -> 208861.12 | J34: =MAX(J32-J33,0)+J28+MAX(J24-J22,0) -> 302880.18 | K34: =MAX(K32-K33,0)+K28+MAX(K24-K22,0) -> 364673.94 | ... DS34: =MAX(DS32-DS33,0)+DS28+MAX(DS24-DS22,0) -> 17669.15
A35: =" Custo SEM Helexia (R$) — só gen própria, sem "&INDEX(PVSYST_Helexia!$A$5:$A$7,MATCH(Premissas!$B$13,PVSYST_Helexia!$B$5:$B$7,0))&"/BAT/banco" -> Custo SEM Helexia (R$) — só gen própria, sem HCS03/BAT/banco | B35: =SUM(D35:BQ35) -> 3557430.3 | C35: =B35/60 -> 59290.505 | D35: =IF(D34>0,0,MAX(D22-D24-D28-D32,0)*Premissas!$B$5+MAX(D23-D26-(IF(Premissas!$B$8>0,MAX(D24+D28+D32-D22,0)*Premissas!$B$8,0)),0)*Premissas!$B$6) -> 0 | E35: =IF(E34>0,0,MAX(E22-E24-E28-E32,0)*Premissas!$B$5+MAX(E23-E26-(IF(Premissas!$B$8>0,MAX(E24+E28+E32-E22,0)*Premissas!$B$8,0)),0)*Premissas!$B$6) -> 199280.76 | F35: =IF(F34>0,0,MAX(F22-F24-F28-F32,0)*Premissas!$B$5+MAX(F23-F26-(IF(Premissas!$B$8>0,MAX(F24+F28+F32-F22,0)*Premissas!$B$8,0)),0)*Premissas!$B$6) -> 121597.68 | G35: =IF(G34>0,0,MAX(G22-G24-G28-G32,0)*Premissas!$B$5+MAX(G23-G26-(IF(Premissas!$B$8>0,MAX(G24+G28+G32-G22,0)*Premissas!$B$8,0)),0)*Premissas!$B$6) -> 0 | H35: =IF(H34>0,0,MAX(H22-H24-H28-H32,0)*Premissas!$B$5+MAX(H23-H26-(IF(Premissas!$B$8>0,MAX(H24+H28+H32-H22,0)*Premissas!$B$8,0)),0)*Premissas!$B$6) -> 0 | I35: =IF(I34>0,0,MAX(I22-I24-I28-I32,0)*Premissas!$B$5+MAX(I23-I26-(IF(Premissas!$B$8>0,MAX(I24+I28+I32-I22,0)*Premissas!$B$8,0)),0)*Premissas!$B$6) -> 0 | J35: =IF(J34>0,0,MAX(J22-J24-J28-J32,0)*Premissas!$B$5+MAX(J23-J26-(IF(Premissas!$B$8>0,MAX(J24+J28+J32-J22,0)*Premissas!$B$8,0)),0)*Premissas!$B$6) -> 0 | K35: =IF(K34>0,0,MAX(K22-K24-K28-K32,0)*Premissas!$B$5+MAX(K23-K26-(IF(Premissas!$B$8>0,MAX(K24+K28+K32-K22,0)*Premissas!$B$8,0)),0)*Premissas!$B$6) -> 0 | ... AA35: =IF(AA34>0,0,MAX(AA22-AA24-AA28-AA32,0)*Premissas!$B$5+MAX(AA23-AA26-(IF(Premissas!$B$8>0,MAX(AA24+AA28+AA32-AA22,0)*Premissas!$B$8,0)),0)*Premissas!$B$6) -> 0 | AB35: =IF(AB34>0,0,MAX(AB22-AB24-AB28-AB32,0)*Premissas!$B$5+MAX(AB23-AB26-(IF(Premissas!$B$8>0,MAX(AB24+AB26-AB22-AB23,0)*Premissas!$B$8,0)),0)*Premissas!$B$6) -> 43170.391 | AC35: =IF(AC34>0,0,MAX(AC22-AC24-AC28-AC32,0)*Premissas!$B$5+MAX(AC23-AC26-(IF(Premissas!$B$8>0,MAX(AC24+AC26-AC22-AC23,0)*Premissas!$B$8,0)),0)*Premissas!$B$6) -> 256179.57 | AD35: =IF(AD34>0,0,MAX(AD22-AD24-AD28-AD32,0)*Premissas!$B$5+MAX(AD23-AD26-(IF(Premissas!$B$8>0,MAX(AD24+AD26-AD22-AD23,0)*Premissas!$B$8,0)),0)*Premissas!$B$6) -> 130299.1 | AE35: =IF(AE34>0,0,MAX(AE22-AE24-AE28-AE32,0)*Premissas!$B$5+MAX(AE23-AE26-(IF(Premissas!$B$8>0,MAX(AE24+AE26-AE22-AE23,0)*Premissas!$B$8,0)),0)*Premissas!$B$6) -> 0 | AF35: =IF(AF34>0,0,MAX(AF22-AF24-AF28-AF32,0)*Premissas!$B$5+MAX(AF23-AF26-(IF(Premissas!$B$8>0,MAX(AF24+AF26-AF22-AF23,0)*Premissas!$B$8,0)),0)*Premissas!$B$6) -> 0 | AG35: =IF(AG34>0,0,MAX(AG22-AG24-AG28-AG32,0)*Premissas!$B$5+MAX(AG23-AG26-(IF(Premissas!$B$8>0,MAX(AG24+AG26-AG22-AG23,0)*Premissas!$B$8,0)),0)*Premissas!$B$6) -> 0 | AH35: =IF(AH34>0,0,MAX(AH22-AH24-AH28-AH32,0)*Premissas!$B$5+MAX(AH23-AH26-(IF(Premissas!$B$8>0,MAX(AH24+AH26-AH22-AH23,0)*Premissas!$B$8,0)),0)*Premissas!$B$6) -> 0 | AI35: =IF(AI34>0,0,MAX(AI22-AI24-AI28-AI32,0)*Premissas!$B$5+MAX(AI23-AI26-(IF(Premissas!$B$8>0,MAX(AI24+AI26-AI22-AI23,0)*Premissas!$B$8,0)),0)*Premissas!$B$6) -> 0 | ... DS35: =IF(DS34>0,0,MAX(DS22-DS24-DS28-DS32,0)*Premissas!$B$5+MAX(DS23-DS26-(IF(Premissas!$B$8>0,MAX(DS24+DS26-DS22-DS23,0)*Premissas!$B$8,0)),0)*Premissas!$B$6) -> 0
A36: Custo COM Helexia — rede remanescente (R$) | B36: =SUM(D36:BQ36) -> 907317.04 | C36: =B36/60 -> 15121.951 | D36: =IF(D31>0,0,MAX(D22-D24-D27+D28-D29,0)*Premissas!$B$5+MAX(D23-D26-(IF(Premissas!$B$8>0,MAX(D24+D27+D28+D29-D22,0)*Premissas!$B$8,0)),0)*Premissas!$B$6) -> 0 | E36: =IF(E31>0,0,MAX(E22-E24-E27+E28-E29,0)*Premissas!$B$5+MAX(E23-E26-(IF(Premissas!$B$8>0,MAX(E24+E27+E28+E29-E22,0)*Premissas!$B$8,0)),0)*Premissas!$B$6) -> 80529.071 | F36: =IF(F31>0,0,MAX(F22-F24-F27+F28-F29,0)*Premissas!$B$5+MAX(F23-F26-(IF(Premissas!$B$8>0,MAX(F24+F27+F28+F29-F22,0)*Premissas!$B$8,0)),0)*Premissas!$B$6) -> 0 | G36: =IF(G31>0,0,MAX(G22-G24-G27+G28-G29,0)*Premissas!$B$5+MAX(G23-G26-(IF(Premissas!$B$8>0,MAX(G24+G27+G28+G29-G22,0)*Premissas!$B$8,0)),0)*Premissas!$B$6) -> 0 | H36: =IF(H31>0,0,MAX(H22-H24-H27+H28-H29,0)*Premissas!$B$5+MAX(H23-H26-(IF(Premissas!$B$8>0,MAX(H24+H27+H28+H29-H22,0)*Premissas!$B$8,0)),0)*Premissas!$B$6) -> 0 | I36: =IF(I31>0,0,MAX(I22-I24-I27+I28-I29,0)*Premissas!$B$5+MAX(I23-I26-(IF(Premissas!$B$8>0,MAX(I24+I27+I28+I29-I22,0)*Premissas!$B$8,0)),0)*Premissas!$B$6) -> 0 | J36: =IF(J31>0,0,MAX(J22-J24-J27+J28-J29,0)*Premissas!$B$5+MAX(J23-J26-(IF(Premissas!$B$8>0,MAX(J24+J27+J28+J29-J22,0)*Premissas!$B$8,0)),0)*Premissas!$B$6) -> 0 | K36: =IF(K31>0,0,MAX(K22-K24-K27+K28-K29,0)*Premissas!$B$5+MAX(K23-K26-(IF(Premissas!$B$8>0,MAX(K24+K27+K28+K29-K22,0)*Premissas!$B$8,0)),0)*Premissas!$B$6) -> 0 | ... AA36: =IF(AA31>0,0,MAX(AA22-AA24-AA27+AA28-AA29,0)*Premissas!$B$5+MAX(AA23-AA26-(IF(Premissas!$B$8>0,MAX(AA24+AA27+AA28+AA29-AA22,0)*Premissas!$B$8,0)),0)*Premissas!$B$6) -> 0 | AB36: =IF(AB31>0,0,MAX(AB22-AB24-AB27+AB28-AB29,0)*Premissas!$B$5+MAX(AB23-AB26-(IF(Premissas!$B$8>0,MAX(AB24+AB26-AB22-AB23,0)*Premissas!$B$8,0)),0)*Premissas!$B$6) -> 0 | AC36: =IF(AC31>0,0,MAX(AC22-AC24-AC27+AC28-AC29,0)*Premissas!$B$5+MAX(AC23-AC26-(IF(Premissas!$B$8>0,MAX(AC24+AC26-AC22-AC23,0)*Premissas!$B$8,0)),0)*Premissas!$B$6) -> 0 | AD36: =IF(AD31>0,0,MAX(AD22-AD24-AD27+AD28-AD29,0)*Premissas!$B$5+MAX(AD23-AD26-(IF(Premissas!$B$8>0,MAX(AD24+AD26-AD22-AD23,0)*Premissas!$B$8,0)),0)*Premissas!$B$6) -> 72494.149 | AE36: =IF(AE31>0,0,MAX(AE22-AE24-AE27+AE28-AE29,0)*Premissas!$B$5+MAX(AE23-AE26-(IF(Premissas!$B$8>0,MAX(AE24+AE26-AE22-AE23,0)*Premissas!$B$8,0)),0)*Premissas!$B$6) -> 0 | AF36: =IF(AF31>0,0,MAX(AF22-AF24-AF27+AF28-AF29,0)*Premissas!$B$5+MAX(AF23-AF26-(IF(Premissas!$B$8>0,MAX(AF24+AF26-AF22-AF23,0)*Premissas!$B$8,0)),0)*Premissas!$B$6) -> 0 | AG36: =IF(AG31>0,0,MAX(AG22-AG24-AG27+AG28-AG29,0)*Premissas!$B$5+MAX(AG23-AG26-(IF(Premissas!$B$8>0,MAX(AG24+AG26-AG22-AG23,0)*Premissas!$B$8,0)),0)*Premissas!$B$6) -> 0 | AH36: =IF(AH31>0,0,MAX(AH22-AH24-AH27+AH28-AH29,0)*Premissas!$B$5+MAX(AH23-AH26-(IF(Premissas!$B$8>0,MAX(AH24+AH26-AH22-AH23,0)*Premissas!$B$8,0)),0)*Premissas!$B$6) -> 0 | AI36: =IF(AI31>0,0,MAX(AI22-AI24-AI27+AI28-AI29,0)*Premissas!$B$5+MAX(AI23-AI26-(IF(Premissas!$B$8>0,MAX(AI24+AI26-AI22-AI23,0)*Premissas!$B$8,0)),0)*Premissas!$B$6) -> 0 | ... DS36: =IF(DS31>0,0,MAX(DS22-DS24-DS27+DS28-DS29,0)*Premissas!$B$5+MAX(DS23-DS26-(IF(Premissas!$B$8>0,MAX(DS24+DS26-DS22-DS23,0)*Premissas!$B$8,0)),0)*Premissas!$B$6) -> 0
A37: ★ Economia mensal (R$) | B37: =SUM(D37:BQ37) -> 2650113.3 | C37: =B37/60 -> 44168.554 | D37: =MAX(D35-D36,0) -> 0 | E37: =MAX(E35-E36,0) -> 118751.69 | F37: =MAX(F35-F36,0) -> 121597.68 | G37: =MAX(G35-G36,0) -> 0 | H37: =MAX(H35-H36,0) -> 0 | I37: =MAX(I35-I36,0) -> 0 | J37: =MAX(J35-J36,0) -> 0 | K37: =MAX(K35-K36,0) -> 0 | ... DS37: =MAX(DS35-DS36,0) -> 0
A39: AMD — Amandina (A3A)
A40: Consumo FP (kWh) | B40: =SUM(D40:BQ40) -> 7440281 | C40: =B40/60 -> 124004.68 | D40: 182445 | E40: 234799 | F40: 134799 | G40: 18637 | H40: 24383 | I40: 20226 | J40: 17142 | K40: 75823 | L40: 214709 | M40: 177592 | N40: 80410 | O40: 105195 | P40: 187006 | Q40: 240669 | R40: 138169 | S40: 19103 | T40: 24992 | U40: 20731 | V40: 17571 | W40: 75823 | X40: 214709 | Y40: 177592 | Z40: 80410 | AA40: 105195 | AB40: 191681 | AC40: 246686 | AD40: 141623 | AE40: 19580 | AF40: 25617 | AG40: 21250 | AH40: 18010 | AI40: 79662 | AJ40: 225579 | AK40: 186583 | AL40: 84481 | AM40: 110520 | AN40: 196473 | AO40: 252853 | AP40: 145164 | AQ40: 20070 | AR40: 26258 | AS40: 21781 | AT40: 18460 | AU40: 81653 | AV40: 231218 | AW40: 191247 | AX40: 86593 | AY40: 113284 | AZ40: 201385 | BA40: 259174 | BB40: 148793 | BC40: 20572 | BD40: 26914 | BE40: 22326 | BF40: 18922 | BG40: 83694 | BH40: 236999 | BI40: 196028 | BJ40: 88758 | BK40: 116116 | BL40: 206420 | BM40: 265654 | BN40: 152513 | BO40: 21086 | BP40: 27587 | BQ40: 22884 | BR40: 19395 | BS40: 85787 | BT40: 242924 | BU40: 200929 | BV40: 90977 | BW40: 119018 | BX40: 211580 | BY40: 272295 | BZ40: 156326 | CA40: 21613 | CB40: 28277 | CC40: 23456 | CD40: 19879 | CE40: 87931 | CF40: 248997 | CG40: 205952 | CH40: 93251 | CI40: 121994 | CJ40: 216870 | CK40: 279102 | CL40: 160234 | CM40: 22154 | CN40: 28984 | CO40: 24042 | CP40: 20376 | CQ40: 90130 | CR40: 255222 | CS40: 211101 | CT40: 95582 | CU40: 125044 | CV40: 222292 | CW40: 286080 | CX40: 164239 | CY40: 22707 | CZ40: 29708 | DA40: 24643 | DB40: 20886 | DC40: 92383 | DD40: 261602 | DE40: 216379 | DF40: 97972 | DG40: 128170 | DH40: 227849 | DI40: 293232 | DJ40: 168345 | DK40: 23275 | DL40: 30451 | DM40: 25260 | DN40: 21408 | DO40: 94693 | DP40: 268142 | DQ40: 221788 | DR40: 100421 | DS40: 131374
A41: Consumo Ponta (kWh) [via FA] | B41: =SUM(D41:BQ41) -> 826696 | C41: =B41/60 -> 13778.267 | D41: 20272 | E41: 26089 | F41: 14978 | G41: 2071 | H41: 2709 | I41: 2247 | J41: 1905 | K41: 8425 | L41: 23857 | M41: 19732 | N41: 8934 | O41: 11688 | P41: 20778 | Q41: 26741 | R41: 15352 | S41: 2123 | T41: 2777 | U41: 2303 | V41: 1952 | W41: 8425 | X41: 23857 | Y41: 19732 | Z41: 8934 | AA41: 11688 | AB41: 21298 | AC41: 27410 | AD41: 15736 | AE41: 2176 | AF41: 2846 | AG41: 2361 | AH41: 2001 | AI41: 8852 | AJ41: 25065 | AK41: 20731 | AL41: 9386 | AM41: 12280 | AN41: 21831 | AO41: 28095 | AP41: 16130 | AQ41: 2230 | AR41: 2917 | AS41: 2420 | AT41: 2051 | AU41: 9073 | AV41: 25691 | AW41: 21249 | AX41: 9621 | AY41: 12587 | AZ41: 22376 | BA41: 28797 | BB41: 16533 | BC41: 2286 | BD41: 2990 | BE41: 2480 | BF41: 2103 | BG41: 9300 | BH41: 26334 | BI41: 21780 | BJ41: 9861 | BK41: 12901 | BL41: 22936 | BM41: 29517 | BN41: 16946 | BO41: 2343 | BP41: 3065 | BQ41: 2542 | BR41: 2155 | BS41: 9532 | BT41: 26992 | BU41: 22325 | BV41: 10108 | BW41: 13224 | BX41: 23509 | BY41: 30255 | BZ41: 17370 | CA41: 2402 | CB41: 3142 | CC41: 2606 | CD41: 2209 | CE41: 9770 | CF41: 27667 | CG41: 22883 | CH41: 10361 | CI41: 13554 | CJ41: 24097 | CK41: 31012 | CL41: 17804 | CM41: 2462 | CN41: 3220 | CO41: 2671 | CP41: 2264 | CQ41: 10015 | CR41: 28358 | CS41: 23455 | CT41: 10620 | CU41: 13893 | CV41: 24699 | CW41: 31787 | CX41: 18249 | CY41: 2523 | CZ41: 3301 | DA41: 2738 | DB41: 2321 | DC41: 10265 | DD41: 29067 | DE41: 24042 | DF41: 10885 | DG41: 14241 | DH41: 25317 | DI41: 32582 | DJ41: 18705 | DK41: 2586 | DL41: 3383 | DM41: 2806 | DN41: 2379 | DO41: 10522 | DP41: 29794 | DQ41: 24643 | DR41: 11157 | DS41: 14597
A42: Geração própria (kWh) | B42: =SUM(D42:BQ42) -> 4913705.4 | C42: =B42/60 -> 81895.09 | D42: =IF(Premissas!$B$24="Sim",Amandina!$L$8*1000,Amandina!$I$8) -> 57829.52 | E42: =IF(Premissas!$B$24="Sim",Amandina!$L$9*1000,Amandina!$I$9) -> 70669.44 | F42: =IF(Premissas!$B$24="Sim",Amandina!$L$10*1000,Amandina!$I$10) -> 74466.16 | G42: =IF(Premissas!$B$24="Sim",Amandina!$L$11*1000,Amandina!$I$11) -> 75546.72 | H42: =IF(Premissas!$B$24="Sim",Amandina!$L$12*1000,Amandina!$I$12) -> 76725.44 | I42: =IF(Premissas!$B$24="Sim",Amandina!$L$13*1000,Amandina!$I$13) -> 86384.48 | J42: =IF(Premissas!$B$24="Sim",Amandina!$L$14*1000,Amandina!$I$14) -> 85283.12 | K42: =IF(Premissas!$B$24="Sim",Amandina!$L$3*1000*(1-Premissas!$B$23),Amandina!$I$3*(1-Premissas!$B$23)) -> 90950.164 | L42: =IF(Premissas!$B$24="Sim",Amandina!$L$4*1000*(1-Premissas!$B$23),Amandina!$I$4*(1-Premissas!$B$23)) -> 72540.992 | M42: =IF(Premissas!$B$24="Sim",Amandina!$L$5*1000*(1-Premissas!$B$23),Amandina!$I$5*(1-Premissas!$B$23)) -> 82037.272 | N42: =IF(Premissas!$B$24="Sim",Amandina!$L$6*1000*(1-Premissas!$B$23),Amandina!$I$6*(1-Premissas!$B$23)) -> 58672.921 | O42: =IF(Premissas!$B$24="Sim",Amandina!$L$7*1000*(1-Premissas!$B$23),Amandina!$I$7*(1-Premissas!$B$23)) -> 72926.814 | P42: =IF(Premissas!$B$24="Sim",Amandina!$L$8*1000*(1-Premissas!$B$23),Amandina!$I$8*(1-Premissas!$B$23)) -> 57540.372 | Q42: =IF(Premissas!$B$24="Sim",Amandina!$L$9*1000*(1-Premissas!$B$23),Amandina!$I$9*(1-Premissas!$B$23)) -> 70316.093 | R42: =IF(Premissas!$B$24="Sim",Amandina!$L$10*1000*(1-Premissas!$B$23),Amandina!$I$10*(1-Premissas!$B$23)) -> 74093.829 | S42: =IF(Premissas!$B$24="Sim",Amandina!$L$11*1000*(1-Premissas!$B$23),Amandina!$I$11*(1-Premissas!$B$23)) -> 75168.986 | T42: =IF(Premissas!$B$24="Sim",Amandina!$L$12*1000*(1-Premissas!$B$23),Amandina!$I$12*(1-Premissas!$B$23)) -> 76341.813 | U42: =IF(Premissas!$B$24="Sim",Amandina!$L$13*1000*(1-Premissas!$B$23),Amandina!$I$13*(1-Premissas!$B$23)) -> 85952.558 | V42: =IF(Premissas!$B$24="Sim",Amandina!$L$14*1000*(1-Premissas!$B$23),Amandina!$I$14*(1-Premissas!$B$23)) -> 84856.704 | W42: =IF(Premissas!$B$24="Sim",Amandina!$L$3*1000*(1-Premissas!$B$23),Amandina!$I$3*(1-Premissas!$B$23)) -> 90950.164 | X42: =IF(Premissas!$B$24="Sim",Amandina!$L$4*1000*(1-Premissas!$B$23),Amandina!$I$4*(1-Premissas!$B$23)) -> 72540.992 | Y42: =IF(Premissas!$B$24="Sim",Amandina!$L$5*1000*(1-Premissas!$B$23),Amandina!$I$5*(1-Premissas!$B$23)) -> 82037.272 | Z42: =IF(Premissas!$B$24="Sim",Amandina!$L$6*1000*(1-Premissas!$B$23),Amandina!$I$6*(1-Premissas!$B$23)) -> 58672.921 | AA42: =IF(Premissas!$B$24="Sim",Amandina!$L$7*1000*(1-Premissas!$B$23),Amandina!$I$7*(1-Premissas!$B$23)) -> 72926.814 | AB42: =P42*(1-Premissas!$B$23) -> 57252.671 | AC42: =Q42*(1-Premissas!$B$23) -> 69964.512 | AD42: =R42*(1-Premissas!$B$23) -> 73723.36 | AE42: =S42*(1-Premissas!$B$23) -> 74793.141 | AF42: =T42*(1-Premissas!$B$23) -> 75960.104 | AG42: =U42*(1-Premissas!$B$23) -> 85522.795 | AH42: =V42*(1-Premissas!$B$23) -> 84432.421 | AI42: =W42*(1-Premissas!$B$23) -> 90495.413 | ... BK42: =AY42*(1-Premissas!$B$23) -> 71838.372 | BL42: =AY42*(1-Premissas!$B$23) -> 71838.372 | BM42: =AY42*(1-Premissas!$B$23) -> 71838.372 | BN42: =AY42*(1-Premissas!$B$23) -> 71838.372 | BO42: =AY42*(1-Premissas!$B$23) -> 71838.372 | BP42: =AY42*(1-Premissas!$B$23) -> 71838.372 | BQ42: =AY42*(1-Premissas!$B$23) -> 71838.372 | BR42: =AY42*(1-Premissas!$B$23) -> 71838.372 | BS42: =AY42*(1-Premissas!$B$23) -> 71838.372 | BT42: =AY42*(1-Premissas!$B$23) -> 71838.372 | BU42: =AY42*(1-Premissas!$B$23) -> 71838.372 | BV42: =AY42*(1-Premissas!$B$23) -> 71838.372 | BW42: =AY42*(1-Premissas!$B$23) -> 71838.372 | BX42: =AY42*(1-Premissas!$B$23) -> 71838.372 | BY42: =AY42*(1-Premissas!$B$23) -> 71838.372 | BZ42: =AY42*(1-Premissas!$B$23) -> 71838.372 | CA42: =AY42*(1-Premissas!$B$23) -> 71838.372 | CB42: =AY42*(1-Premissas!$B$23) -> 71838.372 | CC42: =AY42*(1-Premissas!$B$23) -> 71838.372 | CD42: =AY42*(1-Premissas!$B$23) -> 71838.372 | CE42: =AY42*(1-Premissas!$B$23) -> 71838.372 | CF42: =AY42*(1-Premissas!$B$23) -> 71838.372 | CG42: =AY42*(1-Premissas!$B$23) -> 71838.372 | CH42: =AY42*(1-Premissas!$B$23) -> 71838.372 | CI42: =AY42*(1-Premissas!$B$23) -> 71838.372 | CJ42: =AY42*(1-Premissas!$B$23) -> 71838.372 | CK42: =AY42*(1-Premissas!$B$23) -> 71838.372 | CL42: =AY42*(1-Premissas!$B$23) -> 71838.372 | CM42: =AY42*(1-Premissas!$B$23) -> 71838.372 | CN42: =AY42*(1-Premissas!$B$23) -> 71838.372 | CO42: =AY42*(1-Premissas!$B$23) -> 71838.372 | CP42: =AY42*(1-Premissas!$B$23) -> 71838.372 | CQ42: =AY42*(1-Premissas!$B$23) -> 71838.372 | CR42: =AY42*(1-Premissas!$B$23) -> 71838.372 | CS42: =AY42*(1-Premissas!$B$23) -> 71838.372 | CT42: =AY42*(1-Premissas!$B$23) -> 71838.372 | CU42: =AY42*(1-Premissas!$B$23) -> 71838.372 | CV42: =AY42*(1-Premissas!$B$23) -> 71838.372 | CW42: =AY42*(1-Premissas!$B$23) -> 71838.372 | CX42: =AY42*(1-Premissas!$B$23) -> 71838.372 | CY42: =AY42*(1-Premissas!$B$23) -> 71838.372 | CZ42: =AY42*(1-Premissas!$B$23) -> 71838.372 | DA42: =AY42*(1-Premissas!$B$23) -> 71838.372 | DB42: =AY42*(1-Premissas!$B$23) -> 71838.372 | DC42: =AY42*(1-Premissas!$B$23) -> 71838.372 | DD42: =AY42*(1-Premissas!$B$23) -> 71838.372 | DE42: =AY42*(1-Premissas!$B$23) -> 71838.372 | DF42: =AY42*(1-Premissas!$B$23) -> 71838.372 | DG42: =AY42*(1-Premissas!$B$23) -> 71838.372 | DH42: =AY42*(1-Premissas!$B$23) -> 71838.372 | DI42: =AY42*(1-Premissas!$B$23) -> 71838.372 | DJ42: =AY42*(1-Premissas!$B$23) -> 71838.372 | DK42: =AY42*(1-Premissas!$B$23) -> 71838.372 | DL42: =AY42*(1-Premissas!$B$23) -> 71838.372 | DM42: =AY42*(1-Premissas!$B$23) -> 71838.372 | DN42: =AY42*(1-Premissas!$B$23) -> 71838.372 | DO42: =AY42*(1-Premissas!$B$23) -> 71838.372 | DP42: =AY42*(1-Premissas!$B$23) -> 71838.372 | DQ42: =AY42*(1-Premissas!$B$23) -> 71838.372 | DR42: =AY42*(1-Premissas!$B$23) -> 71838.372 | DS42: =AY42*(1-Premissas!$B$23) -> 71838.372
A43: Auto-comp. FP (kWh) | B43: =SUM(D43:BQ43) -> 3533333.3 | C43: =B43/60 -> 58888.889 | D43: =MIN(D42,D40) -> 57829.52 | E43: =MIN(E42,E40) -> 70669.44 | F43: =MIN(F42,F40) -> 74466.16 | G43: =MIN(G42,G40) -> 18637 | H43: =MIN(H42,H40) -> 24383 | I43: =MIN(I42,I40) -> 20226 | J43: =MIN(J42,J40) -> 17142 | K43: =MIN(K42,K40) -> 75823 | ... DS43: =MIN(DS42,DS40) -> 71838.372
A44: Auto-comp. Ponta via FA (kWh) | B44: =SUM(D44:BQ44) -> 86928.44 | C44: =B44/60 -> 1448.8073 | D44: =MIN((D42-D43)*Premissas!$B$8,D41) -> 0 | E44: =MIN((E42-E43)*Premissas!$B$8,E41) -> 0 | F44: =MIN((F42-F43)*Premissas!$B$8,F41) -> 0 | G44: =MIN((G42-G43)*Premissas!$B$8,G41) -> 2071 | H44: =MIN((H42-H43)*Premissas!$B$8,H41) -> 2709 | I44: =MIN((I42-I43)*Premissas!$B$8,I41) -> 2247 | J44: =MIN((J42-J43)*Premissas!$B$8,J41) -> 1905 | K44: =MIN((K42-K43)*Premissas!$B$8,K41) -> 8425 | ... DS44: =MIN((DS42-DS43)*Premissas!$B$8,DS41) -> 0
A45: =" "&INDEX(PVSYST_Helexia!$A$5:$A$7,MATCH(Premissas!$B$13,PVSYST_Helexia!$B$5:$B$7,0))&" créditos recebidos (kWh)" -> HCS03 créditos recebidos (kWh) | B45: =SUM(D45:BQ45) -> 2142669.7 | C45: =B45/60 -> 35711.161 | D45: =D6*Premissas!$B$35 -> 0 | E45: =E6*Premissas!$B$35 -> 0 | F45: =F6*Premissas!$B$35 -> 0 | G45: =G6*Premissas!$B$35 -> 0 | H45: =H6*Premissas!$C$35 -> 0 | I45: =I6*Premissas!$C$35 -> 0 | J45: =J6*Premissas!$C$35 -> 0 | K45: =K6*Premissas!$C$35 -> 0 | L45: =L6*Premissas!$C$35 -> 0 | M45: =M6*Premissas!$C$35 -> 0 | N45: =N6*Premissas!$D$35 -> 595.52541 | O45: =O6*Premissas!$D$35 -> 557.34129 | P45: =P6*Premissas!$D$35 -> 505.81721 | Q45: =Q6*Premissas!$D$35 -> 532.41554 | R45: =R6*Premissas!$D$35 -> 639.13527 | S45: =S6*Premissas!$D$35 -> 599.7273 | T45: =T6*Premissas!$E$35 -> 23465.67 | U45: =U6*Premissas!$E$35 -> 22689.073 | V45: =V6*Premissas!$E$35 -> 21544.368 | W45: =W6*Premissas!$E$35 -> 22232.433 | X45: =X6*Premissas!$E$35 -> 19811.002 | Y45: =Y6*Premissas!$E$35 -> 22723.243 | Z45: =Z6*Premissas!$E$35 -> 22673.541 | AA45: =AA6*Premissas!$E$35 -> 21219.75 | AB45: =AB6*Premissas!$F$35 -> 45848.32 | AC45: =AC6*Premissas!$F$35 -> 48259.249 | AD45: =AD6*Premissas!$F$35 -> 57932.545 | AE45: =AE6*Premissas!$F$35 -> 54360.525 | AF45: =AF6*Premissas!$F$35 -> 55865.507 | AG45: =AG6*Premissas!$F$35 -> 54016.635 | AH45: =AH6*Premissas!$G$35 -> 50783.291 | AI45: =AI6*Premissas!$G$35 -> 52405.164 | AJ45: =AJ6*Premissas!$G$35 -> 46697.489 | AK45: =AK6*Premissas!$G$35 -> 53562.075 | AL45: =AL6*Premissas!$G$35 -> 53444.92 | AM45: =AM6*Premissas!$G$35 -> 50018.118 | AN45: =AN6*Premissas!$H$35 -> 45509.153 | AO45: =AO6*Premissas!$H$35 -> 47902.247 | AP45: =AP6*Premissas!$H$35 -> 57503.984 | AQ45: =AQ6*Premissas!$H$35 -> 53958.388 | AR45: =AR6*Premissas!$H$35 -> 55452.237 | AS45: =AS6*Premissas!$H$35 -> 53617.042 | AT45: =AT6*Premissas!$I$35 -> 50392.735 | AU45: =AU6*Premissas!$I$35 -> 52002.134 | AV45: =AV6*Premissas!$I$35 -> 46338.356 | AW45: =AW6*Premissas!$I$35 -> 53150.148 | AX45: =AX6*Premissas!$I$35 -> 53033.894 | AY45: =AY6*Premissas!$I$35 -> 49633.447 | AZ45: =AZ6*Premissas!$J$35 -> 28243.278 | BA45: =BA6*Premissas!$J$35 -> 29728.448 | BB45: =BB6*Premissas!$J$35 -> 35687.349 | BC45: =BC6*Premissas!$J$35 -> 33486.929 | BD45: =BD6*Premissas!$J$35 -> 34414.021 | BE45: =BE6*Premissas!$J$35 -> 33275.088 | BF45: =BF6*Premissas!$K$35 -> 39767.287 | BG45: =BG6*Premissas!$K$35 -> 41037.34 | BH45: =BH6*Premissas!$K$35 -> 36567.785 | BI45: =BI6*Premissas!$K$35 -> 41943.293 | BJ45: =BJ6*Premissas!$K$35 -> 41851.551 | BK45: =BK6*Premissas!$K$35 -> 39168.097 | BL45: =BL6*Premissas!$L$35 -> 41461.802 | BM45: =BM6*Premissas!$L$35 -> 43642.066 | BN45: =BN6*Premissas!$L$35 -> 52389.874 | BO45: =BO6*Premissas!$L$35 -> 49159.605 | BP45: =BP6*Premissas!$L$35 -> 50520.598 | BQ45: =BQ6*Premissas!$L$35 -> 48848.617 | BR45: =BR6*Premissas!$M$35 -> 46157.65 | BS45: =BS6*Premissas!$M$35 -> 47631.793 | BT45: =BT6*Premissas!$M$35 -> 42444.008 | BU45: =BU6*Premissas!$M$35 -> 48683.327 | BV45: =BV6*Premissas!$M$35 -> 48576.842 | BW45: =BW6*Premissas!$M$35 -> 45462.174 | BX45: =BX6*Premissas!$N$35 -> 41204.435 | BY45: =BY6*Premissas!$N$35 -> 43371.165 | BZ45: =BZ6*Premissas!$N$35 -> 52064.673 | CA45: =CA6*Premissas!$N$35 -> 48854.456 | CB45: =CB6*Premissas!$N$35 -> 50207.001 | CC45: =CC6*Premissas!$N$35 -> 48545.398 | CD45: =CD6*Premissas!$O$35 -> 45870.528 | CE45: =CE6*Premissas!$O$35 -> 47335.501 | CF45: =CF6*Premissas!$O$35 -> 42179.986 | CG45: =CG6*Premissas!$O$35 -> 48380.493 | CH45: =CH6*Premissas!$O$35 -> 48274.671 | CI45: =CI6*Premissas!$O$35 -> 45179.378 | CJ45: =CJ6*Premissas!$P$35 -> 40948.524 | CK45: =CK6*Premissas!$P$35 -> 43101.797 | CL45: =CL6*Premissas!$P$35 -> 51741.312 | CM45: =CM6*Premissas!$P$35 -> 48551.032 | CN45: =CN6*Premissas!$P$35 -> 49895.177 | CO45: =CO6*Premissas!$P$35 -> 48243.894 | CP45: =CP6*Premissas!$Q$35 -> 45585.014 | CQ45: =CQ6*Premissas!$Q$35 -> 47040.869 | CR45: =CR6*Premissas!$Q$35 -> 41917.443 | CS45: =CS6*Premissas!$Q$35 -> 48079.356 | CT45: =CT6*Premissas!$Q$35 -> 47974.193 | CU45: =CU6*Premissas!$Q$35 -> 44898.166 | CV45: =CV6*Premissas!$R$35 -> 40694.088 | CW45: =CW6*Premissas!$R$35 -> 42833.982 | CX45: =CX6*Premissas!$R$35 -> 51419.815 | CY45: =CY6*Premissas!$R$35 -> 48249.358 | CZ45: =CZ6*Premissas!$R$35 -> 49585.151 | DA45: =DA6*Premissas!$R$35 -> 47944.128 | DB45: =DB6*Premissas!$S$35 -> 45245.086 | DC45: =DC6*Premissas!$S$35 -> 46690.084 | DD45: =DD6*Premissas!$S$35 -> 41604.864 | DE45: =DE6*Premissas!$S$35 -> 47720.828 | DF45: =DF6*Premissas!$S$35 -> 47616.449 | DG45: =DG6*Premissas!$S$35 -> 44563.36 | DH45: =DH6*Premissas!$T$35 -> 40241.428 | DI45: =DI6*Premissas!$T$35 -> 42357.519 | DJ45: =DJ6*Premissas!$T$35 -> 50847.847 | DK45: =DK6*Premissas!$T$35 -> 47712.657 | DL45: =DL6*Premissas!$T$35 -> 49033.591 | DM45: =DM6*Premissas!$T$35 -> 47410.822 | DN45: =DN6*Premissas!$U$35 -> 45018.86 | DO45: =DO6*Premissas!$U$35 -> 46456.634 | DP45: =DP6*Premissas!$U$35 -> 41396.84 | DQ45: =DQ6*Premissas!$U$35 -> 47482.224 | DR45: =DR6*Premissas!$U$35 -> 47378.367 | DS45: =DS6*Premissas!$U$35 -> 44340.543
A46: BAT créditos → AMD (kWh) | B46: =SUM(D46:BQ46) -> 1292164.5 | C46: =B46/60 -> 21536.074 | D46: =D20 -> 0 | E46: =E20 -> 0 | F46: =F20 -> 0 | G46: =G20 -> 32711.293 | H46: =H20 -> 40823.762 | I46: =I20 -> 41560.462 | J46: =J20 -> 47597.362 | K46: =K20 -> 51288.174 | ... DS46: =DS20 -> 17669.15
A47: Banco início mês COM Helexia (kWh) | B47: =AA47 -> 377435.64 | C47: — | D47: =Premissas!$B$28 -> 991029 | E47: =D49 -> 832865.44 | F47: =E49 -> 625561.26 | G47: =F49 -> 540441.37 | H47: =G49 -> 630062.38 | I47: =H49 -> 723228.58 | J47: =I49 -> 830947.52 | K47: =J49 -> 946686 | L47: =K49 -> 976940.33 | ... DS47: =DR49 -> 197374.91
A48: Bank draw COM Helexia (kWh) | B48: =SUM(D48:BQ48) -> 4159810.8 | C48: =B48/60 -> 69330.179 | D48: =MIN(D47,MAX(D40-D42-D45+D46,0)+IF(Premissas!$B$8=0,0,MAX(D41-D44,0)/Premissas!$B$8)) -> 158163.56 | E48: =MIN(E47,MAX(E40-E42-E45+E46,0)+IF(Premissas!$B$8=0,0,MAX(E41-E44,0)/Premissas!$B$8)) -> 207304.18 | F48: =MIN(F47,MAX(F40-F42-F45+F46,0)+IF(Premissas!$B$8=0,0,MAX(F41-F44,0)/Premissas!$B$8)) -> 85119.894 | G48: =MIN(G47,MAX(G40-G42-G45+G46,0)+IF(Premissas!$B$8=0,0,MAX(G41-G44,0)/Premissas!$B$8)) -> 0 | H48: =MIN(H47,MAX(H40-H42-H45+H46,0)+IF(Premissas!$B$8=0,0,MAX(H41-H44,0)/Premissas!$B$8)) -> 0 | I48: =MIN(I47,MAX(I40-I42-I45+I46,0)+IF(Premissas!$B$8=0,0,MAX(I41-I44,0)/Premissas!$B$8)) -> 0 | J48: =MIN(J47,MAX(J40-J42-J45+J46,0)+IF(Premissas!$B$8=0,0,MAX(J41-J44,0)/Premissas!$B$8)) -> 0 | K48: =MIN(K47,MAX(K40-K42-K45+K46,0)+IF(Premissas!$B$8=0,0,MAX(K41-K44,0)/Premissas!$B$8)) -> 36161.01 | ... DS48: =MIN(DS47,MAX(DS40-DS42-DS45+DS46,0)+IF(Premissas!$B$8=0,0,MAX(DS41-DS44,0)/Premissas!$B$8)) -> 57020.773
A49: ★ Banco fim mês COM Helexia (kWh) | B49: =AA49 -> 347044.77 | C49: — | D49: =MAX(D47-D48,0)+D46+MAX(D45-MAX(D40-D42,0),0)+MAX(D42-D40,0) -> 832865.44 | E49: =MAX(E47-E48,0)+E46+MAX(E45-MAX(E40-E42,0),0)+MAX(E42-E40,0) -> 625561.26 | F49: =MAX(F47-F48,0)+F46+MAX(F45-MAX(F40-F42,0),0)+MAX(F42-F40,0) -> 540441.37 | G49: =MAX(G47-G48,0)+G46+MAX(G45-MAX(G40-G42,0),0)+MAX(G42-G40,0) -> 630062.38 | H49: =MAX(H47-H48,0)+H46+MAX(H45-MAX(H40-H42,0),0)+MAX(H42-H40,0) -> 723228.58 | I49: =MAX(I47-I48,0)+I46+MAX(I45-MAX(I40-I42,0),0)+MAX(I42-I40,0) -> 830947.52 | J49: =MAX(J47-J48,0)+J46+MAX(J45-MAX(J40-J42,0),0)+MAX(J42-J40,0) -> 946686 | K49: =MAX(K47-K48,0)+K46+MAX(K45-MAX(K40-K42,0),0)+MAX(K42-K40,0) -> 976940.33 | ... DS49: =MAX(DS47-DS48,0)+DS46+MAX(DS45-MAX(DS40-DS42,0),0)+MAX(DS42-DS40,0) -> 158023.28
A50: Banco início mês SEM Helexia (kWh) | B50: =AA50 -> 362826.55 | C50: — | D50: =Premissas!$B$28 -> 991029 | E50: =D52 -> 832865.44 | F50: =E52 -> 625561.26 | G50: =F52 -> 540441.37 | H50: =G52 -> 630062.38 | I50: =H52 -> 723228.58 | J50: =I52 -> 830947.52 | K50: =J52 -> 946686 | L50: =K52 -> 1013101.3 | ... DS50: =DR52 -> 1104.7843
A51: Bank draw SEM Helexia (kWh) — gen+BAT, no CS3 | B51: =SUM(D51:BQ51) -> 3415697.6 | C51: =B51/60 -> 56928.293 | D51: =MIN(D50,MAX(D40-D42-D46,0)+IF(Premissas!$B$8=0,0,MAX(D41-D44-(IF(Premissas!$B$8>0,MAX(D42-D40,0)*Premissas!$B$8,0)),0)/Premissas!$B$8)) -> 158163.56 | E51: =MIN(E50,MAX(E40-E42-E46,0)+IF(Premissas!$B$8=0,0,MAX(E41-E44-(IF(Premissas!$B$8>0,MAX(E42-E40,0)*Premissas!$B$8,0)),0)/Premissas!$B$8)) -> 207304.18 | F51: =MIN(F50,MAX(F40-F42-F46,0)+IF(Premissas!$B$8=0,0,MAX(F41-F44-(IF(Premissas!$B$8>0,MAX(F42-F40,0)*Premissas!$B$8,0)),0)/Premissas!$B$8)) -> 85119.894 | G51: =MIN(G50,MAX(G40-G42-G46,0)+IF(Premissas!$B$8=0,0,MAX(G41-G44-(IF(Premissas!$B$8>0,MAX(G42-G40,0)*Premissas!$B$8,0)),0)/Premissas!$B$8)) -> 0 | H51: =MIN(H50,MAX(H40-H42-H46,0)+IF(Premissas!$B$8=0,0,MAX(H41-H44-(IF(Premissas!$B$8>0,MAX(H42-H40,0)*Premissas!$B$8,0)),0)/Premissas!$B$8)) -> 0 | I51: =MIN(I50,MAX(I40-I42-I46,0)+IF(Premissas!$B$8=0,0,MAX(I41-I44-(IF(Premissas!$B$8>0,MAX(I42-I40,0)*Premissas!$B$8,0)),0)/Premissas!$B$8)) -> 0 | J51: =MIN(J50,MAX(J40-J42-J46,0)+IF(Premissas!$B$8=0,0,MAX(J41-J44-(IF(Premissas!$B$8>0,MAX(J42-J40,0)*Premissas!$B$8,0)),0)/Premissas!$B$8)) -> 0 | K51: =MIN(K50,MAX(K40-K42-K46,0)+IF(Premissas!$B$8=0,0,MAX(K41-K44-(IF(Premissas!$B$8>0,MAX(K42-K40,0)*Premissas!$B$8,0)),0)/Premissas!$B$8)) -> 0 | ... AA51: =MIN(AA50,MAX(AA40-AA42-AA46,0)+IF(Premissas!$B$8=0,0,MAX(AA41-AA44-(IF(Premissas!$B$8>0,MAX(AA42-AA40,0)*Premissas!$B$8,0)),0)/Premissas!$B$8)) -> 36747.519 | AB51: =MIN(AB50,MAX(AB40-AB42-AB46,0)+IF(Premissas!$B$8=0,0,MAX(AB41-AB44-(IF(Premissas!$B$8>0,MAX(AB42-AB40,0),0))*Premissas!$B$8,0)/Premissas!$B$8)) -> 169674.34 | AC51: =MIN(AC50,MAX(AC40-AC42-AC46,0)+IF(Premissas!$B$8=0,0,MAX(AC41-AC44-(IF(Premissas!$B$8>0,MAX(AC42-AC40,0),0))*Premissas!$B$8,0)/Premissas!$B$8)) -> 171267.8 | AD51: =MIN(AD50,MAX(AD40-AD42-AD46,0)+IF(Premissas!$B$8=0,0,MAX(AD41-AD44-(IF(Premissas!$B$8>0,MAX(AD42-AD40,0),0))*Premissas!$B$8,0)/Premissas!$B$8)) -> 0 | AE51: =MIN(AE50,MAX(AE40-AE42-AE46,0)+IF(Premissas!$B$8=0,0,MAX(AE41-AE44-(IF(Premissas!$B$8>0,MAX(AE42-AE40,0),0))*Premissas!$B$8,0)/Premissas!$B$8)) -> 0 | AF51: =MIN(AF50,MAX(AF40-AF42-AF46,0)+IF(Premissas!$B$8=0,0,MAX(AF41-AF44-(IF(Premissas!$B$8>0,MAX(AF42-AF40,0),0))*Premissas!$B$8,0)/Premissas!$B$8)) -> 0 | AG51: =MIN(AG50,MAX(AG40-AG42-AG46,0)+IF(Premissas!$B$8=0,0,MAX(AG41-AG44-(IF(Premissas!$B$8>0,MAX(AG42-AG40,0),0))*Premissas!$B$8,0)/Premissas!$B$8)) -> 0 | AH51: =MIN(AH50,MAX(AH40-AH42-AH46,0)+IF(Premissas!$B$8=0,0,MAX(AH41-AH44-(IF(Premissas!$B$8>0,MAX(AH42-AH40,0),0))*Premissas!$B$8,0)/Premissas!$B$8)) -> 0 | AI51: =MIN(AI50,MAX(AI40-AI42-AI46,0)+IF(Premissas!$B$8=0,0,MAX(AI41-AI44-(IF(Premissas!$B$8>0,MAX(AI42-AI40,0),0))*Premissas!$B$8,0)/Premissas!$B$8)) -> 0 | ... DS51: =MIN(DS50,MAX(DS40-DS42-DS46,0)+IF(Premissas!$B$8=0,0,MAX(DS41-DS44-(IF(Premissas!$B$8>0,MAX(DS42-DS40,0),0))*Premissas!$B$8,0)/Premissas!$B$8)) -> 1104.7843
A52: Banco fim mês SEM Helexia (kWh) — gen+BAT, no CS3 | B52: =AA52 -> 340942.13 | C52: — | D52: =MAX(D50-D51,0)+D46+MAX(D42-D40,0) -> 832865.44 | E52: =MAX(E50-E51,0)+E46+MAX(E42-E40,0) -> 625561.26 | F52: =MAX(F50-F51,0)+F46+MAX(F42-F40,0) -> 540441.37 | G52: =MAX(G50-G51,0)+G46+MAX(G42-G40,0) -> 630062.38 | H52: =MAX(H50-H51,0)+H46+MAX(H42-H40,0) -> 723228.58 | I52: =MAX(I50-I51,0)+I46+MAX(I42-I40,0) -> 830947.52 | J52: =MAX(J50-J51,0)+J46+MAX(J42-J40,0) -> 946686 | K52: =MAX(K50-K51,0)+K46+MAX(K42-K40,0) -> 1013101.3 | ... DS52: =MAX(DS50-DS51,0)+DS46+MAX(DS42-DS40,0) -> 17669.15
A53: =" Custo SEM Helexia (R$) — só gen própria, sem "&INDEX(PVSYST_Helexia!$A$5:$A$7,MATCH(Premissas!$B$13,PVSYST_Helexia!$B$5:$B$7,0))&"/BAT/banco" -> Custo SEM Helexia (R$) — só gen própria, sem HCS03/BAT/banco | B53: =SUM(D53:BQ53) -> 1337868.9 | C53: =B53/60 -> 22297.815 | D53: =IF(D52>0,0,MAX(D40-D42-D46-D50,0)*Premissas!$B$5+MAX(D41-D44-(IF(Premissas!$B$8>0,MAX(D42+D46+D50-D40,0)*Premissas!$B$8,0)),0)*Premissas!$B$6) -> 0 | E53: =IF(E52>0,0,MAX(E40-E42-E46-E50,0)*Premissas!$B$5+MAX(E41-E44-(IF(Premissas!$B$8>0,MAX(E42+E46+E50-E40,0)*Premissas!$B$8,0)),0)*Premissas!$B$6) -> 0 | F53: =IF(F52>0,0,MAX(F40-F42-F46-F50,0)*Premissas!$B$5+MAX(F41-F44-(IF(Premissas!$B$8>0,MAX(F42+F46+F50-F40,0)*Premissas!$B$8,0)),0)*Premissas!$B$6) -> 0 | G53: =IF(G52>0,0,MAX(G40-G42-G46-G50,0)*Premissas!$B$5+MAX(G41-G44-(IF(Premissas!$B$8>0,MAX(G42+G46+G50-G40,0)*Premissas!$B$8,0)),0)*Premissas!$B$6) -> 0 | H53: =IF(H52>0,0,MAX(H40-H42-H46-H50,0)*Premissas!$B$5+MAX(H41-H44-(IF(Premissas!$B$8>0,MAX(H42+H46+H50-H40,0)*Premissas!$B$8,0)),0)*Premissas!$B$6) -> 0 | I53: =IF(I52>0,0,MAX(I40-I42-I46-I50,0)*Premissas!$B$5+MAX(I41-I44-(IF(Premissas!$B$8>0,MAX(I42+I46+I50-I40,0)*Premissas!$B$8,0)),0)*Premissas!$B$6) -> 0 | J53: =IF(J52>0,0,MAX(J40-J42-J46-J50,0)*Premissas!$B$5+MAX(J41-J44-(IF(Premissas!$B$8>0,MAX(J42+J46+J50-J40,0)*Premissas!$B$8,0)),0)*Premissas!$B$6) -> 0 | K53: =IF(K52>0,0,MAX(K40-K42-K46-K50,0)*Premissas!$B$5+MAX(K41-K44-(IF(Premissas!$B$8>0,MAX(K42+K46+K50-K40,0)*Premissas!$B$8,0)),0)*Premissas!$B$6) -> 0 | ... AA53: =IF(AA52>0,0,MAX(AA40-AA42-AA46-AA50,0)*Premissas!$B$5+MAX(AA41-AA44-(IF(Premissas!$B$8>0,MAX(AA42+AA46+AA50-AA40,0)*Premissas!$B$8,0)),0)*Premissas!$B$6) -> 0 | AB53: =IF(AB52>0,0,MAX(AB40-AB42-AB46-AB50,0)*Premissas!$B$5+MAX(AB41-AB44-(IF(Premissas!$B$8>0,MAX(AB42+AB44-AB40-AB41,0)*Premissas!$B$8,0)),0)*Premissas!$B$6) -> 0 | AC53: =IF(AC52>0,0,MAX(AC40-AC42-AC46-AC50,0)*Premissas!$B$5+MAX(AC41-AC44-(IF(Premissas!$B$8>0,MAX(AC42+AC44-AC40-AC41,0)*Premissas!$B$8,0)),0)*Premissas!$B$6) -> 84344.129 | AD53: =IF(AD52>0,0,MAX(AD40-AD42-AD46-AD50,0)*Premissas!$B$5+MAX(AD41-AD44-(IF(Premissas!$B$8>0,MAX(AD42+AD44-AD40-AD41,0)*Premissas!$B$8,0)),0)*Premissas!$B$6) -> 82520.561 | AE53: =IF(AE52>0,0,MAX(AE40-AE42-AE46-AE50,0)*Premissas!$B$5+MAX(AE41-AE44-(IF(Premissas!$B$8>0,MAX(AE42+AE44-AE40-AE41,0)*Premissas!$B$8,0)),0)*Premissas!$B$6) -> 0 | AF53: =IF(AF52>0,0,MAX(AF40-AF42-AF46-AF50,0)*Premissas!$B$5+MAX(AF41-AF44-(IF(Premissas!$B$8>0,MAX(AF42+AF44-AF40-AF41,0)*Premissas!$B$8,0)),0)*Premissas!$B$6) -> 0 | AG53: =IF(AG52>0,0,MAX(AG40-AG42-AG46-AG50,0)*Premissas!$B$5+MAX(AG41-AG44-(IF(Premissas!$B$8>0,MAX(AG42+AG44-AG40-AG41,0)*Premissas!$B$8,0)),0)*Premissas!$B$6) -> 0 | AH53: =IF(AH52>0,0,MAX(AH40-AH42-AH46-AH50,0)*Premissas!$B$5+MAX(AH41-AH44-(IF(Premissas!$B$8>0,MAX(AH42+AH44-AH40-AH41,0)*Premissas!$B$8,0)),0)*Premissas!$B$6) -> 0 | AI53: =IF(AI52>0,0,MAX(AI40-AI42-AI46-AI50,0)*Premissas!$B$5+MAX(AI41-AI44-(IF(Premissas!$B$8>0,MAX(AI42+AI44-AI40-AI41,0)*Premissas!$B$8,0)),0)*Premissas!$B$6) -> 0 | ... DS53: =IF(DS52>0,0,MAX(DS40-DS42-DS46-DS50,0)*Premissas!$B$5+MAX(DS41-DS44-(IF(Premissas!$B$8>0,MAX(DS42+DS44-DS40-DS41,0)*Premissas!$B$8,0)),0)*Premissas!$B$6) -> 0
A54: Custo COM Helexia — rede remanescente (R$) | B54: =SUM(D54:BQ54) -> 0 | C54: =B54/60 -> 0 | D54: =IF(D49>0,0,MAX(D40-D42-D45+D46-D47,0)*Premissas!$B$5+MAX(D41-D44-(IF(Premissas!$B$8>0,MAX(D42+D45+D46+D47-D40,0)*Premissas!$B$8,0)),0)*Premissas!$B$6) -> 0 | E54: =IF(E49>0,0,MAX(E40-E42-E45+E46-E47,0)*Premissas!$B$5+MAX(E41-E44-(IF(Premissas!$B$8>0,MAX(E42+E45+E46+E47-E40,0)*Premissas!$B$8,0)),0)*Premissas!$B$6) -> 0 | F54: =IF(F49>0,0,MAX(F40-F42-F45+F46-F47,0)*Premissas!$B$5+MAX(F41-F44-(IF(Premissas!$B$8>0,MAX(F42+F45+F46+F47-F40,0)*Premissas!$B$8,0)),0)*Premissas!$B$6) -> 0 | G54: =IF(G49>0,0,MAX(G40-G42-G45+G46-G47,0)*Premissas!$B$5+MAX(G41-G44-(IF(Premissas!$B$8>0,MAX(G42+G45+G46+G47-G40,0)*Premissas!$B$8,0)),0)*Premissas!$B$6) -> 0 | H54: =IF(H49>0,0,MAX(H40-H42-H45+H46-H47,0)*Premissas!$B$5+MAX(H41-H44-(IF(Premissas!$B$8>0,MAX(H42+H45+H46+H47-H40,0)*Premissas!$B$8,0)),0)*Premissas!$B$6) -> 0 | I54: =IF(I49>0,0,MAX(I40-I42-I45+I46-I47,0)*Premissas!$B$5+MAX(I41-I44-(IF(Premissas!$B$8>0,MAX(I42+I45+I46+I47-I40,0)*Premissas!$B$8,0)),0)*Premissas!$B$6) -> 0 | J54: =IF(J49>0,0,MAX(J40-J42-J45+J46-J47,0)*Premissas!$B$5+MAX(J41-J44-(IF(Premissas!$B$8>0,MAX(J42+J45+J46+J47-J40,0)*Premissas!$B$8,0)),0)*Premissas!$B$6) -> 0 | K54: =IF(K49>0,0,MAX(K40-K42-K45+K46-K47,0)*Premissas!$B$5+MAX(K41-K44-(IF(Premissas!$B$8>0,MAX(K42+K45+K46+K47-K40,0)*Premissas!$B$8,0)),0)*Premissas!$B$6) -> 0 | ... AA54: =IF(AA49>0,0,MAX(AA40-AA42-AA45+AA46-AA47,0)*Premissas!$B$5+MAX(AA41-AA44-(IF(Premissas!$B$8>0,MAX(AA42+AA45+AA46+AA47-AA40,0)*Premissas!$B$8,0)),0)*Premissas!$B$6) -> 0 | AB54: =IF(AB49>0,0,MAX(AB40-AB42-AB45+AB46-AB47,0)*Premissas!$B$5+MAX(AB41-AB44-(IF(Premissas!$B$8>0,MAX(AB42+AB44-AB40-AB41,0)*Premissas!$B$8,0)),0)*Premissas!$B$6) -> 0 | AC54: =IF(AC49>0,0,MAX(AC40-AC42-AC45+AC46-AC47,0)*Premissas!$B$5+MAX(AC41-AC44-(IF(Premissas!$B$8>0,MAX(AC42+AC44-AC40-AC41,0)*Premissas!$B$8,0)),0)*Premissas!$B$6) -> 0 | AD54: =IF(AD49>0,0,MAX(AD40-AD42-AD45+AD46-AD47,0)*Premissas!$B$5+MAX(AD41-AD44-(IF(Premissas!$B$8>0,MAX(AD42+AD44-AD40-AD41,0)*Premissas!$B$8,0)),0)*Premissas!$B$6) -> 0 | AE54: =IF(AE49>0,0,MAX(AE40-AE42-AE45+AE46-AE47,0)*Premissas!$B$5+MAX(AE41-AE44-(IF(Premissas!$B$8>0,MAX(AE42+AE44-AE40-AE41,0)*Premissas!$B$8,0)),0)*Premissas!$B$6) -> 0 | AF54: =IF(AF49>0,0,MAX(AF40-AF42-AF45+AF46-AF47,0)*Premissas!$B$5+MAX(AF41-AF44-(IF(Premissas!$B$8>0,MAX(AF42+AF44-AF40-AF41,0)*Premissas!$B$8,0)),0)*Premissas!$B$6) -> 0 | AG54: =IF(AG49>0,0,MAX(AG40-AG42-AG45+AG46-AG47,0)*Premissas!$B$5+MAX(AG41-AG44-(IF(Premissas!$B$8>0,MAX(AG42+AG44-AG40-AG41,0)*Premissas!$B$8,0)),0)*Premissas!$B$6) -> 0 | AH54: =IF(AH49>0,0,MAX(AH40-AH42-AH45+AH46-AH47,0)*Premissas!$B$5+MAX(AH41-AH44-(IF(Premissas!$B$8>0,MAX(AH42+AH44-AH40-AH41,0)*Premissas!$B$8,0)),0)*Premissas!$B$6) -> 0 | AI54: =IF(AI49>0,0,MAX(AI40-AI42-AI45+AI46-AI47,0)*Premissas!$B$5+MAX(AI41-AI44-(IF(Premissas!$B$8>0,MAX(AI42+AI44-AI40-AI41,0)*Premissas!$B$8,0)),0)*Premissas!$B$6) -> 0 | ... DS54: =IF(DS49>0,0,MAX(DS40-DS42-DS45+DS46-DS47,0)*Premissas!$B$5+MAX(DS41-DS44-(IF(Premissas!$B$8>0,MAX(DS42+DS44-DS40-DS41,0)*Premissas!$B$8,0)),0)*Premissas!$B$6) -> 0
A55: ★ Economia mensal (R$) | B55: =SUM(D55:BQ55) -> 1337868.9 | C55: =B55/60 -> 22297.815 | D55: =MAX(D53-D54,0) -> 0 | E55: =MAX(E53-E54,0) -> 0 | F55: =MAX(F53-F54,0) -> 0 | G55: =MAX(G53-G54,0) -> 0 | H55: =MAX(H53-H54,0) -> 0 | I55: =MAX(I53-I54,0) -> 0 | J55: =MAX(J53-J54,0) -> 0 | K55: =MAX(K53-K54,0) -> 0 | ... DS55: =MAX(DS53-DS54,0) -> 0
A57: AREC (B3)
A58: Consumo FP (kWh) | B58: =SUM(D58:BQ58) -> 319448 | C58: =B58/60 -> 5324.1333 | D58: 3657 | E58: 3451 | F58: 3409 | G58: 4205 | H58: 5428 | I58: 6374 | J58: 6073 | K58: 4224 | L58: 4441 | M58: 5202 | N58: 4526 | O58: 4182 | P58: 3749 | Q58: 3537 | R58: 3494 | S58: 4310 | T58: 5564 | U58: 6533 | V58: 6225 | W58: 4224 | X58: 4441 | Y58: 5202 | Z58: 4526 | AA58: 4182 | AB58: 3842 | AC58: 3626 | AD58: 3582 | AE58: 4418 | AF58: 5703 | AG58: 6697 | AH58: 6380 | AI58: 4438 | AJ58: 4666 | AK58: 5465 | AL58: 4755 | AM58: 4394 | AN58: 3938 | AO58: 3716 | AP58: 3671 | AQ58: 4528 | AR58: 5845 | AS58: 6864 | AT58: 6540 | AU58: 4549 | AV58: 4782 | AW58: 5602 | AX58: 4874 | AY58: 4504 | AZ58: 4037 | BA58: 3809 | BB58: 3763 | BC58: 4642 | BD58: 5991 | BE58: 7036 | BF58: 6703 | BG58: 4663 | BH58: 4902 | BI58: 5742 | BJ58: 4996 | BK58: 4616 | BL58: 4138 | BM58: 3904 | BN58: 3857 | BO58: 4758 | BP58: 6141 | BQ58: 7212 | BR58: 6871 | BS58: 4779 | BT58: 5025 | BU58: 5886 | BV58: 5121 | BW58: 4732 | BX58: 4241 | BY58: 4002 | BZ58: 3953 | CA58: 4877 | CB58: 6295 | CC58: 7392 | CD58: 7043 | CE58: 4899 | CF58: 5150 | CG58: 6033 | CH58: 5249 | CI58: 4850 | CJ58: 4347 | CK58: 4102 | CL58: 4052 | CM58: 4998 | CN58: 6452 | CO58: 7577 | CP58: 7219 | CQ58: 5021 | CR58: 5279 | CS58: 6184 | CT58: 5380 | CU58: 4971 | CV58: 4456 | CW58: 4205 | CX58: 4154 | CY58: 5123 | CZ58: 6613 | DA58: 7766 | DB58: 7399 | DC58: 5147 | DD58: 5411 | DE58: 6338 | DF58: 5514 | DG58: 5095 | DH58: 4567 | DI58: 4310 | DJ58: 4257 | DK58: 5251 | DL58: 6779 | DM58: 7960 | DN58: 7584 | DO58: 5275 | DP58: 5546 | DQ58: 6497 | DR58: 5652 | DS58: 5223
A59: =" "&INDEX(PVSYST_Helexia!$A$5:$A$7,MATCH(Premissas!$B$13,PVSYST_Helexia!$B$5:$B$7,0))&" créditos recebidos (kWh)" -> HCS03 créditos recebidos (kWh) | B59: =SUM(D59:BQ59) -> 308535.05 | C59: =B59/60 -> 5142.2508 | D59: =D6*Premissas!$B$36 -> 3347.73 | E59: =E6*Premissas!$B$36 -> 3523.77 | F59: =F6*Premissas!$B$36 -> 4230.09 | G59: =G6*Premissas!$B$36 -> 3969.27 | H59: =H6*Premissas!$C$36 -> 8037.456 | I59: =I6*Premissas!$C$36 -> 7771.456 | J59: =J6*Premissas!$C$36 -> 7379.372 | K59: =K6*Premissas!$C$36 -> 7576.9728 | L59: =L6*Premissas!$C$36 -> 6751.7317 | M59: =M6*Premissas!$C$36 -> 7744.2442 | N59: =N6*Premissas!$D$36 -> 4517.2781 | O59: =O6*Premissas!$D$36 -> 4227.6376 | P59: =P6*Premissas!$D$36 -> 3836.8086 | Q59: =Q6*Premissas!$D$36 -> 4038.5667 | R59: =R6*Premissas!$D$36 -> 4848.0748 | S59: =S6*Premissas!$D$36 -> 4549.1509 | T59: =T6*Premissas!$E$36 -> 10131.878 | U59: =U6*Premissas!$E$36 -> 9796.563 | V59: =V6*Premissas!$E$36 -> 9302.3087 | W59: =W6*Premissas!$E$36 -> 9599.3978 | X59: =X6*Premissas!$E$36 -> 8553.8857 | Y59: =Y6*Premissas!$E$36 -> 9811.3169 | Z59: =Z6*Premissas!$E$36 -> 9789.8567 | AA59: =AA6*Premissas!$E$36 -> 9162.1471 | AB59: =AB6*Premissas!$F$36 -> 1914.9499 | AC59: =AC6*Premissas!$F$36 -> 2015.6473 | AD59: =AD6*Premissas!$F$36 -> 2419.6726 | AE59: =AE6*Premissas!$F$36 -> 2270.4798 | AF59: =AF6*Premissas!$F$36 -> 2333.3384 | AG59: =AG6*Premissas!$F$36 -> 2256.1165 | AH59: =AH6*Premissas!$G$36 -> 2348.2809 | AI59: =AI6*Premissas!$G$36 -> 2423.2783 | AJ59: =AJ6*Premissas!$G$36 -> 2159.3485 | AK59: =AK6*Premissas!$G$36 -> 2476.7752 | AL59: =AL6*Premissas!$G$36 -> 2471.3578 | AM59: =AM6*Premissas!$G$36 -> 2312.8984 | AN59: =AN6*Premissas!$H$36 -> 1954.2309 | AO59: =AO6*Premissas!$H$36 -> 2056.994 | AP59: =AP6*Premissas!$H$36 -> 2469.3069 | AQ59: =AQ6*Premissas!$H$36 -> 2317.0537 | AR59: =AR6*Premissas!$H$36 -> 2381.2018 | AS59: =AS6*Premissas!$H$36 -> 2302.3958 | AT59: =AT6*Premissas!$I$36 -> 2377.5314 | AU59: =AU6*Premissas!$I$36 -> 2453.4629 | AV59: =AV6*Premissas!$I$36 -> 2186.2456 | AW59: =AW6*Premissas!$I$36 -> 2507.6263 | AX59: =AX6*Premissas!$I$36 -> 2502.1414 | AY59: =AY6*Premissas!$I$36 -> 2341.7082 | AZ59: =AZ6*Premissas!$J$36 -> 3694.4736 | BA59: =BA6*Premissas!$J$36 -> 3888.7471 | BB59: =BB6*Premissas!$J$36 -> 4668.2247 | BC59: =BC6*Premissas!$J$36 -> 4380.3901 | BD59: =BD6*Premissas!$J$36 -> 4501.662 | BE59: =BE6*Premissas!$J$36 -> 4352.6793 | BF59: =BF6*Premissas!$K$36 -> 4377.8005 | BG59: =BG6*Premissas!$K$36 -> 4517.6149 | BH59: =BH6*Premissas!$K$36 -> 4025.5818 | BI59: =BI6*Premissas!$K$36 -> 4617.3471 | BJ59: =BJ6*Premissas!$K$36 -> 4607.2476 | BK59: =BK6*Premissas!$K$36 -> 4311.8384 | BL59: =BL6*Premissas!$L$36 -> 5630.5952 | BM59: =BM6*Premissas!$L$36 -> 5926.6794 | BN59: =BN6*Premissas!$L$36 -> 7114.6491 | BO59: =BO6*Premissas!$L$36 -> 6675.9722 | BP59: =BP6*Premissas!$L$36 -> 6860.7978 | BQ59: =BQ6*Premissas!$L$36 -> 6633.7393 | BR59: =BR6*Premissas!$M$36 -> 6317.4096 | BS59: =BS6*Premissas!$M$36 -> 6519.1695 | BT59: =BT6*Premissas!$M$36 -> 5809.1384 | BU59: =BU6*Premissas!$M$36 -> 6663.0886 | BV59: =BV6*Premissas!$M$36 -> 6648.5145 | BW59: =BW6*Premissas!$M$36 -> 6222.2226 | BX59: =BX6*Premissas!$N$36 -> 5606.6978 | BY59: =BY6*Premissas!$N$36 -> 5901.5253 | BZ59: =BZ6*Premissas!$N$36 -> 7084.4531 | CA59: =CA6*Premissas!$N$36 -> 6647.638 | CB59: =CB6*Premissas!$N$36 -> 6831.6792 | CC59: =CC6*Premissas!$N$36 -> 6605.5844 | CD59: =CD6*Premissas!$O$36 -> 6290.018 | CE59: =CE6*Premissas!$O$36 -> 6490.9032 | CF59: =CF6*Premissas!$O$36 -> 5783.9507 | CG59: =CG6*Premissas!$O$36 -> 6634.1982 | CH59: =CH6*Premissas!$O$36 -> 6619.6873 | CI59: =CI6*Premissas!$O$36 -> 6195.2437 | CJ59: =CJ6*Premissas!$P$36 -> 5582.7741 | CK59: =CK6*Premissas!$P$36 -> 5876.3436 | CL59: =CL6*Premissas!$P$36 -> 7054.2239 | CM59: =CM6*Premissas!$P$36 -> 6619.2727 | CN59: =CN6*Premissas!$P$36 -> 6802.5285 | CO59: =CO6*Premissas!$P$36 -> 6577.3985 | CP59: =CP6*Premissas!$Q$36 -> 6262.6152 | CQ59: =CQ6*Premissas!$Q$36 -> 6462.6252 | CR59: =CR6*Premissas!$Q$36 -> 5758.7526 | CS59: =CS6*Premissas!$Q$36 -> 6605.296 | CT59: =CT6*Premissas!$Q$36 -> 6590.8483 | CU59: =CU6*Premissas!$Q$36 -> 6168.2538 | CV59: =CV6*Premissas!$R$36 -> 5558.8232 | CW59: =CW6*Premissas!$R$36 -> 5851.1333 | CX59: =CX6*Premissas!$R$36 -> 7023.9603 | CY59: =CY6*Premissas!$R$36 -> 6590.8751 | CZ59: =CZ6*Premissas!$R$36 -> 6773.3447 | DA59: =DA6*Premissas!$R$36 -> 6549.1806 | DB59: =DB6*Premissas!$S$36 -> 0 | DC59: =DC6*Premissas!$S$36 -> 0 | DD59: =DD6*Premissas!$S$36 -> 0 | DE59: =DE6*Premissas!$S$36 -> 0 | DF59: =DF6*Premissas!$S$36 -> 0 | DG59: =DG6*Premissas!$S$36 -> 0 | DH59: =DH6*Premissas!$T$36 -> 0 | DI59: =DI6*Premissas!$T$36 -> 0 | DJ59: =DJ6*Premissas!$T$36 -> 0 | DK59: =DK6*Premissas!$T$36 -> 0 | DL59: =DL6*Premissas!$T$36 -> 0 | DM59: =DM6*Premissas!$T$36 -> 0 | DN59: =DN6*Premissas!$U$36 -> 0 | DO59: =DO6*Premissas!$U$36 -> 0 | DP59: =DP6*Premissas!$U$36 -> 0 | DQ59: =DQ6*Premissas!$U$36 -> 0 | DR59: =DR6*Premissas!$U$36 -> 0 | DS59: =DS6*Premissas!$U$36 -> 0
A60: Banco início mês COM Helexia (kWh) | B60: =AA60 -> 46667.086 | C60: — | D60: =0 -> 0 | E60: =D62 -> 0 | F60: =E62 -> 72.77 | G60: =F62 -> 893.86 | H60: =G62 -> 658.13 | I60: =H62 -> 3267.586 | J60: =I62 -> 4665.042 | K60: =J62 -> 5971.414 | L60: =K62 -> 9324.3868 | ... DS60: =DR62 -> 0
A61: Bank draw COM Helexia (kWh) | B61: =SUM(D61:BQ61) -> 53454.918 | C61: =B61/60 -> 890.91529 | D61: =MIN(D60,MAX(D58-D59,0)) -> 0 | E61: =MIN(E60,MAX(E58-E59,0)) -> 0 | F61: =MIN(F60,MAX(F58-F59,0)) -> 0 | G61: =MIN(G60,MAX(G58-G59,0)) -> 235.73 | H61: =MIN(H60,MAX(H58-H59,0)) -> 0 | I61: =MIN(I60,MAX(I58-I59,0)) -> 0 | J61: =MIN(J60,MAX(J58-J59,0)) -> 0 | K61: =MIN(K60,MAX(K58-K59,0)) -> 0 | ... DS61: =MIN(DS60,MAX(DS58-DS59,0)) -> 0
A62: ★ Banco fim mês COM Helexia (kWh) | B62: =AA62 -> 51647.233 | C62: — | D62: =MAX(D60-D61,0)+MAX(D59-D58,0) -> 0 | E62: =MAX(E60-E61,0)+MAX(E59-E58,0) -> 72.77 | F62: =MAX(F60-F61,0)+MAX(F59-F58,0) -> 893.86 | G62: =MAX(G60-G61,0)+MAX(G59-G58,0) -> 658.13 | H62: =MAX(H60-H61,0)+MAX(H59-H58,0) -> 3267.586 | I62: =MAX(I60-I61,0)+MAX(I59-I58,0) -> 4665.042 | J62: =MAX(J60-J61,0)+MAX(J59-J58,0) -> 5971.414 | K62: =MAX(K60-K61,0)+MAX(K59-K58,0) -> 9324.3868 | ... DS62: =MAX(DS60-DS61,0)+MAX(DS59-DS58,0) -> 0
A63: Banco início mês SEM Helexia (kWh) | B63: =AA63 -> 0 | C63: — | D63: =0 -> 0 | E63: =D65 -> 0 | F63: =E65 -> 0 | G63: =F65 -> 0 | H63: =G65 -> 0 | I63: =H65 -> 0 | J63: =I65 -> 0 | K63: =J65 -> 0 | L63: =K65 -> 0 | ... DS63: =DR65 -> 0
A64: Bank draw SEM Helexia (kWh) | B64: =SUM(D64:BQ64) -> 0 | C64: =B64/60 -> 0 | D64: =MIN(D63,D58) -> 0 | E64: =MIN(E63,E58) -> 0 | F64: =MIN(F63,F58) -> 0 | G64: =MIN(G63,G58) -> 0 | H64: =MIN(H63,H58) -> 0 | I64: =MIN(I63,I58) -> 0 | J64: =MIN(J63,J58) -> 0 | K64: =MIN(K63,K58) -> 0 | ... DS64: =MIN(DS63,DS58) -> 0
A65: Banco fim mês SEM Helexia (kWh) | B65: =AA65 -> 0 | C65: — | D65: =MAX(D63-D64,0) -> 0 | E65: =MAX(E63-E64,0) -> 0 | F65: =MAX(F63-F64,0) -> 0 | G65: =MAX(G63-G64,0) -> 0 | H65: =MAX(H63-H64,0) -> 0 | I65: =MAX(I63-I64,0) -> 0 | J65: =MAX(J63-J64,0) -> 0 | K65: =MAX(K63-K64,0) -> 0 | ... DS65: =MAX(DS63-DS64,0) -> 0
A66: =" Custo SEM Helexia (R$) — só gen própria, sem "&INDEX(PVSYST_Helexia!$A$5:$A$7,MATCH(Premissas!$B$13,PVSYST_Helexia!$B$5:$B$7,0))&"/BAT/banco" -> Custo SEM Helexia (R$) — só gen própria, sem HCS03/BAT/banco | B66: =SUM(D66:BQ66) -> 295646.22 | C66: =B66/60 -> 4927.4371 | D66: =D58*Premissas!$F$19 -> 3384.5203 | E66: =E58*Premissas!$F$19 -> 3193.8692 | F66: =F58*Premissas!$F$19 -> 3154.9985 | G66: =G58*Premissas!$F$19 -> 3891.6893 | H66: =H58*Premissas!$F$19 -> 5023.5647 | I66: =I58*Premissas!$F$19 -> 5899.0791 | J66: =J58*Premissas!$F$19 -> 5620.5064 | K66: =K58*Premissas!$F$19 -> 3909.2736 | ... DS66: =DS58*Premissas!$F$19 -> 4833.8391
A67: Custo COM Helexia — rede remanescente (R$) | B67: =SUM(D67:BQ67) -> 22842.721 | C67: =B67/60 -> 380.71201 | D67: =IF(D62>0,0,MAX(D58-D59-D60,0)*Premissas!$B$7) -> 357.78322 | E67: =IF(E62>0,0,MAX(E58-E59-E60,0)*Premissas!$B$7) -> 0 | F67: =IF(F62>0,0,MAX(F58-F59-F60,0)*Premissas!$B$7) -> 0 | G67: =IF(G62>0,0,MAX(G58-G59-G60,0)*Premissas!$B$7) -> 0 | H67: =IF(H62>0,0,MAX(H58-H59-H60,0)*Premissas!$B$7) -> 0 | I67: =IF(I62>0,0,MAX(I58-I59-I60,0)*Premissas!$B$7) -> 0 | J67: =IF(J62>0,0,MAX(J58-J59-J60,0)*Premissas!$B$7) -> 0 | K67: =IF(K62>0,0,MAX(K58-K59-K60,0)*Premissas!$B$7) -> 0 | ... DS67: =IF(DS62>0,0,MAX(DS58-DS59-DS60,0)*Premissas!$B$7) -> 6042.2988
A68: ★ Economia mensal (R$) | B68: =SUM(D68:BQ68) -> 272803.5 | C68: =B68/60 -> 4546.725 | D68: =MAX(D66-D67,0) -> 3026.7371 | E68: =MAX(E66-E67,0) -> 3193.8692 | F68: =MAX(F66-F67,0) -> 3154.9985 | G68: =MAX(G66-G67,0) -> 3891.6893 | H68: =MAX(H66-H67,0) -> 5023.5647 | I68: =MAX(I66-I67,0) -> 5899.0791 | J68: =MAX(J66-J67,0) -> 5620.5064 | K68: =MAX(K66-K67,0) -> 3909.2736 | ... DS68: =MAX(DS66-DS67,0) -> 0
A70: Banheiro Motoristas (B3)
A71: Consumo FP (kWh) | B71: =SUM(D71:BQ71) -> 31671 | C71: =B71/60 -> 527.85 | D71: 450 | E71: 450 | F71: 450 | G71: 450 | H71: 450 | I71: 450 | J71: 450 | K71: 461 | L71: 461 | M71: 461 | N71: 461 | O71: 461 | P71: 461 | Q71: 461 | R71: 461 | S71: 461 | T71: 461 | U71: 461 | V71: 461 | W71: 461 | X71: 461 | Y71: 461 | Z71: 461 | AA71: 461 | AB71: 473 | AC71: 473 | AD71: 473 | AE71: 473 | AF71: 473 | AG71: 473 | AH71: 473 | AI71: 484 | AJ71: 484 | AK71: 484 | AL71: 484 | AM71: 484 | AN71: 485 | AO71: 485 | AP71: 485 | AQ71: 485 | AR71: 485 | AS71: 485 | AT71: 485 | AU71: 496 | AV71: 496 | AW71: 496 | AX71: 496 | AY71: 496 | AZ71: 497 | BA71: 497 | BB71: 497 | BC71: 497 | BD71: 497 | BE71: 497 | BF71: 497 | BG71: 509 | BH71: 509 | BI71: 509 | BJ71: 509 | BK71: 509 | BL71: 509 | BM71: 509 | BN71: 509 | BO71: 509 | BP71: 509 | BQ71: 509 | BR71: 509 | BS71: 522 | BT71: 522 | BU71: 522 | BV71: 522 | BW71: 522 | BX71: 522 | BY71: 522 | BZ71: 522 | CA71: 522 | CB71: 522 | CC71: 522 | CD71: 522 | CE71: 535 | CF71: 535 | CG71: 535 | CH71: 535 | CI71: 535 | CJ71: 535 | CK71: 535 | CL71: 535 | CM71: 535 | CN71: 535 | CO71: 535 | CP71: 535 | CQ71: 548 | CR71: 548 | CS71: 548 | CT71: 548 | CU71: 548 | CV71: 548 | CW71: 548 | CX71: 548 | CY71: 548 | CZ71: 548 | DA71: 548 | DB71: 548 | DC71: 562 | DD71: 562 | DE71: 562 | DF71: 562 | DG71: 562 | DH71: 562 | DI71: 562 | DJ71: 562 | DK71: 562 | DL71: 562 | DM71: 562 | DN71: 562 | DO71: 576 | DP71: 576 | DQ71: 576 | DR71: 576 | DS71: 576
A72: =" "&INDEX(PVSYST_Helexia!$A$5:$A$7,MATCH(Premissas!$B$13,PVSYST_Helexia!$B$5:$B$7,0))&" créditos recebidos (kWh)" -> HCS03 créditos recebidos (kWh) | B72: =SUM(D72:BQ72) -> 51558.594 | C72: =B72/60 -> 859.3099 | D72: =D6*Premissas!$B$37 -> 409.167 | E72: =E6*Premissas!$B$37 -> 430.683 | F72: =F6*Premissas!$B$37 -> 517.011 | G72: =G6*Premissas!$B$37 -> 485.133 | H72: =H6*Premissas!$C$37 -> 755.4 | I72: =I6*Premissas!$C$37 -> 730.4 | J72: =J6*Premissas!$C$37 -> 693.55 | K72: =K6*Premissas!$C$37 -> 712.1215 | L72: =L6*Premissas!$C$37 -> 634.56125 | M72: =M6*Premissas!$C$37 -> 727.8425 | N72: =N6*Premissas!$D$37 -> 581.0004 | O72: =O6*Premissas!$D$37 -> 543.7476 | P72: =P6*Premissas!$D$37 -> 493.4802 | Q72: =Q6*Premissas!$D$37 -> 519.4298 | R72: =R6*Premissas!$D$37 -> 623.5466 | S72: =S6*Premissas!$D$37 -> 585.0998 | T72: =T6*Premissas!$E$37 -> 676.4607 | U72: =U6*Premissas!$E$37 -> 654.0732 | V72: =V6*Premissas!$E$37 -> 621.07403 | W72: =W6*Premissas!$E$37 -> 640.90935 | X72: =X6*Premissas!$E$37 -> 571.10512 | Y72: =Y6*Premissas!$E$37 -> 655.05825 | Z72: =Z6*Premissas!$E$37 -> 653.62545 | AA72: =AA6*Premissas!$E$37 -> 611.71605 | AB72: =AB6*Premissas!$F$37 -> 319.15832 | AC72: =AC6*Premissas!$F$37 -> 335.94122 | AD72: =AD6*Premissas!$F$37 -> 403.27876 | AE72: =AE6*Premissas!$F$37 -> 378.4133 | AF72: =AF6*Premissas!$F$37 -> 388.88974 | AG72: =AG6*Premissas!$F$37 -> 376.01942 | AH72: =AH6*Premissas!$G$37 -> 370.78119 | AI72: =AI6*Premissas!$G$37 -> 382.62288 | AJ72: =AJ6*Premissas!$G$37 -> 340.94976 | AK72: =AK6*Premissas!$G$37 -> 391.06978 | AL72: =AL6*Premissas!$G$37 -> 390.21439 | AM72: =AM6*Premissas!$G$37 -> 365.19448 | AN72: =AN6*Premissas!$H$37 -> 317.56253 | AO72: =AO6*Premissas!$H$37 -> 334.26152 | AP72: =AP6*Premissas!$H$37 -> 401.26237 | AQ72: =AQ6*Premissas!$H$37 -> 376.52123 | AR72: =AR6*Premissas!$H$37 -> 386.94529 | AS72: =AS6*Premissas!$H$37 -> 374.13932 | AT72: =AT6*Premissas!$I$37 -> 368.92729 | AU72: =AU6*Premissas!$I$37 -> 380.70977 | AV72: =AV6*Premissas!$I$37 -> 339.24501 | AW72: =AW6*Premissas!$I$37 -> 389.11443 | AX72: =AX6*Premissas!$I$37 -> 388.26332 | AY72: =AY6*Premissas!$I$37 -> 363.36851 | AZ72: =AZ6*Premissas!$J$37 -> 328.12759 | BA72: =BA6*Premissas!$J$37 -> 345.38214 | BB72: =BB6*Premissas!$J$37 -> 414.61206 | BC72: =BC6*Premissas!$J$37 -> 389.0478 | BD72: =BD6*Premissas!$J$37 -> 399.81866 | BE72: =BE6*Premissas!$J$37 -> 386.58665 | BF72: =BF6*Premissas!$K$37 -> 462.25223 | BG72: =BG6*Premissas!$K$37 -> 477.01524 | BH72: =BH6*Premissas!$K$37 -> 425.06143 | BI72: =BI6*Premissas!$K$37 -> 487.54596 | BJ72: =BJ6*Premissas!$K$37 -> 486.47956 | BK72: =BK6*Premissas!$K$37 -> 455.28728 | BL72: =BL6*Premissas!$L$37 -> 3350.3607 | BM72: =BM6*Premissas!$L$37 -> 3526.5391 | BN72: =BN6*Premissas!$L$37 -> 4233.4141 | BO72: =BO6*Premissas!$L$37 -> 3972.3891 | BP72: =BP6*Premissas!$L$37 -> 4082.3655 | BQ72: =BQ6*Premissas!$L$37 -> 3947.2594 | BR72: =BR6*Premissas!$M$37 -> 3780.0275 | BS72: =BS6*Premissas!$M$37 -> 3900.7508 | BT72: =BT6*Premissas!$M$37 -> 3475.903 | BU72: =BU6*Premissas!$M$37 -> 3986.8649 | BV72: =BV6*Premissas!$M$37 -> 3978.1445 | BW72: =BW6*Premissas!$M$37 -> 3723.0723 | BX72: =BX6*Premissas!$N$37 -> 3340.7329 | BY72: =BY6*Premissas!$N$37 -> 3516.4049 | BZ72: =BZ6*Premissas!$N$37 -> 4221.2486 | CA72: =CA6*Premissas!$N$37 -> 3960.9738 | CB72: =CB6*Premissas!$N$37 -> 4070.6341 | CC72: =CC6*Premissas!$N$37 -> 3935.9162 | CD72: =CD6*Premissas!$O$37 -> 3768.9383 | CE72: =CE6*Premissas!$O$37 -> 3889.3073 | CF72: =CF6*Premissas!$O$37 -> 3465.706 | CG72: =CG6*Premissas!$O$37 -> 3975.1688 | CH72: =CH6*Premissas!$O$37 -> 3966.474 | CI72: =CI6*Premissas!$O$37 -> 3712.1501 | CJ72: =CJ6*Premissas!$P$37 -> 3331.0828 | CK72: =CK6*Premissas!$P$37 -> 3506.2474 | CL72: =CL6*Premissas!$P$37 -> 4209.0551 | CM72: =CM6*Premissas!$P$37 -> 3949.5321 | CN72: =CN6*Premissas!$P$37 -> 4058.8756 | CO72: =CO6*Premissas!$P$37 -> 3924.5469 | CP72: =CP6*Premissas!$Q$37 -> 3757.8265 | CQ72: =CQ6*Premissas!$Q$37 -> 3877.8407 | CR72: =CR6*Premissas!$Q$37 -> 3455.4882 | CS72: =CS6*Premissas!$Q$37 -> 3963.4491 | CT72: =CT6*Premissas!$Q$37 -> 3954.7799 | CU72: =CU6*Premissas!$Q$37 -> 3701.2058 | CV72: =CV6*Premissas!$R$37 -> 3321.41 | CW72: =CW6*Premissas!$R$37 -> 3496.0659 | CX72: =CX6*Premissas!$R$37 -> 4196.8328 | CY72: =CY6*Premissas!$R$37 -> 3938.0634 | CZ72: =CZ6*Premissas!$R$37 -> 4047.0894 | DA72: =DA6*Premissas!$R$37 -> 3913.1508 | DB72: =DB6*Premissas!$S$37 -> 0 | DC72: =DC6*Premissas!$S$37 -> 0 | DD72: =DD6*Premissas!$S$37 -> 0 | DE72: =DE6*Premissas!$S$37 -> 0 | DF72: =DF6*Premissas!$S$37 -> 0 | DG72: =DG6*Premissas!$S$37 -> 0 | DH72: =DH6*Premissas!$T$37 -> 0 | DI72: =DI6*Premissas!$T$37 -> 0 | DJ72: =DJ6*Premissas!$T$37 -> 0 | DK72: =DK6*Premissas!$T$37 -> 0 | DL72: =DL6*Premissas!$T$37 -> 0 | DM72: =DM6*Premissas!$T$37 -> 0 | DN72: =DN6*Premissas!$U$37 -> 0 | DO72: =DO6*Premissas!$U$37 -> 0 | DP72: =DP6*Premissas!$U$37 -> 0 | DQ72: =DQ6*Premissas!$U$37 -> 0 | DR72: =DR6*Premissas!$U$37 -> 0 | DS72: =DS6*Premissas!$U$37 -> 0
A73: Banco início mês COM Helexia (kWh) | B73: =AA73 -> 3448.6297 | C73: — | D73: =0 -> 0 | E73: =D75 -> 0 | F73: =E75 -> 0 | G73: =F75 -> 67.011 | H73: =G75 -> 102.144 | I73: =H75 -> 407.544 | J73: =I75 -> 687.944 | K73: =J75 -> 931.494 | L73: =K75 -> 1182.6155 | ... DS73: =DR75 -> 128512.29
A74: Bank draw COM Helexia (kWh) | B74: =SUM(D74:BQ74) -> 3599.3458 | C74: =B74/60 -> 59.989097 | D74: =MIN(D73,MAX(D71-D72,0)) -> 0 | E74: =MIN(E73,MAX(E71-E72,0)) -> 0 | F74: =MIN(F73,MAX(F71-F72,0)) -> 0 | G74: =MIN(G73,MAX(G71-G72,0)) -> 0 | H74: =MIN(H73,MAX(H71-H72,0)) -> 0 | I74: =MIN(I73,MAX(I71-I72,0)) -> 0 | J74: =MIN(J73,MAX(J71-J72,0)) -> 0 | K74: =MIN(K73,MAX(K71-K72,0)) -> 0 | ... DS74: =MIN(DS73,MAX(DS71-DS72,0)) -> 576
A75: ★ Banco fim mês COM Helexia (kWh) | B75: =AA75 -> 3599.3458 | C75: — | D75: =MAX(D73-D74,0)+MAX(D72-D71,0) -> 0 | E75: =MAX(E73-E74,0)+MAX(E72-E71,0) -> 0 | F75: =MAX(F73-F74,0)+MAX(F72-F71,0) -> 67.011 | G75: =MAX(G73-G74,0)+MAX(G72-G71,0) -> 102.144 | H75: =MAX(H73-H74,0)+MAX(H72-H71,0) -> 407.544 | I75: =MAX(I73-I74,0)+MAX(I72-I71,0) -> 687.944 | J75: =MAX(J73-J74,0)+MAX(J72-J71,0) -> 931.494 | K75: =MAX(K73-K74,0)+MAX(K72-K71,0) -> 1182.6155 | ... DS75: =MAX(DS73-DS74,0)+MAX(DS72-DS71,0) -> 127936.29
A76: Banco início mês SEM Helexia (kWh) | B76: =AA76 -> 0 | C76: — | D76: =0 -> 0 | E76: =D78 -> 0 | F76: =E78 -> 0 | G76: =F78 -> 0 | H76: =G78 -> 0 | I76: =H78 -> 0 | J76: =I78 -> 0 | K76: =J78 -> 0 | L76: =K78 -> 0 | ... DS76: =DR78 -> 0
A77: Bank draw SEM Helexia (kWh) | B77: =SUM(D77:BQ77) -> 0 | C77: =B77/60 -> 0 | D77: =MIN(D76,D71) -> 0 | E77: =MIN(E76,E71) -> 0 | F77: =MIN(F76,F71) -> 0 | G77: =MIN(G76,G71) -> 0 | H77: =MIN(H76,H71) -> 0 | I77: =MIN(I76,I71) -> 0 | J77: =MIN(J76,J71) -> 0 | K77: =MIN(K76,K71) -> 0 | ... DS77: =MIN(DS76,DS71) -> 0
A78: Banco fim mês SEM Helexia (kWh) | B78: =AA78 -> 0 | C78: — | D78: =MAX(D76-D77,0) -> 0 | E78: =MAX(E76-E77,0) -> 0 | F78: =MAX(F76-F77,0) -> 0 | G78: =MAX(G76-G77,0) -> 0 | H78: =MAX(H76-H77,0) -> 0 | I78: =MAX(I76-I77,0) -> 0 | J78: =MAX(J76-J77,0) -> 0 | K78: =MAX(K76-K77,0) -> 0 | ... DS78: =MAX(DS76-DS77,0) -> 0
A79: =" Custo SEM Helexia (R$) — só gen própria, sem "&INDEX(PVSYST_Helexia!$A$5:$A$7,MATCH(Premissas!$B$13,PVSYST_Helexia!$B$5:$B$7,0))&"/BAT/banco" -> Custo SEM Helexia (R$) — só gen própria, sem HCS03/BAT/banco | B79: =SUM(D79:BQ79) -> 29311.223 | C79: =B79/60 -> 488.52038 | D79: =D71*Premissas!$F$19 -> 416.47091 | E79: =E71*Premissas!$F$19 -> 416.47091 | F79: =F71*Premissas!$F$19 -> 416.47091 | G79: =G71*Premissas!$F$19 -> 416.47091 | H79: =H71*Premissas!$F$19 -> 416.47091 | I79: =I71*Premissas!$F$19 -> 416.47091 | J79: =J71*Premissas!$F$19 -> 416.47091 | K79: =K71*Premissas!$F$19 -> 426.65131 | ... DS79: =DS71*Premissas!$F$19 -> 533.08277
A80: Custo COM Helexia — rede remanescente (R$) | B80: =SUM(D80:BQ80) -> 197.51569 | C80: =B80/60 -> 3.2919282 | D80: =IF(D75>0,0,MAX(D71-D72-D73,0)*Premissas!$B$7) -> 47.238213 | E80: =IF(E75>0,0,MAX(E71-E72-E73,0)*Premissas!$B$7) -> 22.347135 | F80: =IF(F75>0,0,MAX(F71-F72-F73,0)*Premissas!$B$7) -> 0 | G80: =IF(G75>0,0,MAX(G71-G72-G73,0)*Premissas!$B$7) -> 0 | H80: =IF(H75>0,0,MAX(H71-H72-H73,0)*Premissas!$B$7) -> 0 | I80: =IF(I75>0,0,MAX(I71-I72-I73,0)*Premissas!$B$7) -> 0 | J80: =IF(J75>0,0,MAX(J71-J72-J73,0)*Premissas!$B$7) -> 0 | K80: =IF(K75>0,0,MAX(K71-K72-K73,0)*Premissas!$B$7) -> 0 | ... DS80: =IF(DS75>0,0,MAX(DS71-DS72-DS73,0)*Premissas!$B$7) -> 0
A81: ★ Economia mensal (R$) | B81: =SUM(D81:BQ81) -> 29113.707 | C81: =B81/60 -> 485.22845 | D81: =MAX(D79-D80,0) -> 369.2327 | E81: =MAX(E79-E80,0) -> 394.12378 | F81: =MAX(F79-F80,0) -> 416.47091 | G81: =MAX(G79-G80,0) -> 416.47091 | H81: =MAX(H79-H80,0) -> 416.47091 | I81: =MAX(I79-I80,0) -> 416.47091 | J81: =MAX(J79-J80,0) -> 416.47091 | K81: =MAX(K79-K80,0) -> 426.65131 | ... DS81: =MAX(DS79-DS80,0) -> 533.08277
A83: CTC Copasul (B3)
A84: Consumo FP (kWh) | B84: =SUM(D84:BQ84) -> 42066 | C84: =B84/60 -> 701.1 | D84: 364 | E84: 293 | F84: 369 | G84: 674 | H84: 752 | I84: 769 | J84: 670 | K84: 399 | L84: 917 | M84: 968 | N84: 541 | O84: 610 | P84: 373 | Q84: 300 | R84: 378 | S84: 691 | T84: 771 | U84: 788 | V84: 687 | W84: 399 | X84: 917 | Y84: 968 | Z84: 541 | AA84: 610 | AB84: 382 | AC84: 308 | AD84: 388 | AE84: 708 | AF84: 790 | AG84: 808 | AH84: 704 | AI84: 419 | AJ84: 963 | AK84: 1017 | AL84: 568 | AM84: 641 | AN84: 392 | AO84: 316 | AP84: 397 | AQ84: 726 | AR84: 810 | AS84: 828 | AT84: 722 | AU84: 430 | AV84: 988 | AW84: 1042 | AX84: 583 | AY84: 657 | AZ84: 402 | BA84: 323 | BB84: 407 | BC84: 744 | BD84: 830 | BE84: 849 | BF84: 740 | BG84: 440 | BH84: 1012 | BI84: 1068 | BJ84: 597 | BK84: 673 | BL84: 412 | BM84: 332 | BN84: 417 | BO84: 763 | BP84: 851 | BQ84: 870 | BR84: 758 | BS84: 451 | BT84: 1038 | BU84: 1095 | BV84: 612 | BW84: 690 | BX84: 422 | BY84: 340 | BZ84: 428 | CA84: 782 | CB84: 872 | CC84: 892 | CD84: 777 | CE84: 463 | CF84: 1063 | CG84: 1123 | CH84: 627 | CI84: 707 | CJ84: 433 | CK84: 348 | CL84: 439 | CM84: 801 | CN84: 894 | CO84: 914 | CP84: 796 | CQ84: 474 | CR84: 1090 | CS84: 1151 | CT84: 643 | CU84: 725 | CV84: 443 | CW84: 357 | CX84: 450 | CY84: 821 | CZ84: 916 | DA84: 937 | DB84: 816 | DC84: 486 | DD84: 1117 | DE84: 1179 | DF84: 659 | DG84: 743 | DH84: 455 | DI84: 366 | DJ84: 461 | DK84: 842 | DL84: 939 | DM84: 960 | DN84: 837 | DO84: 498 | DP84: 1145 | DQ84: 1209 | DR84: 676 | DS84: 762
A85: =" "&INDEX(PVSYST_Helexia!$A$5:$A$7,MATCH(Premissas!$B$13,PVSYST_Helexia!$B$5:$B$7,0))&" créditos recebidos (kWh)" -> HCS03 créditos recebidos (kWh) | B85: =SUM(D85:BQ85) -> 60461.298 | C85: =B85/60 -> 1007.6883 | D85: =D6*Premissas!$B$38 -> 384.369 | E85: =E6*Premissas!$B$38 -> 404.581 | F85: =F6*Premissas!$B$38 -> 485.677 | G85: =G6*Premissas!$B$38 -> 455.731 | H85: =H6*Premissas!$C$38 -> 1163.316 | I85: =I6*Premissas!$C$38 -> 1124.816 | J85: =J6*Premissas!$C$38 -> 1068.067 | K85: =K6*Premissas!$C$38 -> 1096.6671 | L85: =L6*Premissas!$C$38 -> 977.22433 | M85: =M6*Premissas!$C$38 -> 1120.8774 | N85: =N6*Premissas!$D$38 -> 566.47539 | O85: =O6*Premissas!$D$38 -> 530.15391 | P85: =P6*Premissas!$D$38 -> 481.14319 | Q85: =Q6*Premissas!$D$38 -> 506.44405 | R85: =R6*Premissas!$D$38 -> 607.95793 | S85: =S6*Premissas!$D$38 -> 570.47231 | T85: =T6*Premissas!$E$38 -> 1082.3371 | U85: =U6*Premissas!$E$38 -> 1046.5171 | V85: =V6*Premissas!$E$38 -> 993.71844 | W85: =W6*Premissas!$E$38 -> 1025.455 | X85: =X6*Premissas!$E$38 -> 913.7682 | Y85: =Y6*Premissas!$E$38 -> 1048.0932 | Z85: =Z6*Premissas!$E$38 -> 1045.8007 | AA85: =AA6*Premissas!$E$38 -> 978.74568 | AB85: =AB6*Premissas!$F$38 -> 392.81024 | AC85: =AC6*Premissas!$F$38 -> 413.46612 | AD85: =AD6*Premissas!$F$38 -> 496.34309 | AE85: =AE6*Premissas!$F$38 -> 465.73944 | AF85: =AF6*Premissas!$F$38 -> 478.63353 | AG85: =AG6*Premissas!$F$38 -> 462.79313 | AH85: =AH6*Premissas!$G$38 -> 466.90965 | AI85: =AI6*Premissas!$G$38 -> 481.82141 | AJ85: =AJ6*Premissas!$G$38 -> 429.34414 | AK85: =AK6*Premissas!$G$38 -> 492.45824 | AL85: =AL6*Premissas!$G$38 -> 491.38109 | AM85: =AM6*Premissas!$G$38 -> 459.87453 | AN85: =AN6*Premissas!$H$38 -> 390.84619 | AO85: =AO6*Premissas!$H$38 -> 411.39879 | AP85: =AP6*Premissas!$H$38 -> 493.86138 | AQ85: =AQ6*Premissas!$H$38 -> 463.41074 | AR85: =AR6*Premissas!$H$38 -> 476.24036 | AS85: =AS6*Premissas!$H$38 -> 460.47916 | AT85: =AT6*Premissas!$I$38 -> 464.5751 | AU85: =AU6*Premissas!$I$38 -> 479.4123 | AV85: =AV6*Premissas!$I$38 -> 427.19742 | AW85: =AW6*Premissas!$I$38 -> 489.99594 | AX85: =AX6*Premissas!$I$38 -> 488.92418 | AY85: =AY6*Premissas!$I$38 -> 457.57516 | AZ85: =AZ6*Premissas!$J$38 -> 449.65633 | BA85: =BA6*Premissas!$J$38 -> 473.30145 | BB85: =BB6*Premissas!$J$38 -> 568.17208 | BC85: =BC6*Premissas!$J$38 -> 533.13958 | BD85: =BD6*Premissas!$J$38 -> 547.89965 | BE85: =BE6*Premissas!$J$38 -> 529.76688 | BF85: =BF6*Premissas!$K$38 -> 584.61311 | BG85: =BG6*Premissas!$K$38 -> 603.28398 | BH85: =BH6*Premissas!$K$38 -> 537.5777 | BI85: =BI6*Premissas!$K$38 -> 616.60225 | BJ85: =BJ6*Premissas!$K$38 -> 615.25356 | BK85: =BK6*Premissas!$K$38 -> 575.80451 | BL85: =BL6*Premissas!$L$38 -> 3350.3607 | BM85: =BM6*Premissas!$L$38 -> 3526.5391 | BN85: =BN6*Premissas!$L$38 -> 4233.4141 | BO85: =BO6*Premissas!$L$38 -> 3972.3891 | BP85: =BP6*Premissas!$L$38 -> 4082.3655 | BQ85: =BQ6*Premissas!$L$38 -> 3947.2594 | BR85: =BR6*Premissas!$M$38 -> 3780.0275 | BS85: =BS6*Premissas!$M$38 -> 3900.7508 | BT85: =BT6*Premissas!$M$38 -> 3475.903 | BU85: =BU6*Premissas!$M$38 -> 3986.8649 | BV85: =BV6*Premissas!$M$38 -> 3978.1445 | BW85: =BW6*Premissas!$M$38 -> 3723.0723 | BX85: =BX6*Premissas!$N$38 -> 3340.7329 | BY85: =BY6*Premissas!$N$38 -> 3516.4049 | BZ85: =BZ6*Premissas!$N$38 -> 4221.2486 | CA85: =CA6*Premissas!$N$38 -> 3960.9738 | CB85: =CB6*Premissas!$N$38 -> 4070.6341 | CC85: =CC6*Premissas!$N$38 -> 3935.9162 | CD85: =CD6*Premissas!$O$38 -> 3768.9383 | CE85: =CE6*Premissas!$O$38 -> 3889.3073 | CF85: =CF6*Premissas!$O$38 -> 3465.706 | CG85: =CG6*Premissas!$O$38 -> 3975.1688 | CH85: =CH6*Premissas!$O$38 -> 3966.474 | CI85: =CI6*Premissas!$O$38 -> 3712.1501 | CJ85: =CJ6*Premissas!$P$38 -> 3331.0828 | CK85: =CK6*Premissas!$P$38 -> 3506.2474 | CL85: =CL6*Premissas!$P$38 -> 4209.0551 | CM85: =CM6*Premissas!$P$38 -> 3949.5321 | CN85: =CN6*Premissas!$P$38 -> 4058.8756 | CO85: =CO6*Premissas!$P$38 -> 3924.5469 | CP85: =CP6*Premissas!$Q$38 -> 3757.8265 | CQ85: =CQ6*Premissas!$Q$38 -> 3877.8407 | CR85: =CR6*Premissas!$Q$38 -> 3455.4882 | CS85: =CS6*Premissas!$Q$38 -> 3963.4491 | CT85: =CT6*Premissas!$Q$38 -> 3954.7799 | CU85: =CU6*Premissas!$Q$38 -> 3701.2058 | CV85: =CV6*Premissas!$R$38 -> 3321.41 | CW85: =CW6*Premissas!$R$38 -> 3496.0659 | CX85: =CX6*Premissas!$R$38 -> 4196.8328 | CY85: =CY6*Premissas!$R$38 -> 3938.0634 | CZ85: =CZ6*Premissas!$R$38 -> 4047.0894 | DA85: =DA6*Premissas!$R$38 -> 3913.1508 | DB85: =DB6*Premissas!$S$38 -> 0 | DC85: =DC6*Premissas!$S$38 -> 0 | DD85: =DD6*Premissas!$S$38 -> 0 | DE85: =DE6*Premissas!$S$38 -> 0 | DF85: =DF6*Premissas!$S$38 -> 0 | DG85: =DG6*Premissas!$S$38 -> 0 | DH85: =DH6*Premissas!$T$38 -> 0 | DI85: =DI6*Premissas!$T$38 -> 0 | DJ85: =DJ6*Premissas!$T$38 -> 0 | DK85: =DK6*Premissas!$T$38 -> 0 | DL85: =DL6*Premissas!$T$38 -> 0 | DM85: =DM6*Premissas!$T$38 -> 0 | DN85: =DN6*Premissas!$U$38 -> 0 | DO85: =DO6*Premissas!$U$38 -> 0 | DP85: =DP6*Premissas!$U$38 -> 0 | DQ85: =DQ6*Premissas!$U$38 -> 0 | DR85: =DR6*Premissas!$U$38 -> 0 | DS85: =DS6*Premissas!$U$38 -> 0
A86: Banco início mês COM Helexia (kWh) | B86: =AA86 -> 4560.6624 | C86: — | D86: =0 -> 0 | E86: =D88 -> 20.369 | F86: =E88 -> 131.95 | G86: =F88 -> 248.627 | H86: =G88 -> 30.358 | I86: =H88 -> 441.674 | J86: =I88 -> 797.49 | K86: =J88 -> 1195.557 | L86: =K88 -> 1893.2241 | ... DS86: =DR88 -> 117578.29
A87: Bank draw COM Helexia (kWh) | B87: =SUM(D87:BQ87) -> 6421.0634 | C87: =B87/60 -> 107.01772 | D87: =MIN(D86,MAX(D84-D85,0)) -> 0 | E87: =MIN(E86,MAX(E84-E85,0)) -> 0 | F87: =MIN(F86,MAX(F84-F85,0)) -> 0 | G87: =MIN(G86,MAX(G84-G85,0)) -> 218.269 | H87: =MIN(H86,MAX(H84-H85,0)) -> 0 | I87: =MIN(I86,MAX(I84-I85,0)) -> 0 | J87: =MIN(J86,MAX(J84-J85,0)) -> 0 | K87: =MIN(K86,MAX(K84-K85,0)) -> 0 | ... DS87: =MIN(DS86,MAX(DS84-DS85,0)) -> 762
A88: ★ Banco fim mês COM Helexia (kWh) | B88: =AA88 -> 4929.4081 | C88: — | D88: =MAX(D86-D87,0)+MAX(D85-D84,0) -> 20.369 | E88: =MAX(E86-E87,0)+MAX(E85-E84,0) -> 131.95 | F88: =MAX(F86-F87,0)+MAX(F85-F84,0) -> 248.627 | G88: =MAX(G86-G87,0)+MAX(G85-G84,0) -> 30.358 | H88: =MAX(H86-H87,0)+MAX(H85-H84,0) -> 441.674 | I88: =MAX(I86-I87,0)+MAX(I85-I84,0) -> 797.49 | J88: =MAX(J86-J87,0)+MAX(J85-J84,0) -> 1195.557 | K88: =MAX(K86-K87,0)+MAX(K85-K84,0) -> 1893.2241 | ... DS88: =MAX(DS86-DS87,0)+MAX(DS85-DS84,0) -> 116816.29
A89: Banco início mês SEM Helexia (kWh) | B89: =AA89 -> 0 | C89: — | D89: =0 -> 0 | E89: =D91 -> 0 | F89: =E91 -> 0 | G89: =F91 -> 0 | H89: =G91 -> 0 | I89: =H91 -> 0 | J89: =I91 -> 0 | K89: =J91 -> 0 | L89: =K91 -> 0 | ... DS89: =DR91 -> 0
A90: Bank draw SEM Helexia (kWh) | B90: =SUM(D90:BQ90) -> 0 | C90: =B90/60 -> 0 | D90: =MIN(D89,D84) -> 0 | E90: =MIN(E89,E84) -> 0 | F90: =MIN(F89,F84) -> 0 | G90: =MIN(G89,G84) -> 0 | H90: =MIN(H89,H84) -> 0 | I90: =MIN(I89,I84) -> 0 | J90: =MIN(J89,J84) -> 0 | K90: =MIN(K89,K84) -> 0 | ... DS90: =MIN(DS89,DS84) -> 0
A91: Banco fim mês SEM Helexia (kWh) | B91: =AA91 -> 0 | C91: — | D91: =MAX(D89-D90,0) -> 0 | E91: =MAX(E89-E90,0) -> 0 | F91: =MAX(F89-F90,0) -> 0 | G91: =MAX(G89-G90,0) -> 0 | H91: =MAX(H89-H90,0) -> 0 | I91: =MAX(I89-I90,0) -> 0 | J91: =MAX(J89-J90,0) -> 0 | K91: =MAX(K89-K90,0) -> 0 | ... DS91: =MAX(DS89-DS90,0) -> 0
A92: =" Custo SEM Helexia (R$) — só gen própria, sem "&INDEX(PVSYST_Helexia!$A$5:$A$7,MATCH(Premissas!$B$13,PVSYST_Helexia!$B$5:$B$7,0))&"/BAT/banco" -> Custo SEM Helexia (R$) — só gen própria, sem HCS03/BAT/banco | B92: =SUM(D92:BQ92) -> 38931.701 | C92: =B92/60 -> 648.86168 | D92: =D84*Premissas!$F$19 -> 336.87869 | E92: =E84*Premissas!$F$19 -> 271.16884 | F92: =F84*Premissas!$F$19 -> 341.50615 | G92: =G84*Premissas!$F$19 -> 623.78088 | H92: =H84*Premissas!$F$19 -> 695.96917 | I92: =I84*Premissas!$F$19 -> 711.70252 | J92: =J84*Premissas!$F$19 -> 620.07892 | K92: =K84*Premissas!$F$19 -> 369.27088 | ... DS92: =DS84*Premissas!$F$19 -> 705.22408
A93: Custo COM Helexia — rede remanescente (R$) | B93: =SUM(D93:BQ93) -> 1240.1919 | C93: =B93/60 -> 20.669866 | D93: =IF(D88>0,0,MAX(D84-D85-D86,0)*Premissas!$B$7) -> 0 | E93: =IF(E88>0,0,MAX(E84-E85-E86,0)*Premissas!$B$7) -> 0 | F93: =IF(F88>0,0,MAX(F84-F85-F86,0)*Premissas!$B$7) -> 0 | G93: =IF(G88>0,0,MAX(G84-G85-G86,0)*Premissas!$B$7) -> 0 | H93: =IF(H88>0,0,MAX(H84-H85-H86,0)*Premissas!$B$7) -> 0 | I93: =IF(I88>0,0,MAX(I84-I85-I86,0)*Premissas!$B$7) -> 0 | J93: =IF(J88>0,0,MAX(J84-J85-J86,0)*Premissas!$B$7) -> 0 | K93: =IF(K88>0,0,MAX(K84-K85-K86,0)*Premissas!$B$7) -> 0 | ... DS93: =IF(DS88>0,0,MAX(DS84-DS85-DS86,0)*Premissas!$B$7) -> 0
A94: ★ Economia mensal (R$) | B94: =SUM(D94:BQ94) -> 37691.509 | C94: =B94/60 -> 628.19182 | D94: =MAX(D92-D93,0) -> 336.87869 | E94: =MAX(E92-E93,0) -> 271.16884 | F94: =MAX(F92-F93,0) -> 341.50615 | G94: =MAX(G92-G93,0) -> 623.78088 | H94: =MAX(H92-H93,0) -> 695.96917 | I94: =MAX(I92-I93,0) -> 711.70252 | J94: =MAX(J92-J93,0) -> 620.07892 | K94: =MAX(K92-K93,0) -> 369.27088 | ... DS94: =MAX(DS92-DS93,0) -> 705.22408
A96: Depósito Irrigação (B3)
A97: Consumo FP (kWh) | B97: =SUM(D97:BQ97) -> 65325 | C97: =B97/60 -> 1088.75 | D97: 1067 | E97: 899 | F97: 816 | G97: 719 | H97: 943 | I97: 925 | J97: 838 | K97: 898 | L97: 909 | M97: 1056 | N97: 1052 | O97: 1175 | P97: 1094 | Q97: 921 | R97: 836 | S97: 737 | T97: 967 | U97: 948 | V97: 859 | W97: 898 | X97: 909 | Y97: 1056 | Z97: 1052 | AA97: 1175 | AB97: 1121 | AC97: 945 | AD97: 857 | AE97: 755 | AF97: 991 | AG97: 972 | AH97: 880 | AI97: 943 | AJ97: 955 | AK97: 1109 | AL97: 1105 | AM97: 1234 | AN97: 1149 | AO97: 968 | AP97: 879 | AQ97: 774 | AR97: 1016 | AS97: 996 | AT97: 902 | AU97: 967 | AV97: 979 | AW97: 1137 | AX97: 1133 | AY97: 1265 | AZ97: 1178 | BA97: 992 | BB97: 901 | BC97: 794 | BD97: 1041 | BE97: 1021 | BF97: 925 | BG97: 991 | BH97: 1003 | BI97: 1166 | BJ97: 1161 | BK97: 1297 | BL97: 1207 | BM97: 1017 | BN97: 923 | BO97: 813 | BP97: 1067 | BQ97: 1047 | BR97: 948 | BS97: 1016 | BT97: 1028 | BU97: 1195 | BV97: 1190 | BW97: 1329 | BX97: 1237 | BY97: 1043 | BZ97: 946 | CA97: 834 | CB97: 1094 | CC97: 1073 | CD97: 972 | CE97: 1041 | CF97: 1054 | CG97: 1225 | CH97: 1220 | CI97: 1363 | CJ97: 1268 | CK97: 1069 | CL97: 970 | CM97: 855 | CN97: 1121 | CO97: 1100 | CP97: 996 | CQ97: 1067 | CR97: 1081 | CS97: 1255 | CT97: 1250 | CU97: 1397 | CV97: 1300 | CW97: 1095 | CX97: 994 | CY97: 876 | CZ97: 1149 | DA97: 1127 | DB97: 1021 | DC97: 1094 | DD97: 1108 | DE97: 1287 | DF97: 1282 | DG97: 1432 | DH97: 1333 | DI97: 1123 | DJ97: 1019 | DK97: 898 | DL97: 1178 | DM97: 1155 | DN97: 1047 | DO97: 1121 | DP97: 1135 | DQ97: 1319 | DR97: 1314 | DS97: 1467
A98: =" "&INDEX(PVSYST_Helexia!$A$5:$A$7,MATCH(Premissas!$B$13,PVSYST_Helexia!$B$5:$B$7,0))&" créditos recebidos (kWh)" -> HCS03 créditos recebidos (kWh) | B98: =SUM(D98:BQ98) -> 90134.414 | C98: =B98/60 -> 1502.2402 | D98: =D6*Premissas!$B$39 -> 793.536 | E98: =E6*Premissas!$B$39 -> 835.264 | F98: =F6*Premissas!$B$39 -> 1002.688 | G98: =G6*Premissas!$B$39 -> 940.864 | H98: =H6*Premissas!$C$39 -> 1722.312 | I98: =I6*Premissas!$C$39 -> 1665.312 | J98: =J6*Premissas!$C$39 -> 1581.294 | K98: =K6*Premissas!$C$39 -> 1623.637 | L98: =L6*Premissas!$C$39 -> 1446.7997 | M98: =M6*Premissas!$C$39 -> 1659.4809 | N98: =N6*Premissas!$D$39 -> 1176.5258 | O98: =O6*Premissas!$D$39 -> 1101.0889 | P98: =P6*Premissas!$D$39 -> 999.29741 | Q98: =Q6*Premissas!$D$39 -> 1051.8453 | R98: =R6*Premissas!$D$39 -> 1262.6819 | S98: =S6*Premissas!$D$39 -> 1184.8271 | T98: =T6*Premissas!$E$39 -> 1428.0837 | U98: =U6*Premissas!$E$39 -> 1380.8212 | V98: =V6*Premissas!$E$39 -> 1311.1563 | W98: =W6*Premissas!$E$39 -> 1353.0308 | X98: =X6*Premissas!$E$39 -> 1205.6664 | Y98: =Y6*Premissas!$E$39 -> 1382.9008 | Z98: =Z6*Premissas!$E$39 -> 1379.876 | AA98: =AA6*Premissas!$E$39 -> 1291.4005 | AB98: =AB6*Premissas!$F$39 -> 859.2724 | AC98: =AC6*Premissas!$F$39 -> 904.45714 | AD98: =AD6*Premissas!$F$39 -> 1085.7505 | AE98: =AE6*Premissas!$F$39 -> 1018.805 | AF98: =AF6*Premissas!$F$39 -> 1047.0108 | AG98: =AG6*Premissas!$F$39 -> 1012.36 | AH98: =AH6*Premissas!$G$39 -> 1029.9478 | AI98: =AI6*Premissas!$G$39 -> 1062.8413 | AJ98: =AJ6*Premissas!$G$39 -> 947.08267 | AK98: =AK6*Premissas!$G$39 -> 1086.3049 | AL98: =AL6*Premissas!$G$39 -> 1083.9289 | AM98: =AM6*Premissas!$G$39 -> 1014.4291 | AN98: =AN6*Premissas!$H$39 -> 867.18998 | AO98: =AO6*Premissas!$H$39 -> 912.79107 | AP98: =AP6*Premissas!$H$39 -> 1095.7549 | AQ98: =AQ6*Premissas!$H$39 -> 1028.1926 | AR98: =AR6*Premissas!$H$39 -> 1056.6583 | AS98: =AS6*Premissas!$H$39 -> 1021.6881 | AT98: =AT6*Premissas!$I$39 -> 1038.462 | AU98: =AU6*Premissas!$I$39 -> 1071.6275 | AV98: =AV6*Premissas!$I$39 -> 954.91188 | AW98: =AW6*Premissas!$I$39 -> 1095.2851 | AX98: =AX6*Premissas!$I$39 -> 1092.8893 | AY98: =AY6*Premissas!$I$39 -> 1022.8151 | AZ98: =AZ6*Premissas!$J$39 -> 1190.9816 | BA98: =BA6*Premissas!$J$39 -> 1253.6093 | BB98: =BB6*Premissas!$J$39 -> 1504.8882 | BC98: =BC6*Premissas!$J$39 -> 1412.0994 | BD98: =BD6*Premissas!$J$39 -> 1451.1937 | BE98: =BE6*Premissas!$J$39 -> 1403.1663 | BF98: =BF6*Premissas!$K$39 -> 598.20876 | BG98: =BG6*Premissas!$K$39 -> 617.31384 | BH98: =BH6*Premissas!$K$39 -> 550.0795 | BI98: =BI6*Premissas!$K$39 -> 630.94184 | BJ98: =BJ6*Premissas!$K$39 -> 629.56179 | BK98: =BK6*Premissas!$K$39 -> 589.19531 | BL98: =BL6*Premissas!$L$39 -> 3350.3607 | BM98: =BM6*Premissas!$L$39 -> 3526.5391 | BN98: =BN6*Premissas!$L$39 -> 4233.4141 | BO98: =BO6*Premissas!$L$39 -> 3972.3891 | BP98: =BP6*Premissas!$L$39 -> 4082.3655 | BQ98: =BQ6*Premissas!$L$39 -> 3947.2594 | BR98: =BR6*Premissas!$M$39 -> 3780.0275 | BS98: =BS6*Premissas!$M$39 -> 3900.7508 | BT98: =BT6*Premissas!$M$39 -> 3475.903 | BU98: =BU6*Premissas!$M$39 -> 3986.8649 | BV98: =BV6*Premissas!$M$39 -> 3978.1445 | BW98: =BW6*Premissas!$M$39 -> 3723.0723 | BX98: =BX6*Premissas!$N$39 -> 3340.7329 | BY98: =BY6*Premissas!$N$39 -> 3516.4049 | BZ98: =BZ6*Premissas!$N$39 -> 4221.2486 | CA98: =CA6*Premissas!$N$39 -> 3960.9738 | CB98: =CB6*Premissas!$N$39 -> 4070.6341 | CC98: =CC6*Premissas!$N$39 -> 3935.9162 | CD98: =CD6*Premissas!$O$39 -> 3768.9383 | CE98: =CE6*Premissas!$O$39 -> 3889.3073 | CF98: =CF6*Premissas!$O$39 -> 3465.706 | CG98: =CG6*Premissas!$O$39 -> 3975.1688 | CH98: =CH6*Premissas!$O$39 -> 3966.474 | CI98: =CI6*Premissas!$O$39 -> 3712.1501 | CJ98: =CJ6*Premissas!$P$39 -> 3331.0828 | CK98: =CK6*Premissas!$P$39 -> 3506.2474 | CL98: =CL6*Premissas!$P$39 -> 4209.0551 | CM98: =CM6*Premissas!$P$39 -> 3949.5321 | CN98: =CN6*Premissas!$P$39 -> 4058.8756 | CO98: =CO6*Premissas!$P$39 -> 3924.5469 | CP98: =CP6*Premissas!$Q$39 -> 3757.8265 | CQ98: =CQ6*Premissas!$Q$39 -> 3877.8407 | CR98: =CR6*Premissas!$Q$39 -> 3455.4882 | CS98: =CS6*Premissas!$Q$39 -> 3963.4491 | CT98: =CT6*Premissas!$Q$39 -> 3954.7799 | CU98: =CU6*Premissas!$Q$39 -> 3701.2058 | CV98: =CV6*Premissas!$R$39 -> 3321.41 | CW98: =CW6*Premissas!$R$39 -> 3496.0659 | CX98: =CX6*Premissas!$R$39 -> 4196.8328 | CY98: =CY6*Premissas!$R$39 -> 3938.0634 | CZ98: =CZ6*Premissas!$R$39 -> 4047.0894 | DA98: =DA6*Premissas!$R$39 -> 3913.1508 | DB98: =DB6*Premissas!$S$39 -> 0 | DC98: =DC6*Premissas!$S$39 -> 0 | DD98: =DD6*Premissas!$S$39 -> 0 | DE98: =DE6*Premissas!$S$39 -> 0 | DF98: =DF6*Premissas!$S$39 -> 0 | DG98: =DG6*Premissas!$S$39 -> 0 | DH98: =DH6*Premissas!$T$39 -> 0 | DI98: =DI6*Premissas!$T$39 -> 0 | DJ98: =DJ6*Premissas!$T$39 -> 0 | DK98: =DK6*Premissas!$T$39 -> 0 | DL98: =DL6*Premissas!$T$39 -> 0 | DM98: =DM6*Premissas!$T$39 -> 0 | DN98: =DN6*Premissas!$U$39 -> 0 | DO98: =DO6*Premissas!$U$39 -> 0 | DP98: =DP6*Premissas!$U$39 -> 0 | DQ98: =DQ6*Premissas!$U$39 -> 0 | DR98: =DR6*Premissas!$U$39 -> 0 | DS98: =DS6*Premissas!$U$39 -> 0
A99: Banco início mês COM Helexia (kWh) | B99: =AA99 -> 8252.1891 | C99: — | D99: =0 -> 0 | E99: =D101 -> 0 | F99: =E101 -> 0 | G99: =F101 -> 186.688 | H99: =G101 -> 408.552 | I99: =H101 -> 1187.864 | J99: =I101 -> 1928.176 | K99: =J101 -> 2671.47 | L99: =K101 -> 3397.107 | ... DS99: =DR101 -> 102773.57
A100: Bank draw COM Helexia (kWh) | B100: =SUM(D100:BQ100) -> 4354.9552 | C100: =B100/60 -> 72.582586 | D100: =MIN(D99,MAX(D97-D98,0)) -> 0 | E100: =MIN(E99,MAX(E97-E98,0)) -> 0 | F100: =MIN(F99,MAX(F97-F98,0)) -> 0 | G100: =MIN(G99,MAX(G97-G98,0)) -> 0 | H100: =MIN(H99,MAX(H97-H98,0)) -> 0 | I100: =MIN(I99,MAX(I97-I98,0)) -> 0 | J100: =MIN(J99,MAX(J97-J98,0)) -> 0 | K100: =MIN(K99,MAX(K97-K98,0)) -> 0 | ... DS100: =MIN(DS99,MAX(DS97-DS98,0)) -> 1467
A101: ★ Banco fim mês COM Helexia (kWh) | B101: =AA101 -> 8368.5896 | C101: — | D101: =MAX(D99-D100,0)+MAX(D98-D97,0) -> 0 | E101: =MAX(E99-E100,0)+MAX(E98-E97,0) -> 0 | F101: =MAX(F99-F100,0)+MAX(F98-F97,0) -> 186.688 | G101: =MAX(G99-G100,0)+MAX(G98-G97,0) -> 408.552 | H101: =MAX(H99-H100,0)+MAX(H98-H97,0) -> 1187.864 | I101: =MAX(I99-I100,0)+MAX(I98-I97,0) -> 1928.176 | J101: =MAX(J99-J100,0)+MAX(J98-J97,0) -> 2671.47 | K101: =MAX(K99-K100,0)+MAX(K98-K97,0) -> 3397.107 | ... DS101: =MAX(DS99-DS100,0)+MAX(DS98-DS97,0) -> 101306.57
A102: Banco início mês SEM Helexia (kWh) | B102: =AA102 -> 0 | C102: — | D102: =0 -> 0 | E102: =D104 -> 0 | F102: =E104 -> 0 | G102: =F104 -> 0 | H102: =G104 -> 0 | I102: =H104 -> 0 | J102: =I104 -> 0 | K102: =J104 -> 0 | L102: =K104 -> 0 | ... DS102: =DR104 -> 0
A103: Bank draw SEM Helexia (kWh) | B103: =SUM(D103:BQ103) -> 0 | C103: =B103/60 -> 0 | D103: =MIN(D102,D97) -> 0 | E103: =MIN(E102,E97) -> 0 | F103: =MIN(F102,F97) -> 0 | G103: =MIN(G102,G97) -> 0 | H103: =MIN(H102,H97) -> 0 | I103: =MIN(I102,I97) -> 0 | J103: =MIN(J102,J97) -> 0 | K103: =MIN(K102,K97) -> 0 | ... DS103: =MIN(DS102,DS97) -> 0
A104: Banco fim mês SEM Helexia (kWh) | B104: =AA104 -> 0 | C104: — | D104: =MAX(D102-D103,0) -> 0 | E104: =MAX(E102-E103,0) -> 0 | F104: =MAX(F102-F103,0) -> 0 | G104: =MAX(G102-G103,0) -> 0 | H104: =MAX(H102-H103,0) -> 0 | I104: =MAX(I102-I103,0) -> 0 | J104: =MAX(J102-J103,0) -> 0 | K104: =MAX(K102-K103,0) -> 0 | ... DS104: =MAX(DS102-DS103,0) -> 0
A105: =" Custo SEM Helexia (R$) — só gen própria, sem "&INDEX(PVSYST_Helexia!$A$5:$A$7,MATCH(Premissas!$B$13,PVSYST_Helexia!$B$5:$B$7,0))&"/BAT/banco" -> Custo SEM Helexia (R$) — só gen própria, sem HCS03/BAT/banco | B105: =SUM(D105:BQ105) -> 60457.694 | C105: =B105/60 -> 1007.6282 | D105: =D97*Premissas!$F$19 -> 987.49881 | E105: =E97*Premissas!$F$19 -> 832.01634 | F105: =F97*Premissas!$F$19 -> 755.20059 | G105: =G97*Premissas!$F$19 -> 665.42797 | H105: =H97*Premissas!$F$19 -> 872.73794 | I105: =I97*Premissas!$F$19 -> 856.0791 | J105: =J97*Premissas!$F$19 -> 775.56139 | K105: =K97*Premissas!$F$19 -> 831.09085 | ... DS105: =DS97*Premissas!$F$19 -> 1357.6952
A106: Custo COM Helexia — rede remanescente (R$) | B106: =SUM(D106:BQ106) -> 390.09442 | C106: =B106/60 -> 6.5015737 | D106: =IF(D101>0,0,MAX(D97-D98-D99,0)*Premissas!$B$7) -> 316.36056 | E106: =IF(E101>0,0,MAX(E97-E98-E99,0)*Premissas!$B$7) -> 73.733862 | F106: =IF(F101>0,0,MAX(F97-F98-F99,0)*Premissas!$B$7) -> 0 | G106: =IF(G101>0,0,MAX(G97-G98-G99,0)*Premissas!$B$7) -> 0 | H106: =IF(H101>0,0,MAX(H97-H98-H99,0)*Premissas!$B$7) -> 0 | I106: =IF(I101>0,0,MAX(I97-I98-I99,0)*Premissas!$B$7) -> 0 | J106: =IF(J101>0,0,MAX(J97-J98-J99,0)*Premissas!$B$7) -> 0 | K106: =IF(K101>0,0,MAX(K97-K98-K99,0)*Premissas!$B$7) -> 0 | ... DS106: =IF(DS101>0,0,MAX(DS97-DS98-DS99,0)*Premissas!$B$7) -> 0
...

Sheet Dados_Produção_Copasul

Sheet Amandina
A1: Unidade | B1: Data | C1: Geração (kWh) | D1: Yf Diário (kWh/kWp)
A2: Amandina | B2: 45716 | C2: 190.1 | D2: =IFERROR(C2/VLOOKUP(A2,Usinas!$A:$B,2,FALSE()),"") -> 0.27274032 | F2: Geração Mensal | H2: Mês | I2: Kwh | J2: MWh | L2: Proxi Bataypora | P2: proxy Rate | Q2: 0.8
A3: Amandina | B3: 45717 | C3: 249.5 | D3: =IFERROR(C3/VLOOKUP(A3,Usinas!$A:$B,2,FALSE()),"") -> 0.3579627 | F3: 45658 | G3: =+F3+30 -> 45688 | H3: =+F3 -> 45658 | I3: 0 | J3: 0 | L3: =+Batayporã!J3*Amandina!$Q$2 -> 91.4072
A4: Amandina | B4: 45718 | C4: 295.9 | D4: =IFERROR(C4/VLOOKUP(A4,Usinas!$A:$B,2,FALSE()),"") -> 0.42453372 | F4: =+B2 -> 45716 | G4: =+F4 -> 45716 | H4: =+F4 -> 45716 | I4: =SUMIFS($C$1:$C$366, $B$1:$B$366, ">="&F4, $B$1:$B$366, "<="&G4) -> 190.1 | J4: =+I4/1000 -> 0.1901 | L4: =+Batayporã!J4*Amandina!$Q$2 -> 72.90552
A5: Amandina | B5: 45719 | C5: 250.2 | D5: =IFERROR(C5/VLOOKUP(A5,Usinas!$A:$B,2,FALSE()),"") -> 0.358967 | F5: =+G4+1 -> 45717 | G5: =+F5+30 -> 45747 | H5: =+F5 -> 45717 | I5: =SUMIFS($C$1:$C$366, $B$1:$B$366, ">="&F5, $B$1:$B$366, "<="&G5) -> 7913.8 | J5: =+I5/1000 -> 7.9138 | L5: =+Batayporã!J5*Amandina!$Q$2 -> 82.44952
A6: Amandina | B6: 45720 | C6: 256.6 | D6: =IFERROR(C6/VLOOKUP(A6,Usinas!$A:$B,2,FALSE()),"") -> 0.36814921 | F6: =+G5+1 -> 45748 | G6: =+F6+29 -> 45777 | H6: =+F6 -> 45748 | I6: =SUMIFS($C$1:$C$366, $B$1:$B$366, ">="&F6, $B$1:$B$366, "<="&G6) -> 23902.8 | J6: =+I6/1000 -> 23.9028 | L6: =+Batayporã!J6*Amandina!$Q$2 -> 58.96776
A7: Amandina | B7: 45721 | C7: 241 | D7: =IFERROR(C7/VLOOKUP(A7,Usinas!$A:$B,2,FALSE()),"") -> 0.34576758 | F7: =+G6+1 -> 45778 | G7: =+F7+30 -> 45808 | H7: =+F7 -> 45778 | I7: =SUMIFS($C$1:$C$366, $B$1:$B$366, ">="&F7, $B$1:$B$366, "<="&G7) -> 28781.7 | J7: =+I7/1000 -> 28.7817 | L7: =+Batayporã!J7*Amandina!$Q$2 -> 73.29328
A8: Amandina | B8: 45722 | C8: 194.3 | D8: =IFERROR(C8/VLOOKUP(A8,Usinas!$A:$B,2,FALSE()),"") -> 0.27876614 | F8: =+G7+1 -> 45809 | G8: =+F8+29 -> 45838 | H8: =+F8 -> 45809 | I8: =SUMIFS($C$1:$C$366, $B$1:$B$366, ">="&F8, $B$1:$B$366, "<="&G8) -> 20798.2 | J8: =+I8/1000 -> 20.7982 | L8: =+Batayporã!J8*Amandina!$Q$2 -> 57.82952
A9: Amandina | B9: 45723 | C9: 89.9 | D9: =IFERROR(C9/VLOOKUP(A9,Usinas!$A:$B,2,FALSE()),"") -> 0.12898135 | F9: =+G8+1 -> 45839 | G9: =+F9+30 -> 45869 | H9: =+F9 -> 45839 | I9: =SUMIFS($C$1:$C$366, $B$1:$B$366, ">="&F9, $B$1:$B$366, "<="&G9) -> 37317.8 | J9: =+I9/1000 -> 37.3178 | L9: =+Batayporã!J9*Amandina!$Q$2 -> 70.66944
A10: Amandina | B10: 45724 | C10: 357.6 | D10: =IFERROR(C10/VLOOKUP(A10,Usinas!$A:$B,2,FALSE()),"") -> 0.51305595 | F10: =+G9+1 -> 45870 | G10: =+F10+30 -> 45900 | H10: =+F10 -> 45870 | I10: =SUMIFS($C$1:$C$366, $B$1:$B$366, ">="&F10, $B$1:$B$366, "<="&G10) -> 16177.9 | J10: =+I10/1000 -> 16.1779 | L10: =+Batayporã!J10*Amandina!$Q$2 -> 74.46616
A11: Amandina | B11: 45725 | C11: 287 | D11: =IFERROR(C11/VLOOKUP(A11,Usinas!$A:$B,2,FALSE()),"") -> 0.41176471 | F11: =+G10+1 -> 45901 | G11: =+F11+29 -> 45930 | H11: =+F11 -> 45901 | I11: =SUMIFS($C$1:$C$366, $B$1:$B$366, ">="&F11, $B$1:$B$366, "<="&G11) -> 37738.8 | J11: =+I11/1000 -> 37.7388 | L11: =+Batayporã!J11*Amandina!$Q$2 -> 75.54672
A12: Amandina | B12: 45726 | C12: 248.1 | D12: =IFERROR(C12/VLOOKUP(A12,Usinas!$A:$B,2,FALSE()),"") -> 0.35595409 | F12: =+G11+1 -> 45931 | G12: =+F12+30 -> 45961 | H12: =+F12 -> 45931 | I12: =SUMIFS($C$1:$C$366, $B$1:$B$366, ">="&F12, $B$1:$B$366, "<="&G12) -> 40322 | J12: =+I12/1000 -> 40.322 | L12: =+Batayporã!J12*Amandina!$Q$2 -> 76.72544
A13: Amandina | B13: 45727 | C13: 142.1 | D13: =IFERROR(C13/VLOOKUP(A13,Usinas!$A:$B,2,FALSE()),"") -> 0.20387374 | F13: =+G12+1 -> 45962 | G13: =+F13+29 -> 45991 | H13: =+F13 -> 45962 | I13: =SUMIFS($C$1:$C$366, $B$1:$B$366, ">="&F13, $B$1:$B$366, "<="&G13) -> 36462.9 | J13: =+I13/1000 -> 36.4629 | L13: =+Batayporã!J13*Amandina!$Q$2 -> 86.38448
A14: Amandina | B14: 45728 | C14: 224.8 | D14: =IFERROR(C14/VLOOKUP(A14,Usinas!$A:$B,2,FALSE()),"") -> 0.32252511 | F14: =+G13+1 -> 45992 | G14: =+F14+30 -> 46022 | H14: =+F14 -> 45992 | I14: =SUMIFS($C$1:$C$366, $B$1:$B$366, ">="&F14, $B$1:$B$366, "<="&G14) -> 19968.1 | J14: =+I14/1000 -> 19.9681 | L14: =+Batayporã!J14*Amandina!$Q$2 -> 85.28312
A15: Amandina | B15: 45729 | C15: 242.3 | D15: =IFERROR(C15/VLOOKUP(A15,Usinas!$A:$B,2,FALSE()),"") -> 0.34763271
A16: Amandina | B16: 45730 | C16: 288.4 | D16: =IFERROR(C16/VLOOKUP(A16,Usinas!$A:$B,2,FALSE()),"") -> 0.41377331
A17: Amandina | B17: 45731 | C17: 347.5 | D17: =IFERROR(C17/VLOOKUP(A17,Usinas!$A:$B,2,FALSE()),"") -> 0.49856528 | L17: =+SUM(L2:L14) -> 905.92816
A18: Amandina | B18: 45732 | C18: 310.4 | D18: =IFERROR(C18/VLOOKUP(A18,Usinas!$A:$B,2,FALSE()),"") -> 0.44533716
A19: Amandina | B19: 45733 | C19: 278 | D19: =IFERROR(C19/VLOOKUP(A19,Usinas!$A:$B,2,FALSE()),"") -> 0.39885222
A20: Amandina | B20: 45734 | C20: 222.1 | D20: =IFERROR(C20/VLOOKUP(A20,Usinas!$A:$B,2,FALSE()),"") -> 0.31865136
A21: Amandina | B21: 45735 | C21: 332.3 | D21: =IFERROR(C21/VLOOKUP(A21,Usinas!$A:$B,2,FALSE()),"") -> 0.47675753
A22: Amandina | B22: 45736 | C22: 318.3 | D22: =IFERROR(C22/VLOOKUP(A22,Usinas!$A:$B,2,FALSE()),"") -> 0.45667145
A23: Amandina | B23: 45737 | C23: 321.4 | D23: =IFERROR(C23/VLOOKUP(A23,Usinas!$A:$B,2,FALSE()),"") -> 0.46111908
A24: Amandina | B24: 45738 | C24: 272.8 | D24: =IFERROR(C24/VLOOKUP(A24,Usinas!$A:$B,2,FALSE()),"") -> 0.39139168
A25: Amandina | B25: 45739 | C25: 250.5 | D25: =IFERROR(C25/VLOOKUP(A25,Usinas!$A:$B,2,FALSE()),"") -> 0.35939742
A26: Amandina | B26: 45740 | C26: 281.2 | D26: =IFERROR(C26/VLOOKUP(A26,Usinas!$A:$B,2,FALSE()),"") -> 0.40344333
A27: Amandina | B27: 45741 | C27: 264.2 | D27: =IFERROR(C27/VLOOKUP(A27,Usinas!$A:$B,2,FALSE()),"") -> 0.37905308
A28: Amandina | B28: 45742 | C28: 275 | D28: =IFERROR(C28/VLOOKUP(A28,Usinas!$A:$B,2,FALSE()),"") -> 0.39454806
A29: Amandina | B29: 45743 | C29: 297 | D29: =IFERROR(C29/VLOOKUP(A29,Usinas!$A:$B,2,FALSE()),"") -> 0.42611191
... A356: Amandina | B356: 46022 | C356: 990.9 | D356: =IFERROR(C356/VLOOKUP(A356,Usinas!$A:$B,2,FALSE()),"") -> 1.4216643

Sheet Batayporã
A1: Unidade | B1: Data | C1: Geração (kWh) | D1: Yf Diário (kWh/kWp)
A2: Batayporã | B2: 45658 | C2: 3715.4 | D2: =IFERROR(C2/VLOOKUP(A2,Usinas!$A:$B,2,FALSE()),"") -> 5.2925926 | F2: Geração Mensal | H2: Mês | I2: Kwh | J2: MWh
A3: Batayporã | B3: 45659 | C3: 2498.6 | D3: =IFERROR(C3/VLOOKUP(A3,Usinas!$A:$B,2,FALSE()),"") -> 3.5592593 | F3: =+B2 -> 45658 | G3: =+B32 -> 45688 | H3: =+F3 -> 45658 | I3: =SUMIFS($C$1:$C$366, $B$1:$B$366, ">="&F3, $B$1:$B$366, "<="&G3) -> 114259 | J3: =+I3/1000 -> 114.259
A4: Batayporã | B4: 45660 | C4: 4061.9 | D4: =IFERROR(C4/VLOOKUP(A4,Usinas!$A:$B,2,FALSE()),"") -> 5.7861823 | F4: =+B33 -> 45689 | G4: =+F4+27 -> 45716 | H4: =+F4 -> 45689 | I4: =SUMIFS($C$1:$C$366, $B$1:$B$366, ">="&F4, $B$1:$B$366, "<="&G4) -> 91131.9 | J4: =+I4/1000 -> 91.1319
A5: Batayporã | B5: 45661 | C5: 3262.5 | D5: =IFERROR(C5/VLOOKUP(A5,Usinas!$A:$B,2,FALSE()),"") -> 4.6474359 | F5: =+G4+1 -> 45717 | G5: =+F5+30 -> 45747 | H5: =+F5 -> 45717 | I5: =SUMIFS($C$1:$C$366, $B$1:$B$366, ">="&F5, $B$1:$B$366, "<="&G5) -> 103061.9 | J5: =+I5/1000 -> 103.0619
A6: Batayporã | B6: 45662 | C6: 4061 | D6: =IFERROR(C6/VLOOKUP(A6,Usinas!$A:$B,2,FALSE()),"") -> 5.7849003 | F6: =+G5+1 -> 45748 | G6: =+F6+29 -> 45777 | H6: =+F6 -> 45748 | I6: =SUMIFS($C$1:$C$366, $B$1:$B$366, ">="&F6, $B$1:$B$366, "<="&G6) -> 73709.7 | J6: =+I6/1000 -> 73.7097
A7: Batayporã | B7: 45663 | C7: 4431.9 | D7: =IFERROR(C7/VLOOKUP(A7,Usinas!$A:$B,2,FALSE()),"") -> 6.3132479 | F7: =+G6+1 -> 45778 | G7: =+F7+30 -> 45808 | H7: =+F7 -> 45778 | I7: =SUMIFS($C$1:$C$366, $B$1:$B$366, ">="&F7, $B$1:$B$366, "<="&G7) -> 91616.6 | J7: =+I7/1000 -> 91.6166
A8: Batayporã | B8: 45664 | C8: 4460 | D8: =IFERROR(C8/VLOOKUP(A8,Usinas!$A:$B,2,FALSE()),"") -> 6.3532764 | F8: =+G7+1 -> 45809 | G8: =+F8+29 -> 45838 | H8: =+F8 -> 45809 | I8: =SUMIFS($C$1:$C$366, $B$1:$B$366, ">="&F8, $B$1:$B$366, "<="&G8) -> 72286.9 | J8: =+I8/1000 -> 72.2869
A9: Batayporã | B9: 45665 | C9: 3524.3 | D9: =IFERROR(C9/VLOOKUP(A9,Usinas!$A:$B,2,FALSE()),"") -> 5.0203704 | F9: =+G8+1 -> 45839 | G9: =+F9+30 -> 45869 | H9: =+F9 -> 45839 | I9: =SUMIFS($C$1:$C$366, $B$1:$B$366, ">="&F9, $B$1:$B$366, "<="&G9) -> 88336.8 | J9: =+I9/1000 -> 88.3368
A10: Batayporã | B10: 45666 | C10: 4744.5 | D10: =IFERROR(C10/VLOOKUP(A10,Usinas!$A:$B,2,FALSE()),"") -> 6.758547 | F10: =+G9+1 -> 45870 | G10: =+F10+30 -> 45900 | H10: =+F10 -> 45870 | I10: =SUMIFS($C$1:$C$366, $B$1:$B$366, ">="&F10, $B$1:$B$366, "<="&G10) -> 93082.7 | J10: =+I10/1000 -> 93.0827
A11: Batayporã | B11: 45667 | C11: 3305 | D11: =IFERROR(C11/VLOOKUP(A11,Usinas!$A:$B,2,FALSE()),"") -> 4.7079772 | F11: =+G10+1 -> 45901 | G11: =+F11+29 -> 45930 | H11: =+F11 -> 45901 | I11: =SUMIFS($C$1:$C$366, $B$1:$B$366, ">="&F11, $B$1:$B$366, "<="&G11) -> 94433.4 | J11: =+I11/1000 -> 94.4334
A12: Batayporã | B12: 45668 | C12: 4671.1 | D12: =IFERROR(C12/VLOOKUP(A12,Usinas!$A:$B,2,FALSE()),"") -> 6.6539886 | F12: =+G11+1 -> 45931 | G12: =+F12+30 -> 45961 | H12: =+F12 -> 45931 | I12: =SUMIFS($C$1:$C$366, $B$1:$B$366, ">="&F12, $B$1:$B$366, "<="&G12) -> 95906.8 | J12: =+I12/1000 -> 95.9068
A13: Batayporã | B13: 45669 | C13: 4211.9 | D13: =IFERROR(C13/VLOOKUP(A13,Usinas!$A:$B,2,FALSE()),"") -> 5.9998575 | F13: =+G12+1 -> 45962 | G13: =+F13+29 -> 45991 | H13: =+F13 -> 45962 | I13: =SUMIFS($C$1:$C$366, $B$1:$B$366, ">="&F13, $B$1:$B$366, "<="&G13) -> 107980.6 | J13: =+I13/1000 -> 107.9806
A14: Batayporã | B14: 45670 | C14: 4327.1 | D14: =IFERROR(C14/VLOOKUP(A14,Usinas!$A:$B,2,FALSE()),"") -> 6.1639601 | F14: =+G13+1 -> 45992 | G14: =+F14+30 -> 46022 | H14: =+F14 -> 45992 | I14: =SUMIFS($C$1:$C$366, $B$1:$B$366, ">="&F14, $B$1:$B$366, "<="&G14) -> 106603.9 | J14: =+I14/1000 -> 106.6039
A15: Batayporã | B15: 45671 | C15: 4370 | D15: =IFERROR(C15/VLOOKUP(A15,Usinas!$A:$B,2,FALSE()),"") -> 6.2250712
A16: Batayporã | B16: 45672 | C16: 4324 | D16: =IFERROR(C16/VLOOKUP(A16,Usinas!$A:$B,2,FALSE()),"") -> 6.1595442
A17: Batayporã | B17: 45673 | C17: 4173.6 | D17: =IFERROR(C17/VLOOKUP(A17,Usinas!$A:$B,2,FALSE()),"") -> 5.9452991
A18: Batayporã | B18: 45674 | C18: 2490.4 | D18: =IFERROR(C18/VLOOKUP(A18,Usinas!$A:$B,2,FALSE()),"") -> 3.5475783
A19: Batayporã | B19: 45675 | C19: 2419.1 | D19: =IFERROR(C19/VLOOKUP(A19,Usinas!$A:$B,2,FALSE()),"") -> 3.4460114
A20: Batayporã | B20: 45676 | C20: 3206.2 | D20: =IFERROR(C20/VLOOKUP(A20,Usinas!$A:$B,2,FALSE()),"") -> 4.5672365
A21: Batayporã | B21: 45677 | C21: 2768 | D21: =IFERROR(C21/VLOOKUP(A21,Usinas!$A:$B,2,FALSE()),"") -> 3.9430199
A22: Batayporã | B22: 45678 | C22: 3998.4 | D22: =IFERROR(C22/VLOOKUP(A22,Usinas!$A:$B,2,FALSE()),"") -> 5.6957265
A23: Batayporã | B23: 45679 | C23: 2927.9 | D23: =IFERROR(C23/VLOOKUP(A23,Usinas!$A:$B,2,FALSE()),"") -> 4.1707977
A24: Batayporã | B24: 45680 | C24: 3035.9 | D24: =IFERROR(C24/VLOOKUP(A24,Usinas!$A:$B,2,FALSE()),"") -> 4.3246439
A25: Batayporã | B25: 45681 | C25: 4013.7 | D25: =IFERROR(C25/VLOOKUP(A25,Usinas!$A:$B,2,FALSE()),"") -> 5.7175214
A26: Batayporã | B26: 45682 | C26: 3852.9 | D26: =IFERROR(C26/VLOOKUP(A26,Usinas!$A:$B,2,FALSE()),"") -> 5.4884615
... A366: Batayporã | B366: 46022 | C366: 3694.2 | D366: =IFERROR(C366/VLOOKUP(A366,Usinas!$A:$B,2,FALSE()),"") -> 5.2623932

Sheet Novo Horizonte do Sul
A1: Unidade | B1: Data | C1: Geração (kWh) | D1: Yf Diário (kWh/kWp)
A2: Novo Horizonte do Sul | B2: 45659 | C2: 1838.7 | D2: =IFERROR(C2/VLOOKUP(A2,Usinas!$A:$B,2,FALSE()),"") -> 2.9608696 | F2: Geração Mensal | H2: Mês | I2: Kwh | J2: MWh
A3: Novo Horizonte do Sul | B3: 45660 | C3: 2731.7 | D3: =IFERROR(C3/VLOOKUP(A3,Usinas!$A:$B,2,FALSE()),"") -> 4.3988728 | F3: =+B2 -> 45659 | G3: =+F3+29 -> 45688 | H3: =+F3 -> 45659 | I3: =SUMIFS($C$1:$C$366, $B$1:$B$366, ">="&F3, $B$1:$B$366, "<="&G3) -> 83461.9 | J3: =+I3/1000 -> 83.4619
A4: Novo Horizonte do Sul | B4: 45661 | C4: 3144 | D4: =IFERROR(C4/VLOOKUP(A4,Usinas!$A:$B,2,FALSE()),"") -> 5.0628019 | F4: =+G3+1 -> 45689 | G4: =+F4+27 -> 45716 | H4: =+F4 -> 45689 | I4: =SUMIFS($C$1:$C$366, $B$1:$B$366, ">="&F4, $B$1:$B$366, "<="&G4) -> 76124.4 | J4: =+I4/1000 -> 76.1244
A5: Novo Horizonte do Sul | B5: 45662 | C5: 3472.1 | D5: =IFERROR(C5/VLOOKUP(A5,Usinas!$A:$B,2,FALSE()),"") -> 5.5911433 | F5: =+G4+1 -> 45717 | G5: =+F5+30 -> 45747 | H5: =+F5 -> 45717 | I5: =SUMIFS($C$1:$C$366, $B$1:$B$366, ">="&F5, $B$1:$B$366, "<="&G5) -> 89858.2 | J5: =+I5/1000 -> 89.8582
A6: Novo Horizonte do Sul | B6: 45663 | C6: 3397.4 | D6: =IFERROR(C6/VLOOKUP(A6,Usinas!$A:$B,2,FALSE()),"") -> 5.4708535 | F6: =+G5+1 -> 45748 | G6: =+F6+29 -> 45777 | H6: =+F6 -> 45748 | I6: =SUMIFS($C$1:$C$366, $B$1:$B$366, ">="&F6, $B$1:$B$366, "<="&G6) -> 62725.4 | J6: =+I6/1000 -> 62.7254
A7: Novo Horizonte do Sul | B7: 45664 | C7: 3375.8 | D7: =IFERROR(C7/VLOOKUP(A7,Usinas!$A:$B,2,FALSE()),"") -> 5.4360709 | F7: =+G6+1 -> 45778 | G7: =+F7+30 -> 45808 | H7: =+F7 -> 45778 | I7: =SUMIFS($C$1:$C$366, $B$1:$B$366, ">="&F7, $B$1:$B$366, "<="&G7) -> 78227.5 | J7: =+I7/1000 -> 78.2275
A8: Novo Horizonte do Sul | B8: 45665 | C8: 3146.5 | D8: =IFERROR(C8/VLOOKUP(A8,Usinas!$A:$B,2,FALSE()),"") -> 5.0668277 | F8: =+G7+1 -> 45809 | G8: =+F8+29 -> 45838 | H8: =+F8 -> 45809 | I8: =SUMIFS($C$1:$C$366, $B$1:$B$366, ">="&F8, $B$1:$B$366, "<="&G8) -> 60380.6 | J8: =+I8/1000 -> 60.3806
A9: Novo Horizonte do Sul | B9: 45666 | C9: 3235.6 | D9: =IFERROR(C9/VLOOKUP(A9,Usinas!$A:$B,2,FALSE()),"") -> 5.210306 | F9: =+G8+1 -> 45839 | G9: =+F9+30 -> 45869 | H9: =+F9 -> 45839 | I9: =SUMIFS($C$1:$C$366, $B$1:$B$366, ">="&F9, $B$1:$B$366, "<="&G9) -> 76551.2 | J9: =+I9/1000 -> 76.5512
A10: Novo Horizonte do Sul | B10: 45667 | C10: 2990.9 | D10: =IFERROR(C10/VLOOKUP(A10,Usinas!$A:$B,2,FALSE()),"") -> 4.8162641 | F10: =+G9+1 -> 45870 | G10: =+F10+30 -> 45900 | H10: =+F10 -> 45870 | I10: =SUMIFS($C$1:$C$366, $B$1:$B$366, ">="&F10, $B$1:$B$366, "<="&G10) -> 79815.6 | J10: =+I10/1000 -> 79.8156
A11: Novo Horizonte do Sul | B11: 45668 | C11: 3034 | D11: =IFERROR(C11/VLOOKUP(A11,Usinas!$A:$B,2,FALSE()),"") -> 4.8856683 | F11: =+G10+1 -> 45901 | G11: =+F11+29 -> 45930 | H11: =+F11 -> 45901 | I11: =SUMIFS($C$1:$C$366, $B$1:$B$366, ">="&F11, $B$1:$B$366, "<="&G11) -> 78203 | J11: =+I11/1000 -> 78.203
A12: Novo Horizonte do Sul | B12: 45669 | C12: 3316.5 | D12: =IFERROR(C12/VLOOKUP(A12,Usinas!$A:$B,2,FALSE()),"") -> 5.3405797 | F12: =+G11+1 -> 45931 | G12: =+F12+30 -> 45961 | H12: =+F12 -> 45931 | I12: =SUMIFS($C$1:$C$366, $B$1:$B$366, ">="&F12, $B$1:$B$366, "<="&G12) -> 73160.1 | J12: =+I12/1000 -> 73.1601
A13: Novo Horizonte do Sul | B13: 45670 | C13: 3271.8 | D13: =IFERROR(C13/VLOOKUP(A13,Usinas!$A:$B,2,FALSE()),"") -> 5.268599 | F13: =+G12+1 -> 45962 | G13: =+F13+29 -> 45991 | H13: =+F13 -> 45962 | I13: =SUMIFS($C$1:$C$366, $B$1:$B$366, ">="&F13, $B$1:$B$366, "<="&G13) -> 91030.5 | J13: =+I13/1000 -> 91.0305
A14: Novo Horizonte do Sul | B14: 45671 | C14: 2991 | D14: =IFERROR(C14/VLOOKUP(A14,Usinas!$A:$B,2,FALSE()),"") -> 4.8164251 | F14: =+G13+1 -> 45992 | G14: =+F14+30 -> 46022 | H14: =+F14 -> 45992 | I14: =SUMIFS($C$1:$C$366, $B$1:$B$366, ">="&F14, $B$1:$B$366, "<="&G14) -> 88631.7 | J14: =+I14/1000 -> 88.6317
A15: Novo Horizonte do Sul | B15: 45672 | C15: 3157.2 | D15: =IFERROR(C15/VLOOKUP(A15,Usinas!$A:$B,2,FALSE()),"") -> 5.084058
A16: Novo Horizonte do Sul | B16: 45673 | C16: 3240.1 | D16: =IFERROR(C16/VLOOKUP(A16,Usinas!$A:$B,2,FALSE()),"") -> 5.2175523
A17: Novo Horizonte do Sul | B17: 45674 | C17: 2894.7 | D17: =IFERROR(C17/VLOOKUP(A17,Usinas!$A:$B,2,FALSE()),"") -> 4.6613527 | J17: =+SUM(J3:J14) -> 938.1701
A18: Novo Horizonte do Sul | B18: 45675 | C18: 1963.6 | D18: =IFERROR(C18/VLOOKUP(A18,Usinas!$A:$B,2,FALSE()),"") -> 3.1619968
A19: Novo Horizonte do Sul | B19: 45676 | C19: 2656 | D19: =IFERROR(C19/VLOOKUP(A19,Usinas!$A:$B,2,FALSE()),"") -> 4.2769726
A20: Novo Horizonte do Sul | B20: 45677 | C20: 1379.4 | D20: =IFERROR(C20/VLOOKUP(A20,Usinas!$A:$B,2,FALSE()),"") -> 2.221256
A21: Novo Horizonte do Sul | B21: 45678 | C21: 2442.7 | D21: =IFERROR(C21/VLOOKUP(A21,Usinas!$A:$B,2,FALSE()),"") -> 3.9334944
A22: Novo Horizonte do Sul | B22: 45679 | C22: 2855.3 | D22: =IFERROR(C22/VLOOKUP(A22,Usinas!$A:$B,2,FALSE()),"") -> 4.5979066
A23: Novo Horizonte do Sul | B23: 45680 | C23: 1825.6 | D23: =IFERROR(C23/VLOOKUP(A23,Usinas!$A:$B,2,FALSE()),"") -> 2.9397746
A24: Novo Horizonte do Sul | B24: 45681 | C24: 3219.2 | D24: =IFERROR(C24/VLOOKUP(A24,Usinas!$A:$B,2,FALSE()),"") -> 5.1838969
A25: Novo Horizonte do Sul | B25: 45682 | C25: 2932.2 | D25: =IFERROR(C25/VLOOKUP(A25,Usinas!$A:$B,2,FALSE()),"") -> 4.7217391
A26: Novo Horizonte do Sul | B26: 45683 | C26: 2721.4 | D26: =IFERROR(C26/VLOOKUP(A26,Usinas!$A:$B,2,FALSE()),"") -> 4.3822866
A27: Novo Horizonte do Sul | B27: 45684 | C27: 2272 | D27: =IFERROR(C27/VLOOKUP(A27,Usinas!$A:$B,2,FALSE()),"") -> 3.6586151
A28: Novo Horizonte do Sul | B28: 45685 | C28: 2223.6 | D28: =IFERROR(C28/VLOOKUP(A28,Usinas!$A:$B,2,FALSE()),"") -> 3.5806763
A29: Novo Horizonte do Sul | B29: 45686 | C29: 2824.9 | D29: =IFERROR(C29/VLOOKUP(A29,Usinas!$A:$B,2,FALSE()),"") -> 4.5489533
... A364: Novo Horizonte do Sul | B364: 46022 | C364: 2728.3 | D364: =IFERROR(C364/VLOOKUP(A364,Usinas!$A:$B,2,FALSE()),"") -> 4.3933977

Sheet Dados_Consumo_Copasul

Sheet Formula Dados Copasul
D4: 45658 | E4: 45689 | F4: 45717 | G4: 45748 | H4: 45778 | I4: 45809 | J4: 45839 | K4: 45870 | L4: 45901 | M4: 45931 | N4: 45962 | O4: 45992 | Q4: Total | S4: Meia Mensal
A5: Grupo B | B5: Consomo Fora Ponta Grupo B (kWh) | D5: =+SUMIFS('Memória de Massa - 2025'!$H$1:$H$217,'Memória de Massa - 2025'!$A$1:$A$217,'Formula Dados Copasul'!$A5,'Memória de Massa - 2025'!$F$1:$F$217,'Formula Dados Copasul'!D$4) -> 44785.32 | E5: =+SUMIFS('Memória de Massa - 2025'!$H$1:$H$217,'Memória de Massa - 2025'!$A$1:$A$217,'Formula Dados Copasul'!$A5,'Memória de Massa - 2025'!$F$1:$F$217,'Formula Dados Copasul'!E$4) -> 47470.69 | F5: =+SUMIFS('Memória de Massa - 2025'!$H$1:$H$217,'Memória de Massa - 2025'!$A$1:$A$217,'Formula Dados Copasul'!$A5,'Memória de Massa - 2025'!$F$1:$F$217,'Formula Dados Copasul'!F$4) -> 42520.65 | G5: =+SUMIFS('Memória de Massa - 2025'!$H$1:$H$217,'Memória de Massa - 2025'!$A$1:$A$217,'Formula Dados Copasul'!$A5,'Memória de Massa - 2025'!$F$1:$F$217,'Formula Dados Copasul'!G$4) -> 37072.04 | H5: =+SUMIFS('Memória de Massa - 2025'!$H$1:$H$217,'Memória de Massa - 2025'!$A$1:$A$217,'Formula Dados Copasul'!$A5,'Memória de Massa - 2025'!$F$1:$F$217,'Formula Dados Copasul'!H$4) -> 34493.16 | I5: =+SUMIFS('Memória de Massa - 2025'!$H$1:$H$217,'Memória de Massa - 2025'!$A$1:$A$217,'Formula Dados Copasul'!$A5,'Memória de Massa - 2025'!$F$1:$F$217,'Formula Dados Copasul'!I$4) -> 32323.4 | J5: =+SUMIFS('Memória de Massa - 2025'!$H$1:$H$217,'Memória de Massa - 2025'!$A$1:$A$217,'Formula Dados Copasul'!$A5,'Memória de Massa - 2025'!$F$1:$F$217,'Formula Dados Copasul'!J$4) -> 34695.56 | K5: =+SUMIFS('Memória de Massa - 2025'!$H$1:$H$217,'Memória de Massa - 2025'!$A$1:$A$217,'Formula Dados Copasul'!$A5,'Memória de Massa - 2025'!$F$1:$F$217,'Formula Dados Copasul'!K$4) -> 37764.79 | ... O5: =+SUMIFS('Memória de Massa - 2025'!$H$1:$H$217,'Memória de Massa - 2025'!$A$1:$A$217,'Formula Dados Copasul'!$A5,'Memória de Massa - 2025'!$F$1:$F$217,'Formula Dados Copasul'!O$4) -> 48254.06 | Q5: =+SUM(D5:O5) -> 498958.69 | S5: =+Q5/12 -> 41579.891
A6: A4 Verde | B6: Consumo Fora Ponta Grupo A (kWh) | D6: =+SUMIFS('Memória de Massa - 2025'!$H$1:$H$217,'Memória de Massa - 2025'!$A$1:$A$217,'Formula Dados Copasul'!$A6,'Memória de Massa - 2025'!$F$1:$F$217,'Formula Dados Copasul'!D$4) -> 50942.72 | E6: =+SUMIFS('Memória de Massa - 2025'!$H$1:$H$217,'Memória de Massa - 2025'!$A$1:$A$217,'Formula Dados Copasul'!$A6,'Memória de Massa - 2025'!$F$1:$F$217,'Formula Dados Copasul'!E$4) -> 200728.75 | F6: =+SUMIFS('Memória de Massa - 2025'!$H$1:$H$217,'Memória de Massa - 2025'!$A$1:$A$217,'Formula Dados Copasul'!$A6,'Memória de Massa - 2025'!$F$1:$F$217,'Formula Dados Copasul'!F$4) -> 207178.06 | G6: =+SUMIFS('Memória de Massa - 2025'!$H$1:$H$217,'Memória de Massa - 2025'!$A$1:$A$217,'Formula Dados Copasul'!$A6,'Memória de Massa - 2025'!$F$1:$F$217,'Formula Dados Copasul'!G$4) -> 75954.61 | H6: =+SUMIFS('Memória de Massa - 2025'!$H$1:$H$217,'Memória de Massa - 2025'!$A$1:$A$217,'Formula Dados Copasul'!$A6,'Memória de Massa - 2025'!$F$1:$F$217,'Formula Dados Copasul'!H$4) -> 87080.03 | I6: =+SUMIFS('Memória de Massa - 2025'!$H$1:$H$217,'Memória de Massa - 2025'!$A$1:$A$217,'Formula Dados Copasul'!$A6,'Memória de Massa - 2025'!$F$1:$F$217,'Formula Dados Copasul'!I$4) -> 147398.37 | J6: =+SUMIFS('Memória de Massa - 2025'!$H$1:$H$217,'Memória de Massa - 2025'!$A$1:$A$217,'Formula Dados Copasul'!$A6,'Memória de Massa - 2025'!$F$1:$F$217,'Formula Dados Copasul'!J$4) -> 307662.77 | K6: =+SUMIFS('Memória de Massa - 2025'!$H$1:$H$217,'Memória de Massa - 2025'!$A$1:$A$217,'Formula Dados Copasul'!$A6,'Memória de Massa - 2025'!$F$1:$F$217,'Formula Dados Copasul'!K$4) -> 309712.87 | ... O6: =+SUMIFS('Memória de Massa - 2025'!$H$1:$H$217,'Memória de Massa - 2025'!$A$1:$A$217,'Formula Dados Copasul'!$A6,'Memória de Massa - 2025'!$F$1:$F$217,'Formula Dados Copasul'!O$4) -> 11745.55 | Q6: =+SUM(D6:O6) -> 1504995.5 | S6: =+Q6/12 -> 125416.29
A7: A3A rural | B7: Consumo Fora Ponta Grupo A3A Rural (kWh) | D7: =+SUMIFS('Memória de Massa - 2025'!$H$1:$H$217,'Memória de Massa - 2025'!$A$1:$A$217,'Formula Dados Copasul'!$A7,'Memória de Massa - 2025'!$F$1:$F$217,'Formula Dados Copasul'!D$4) -> 72928.49 | E7: =+SUMIFS('Memória de Massa - 2025'!$H$1:$H$217,'Memória de Massa - 2025'!$A$1:$A$217,'Formula Dados Copasul'!$A7,'Memória de Massa - 2025'!$F$1:$F$217,'Formula Dados Copasul'!E$4) -> 212798.25 | F7: =+SUMIFS('Memória de Massa - 2025'!$H$1:$H$217,'Memória de Massa - 2025'!$A$1:$A$217,'Formula Dados Copasul'!$A7,'Memória de Massa - 2025'!$F$1:$F$217,'Formula Dados Copasul'!F$4) -> 177578.42 | G7: =+SUMIFS('Memória de Massa - 2025'!$H$1:$H$217,'Memória de Massa - 2025'!$A$1:$A$217,'Formula Dados Copasul'!$A7,'Memória de Massa - 2025'!$F$1:$F$217,'Formula Dados Copasul'!G$4) -> 84395.43 | H7: =+SUMIFS('Memória de Massa - 2025'!$H$1:$H$217,'Memória de Massa - 2025'!$A$1:$A$217,'Formula Dados Copasul'!$A7,'Memória de Massa - 2025'!$F$1:$F$217,'Formula Dados Copasul'!H$4) -> 106720.74 | I7: =+SUMIFS('Memória de Massa - 2025'!$H$1:$H$217,'Memória de Massa - 2025'!$A$1:$A$217,'Formula Dados Copasul'!$A7,'Memória de Massa - 2025'!$F$1:$F$217,'Formula Dados Copasul'!I$4) -> 183159.59 | J7: =+SUMIFS('Memória de Massa - 2025'!$H$1:$H$217,'Memória de Massa - 2025'!$A$1:$A$217,'Formula Dados Copasul'!$A7,'Memória de Massa - 2025'!$F$1:$F$217,'Formula Dados Copasul'!J$4) -> 223302.56 | K7: =+SUMIFS('Memória de Massa - 2025'!$H$1:$H$217,'Memória de Massa - 2025'!$A$1:$A$217,'Formula Dados Copasul'!$A7,'Memória de Massa - 2025'!$F$1:$F$217,'Formula Dados Copasul'!K$4) -> 130522.46 | ... O7: =+SUMIFS('Memória de Massa - 2025'!$H$1:$H$217,'Memória de Massa - 2025'!$A$1:$A$217,'Formula Dados Copasul'!$A7,'Memória de Massa - 2025'!$F$1:$F$217,'Formula Dados Copasul'!O$4) -> 15428.7 | Q7: =+SUM(D7:O7) -> 1245343.7 | S7: =+Q7/12 -> 103778.64
B9: Total Fora Ponta (kWh) | D9: =+SUM(D5:D7) -> 168656.53 | E9: =+SUM(E5:E7) -> 460997.69 | F9: =+SUM(F5:F7) -> 427277.13 | G9: =+SUM(G5:G7) -> 197422.08 | H9: =+SUM(H5:H7) -> 228293.93 | I9: =+SUM(I5:I7) -> 362881.36 | J9: =+SUM(J5:J7) -> 565660.89 | K9: =+SUM(K5:K7) -> 478000.12 | ... O9: =+SUM(O5:O7) -> 75428.31 | Q9: =+SUM(D9:O9) -> 3249297.9 | S9: =+Q9/12 -> 270774.83
A11: A4 Verde | B11: Consumo Ponta Grupo A (kWh) | D11: =+SUMIFS('Memória de Massa - 2025'!$G$1:$G$217,'Memória de Massa - 2025'!$A$1:$A$217,'Formula Dados Copasul'!$A11,'Memória de Massa - 2025'!$F$1:$F$217,'Formula Dados Copasul'!D$4) -> 10827.94 | E11: =+SUMIFS('Memória de Massa - 2025'!$G$1:$G$217,'Memória de Massa - 2025'!$A$1:$A$217,'Formula Dados Copasul'!$A11,'Memória de Massa - 2025'!$F$1:$F$217,'Formula Dados Copasul'!E$4) -> 37839.9 | F11: =+SUMIFS('Memória de Massa - 2025'!$G$1:$G$217,'Memória de Massa - 2025'!$A$1:$A$217,'Formula Dados Copasul'!$A11,'Memória de Massa - 2025'!$F$1:$F$217,'Formula Dados Copasul'!F$4) -> 27093.4 | G11: =+SUMIFS('Memória de Massa - 2025'!$G$1:$G$217,'Memória de Massa - 2025'!$A$1:$A$217,'Formula Dados Copasul'!$A11,'Memória de Massa - 2025'!$F$1:$F$217,'Formula Dados Copasul'!G$4) -> 4120.62 | H11: =+SUMIFS('Memória de Massa - 2025'!$G$1:$G$217,'Memória de Massa - 2025'!$A$1:$A$217,'Formula Dados Copasul'!$A11,'Memória de Massa - 2025'!$F$1:$F$217,'Formula Dados Copasul'!H$4) -> 7310.48 | I11: =+SUMIFS('Memória de Massa - 2025'!$G$1:$G$217,'Memória de Massa - 2025'!$A$1:$A$217,'Formula Dados Copasul'!$A11,'Memória de Massa - 2025'!$F$1:$F$217,'Formula Dados Copasul'!I$4) -> 22180.07 | J11: =+SUMIFS('Memória de Massa - 2025'!$G$1:$G$217,'Memória de Massa - 2025'!$A$1:$A$217,'Formula Dados Copasul'!$A11,'Memória de Massa - 2025'!$F$1:$F$217,'Formula Dados Copasul'!J$4) -> 53060.15 | K11: =+SUMIFS('Memória de Massa - 2025'!$G$1:$G$217,'Memória de Massa - 2025'!$A$1:$A$217,'Formula Dados Copasul'!$A11,'Memória de Massa - 2025'!$F$1:$F$217,'Formula Dados Copasul'!K$4) -> 44066.23 | ... O11: =+SUMIFS('Memória de Massa - 2025'!$G$1:$G$217,'Memória de Massa - 2025'!$A$1:$A$217,'Formula Dados Copasul'!$A11,'Memória de Massa - 2025'!$F$1:$F$217,'Formula Dados Copasul'!O$4) -> 2595.31 | Q11: =+SUM(D11:O11) -> 224581.82 | S11: =+Q11/12 -> 18715.152
A12: A3A rural | B12: Consumo Ponta Grupo A3A (kWh) | D12: =+SUMIFS('Memória de Massa - 2025'!$G$1:$G$217,'Memória de Massa - 2025'!$A$1:$A$217,'Formula Dados Copasul'!$A12,'Memória de Massa - 2025'!$F$1:$F$217,'Formula Dados Copasul'!D$4) -> 9264.15 | E12: =+SUMIFS('Memória de Massa - 2025'!$G$1:$G$217,'Memória de Massa - 2025'!$A$1:$A$217,'Formula Dados Copasul'!$A12,'Memória de Massa - 2025'!$F$1:$F$217,'Formula Dados Copasul'!E$4) -> 19948.64 | F12: =+SUMIFS('Memória de Massa - 2025'!$G$1:$G$217,'Memória de Massa - 2025'!$A$1:$A$217,'Formula Dados Copasul'!$A12,'Memória de Massa - 2025'!$F$1:$F$217,'Formula Dados Copasul'!F$4) -> 14932.89 | G12: =+SUMIFS('Memória de Massa - 2025'!$G$1:$G$217,'Memória de Massa - 2025'!$A$1:$A$217,'Formula Dados Copasul'!$A12,'Memória de Massa - 2025'!$F$1:$F$217,'Formula Dados Copasul'!G$4) -> 2769.48 | H12: =+SUMIFS('Memória de Massa - 2025'!$G$1:$G$217,'Memória de Massa - 2025'!$A$1:$A$217,'Formula Dados Copasul'!$A12,'Memória de Massa - 2025'!$F$1:$F$217,'Formula Dados Copasul'!H$4) -> 7312.1 | I12: =+SUMIFS('Memória de Massa - 2025'!$G$1:$G$217,'Memória de Massa - 2025'!$A$1:$A$217,'Formula Dados Copasul'!$A12,'Memória de Massa - 2025'!$F$1:$F$217,'Formula Dados Copasul'!I$4) -> 19556.78 | J12: =+SUMIFS('Memória de Massa - 2025'!$G$1:$G$217,'Memória de Massa - 2025'!$A$1:$A$217,'Formula Dados Copasul'!$A12,'Memória de Massa - 2025'!$F$1:$F$217,'Formula Dados Copasul'!J$4) -> 37585.8 | K12: =+SUMIFS('Memória de Massa - 2025'!$G$1:$G$217,'Memória de Massa - 2025'!$A$1:$A$217,'Formula Dados Copasul'!$A12,'Memória de Massa - 2025'!$F$1:$F$217,'Formula Dados Copasul'!K$4) -> 19255.01 | ... O12: =+SUMIFS('Memória de Massa - 2025'!$G$1:$G$217,'Memória de Massa - 2025'!$A$1:$A$217,'Formula Dados Copasul'!$A12,'Memória de Massa - 2025'!$F$1:$F$217,'Formula Dados Copasul'!O$4) -> 1514.84 | Q12: =+SUM(D12:O12) -> 138419.85 | S12: =+Q12/12 -> 11534.988
B14: Total Ponta (kWh) | D14: =+SUM(D11:D12) -> 20092.09 | E14: =+SUM(E11:E12) -> 57788.54 | F14: =+SUM(F11:F12) -> 42026.29 | G14: =+SUM(G11:G12) -> 6890.1 | H14: =+SUM(H11:H12) -> 14622.58 | I14: =+SUM(I11:I12) -> 41736.85 | J14: =+SUM(J11:J12) -> 90645.95 | K14: =+SUM(K11:K12) -> 63321.24 | ... O14: =+SUM(O11:O12) -> 4110.15 | Q14: =+SUM(D14:O14) -> 363001.67 | S14: =+Q14/12 -> 30250.139
B17: Total Consumo (kWh) | D17: =+SUM(D14,D9) -> 188748.62 | E17: =+SUM(E14,E9) -> 518786.23 | F17: =+SUM(F14,F9) -> 469303.42 | G17: =+SUM(G14,G9) -> 204312.18 | H17: =+SUM(H14,H9) -> 242916.51 | I17: =+SUM(I14,I9) -> 404618.21 | J17: =+SUM(J14,J9) -> 656306.84 | K17: =+SUM(K14,K9) -> 541321.36 | ... O17: =+SUM(O14,O9) -> 79538.46 | Q17: =+SUM(Q14,Q9) -> 3612299.6 | S17: =+Q17/12 -> 301024.96
A20: SiIos Novo Horizonte do Sul | B20: Produçao Usina 1 | D20: =+SUMIFS('Memória de Massa - 2025'!$K$1:$K$217,'Memória de Massa - 2025'!$B$1:$B$217,$A20,'Memória de Massa - 2025'!$F$1:$F$217,'Formula Dados Copasul'!D$4) -> 83461.9 | E20: =+SUMIFS('Memória de Massa - 2025'!$K$1:$K$217,'Memória de Massa - 2025'!$B$1:$B$217,$A20,'Memória de Massa - 2025'!$F$1:$F$217,'Formula Dados Copasul'!E$4) -> 76124.4 | F20: =+SUMIFS('Memória de Massa - 2025'!$K$1:$K$217,'Memória de Massa - 2025'!$B$1:$B$217,$A20,'Memória de Massa - 2025'!$F$1:$F$217,'Formula Dados Copasul'!F$4) -> 89858.2 | G20: =+SUMIFS('Memória de Massa - 2025'!$K$1:$K$217,'Memória de Massa - 2025'!$B$1:$B$217,$A20,'Memória de Massa - 2025'!$F$1:$F$217,'Formula Dados Copasul'!G$4) -> 62725.4 | H20: =+SUMIFS('Memória de Massa - 2025'!$K$1:$K$217,'Memória de Massa - 2025'!$B$1:$B$217,$A20,'Memória de Massa - 2025'!$F$1:$F$217,'Formula Dados Copasul'!H$4) -> 78227.5 | I20: =+SUMIFS('Memória de Massa - 2025'!$K$1:$K$217,'Memória de Massa - 2025'!$B$1:$B$217,$A20,'Memória de Massa - 2025'!$F$1:$F$217,'Formula Dados Copasul'!I$4) -> 60380.6 | J20: =+SUMIFS('Memória de Massa - 2025'!$K$1:$K$217,'Memória de Massa - 2025'!$B$1:$B$217,$A20,'Memória de Massa - 2025'!$F$1:$F$217,'Formula Dados Copasul'!J$4) -> 76551.2 | K20: =+SUMIFS('Memória de Massa - 2025'!$K$1:$K$217,'Memória de Massa - 2025'!$B$1:$B$217,$A20,'Memória de Massa - 2025'!$F$1:$F$217,'Formula Dados Copasul'!K$4) -> 79815.6 | ... O20: =+SUMIFS('Memória de Massa - 2025'!$K$1:$K$217,'Memória de Massa - 2025'!$B$1:$B$217,$A20,'Memória de Massa - 2025'!$F$1:$F$217,'Formula Dados Copasul'!O$4) -> 88631.7 | Q20: =+SUM(D20:O20) -> 938170.1 | S20: =+Q20/12 -> 78180.842
A21: Silos Batayporã | B21: Produção Usina 2 | D21: =+SUMIFS('Memória de Massa - 2025'!$K$1:$K$217,'Memória de Massa - 2025'!$B$1:$B$217,$A21,'Memória de Massa - 2025'!$F$1:$F$217,'Formula Dados Copasul'!D$4) -> 114259 | E21: =+SUMIFS('Memória de Massa - 2025'!$K$1:$K$217,'Memória de Massa - 2025'!$B$1:$B$217,$A21,'Memória de Massa - 2025'!$F$1:$F$217,'Formula Dados Copasul'!E$4) -> 91131.9 | F21: =+SUMIFS('Memória de Massa - 2025'!$K$1:$K$217,'Memória de Massa - 2025'!$B$1:$B$217,$A21,'Memória de Massa - 2025'!$F$1:$F$217,'Formula Dados Copasul'!F$4) -> 103061.9 | G21: =+SUMIFS('Memória de Massa - 2025'!$K$1:$K$217,'Memória de Massa - 2025'!$B$1:$B$217,$A21,'Memória de Massa - 2025'!$F$1:$F$217,'Formula Dados Copasul'!G$4) -> 73709.7 | H21: =+SUMIFS('Memória de Massa - 2025'!$K$1:$K$217,'Memória de Massa - 2025'!$B$1:$B$217,$A21,'Memória de Massa - 2025'!$F$1:$F$217,'Formula Dados Copasul'!H$4) -> 91616.6 | I21: =+SUMIFS('Memória de Massa - 2025'!$K$1:$K$217,'Memória de Massa - 2025'!$B$1:$B$217,$A21,'Memória de Massa - 2025'!$F$1:$F$217,'Formula Dados Copasul'!I$4) -> 72286.9 | J21: =+SUMIFS('Memória de Massa - 2025'!$K$1:$K$217,'Memória de Massa - 2025'!$B$1:$B$217,$A21,'Memória de Massa - 2025'!$F$1:$F$217,'Formula Dados Copasul'!J$4) -> 88336.8 | K21: =+SUMIFS('Memória de Massa - 2025'!$K$1:$K$217,'Memória de Massa - 2025'!$B$1:$B$217,$A21,'Memória de Massa - 2025'!$F$1:$F$217,'Formula Dados Copasul'!K$4) -> 93082.7 | ... O21: =+SUMIFS('Memória de Massa - 2025'!$K$1:$K$217,'Memória de Massa - 2025'!$B$1:$B$217,$A21,'Memória de Massa - 2025'!$F$1:$F$217,'Formula Dados Copasul'!O$4) -> 106603.9 | Q21: =+SUM(D21:O21) -> 1132410.2 | S21: =+Q21/12 -> 94367.517
A22: Silos Amandina | B22: Produção Usina 3 | D22: =+SUMIFS('Memória de Massa - 2025'!$K$1:$K$217,'Memória de Massa - 2025'!$B$1:$B$217,$A22,'Memória de Massa - 2025'!$F$1:$F$217,'Formula Dados Copasul'!D$4) -> 0 | E22: =+SUMIFS('Memória de Massa - 2025'!$K$1:$K$217,'Memória de Massa - 2025'!$B$1:$B$217,$A22,'Memória de Massa - 2025'!$F$1:$F$217,'Formula Dados Copasul'!E$4) -> 190.1 | F22: =+SUMIFS('Memória de Massa - 2025'!$K$1:$K$217,'Memória de Massa - 2025'!$B$1:$B$217,$A22,'Memória de Massa - 2025'!$F$1:$F$217,'Formula Dados Copasul'!F$4) -> 7913.8 | G22: =+SUMIFS('Memória de Massa - 2025'!$K$1:$K$217,'Memória de Massa - 2025'!$B$1:$B$217,$A22,'Memória de Massa - 2025'!$F$1:$F$217,'Formula Dados Copasul'!G$4) -> 23902.8 | H22: =+SUMIFS('Memória de Massa - 2025'!$K$1:$K$217,'Memória de Massa - 2025'!$B$1:$B$217,$A22,'Memória de Massa - 2025'!$F$1:$F$217,'Formula Dados Copasul'!H$4) -> 28781.7 | I22: =+SUMIFS('Memória de Massa - 2025'!$K$1:$K$217,'Memória de Massa - 2025'!$B$1:$B$217,$A22,'Memória de Massa - 2025'!$F$1:$F$217,'Formula Dados Copasul'!I$4) -> 20798.2 | J22: =+SUMIFS('Memória de Massa - 2025'!$K$1:$K$217,'Memória de Massa - 2025'!$B$1:$B$217,$A22,'Memória de Massa - 2025'!$F$1:$F$217,'Formula Dados Copasul'!J$4) -> 37317.8 | K22: =+SUMIFS('Memória de Massa - 2025'!$K$1:$K$217,'Memória de Massa - 2025'!$B$1:$B$217,$A22,'Memória de Massa - 2025'!$F$1:$F$217,'Formula Dados Copasul'!K$4) -> 16177.9 | ... O22: =+SUMIFS('Memória de Massa - 2025'!$K$1:$K$217,'Memória de Massa - 2025'!$B$1:$B$217,$A22,'Memória de Massa - 2025'!$F$1:$F$217,'Formula Dados Copasul'!O$4) -> 19968.1 | Q22: =+SUM(D22:O22) -> 269574.1 | S22: =+Q22/12 -> 22464.508
B24: Total Produção (kWH) | D24: =+SUM(D20:D22) -> 197720.9 | E24: =+SUM(E20:E22) -> 167446.4 | F24: =+SUM(F20:F22) -> 200833.9 | G24: =+SUM(G20:G22) -> 160337.9 | H24: =+SUM(H20:H22) -> 198625.8 | I24: =+SUM(I20:I22) -> 153465.7 | J24: =+SUM(J20:J22) -> 202205.8 | K24: =+SUM(K20:K22) -> 189076.2 | ... O24: =+SUM(O20:O22) -> 215203.7 | Q24: =+SUM(Q20:Q22) -> 2340154.4 | S24: =+SUM(S20:S22) -> 195012.87
A26: SiIos Novo Horizonte do Sul | B26: Compensão usina 1 | D26: =+SUMIFS('Memória de Massa - 2025'!$L$1:$L$217,'Memória de Massa - 2025'!$B$1:$B$217,$A26,'Memória de Massa - 2025'!$F$1:$F$217,'Formula Dados Copasul'!D$4) -> 54986 | E26: =+SUMIFS('Memória de Massa - 2025'!$L$1:$L$217,'Memória de Massa - 2025'!$B$1:$B$217,$A26,'Memória de Massa - 2025'!$F$1:$F$217,'Formula Dados Copasul'!E$4) -> 188910 | F26: =+SUMIFS('Memória de Massa - 2025'!$L$1:$L$217,'Memória de Massa - 2025'!$B$1:$B$217,$A26,'Memória de Massa - 2025'!$F$1:$F$217,'Formula Dados Copasul'!F$4) -> 32411 | G26: =+SUMIFS('Memória de Massa - 2025'!$L$1:$L$217,'Memória de Massa - 2025'!$B$1:$B$217,$A26,'Memória de Massa - 2025'!$F$1:$F$217,'Formula Dados Copasul'!G$4) -> 41488 | H26: =+SUMIFS('Memória de Massa - 2025'!$L$1:$L$217,'Memória de Massa - 2025'!$B$1:$B$217,$A26,'Memória de Massa - 2025'!$F$1:$F$217,'Formula Dados Copasul'!H$4) -> 55127 | I26: =+SUMIFS('Memória de Massa - 2025'!$L$1:$L$217,'Memória de Massa - 2025'!$B$1:$B$217,$A26,'Memória de Massa - 2025'!$F$1:$F$217,'Formula Dados Copasul'!I$4) -> 24600 | J26: =+SUMIFS('Memória de Massa - 2025'!$L$1:$L$217,'Memória de Massa - 2025'!$B$1:$B$217,$A26,'Memória de Massa - 2025'!$F$1:$F$217,'Formula Dados Copasul'!J$4) -> 10848 | K26: =+SUMIFS('Memória de Massa - 2025'!$L$1:$L$217,'Memória de Massa - 2025'!$B$1:$B$217,$A26,'Memória de Massa - 2025'!$F$1:$F$217,'Formula Dados Copasul'!K$4) -> 37261 | ... O26: =+SUMIFS('Memória de Massa - 2025'!$L$1:$L$217,'Memória de Massa - 2025'!$B$1:$B$217,$A26,'Memória de Massa - 2025'!$F$1:$F$217,'Formula Dados Copasul'!O$4) -> 8737 | Q26: =+SUM(D26:O26) -> 547684 | S26: =+Q26/12 -> 45640.333
A27: Silos Batayporã | B27: Compensão usina 2 | D27: =+SUMIFS('Memória de Massa - 2025'!$L$1:$L$217,'Memória de Massa - 2025'!$B$1:$B$217,$A27,'Memória de Massa - 2025'!$F$1:$F$217,'Formula Dados Copasul'!D$4) -> 6785 | E27: =+SUMIFS('Memória de Massa - 2025'!$L$1:$L$217,'Memória de Massa - 2025'!$B$1:$B$217,$A27,'Memória de Massa - 2025'!$F$1:$F$217,'Formula Dados Copasul'!E$4) -> 36315 | F27: =+SUMIFS('Memória de Massa - 2025'!$L$1:$L$217,'Memória de Massa - 2025'!$B$1:$B$217,$A27,'Memória de Massa - 2025'!$F$1:$F$217,'Formula Dados Copasul'!F$4) -> 63697 | G27: =+SUMIFS('Memória de Massa - 2025'!$L$1:$L$217,'Memória de Massa - 2025'!$B$1:$B$217,$A27,'Memória de Massa - 2025'!$F$1:$F$217,'Formula Dados Copasul'!G$4) -> 38586 | H27: =+SUMIFS('Memória de Massa - 2025'!$L$1:$L$217,'Memória de Massa - 2025'!$B$1:$B$217,$A27,'Memória de Massa - 2025'!$F$1:$F$217,'Formula Dados Copasul'!H$4) -> 37159 | I27: =+SUMIFS('Memória de Massa - 2025'!$L$1:$L$217,'Memória de Massa - 2025'!$B$1:$B$217,$A27,'Memória de Massa - 2025'!$F$1:$F$217,'Formula Dados Copasul'!I$4) -> 36580 | J27: =+SUMIFS('Memória de Massa - 2025'!$L$1:$L$217,'Memória de Massa - 2025'!$B$1:$B$217,$A27,'Memória de Massa - 2025'!$F$1:$F$217,'Formula Dados Copasul'!J$4) -> 64186 | K27: =+SUMIFS('Memória de Massa - 2025'!$L$1:$L$217,'Memória de Massa - 2025'!$B$1:$B$217,$A27,'Memória de Massa - 2025'!$F$1:$F$217,'Formula Dados Copasul'!K$4) -> 59224 | ... O27: =+SUMIFS('Memória de Massa - 2025'!$L$1:$L$217,'Memória de Massa - 2025'!$B$1:$B$217,$A27,'Memória de Massa - 2025'!$F$1:$F$217,'Formula Dados Copasul'!O$4) -> 5604 | Q27: =+SUM(D27:O27) -> 389018 | S27: =+Q27/12 -> 32418.167
A28: Silos Amandina | B28: Compensão usina 3 | D28: =+SUMIFS('Memória de Massa - 2025'!$L$1:$L$217,'Memória de Massa - 2025'!$B$1:$B$217,$A28,'Memória de Massa - 2025'!$F$1:$F$217,'Formula Dados Copasul'!D$4) -> 0 | E28: =+SUMIFS('Memória de Massa - 2025'!$L$1:$L$217,'Memória de Massa - 2025'!$B$1:$B$217,$A28,'Memória de Massa - 2025'!$F$1:$F$217,'Formula Dados Copasul'!E$4) -> 0 | F28: =+SUMIFS('Memória de Massa - 2025'!$L$1:$L$217,'Memória de Massa - 2025'!$B$1:$B$217,$A28,'Memória de Massa - 2025'!$F$1:$F$217,'Formula Dados Copasul'!F$4) -> 419 | G28: =+SUMIFS('Memória de Massa - 2025'!$L$1:$L$217,'Memória de Massa - 2025'!$B$1:$B$217,$A28,'Memória de Massa - 2025'!$F$1:$F$217,'Formula Dados Copasul'!G$4) -> 1423 | H28: =+SUMIFS('Memória de Massa - 2025'!$L$1:$L$217,'Memória de Massa - 2025'!$B$1:$B$217,$A28,'Memória de Massa - 2025'!$F$1:$F$217,'Formula Dados Copasul'!H$4) -> 9127 | I28: =+SUMIFS('Memória de Massa - 2025'!$L$1:$L$217,'Memória de Massa - 2025'!$B$1:$B$217,$A28,'Memória de Massa - 2025'!$F$1:$F$217,'Formula Dados Copasul'!I$4) -> 7190 | J28: =+SUMIFS('Memória de Massa - 2025'!$L$1:$L$217,'Memória de Massa - 2025'!$B$1:$B$217,$A28,'Memória de Massa - 2025'!$F$1:$F$217,'Formula Dados Copasul'!J$4) -> 9165 | K28: =+SUMIFS('Memória de Massa - 2025'!$L$1:$L$217,'Memória de Massa - 2025'!$B$1:$B$217,$A28,'Memória de Massa - 2025'!$F$1:$F$217,'Formula Dados Copasul'!K$4) -> 5142 | ... O28: =+SUMIFS('Memória de Massa - 2025'!$L$1:$L$217,'Memória de Massa - 2025'!$B$1:$B$217,$A28,'Memória de Massa - 2025'!$F$1:$F$217,'Formula Dados Copasul'!O$4) -> 16944 | Q28: =+SUM(D28:O28) -> 94200 | S28: =+Q28/12 -> 7850
B30: Total Compensação (kWH) | D30: =+SUM(D26:D28) -> 61771 | E30: =+SUM(E26:E28) -> 225225 | F30: =+SUM(F26:F28) -> 96527 | G30: =+SUM(G26:G28) -> 81497 | H30: =+SUM(H26:H28) -> 101413 | I30: =+SUM(I26:I28) -> 68370 | J30: =+SUM(J26:J28) -> 84199 | K30: =+SUM(K26:K28) -> 101627 | ... O30: =+SUM(O26:O28) -> 31285 | Q30: =+SUM(Q26:Q28) -> 1030902 | S30: =+SUM(S26:S28) -> 85908.5

Sheet Memória de Massa - 2025
